Workbook
Name _dma1: #REF!
Name _dma2: #REF!
Name _dma3: #REF!
Name _dmb1: #REF!
Name _dmb2: #REF!
Name _dmc1: #REF!
Name _dmc2: #REF!
Name _dmd1: #REF!
Name _dmd2: #REF!
Name _Lag1: #REF!
Name _Lag2: #REF!
Name _PV1: 7
Name a: #REF!
Name A1loss: #REF!
Name A2loss: #REF!
Name A3loss: #REF!
Name AB: #REF!
Name AB_H: #REF!
Name AB_Orig: #REF!
Name ABS_Senior_____10: "FitchRecoverybyType"
Name ActiveRows: #REF!
Name Actual: #REF!
Name Actual12moChargeoffRatio: #REF!
Name Actual3moChargeoffRatio: #REF!
Name Actual3moDefaultRatio: #REF!
Name AdjAdvRate: #REF!
Name adv_rate: #REF!
Name adv_rate_reduced: #REF!
Name adv_rate_type: #REF!
Name advance_outstanding: #REF!
Name AdvancesOS: #REF!
Name agg_commit_bal: #REF!
Name AggregateAdjustedBalanceUSD: #REF!
Name AgingsDetail: #REF!
Name agreed_currency: #REF!
Name amort_adv_outstanding: #REF!
Name amort_period: #REF!
Name AOLB: #REF!
Name AOLBrange: #REF!
Name applicable_margin: #REF!
Name asfsdf: #REF!
Name ASH: #REF!
Name ASL: #REF!
Name asset_rating: #REF!
Name asset_types: #REF!
Name asset_value: #REF!
Name AUSTRALIA_NET: 110
Name AUSTRIA_NET: 107
Name AvailableCollections: #REF!
Name AverageABAgg: #REF!
Name AverageABL: #REF!
Name averageABL2: #REF!
Name AverageAgg: #REF!
Name b: #REF!
Name B1loss: #REF!
Name B2loss: #REF!
Name BackupServiceFee: #REF!
Name balances: #REF!
Name BeginningABAgg: #REF!
Name BeginningABL: #REF!

Sheet Summary
C2: PennantPark Investment Funding I, LLC
B7: Reconciliation Date | C7: 45777
B9: Account Balances
B10: Account | C10: Currency | D10: FX Rate | E10: Account Number | F10: Cash Date (Currency) | G10: Pending Trades (Currency) | H10: Trade Date (Currency)
B11: Trust Account | C11: USD | D11: 1 | E11: 10107500 | F11: 0 | G11: 0 | H11: 0
B12: Interest Collection Subaccount | C12: USD | D12: 1 | E12: 10107501 | F12: 616421.06 | G12: 0 | H12: 616421.06
B13: Principal Collection Subaccount | C13: USD | D13: 1 | E13: 10107502 | F13: 25110258 | G13: 13006000 | H13: 38116258
B14: Payment Account | C14: USD | D14: 1 | E14: 10107503 | F14: 0 | G14: 0 | H14: 0
B16: Outstanding Payments
C17: Number of Items
B18: Unapplied Transactions | C18: 9
B19: Past Due Receivables | C19: 55
B21: Holdings
B22: Positions | C22: Currency | D22: FX Rate | E22: Settle Date (Currency) | F22: Pending Trades (Currency) | G22: Trade Date (Currency)
B23: Funded | C23: USD | D23: 1 | E23: 4.1360387e+08 | F23: -13100000 | G23: 4.0050387e+08
B24: Unfunded | C24: USD | D24: 1 | E24: -0.05 | F24: 1.0728836e-07 | G24: -0.049999893
B25: Committed | C25: USD | D25: 1 | E25: 4.1360387e+08 | F25: -13100000 | G25: 4.0050387e+08

Sheet Transactions
A7: Transactions as of 04/30/2025
A8: Transaction Data | N8: Account Balances | R8: Collateral Balance
A9: Applied Date | B9: Settle Date | C9: Trade Date | D9: Issuer/Borrower | E9: Facility/Security | F9: Identifier | G9: Transaction Type | H9: Account | I9: Currency | J9: Transaction Amount | K9: Price | L9: Funded par | M9: Unfunded par | N9: Trust Account | O9: Interest Collection Subaccount | P9: Principal Collection Subaccount | Q9: Payment Account | R9: Funded Collateral | S9: Unfunded Collateral | T9: Committed Collateral
N10: USD | O10: USD | P10: USD | Q10: USD | R10: USD | S10: USD | T10: USD
D11: Beginning Balance | N11: 0 | O11: 0 | P11: 0 | Q11: 0 | R11: 0 | S11: 0 | T11: 0
A12: 45642 | B12: 45642 | C12: 45642 | D12: PennantPark Investment Funding I, LLC | E12: PennantPark Investment Funding I LLC | G12: Facility - Sale | I12: USD | J12: 0 | K12: 1 | L12: 0 | M12: 0 | N12: 0 | O12: 0 | P12: 0 | Q12: 0 | R12: 0 | S12: 0 | T12: 0
A13: 45688 | B13: 45678 | C13: 45678 | D13: Historic Borrowing Offset | G13: Cash Adjustment (R) | H13: Principal Collection Subaccount | I13: USD | J13: -142600000 | K13: 0 | L13: 0 | M13: 0 | N13: 0 | O13: 0 | P13: -142600000 | Q13: 0 | R13: 0 | S13: 0 | T13: 0
A14: 45688 | B14: 45678 | C14: 45678 | D14: PennantPark Investment Funding I, LLC | E14: PennantPark Investment Funding I LLC | G14: Facility - Borrowing (R) | H14: Principal Collection Subaccount | I14: USD | J14: 142600000 | K14: 1 | L14: 0 | M14: 0 | N14: 0 | O14: 0 | P14: 0 | Q14: 0 | R14: 0 | S14: 0 | T14: 0
A15: 45688 | B15: 45688 | C15: 45688 | D15: PennantPark Investment Funding I, LLC | E15: PennantPark Investment Funding I LLC | G15: Facility - Borrowing (R) | H15: Principal Collection Subaccount | I15: USD | J15: 72000000 | K15: 1 | L15: 0 | M15: 0 | N15: 0 | O15: 0 | P15: 72000000 | Q15: 0 | R15: 0 | S15: 0 | T15: 0
A16: 45692 | B16: 45686 | C16: 45686 | D16: Michael Baker International LLC | E16: New Term B Loan | F16: LX234003 | G16: Facility - Payoff | I16: USD | J16: 0 | K16: 0 | L16: -491762.96 | M16: 0 | N16: 0 | O16: 0 | P16: 72000000 | Q16: 0 | R16: -491762.96 | S16: 0 | T16: -491762.96
A17: 45693 | B17: 45660 | C17: 45660 | D17: STG Distribution LLC | E17: First Out New Money Term Loan | F17: LX249176 | G17: Facility - Commitment Increase | I17: USD | J17: 0 | K17: 0 | L17: 8327.77 | M17: 0 | N17: 0 | O17: 0 | P17: 72000000 | Q17: 0 | R17: -483435.19 | S17: 0 | T17: -483435.19
A18: 45693 | B18: 45691 | C18: 45691 | D18: STG Distribution LLC | E18: First Out New Money Term Loan | F18: LX249176 | G18: Facility - Commitment Increase | I18: USD | J18: 0 | K18: 0 | L18: 8657.36 | M18: 0 | N18: 0 | O18: 0 | P18: 72000000 | Q18: 0 | R18: -474777.83 | S18: 0 | T18: -474777.83
A19: 45693 | B19: 45657 | C19: 45657 | D19: 48Forty Intermediate Holdings Inc | E19: 48forty Common Equity | G19: Shares/Units - Purchase | I19: USD | J19: 0 | K19: 0 | L19: 522.15 | N19: 0 | O19: 0 | P19: 72000000 | Q19: 0 | R19: -474255.68 | S19: 0 | T19: -474255.68
A20: 45693 | B20: 45659 | C20: 45659 | D20: Alpine Acquisition Corp II | E20: Amend 4 TLA-2 | F20: LX207291 | G20: Facility - Commitment Increase | I20: USD | J20: 0 | K20: 0 | L20: 28686.7 | M20: 0 | N20: 0 | O20: 0 | P20: 72000000 | Q20: 0 | R20: -445568.98 | S20: 0 | T20: -445568.98
A21: 45693 | B21: 45691 | C21: 45691 | D21: Alpine Acquisition Corp II | E21: Amend 4 TLA-2 | F21: LX207291 | G21: Facility - Commitment Increase | I21: USD | J21: 0 | K21: 0 | L21: 29089.33 | M21: 0 | N21: 0 | O21: 0 | P21: 72000000 | Q21: 0 | R21: -416479.65 | S21: 0 | T21: -416479.65
A22: 45693 | B22: 45688 | C22: 45688 | D22: Carnegie Dartlet LLC | E22: Initial Term Loan | G22: Loan - Interest Payment (R) | H22: Interest Collection Subaccount | I22: USD | J22: 58716.25 | K22: 0 | L22: 0 | M22: 0 | N22: 0 | O22: 58716.25 | P22: 72000000 | Q22: 0 | R22: -416479.65 | S22: 0 | T22: -416479.65
A23: 45693 | B23: 45688 | C23: 45688 | D23: Eval Home Health Solutions Intermediate LLC | E23: Initial Term Loan | F23: LX233420 | G23: Loan - Interest Payment (R) | H23: Interest Collection Subaccount | I23: USD | J23: 12119.62 | K23: 0 | L23: 0 | M23: 0 | N23: 0 | O23: 70835.87 | P23: 72000000 | Q23: 0 | R23: -416479.65 | S23: 0 | T23: -416479.65
A24: 45693 | B24: 45688 | C24: 45688 | D24: Transgo LLC | E24: Initial Term Loan | F24: LX225916 | G24: Loan - Interest Payment (R) | H24: Interest Collection Subaccount | I24: USD | J24: 28603.02 | K24: 0 | L24: 0 | M24: 0 | N24: 0 | O24: 99438.89 | P24: 72000000 | Q24: 0 | R24: -416479.65 | S24: 0 | T24: -416479.65
A25: 45693 | B25: 45688 | C25: 45688 | D25: Transgo LLC | E25: Initial Term Loan | F25: LX225916 | G25: Facility - Paydown (R) | H25: Principal Collection Subaccount | I25: USD | J25: 22715.13 | K25: 1 | L25: -22715.13 | M25: 0 | N25: 0 | O25: 99438.89 | P25: 72022715 | Q25: 0 | R25: -439194.78 | S25: 0 | T25: -439194.78
A26: 45693 | B26: 45688 | C26: 45688 | D26: Transgo LLC | E26: Initial Term Loan | F26: LX225916 | G26: Facility - Upfront Fee (R) | H26: Principal Collection Subaccount | I26: USD | J26: 227.15 | K26: 0 | L26: 0 | M26: 0 | N26: 0 | O26: 99438.89 | P26: 72022942 | Q26: 0 | R26: -439194.78 | S26: 0 | T26: -439194.78
A27: 45693 | B27: 45688 | C27: 45674 | D27: Arcfield Acquisition Corp | E27: REFI Term Loan | F27: LX251125 | G27: Facility - Purchase (D) | H27: Principal Collection Subaccount | I27: USD | J27: -14973750 | K27: 0.9982 | L27: 15000000 | M27: 0 | N27: 0 | O27: 99438.89 | P27: 57049192 | Q27: 0 | R27: 14560805 | S27: 0 | T27: 14560805
A28: 45693 | B28: 45657 | C28: 45657 | D28: 12.31.24 Trades/Position Offset | G28: Cash Adjustment (R) | H28: Principal Collection Subaccount | I28: USD | J28: 2.986352e+08 | K28: 0 | L28: 0 | M28: 0 | N28: 0 | O28: 99438.89 | P28: 3.5568439e+08 | Q28: 0 | R28: 14560805 | S28: 0 | T28: 14560805
A29: 45693 | B29: 45685 | C29: 45646 | D29: CF512 Inc | E29: Initial Term Loan | F29: LX205355 | G29: Facility - Purchase (D) | H29: Principal Collection Subaccount | I29: USD | J29: -3879466.4 | K29: 0.985 | L29: 3940540.6 | M29: 0 | N29: 0 | O29: 99438.89 | P29: 3.5180492e+08 | Q29: 0 | R29: 18501346 | S29: 0 | T29: 18501346
A30: 45693 | B30: 45665 | C30: 45593 | D30: Dr. Squatch LLC | E30: 2022-1 Incremental Term Loan | F30: LX203689 | G30: Facility - Purchase (D) | H30: Principal Collection Subaccount | I30: USD | J30: -1719796.1 | K30: 1 | L30: 1719796.1 | M30: 0 | N30: 0 | O30: 99438.89 | P30: 3.5008513e+08 | Q30: 0 | R30: 20221142 | S30: 0 | T30: 20221142
A31: 45693 | B31: 45665 | C31: 45593 | D31: Dr. Squatch LLC | E31: Delayed Draw Term Loan | F31: LX203614 | G31: Facility - Purchase (D) | H31: Principal Collection Subaccount | I31: USD | J31: -6365000 | K31: 1 | L31: 6365000 | M31: 0 | N31: 0 | O31: 99438.89 | P31: 3.4372013e+08 | Q31: 0 | R31: 26586142 | S31: 0 | T31: 26586142
A32: 45693 | B32: 45657 | C32: 45657 | D32: AFC-Dell Holding Corp | E32: Term Loan | G32: Facility - Purchase (D) | H32: Principal Collection Subaccount | I32: USD | J32: -1612929.6 | K32: 1 | L32: 1612929.6 | M32: 0 | N32: 0 | O32: 99438.89 | P32: 3.421072e+08 | Q32: 0 | R32: 28199072 | S32: 0 | T32: 28199072
A33: 45693 | B33: 45657 | C33: 45657 | D33: Watchtower Buyer LLC | E33: Initial Term Loan | F33: LX221597 | G33: Facility - Purchase (D) | H33: Principal Collection Subaccount | I33: USD | J33: -2275337 | K33: 1 | L33: 2275337 | M33: 0 | N33: 0 | O33: 99438.89 | P33: 3.3983186e+08 | Q33: 0 | R33: 30474409 | S33: 0 | T33: 30474409
A34: 45693 | B34: 45657 | C34: 45657 | D34: Transgo LLC | E34: Initial Term Loan | F34: LX225916 | G34: Facility - Purchase (D) | H34: Principal Collection Subaccount | I34: USD | J34: -3286471 | K34: 1 | L34: 3286471 | M34: 0 | N34: 0 | O34: 99438.89 | P34: 3.3654539e+08 | Q34: 0 | R34: 33760880 | S34: 0 | T34: 33760880
A35: 45693 | B35: 45657 | C35: 45657 | D35: AFC-Dell Holding Corp | E35: 5th AMD Delayed Draw Term Loan | F35: LX194355 | G35: Facility - Purchase (D) | H35: Principal Collection Subaccount | I35: USD | J35: -2377281.1 | K35: 1 | L35: 2377281.1 | M35: 0 | N35: 0 | O35: 99438.89 | P35: 3.3416811e+08 | Q35: 0 | R35: 36138161 | S35: 0 | T35: 36138161
A36: 45693 | B36: 45657 | C36: 45657 | D36: BlackHawk Industrial Distribution Inc | E36: Initial Term Loan | F36: LX176035 | G36: Facility - Purchase (D) | H36: Principal Collection Subaccount | I36: USD | J36: -5060290.4 | K36: 1 | L36: 5060290.4 | M36: 0 | N36: 0 | O36: 99438.89 | P36: 3.2910782e+08 | Q36: 0 | R36: 41198451 | S36: 0 | T36: 41198451
A37: 45693 | B37: 45657 | C37: 45657 | D37: Bluebird Group LLC, The | E37: Term Loan | F37: LX206792 | G37: Facility - Purchase (D) | H37: Principal Collection Subaccount | I37: USD | J37: -3642206.1 | K37: 1 | L37: 3642206.1 | M37: 0 | N37: 0 | O37: 99438.89 | P37: 3.2546561e+08 | Q37: 0 | R37: 44840657 | S37: 0 | T37: 44840657
A38: 45693 | B38: 45657 | C38: 45657 | D38: BlueHalo Global Holdings LLC | E38: Initial Term Loan | F38: LX189087 | G38: Facility - Purchase (D) | H38: Principal Collection Subaccount | I38: USD | J38: -2193219.3 | K38: 1 | L38: 2193219.3 | M38: 0 | N38: 0 | O38: 99438.89 | P38: 3.2327239e+08 | Q38: 0 | R38: 47033876 | S38: 0 | T38: 47033876
A39: 45693 | B39: 45657 | C39: 45657 | D39: TCG 3.0 Jogger Acquisitionco Inc | E39: Initial Term Loan | F39: LX226175 | G39: Facility - Purchase (D) | H39: Principal Collection Subaccount | I39: USD | J39: -3940075.4 | K39: 1 | L39: 3940075.4 | M39: 0 | N39: 0 | O39: 99438.89 | P39: 3.1933232e+08 | Q39: 0 | R39: 50973952 | S39: 0 | T39: 50973952
A40: 45693 | B40: 45657 | C40: 45657 | D40: Carisk Buyer Inc | E40: Initial Term Loan | F40: LX221535 | G40: Facility - Purchase (D) | H40: Principal Collection Subaccount | I40: USD | J40: -1119537 | K40: 1 | L40: 1119537 | M40: 0 | N40: 0 | O40: 99438.89 | P40: 3.1821278e+08 | Q40: 0 | R40: 52093489 | S40: 0 | T40: 52093489
A41: 45693 | B41: 45657 | C41: 45657 | D41: Carnegie Dartlet LLC | E41: Initial Term Loan | G41: Facility - Purchase (D) | H41: Principal Collection Subaccount | I41: USD | J41: -6917575.4 | K41: 1 | L41: 6917575.4 | M41: 0 | N41: 0 | O41: 99438.89 | P41: 3.1129521e+08 | Q41: 0 | R41: 59011064 | S41: 0 | T41: 59011064
A42: 45693 | B42: 45657 | C42: 45657 | D42: Sigma Defense Systems LLC | E42: Initial Term Loan | F42: LX193132 | G42: Facility - Purchase (D) | H42: Principal Collection Subaccount | I42: USD | J42: -18537394 | K42: 1 | L42: 18537394 | M42: 0 | N42: 0 | O42: 99438.89 | P42: 2.9275781e+08 | Q42: 0 | R42: 77548458 | S42: 0 | T42: 77548458
A43: 45693 | B43: 45657 | C43: 45657 | D43: Dr. Squatch LLC | E43: Initial Term Loan | F43: LX197743 | G43: Facility - Purchase (D) | H43: Principal Collection Subaccount | I43: USD | J43: -1159.44 | K43: 1 | L43: 1159.44 | M43: 0 | N43: 0 | O43: 99438.89 | P43: 2.9275665e+08 | Q43: 0 | R43: 77549618 | S43: 0 | T43: 77549618
A44: 45693 | B44: 45657 | C44: 45657 | D44: Seaway Buyer LLC | E44: Initial Term Loan | F44: LX206101 | G44: Facility - Purchase (D) | H44: Principal Collection Subaccount | I44: USD | J44: -609654.28 | K44: 1 | L44: 609654.28 | M44: 0 | N44: 0 | O44: 99438.89 | P44: 2.92147e+08 | Q44: 0 | R44: 78159272 | S44: 0 | T44: 78159272
A45: 45693 | B45: 45657 | C45: 45657 | D45: HW Holdco LLC | E45: Third Amendment Incremental Term Loan | F45: LX205427 | G45: Facility - Purchase (D) | H45: Principal Collection Subaccount | I45: USD | J45: -2338198.5 | K45: 1 | L45: 2338198.5 | M45: 0 | N45: 0 | O45: 99438.89 | P45: 2.898088e+08 | Q45: 0 | R45: 80497471 | S45: 0 | T45: 80497471
A46: 45693 | B46: 45657 | C46: 45657 | D46: Infolinks Media Buyco LLC | E46: Delayed Draw Term Loan | F46: LX200854 | G46: Facility - Purchase (D) | H46: Principal Collection Subaccount | I46: USD | J46: -1402092.3 | K46: 1 | L46: 1402092.3 | M46: 0 | N46: 0 | O46: 99438.89 | P46: 2.8840671e+08 | Q46: 0 | R46: 81899563 | S46: 0 | T46: 81899563
A47: 45693 | B47: 45657 | C47: 45657 | D47: Infolinks Media Buyco LLC | E47: Term Loan | F47: LX200853 | G47: Facility - Purchase (D) | H47: Principal Collection Subaccount | I47: USD | J47: -653448.36 | K47: 1 | L47: 653448.36 | M47: 0 | N47: 0 | O47: 99438.89 | P47: 2.8775326e+08 | Q47: 0 | R47: 82553011 | S47: 0 | T47: 82553011
A48: 45693 | B48: 45657 | C48: 45657 | D48: Inventus Power Inc | E48: Term Loan | F48: LX213612 | G48: Facility - Purchase (D) | H48: Principal Collection Subaccount | I48: USD | J48: -1980511.2 | K48: 1 | L48: 1980511.2 | M48: 0 | N48: 0 | O48: 99438.89 | P48: 2.8577275e+08 | Q48: 0 | R48: 84533522 | S48: 0 | T48: 84533522
A49: 45693 | B49: 45657 | C49: 45657 | D49: S101 Acquisition Inc | E49: Delayed Draw Term Loan B | G49: Facility - Purchase (D) | H49: Principal Collection Subaccount | I49: USD | J49: -465740.53 | K49: 1 | L49: 465740.53 | M49: 0 | N49: 0 | O49: 99438.89 | P49: 2.8530701e+08 | Q49: 0 | R49: 84999263 | S49: 0 | T49: 84999263
A50: 45693 | B50: 45657 | C50: 45657 | D50: Rancho Health MSO Inc | E50: Initial Term Loan | F50: LX191986 | G50: Facility - Purchase (D) | H50: Principal Collection Subaccount | I50: USD | J50: -9614976.2 | K50: 1 | L50: 9614976.2 | M50: 0 | N50: 0 | O50: 99438.89 | P50: 2.7569203e+08 | Q50: 0 | R50: 94614239 | S50: 0 | T50: 94614239
A51: 45693 | B51: 45657 | C51: 45657 | D51: Omnia Exterior Solutions LLC | E51: 2023-1 DDTL (OES TopCo) | F51: LX224334 | G51: Facility - Purchase (D) | H51: Principal Collection Subaccount | I51: USD | J51: -2779875 | K51: 1 | L51: 2779875 | M51: 0 | N51: 0 | O51: 99438.89 | P51: 2.7291216e+08 | Q51: 0 | R51: 97394114 | S51: 0 | T51: 97394114
A52: 45693 | B52: 45657 | C52: 45657 | D52: Nora Acquisition LLC | E52: Term Loan A | F52: LX216658 | G52: Facility - Purchase (D) | H52: Principal Collection Subaccount | I52: USD | J52: -3787411.6 | K52: 1 | L52: 3787411.6 | M52: 0 | N52: 0 | O52: 99438.89 | P52: 2.6912474e+08 | Q52: 0 | R52: 1.0118153e+08 | S52: 0 | T52: 1.0118153e+08
A53: 45693 | B53: 45657 | C53: 45657 | D53: MOREgroup Holdings Inc | E53: Initial Term Loan | F53: LX225324 | G53: Facility - Purchase (D) | H53: Principal Collection Subaccount | I53: USD | J53: -4263446.3 | K53: 1 | L53: 4263446.3 | M53: 0 | N53: 0 | O53: 99438.89 | P53: 2.648613e+08 | Q53: 0 | R53: 1.0544497e+08 | S53: 0 | T53: 1.0544497e+08
A54: 45693 | B54: 45657 | C54: 45657 | D54: Megawatt Acquisitionco Inc | E54: Initial Term Loan | F54: LX228852 | G54: Facility - Purchase (D) | H54: Principal Collection Subaccount | I54: USD | J54: -4955037.6 | K54: 1 | L54: 4955037.6 | M54: 0 | N54: 0 | O54: 99438.89 | P54: 2.5990626e+08 | Q54: 0 | R54: 1.1040001e+08 | S54: 0 | T54: 1.1040001e+08
A55: 45693 | B55: 45657 | C55: 45657 | D55: Medina Health LLC | E55: Initial Term Loan | F55: LX218963 | G55: Facility - Purchase (D) | H55: Principal Collection Subaccount | I55: USD | J55: -3790175.7 | K55: 1 | L55: 3790175.7 | M55: 0 | N55: 0 | O55: 99438.89 | P55: 2.5611608e+08 | Q55: 0 | R55: 1.1419019e+08 | S55: 0 | T55: 1.1419019e+08
A56: 45693 | B56: 45657 | C56: 45657 | D56: Rancho Health MSO Inc | E56: Second Amendment Funded Delayed Draw Term Loan | G56: Facility - Purchase (D) | H56: Principal Collection Subaccount | I56: USD | J56: -4884576 | K56: 1 | L56: 4884576 | M56: 0 | N56: 0 | O56: 99438.89 | P56: 2.5123151e+08 | Q56: 0 | R56: 1.1907476e+08 | S56: 0 | T56: 1.1907476e+08
A57: 45693 | B57: 45657 | C57: 45657 | D57: Zips Car Wash LLC | E57: 13th Amendment Term Loan | F57: LX201147 | G57: Facility - Purchase (D) | H57: Principal Collection Subaccount | I57: USD | J57: -9085899.6 | K57: 1 | L57: 9085899.6 | M57: 0 | N57: 0 | O57: 99438.89 | P57: 2.4214561e+08 | Q57: 0 | R57: 1.2816066e+08 | S57: 0 | T57: 1.2816066e+08
A58: 45693 | B58: 45657 | C58: 45657 | D58: RTIC Subsidiary Holdings LLC | E58: Initial Term Loan | F58: LX233174 | G58: Facility - Purchase (D) | H58: Principal Collection Subaccount | I58: USD | J58: -12917544 | K58: 1 | L58: 12917544 | M58: 0 | N58: 0 | O58: 99438.89 | P58: 2.2922807e+08 | Q58: 0 | R58: 1.410782e+08 | S58: 0 | T58: 1.410782e+08
A59: 45693 | B59: 45657 | C59: 45657 | D59: Eval Home Health Solutions Intermediate LLC | E59: Initial Term Loan | F59: LX233420 | G59: Facility - Purchase (D) | H59: Principal Collection Subaccount | I59: USD | J59: -1392538.3 | K59: 1 | L59: 1392538.3 | M59: 0 | N59: 0 | O59: 99438.89 | P59: 2.2783553e+08 | Q59: 0 | R59: 1.4247074e+08 | S59: 0 | T59: 1.4247074e+08
A60: 45693 | B60: 45657 | C60: 45657 | D60: Michael Baker International LLC | E60: New Term B Loan | F60: LX234003 | G60: Facility - Purchase (D) | H60: Principal Collection Subaccount | I60: USD | J60: -498746.87 | K60: 1 | L60: 498746.87 | M60: 0 | N60: 0 | O60: 99438.89 | P60: 2.2733678e+08 | Q60: 0 | R60: 1.4296949e+08 | S60: 0 | T60: 1.4296949e+08
A61: 45693 | B61: 45657 | C61: 45657 | D61: Burgess Point Purchaser Corporation | E61: Initial Term Loan | F61: LX205817 | G61: Facility - Purchase (D) | H61: Principal Collection Subaccount | I61: USD | J61: -249597.72 | K61: 1 | L61: 249597.72 | M61: 0 | N61: 0 | O61: 99438.89 | P61: 2.2708718e+08 | Q61: 0 | R61: 1.4321909e+08 | S61: 0 | T61: 1.4321909e+08
A62: 45693 | B62: 45657 | C62: 45657 | D62: HEC Purchaser Corp. | E62: Term Loan A | F62: LX237049 | G62: Facility - Purchase (D) | H62: Principal Collection Subaccount | I62: USD | J62: -1975037.6 | K62: 1 | L62: 1975037.6 | M62: 0 | N62: 0 | O62: 99438.89 | P62: 2.2511214e+08 | Q62: 0 | R62: 1.4519413e+08 | S62: 0 | T62: 1.4519413e+08
A63: 45693 | B63: 45657 | C63: 45657 | D63: Omnia Exterior Solutions LLC | E63: 2023-2 DDTL (OES TopCo) | F63: LX224335 | G63: Facility - Purchase (D) | H63: Principal Collection Subaccount | I63: USD | J63: -4875500 | K63: 1 | L63: 4875500 | M63: 0 | N63: 0 | O63: 99438.89 | P63: 2.2023664e+08 | Q63: 0 | R63: 1.5006963e+08 | S63: 0 | T63: 1.5006963e+08
A64: 45693 | B64: 45657 | C64: 45657 | D64: US Fertility Enterprises LLC | E64: Initial Term Loan | F64: LX245293 | G64: Facility - Purchase (D) | H64: Principal Collection Subaccount | I64: USD | J64: -5000000 | K64: 1 | L64: 5000000 | M64: 0 | N64: 0 | O64: 99438.89 | P64: 2.1523664e+08 | Q64: 0 | R64: 1.5506963e+08 | S64: 0 | T64: 1.5506963e+08
A65: 45693 | B65: 45657 | C65: 45657 | D65: Case Works LLC | E65: Term Loan | F65: LX248336 | G65: Facility - Purchase (D) | H65: Principal Collection Subaccount | I65: USD | J65: -3000000 | K65: 1 | L65: 3000000 | M65: 0 | N65: 0 | O65: 99438.89 | P65: 2.1223664e+08 | Q65: 0 | R65: 1.5806963e+08 | S65: 0 | T65: 1.5806963e+08
A66: 45693 | B66: 45657 | C66: 45657 | D66: Omnia Exterior Solutions LLC | E66: Second Amendment Term Loan | F66: LX248961 | G66: Facility - Purchase (D) | H66: Principal Collection Subaccount | I66: USD | J66: -979049.89 | K66: 1 | L66: 979049.89 | M66: 0 | N66: 0 | O66: 99438.89 | P66: 2.1125759e+08 | Q66: 0 | R66: 1.5904868e+08 | S66: 0 | T66: 1.5904868e+08
A67: 45693 | B67: 45657 | C67: 45657 | D67: Archer Lewis LLC | E67: Term Loan | F67: LX245453 | G67: Facility - Purchase (D) | H67: Principal Collection Subaccount | I67: USD | J67: -2693250 | K67: 1 | L67: 2693250 | M67: 0 | N67: 0 | O67: 99438.89 | P67: 2.0856434e+08 | Q67: 0 | R67: 1.6174193e+08 | S67: 0 | T67: 1.6174193e+08
A68: 45693 | B68: 45657 | C68: 45657 | D68: Argano LLC | E68: Term Loan | F68: LX246656 | G68: Facility - Purchase (D) | H68: Principal Collection Subaccount | I68: USD | J68: -8977500 | K68: 1 | L68: 8977500 | M68: 0 | N68: 0 | O68: 99438.89 | P68: 1.9958684e+08 | Q68: 0 | R68: 1.7071943e+08 | S68: 0 | T68: 1.7071943e+08
... A94: 45693 | B94: 45657 | C94: 45657 | D94: LJ Avalon Holdings LLC | E94: Term Loan | F94: LX210725 | G94: Facility - Purchase (D) | H94: Principal Collection Subaccount | I94: USD | J94: -329100.54 | K94: 1 | L94: 329100.54 | M94: 0 | N94: 0 | O94: 99438.89 | P94: 1.0425326e+08 | Q94: 0 | R94: 2.6605301e+08 | S94: 0 | T94: 2.6605301e+08
A95: 45693 | B95: 45657 | C95: 45657 | D95: Rancho Health MSO Inc | E95: Sixth Amendment Delayed Draw Term Loan | G95: Facility - Purchase (D) | H95: Principal Collection Subaccount | I95: USD | J95: -500447.82 | K95: 1 | L95: 500447.82 | M95: 0 | N95: 0 | O95: 99438.89 | P95: 1.0375282e+08 | Q95: 0 | R95: 2.6655345e+08 | S95: 0 | T95: 2.6655345e+08
A96: 45693 | B96: 45657 | C96: 45657 | D96: Lightspeed Buyer Inc | E96: Restatement Date TL | F96: LX255973 | G96: Facility - Purchase (D) | H96: Principal Collection Subaccount | I96: USD | J96: -2512707.5 | K96: 1 | L96: 2512707.5 | M96: 0 | N96: 0 | O96: 99438.89 | P96: 1.0124011e+08 | Q96: 0 | R96: 2.6906616e+08 | S96: 0 | T96: 2.6906616e+08
A97: 45693 | B97: 45657 | C97: 45657 | D97: NFS - CFP Holdings LLC | E97: Initial Term Loan | G97: Facility - Purchase (D) | H97: Principal Collection Subaccount | I97: USD | J97: -6982500 | K97: 1 | L97: 6982500 | M97: 0 | N97: 0 | O97: 99438.89 | P97: 94257608 | Q97: 0 | R97: 2.7604866e+08 | S97: 0 | T97: 2.7604866e+08
A98: 45693 | B98: 45657 | C98: 45657 | D98: BlackHawk Industrial Distribution Inc | E98: 2022-2 Incr TL 10MM | F98: LX208588 | G98: Facility - Purchase (D) | H98: Principal Collection Subaccount | I98: USD | J98: -4354323.2 | K98: 1 | L98: 4354323.2 | M98: 0 | N98: 0 | O98: 99438.89 | P98: 89903285 | Q98: 0 | R98: 2.8040298e+08 | S98: 0 | T98: 2.8040298e+08
A99: 45693 | B99: 45657 | C99: 45657 | D99: Archer Lewis LLC | E99: Delayed Draw Term Loan A | F99: LX245455 | G99: Facility - Purchase (D) | H99: Principal Collection Subaccount | I99: USD | J99: -3452013.3 | K99: 1 | L99: 3452013.3 | M99: 0 | N99: 0 | O99: 99438.89 | P99: 86451272 | Q99: 0 | R99: 2.83855e+08 | S99: 0 | T99: 2.83855e+08
A100: 45693 | B100: 45657 | C100: 45657 | D100: BlackHawk Industrial Distribution Inc | E100: 2024 Incremental Term Loan | F100: LX239453 | G100: Facility - Purchase (D) | H100: Principal Collection Subaccount | I100: USD | J100: -907682.02 | K100: 1 | L100: 907682.02 | M100: 0 | N100: 0 | O100: 99438.89 | P100: 85543590 | Q100: 0 | R100: 2.8476268e+08 | S100: 0 | T100: 2.8476268e+08
A101: 45693 | B101: 45657 | C101: 45657 | D101: Case Works LLC | E101: Delayed Draw Term Loan | F101: LX248337 | G101: Facility - Purchase (D) | H101: Principal Collection Subaccount | I101: USD | J101: -1514565.6 | K101: 1 | L101: 1514565.6 | M101: 0 | N101: 0 | O101: 99438.89 | P101: 84029024 | Q101: 0 | R101: 2.8627725e+08 | S101: 0 | T101: 2.8627725e+08
A102: 45693 | B102: 45657 | C102: 45657 | D102: STG Distribution LLC | E102: First Out New Money Term Loan | F102: LX249176 | G102: Facility - Purchase (D) | H102: Principal Collection Subaccount | I102: USD | J102: -1378390.1 | K102: 1 | L102: 1378390.1 | M102: 0 | N102: 0 | O102: 99438.89 | P102: 82650634 | Q102: 0 | R102: 2.8765564e+08 | S102: 0 | T102: 2.8765564e+08
A103: 45693 | B103: 45657 | C103: 45657 | D103: Vertex Companies Inc, The | E103: Term Loan D | F103: LX256513 | G103: Facility - Purchase (D) | H103: Principal Collection Subaccount | I103: USD | J103: -7000000 | K103: 1 | L103: 7000000 | M103: 0 | N103: 0 | O103: 99438.89 | P103: 75650634 | Q103: 0 | R103: 2.9465564e+08 | S103: 0 | T103: 2.9465564e+08
A104: 45693 | B104: 45657 | C104: 45657 | D104: Watchtower Buyer LLC | E104: Initial Delayed Draw Term Loan | F104: LX221598 | G104: Facility - Purchase (D) | H104: Principal Collection Subaccount | I104: USD | J104: -2084250 | K104: 1 | L104: 2084250 | M104: 0 | N104: 0 | O104: 99438.89 | P104: 73566384 | Q104: 0 | R104: 2.9673989e+08 | S104: 0 | T104: 2.9673989e+08
A105: 45693 | B105: 45657 | C105: 45657 | D105: Beacon Behavioral Support Services LLC | E105: Closing Date Delayed Draw Term Loan | F105: LX237495 | G105: Facility - Purchase (D) | H105: Principal Collection Subaccount | I105: USD | J105: -4019856.2 | K105: 1 | L105: 4019856.2 | M105: 0 | N105: 0 | O105: 99438.89 | P105: 69546528 | Q105: 0 | R105: 3.0075974e+08 | S105: 0 | T105: 3.0075974e+08
A106: 45693 | B106: 45657 | C106: 45657 | D106: Dr. Squatch LLC | E106: 2024-1 Incremental Term Loan | F106: LX239333 | G106: Facility - Purchase (D) | H106: Principal Collection Subaccount | I106: USD | J106: -6405704.7 | K106: 1 | L106: 6405704.7 | M106: 0 | N106: 0 | O106: 99438.89 | P106: 63140823 | Q106: 0 | R106: 3.0716545e+08 | S106: 0 | T106: 3.0716545e+08
A107: 45693 | B107: 45685 | C107: 45646 | D107: CF512 Inc | E107: DDTL | F107: LX205356 | G107: Facility - Purchase (D) | H107: Principal Collection Subaccount | I107: USD | J107: -2337461.4 | K107: 0.985 | L107: 2374259.7 | M107: 0 | N107: 0 | O107: 99438.89 | P107: 60803362 | Q107: 0 | R107: 3.0953971e+08 | S107: 0 | T107: 3.0953971e+08
A108: 45693 | B108: 45685 | C108: 45646 | D108: CF512 Inc | E108: DDTL | F108: LX205356 | G108: Facility Purchase - Net Economic Benefit (R) | H108: Principal Collection Subaccount | I108: USD | J108: -3150.46 | K108: 0 | L108: 0 | M108: 0 | N108: 0 | O108: 99438.89 | P108: 60800211 | Q108: 0 | R108: 3.0953971e+08 | S108: 0 | T108: 3.0953971e+08
A109: 45693 | B109: 45657 | C109: 45657 | D109: AFC-Dell Holding Corp | E109: Term Loan | G109: Facility - Purchase (D) | H109: Principal Collection Subaccount | I109: USD | J109: -2270815.5 | K109: 1 | L109: 2270815.5 | M109: 0 | N109: 0 | O109: 99438.89 | P109: 58529396 | Q109: 0 | R109: 3.1181052e+08 | S109: 0 | T109: 3.1181052e+08
A110: 45693 | B110: 45657 | C110: 44561 | D110: BlackHawk Industrial Distribution Inc | E110: 2022 DDTL | F110: LX206562 | G110: Facility - Purchase (D) | H110: Principal Collection Subaccount | I110: USD | J110: -376591.21 | K110: 1 | L110: 376591.21 | M110: 0 | N110: 0 | O110: 99438.89 | P110: 58152804 | Q110: 0 | R110: 3.1218711e+08 | S110: 0 | T110: 3.1218711e+08
A111: 45693 | B111: 45657 | C111: 45657 | D111: BlackHawk Industrial Distribution Inc | E111: 2022 Term | G111: Facility - Purchase (D) | H111: Principal Collection Subaccount | I111: USD | J111: -1860972.9 | K111: 1 | L111: 1860972.9 | M111: 0 | N111: 0 | O111: 99438.89 | P111: 56291832 | Q111: 0 | R111: 3.1404809e+08 | S111: 0 | T111: 3.1404809e+08
A112: 45693 | B112: 45670 | C112: 45658 | D112: MDI Buyer Inc | E112: First Amendment Delayed Draw Term Loan | F112: LX209153 | G112: Facility - Purchase (D) | H112: Principal Collection Subaccount | I112: USD | J112: -718441.96 | K112: 0.9902 | L112: 725567.03 | M112: 0 | N112: 0 | O112: 99438.89 | P112: 55573390 | Q112: 0 | R112: 3.1477365e+08 | S112: 0 | T112: 3.1477365e+08
A113: 45693 | B113: 45670 | C113: 45658 | D113: MDI Buyer Inc | E113: Initial Delayed Draw Term Loan | F113: LX206515 | G113: Facility - Purchase (D) | H113: Principal Collection Subaccount | I113: USD | J113: -5029093.6 | K113: 0.9902 | L113: 5078969.1 | M113: 0 | N113: 0 | O113: 99438.89 | P113: 50544296 | Q113: 0 | R113: 3.1985262e+08 | S113: 0 | T113: 3.1985262e+08
A114: 45693 | B114: 45670 | C114: 45658 | D114: MDI Buyer Inc | E114: Term Loan | F114: LX206514 | G114: Facility - Purchase (D) | H114: Principal Collection Subaccount | I114: USD | J114: -13937774 | K114: 0.9902 | L114: 14076000 | M114: 0 | N114: 0 | O114: 99438.89 | P114: 36606522 | Q114: 0 | R114: 3.3392862e+08 | S114: 0 | T114: 3.3392862e+08
A115: 45693 | B115: 45657 | C115: 45657 | D115: Pink Lily Holdings LLC | E115: Term Loan (PL Acquisitionco) | F115: LX201339 | G115: Facility - Purchase (D) | H115: Principal Collection Subaccount | I115: USD | J115: -8308979 | K115: 1 | L115: 8308979 | M115: 0 | N115: 0 | O115: 99438.89 | P115: 28297543 | Q115: 0 | R115: 3.422376e+08 | S115: 0 | T115: 3.422376e+08
A116: 45693 | B116: 45657 | C116: 45657 | D116: New Insight Holdings Inc | E116: New Insight Common | G116: Equity - Purchase (D) | H116: Principal Collection Subaccount | I116: USD | J116: -1388432.5 | K116: 17.5 | L116: 79339 | M116: 0 | N116: 0 | O116: 99438.89 | P116: 26909111 | Q116: 0 | R116: 3.4231694e+08 | S116: 0 | T116: 3.4231694e+08
A117: 45693 | B117: 45657 | C117: 45657 | D117: Alpine Acquisition Corp II | E117: Amend 4 TLA-2 | F117: LX207291 | G117: Facility - Purchase (D) | H117: Principal Collection Subaccount | I117: USD | J117: -3850102.3 | K117: 1 | L117: 3850102.3 | M117: -0.04 | N117: 0 | O117: 99438.89 | P117: 23059009 | Q117: 0 | R117: 3.4616704e+08 | S117: -0.04 | T117: 3.4616704e+08
A118: 45693 | B118: 45693 | C118: 45688 | D118: By Light Professional IT Services LLC | E118: Seventh Additional Term Loan | G118: Facility - Purchase (D) | H118: Principal Collection Subaccount | I118: USD | J118: -14932500 | K118: 0.9955 | L118: 15000000 | M118: 0 | N118: 0 | O118: 99438.89 | P118: 8126508.6 | Q118: 0 | R118: 3.6116704e+08 | S118: -0.04 | T118: 3.6116704e+08
A119: 45693 | B119: 45686 | C119: 45686 | D119: Michael Baker International LLC | E119: New Term B Loan | F119: LX234003 | G119: Facility - Payoff | I119: USD | J119: 0 | K119: 0 | L119: 491762.96 | M119: 0 | N119: 0 | O119: 99438.89 | P119: 8126508.6 | Q119: 0 | R119: 3.6165881e+08 | S119: -0.04 | T119: 3.6165881e+08
A120: 45693 | B120: 45686 | C120: 45686 | D120: Michael Baker International LLC | E120: New Term B Loan | F120: LX234003 | G120: Facility - Payoff | I120: USD | J120: 0 | K120: 0 | L120: -498746.87 | M120: 0 | N120: 0 | O120: 99438.89 | P120: 8126508.6 | Q120: 0 | R120: 3.6116006e+08 | S120: -0.04 | T120: 3.6116006e+08
A121: 45693 | B121: 45686 | C121: 45686 | D121: Michael Baker International LLC | E121: Term B-1 Loan | F121: LX258116 | G121: Facility Exchange - New Position | I121: USD | J121: 0 | K121: 0 | L121: 498746.87 | M121: 0 | N121: 0 | O121: 99438.89 | P121: 8126508.6 | Q121: 0 | R121: 3.6165881e+08 | S121: -0.04 | T121: 3.6165881e+08
A122: 45694 | B122: 45688 | C122: 45688 | D122: Lash OpCo LLC | E122: Restatement Term Loan | F122: LX201224 | G122: Facility - Commitment Increase | I122: USD | J122: 0 | K122: 0 | L122: 42817.28 | M122: 0 | N122: 0 | O122: 99438.89 | P122: 8126508.6 | Q122: 0 | R122: 3.6170162e+08 | S122: -0.04 | T122: 3.6170162e+08
A123: 45694 | B123: 45691 | C123: 45679 | D123: MDI Buyer Inc | E123: Term Loan | F123: LX206514 | G123: Facility - Sale (R) | H123: Principal Collection Subaccount | I123: USD | J123: 2376000 | K123: 0.99 | L123: -2400000 | M123: 0 | N123: 0 | O123: 99438.89 | P123: 10502509 | Q123: 0 | R123: 3.5930162e+08 | S123: -0.04 | T123: 3.5930162e+08
A124: 45694 | B124: 45691 | C124: 45679 | D124: MDI Buyer Inc | E124: Term Loan | F124: LX206514 | G124: Facility - Sale (R) | H124: Principal Collection Subaccount | I124: USD | J124: 990000 | K124: 0.99 | L124: -1000000 | M124: 0 | N124: 0 | O124: 99438.89 | P124: 11492509 | Q124: 0 | R124: 3.5830162e+08 | S124: -0.04 | T124: 3.5830162e+08
A125: 45694 | B125: 45688 | C125: 45688 | D125: Harris & Co. LLC | E125: Delayed Draw Term Loan A | F125: LX245516 | G125: Loan - Interest Payment (R) | H125: Interest Collection Subaccount | I125: USD | J125: 42956.85 | K125: 0 | L125: 0 | M125: 0 | N125: 0 | O125: 142395.74 | P125: 11492509 | Q125: 0 | R125: 3.5830162e+08 | S125: -0.04 | T125: 3.5830162e+08
A126: 45694 | B126: 45688 | C126: 45688 | D126: Bulk Trade Offset-(Trade Settlement from 12.31 to 2.4) | G126: Cash Adjustment (R) | H126: Principal Collection Subaccount | I126: USD | J126: 32740647 | K126: 0 | L126: 0 | M126: 0 | N126: 0 | O126: 142395.74 | P126: 44233155 | Q126: 0 | R126: 3.5830162e+08 | S126: -0.04 | T126: 3.5830162e+08
A127: 45694 | B127: 45673 | C127: 45658 | D127: S101 Acquisition Inc | E127: Delayed Draw Term Loan C | G127: Facility - Purchase (D) | H127: Principal Collection Subaccount | I127: USD | J127: -3421249.5 | K127: 0.99 | L127: 3455807.6 | M127: 0 | N127: 0 | O127: 142395.74 | P127: 40811906 | Q127: 0 | R127: 3.6175743e+08 | S127: -0.04 | T127: 3.6175743e+08
A128: 45694 | B128: 45685 | C128: 45646 | D128: Municipal Emergency Services Inc | E128: Second Amendment DDTL B | F128: LX210224 | G128: Facility - Purchase (D) | H128: Principal Collection Subaccount | I128: USD | J128: -2506186.2 | K128: 1 | L128: 2506186.2 | M128: 0 | N128: 0 | O128: 142395.74 | P128: 38305720 | Q128: 0 | R128: 3.6426362e+08 | S128: -0.04 | T128: 3.6426362e+08
A129: 45694 | B129: 45684 | C129: 45646 | D129: Omnia Exterior Solutions LLC | E129: 2024-1 Delayed Draw Term Loan | F129: LX248962 | G129: Facility - Purchase (D) | H129: Principal Collection Subaccount | I129: USD | J129: -3437902.3 | K129: 0.985 | L129: 3490256.1 | M129: 0 | N129: 0 | O129: 142395.74 | P129: 34867817 | Q129: 0 | R129: 3.6775387e+08 | S129: -0.04 | T129: 3.6775387e+08
A130: 45694 | B130: 45670 | C130: 45657 | D130: Argano LLC | E130: Term Loan | F130: LX246656 | G130: Facility - Sale (R) | H130: Principal Collection Subaccount | I130: USD | J130: 3456315.8 | K130: 0.99 | L130: -3491228.1 | M130: 0 | N130: 0 | O130: 142395.74 | P130: 38324133 | Q130: 0 | R130: 3.6426264e+08 | S130: -0.04 | T130: 3.6426264e+08
A131: 45694 | B131: 45678 | C131: 45657 | D131: EDS Buyer LLC | E131: Term Loan | F131: LX246993 | G131: Facility - Sale (R) | H131: Principal Collection Subaccount | I131: USD | J131: 5780423.5 | K131: 0.985 | L131: -5868450.3 | M131: 0 | N131: 0 | O131: 142395.74 | P131: 44104557 | Q131: 0 | R131: 3.5839419e+08 | S131: -0.04 | T131: 3.5839419e+08
...

Sheet Outstanding Payments
A7: Outstanding Payments as of 04/30/2025
A8: Unapplied Cash Transactions
A9: Date | B9: Issuer/Borrower | C9: Facility/Security | D9: Amount | E9: Wire Details | F9: Notes
A10: 45698 | B10: TWS Acquisition Corporation (dba Stratatch Education Group) | D10: 2601.86 | E10: FFC:10107500 PENNANTPARK INVESTMENTFUNDING I, LLC: TRUST ACCOUNTTWS ACQUISITION9070000001WATC CLEARINGPENNANTPARK LOAN AGENCY SERVICING,18899
A11: 45742 | B11: HW Holdco LLC | D11: 1899.64 | E11: 10107500 - PENNANTPARK INVESTMENT FHW HOLDCO, LLCPENNANTPARK INVESTMENT FUNDING I, LLOAN - INTEREST PAYMENT9070000001WATC CLEARING590 MADISON AVENUE NEW YORK NY 100HW HOLDCO, LLC250326B01XF3
A12: 45747 | B12: EDS Buyer LLC | D12: 186686.87 | E12: FFC:10107500 PENNANTPARK INVESTMENTFUNDING I, LLC: TRUST ACCOUNTEDS BUYER, LLC9070000001WATC CLEARINGPENNANTPARK LOAN AGENCY SERVICING,19114
A13: 45747 | B13: MDI Buyer Inc | D13: 1868.15 | E13: FFC 10107500 PENNANTPARK INVESTMENTFUNDING I LLC TRUST ACCOUNT REF MDIBUYER9070000001WATC CLEARING590 MADISON AVENUE 15TH FLOORCHURCHILL AGENCY SERVICES, LLC5031699
A14: 45747 | B14: MDI Buyer Inc | D14: 10515.81 | E14: FFC 10107500 PENNANTPARK INVESTMENTFUNDING I LLC TRUST ACCOUNT REF MDIBUYER9070000001WATC CLEARING590 MADISON AVENUE 15TH FLOORCHURCHILL AGENCY SERVICES, LLC5031690
A15: 45756 | B15: CJX Borrower LLC | D15: 2365.7 | E15: AC WATC CLEARING FFC 10107500 - PENNANTPARK INV FUNDING I, LLC TRUST AC REF CONNATIX9070000001PENNANTPARK INVESTMT FD I LLCCJX BORROWER, LLC
A16: 45762 | B16: HW Holdco LLC | D16: 6149.3 | E16: 10107500 - PENNANTPARK INVESTMENT FHW HOLDCO, LLCPENNANTPARK INVESTMENT FUNDING I, LLOAN - INTEREST PAYMENT9070000001WATC CLEARING590 MADISON AVENUE NEW YORK NY 100HW HOLDCO, LLC250415B01GKN
A17: 45762 | B17: HW Holdco LLC | D17: 19866.14 | E17: 10107500 - PENNANTPARK INVESTMENT FHW HOLDCO, LLCPENNANTPARK INVESTMENT FUNDING I, LLOAN - INTEREST PAYMENT9070000001WATC CLEARING590 MADISON AVENUE NEW YORK NY 100HW HOLDCO, LLC250415B01GNX
A18: 45771 | B18: EDS Buyer LLC | D18: 6.41 | E18: FFC 10107500 PENNANTPARK INVESTMENT FUNDING I LLC TRUST ACCOUNT REF EDS BUYER, LLC9070000001WATC CLEARINGPENNANTPARK CLO IV, LLC
D19: 231959.88
A22: Past Due Receivables
A23: Transaction ID | B23: Asset ID | C23: Currency | D23: Date | E23: Issuer/Borrower | F23: Facility/Security | G23: Identifier | H23: Transaction Type | I23: Account | J23: Participation Counterparty | K23: Transaction Amount | L23: Cash Not Applied | M23: Research | N23: Notes
K24: 1541425.3 | L24: 997245.67
A25: 219522 | B25: 12194 | C25: USD | D25: 45657 | E25: Amsive Holdings Corporation | F25: Incremental TL 75MM PIK Fee | H25: Facility - Paydown - Unscheduled Optional | I25: Principal Collection Subaccount | K25: 38.28 | L25: 38.28
A26: 190877 | B26: 5628 | C26: USD | D26: 45657 | E26: Burgess Point Purchaser Corporation | F26: Initial Term Loan | G26: LX205817 | H26: Facility - Paydown - Scheduled | I26: Principal Collection Subaccount | K26: 635.11 | L26: 635.11
A27: 164205 | B27: 10508 | C27: USD | D27: 45657 | E27: Dr. Squatch LLC | F27: 2024-1 Incremental Term Loan | G27: LX239333 | H27: Facility - Paydown - Unscheduled Optional | I27: Principal Collection Subaccount | K27: 16054.4 | L27: 16054.4
A28: 164311 | B28: 11795 | C28: USD | D28: 45659 | E28: Alpine Acquisition Corp II | F28: Amend 4 TLA-2 | G28: LX207291 | H28: Loan - Interest Payment | I28: Interest Collection Subaccount | K28: 10.71 | L28: 10.71
A29: 164309 | B29: 11795 | C29: USD | D29: 45659 | E29: Alpine Acquisition Corp II | F29: Amend 4 TLA-2 | G29: LX207291 | H29: Loan - Interest Payment | I29: Interest Collection Subaccount | K29: 417.08 | L29: 417.08
A30: 163541 | B30: 3273 | C30: USD | D30: 45659 | E30: Rancho Health MSO Inc | F30: Initial Term Loan | G30: LX191986 | H30: Loan - Interest Payment | I30: Interest Collection Subaccount | K30: 5246.07 | L30: 5246.07
A31: 163545 | B31: 3377 | C31: USD | D31: 45659 | E31: Rancho Health MSO Inc | F31: Second Amendment Funded Delayed Draw Term Loan | H31: Loan - Interest Payment | I31: Interest Collection Subaccount | K31: 135.76 | L31: 135.76
A32: 163544 | B32: 3377 | C32: USD | D32: 45659 | E32: Rancho Health MSO Inc | F32: Second Amendment Funded Delayed Draw Term Loan | H32: Loan - Interest Payment | I32: Interest Collection Subaccount | K32: 134.54 | L32: 134.54
A33: 163543 | B33: 3377 | C33: USD | D33: 45659 | E33: Rancho Health MSO Inc | F33: Second Amendment Funded Delayed Draw Term Loan | H33: Loan - Interest Payment | I33: Interest Collection Subaccount | K33: 1077.44 | L33: 1077.44
A34: 163542 | B34: 3377 | C34: USD | D34: 45659 | E34: Rancho Health MSO Inc | F34: Second Amendment Funded Delayed Draw Term Loan | H34: Loan - Interest Payment | I34: Interest Collection Subaccount | K34: 1317.05 | L34: 1317.05
A35: 163550 | B35: 11022 | C35: USD | D35: 45659 | E35: Rancho Health MSO Inc | F35: Sixth Amendment Delayed Draw Term Loan | H35: Loan - Interest Payment | I35: Interest Collection Subaccount | K35: 269.09 | L35: 269.09
A36: 163540 | B36: 3261 | C36: USD | D36: 45659 | E36: S101 Acquisition Inc | F36: Delayed Draw Term Loan B | H36: Loan - Interest Payment | I36: Interest Collection Subaccount | K36: 265.04 | L36: 265.04
A37: 163551 | B37: 11807 | C37: USD | D37: 45660 | E37: STG Distribution LLC | F37: First Out New Money Term Loan | G37: LX249176 | H37: Loan - Interest Payment | I37: Interest Collection Subaccount | K37: 646 | L37: 646
A38: 163552 | B38: 11809 | C38: USD | D38: 45663 | E38: Vertex Companies Inc, The | F38: Term Loan D | G38: LX256513 | H38: Loan - Interest Payment | I38: Interest Collection Subaccount | K38: 11111.3 | L38: 11111.3
A39: 207260 | B39: 10564 | C39: USD | D39: 45672 | E39: Radius Aerospace Inc | F39: Initial Term Loan | G39: LX179630 | H39: Facility - Paydown - Unscheduled Optional | I39: Principal Collection Subaccount | K39: 663518.63 | L39: 663518.63
A40: 163981 | B40: 9063 | C40: USD | D40: 45673 | E40: Argano LLC | F40: Term Loan | G40: LX246656 | H40: Loan - Interest Payment | I40: Interest Collection Subaccount | K40: 37534.74 | L40: 37534.74
A41: 163377 | B41: 4368 | C41: USD | D41: 45686 | E41: Michael Baker International LLC | F41: New Term B Loan | H41: Loan - Interest Payment | I41: Interest Collection Subaccount | K41: 3658.91 | L41: 3658.91
A42: 164060 | B42: 2495 | C42: USD | D42: 45688 | E42: AFC-Dell Holding Corp | F42: Term Loan | H42: Loan - Interest Payment | I42: Interest Collection Subaccount | K42: 15507.34 | L42: 15507.34
A43: 162884 | B43: 12770 | C43: USD | D43: 45688 | E43: Dr. Squatch LLC | F43: Delayed Draw Term Loan | G43: LX203614 | H43: Loan - Interest Payment | I43: Interest Collection Subaccount | K43: 6188.91 | L43: 6188.91
A44: 164787 | B44: 10550 | C44: USD | D44: 45688 | E44: Infinity Home Services Holdco Inc | F44: Closing Date Delayed Draw Term Loan | G44: LX210066 | H44: Loan - Interest Payment | I44: Interest Collection Subaccount | K44: 19831.28 | L44: 19831.28
A45: 163539 | B45: 3236 | C45: USD | D45: 45688 | E45: Inventus Power Inc | F45: Term Loan | G45: LX213612 | H45: Loan - Interest Payment | I45: Interest Collection Subaccount | K45: 20416.66 | L45: 20416.66
A46: 164790 | B46: 10568 | C46: USD | D46: 45688 | E46: Lash OpCo LLC | F46: Restatement Term Loan | G46: LX201224 | H46: Loan - Interest Payment | I46: Interest Collection Subaccount | K46: 22172.31 | L46: 22172.31
A47: 199238 | B47: 14717 | C47: USD | D47: 45688 | E47: LAV Gear Holdings Inc | F47: Twelfth Amendment Term Loan | G47: LX258942 | H47: Facility Trade - Miscellaneous Fee | I47: Interest Collection Subaccount | K47: 1264.03 | L47: 1264.03
A48: 164470 | B48: 12399 | C48: USD | D48: 45688 | E48: Michael Baker International LLC | F48: Term B-1 Loan | G48: LX258116 | H48: Loan - Interest Payment | I48: Interest Collection Subaccount | K48: 230.34 | L48: 230.34
A49: 164904 | B49: 10527 | C49: USD | D49: 45688 | E49: Team Services Group LLC | F49: Incremental Term Loan | G49: LX236336 | H49: Loan - Interest Payment | I49: Interest Collection Subaccount | K49: 8272.7 | L49: 8272.7
A50: 163375 | B50: 10523 | C50: USD | D50: 45688 | E50: TMII Enterprises LLC | F50: DDTL | G50: LX210294 | H50: Loan - Interest Payment | I50: Interest Collection Subaccount | K50: 25096.3 | L50: 25096.3
A51: 164327 | B51: 11795 | C51: USD | D51: 45691 | E51: Alpine Acquisition Corp II | F51: Amend 4 TLA-2 | G51: LX207291 | H51: Loan - Interest Payment | I51: Interest Collection Subaccount | K51: 6673.34 | L51: 6673.34
A52: 164330 | B52: 11795 | C52: USD | D52: 45691 | E52: Alpine Acquisition Corp II | F52: Amend 4 TLA-2 | G52: LX207291 | H52: Loan - Interest Payment | I52: Interest Collection Subaccount | K52: 222.28 | L52: 222.28
A53: 226970 | B53: 10572 | C53: USD | D53: 45691 | E53: LJ Avalon Holdings LLC | F53: Delayed Draw Term Loan | G53: LX210727 | H53: Loan - Interest Payment | I53: Interest Collection Subaccount | K53: 1053.73 | L53: 1053.73
A54: 226971 | B54: 10572 | C54: USD | D54: 45691 | E54: LJ Avalon Holdings LLC | F54: Delayed Draw Term Loan | G54: LX210727 | H54: Loan - Interest Payment | I54: Interest Collection Subaccount | K54: 1645.6 | L54: 1645.6
A55: 180877 | B55: 10576 | C55: USD | D55: 45691 | E55: LJ Avalon Holdings LLC | F55: Term Loan | G55: LX210725 | H55: Loan - Interest Payment | I55: Interest Collection Subaccount | K55: 609.95 | L55: 609.95
A56: 164009 | B56: 3261 | C56: USD | D56: 45691 | E56: S101 Acquisition Inc | F56: Delayed Draw Term Loan B | H56: Loan - Interest Payment | I56: Interest Collection Subaccount | K56: 4123.54 | L56: 4123.54
A57: 163951 | B57: 3259 | C57: USD | D57: 45691 | E57: S101 Acquisition Inc | F57: Delayed Draw Term Loan C | H57: Loan - Interest Payment | I57: Interest Collection Subaccount | K57: 17210.68 | L57: 17210.68
A58: 163574 | B58: 11807 | C58: USD | D58: 45691 | E58: STG Distribution LLC | F58: First Out New Money Term Loan | G58: LX249176 | H58: Loan - Interest Payment | I58: Interest Collection Subaccount | K58: 6487.04 | L58: 6487.04
A59: 176734 | B59: 10525 | C59: USD | D59: 45716 | E59: Harris & Co. LLC | F59: Delayed Draw Term Loan A | G59: LX245516 | H59: Loan - Interest Payment | I59: Interest Collection Subaccount | K59: 23198.81 | L59: -367.59
A60: 177489 | B60: 12755 | C60: USD | D60: 45721 | E60: MDI Buyer Inc | F60: First Amendment Delayed Draw Term Loan | G60: LX209153 | H60: Loan - Interest Payment | I60: Interest Collection Subaccount | K60: 9781.26 | L60: 17.44
A61: 219527 | B61: 12194 | C61: USD | D61: 45734 | E61: Amsive Holdings Corporation | F61: Incremental TL 75MM PIK Fee | H61: Facility - Paydown - Unscheduled Optional | I61: Principal Collection Subaccount | K61: 76.56 | L61: 76.56
A62: 219529 | B62: 12194 | C62: USD | D62: 45747 | E62: Amsive Holdings Corporation | F62: Incremental TL 75MM PIK Fee | H62: Facility - Paydown - Unscheduled Optional | I62: Principal Collection Subaccount | K62: 38.28 | L62: 38.28
A63: 233667 | B63: 12194 | C63: USD | D63: 45747 | E63: Amsive Holdings Corporation | F63: Incremental TL 75MM PIK Fee | H63: Loan - Interest Payment | I63: Interest Collection Subaccount | K63: 401.64 | L63: 401.64
A64: 211900 | B64: 11551 | C64: USD | D64: 45747 | E64: BlackHawk Industrial Distribution Inc | F64: 2022-2 Incr TL 10MM | G64: LX208588 | H64: Loan - Interest Payment | I64: Interest Collection Subaccount | K64: 1313.76 | L64: -38.32
A65: 210093 | B65: 3149 | C65: USD | D65: 45747 | E65: BlackHawk Industrial Distribution Inc | F65: Initial Term Loan | G65: LX176035 | H65: Loan - Interest Payment | I65: Interest Collection Subaccount | K65: 123076.13 | L65: -10126.5
A66: 190881 | B66: 5628 | C66: USD | D66: 45747 | E66: Burgess Point Purchaser Corporation | F66: Initial Term Loan | G66: LX205817 | H66: Loan - Interest Payment | I66: Interest Collection Subaccount | K66: 6024.14 | L66: -49879.78
A67: 228220 | B67: 10514 | C67: USD | D67: 45747 | E67: EDS Buyer LLC | F67: Delayed Draw Term Loan | G67: LX246994 | H67: Facility - Paydown - Scheduled | I67: Principal Collection Subaccount | K67: 13769.35 | L67: 13769.35
A68: 228226 | B68: 10514 | C68: USD | D68: 45747 | E68: EDS Buyer LLC | F68: Delayed Draw Term Loan | G68: LX246994 | H68: Loan - Interest Payment | I68: Interest Collection Subaccount | K68: 138421.64 | L68: 138421.64
A69: 208200 | B69: 10512 | C69: USD | D69: 45747 | E69: EDS Buyer LLC | F69: Term Loan | G69: LX246993 | H69: Loan - Interest Payment | I69: Interest Collection Subaccount | K69: 34502.31 | L69: 34502.31
A70: 200103 | B70: 10538 | C70: USD | D70: 45747 | E70: HW Holdco LLC | F70: Restatement Date Term Loan | G70: LX227878 | H70: Loan - Interest Payment | I70: Interest Collection Subaccount | K70: 40659.83 | L70: -27226.98
A71: 193988 | B71: 11180 | C71: USD | D71: 45747 | E71: Lightspeed Buyer Inc | F71: Restatement Date TL | G71: LX255973 | H71: Loan - Interest Payment | I71: Interest Collection Subaccount | K71: 57030.8 | L71: -10591.91
A72: 194709 | B72: 12755 | C72: USD | D72: 45747 | E72: MDI Buyer Inc | F72: First Amendment Delayed Draw Term Loan | G72: LX209153 | H72: Facility - Paydown - Unscheduled Optional | I72: Principal Collection Subaccount | K72: 1855.67 | L72: 1855.67
A73: 194702 | B73: 12753 | C73: USD | D73: 45747 | E73: MDI Buyer Inc | F73: Initial Delayed Draw Term Loan | G73: LX206515 | H73: Facility - Paydown - Unscheduled Optional | I73: Principal Collection Subaccount | K73: 10432.15 | L73: 10432.15
A74: 207936 | B74: 12399 | C74: USD | D74: 45747 | E74: Michael Baker International LLC | F74: Term B-1 Loan | G74: LX258116 | H74: Facility - Paydown - Unscheduled Optional | I74: Principal Collection Subaccount | K74: 1253.13 | L74: 1253.13
A75: 207933 | B75: 12399 | C75: USD | D75: 45747 | E75: Michael Baker International LLC | F75: Term B-1 Loan | G75: LX258116 | H75: Loan - Interest Payment | I75: Interest Collection Subaccount | K75: 3574.89 | L75: 3574.89
... A77: 204371 | B77: 10461 | C77: USD | D77: 45747 | E77: Urology Management Holdings Inc | F77: 6th Amen DDTL 50MM | G77: LX210841 | H77: Loan - Interest Payment | I77: Interest Collection Subaccount | K77: 28670.37 | L77: -11438.09
A78: 212118 | B78: 11022 | C78: USD | D78: 45748 | E78: Rancho Health MSO Inc | F78: Sixth Amendment Delayed Draw Term Loan | H78: Loan - Interest Payment | I78: Interest Collection Subaccount | K78: 11043.85 | L78: 4.26
A79: 233509 | B79: 12399 | C79: USD | D79: 45777 | E79: Michael Baker International LLC | F79: Term B-1 Loan | G79: LX258116 | H79: Loan - Interest Payment | I79: Interest Collection Subaccount | K79: 3451.33 | L79: 3451.33

Sheet Sheet1
A1: Asset Type | B1: Facility | K1: 1 | L1: =K1+1 -> 2 | M1: =L1+1 -> 3 | N1: =M1+1 -> 4 | O1: =N1+1 -> 5 | P1: =O1+1 -> 6 | Q1: =P1+1 -> 7 | R1: =Q1+1 -> 8 | S1: =R1+1 -> 9 | ... W1: =V1+1 -> 13
E2: =SUM(E4:E76) -> 4.1352401e+08 | L2: =M3-E2 -> 0.0099999905 | M2: WA | N2: BB | O2: SOI | Q2: Coupon | R2: Spread | S2: Date of Latest Financial Reporting | T2: Net Senior Lev Ratio | U2: EBITDA ($m) | V2: Total Leverage Ratio (current) | W2: Cash Interest Coverage Ratio (current)
A3: Row Labels | B3: Sum of Settled Funded | I3: SOI | J3: Western Alliance | K3: Borrowing Base | L3: Master Comps | M3: =SUM(M4:M79) -> 4.1352401e+08 | N3: =SUM(N4:N79) -> 4.0044313e+08 | O3: =SUM(O4:O79) -> 4.0044313e+08
A4: AFC-Dell Holding Corp | B4: 269595.43 | D4: AFC-Dell Holding Corp | E4: 269595.43 | F4: =VLOOKUP(D4, $J$4:$K$79, 2, FALSE) -> AFC - Dell Holding Corp. | I4: A1 Garage Merger Sub, LLC | J4: =+VLOOKUP(K4,'[2]Sheet2 (2)'!$G$1:$H$73, 2, FALSE) -> TMII Enterprises LLC | K4: A1 Garage Merger Sub, LLC | L4: A1 Garage Merger Sub, LLC | M4: =VLOOKUP(J4, $D$4:$E$78, 2, FALSE) -> 3192037.2 | N4: =VLOOKUP(K4, 'Loan List '!$A$6:$H$82, 8, FALSE) -> 3192037.3 | O4: =VLOOKUP(I4, Sheet2!$A$1:$D$78, 4, FALSE) -> 3192037.3 | P4: =N4-O4 -> 0 | Q4: =VLOOKUP(I4, Sheet2!$A$1:$E$78, 5, FALSE) -> 0.090083815 | R4: =VLOOKUP($L4, '[3]BNP Borrowing Base PSLF JV (PIF'!$A$8:$AI$181, 11, FALSE) -> 0.0475 | S4: =VLOOKUP($L4, '[3]BNP Borrowing Base PSLF JV (PIF'!$A$8:$AI$181, 20, FALSE) -> 45716 | T4: =VLOOKUP($L4, '[3]BNP Borrowing Base PSLF JV (PIF'!$A$8:$AI$181, 22, FALSE) -> 2.3958956 | U4: =VLOOKUP($L4, '[3]BNP Borrowing Base PSLF JV (PIF'!$A$8:$AI$181, 23, FALSE) -> 60.907 | V4: =VLOOKUP($L4, '[3]BNP Borrowing Base PSLF JV (PIF'!$A$8:$AI$181, 32, FALSE) -> 2.3958956 | W4: =VLOOKUP($L4, '[3]BNP Borrowing Base PSLF JV (PIF'!$A$8:$AI$181, 34, FALSE) -> 3.1669615
A5: Alpine Acquisition Corp II | B5: 3958430.5 | D5: Alpine Acquisition Corp II | E5: 3958430.5 | F5: =VLOOKUP(D5, $J$4:$K$79, 2, FALSE) -> Alpine Acquisition Corp II | I5: AFC - Dell Holding Corp. | J5: =+VLOOKUP(K5,'[2]Sheet2 (2)'!$G$1:$H$73, 2, FALSE) -> AFC-Dell Holding Corp | K5: AFC - Dell Holding Corp. | L5: AFC - Dell Holding Corp. | M5: =VLOOKUP(J5, $D$4:$E$78, 2, FALSE) -> 269595.43 | N5: =VLOOKUP(K5, 'Loan List '!$A$6:$H$82, 8, FALSE) -> 269595.42 | O5: =VLOOKUP(I5, Sheet2!$A$1:$D$78, 4, FALSE) -> 269595.42 | P5: =N5-O5 -> 0 | Q5: =VLOOKUP(I5, Sheet2!$A$1:$E$78, 5, FALSE) -> 0.097908 | R5: =VLOOKUP($L5, '[3]BNP Borrowing Base PSLF JV (PIF'!$A$8:$AI$181, 11, FALSE) -> 0.0625 | S5: =VLOOKUP($L5, '[3]BNP Borrowing Base PSLF JV (PIF'!$A$8:$AI$181, 20, FALSE) -> 45716 | T5: =VLOOKUP($L5, '[3]BNP Borrowing Base PSLF JV (PIF'!$A$8:$AI$181, 22, FALSE) -> 6.0802911 | U5: =VLOOKUP($L5, '[3]BNP Borrowing Base PSLF JV (PIF'!$A$8:$AI$181, 23, FALSE) -> 76.694092 | V5: =VLOOKUP($L5, '[3]BNP Borrowing Base PSLF JV (PIF'!$A$8:$AI$181, 32, FALSE) -> 7.1419735 | W5: =VLOOKUP($L5, '[3]BNP Borrowing Base PSLF JV (PIF'!$A$8:$AI$181, 34, FALSE) -> 1.3690869
A6: Amsive Holdings Corporation | B6: 15083.03 | D6: Amsive Holdings Corporation | E6: 15083.03 | F6: =VLOOKUP(D6, $J$4:$K$79, 2, FALSE) -> Amsive Holding Corporation | I6: Alpine Acquisition Corp II | J6: =+VLOOKUP(K6,'[2]Sheet2 (2)'!$G$1:$H$73, 2, FALSE) -> Alpine Acquisition Corp II | K6: Alpine Acquisition Corp II | L6: Alpine Acquisition Corp II | M6: =VLOOKUP(J6, $D$4:$E$78, 2, FALSE) -> 3958430.5 | N6: =O6 -> 3958430.6 | O6: =VLOOKUP(I6, Sheet2!$A$1:$D$78, 4, FALSE) -> 3958430.6 | P6: =N6-O6 -> 0 | Q6: =VLOOKUP(I6, Sheet2!$A$1:$E$78, 5, FALSE) -> 0.1042 | R6: =VLOOKUP($L6, '[3]BNP Borrowing Base PSLF JV (PIF'!$A$8:$AI$181, 11, FALSE) -> 0 | S6: =VLOOKUP($L6, '[3]BNP Borrowing Base PSLF JV (PIF'!$A$8:$AI$181, 20, FALSE) -> 45716 | T6: =VLOOKUP($L6, '[3]BNP Borrowing Base PSLF JV (PIF'!$A$8:$AI$181, 22, FALSE) -> 17.877093 | U6: =VLOOKUP($L6, '[3]BNP Borrowing Base PSLF JV (PIF'!$A$8:$AI$181, 23, FALSE) -> 103.045 | V6: =VLOOKUP($L6, '[3]BNP Borrowing Base PSLF JV (PIF'!$A$8:$AI$181, 32, FALSE) -> 18.393702 | W6: =VLOOKUP($L6, '[3]BNP Borrowing Base PSLF JV (PIF'!$A$8:$AI$181, 34, FALSE) -> 0.67151292
A7: Arcfield Acquisition Corp | B7: 11620875 | D7: Arcfield Acquisition Corp | E7: 11620875 | F7: =VLOOKUP(D7, $J$4:$K$79, 2, FALSE) -> Arcfield | I7: Archer Lewis, LLC | J7: =+VLOOKUP(K7,'[2]Sheet2 (2)'!$G$1:$H$73, 2, FALSE) -> Archer Lewis LLC | K7: Archer Lewis | L7: Archer Lewis | M7: =VLOOKUP(J7, $D$4:$E$78, 2, FALSE) -> 8816867.8 | N7: =VLOOKUP(K7, 'Loan List '!$A$6:$H$82, 8, FALSE) -> 8816867.8 | O7: =VLOOKUP(I7, Sheet2!$A$1:$D$78, 4, FALSE) -> 8816867.8 | P7: =N7-O7 -> 0 | Q7: =VLOOKUP(I7, Sheet2!$A$1:$E$78, 5, FALSE) -> 0.10051621 | R7: =VLOOKUP($L7, '[3]BNP Borrowing Base PSLF JV (PIF'!$A$8:$AI$181, 11, FALSE) -> 0.0575 | S7: =VLOOKUP($L7, '[3]BNP Borrowing Base PSLF JV (PIF'!$A$8:$AI$181, 20, FALSE) -> 45716 | T7: =VLOOKUP($L7, '[3]BNP Borrowing Base PSLF JV (PIF'!$A$8:$AI$181, 22, FALSE) -> 4.5132407 | U7: =VLOOKUP($L7, '[3]BNP Borrowing Base PSLF JV (PIF'!$A$8:$AI$181, 23, FALSE) -> 14.222627 | V7: =VLOOKUP($L7, '[3]BNP Borrowing Base PSLF JV (PIF'!$A$8:$AI$181, 32, FALSE) -> 4.5132407 | W7: =VLOOKUP($L7, '[3]BNP Borrowing Base PSLF JV (PIF'!$A$8:$AI$181, 34, FALSE) -> 3.1751472
A8: Archer Lewis LLC | B8: 8816867.8 | D8: Archer Lewis LLC | E8: 8816867.8 | F8: =VLOOKUP(D8, $J$4:$K$79, 2, FALSE) -> Archer Lewis | I8: Argano, LLC | J8: =+VLOOKUP(K8,'[2]Sheet2 (2)'!$G$1:$H$73, 2, FALSE) -> Argano LLC | K8: Argano, LLC | L8: Argano, LLC | M8: =VLOOKUP(J8, $D$4:$E$78, 2, FALSE) -> 5472521.9 | N8: =VLOOKUP(K8, 'Loan List '!$A$6:$H$82, 8, FALSE) -> 5472500 | O8: =VLOOKUP(I8, Sheet2!$A$1:$D$78, 4, FALSE) -> 5472500 | P8: =N8-O8 -> 0 | Q8: =VLOOKUP(I8, Sheet2!$A$1:$E$78, 5, FALSE) -> 0.100664 | R8: =VLOOKUP($L8, '[3]BNP Borrowing Base PSLF JV (PIF'!$A$8:$AI$181, 11, FALSE) -> 0.0575 | S8: =VLOOKUP($L8, '[3]BNP Borrowing Base PSLF JV (PIF'!$A$8:$AI$181, 20, FALSE) -> 45716 | T8: =VLOOKUP($L8, '[3]BNP Borrowing Base PSLF JV (PIF'!$A$8:$AI$181, 22, FALSE) -> 3.9962264 | U8: =VLOOKUP($L8, '[3]BNP Borrowing Base PSLF JV (PIF'!$A$8:$AI$181, 23, FALSE) -> 61.919506 | V8: =VLOOKUP($L8, '[3]BNP Borrowing Base PSLF JV (PIF'!$A$8:$AI$181, 32, FALSE) -> 6.4187263 | W8: =VLOOKUP($L8, '[3]BNP Borrowing Base PSLF JV (PIF'!$A$8:$AI$181, 34, FALSE) -> 1.532529
A9: Argano LLC | B9: 5472521.9 | D9: Argano LLC | E9: 5472521.9 | F9: =VLOOKUP(D9, $J$4:$K$79, 2, FALSE) -> Argano, LLC | I9: Burgess Point Purchaser Corporation | J9: =+VLOOKUP(K9,'[2]Sheet2 (2)'!$G$1:$H$73, 2, FALSE) -> Burgess Point Purchaser Corporation | K9: BBB Industries | L9: BBB Industries | M9: =VLOOKUP(J9, $D$4:$E$78, 2, FALSE) -> 248327.5 | N9: =VLOOKUP(K9, 'Loan List '!$A$6:$H$82, 8, FALSE) -> 248327.5 | O9: =VLOOKUP(I9, Sheet2!$A$1:$D$78, 4, FALSE) -> 248327.5 | P9: =N9-O9 -> 0 | Q9: =VLOOKUP(I9, Sheet2!$A$1:$E$78, 5, FALSE) -> 0.096492 | R9: =VLOOKUP($L9, '[3]BNP Borrowing Base PSLF JV (PIF'!$A$8:$AI$181, 11, FALSE) -> 0.0525 | S9: =VLOOKUP($L9, '[3]BNP Borrowing Base PSLF JV (PIF'!$A$8:$AI$181, 20, FALSE) -> 45565 | T9: =VLOOKUP($L9, '[3]BNP Borrowing Base PSLF JV (PIF'!$A$8:$AI$181, 22, FALSE) -> 5.6274247 | U9: =VLOOKUP($L9, '[3]BNP Borrowing Base PSLF JV (PIF'!$A$8:$AI$181, 23, FALSE) -> 299 | V9: =VLOOKUP($L9, '[3]BNP Borrowing Base PSLF JV (PIF'!$A$8:$AI$181, 32, FALSE) -> 6.8197324 | W9: =VLOOKUP($L9, '[3]BNP Borrowing Base PSLF JV (PIF'!$A$8:$AI$181, 34, FALSE) -> 1.3906977
A10: Beacon Behavioral Support Services LLC | B10: 12170103 | D10: Beacon Behavioral Support Services LLC | E10: 12170103 | F10: =VLOOKUP(D10, $J$4:$K$79, 2, FALSE) -> Beacon Behavioral Support Services, LLC | I10: Beacon Behavioral Support Services, LLC | J10: =+VLOOKUP(K10,'[2]Sheet2 (2)'!$G$1:$H$73, 2, FALSE) -> Beacon Behavioral Support Services LLC | K10: Beacon Behavioral Support Services, LLC | L10: Beacon Behavioral | M10: =VLOOKUP(J10, $D$4:$E$78, 2, FALSE) -> 12170103 | N10: =VLOOKUP(K10, 'Loan List '!$A$6:$H$82, 8, FALSE) -> 12170103 | O10: =VLOOKUP(I10, Sheet2!$A$1:$D$78, 4, FALSE) -> 12170103 | P10: =N10-O10 -> 0 | Q10: =VLOOKUP(I10, Sheet2!$A$1:$E$78, 5, FALSE) -> 0.098011024 | R10: =VLOOKUP($L10, '[3]BNP Borrowing Base PSLF JV (PIF'!$A$8:$AI$181, 11, FALSE) -> 0.055 | S10: =VLOOKUP($L10, '[3]BNP Borrowing Base PSLF JV (PIF'!$A$8:$AI$181, 20, FALSE) -> 45716 | T10: =VLOOKUP($L10, '[3]BNP Borrowing Base PSLF JV (PIF'!$A$8:$AI$181, 22, FALSE) -> 4.9021373 | U10: =VLOOKUP($L10, '[3]BNP Borrowing Base PSLF JV (PIF'!$A$8:$AI$181, 23, FALSE) -> 22.015998 | V10: =VLOOKUP($L10, '[3]BNP Borrowing Base PSLF JV (PIF'!$A$8:$AI$181, 32, FALSE) -> 5.4872036 | W10: =VLOOKUP($L10, '[3]BNP Borrowing Base PSLF JV (PIF'!$A$8:$AI$181, 34, FALSE) -> 2.4399881
A11: Best Practice Associates LLC | B11: 10781438 | D11: Best Practice Associates LLC | E11: 10781438 | F11: =VLOOKUP(D11, $J$4:$K$79, 2, FALSE) -> Federal Advisory Partners | I11: Blackhawk Industrial Distribution, Inc. | J11: =+VLOOKUP(K11,'[2]Sheet2 (2)'!$G$1:$H$73, 2, FALSE) -> BlackHawk Industrial Distribution Inc | K11: BlackHawk Industrial | L11: BlackHawk Industrial | M11: =VLOOKUP(J11, $D$4:$E$78, 2, FALSE) -> 8649720.3 | N11: =VLOOKUP(K11, 'Loan List '!$A$6:$H$82, 8, FALSE) -> 8653790.5 | O11: =VLOOKUP(I11, Sheet2!$A$1:$D$78, 4, FALSE) -> 8653790.5 | P11: =N11-O11 -> 0 | Q11: =VLOOKUP(I11, Sheet2!$A$1:$E$78, 5, FALSE) -> 0.096992704 | R11: =VLOOKUP($L11, '[3]BNP Borrowing Base PSLF JV (PIF'!$A$8:$AI$181, 11, FALSE) -> 0.05 | S11: =VLOOKUP($L11, '[3]BNP Borrowing Base PSLF JV (PIF'!$A$8:$AI$181, 20, FALSE) -> 45716 | T11: =VLOOKUP($L11, '[3]BNP Borrowing Base PSLF JV (PIF'!$A$8:$AI$181, 22, FALSE) -> 5.8248222 | U11: =VLOOKUP($L11, '[3]BNP Borrowing Base PSLF JV (PIF'!$A$8:$AI$181, 23, FALSE) -> 51.188 | V11: =VLOOKUP($L11, '[3]BNP Borrowing Base PSLF JV (PIF'!$A$8:$AI$181, 32, FALSE) -> 6.4096273 | W11: =VLOOKUP($L11, '[3]BNP Borrowing Base PSLF JV (PIF'!$A$8:$AI$181, 34, FALSE) -> 1.2666221
A12: BlackHawk Industrial Distribution Inc | B12: 8649720.3 | D12: BlackHawk Industrial Distribution Inc | E12: 8649720.3 | F12: =VLOOKUP(D12, $J$4:$K$79, 2, FALSE) -> BlackHawk Industrial | I12: BlueHalo Global Holdings, LLC | J12: =+VLOOKUP(K12,'[2]Sheet2 (2)'!$G$1:$H$73, 2, FALSE) -> BlueHalo Global Holdings LLC | K12: BlueHalo Financing Holdings, LLC | L12: BlueHalo Financing Holdings, LLC | M12: =VLOOKUP(J12, $D$4:$E$78, 2, FALSE) -> 2628762.5 | N12: =VLOOKUP(K12, 'Loan List '!$A$6:$H$82, 8, FALSE) -> 2628762.5 | O12: =VLOOKUP(I12, Sheet2!$A$1:$D$78, 4, FALSE) -> 2628762.5 | P12: =N12-O12 -> 0 | Q12: =VLOOKUP(I12, Sheet2!$A$1:$E$78, 5, FALSE) -> 0.1029917 | R12: =VLOOKUP($L12, '[3]BNP Borrowing Base PSLF JV (PIF'!$A$8:$AI$181, 11, FALSE) -> 0.06 | S12: =VLOOKUP($L12, '[3]BNP Borrowing Base PSLF JV (PIF'!$A$8:$AI$181, 20, FALSE) -> 45657 | T12: =VLOOKUP($L12, '[3]BNP Borrowing Base PSLF JV (PIF'!$A$8:$AI$181, 22, FALSE) -> 7.6702881 | U12: =VLOOKUP($L12, '[3]BNP Borrowing Base PSLF JV (PIF'!$A$8:$AI$181, 23, FALSE) -> 103.7901 | V12: =VLOOKUP($L12, '[3]BNP Borrowing Base PSLF JV (PIF'!$A$8:$AI$181, 32, FALSE) -> 7.7329145 | W12: =VLOOKUP($L12, '[3]BNP Borrowing Base PSLF JV (PIF'!$A$8:$AI$181, 34, FALSE) -> 1.5967892
A13: BLC Holding Company Inc | B13: 2098550.6 | D13: BLC Holding Company Inc | E13: 2098550.6 | F13: =VLOOKUP(D13, $J$4:$K$79, 2, FALSE) -> Bland Landscaping | I13: C5MI Acquisition, LLC | J13: =+VLOOKUP(K13,'[2]Sheet2 (2)'!$G$1:$H$73, 2, FALSE) -> C5MI Acquisition LLC | K13: C5MI Acquisition, LLC | L13: C5MI | M13: =VLOOKUP(J13, $D$4:$E$78, 2, FALSE) -> 1492500 | N13: =VLOOKUP(K13, 'Loan List '!$A$6:$H$82, 8, FALSE) -> 1492500 | O13: =VLOOKUP(I13, Sheet2!$A$1:$D$78, 4, FALSE) -> 1492500 | P13: =N13-O13 -> 0 | Q13: =VLOOKUP(I13, Sheet2!$A$1:$E$78, 5, FALSE) -> 0.102992 | R13: =VLOOKUP($L13, '[3]BNP Borrowing Base PSLF JV (PIF'!$A$8:$AI$181, 11, FALSE) -> 0.06 | S13: =VLOOKUP($L13, '[3]BNP Borrowing Base PSLF JV (PIF'!$A$8:$AI$181, 20, FALSE) -> 45716 | T13: =VLOOKUP($L13, '[3]BNP Borrowing Base PSLF JV (PIF'!$A$8:$AI$181, 22, FALSE) -> 5.1127309 | U13: =VLOOKUP($L13, '[3]BNP Borrowing Base PSLF JV (PIF'!$A$8:$AI$181, 23, FALSE) -> 15.613157 | V13: =VLOOKUP($L13, '[3]BNP Borrowing Base PSLF JV (PIF'!$A$8:$AI$181, 32, FALSE) -> 5.5418561 | W13: =VLOOKUP($L13, '[3]BNP Borrowing Base PSLF JV (PIF'!$A$8:$AI$181, 34, FALSE) -> 1.7344098
A14: Bluebird Group LLC, The | B14: 3635030.3 | D14: Bluebird Group LLC, The | E14: 3635030.3 | F14: =VLOOKUP(D14, $J$4:$K$79, 2, FALSE) -> The Bluebird Group LLC | I14: CF512, Inc. | J14: =+VLOOKUP(K14,'[2]Sheet2 (2)'!$G$1:$H$73, 2, FALSE) -> CF512 Inc | K14: CF512, Inc. | L14: Gen3 Marketing | M14: =VLOOKUP(J14, $D$4:$E$78, 2, FALSE) -> 6298498.8 | N14: =VLOOKUP(K14, 'Loan List '!$A$6:$H$82, 8, FALSE) -> 6298498.8 | O14: =VLOOKUP(I14, Sheet2!$A$1:$D$78, 4, FALSE) -> 6298498.8 | P14: =N14-O14 -> 0 | Q14: =VLOOKUP(I14, Sheet2!$A$1:$E$78, 5, FALSE) -> 0.10501243 | R14: =VLOOKUP($L14, '[3]BNP Borrowing Base PSLF JV (PIF'!$A$8:$AI$181, 11, FALSE) -> 0.06 | S14: =VLOOKUP($L14, '[3]BNP Borrowing Base PSLF JV (PIF'!$A$8:$AI$181, 20, FALSE) -> 45747 | T14: =VLOOKUP($L14, '[3]BNP Borrowing Base PSLF JV (PIF'!$A$8:$AI$181, 22, FALSE) -> 5.6147306 | U14: =VLOOKUP($L14, '[3]BNP Borrowing Base PSLF JV (PIF'!$A$8:$AI$181, 23, FALSE) -> 11.88 | V14: =VLOOKUP($L14, '[3]BNP Borrowing Base PSLF JV (PIF'!$A$8:$AI$181, 32, FALSE) -> 5.6147306 | W14: =VLOOKUP($L14, '[3]BNP Borrowing Base PSLF JV (PIF'!$A$8:$AI$181, 34, FALSE) -> 1.3873642
A15: BlueHalo Global Holdings LLC | B15: 2628762.5 | D15: BlueHalo Global Holdings LLC | E15: 2628762.5 | F15: =VLOOKUP(D15, $J$4:$K$79, 2, FALSE) -> BlueHalo Financing Holdings, LLC | I15: Carnegie Dartlet, LLC | J15: =+VLOOKUP(K15,'[2]Sheet2 (2)'!$G$1:$H$73, 2, FALSE) -> Carnegie Dartlet LLC | K15: Carnegie Dartlet, LLC | L15: Carnegie Dartlet, LLC | M15: =VLOOKUP(J15, $D$4:$E$78, 2, FALSE) -> 6900150.8 | N15: =VLOOKUP(K15, 'Loan List '!$A$6:$H$82, 8, FALSE) -> 6900150.8 | O15: =VLOOKUP(I15, Sheet2!$A$1:$D$78, 4, FALSE) -> 6900150.8 | P15: =N15-O15 -> 0 | Q15: =VLOOKUP(I15, Sheet2!$A$1:$E$78, 5, FALSE) -> 0.098249 | R15: =VLOOKUP($L15, '[3]BNP Borrowing Base PSLF JV (PIF'!$A$8:$AI$181, 11, FALSE) -> 0.055 | S15: =VLOOKUP($L15, '[3]BNP Borrowing Base PSLF JV (PIF'!$A$8:$AI$181, 20, FALSE) -> 45716 | T15: =VLOOKUP($L15, '[3]BNP Borrowing Base PSLF JV (PIF'!$A$8:$AI$181, 22, FALSE) -> 4.6093662 | U15: =VLOOKUP($L15, '[3]BNP Borrowing Base PSLF JV (PIF'!$A$8:$AI$181, 23, FALSE) -> 19.453 | V15: =VLOOKUP($L15, '[3]BNP Borrowing Base PSLF JV (PIF'!$A$8:$AI$181, 32, FALSE) -> 4.6093662 | W15: =VLOOKUP($L15, '[3]BNP Borrowing Base PSLF JV (PIF'!$A$8:$AI$181, 34, FALSE) -> 2.2110269
A16: Boss Industries LLC | B16: 5985000 | D16: Boss Industries LLC | E16: 5985000 | F16: =VLOOKUP(D16, $J$4:$K$79, 2, FALSE) -> Boss Industries | I16: Carisk Buyer, Inc. | J16: =+VLOOKUP(K16,'[2]Sheet2 (2)'!$G$1:$H$73, 2, FALSE) -> Carisk Buyer Inc | K16: Carisk Buyer, Inc. | L16: Carisk Buyer, Inc. | M16: =VLOOKUP(J16, $D$4:$E$78, 2, FALSE) -> 1116738.2 | N16: =VLOOKUP(K16, 'Loan List '!$A$6:$H$82, 8, FALSE) -> 1116738.2 | O16: =VLOOKUP(I16, Sheet2!$A$1:$D$78, 4, FALSE) -> 1116738.2 | P16: =N16-O16 -> 0 | Q16: =VLOOKUP(I16, Sheet2!$A$1:$E$78, 5, FALSE) -> 0.095492 | R16: =VLOOKUP($L16, '[3]BNP Borrowing Base PSLF JV (PIF'!$A$8:$AI$181, 11, FALSE) -> 0.0575 | S16: =VLOOKUP($L16, '[3]BNP Borrowing Base PSLF JV (PIF'!$A$8:$AI$181, 20, FALSE) -> 45747 | T16: =VLOOKUP($L16, '[3]BNP Borrowing Base PSLF JV (PIF'!$A$8:$AI$181, 22, FALSE) -> 3.2892937 | U16: =VLOOKUP($L16, '[3]BNP Borrowing Base PSLF JV (PIF'!$A$8:$AI$181, 23, FALSE) -> 18.868362 | V16: =VLOOKUP($L16, '[3]BNP Borrowing Base PSLF JV (PIF'!$A$8:$AI$181, 32, FALSE) -> 3.2892937 | W16: =VLOOKUP($L16, '[3]BNP Borrowing Base PSLF JV (PIF'!$A$8:$AI$181, 34, FALSE) -> 2.1712655
A17: Burgess Point Purchaser Corporation | B17: 248327.5 | D17: Burgess Point Purchaser Corporation | E17: 248327.5 | F17: =VLOOKUP(D17, $J$4:$K$79, 2, FALSE) -> BBB Industries | I17: Cartessa Aesthetics, LLC | J17: =+VLOOKUP(K17,'[2]Sheet2 (2)'!$G$1:$H$73, 2, FALSE) -> Cartessa Aesthetics LLC | K17: Cartessa | L17: Cartessa | M17: =VLOOKUP(J17, $D$4:$E$78, 2, FALSE) -> 5205875.1 | N17: =VLOOKUP(K17, 'Loan List '!$A$6:$H$82, 8, FALSE) -> 5205875 | O17: =VLOOKUP(I17, Sheet2!$A$1:$D$78, 4, FALSE) -> 5205875 | P17: =N17-O17 -> 0 | Q17: =VLOOKUP(I17, Sheet2!$A$1:$E$78, 5, FALSE) -> 0.100492 | R17: =VLOOKUP($L17, '[3]BNP Borrowing Base PSLF JV (PIF'!$A$8:$AI$181, 11, FALSE) -> 0.06 | S17: =VLOOKUP($L17, '[3]BNP Borrowing Base PSLF JV (PIF'!$A$8:$AI$181, 20, FALSE) -> 45716 | T17: =VLOOKUP($L17, '[3]BNP Borrowing Base PSLF JV (PIF'!$A$8:$AI$181, 22, FALSE) -> 3.2680581 | U17: =VLOOKUP($L17, '[3]BNP Borrowing Base PSLF JV (PIF'!$A$8:$AI$181, 23, FALSE) -> 19.711492 | V17: =VLOOKUP($L17, '[3]BNP Borrowing Base PSLF JV (PIF'!$A$8:$AI$181, 32, FALSE) -> 3.2680581 | W17: =VLOOKUP($L17, '[3]BNP Borrowing Base PSLF JV (PIF'!$A$8:$AI$181, 34, FALSE) -> 2.5267405
A18: C5MI Acquisition LLC | B18: 1492500 | D18: C5MI Acquisition LLC | E18: 1492500 | F18: =VLOOKUP(D18, $J$4:$K$79, 2, FALSE) -> C5MI Acquisition, LLC | I18: Case Works, LLC | J18: =+VLOOKUP(K18,'[2]Sheet2 (2)'!$G$1:$H$73, 2, FALSE) -> Case Works LLC | K18: Case Works | L18: Case Works | M18: =VLOOKUP(J18, $D$4:$E$78, 2, FALSE) -> 4503279.2 | N18: =VLOOKUP(K18, 'Loan List '!$A$6:$H$82, 8, FALSE) -> 4503279.2 | O18: =VLOOKUP(I18, Sheet2!$A$1:$D$78, 4, FALSE) -> 4503279.2 | P18: =N18-O18 -> 0 | Q18: =VLOOKUP(I18, Sheet2!$A$1:$E$78, 5, FALSE) -> 0.095492 | R18: =VLOOKUP($L18, '[3]BNP Borrowing Base PSLF JV (PIF'!$A$8:$AI$181, 11, FALSE) -> 0.0525 | S18: =VLOOKUP($L18, '[3]BNP Borrowing Base PSLF JV (PIF'!$A$8:$AI$181, 20, FALSE) -> 45716 | T18: =VLOOKUP($L18, '[3]BNP Borrowing Base PSLF JV (PIF'!$A$8:$AI$181, 22, FALSE) -> 4.3945971 | U18: =VLOOKUP($L18, '[3]BNP Borrowing Base PSLF JV (PIF'!$A$8:$AI$181, 23, FALSE) -> 19.945156 | V18: =VLOOKUP($L18, '[3]BNP Borrowing Base PSLF JV (PIF'!$A$8:$AI$181, 32, FALSE) -> 4.3945971 | W18: =VLOOKUP($L18, '[3]BNP Borrowing Base PSLF JV (PIF'!$A$8:$AI$181, 34, FALSE) -> 1.579057
... A21: Cartessa Aesthetics LLC | B21: 5205875.1 | D21: Cartessa Aesthetics LLC | E21: 5205875.1 | F21: =VLOOKUP(D21, $J$4:$K$79, 2, FALSE) -> Cartessa | I21: Crane 1 Services, Inc. | J21: =+VLOOKUP(K21,'[2]Sheet2 (2)'!$G$1:$H$73, 2, FALSE) -> Crane 1 Acquisition Holdings Inc | K21: Crane 1 Services, Inc. | L21: Crane 1 Services, Inc. | M21: =VLOOKUP(J21, $D$4:$E$78, 2, FALSE) -> 995000 | N21: =VLOOKUP(K21, 'Loan List '!$A$6:$H$82, 8, FALSE) -> 995000 | O21: =VLOOKUP(I21, Sheet2!$A$1:$D$78, 4, FALSE) -> 995000 | P21: =N21-O21 -> 0 | Q21: =VLOOKUP(I21, Sheet2!$A$1:$E$78, 5, FALSE) -> 0.097571256 | R21: =VLOOKUP($L21, '[3]BNP Borrowing Base PSLF JV (PIF'!$A$8:$AI$181, 11, FALSE) -> 0.0575 | S21: =VLOOKUP($L21, '[3]BNP Borrowing Base PSLF JV (PIF'!$A$8:$AI$181, 20, FALSE) -> 45747 | T21: =VLOOKUP($L21, '[3]BNP Borrowing Base PSLF JV (PIF'!$A$8:$AI$181, 22, FALSE) -> 4.9018235 | U21: =VLOOKUP($L21, '[3]BNP Borrowing Base PSLF JV (PIF'!$A$8:$AI$181, 23, FALSE) -> 27.858 | V21: =VLOOKUP($L21, '[3]BNP Borrowing Base PSLF JV (PIF'!$A$8:$AI$181, 32, FALSE) -> 4.9018235 | W21: =VLOOKUP($L21, '[3]BNP Borrowing Base PSLF JV (PIF'!$A$8:$AI$181, 34, FALSE) -> 2.1485423
A22: Case Works LLC | B22: 4503279.2 | D22: Case Works LLC | E22: 4503279.2 | F22: =VLOOKUP(D22, $J$4:$K$79, 2, FALSE) -> Case Works | I22: Dr. Squatch, LLC | J22: =+VLOOKUP(K22,'[2]Sheet2 (2)'!$G$1:$H$73, 2, FALSE) -> Dr. Squatch LLC | K22: Dr. Squatch, LLC | L22: Dr. Squatch, LLC | M22: =VLOOKUP(J22, $D$4:$E$78, 2, FALSE) -> 14433540 | N22: =O22 -> 14433540 | O22: =VLOOKUP(I22, Sheet2!$A$1:$D$78, 4, FALSE) -> 14433540 | P22: =N22-O22 -> 0 | Q22: =VLOOKUP(I22, Sheet2!$A$1:$E$78, 5, FALSE) -> 0.10103333 | R22: =VLOOKUP($L22, '[3]BNP Borrowing Base PSLF JV (PIF'!$A$8:$AI$181, 11, FALSE) -> 0.0525 | S22: =VLOOKUP($L22, '[3]BNP Borrowing Base PSLF JV (PIF'!$A$8:$AI$181, 20, FALSE) -> 45657 | T22: =VLOOKUP($L22, '[3]BNP Borrowing Base PSLF JV (PIF'!$A$8:$AI$181, 22, FALSE) -> 1.2974759 | U22: =VLOOKUP($L22, '[3]BNP Borrowing Base PSLF JV (PIF'!$A$8:$AI$181, 23, FALSE) -> 96.404406 | V22: =VLOOKUP($L22, '[3]BNP Borrowing Base PSLF JV (PIF'!$A$8:$AI$181, 32, FALSE) -> 1.2974759 | W22: =VLOOKUP($L22, '[3]BNP Borrowing Base PSLF JV (PIF'!$A$8:$AI$181, 34, FALSE) -> 6.1659888
A23: CF512 Inc | B23: 6298498.8 | D23: CF512 Inc | E23: 6298498.8 | F23: =VLOOKUP(D23, $J$4:$K$79, 2, FALSE) -> CF512, Inc. | I23: EDS Buyer, LLC | J23: =+VLOOKUP(K23,'[2]Sheet2 (2)'!$G$1:$H$73, 2, FALSE) -> EDS Buyer LLC | K23: EDS Buyers, LLC | L23: EDS Buyers, LLC | M23: =VLOOKUP(J23, $D$4:$E$78, 2, FALSE) -> 5452662.2 | N23: =O23 -> 5452661.1 | O23: =VLOOKUP(I23, Sheet2!$A$1:$D$78, 4, FALSE) -> 5452661.1 | P23: =N23-O23 -> 0 | Q23: =VLOOKUP(I23, Sheet2!$A$1:$E$78, 5, FALSE) -> 0.099475564 | R23: =VLOOKUP($L23, '[3]BNP Borrowing Base PSLF JV (PIF'!$A$8:$AI$181, 11, FALSE) -> 0.0575 | S23: =VLOOKUP($L23, '[3]BNP Borrowing Base PSLF JV (PIF'!$A$8:$AI$181, 20, FALSE) -> 45716 | T23: =VLOOKUP($L23, '[3]BNP Borrowing Base PSLF JV (PIF'!$A$8:$AI$181, 22, FALSE) -> 3.1697908 | U23: =VLOOKUP($L23, '[3]BNP Borrowing Base PSLF JV (PIF'!$A$8:$AI$181, 23, FALSE) -> 26.727 | V23: =VLOOKUP($L23, '[3]BNP Borrowing Base PSLF JV (PIF'!$A$8:$AI$181, 32, FALSE) -> 3.1697908 | W23: =VLOOKUP($L23, '[3]BNP Borrowing Base PSLF JV (PIF'!$A$8:$AI$181, 34, FALSE) -> 2.3344397
A24: Crane 1 Acquisition Holdings Inc | B24: 995000 | D24: Crane 1 Acquisition Holdings Inc | E24: 995000 | F24: =VLOOKUP(D24, $J$4:$K$79, 2, FALSE) -> Crane 1 Services, Inc. | I24: Eval Home Health Solutions Intermediate, LLC | J24: =+VLOOKUP(K24,'[2]Sheet2 (2)'!$G$1:$H$73, 2, FALSE) -> Eval Home Health Solutions Intermediate LLC | K24: Eval Home Health Solutions Intermediate, LLC | L24: Eval | M24: =VLOOKUP(J24, $D$4:$E$78, 2, FALSE) -> 1362351.4 | N24: =VLOOKUP(K24, 'Loan List '!$A$6:$H$82, 8, FALSE) -> 1362351.4 | O24: =VLOOKUP(I24, Sheet2!$A$1:$D$78, 4, FALSE) -> 1362351.4 | P24: =N24-O24 -> 0 | Q24: =VLOOKUP(I24, Sheet2!$A$1:$E$78, 5, FALSE) -> 0.096512477 | R24: =VLOOKUP($L24, '[3]BNP Borrowing Base PSLF JV (PIF'!$A$8:$AI$181, 11, FALSE) -> 0.0575 | S24: =VLOOKUP($L24, '[3]BNP Borrowing Base PSLF JV (PIF'!$A$8:$AI$181, 20, FALSE) -> 45747 | T24: =VLOOKUP($L24, '[3]BNP Borrowing Base PSLF JV (PIF'!$A$8:$AI$181, 22, FALSE) -> 3.6690952 | U24: =VLOOKUP($L24, '[3]BNP Borrowing Base PSLF JV (PIF'!$A$8:$AI$181, 23, FALSE) -> 12.975206 | V24: =VLOOKUP($L24, '[3]BNP Borrowing Base PSLF JV (PIF'!$A$8:$AI$181, 32, FALSE) -> 3.6690952 | W24: =VLOOKUP($L24, '[3]BNP Borrowing Base PSLF JV (PIF'!$A$8:$AI$181, 34, FALSE) -> 2.5409656
A25: Dr. Squatch LLC | B25: 14433540 | D25: Dr. Squatch LLC | E25: 14433540 | F25: =VLOOKUP(D25, $J$4:$K$79, 2, FALSE) -> Dr. Squatch, LLC | I25: GGG Midco, LLC | J25: =+VLOOKUP(K25,'[2]Sheet2 (2)'!$G$1:$H$73, 2, FALSE) -> GGG Midco LLC | K25: GGG Midco, LLC | L25: GGG Midco, LLC | M25: =VLOOKUP(J25, $D$4:$E$78, 2, FALSE) -> 6578437.8 | N25: =VLOOKUP(K25, 'Loan List '!$A$6:$H$82, 8, FALSE) -> 6578437.8 | O25: =VLOOKUP(I25, Sheet2!$A$1:$D$78, 4, FALSE) -> 6578437.8 | P25: =N25-O25 -> 0 | Q25: =VLOOKUP(I25, Sheet2!$A$1:$E$78, 5, FALSE) -> 0.091839322 | R25: =VLOOKUP($L25, '[3]BNP Borrowing Base PSLF JV (PIF'!$A$8:$AI$181, 11, FALSE) -> 0.05 | S25: =VLOOKUP($L25, '[3]BNP Borrowing Base PSLF JV (PIF'!$A$8:$AI$181, 20, FALSE) -> 45716 | T25: =VLOOKUP($L25, '[3]BNP Borrowing Base PSLF JV (PIF'!$A$8:$AI$181, 22, FALSE) -> 3.5049196 | U25: =VLOOKUP($L25, '[3]BNP Borrowing Base PSLF JV (PIF'!$A$8:$AI$181, 23, FALSE) -> 19.61 | V25: =VLOOKUP($L25, '[3]BNP Borrowing Base PSLF JV (PIF'!$A$8:$AI$181, 32, FALSE) -> 3.8720792 | W25: =VLOOKUP($L25, '[3]BNP Borrowing Base PSLF JV (PIF'!$A$8:$AI$181, 34, FALSE) -> 2.7619718
A26: EDS Buyer LLC | B26: 5452662.2 | D26: EDS Buyer LLC | E26: 5452662.2 | F26: =VLOOKUP(D26, $J$4:$K$79, 2, FALSE) -> EDS Buyers, LLC | I26: HEC Purchaser Corp. | J26: =+VLOOKUP(K26,'[2]Sheet2 (2)'!$G$1:$H$73, 2, FALSE) -> HEC Purchaser Corp. | K26: HEC Purchaser Corp. | L26: Health-E Commerce | M26: =VLOOKUP(J26, $D$4:$E$78, 2, FALSE) -> 1970075.2 | N26: =VLOOKUP(K26, 'Loan List '!$A$6:$H$82, 8, FALSE) -> 1970075.2 | O26: =VLOOKUP(I26, Sheet2!$A$1:$D$78, 4, FALSE) -> 1970075.2 | P26: =N26-O26 -> 0 | Q26: =VLOOKUP(I26, Sheet2!$A$1:$E$78, 5, FALSE) -> 0.094027654 | R26: =VLOOKUP($L26, '[3]BNP Borrowing Base PSLF JV (PIF'!$A$8:$AI$181, 11, FALSE) -> 0.055 | S26: =VLOOKUP($L26, '[3]BNP Borrowing Base PSLF JV (PIF'!$A$8:$AI$181, 20, FALSE) -> 45716 | T26: =VLOOKUP($L26, '[3]BNP Borrowing Base PSLF JV (PIF'!$A$8:$AI$181, 22, FALSE) -> 3.9063922 | U26: =VLOOKUP($L26, '[3]BNP Borrowing Base PSLF JV (PIF'!$A$8:$AI$181, 23, FALSE) -> 58.283953 | V26: =VLOOKUP($L26, '[3]BNP Borrowing Base PSLF JV (PIF'!$A$8:$AI$181, 32, FALSE) -> 3.9063922 | W26: =VLOOKUP($L26, '[3]BNP Borrowing Base PSLF JV (PIF'!$A$8:$AI$181, 34, FALSE) -> 2.2577367
A27: Emergency Care Partners LLC | B27: 995000 | D27: Emergency Care Partners LLC | E27: 995000 | F27: =VLOOKUP(D27, $J$4:$K$79, 2, FALSE) -> Emergency Care Partners LLC | I27: Harris & Co. LLC | J27: =+VLOOKUP(K27,'[2]Sheet2 (2)'!$G$1:$H$73, 2, FALSE) -> Harris & Co. LLC | K27: Harris & Co. LLC | L27: Harris & Co. | M27: =VLOOKUP(J27, $D$4:$E$78, 2, FALSE) -> 8726327.5 | N27: =VLOOKUP(K27, 'Loan List '!$A$6:$H$82, 8, FALSE) -> 8726327.5 | O27: =VLOOKUP(I27, Sheet2!$A$1:$D$78, 4, FALSE) -> 8726327.5 | P27: =N27-O27 -> 0 | Q27: =VLOOKUP(I27, Sheet2!$A$1:$E$78, 5, FALSE) -> 0.091722796 | R27: =VLOOKUP($L27, '[3]BNP Borrowing Base PSLF JV (PIF'!$A$8:$AI$181, 11, FALSE) -> 0.05 | S27: =VLOOKUP($L27, '[3]BNP Borrowing Base PSLF JV (PIF'!$A$8:$AI$181, 20, FALSE) -> 45747 | T27: =VLOOKUP($L27, '[3]BNP Borrowing Base PSLF JV (PIF'!$A$8:$AI$181, 22, FALSE) -> 3.6245035 | U27: =VLOOKUP($L27, '[3]BNP Borrowing Base PSLF JV (PIF'!$A$8:$AI$181, 23, FALSE) -> 30.461 | V27: =VLOOKUP($L27, '[3]BNP Borrowing Base PSLF JV (PIF'!$A$8:$AI$181, 32, FALSE) -> 3.6245035 | W27: =VLOOKUP($L27, '[3]BNP Borrowing Base PSLF JV (PIF'!$A$8:$AI$181, 34, FALSE) -> 5.3721683
A28: Eval Home Health Solutions Intermediate LLC | B28: 1362351.4 | D28: Eval Home Health Solutions Intermediate LLC | E28: 1362351.4 | F28: =VLOOKUP(D28, $J$4:$K$79, 2, FALSE) -> Eval Home Health Solutions Intermediate, LLC | I28: HW Holdco, LLC | J28: =+VLOOKUP(K28,'[2]Sheet2 (2)'!$G$1:$H$73, 2, FALSE) -> HW Holdco LLC | K28: HW Holdco, LLC | L28: HW Holdco, LLC | M28: =VLOOKUP(J28, $D$4:$E$78, 2, FALSE) -> 7618243.3 | N28: =VLOOKUP(K28, 'Loan List '!$A$6:$H$82, 8, FALSE) -> 7618243.4 | O28: =VLOOKUP(I28, Sheet2!$A$1:$D$78, 4, FALSE) -> 7618243.4 | P28: =N28-O28 -> 0 | Q28: =VLOOKUP(I28, Sheet2!$A$1:$E$78, 5, FALSE) -> 0.10147808 | R28: =VLOOKUP($L28, '[3]BNP Borrowing Base PSLF JV (PIF'!$A$8:$AI$181, 11, FALSE) -> 0.05 | S28: =VLOOKUP($L28, '[3]BNP Borrowing Base PSLF JV (PIF'!$A$8:$AI$181, 20, FALSE) -> 45716 | T28: =VLOOKUP($L28, '[3]BNP Borrowing Base PSLF JV (PIF'!$A$8:$AI$181, 22, FALSE) -> 3.0055762 | U28: =VLOOKUP($L28, '[3]BNP Borrowing Base PSLF JV (PIF'!$A$8:$AI$181, 23, FALSE) -> 58.463 | V28: =VLOOKUP($L28, '[3]BNP Borrowing Base PSLF JV (PIF'!$A$8:$AI$181, 32, FALSE) -> 3.0055762 | W28: =VLOOKUP($L28, '[3]BNP Borrowing Base PSLF JV (PIF'!$A$8:$AI$181, 34, FALSE) -> 2.5529694
A29: GGG Midco LLC | B29: 6578437.8 | D29: GGG Midco LLC | E29: 6578437.8 | F29: =VLOOKUP(D29, $J$4:$K$79, 2, FALSE) -> GGG Midco, LLC | I29: Infinity Home Services Holdco, Inc. | J29: =+VLOOKUP(K29,'[2]Sheet2 (2)'!$G$1:$H$73, 2, FALSE) -> Infinity Home Services Holdco Inc | K29: Infinity Home Services Holdco, Inc. | L29: Infinity Home Services Holdco, Inc. | M29: =VLOOKUP(J29, $D$4:$E$78, 2, FALSE) -> 5118399.2 | N29: =VLOOKUP(K29, 'Loan List '!$A$6:$H$82, 8, FALSE) -> 5118399.2 | O29: =VLOOKUP(I29, Sheet2!$A$1:$D$78, 4, FALSE) -> 5118399.2 | P29: =N29-O29 -> 0 | Q29: =VLOOKUP(I29, Sheet2!$A$1:$E$78, 5, FALSE) -> 0.097992 | R29: =VLOOKUP($L29, '[3]BNP Borrowing Base PSLF JV (PIF'!$A$8:$AI$181, 11, FALSE) -> 0.0675 | S29: =VLOOKUP($L29, '[3]BNP Borrowing Base PSLF JV (PIF'!$A$8:$AI$181, 20, FALSE) -> 45716 | T29: =VLOOKUP($L29, '[3]BNP Borrowing Base PSLF JV (PIF'!$A$8:$AI$181, 22, FALSE) -> 5.1442629 | U29: =VLOOKUP($L29, '[3]BNP Borrowing Base PSLF JV (PIF'!$A$8:$AI$181, 23, FALSE) -> 63.211 | V29: =VLOOKUP($L29, '[3]BNP Borrowing Base PSLF JV (PIF'!$A$8:$AI$181, 32, FALSE) -> 5.1442629 | W29: =VLOOKUP($L29, '[3]BNP Borrowing Base PSLF JV (PIF'!$A$8:$AI$181, 34, FALSE) -> 2.0660565
A30: Harris & Co. LLC | B30: 8726327.5 | D30: Harris & Co. LLC | E30: 8726327.5 | F30: =VLOOKUP(D30, $J$4:$K$79, 2, FALSE) -> Harris & Co. LLC | I30: Infolinks Media Buyco, LLC | J30: =+VLOOKUP(K30,'[2]Sheet2 (2)'!$G$1:$H$73, 2, FALSE) -> Infolinks Media Buyco LLC | K30: Infolinks | L30: Infolinks | M30: =VLOOKUP(J30, $D$4:$E$78, 2, FALSE) -> 2051982.1 | N30: =VLOOKUP(K30, 'Loan List '!$A$6:$H$82, 8, FALSE) -> 2051982.1 | O30: =VLOOKUP(I30, Sheet2!$A$1:$D$78, 4, FALSE) -> 2051982.1 | P30: =N30-O30 -> 0 | Q30: =VLOOKUP(I30, Sheet2!$A$1:$E$78, 5, FALSE) -> 0.097619943 | R30: =VLOOKUP($L30, '[3]BNP Borrowing Base PSLF JV (PIF'!$A$8:$AI$181, 11, FALSE) -> 0.055 | S30: =VLOOKUP($L30, '[3]BNP Borrowing Base PSLF JV (PIF'!$A$8:$AI$181, 20, FALSE) -> 45716 | T30: =VLOOKUP($L30, '[3]BNP Borrowing Base PSLF JV (PIF'!$A$8:$AI$181, 22, FALSE) -> 3.2535092 | U30: =VLOOKUP($L30, '[3]BNP Borrowing Base PSLF JV (PIF'!$A$8:$AI$181, 23, FALSE) -> 49.399276 | V30: =VLOOKUP($L30, '[3]BNP Borrowing Base PSLF JV (PIF'!$A$8:$AI$181, 32, FALSE) -> 3.2535092 | W30: =VLOOKUP($L30, '[3]BNP Borrowing Base PSLF JV (PIF'!$A$8:$AI$181, 34, FALSE) -> 3.0077525
A31: HEC Purchaser Corp. | B31: 1970075.2 | D31: HEC Purchaser Corp. | E31: 1970075.2 | F31: =VLOOKUP(D31, $J$4:$K$79, 2, FALSE) -> HEC Purchaser Corp. | I31: Inventus Power, Inc. | J31: =+VLOOKUP(K31,'[2]Sheet2 (2)'!$G$1:$H$73, 2, FALSE) -> Inventus Power Inc | K31: Inventus Power Inc. | L31: Inventus Power Inc. | M31: =VLOOKUP(J31, $D$4:$E$78, 2, FALSE) -> 1975484.5 | N31: =VLOOKUP(K31, 'Loan List '!$A$6:$H$82, 8, FALSE) -> 1975484.5 | O31: =VLOOKUP(I31, Sheet2!$A$1:$D$78, 4, FALSE) -> 1975484.5 | P31: =N31-O31 -> 0 | Q31: =VLOOKUP(I31, Sheet2!$A$1:$E$78, 5, FALSE) -> 0.119394 | R31: =VLOOKUP($L31, '[3]BNP Borrowing Base PSLF JV (PIF'!$A$8:$AI$181, 11, FALSE) -> 0.075 | S31: =VLOOKUP($L31, '[3]BNP Borrowing Base PSLF JV (PIF'!$A$8:$AI$181, 20, FALSE) -> 45716 | T31: =VLOOKUP($L31, '[3]BNP Borrowing Base PSLF JV (PIF'!$A$8:$AI$181, 22, FALSE) -> 4.9069445 | U31: =VLOOKUP($L31, '[3]BNP Borrowing Base PSLF JV (PIF'!$A$8:$AI$181, 23, FALSE) -> 51.788 | V31: =VLOOKUP($L31, '[3]BNP Borrowing Base PSLF JV (PIF'!$A$8:$AI$181, 32, FALSE) -> 4.9069445 | W31: =VLOOKUP($L31, '[3]BNP Borrowing Base PSLF JV (PIF'!$A$8:$AI$181, 34, FALSE) -> 1.4563555
A32: HV Watterson Holdings LLC | B32: 9328396.7 | D32: HV Watterson Holdings LLC | E32: 9328396.7 | F32: =VLOOKUP(D32, $J$4:$K$79, 2, FALSE) -> Watterson | I32: Lash OpCo, LLC | J32: =+VLOOKUP(K32,'[2]Sheet2 (2)'!$G$1:$H$73, 2, FALSE) -> Lash OpCo LLC | K32: Lash OpCo, LLC | L32: Lash OpCo, LLC | M32: =VLOOKUP(J32, $D$4:$E$78, 2, FALSE) -> 3328030.8 | N32: =VLOOKUP(K32, 'Loan List '!$A$6:$H$82, 8, FALSE) -> 3328030.9 | O32: =VLOOKUP(I32, Sheet2!$A$1:$D$78, 4, FALSE) -> 3328030.9 | P32: =N32-O32 -> 0 | Q32: =VLOOKUP(I32, Sheet2!$A$1:$E$78, 5, FALSE) -> 0.11582122 | R32: =VLOOKUP($L32, '[3]BNP Borrowing Base PSLF JV (PIF'!$A$8:$AI$181, 11, FALSE) -> 0.07 | S32: =VLOOKUP($L32, '[3]BNP Borrowing Base PSLF JV (PIF'!$A$8:$AI$181, 20, FALSE) -> 45716 | T32: =VLOOKUP($L32, '[3]BNP Borrowing Base PSLF JV (PIF'!$A$8:$AI$181, 22, FALSE) -> 8.2594418 | U32: =VLOOKUP($L32, '[3]BNP Borrowing Base PSLF JV (PIF'!$A$8:$AI$181, 23, FALSE) -> 60.446582 | V32: =VLOOKUP($L32, '[3]BNP Borrowing Base PSLF JV (PIF'!$A$8:$AI$181, 32, FALSE) -> 8.2594418 | W32: =VLOOKUP($L32, '[3]BNP Borrowing Base PSLF JV (PIF'!$A$8:$AI$181, 34, FALSE) -> 0.91660285
A33: HW Holdco LLC | B33: 7618243.3 | D33: HW Holdco LLC | E33: 7618243.3 | F33: =VLOOKUP(D33, $J$4:$K$79, 2, FALSE) -> HW Holdco, LLC | I33: MDI Buyer Inc. | J33: =+VLOOKUP(K33,'[2]Sheet2 (2)'!$G$1:$H$73, 2, FALSE) -> MDI Buyer Inc | K33: MDI Buyer Inc. | L33: Molded Devices | M33: =VLOOKUP(J33, $D$4:$E$78, 2, FALSE) -> 4792248.3 | N33: =VLOOKUP(K33, 'Loan List '!$A$6:$H$82, 8, FALSE) -> 4792248.3 | O33: =VLOOKUP(I33, Sheet2!$A$1:$D$78, 4, FALSE) -> 4792248.3 | P33: =N33-O33 -> 0 | Q33: =VLOOKUP(I33, Sheet2!$A$1:$E$78, 5, FALSE) -> 0.10117766 | R33: =VLOOKUP($L33, '[3]BNP Borrowing Base PSLF JV (PIF'!$A$8:$AI$181, 11, FALSE) -> 0.06 | S33: =VLOOKUP($L33, '[3]BNP Borrowing Base PSLF JV (PIF'!$A$8:$AI$181, 20, FALSE) -> 45716 | T33: =VLOOKUP($L33, '[3]BNP Borrowing Base PSLF JV (PIF'!$A$8:$AI$181, 22, FALSE) -> 5.1521667 | U33: =VLOOKUP($L33, '[3]BNP Borrowing Base PSLF JV (PIF'!$A$8:$AI$181, 23, FALSE) -> 34.693125 | V33: =VLOOKUP($L33, '[3]BNP Borrowing Base PSLF JV (PIF'!$A$8:$AI$181, 32, FALSE) -> 6.689848 | W33: =VLOOKUP($L33, '[3]BNP Borrowing Base PSLF JV (PIF'!$A$8:$AI$181, 34, FALSE) -> 2.33
A34: Infinity Home Services Holdco Inc | B34: 5118399.2 | D34: Infinity Home Services Holdco Inc | E34: 5118399.2 | F34: =VLOOKUP(D34, $J$4:$K$79, 2, FALSE) -> Infinity Home Services Holdco, Inc. | I34: Megawatt Acquisitionco, Inc. | J34: =+VLOOKUP(K34,'[2]Sheet2 (2)'!$G$1:$H$73, 2, FALSE) -> Megawatt Acquisitionco Inc | K34: Megawatt Acquisitionco, Inc. | L34: Megawatt Acquisitionco, Inc. | M34: =VLOOKUP(J34, $D$4:$E$78, 2, FALSE) -> 4942556.4 | N34: =VLOOKUP(K34, 'Loan List '!$A$6:$H$82, 8, FALSE) -> 4942556.4 | O34: =VLOOKUP(I34, Sheet2!$A$1:$D$78, 4, FALSE) -> 4942556.4 | P34: =N34-O34 -> 0 | Q34: =VLOOKUP(I34, Sheet2!$A$1:$E$78, 5, FALSE) -> 0.097992 | R34: =VLOOKUP($L34, '[3]BNP Borrowing Base PSLF JV (PIF'!$A$8:$AI$181, 11, FALSE) -> 0.0525 | S34: =VLOOKUP($L34, '[3]BNP Borrowing Base PSLF JV (PIF'!$A$8:$AI$181, 20, FALSE) -> 45716 | T34: =VLOOKUP($L34, '[3]BNP Borrowing Base PSLF JV (PIF'!$A$8:$AI$181, 22, FALSE) -> 7.1829156 | U34: =VLOOKUP($L34, '[3]BNP Borrowing Base PSLF JV (PIF'!$A$8:$AI$181, 23, FALSE) -> 19.55 | V34: =VLOOKUP($L34, '[3]BNP Borrowing Base PSLF JV (PIF'!$A$8:$AI$181, 32, FALSE) -> 7.1829156 | W34: =VLOOKUP($L34, '[3]BNP Borrowing Base PSLF JV (PIF'!$A$8:$AI$181, 34, FALSE) -> 1.2849162
A35: Infolinks Media Buyco LLC | B35: 2051982.1 | D35: Infolinks Media Buyco LLC | E35: 2051982.1 | F35: =VLOOKUP(D35, $J$4:$K$79, 2, FALSE) -> Infolinks | I35: Michael Baker International, LLC | J35: =+VLOOKUP(K35,'[2]Sheet2 (2)'!$G$1:$H$73, 2, FALSE) -> Michael Baker International LLC | K35: Michael Baker International, LLC | L35: Michael Baker | M35: =VLOOKUP(J35, $D$4:$E$78, 2, FALSE) -> 497493.74 | N35: =VLOOKUP(K35, 'Loan List '!$A$6:$H$82, 8, FALSE) -> 497493.74 | O35: =VLOOKUP(I35, Sheet2!$A$1:$D$78, 4, FALSE) -> 497493.74 | P35: =N35-O35 -> 0 | Q35: =VLOOKUP(I35, Sheet2!$A$1:$E$78, 5, FALSE) -> 0.083249 | R35: =VLOOKUP($L35, '[3]BNP Borrowing Base PSLF JV (PIF'!$A$8:$AI$181, 11, FALSE) -> 0.0475 | S35: =VLOOKUP($L35, '[3]BNP Borrowing Base PSLF JV (PIF'!$A$8:$AI$181, 20, FALSE) -> 45657 | T35: =VLOOKUP($L35, '[3]BNP Borrowing Base PSLF JV (PIF'!$A$8:$AI$181, 22, FALSE) -> 3.7058168 | U35: =VLOOKUP($L35, '[3]BNP Borrowing Base PSLF JV (PIF'!$A$8:$AI$181, 23, FALSE) -> 175.112 | V35: =VLOOKUP($L35, '[3]BNP Borrowing Base PSLF JV (PIF'!$A$8:$AI$181, 32, FALSE) -> 3.7058168 | W35: =VLOOKUP($L35, '[3]BNP Borrowing Base PSLF JV (PIF'!$A$8:$AI$181, 34, FALSE) -> 3.0605425
... A42: MDI Buyer Inc | B42: 4792248.3 | D42: MDI Buyer Inc | E42: 4792248.3 | F42: =VLOOKUP(D42, $J$4:$K$79, 2, FALSE) -> MDI Buyer Inc. | I42: PL Acquisitionco, LLC | J42: =+VLOOKUP(K42,'[2]Sheet2 (2)'!$G$1:$H$73, 2, FALSE) -> Pink Lily Holdings LLC | K42: PL Acquisitionco, LLC | L42: PL Acquisitionco, LLC | M42: =VLOOKUP(J42, $D$4:$E$78, 2, FALSE) -> 8459233 | N42: =VLOOKUP(K42, 'Loan List '!$A$6:$H$82, 8, FALSE) -> 8459233 | O42: =VLOOKUP(I42, Sheet2!$A$1:$D$78, 4, FALSE) -> 8459233 | P42: =N42-O42 -> 0 | Q42: =VLOOKUP(I42, Sheet2!$A$1:$E$78, 5, FALSE) -> 0.115016 | R42: =VLOOKUP($L42, '[3]BNP Borrowing Base PSLF JV (PIF'!$A$8:$AI$181, 11, FALSE) -> 0.065 | S42: =VLOOKUP($L42, '[3]BNP Borrowing Base PSLF JV (PIF'!$A$8:$AI$181, 20, FALSE) -> 45716 | T42: =VLOOKUP($L42, '[3]BNP Borrowing Base PSLF JV (PIF'!$A$8:$AI$181, 22, FALSE) -> NM | U42: =VLOOKUP($L42, '[3]BNP Borrowing Base PSLF JV (PIF'!$A$8:$AI$181, 23, FALSE) -> -3.648616 | V42: =VLOOKUP($L42, '[3]BNP Borrowing Base PSLF JV (PIF'!$A$8:$AI$181, 32, FALSE) -> -18.2598 | W42: =VLOOKUP($L42, '[3]BNP Borrowing Base PSLF JV (PIF'!$A$8:$AI$181, 34, FALSE) -> -0.39253534
A43: Medina Health LLC | B43: 3780604.5 | D43: Medina Health LLC | E43: 3780604.5 | F43: =VLOOKUP(D43, $J$4:$K$79, 2, FALSE) -> Comprehensive Rehab Consultants | I43: Radius Aerospace, Inc. | J43: =+VLOOKUP(K43,'[2]Sheet2 (2)'!$G$1:$H$73, 2, FALSE) -> Radius Aerospace Inc | K43: Radius Aerospace | L43: Radius Aerospace | M43: =VLOOKUP(J43, $D$4:$E$78, 2, FALSE) -> 11840921 | N43: =O43 -> 11840920 | O43: =VLOOKUP(I43, Sheet2!$A$1:$D$78, 4, FALSE) -> 11840920 | P43: =N43-O43 -> 0 | Q43: =VLOOKUP(I43, Sheet2!$A$1:$E$78, 5, FALSE) -> 0.1047878 | R43: =VLOOKUP($L43, '[3]BNP Borrowing Base PSLF JV (PIF'!$A$8:$AI$181, 11, FALSE) -> 0.0575 | S43: =VLOOKUP($L43, '[3]BNP Borrowing Base PSLF JV (PIF'!$A$8:$AI$181, 20, FALSE) -> 45747 | T43: =VLOOKUP($L43, '[3]BNP Borrowing Base PSLF JV (PIF'!$A$8:$AI$181, 22, FALSE) -> 5.4995528 | U43: =VLOOKUP($L43, '[3]BNP Borrowing Base PSLF JV (PIF'!$A$8:$AI$181, 23, FALSE) -> 23.997 | V43: =VLOOKUP($L43, '[3]BNP Borrowing Base PSLF JV (PIF'!$A$8:$AI$181, 32, FALSE) -> 5.4995528 | W43: =VLOOKUP($L43, '[3]BNP Borrowing Base PSLF JV (PIF'!$A$8:$AI$181, 34, FALSE) -> 1.3285169
A44: Megawatt Acquisitionco Inc | B44: 4942556.4 | D44: Megawatt Acquisitionco Inc | E44: 4942556.4 | F44: =VLOOKUP(D44, $J$4:$K$79, 2, FALSE) -> Megawatt Acquisitionco, Inc. | I44: Rancho Health MSO, Inc. | J44: =+VLOOKUP(K44,'[2]Sheet2 (2)'!$G$1:$H$73, 2, FALSE) -> Rancho Health MSO Inc | K44: Rancho Medical | L44: Rancho Medical | M44: =VLOOKUP(J44, $D$4:$E$78, 2, FALSE) -> 17282079 | N44: =O44 -> 17282079 | O44: =VLOOKUP(I44, Sheet2!$A$1:$D$78, 4, FALSE) -> 17282079 | P44: =N44-O44 -> 0 | Q44: =VLOOKUP(I44, Sheet2!$A$1:$E$78, 5, FALSE) -> 0.095673121 | R44: =VLOOKUP($L44, '[3]BNP Borrowing Base PSLF JV (PIF'!$A$8:$AI$181, 11, FALSE) -> 0.0575 | S44: =VLOOKUP($L44, '[3]BNP Borrowing Base PSLF JV (PIF'!$A$8:$AI$181, 20, FALSE) -> 45716 | T44: =VLOOKUP($L44, '[3]BNP Borrowing Base PSLF JV (PIF'!$A$8:$AI$181, 22, FALSE) -> 3.402692 | U44: =VLOOKUP($L44, '[3]BNP Borrowing Base PSLF JV (PIF'!$A$8:$AI$181, 23, FALSE) -> 18.840077 | V44: =VLOOKUP($L44, '[3]BNP Borrowing Base PSLF JV (PIF'!$A$8:$AI$181, 32, FALSE) -> 3.402692 | W44: =VLOOKUP($L44, '[3]BNP Borrowing Base PSLF JV (PIF'!$A$8:$AI$181, 34, FALSE) -> 2.364428
A45: Michael Baker International LLC | B45: 497493.74 | D45: Michael Baker International LLC | E45: 497493.74 | F45: =VLOOKUP(D45, $J$4:$K$79, 2, FALSE) -> Michael Baker International, LLC | I45: STG Distribution, LLC (fka Reception Purchaser) - First Out New Money Term Loans | J45: =+VLOOKUP(K45,'[2]Sheet2 (2)'!$G$1:$H$73, 2, FALSE) -> STG Distribution LLC | K45: Reception Purchaser, LLC -First Out Term loan | L45: Reception Purchaser, LLC | M45: =VLOOKUP(J45, $D$4:$E$78, 2, FALSE) -> 1412004.2 | N45: =O45 -> 1412004.2 | O45: =VLOOKUP(I45, Sheet2!$A$1:$D$78, 4, FALSE) -> 1412004.2 | P45: =N45-O45 -> 0 | Q45: =VLOOKUP(I45, Sheet2!$A$1:$E$78, 5, FALSE) -> 0.1267268 | R45: =VLOOKUP($L45, '[3]BNP Borrowing Base PSLF JV (PIF'!$A$8:$AI$181, 11, FALSE) -> 0.06 | S45: =VLOOKUP($L45, '[3]BNP Borrowing Base PSLF JV (PIF'!$A$8:$AI$181, 20, FALSE) -> 45657 | T45: =VLOOKUP($L45, '[3]BNP Borrowing Base PSLF JV (PIF'!$A$8:$AI$181, 22, FALSE) -> 165.14773 | U45: =VLOOKUP($L45, '[3]BNP Borrowing Base PSLF JV (PIF'!$A$8:$AI$181, 23, FALSE) -> 5.449 | V45: =VLOOKUP($L45, '[3]BNP Borrowing Base PSLF JV (PIF'!$A$8:$AI$181, 32, FALSE) -> 165.14773 | W45: =VLOOKUP($L45, '[3]BNP Borrowing Base PSLF JV (PIF'!$A$8:$AI$181, 34, FALSE) -> 0.045334665
A46: MOREgroup Holdings Inc | B46: 4252707.2 | D46: MOREgroup Holdings Inc | E46: 4252707.2 | F46: =VLOOKUP(D46, $J$4:$K$79, 2, FALSE) -> MOREgroup Holdings, LLC | I46: Dynata, LLC - First Out Term Loan | J46: =+VLOOKUP(K46,'[2]Sheet2 (2)'!$G$1:$H$73, 2, FALSE) -> Research Now Group LLC | K46: Research Now Group, LLC and Dynata, LLC - First Out Term Loan | L46: Research Now / SSI | M46: =N46 -> 1580211.2 | N46: =O46 -> 1580211.2 | O46: =VLOOKUP(I46, Sheet2!$A$1:$D$78, 4, FALSE) -> 1580211.2 | P46: =N46-O46 -> 0 | Q46: =VLOOKUP(I46, Sheet2!$A$1:$E$78, 5, FALSE) -> 0.0958459 | R46: =VLOOKUP($L46, '[3]BNP Borrowing Base PSLF JV (PIF'!$A$8:$AI$181, 11, FALSE) -> 0.05 | S46: =VLOOKUP($L46, '[3]BNP Borrowing Base PSLF JV (PIF'!$A$8:$AI$181, 20, FALSE) -> 45657 | T46: =VLOOKUP($L46, '[3]BNP Borrowing Base PSLF JV (PIF'!$A$8:$AI$181, 22, FALSE) -> 4.4571244 | U46: =VLOOKUP($L46, '[3]BNP Borrowing Base PSLF JV (PIF'!$A$8:$AI$181, 23, FALSE) -> 159.053 | V46: =VLOOKUP($L46, '[3]BNP Borrowing Base PSLF JV (PIF'!$A$8:$AI$181, 32, FALSE) -> 4.4571244 | W46: =VLOOKUP($L46, '[3]BNP Borrowing Base PSLF JV (PIF'!$A$8:$AI$181, 34, FALSE) -> 1.2681832
A47: Municipal Emergency Services Inc | B47: 2499911.1 | D47: Municipal Emergency Services Inc | E47: 2499911.1 | F47: =VLOOKUP(D47, $J$4:$K$79, 2, FALSE) -> Municipal Emergency Services, Inc. | I47: Dynata, LLC - Last Out Term Loan | J47: =+VLOOKUP(K47,'[2]Sheet2 (2)'!$G$1:$H$73, 2, FALSE) -> Research Now Group LLC | K47: Research Now Group, LLC and Dynata, LLC-Last Out Term loan | L47: Research Now / SSI | M47: =N47 -> 5740273.6 | N47: =O47 -> 5740273.6 | O47: =VLOOKUP(I47, Sheet2!$A$1:$D$78, 4, FALSE) -> 5740273.6 | P47: =N47-O47 -> 0 | Q47: =VLOOKUP(I47, Sheet2!$A$1:$E$78, 5, FALSE) -> 0.1008459 | R47: =VLOOKUP($L47, '[3]BNP Borrowing Base PSLF JV (PIF'!$A$8:$AI$181, 11, FALSE) -> 0.05 | S47: =VLOOKUP($L47, '[3]BNP Borrowing Base PSLF JV (PIF'!$A$8:$AI$181, 20, FALSE) -> 45657 | T47: =VLOOKUP($L47, '[3]BNP Borrowing Base PSLF JV (PIF'!$A$8:$AI$181, 22, FALSE) -> 4.4571244 | U47: =VLOOKUP($L47, '[3]BNP Borrowing Base PSLF JV (PIF'!$A$8:$AI$181, 23, FALSE) -> 159.053 | V47: =VLOOKUP($L47, '[3]BNP Borrowing Base PSLF JV (PIF'!$A$8:$AI$181, 32, FALSE) -> 4.4571244 | W47: =VLOOKUP($L47, '[3]BNP Borrowing Base PSLF JV (PIF'!$A$8:$AI$181, 34, FALSE) -> 1.2681832
A48: NFS - CFP Holdings LLC | B48: 3990869.1 | D48: NFS - CFP Holdings LLC | E48: 3990869.1 | F48: =VLOOKUP(D48, $J$4:$K$79, 2, FALSE) -> NFS - CFP Holdings, LLC | I48: RTIC subsidiary Holdings, LLC | J48: =+VLOOKUP(K48,'[2]Sheet2 (2)'!$G$1:$H$73, 2, FALSE) -> RTIC Subsidiary Holdings LLC | K48: RTIC subsidiary Holdings, LLC | L48: RTIC | M48: =VLOOKUP(J48, $D$4:$E$78, 2, FALSE) -> 12885088 | N48: =VLOOKUP(K48, 'Loan List '!$A$6:$H$82, 8, FALSE) -> 12885088 | O48: =VLOOKUP(I48, Sheet2!$A$1:$D$78, 4, FALSE) -> 12885088 | P48: =N48-O48 -> 0 | Q48: =VLOOKUP(I48, Sheet2!$A$1:$E$78, 5, FALSE) -> 0.09959188 | R48: =VLOOKUP($L48, '[3]BNP Borrowing Base PSLF JV (PIF'!$A$8:$AI$181, 11, FALSE) -> 0.0575 | S48: =VLOOKUP($L48, '[3]BNP Borrowing Base PSLF JV (PIF'!$A$8:$AI$181, 20, FALSE) -> 45747 | T48: =VLOOKUP($L48, '[3]BNP Borrowing Base PSLF JV (PIF'!$A$8:$AI$181, 22, FALSE) -> 4.2783341 | U48: =VLOOKUP($L48, '[3]BNP Borrowing Base PSLF JV (PIF'!$A$8:$AI$181, 23, FALSE) -> 30.847492 | V48: =VLOOKUP($L48, '[3]BNP Borrowing Base PSLF JV (PIF'!$A$8:$AI$181, 32, FALSE) -> 4.2783341 | W48: =VLOOKUP($L48, '[3]BNP Borrowing Base PSLF JV (PIF'!$A$8:$AI$181, 34, FALSE) -> 1.7930334
A49: Nora Acquisition LLC | B49: 3777823.2 | D49: Nora Acquisition LLC | E49: 3777823.2 | F49: =VLOOKUP(D49, $J$4:$K$79, 2, FALSE) -> NORA ACQUISITION, LLC | I49: SV- Aero Holdings, LLC (Aeronix) | J49: =+VLOOKUP(K49,'[2]Sheet2 (2)'!$G$1:$H$73, 2, FALSE) -> SV-Aero Holdings LLC | K49: SV- Aero Holdings, LLC (Aeronix) | L49: Aeronix, Inc. | M49: =VLOOKUP(J49, $D$4:$E$78, 2, FALSE) -> 795000 | N49: =VLOOKUP(K49, 'Loan List '!$A$6:$H$82, 8, FALSE) -> 795000 | O49: =VLOOKUP(I49, Sheet2!$A$1:$D$78, 4, FALSE) -> 795000 | P49: =N49-O49 -> 0 | Q49: =VLOOKUP(I49, Sheet2!$A$1:$E$78, 5, FALSE) -> 0.097492 | R49: =VLOOKUP($L49, '[3]BNP Borrowing Base PSLF JV (PIF'!$A$8:$AI$181, 11, FALSE) -> 0.055 | S49: =VLOOKUP($L49, '[3]BNP Borrowing Base PSLF JV (PIF'!$A$8:$AI$181, 20, FALSE) -> 45657 | T49: =VLOOKUP($L49, '[3]BNP Borrowing Base PSLF JV (PIF'!$A$8:$AI$181, 22, FALSE) -> 3.4534394 | U49: =VLOOKUP($L49, '[3]BNP Borrowing Base PSLF JV (PIF'!$A$8:$AI$181, 23, FALSE) -> 65.760529 | V49: =VLOOKUP($L49, '[3]BNP Borrowing Base PSLF JV (PIF'!$A$8:$AI$181, 32, FALSE) -> 3.4534394 | W49: =VLOOKUP($L49, '[3]BNP Borrowing Base PSLF JV (PIF'!$A$8:$AI$181, 34, FALSE) -> 2.391292
A50: Omnia Exterior Solutions LLC | B50: 7136692.4 | D50: Omnia Exterior Solutions LLC | E50: 7136692.4 | F50: =VLOOKUP(D50, $J$4:$K$79, 2, FALSE) -> Omnia Exterior Solutions, LLC | I50: Sabel Systems Technology Solutions, LLC | J50: =+VLOOKUP(K50,'[2]Sheet2 (2)'!$G$1:$H$73, 2, FALSE) -> Sabel Systems Technology Solutions | K50: Sabel Systems Technology Solutions, LLC | L50: Sabel Systems | M50: =VLOOKUP(J50, $D$4:$E$78, 2, FALSE) -> 5985000 | N50: =VLOOKUP(K50, 'Loan List '!$A$6:$H$82, 8, FALSE) -> 5985000 | O50: =VLOOKUP(I50, Sheet2!$A$1:$D$78, 4, FALSE) -> 5985000 | P50: =N50-O50 -> 0 | Q50: =VLOOKUP(I50, Sheet2!$A$1:$E$78, 5, FALSE) -> 0.102992 | R50: =VLOOKUP($L50, '[3]BNP Borrowing Base PSLF JV (PIF'!$A$8:$AI$181, 11, FALSE) -> 0.0625 | S50: =VLOOKUP($L50, '[3]BNP Borrowing Base PSLF JV (PIF'!$A$8:$AI$181, 20, FALSE) -> 45716 | T50: =VLOOKUP($L50, '[3]BNP Borrowing Base PSLF JV (PIF'!$A$8:$AI$181, 22, FALSE) -> 3.1015235 | U50: =VLOOKUP($L50, '[3]BNP Borrowing Base PSLF JV (PIF'!$A$8:$AI$181, 23, FALSE) -> 24.359713 | V50: =VLOOKUP($L50, '[3]BNP Borrowing Base PSLF JV (PIF'!$A$8:$AI$181, 32, FALSE) -> 3.1015235 | W50: =VLOOKUP($L50, '[3]BNP Borrowing Base PSLF JV (PIF'!$A$8:$AI$181, 34, FALSE) -> 2.3422801
A51: OSP Embedded Purchaser LLC | B51: 19022012 | D51: OSP Embedded Purchaser LLC | E51: 19022012 | F51: =VLOOKUP(D51, $J$4:$K$79, 2, FALSE) -> Lynx Technologies | I51: S101 Holdings Inc. | J51: =+VLOOKUP(K51,'[2]Sheet2 (2)'!$G$1:$H$73, 2, FALSE) -> S101 Acquisition Inc | K51: Security 101 | L51: Security 101 | M51: 0 | N51: =VLOOKUP(K51, 'Loan List '!$A$6:$H$82, 8, FALSE) -> 0 | O51: 0 | P51: =N51-O51 -> 0 | Q51: =VLOOKUP(I51, Sheet2!$A$1:$E$78, 5, FALSE) -> #N/A | R51: 0
A52: Par Excellence Holdings Inc. | B52: 997500 | D52: Par Excellence Holdings Inc. | E52: 997500 | F52: =VLOOKUP(D52, $J$4:$K$79, 2, FALSE) -> PAR Excellence | I52: Seaway Buyer, LLC | J52: =+VLOOKUP(K52,'[2]Sheet2 (2)'!$G$1:$H$73, 2, FALSE) -> Seaway Buyer LLC | K52: Seaway Plastics | L52: Seaway Plastics | M52: =VLOOKUP(J52, $D$4:$E$78, 2, FALSE) -> 608095.06 | N52: =VLOOKUP(K52, 'Loan List '!$A$6:$H$82, 8, FALSE) -> 608095.06 | O52: =VLOOKUP(I52, Sheet2!$A$1:$D$78, 4, FALSE) -> 608095.06 | P52: =N52-O52 -> 0 | Q52: =VLOOKUP(I52, Sheet2!$A$1:$E$78, 5, FALSE) -> 0.10086424 | R52: =VLOOKUP($L52, '[3]BNP Borrowing Base PSLF JV (PIF'!$A$8:$AI$181, 11, FALSE) -> 0.0605 | S52: =VLOOKUP($L52, '[3]BNP Borrowing Base PSLF JV (PIF'!$A$8:$AI$181, 20, FALSE) -> 45747 | T52: =VLOOKUP($L52, '[3]BNP Borrowing Base PSLF JV (PIF'!$A$8:$AI$181, 22, FALSE) -> 8.0705579 | U52: =VLOOKUP($L52, '[3]BNP Borrowing Base PSLF JV (PIF'!$A$8:$AI$181, 23, FALSE) -> 7.721276 | V52: =VLOOKUP($L52, '[3]BNP Borrowing Base PSLF JV (PIF'!$A$8:$AI$181, 32, FALSE) -> 8.0705579 | W52: =VLOOKUP($L52, '[3]BNP Borrowing Base PSLF JV (PIF'!$A$8:$AI$181, 34, FALSE) -> 2.889
A53: Pink Lily Holdings LLC | B53: 8459233 | D53: Pink Lily Holdings LLC | E53: 8459233 | F53: =VLOOKUP(D53, $J$4:$K$79, 2, FALSE) -> PL Acquisitionco, LLC | I53: Sigma Defense Systems, LLC | J53: =+VLOOKUP(K53,'[2]Sheet2 (2)'!$G$1:$H$73, 2, FALSE) -> Sigma Defense Systems LLC | K53: Sigma Defense Systems, LLC | L53: Sigma Defense | M53: =VLOOKUP(J53, $D$4:$E$78, 2, FALSE) -> 18453743 | N53: =VLOOKUP(K53, 'Loan List '!$A$6:$H$82, 8, FALSE) -> 18453743 | O53: =VLOOKUP(I53, Sheet2!$A$1:$D$78, 4, FALSE) -> 18453743 | P53: =N53-O53 -> 0 | Q53: =VLOOKUP(I53, Sheet2!$A$1:$E$78, 5, FALSE) -> 0.11259124 | R53: =VLOOKUP($L53, '[3]BNP Borrowing Base PSLF JV (PIF'!$A$8:$AI$181, 11, FALSE) -> 0.07 | S53: =VLOOKUP($L53, '[3]BNP Borrowing Base PSLF JV (PIF'!$A$8:$AI$181, 20, FALSE) -> 45716 | T53: =VLOOKUP($L53, '[3]BNP Borrowing Base PSLF JV (PIF'!$A$8:$AI$181, 22, FALSE) -> 4.3893983 | U53: =VLOOKUP($L53, '[3]BNP Borrowing Base PSLF JV (PIF'!$A$8:$AI$181, 23, FALSE) -> 30.719017 | V53: =VLOOKUP($L53, '[3]BNP Borrowing Base PSLF JV (PIF'!$A$8:$AI$181, 32, FALSE) -> 6.3288483 | W53: =VLOOKUP($L53, '[3]BNP Borrowing Base PSLF JV (PIF'!$A$8:$AI$181, 34, FALSE) -> 1.8807125
A54: Project Granite Buyer Inc | B54: 5985000 | D54: Project Granite Buyer Inc | E54: 5985000 | F54: =VLOOKUP(D54, $J$4:$K$79, 2, FALSE) -> Tranzact | I54: System Planning and Analysis, Inc. (f/k/a Management Consulting & Research, LLC) | J54: =+VLOOKUP(K54,'[2]Sheet2 (2)'!$G$1:$H$73, 2, FALSE) -> Systems Planning and Analysis Inc | K54: System Planning and Analysis, Inc. | L54: System Planning and Analysis, Inc. | M54: =VLOOKUP(J54, $D$4:$E$78, 2, FALSE) -> 1279276.3 | N54: =O54 -> 1279276.3 | O54: =VLOOKUP(I54, Sheet2!$A$1:$D$78, 4, FALSE) -> 1279276.3 | P54: =N54-O54 -> 0 | Q54: =VLOOKUP(I54, Sheet2!$A$1:$E$78, 5, FALSE) -> 0.095534302 | R54: =VLOOKUP($L54, '[3]BNP Borrowing Base PSLF JV (PIF'!$A$8:$AI$181, 11, FALSE) -> 0.06 | S54: =VLOOKUP($L54, '[3]BNP Borrowing Base PSLF JV (PIF'!$A$8:$AI$181, 20, FALSE) -> 45657 | T54: =VLOOKUP($L54, '[3]BNP Borrowing Base PSLF JV (PIF'!$A$8:$AI$181, 22, FALSE) -> 5.0369789 | U54: =VLOOKUP($L54, '[3]BNP Borrowing Base PSLF JV (PIF'!$A$8:$AI$181, 23, FALSE) -> 64.78867 | V54: =VLOOKUP($L54, '[3]BNP Borrowing Base PSLF JV (PIF'!$A$8:$AI$181, 32, FALSE) -> 5.0369789 | W54: =VLOOKUP($L54, '[3]BNP Borrowing Base PSLF JV (PIF'!$A$8:$AI$181, 34, FALSE) -> 4.89
A55: Radius Aerospace Inc | B55: 11840921 | D55: Radius Aerospace Inc | E55: 11840921 | F55: =VLOOKUP(D55, $J$4:$K$79, 2, FALSE) -> Radius Aerospace | I55: Team Services Group, LLC | J55: =+VLOOKUP(K55,'[2]Sheet2 (2)'!$G$1:$H$73, 2, FALSE) -> Team Services Group LLC | K55: Team Services Group, LLC | L55: TEAM Services Group | M55: =VLOOKUP(J55, $D$4:$E$78, 2, FALSE) -> 997500 | N55: =VLOOKUP(K55, 'Loan List '!$A$6:$H$82, 8, FALSE) -> 997500 | O55: =VLOOKUP(I55, Sheet2!$A$1:$D$78, 4, FALSE) -> 997500 | P55: =N55-O55 -> 0 | Q55: =VLOOKUP(I55, Sheet2!$A$1:$E$78, 5, FALSE) -> 0.098019897 | R55: =VLOOKUP($L55, '[3]BNP Borrowing Base PSLF JV (PIF'!$A$8:$AI$181, 11, FALSE) -> 0.05 | S55: =VLOOKUP($L55, '[3]BNP Borrowing Base PSLF JV (PIF'!$A$8:$AI$181, 20, FALSE) -> 45565 | T55: =VLOOKUP($L55, '[3]BNP Borrowing Base PSLF JV (PIF'!$A$8:$AI$181, 22, FALSE) -> 3.6794724 | U55: =VLOOKUP($L55, '[3]BNP Borrowing Base PSLF JV (PIF'!$A$8:$AI$181, 23, FALSE) -> 225.082 | V55: =VLOOKUP($L55, '[3]BNP Borrowing Base PSLF JV (PIF'!$A$8:$AI$181, 32, FALSE) -> 4.2348255 | W55: =VLOOKUP($L55, '[3]BNP Borrowing Base PSLF JV (PIF'!$A$8:$AI$181, 34, FALSE) -> 2.3192853
A56: Rancho Health MSO Inc | B56: 17282079 | D56: Rancho Health MSO Inc | E56: 17282079 | F56: =VLOOKUP(D56, $J$4:$K$79, 2, FALSE) -> Rancho Medical | I56: TCG 3.0 Jogger Acquisitionco, Inc. | J56: =+VLOOKUP(K56,'[2]Sheet2 (2)'!$G$1:$H$73, 2, FALSE) -> TCG 3.0 Jogger Acquisitionco Inc | K56: TCD 3.0 Jogger Acquisitionco, Inc. Term Loan | L56: TCD 3.0 Jogger Acquisitionco, Inc. Term Loan | M56: =VLOOKUP(J56, $D$4:$E$78, 2, FALSE) -> 3930150.8 | N56: =VLOOKUP(K56, 'Loan List '!$A$6:$H$82, 8, FALSE) -> 3930150.8 | O56: =VLOOKUP(I56, Sheet2!$A$1:$D$78, 4, FALSE) -> 3930150.8 | P56: =N56-O56 -> 0 | Q56: =VLOOKUP(I56, Sheet2!$A$1:$E$78, 5, FALSE) -> 0.10293391 | R56: =VLOOKUP($L56, '[3]BNP Borrowing Base PSLF JV (PIF'!$A$8:$AI$181, 11, FALSE) -> 0.065 | S56: =VLOOKUP($L56, '[3]BNP Borrowing Base PSLF JV (PIF'!$A$8:$AI$181, 20, FALSE) -> 45747 | T56: =VLOOKUP($L56, '[3]BNP Borrowing Base PSLF JV (PIF'!$A$8:$AI$181, 22, FALSE) -> 4.3446448 | U56: =VLOOKUP($L56, '[3]BNP Borrowing Base PSLF JV (PIF'!$A$8:$AI$181, 23, FALSE) -> 13.69498 | V56: =VLOOKUP($L56, '[3]BNP Borrowing Base PSLF JV (PIF'!$A$8:$AI$181, 32, FALSE) -> 4.3446448 | W56: =VLOOKUP($L56, '[3]BNP Borrowing Base PSLF JV (PIF'!$A$8:$AI$181, 34, FALSE) -> 1.8373955
A57: Research Now Group LLC | B57: 7320484.8 | D57: Research Now Group LLC | E57: 7320484.8 | F57: =VLOOKUP(D57, $J$4:$K$79, 2, FALSE) -> Research Now Group, LLC and Dynata, LLC - First Out Term Loan | I57: The Bluebird Group LLC | J57: =+VLOOKUP(K57,'[2]Sheet2 (2)'!$G$1:$H$73, 2, FALSE) -> Bluebird Group LLC, The | K57: The Bluebird Group LLC | L57: The Bluebird Group LLC | M57: =VLOOKUP(J57, $D$4:$E$78, 2, FALSE) -> 3635030.3 | N57: =VLOOKUP(K57, 'Loan List '!$A$6:$H$82, 8, FALSE) -> 3635030.3 | O57: =VLOOKUP(I57, Sheet2!$A$1:$D$78, 4, FALSE) -> 3635030.3 | P57: =N57-O57 -> 0 | Q57: =VLOOKUP(I57, Sheet2!$A$1:$E$78, 5, FALSE) -> 0.10117049 | R57: =VLOOKUP($L57, '[3]BNP Borrowing Base PSLF JV (PIF'!$A$8:$AI$181, 11, FALSE) -> 0.07 | S57: =VLOOKUP($L57, '[3]BNP Borrowing Base PSLF JV (PIF'!$A$8:$AI$181, 20, FALSE) -> 45716 | T57: =VLOOKUP($L57, '[3]BNP Borrowing Base PSLF JV (PIF'!$A$8:$AI$181, 22, FALSE) -> 1.762627 | U57: =VLOOKUP($L57, '[3]BNP Borrowing Base PSLF JV (PIF'!$A$8:$AI$181, 23, FALSE) -> 25.645609 | V57: =VLOOKUP($L57, '[3]BNP Borrowing Base PSLF JV (PIF'!$A$8:$AI$181, 32, FALSE) -> 1.762627 | W57: =VLOOKUP($L57, '[3]BNP Borrowing Base PSLF JV (PIF'!$A$8:$AI$181, 34, FALSE) -> 4.1889177
A58: Ro Health LLC | B58: 10000000 | D58: Ro Health LLC | E58: 10000000 | F58: =VLOOKUP(D58, $J$4:$K$79, 2, FALSE) -> Ro Health | I58: The Vertex Companies, LLC | J58: =+VLOOKUP(K58,'[2]Sheet2 (2)'!$G$1:$H$73, 2, FALSE) -> Vertex Companies Inc, The | K58: The Vertex Companies, LLC | L58: Vertex | M58: =VLOOKUP(J58, $D$4:$E$78, 2, FALSE) -> 6982500 | N58: =VLOOKUP(K58, 'Loan List '!$A$6:$H$82, 8, FALSE) -> 6982500 | O58: =VLOOKUP(I58, Sheet2!$A$1:$D$78, 4, FALSE) -> 6982500 | P58: =N58-O58 -> 0 | Q58: =VLOOKUP(I58, Sheet2!$A$1:$E$78, 5, FALSE) -> 0.093141 | R58: =VLOOKUP($L58, '[3]BNP Borrowing Base PSLF JV (PIF'!$A$8:$AI$181, 11, FALSE) -> 0.055 | S58: =VLOOKUP($L58, '[3]BNP Borrowing Base PSLF JV (PIF'!$A$8:$AI$181, 20, FALSE) -> 45747 | T58: =VLOOKUP($L58, '[3]BNP Borrowing Base PSLF JV (PIF'!$A$8:$AI$181, 22, FALSE) -> 5.4134313 | U58: =VLOOKUP($L58, '[3]BNP Borrowing Base PSLF JV (PIF'!$A$8:$AI$181, 23, FALSE) -> 32.119 | V58: =VLOOKUP($L58, '[3]BNP Borrowing Base PSLF JV (PIF'!$A$8:$AI$181, 32, FALSE) -> 5.4134313 | W58: =VLOOKUP($L58, '[3]BNP Borrowing Base PSLF JV (PIF'!$A$8:$AI$181, 34, FALSE) -> 2.7064182
A59: RTIC Subsidiary Holdings LLC | B59: 12885088 | D59: RTIC Subsidiary Holdings LLC | E59: 12885088 | F59: =VLOOKUP(D59, $J$4:$K$79, 2, FALSE) -> RTIC subsidiary Holdings, LLC | I59: Transgo, LLC | J59: =+VLOOKUP(K59,'[2]Sheet2 (2)'!$G$1:$H$73, 2, FALSE) -> Transgo LLC | K59: Transgo | L59: Transgo | M59: =VLOOKUP(J59, $D$4:$E$78, 2, FALSE) -> 3163695.7 | N59: =O59 -> 3163695.7 | O59: =VLOOKUP(I59, Sheet2!$A$1:$D$78, 4, FALSE) -> 3163695.7 | P59: =N59-O59 -> 0 | Q59: =VLOOKUP(I59, Sheet2!$A$1:$E$78, 5, FALSE) -> 0.10439937 | R59: =VLOOKUP($L59, '[3]BNP Borrowing Base PSLF JV (PIF'!$A$8:$AI$181, 11, FALSE) -> 0.06 | S59: =VLOOKUP($L59, '[3]BNP Borrowing Base PSLF JV (PIF'!$A$8:$AI$181, 20, FALSE) -> 45747 | T59: =VLOOKUP($L59, '[3]BNP Borrowing Base PSLF JV (PIF'!$A$8:$AI$181, 22, FALSE) -> 3.4758744 | U59: =VLOOKUP($L59, '[3]BNP Borrowing Base PSLF JV (PIF'!$A$8:$AI$181, 23, FALSE) -> 19.703963 | V59: =VLOOKUP($L59, '[3]BNP Borrowing Base PSLF JV (PIF'!$A$8:$AI$181, 32, FALSE) -> 3.4758744 | W59: =VLOOKUP($L59, '[3]BNP Borrowing Base PSLF JV (PIF'!$A$8:$AI$181, 34, FALSE) -> 2.0913062
A60: Sabel Systems Technology Solutions | B60: 5985000 | D60: Sabel Systems Technology Solutions | E60: 5985000 | F60: =VLOOKUP(D60, $J$4:$K$79, 2, FALSE) -> Sabel Systems Technology Solutions, LLC | I60: Urology Management Holdings, Inc. | J60: =+VLOOKUP(K60,'[2]Sheet2 (2)'!$G$1:$H$73, 2, FALSE) -> Urology Management Holdings Inc | K60: UROLOGY MANAGEMENT HOLDINGS, INC. | L60: UROLOGY MANAGEMENT HOLDINGS, INC. | M60: =VLOOKUP(J60, $D$4:$E$78, 2, FALSE) -> 2672274 | N60: =VLOOKUP(K60, 'Loan List '!$A$6:$H$82, 8, FALSE) -> 2672274 | O60: =VLOOKUP(I60, Sheet2!$A$1:$D$78, 4, FALSE) -> 2672274 | P60: =N60-O60 -> 0 | Q60: =VLOOKUP(I60, Sheet2!$A$1:$E$78, 5, FALSE) -> 0.096792455 | R60: =VLOOKUP($L60, '[3]BNP Borrowing Base PSLF JV (PIF'!$A$8:$AI$181, 11, FALSE) -> 0.055 | S60: =VLOOKUP($L60, '[3]BNP Borrowing Base PSLF JV (PIF'!$A$8:$AI$181, 20, FALSE) -> 45657 | T60: =VLOOKUP($L60, '[3]BNP Borrowing Base PSLF JV (PIF'!$A$8:$AI$181, 22, FALSE) -> 4.3827134 | U60: =VLOOKUP($L60, '[3]BNP Borrowing Base PSLF JV (PIF'!$A$8:$AI$181, 23, FALSE) -> 115.77626 | V60: =VLOOKUP($L60, '[3]BNP Borrowing Base PSLF JV (PIF'!$A$8:$AI$181, 32, FALSE) -> 4.3827134 | W60: =VLOOKUP($L60, '[3]BNP Borrowing Base PSLF JV (PIF'!$A$8:$AI$181, 34, FALSE) -> 1.6708016
A61: Seacoast Service Partners NA LLC | B61: 4987500 | D61: Seacoast Service Partners NA LLC | E61: 4987500 | F61: =VLOOKUP(D61, $J$4:$K$79, 2, FALSE) -> Seacoast | I61: US Fertility Enterprises, LLC | J61: =+VLOOKUP(K61,'[2]Sheet2 (2)'!$G$1:$H$73, 2, FALSE) -> US Fertility Enterprises LLC | K61: US Fertility | L61: US Fertility | M61: =VLOOKUP(J61, $D$4:$E$78, 2, FALSE) -> 4987500 | N61: =VLOOKUP(K61, 'Loan List '!$A$6:$H$82, 8, FALSE) -> 4987500 | O61: =VLOOKUP(I61, Sheet2!$A$1:$D$78, 4, FALSE) -> 4987500 | P61: =N61-O61 -> 0 | Q61: =VLOOKUP(I61, Sheet2!$A$1:$E$78, 5, FALSE) -> 0.0882878 | R61: =VLOOKUP($L61, '[3]BNP Borrowing Base PSLF JV (PIF'!$A$8:$AI$181, 11, FALSE) -> 0.045 | S61: =VLOOKUP($L61, '[3]BNP Borrowing Base PSLF JV (PIF'!$A$8:$AI$181, 20, FALSE) -> 45657 | T61: =VLOOKUP($L61, '[3]BNP Borrowing Base PSLF JV (PIF'!$A$8:$AI$181, 22, FALSE) -> 4.2508902 | U61: =VLOOKUP($L61, '[3]BNP Borrowing Base PSLF JV (PIF'!$A$8:$AI$181, 23, FALSE) -> 115.7 | V61: =VLOOKUP($L61, '[3]BNP Borrowing Base PSLF JV (PIF'!$A$8:$AI$181, 32, FALSE) -> 4.2508902 | W61: =VLOOKUP($L61, '[3]BNP Borrowing Base PSLF JV (PIF'!$A$8:$AI$181, 34, FALSE) -> 1.6915205
A62: Seaway Buyer LLC | B62: 608095.06 | D62: Seaway Buyer LLC | E62: 608095.06 | F62: =VLOOKUP(D62, $J$4:$K$79, 2, FALSE) -> Seaway Plastics | I62: Watchtower Buyer, LLC | J62: =+VLOOKUP(K62,'[2]Sheet2 (2)'!$G$1:$H$73, 2, FALSE) -> Watchtower Buyer LLC | K62: Watchtower Buyer, LLC | L62: Watchtower Buyer, LLC | M62: =VLOOKUP(J62, $D$4:$E$78, 2, FALSE) -> 6443355.6 | N62: =VLOOKUP(K62, 'Loan List '!$A$6:$H$82, 8, FALSE) -> 6443355.6 | O62: =VLOOKUP(I62, Sheet2!$A$1:$D$78, 4, FALSE) -> 6443355.6 | P62: =N62-O62 -> 0 | Q62: =VLOOKUP(I62, Sheet2!$A$1:$E$78, 5, FALSE) -> 0.1003855 | R62: =VLOOKUP($L62, '[3]BNP Borrowing Base PSLF JV (PIF'!$A$8:$AI$181, 11, FALSE) -> 0.06 | S62: =VLOOKUP($L62, '[3]BNP Borrowing Base PSLF JV (PIF'!$A$8:$AI$181, 20, FALSE) -> 45716 | T62: =VLOOKUP($L62, '[3]BNP Borrowing Base PSLF JV (PIF'!$A$8:$AI$181, 22, FALSE) -> 4.8891218 | U62: =VLOOKUP($L62, '[3]BNP Borrowing Base PSLF JV (PIF'!$A$8:$AI$181, 23, FALSE) -> 10.983887 | V62: =VLOOKUP($L62, '[3]BNP Borrowing Base PSLF JV (PIF'!$A$8:$AI$181, 32, FALSE) -> 4.8891218 | W62: =VLOOKUP($L62, '[3]BNP Borrowing Base PSLF JV (PIF'!$A$8:$AI$181, 34, FALSE) -> 1.6233363
A63: Sigma Defense Systems LLC | B63: 18453743 | D63: Sigma Defense Systems LLC | E63: 18453743 | F63: =VLOOKUP(D63, $J$4:$K$79, 2, FALSE) -> Sigma Defense Systems, LLC | I63: HV Watterson Holdings, LLC | J63: =+VLOOKUP(K63,'[2]Sheet2 (2)'!$G$1:$H$73, 2, FALSE) -> HV Watterson Holdings LLC | K63: Watterson | L63: Watterson | M63: =VLOOKUP(J63, $D$4:$E$78, 2, FALSE) -> 9328396.7 | N63: =VLOOKUP(K63, 'Loan List '!$A$6:$H$82, 8, FALSE) -> 9328396.8 | O63: =VLOOKUP(I63, Sheet2!$A$1:$D$78, 4, FALSE) -> 9328396.8 | P63: =N63-O63 -> 0 | Q63: =VLOOKUP(I63, Sheet2!$A$1:$E$78, 5, FALSE) -> 0.12 | R63: =VLOOKUP($L63, '[3]BNP Borrowing Base PSLF JV (PIF'!$A$8:$AI$181, 11, FALSE) -> 0.06 | S63: =VLOOKUP($L63, '[3]BNP Borrowing Base PSLF JV (PIF'!$A$8:$AI$181, 20, FALSE) -> 45716 | T63: =VLOOKUP($L63, '[3]BNP Borrowing Base PSLF JV (PIF'!$A$8:$AI$181, 22, FALSE) -> 13.366389 | U63: =VLOOKUP($L63, '[3]BNP Borrowing Base PSLF JV (PIF'!$A$8:$AI$181, 23, FALSE) -> 8.8660475 | V63: =VLOOKUP($L63, '[3]BNP Borrowing Base PSLF JV (PIF'!$A$8:$AI$181, 32, FALSE) -> 13.366389 | W63: =VLOOKUP($L63, '[3]BNP Borrowing Base PSLF JV (PIF'!$A$8:$AI$181, 34, FALSE) -> 0.56537769
A64: STG Distribution LLC | B64: 1412004.2 | D64: STG Distribution LLC | E64: 1412004.2 | F64: =VLOOKUP(D64, $J$4:$K$79, 2, FALSE) -> Reception Purchaser, LLC -First Out Term loan | I64: Zips Car Wash, LLC | J64: =+VLOOKUP(K64,'[2]Sheet2 (2)'!$G$1:$H$73, 2, FALSE) -> Zips Car Wash LLC | K64: Zips Car Wash, LLC | L64: Zips | M64: =VLOOKUP(J64, $D$4:$E$78, 2, FALSE) -> 8577681.2 | N64: =VLOOKUP(K64, 'Loan List '!$A$6:$H$82, 8, FALSE) -> 8577681.3 | O64: =VLOOKUP(I64, Sheet2!$A$1:$D$78, 4, FALSE) -> 8577681.3 | P64: =N64-O64 -> 0 | Q64: =VLOOKUP(I64, Sheet2!$A$1:$E$78, 5, FALSE) -> 0 | R64: =VLOOKUP($L64, '[3]BNP Borrowing Base PSLF JV (PIF'!$A$8:$AI$181, 11, FALSE) -> 0 | S64: =VLOOKUP($L64, '[3]BNP Borrowing Base PSLF JV (PIF'!$A$8:$AI$181, 20, FALSE) -> 45777 | T64: =VLOOKUP($L64, '[3]BNP Borrowing Base PSLF JV (PIF'!$A$8:$AI$181, 22, FALSE) -> 4.4412693 | U64: =VLOOKUP($L64, '[3]BNP Borrowing Base PSLF JV (PIF'!$A$8:$AI$181, 23, FALSE) -> 50.391 | V64: =VLOOKUP($L64, '[3]BNP Borrowing Base PSLF JV (PIF'!$A$8:$AI$181, 32, FALSE) -> 7.4179913 | W64: =VLOOKUP($L64, '[3]BNP Borrowing Base PSLF JV (PIF'!$A$8:$AI$181, 34, FALSE) -> 2.2495982
A65: SV-Aero Holdings LLC | B65: 795000 | D65: SV-Aero Holdings LLC | E65: 795000 | F65: =VLOOKUP(D65, $J$4:$K$79, 2, FALSE) -> SV- Aero Holdings, LLC (Aeronix) | I65: By Light professional IT Services, LLC | J65: =+VLOOKUP(K65,'[2]Sheet2 (2)'!$G$1:$H$73, 2, FALSE) -> By Light Professional IT Services LLC | K65: By Light | L65: By Light | M65: 0 | N65: =VLOOKUP(K65, 'Loan List '!$A$6:$H$82, 8, FALSE) -> 0 | O65: =VLOOKUP(I65, Sheet2!$A$1:$D$78, 4, FALSE) -> 0 | P65: =N65-O65 -> 0 | Q65: =VLOOKUP(I65, Sheet2!$A$1:$E$78, 5, FALSE) -> 0.107927 | R65: =VLOOKUP($L65, '[3]BNP Borrowing Base PSLF JV (PIF'!$A$8:$AI$181, 11, FALSE) -> 0.0625 | S65: =VLOOKUP($L65, '[3]BNP Borrowing Base PSLF JV (PIF'!$A$8:$AI$181, 20, FALSE) -> 45747 | T65: =VLOOKUP($L65, '[3]BNP Borrowing Base PSLF JV (PIF'!$A$8:$AI$181, 22, FALSE) -> 4.9760178 | U65: =VLOOKUP($L65, '[3]BNP Borrowing Base PSLF JV (PIF'!$A$8:$AI$181, 23, FALSE) -> 109.06673 | V65: =VLOOKUP($L65, '[3]BNP Borrowing Base PSLF JV (PIF'!$A$8:$AI$181, 32, FALSE) -> 5.2120934 | W65: =VLOOKUP($L65, '[3]BNP Borrowing Base PSLF JV (PIF'!$A$8:$AI$181, 34, FALSE) -> 1.6536057
A66: Systems Planning and Analysis Inc | B66: 1279276.3 | D66: Systems Planning and Analysis Inc | E66: 1279276.3 | F66: =VLOOKUP(D66, $J$4:$K$79, 2, FALSE) -> System Planning and Analysis, Inc. | I66: Best Practice Associates, LLC | J66: =+VLOOKUP(K66,'[2]Sheet2 (2)'!$G$1:$H$73, 2, FALSE) -> Best Practice Associates LLC | K66: Federal Advisory Partners | L66: Federal Advisory Partners | M66: =VLOOKUP(J66, $D$4:$E$78, 2, FALSE) -> 10781438 | N66: =O66 -> 6981437.5 | O66: =VLOOKUP(I66, Sheet2!$A$1:$D$78, 4, FALSE) -> 6981437.5 | P66: =N66-O66 -> 0 | Q66: =VLOOKUP(I66, Sheet2!$A$1:$E$78, 5, FALSE) -> 0.1104917 | R66: =VLOOKUP($L66, '[3]BNP Borrowing Base PSLF JV (PIF'!$A$8:$AI$181, 11, FALSE) -> 0.0675 | S66: =VLOOKUP($L66, '[3]BNP Borrowing Base PSLF JV (PIF'!$A$8:$AI$181, 20, FALSE) -> 45716 | T66: =VLOOKUP($L66, '[3]BNP Borrowing Base PSLF JV (PIF'!$A$8:$AI$181, 22, FALSE) -> 4.4216391 | U66: =VLOOKUP($L66, '[3]BNP Borrowing Base PSLF JV (PIF'!$A$8:$AI$181, 23, FALSE) -> 71.800263 | V66: =VLOOKUP($L66, '[3]BNP Borrowing Base PSLF JV (PIF'!$A$8:$AI$181, 32, FALSE) -> 4.6924709 | W66: =VLOOKUP($L66, '[3]BNP Borrowing Base PSLF JV (PIF'!$A$8:$AI$181, 34, FALSE) -> 2.2291668
A67: TCG 3.0 Jogger Acquisitionco Inc | B67: 3930150.8 | D67: TCG 3.0 Jogger Acquisitionco Inc | E67: 3930150.8 | F67: =VLOOKUP(D67, $J$4:$K$79, 2, FALSE) -> TCD 3.0 Jogger Acquisitionco, Inc. Term Loan | I67: Arcfield Acquisition Corp. | J67: =+VLOOKUP(K67,'[2]Sheet2 (2)'!$G$1:$H$73, 2, FALSE) -> Arcfield Acquisition Corp | K67: Arcfield | L67: Arcfield | M67: =VLOOKUP(J67, $D$4:$E$78, 2, FALSE) -> 11620875 | N67: =O67 -> 2320875 | O67: =VLOOKUP(I67, Sheet2!$A$1:$D$78, 4, FALSE) -> 2320875 | P67: =N67-O67 -> 0 | Q67: =VLOOKUP(I67, Sheet2!$A$1:$E$78, 5, FALSE) -> 0.092998 | R67: =VLOOKUP($L67, '[3]BNP Borrowing Base PSLF JV (PIF'!$A$8:$AI$181, 11, FALSE) -> 0.0625 | S67: =VLOOKUP($L67, '[3]BNP Borrowing Base PSLF JV (PIF'!$A$8:$AI$181, 20, FALSE) -> 45565 | T67: =VLOOKUP($L67, '[3]BNP Borrowing Base PSLF JV (PIF'!$A$8:$AI$181, 22, FALSE) -> 3.9264545 | U67: =VLOOKUP($L67, '[3]BNP Borrowing Base PSLF JV (PIF'!$A$8:$AI$181, 23, FALSE) -> 65.728 | V67: =VLOOKUP($L67, '[3]BNP Borrowing Base PSLF JV (PIF'!$A$8:$AI$181, 32, FALSE) -> 3.9264545 | W67: =VLOOKUP($L67, '[3]BNP Borrowing Base PSLF JV (PIF'!$A$8:$AI$181, 34, FALSE) -> 1.7868153
A68: Team Services Group LLC | B68: 997500 | D68: Team Services Group LLC | E68: 997500 | F68: =VLOOKUP(D68, $J$4:$K$79, 2, FALSE) -> Team Services Group, LLC | I68: BLC Holding Company, INC. | J68: =+VLOOKUP(K68,'[2]Sheet2 (2)'!$G$1:$H$73, 2, FALSE) -> BLC Holding Company Inc | K68: Bland Landscaping | L68: Bland Landscaping | M68: =VLOOKUP(J68, $D$4:$E$78, 2, FALSE) -> 2098550.6 | N68: =O68 -> 2098550.6 | O68: =VLOOKUP(I68, Sheet2!$A$1:$D$78, 4, FALSE) -> 2098550.6 | P68: =N68-O68 -> 0 | Q68: =VLOOKUP(I68, Sheet2!$A$1:$E$78, 5, FALSE) -> 0.090492 | R68: =VLOOKUP($L68, '[3]BNP Borrowing Base PSLF JV (PIF'!$A$8:$AI$181, 11, FALSE) -> 0.0475 | S68: =VLOOKUP($L68, '[3]BNP Borrowing Base PSLF JV (PIF'!$A$8:$AI$181, 20, FALSE) -> 45716 | T68: =VLOOKUP($L68, '[3]BNP Borrowing Base PSLF JV (PIF'!$A$8:$AI$181, 22, FALSE) -> 4.1780535 | U68: =VLOOKUP($L68, '[3]BNP Borrowing Base PSLF JV (PIF'!$A$8:$AI$181, 23, FALSE) -> 13.237993 | V68: =VLOOKUP($L68, '[3]BNP Borrowing Base PSLF JV (PIF'!$A$8:$AI$181, 32, FALSE) -> 4.1780535 | W68: =VLOOKUP($L68, '[3]BNP Borrowing Base PSLF JV (PIF'!$A$8:$AI$181, 34, FALSE) -> 2.103953
A69: TMII Enterprises LLC | B69: 3192037.2 | D69: TMII Enterprises LLC | E69: 3192037.2 | F69: =VLOOKUP(D69, $J$4:$K$79, 2, FALSE) -> A1 Garage Merger Sub, LLC | I69: OSP Embedded Purchaser, LLC | J69: =+VLOOKUP(K69,'[2]Sheet2 (2)'!$G$1:$H$73, 2, FALSE) -> OSP Embedded Purchaser LLC | K69: Lynx Technologies | L69: Lynx Technologies | M69: =VLOOKUP(J69, $D$4:$E$78, 2, FALSE) -> 19022012 | N69: =VLOOKUP(K69, 'Loan List '!$A$6:$H$82, 8, FALSE) -> 19022012 | O69: =VLOOKUP(I69, Sheet2!$A$1:$D$78, 4, FALSE) -> 19022012 | P69: =N69-O69 -> 0 | Q69: =VLOOKUP(I69, Sheet2!$A$1:$E$78, 5, FALSE) -> 0.100492 | R69: =VLOOKUP($L69, '[3]BNP Borrowing Base PSLF JV (PIF'!$A$8:$AI$181, 11, FALSE) -> 0.0585 | S69: =VLOOKUP($L69, '[3]BNP Borrowing Base PSLF JV (PIF'!$A$8:$AI$181, 20, FALSE) -> 45688 | T69: =VLOOKUP($L69, '[3]BNP Borrowing Base PSLF JV (PIF'!$A$8:$AI$181, 22, FALSE) -> 3.7932843 | U69: =VLOOKUP($L69, '[3]BNP Borrowing Base PSLF JV (PIF'!$A$8:$AI$181, 23, FALSE) -> 20.4 | V69: =VLOOKUP($L69, '[3]BNP Borrowing Base PSLF JV (PIF'!$A$8:$AI$181, 32, FALSE) -> 4.2834804 | W69: =VLOOKUP($L69, '[3]BNP Borrowing Base PSLF JV (PIF'!$A$8:$AI$181, 34, FALSE) -> 2.1935484
A70: Transgo LLC | B70: 3163695.7 | D70: Transgo LLC | E70: 3163695.7 | F70: =VLOOKUP(D70, $J$4:$K$79, 2, FALSE) -> Transgo | I70: VRS Buyer, Inc. | J70: VRS Buyer Inc | K70: VRS Buyer | L70: Velocity Rail Solutions | M70: =VLOOKUP(J70, $D$4:$E$78, 2, FALSE) -> 9000000 | N70: =VLOOKUP(K70, 'Loan List '!$A$6:$H$82, 8, FALSE) -> 9000000 | O70: =VLOOKUP(I70, Sheet2!$A$1:$D$78, 4, FALSE) -> 9000000 | P70: =N70-O70 -> 0 | Q70: =VLOOKUP(I70, Sheet2!$A$1:$E$78, 5, FALSE) -> 0.090786 | R70: =VLOOKUP($L70, '[3]BNP Borrowing Base PSLF JV (PIF'!$A$8:$AI$181, 11, FALSE) -> 0.0475 | S70: =VLOOKUP($L70, '[3]BNP Borrowing Base PSLF JV (PIF'!$A$8:$AI$181, 20, FALSE) -> 45688 | T70: =VLOOKUP($L70, '[3]BNP Borrowing Base PSLF JV (PIF'!$A$8:$AI$181, 22, FALSE) -> 3.8707963 | U70: =VLOOKUP($L70, '[3]BNP Borrowing Base PSLF JV (PIF'!$A$8:$AI$181, 23, FALSE) -> 15.998 | V70: =VLOOKUP($L70, '[3]BNP Borrowing Base PSLF JV (PIF'!$A$8:$AI$181, 32, FALSE) -> 3.8707963 | W70: =VLOOKUP($L70, '[3]BNP Borrowing Base PSLF JV (PIF'!$A$8:$AI$181, 34, FALSE) -> 2.0776623
A71: Urology Management Holdings Inc | B71: 2672274 | D71: Urology Management Holdings Inc | E71: 2672274 | F71: =VLOOKUP(D71, $J$4:$K$79, 2, FALSE) -> UROLOGY MANAGEMENT HOLDINGS, INC. | I71: Inovex Information Systems Incorporated | J71: Inovex Information Systems Incorporated | K71: RealmOne | L71: RealmOne | M71: =VLOOKUP(J71, $D$4:$E$78, 2, FALSE) -> 5985000 | N71: =VLOOKUP(K71, 'Loan List '!$A$6:$H$82, 8, FALSE) -> 6000000 | O71: =VLOOKUP(I71, Sheet2!$A$1:$D$78, 4, FALSE) -> 6000000 | P71: =N71-O71 -> 0 | Q71: =VLOOKUP(I71, Sheet2!$A$1:$E$78, 5, FALSE) -> 0.0957384 | R71: =VLOOKUP($L71, '[3]BNP Borrowing Base PSLF JV (PIF'!$A$8:$AI$181, 11, FALSE) -> 0.0525 | S71: =VLOOKUP($L71, '[3]BNP Borrowing Base PSLF JV (PIF'!$A$8:$AI$181, 20, FALSE) -> 45716 | T71: =VLOOKUP($L71, '[3]BNP Borrowing Base PSLF JV (PIF'!$A$8:$AI$181, 22, FALSE) -> 5.0326622 | U71: =VLOOKUP($L71, '[3]BNP Borrowing Base PSLF JV (PIF'!$A$8:$AI$181, 23, FALSE) -> 22.916579 | V71: =VLOOKUP($L71, '[3]BNP Borrowing Base PSLF JV (PIF'!$A$8:$AI$181, 32, FALSE) -> 5.0326622 | W71: =VLOOKUP($L71, '[3]BNP Borrowing Base PSLF JV (PIF'!$A$8:$AI$181, 34, FALSE) -> 1.6473027
A72: US Fertility Enterprises LLC | B72: 4987500 | D72: US Fertility Enterprises LLC | E72: 4987500 | F72: =VLOOKUP(D72, $J$4:$K$79, 2, FALSE) -> US Fertility | I72: Seacoast Service Partners, LLC | J72: Seacoast Service Partners NA LLC | K72: Seacoast | L72: Seacoast Service Partners | M72: =VLOOKUP(J72, $D$4:$E$78, 2, FALSE) -> 4987500 | N72: =VLOOKUP(K72, 'Loan List '!$A$6:$H$82, 8, FALSE) -> 4987500 | O72: =VLOOKUP(I72, Sheet2!$A$1:$D$78, 4, FALSE) -> 4987500 | P72: =N72-O72 -> 0 | Q72: =VLOOKUP(I72, Sheet2!$A$1:$E$78, 5, FALSE) -> 0.092992 | R72: =VLOOKUP($L72, '[3]BNP Borrowing Base PSLF JV (PIF'!$A$8:$AI$181, 11, FALSE) -> 0.05 | S72: =VLOOKUP($L72, '[3]BNP Borrowing Base PSLF JV (PIF'!$A$8:$AI$181, 20, FALSE) -> 45716 | T72: =VLOOKUP($L72, '[3]BNP Borrowing Base PSLF JV (PIF'!$A$8:$AI$181, 22, FALSE) -> 2.6148019 | U72: =VLOOKUP($L72, '[3]BNP Borrowing Base PSLF JV (PIF'!$A$8:$AI$181, 23, FALSE) -> 9.9211258 | V72: =VLOOKUP($L72, '[3]BNP Borrowing Base PSLF JV (PIF'!$A$8:$AI$181, 32, FALSE) -> 2.6148019 | W72: =VLOOKUP($L72, '[3]BNP Borrowing Base PSLF JV (PIF'!$A$8:$AI$181, 34, FALSE) -> 4.9605629
A73: Vertex Companies Inc, The | B73: 6982500 | D73: Vertex Companies Inc, The | E73: 6982500 | F73: =VLOOKUP(D73, $J$4:$K$79, 2, FALSE) -> The Vertex Companies, LLC | I73: Marketplace Events Acquisition, LLC | J73: Marketplace Events LLC | K73: Marketplace | L73: Marketplace Events | M73: =VLOOKUP(J73, $D$4:$E$78, 2, FALSE) -> 20000000 | N73: =VLOOKUP(K73, 'Loan List '!$A$6:$H$82, 8, FALSE) -> 20000000 | O73: =VLOOKUP(I73, Sheet2!$A$1:$D$78, 4, FALSE) -> 20000000 | P73: =N73-O73 -> 0 | Q73: =VLOOKUP(I73, Sheet2!$A$1:$E$78, 5, FALSE) -> 0.094666 | R73: =VLOOKUP($L73, '[3]BNP Borrowing Base PSLF JV (PIF'!$A$8:$AI$181, 11, FALSE) -> 0.0525 | S73: =VLOOKUP($L73, '[3]BNP Borrowing Base PSLF JV (PIF'!$A$8:$AI$181, 20, FALSE) -> 45716 | T73: =VLOOKUP($L73, '[3]BNP Borrowing Base PSLF JV (PIF'!$A$8:$AI$181, 22, FALSE) -> 4.9990672 | U73: =VLOOKUP($L73, '[3]BNP Borrowing Base PSLF JV (PIF'!$A$8:$AI$181, 23, FALSE) -> 21.441 | V73: =VLOOKUP($L73, '[3]BNP Borrowing Base PSLF JV (PIF'!$A$8:$AI$181, 32, FALSE) -> 4.9990672 | W73: =VLOOKUP($L73, '[3]BNP Borrowing Base PSLF JV (PIF'!$A$8:$AI$181, 34, FALSE) -> 1.756883
A74: VRS Buyer Inc | B74: 9000000 | D74: VRS Buyer Inc | E74: 9000000 | F74: =VLOOKUP(D74, $J$4:$K$79, 2, FALSE) -> VRS Buyer | I74: Emergency Care Partners, LLC | J74: Emergency Care Partners LLC | K74: Emergency Care Partners LLC | L74: Emergency Care Partners | M74: =VLOOKUP(J74, $D$4:$E$78, 2, FALSE) -> 995000 | N74: =VLOOKUP(K74, 'Loan List '!$A$6:$H$82, 8, FALSE) -> 995000 | O74: =VLOOKUP(I74, Sheet2!$A$1:$D$78, 4, FALSE) -> 995000 | P74: =N74-O74 -> 0 | Q74: =VLOOKUP(I74, Sheet2!$A$1:$E$78, 5, FALSE) -> 0.096926571 | R74: =VLOOKUP($L74, '[3]BNP Borrowing Base PSLF JV (PIF'!$A$8:$AI$181, 11, FALSE) -> 0.055 | S74: =VLOOKUP($L74, '[3]BNP Borrowing Base PSLF JV (PIF'!$A$8:$AI$181, 20, FALSE) -> 45716 | T74: =VLOOKUP($L74, '[3]BNP Borrowing Base PSLF JV (PIF'!$A$8:$AI$181, 22, FALSE) -> 4.6148697 | U74: =VLOOKUP($L74, '[3]BNP Borrowing Base PSLF JV (PIF'!$A$8:$AI$181, 23, FALSE) -> 33.67822 | V74: =VLOOKUP($L74, '[3]BNP Borrowing Base PSLF JV (PIF'!$A$8:$AI$181, 32, FALSE) -> 4.6148697 | W74: =VLOOKUP($L74, '[3]BNP Borrowing Base PSLF JV (PIF'!$A$8:$AI$181, 34, FALSE) -> 1.6611449
A75: Watchtower Buyer LLC | B75: 6443355.6 | D75: Watchtower Buyer LLC | E75: 6443355.6 | F75: =VLOOKUP(D75, $J$4:$K$79, 2, FALSE) -> Watchtower Buyer, LLC | I75: Amsive Holding Corporation (f/k/a Vision Purchaser Corporation) | J75: Amsive Holdings Corporation | K75: Amsive Holding Corporation | L75: Vision Purchaser Corporation | M75: =VLOOKUP(J75, $D$4:$E$78, 2, FALSE) -> 15083.03 | N75: =VLOOKUP(K75, 'Loan List '!$A$6:$H$82, 8, FALSE) -> 15159.59 | O75: =VLOOKUP(I75, Sheet2!$A$1:$D$78, 4, FALSE) -> 15159.59 | P75: =N75-O75 -> 0 | Q75: =VLOOKUP(I75, Sheet2!$A$1:$E$78, 5, FALSE) -> 0.1067492 | R75: =VLOOKUP($L75, '[3]BNP Borrowing Base PSLF JV (PIF'!$A$8:$AI$181, 11, FALSE) -> 0.0625 | S75: =VLOOKUP($L75, '[3]BNP Borrowing Base PSLF JV (PIF'!$A$8:$AI$181, 20, FALSE) -> 45716 | T75: =VLOOKUP($L75, '[3]BNP Borrowing Base PSLF JV (PIF'!$A$8:$AI$181, 22, FALSE) -> 4.0486434 | U75: =VLOOKUP($L75, '[3]BNP Borrowing Base PSLF JV (PIF'!$A$8:$AI$181, 23, FALSE) -> 38.704323 | V75: =VLOOKUP($L75, '[3]BNP Borrowing Base PSLF JV (PIF'!$A$8:$AI$181, 32, FALSE) -> 6.0923427 | W75: =VLOOKUP($L75, '[3]BNP Borrowing Base PSLF JV (PIF'!$A$8:$AI$181, 34, FALSE) -> 1.3027897
A76: Zips Car Wash LLC | B76: 8577681.2 | D76: Zips Car Wash LLC | E76: 8577681.2 | F76: =VLOOKUP(D76, $J$4:$K$79, 2, FALSE) -> Zips Car Wash, LLC | I76: LAV Gear Holdings, Inc. - Incremental TL | J76: LAV Gear Holdings Inc | K76: LAV Gear Holdings, Inc. | L76: LAV Gear Holdings, Inc. | M76: =VLOOKUP(J76, $D$4:$E$78, 2, FALSE) -> 300766.91 | N76: =VLOOKUP(K76, 'Loan List '!$A$6:$H$82, 8, FALSE) -> 300766.91 | O76: =VLOOKUP(I76, Sheet2!$A$1:$D$78, 4, FALSE) -> 300766.91 | P76: =N76-O76 -> 0 | Q76: =VLOOKUP(I76, Sheet2!$A$1:$E$78, 5, FALSE) -> 0.1 | R76: =VLOOKUP($L76, '[3]BNP Borrowing Base PSLF JV (PIF'!$A$8:$AI$181, 11, FALSE) -> 0.0625 | S76: =VLOOKUP($L76, '[3]BNP Borrowing Base PSLF JV (PIF'!$A$8:$AI$181, 20, FALSE) -> 45747 | T76: =VLOOKUP($L76, '[3]BNP Borrowing Base PSLF JV (PIF'!$A$8:$AI$181, 22, FALSE) -> 7.8890552 | U76: =VLOOKUP($L76, '[3]BNP Borrowing Base PSLF JV (PIF'!$A$8:$AI$181, 23, FALSE) -> 60.12 | V76: =VLOOKUP($L76, '[3]BNP Borrowing Base PSLF JV (PIF'!$A$8:$AI$181, 32, FALSE) -> 8.3705921 | W76: =VLOOKUP($L76, '[3]BNP Borrowing Base PSLF JV (PIF'!$A$8:$AI$181, 34, FALSE) -> 1.0521342
A77: Grand Total | B77: 4.1352401e+08 | I77: Boss Industries, LLC | J77: Boss Industries LLC | K77: Boss Industries | L77: Boss Industries | M77: =VLOOKUP(J77, $D$4:$E$78, 2, FALSE) -> 5985000 | N77: =VLOOKUP(K77, 'Loan List '!$A$6:$H$82, 8, FALSE) -> 5985000 | O77: =VLOOKUP(I77, Sheet2!$A$1:$D$78, 4, FALSE) -> 5985000 | P77: =N77-O77 -> 0 | Q77: =VLOOKUP(I77, Sheet2!$A$1:$E$78, 5, FALSE) -> 0.0929917 | R77: =VLOOKUP($L77, '[3]BNP Borrowing Base PSLF JV (PIF'!$A$8:$AI$181, 11, FALSE) -> 0.05 | S77: =VLOOKUP($L77, '[3]BNP Borrowing Base PSLF JV (PIF'!$A$8:$AI$181, 20, FALSE) -> 45747 | T77: =VLOOKUP($L77, '[3]BNP Borrowing Base PSLF JV (PIF'!$A$8:$AI$181, 22, FALSE) -> 3.4876876 | U77: =VLOOKUP($L77, '[3]BNP Borrowing Base PSLF JV (PIF'!$A$8:$AI$181, 23, FALSE) -> 11.396799 | V77: =VLOOKUP($L77, '[3]BNP Borrowing Base PSLF JV (PIF'!$A$8:$AI$181, 32, FALSE) -> 3.4876876 | W77: =VLOOKUP($L77, '[3]BNP Borrowing Base PSLF JV (PIF'!$A$8:$AI$181, 34, FALSE) -> 2.3974644
I78: Project Granite Buyer, Inc. | J78: Project Granite Buyer Inc | K78: Tranzact | L78: Tranzact | M78: =VLOOKUP(J78, $D$4:$E$78, 2, FALSE) -> 5985000 | N78: =VLOOKUP(K78, 'Loan List '!$A$6:$H$82, 8, FALSE) -> 5985000 | O78: =VLOOKUP(I78, Sheet2!$A$1:$D$78, 4, FALSE) -> 5985000 | P78: =N78-O78 -> 0 | Q78: =VLOOKUP(I78, Sheet2!$A$1:$E$78, 5, FALSE) -> 0.1004917 | R78: =VLOOKUP($L78, '[3]BNP Borrowing Base PSLF JV (PIF'!$A$8:$AI$181, 11, FALSE) -> 0.0575 | S78: =VLOOKUP($L78, '[3]BNP Borrowing Base PSLF JV (PIF'!$A$8:$AI$181, 20, FALSE) -> 45716 | T78: =VLOOKUP($L78, '[3]BNP Borrowing Base PSLF JV (PIF'!$A$8:$AI$181, 22, FALSE) -> 1.6513784 | U78: =VLOOKUP($L78, '[3]BNP Borrowing Base PSLF JV (PIF'!$A$8:$AI$181, 23, FALSE) -> 120.21533 | V78: =VLOOKUP($L78, '[3]BNP Borrowing Base PSLF JV (PIF'!$A$8:$AI$181, 32, FALSE) -> 1.6513784 | W78: =VLOOKUP($L78, '[3]BNP Borrowing Base PSLF JV (PIF'!$A$8:$AI$181, 34, FALSE) -> 3.3622621
I79: Ro Health, LLC | J79: Ro Health LLC | K79: Ro Health | L79: Ro Health | M79: =VLOOKUP(J79, $D$4:$E$78, 2, FALSE) -> 10000000 | N79: =VLOOKUP(K79, 'Loan List '!$A$6:$H$82, 8, FALSE) -> 10000000 | O79: =VLOOKUP(I79, Sheet2!$A$1:$D$78, 4, FALSE) -> 10000000 | P79: =N79-O79 -> 0 | Q79: =VLOOKUP(I79, Sheet2!$A$1:$E$78, 5, FALSE) -> 0.0929917 | R79: =VLOOKUP($L79, '[3]BNP Borrowing Base PSLF JV (PIF'!$A$8:$AI$181, 11, FALSE) -> 0.05 | S79: =VLOOKUP($L79, '[3]BNP Borrowing Base PSLF JV (PIF'!$A$8:$AI$181, 20, FALSE) -> 45716 | T79: =VLOOKUP($L79, '[3]BNP Borrowing Base PSLF JV (PIF'!$A$8:$AI$181, 22, FALSE) -> 3.6617534 | U79: =VLOOKUP($L79, '[3]BNP Borrowing Base PSLF JV (PIF'!$A$8:$AI$181, 23, FALSE) -> 20.7734 | V79: =VLOOKUP($L79, '[3]BNP Borrowing Base PSLF JV (PIF'!$A$8:$AI$181, 32, FALSE) -> 3.6617534 | W79: =VLOOKUP($L79, '[3]BNP Borrowing Base PSLF JV (PIF'!$A$8:$AI$181, 34, FALSE) -> 2.7771925

Sheet Sheet2
A1: DESCRIPTION | B1: Investment Family | C1: Concatenate | D1: UNITS (IN USD UNLESS OTHERWISE NOTED)
A2: A1 Garage Merger Sub, LLC | B2: A1 Garage Merger Sub, LLC | C2: 47109A1 Garage Merger Sub, LLC | D2: 3192037.3 | E2: 0.090083815
A3: AFC - Dell Holding Corp. | B3: AFC - Dell Holding Corp. | C3: 46486AFC - Dell Holding Corp. | D3: 269595.42 | E3: 0.097908
A4: Alpine Acquisition Corp II | B4: Alpine Acquisition Corp II | C4: 46356Alpine Acquisition Corp II | D4: 3958430.6 | E4: 0.1042
A5: Amsive Holding Corporation (f/k/a Vision Purchaser Corporation) | B5: Amsive Holding Corporation (f/k/a Vision Purchaser Corporation) | C5: 45818Amsive Holding Corporation (f/k/a Vision Purchaser Corporation) | D5: 15159.59 | E5: 0.1067492
A6: Arcfield Acquisition Corp. | B6: Arcfield Acquisition Corp. | C6: 48149Arcfield Acquisition Corp. | D6: 2320875 | E6: 0.092998
A7: Archer Lewis, LLC | B7: Archer Lewis, LLC | C7: 47358Archer Lewis, LLC | D7: 8816867.8 | E7: 0.10051621
A8: Argano, LLC | B8: Argano, LLC | C8: 47374Argano, LLC | D8: 5472500 | E8: 0.100664
A9: BLC Holding Company, INC. | B9: BLC Holding Company, INC. | C9: 47807BLC Holding Company, INC. | D9: 2098550.6 | E9: 0.090492
A10: Beacon Behavioral Support Services, LLC | B10: Beacon Behavioral Support Services, LLC | C10: 47290Beacon Behavioral Support Services, LLC | D10: 12170103 | E10: 0.098011024
A11: Best Practice Associates, LLC | B11: Best Practice Associates, LLC | C11: 47430Best Practice Associates, LLC | D11: 6981437.5 | E11: 0.1104917
A12: Blackhawk Industrial Distribution, Inc. | B12: Blackhawk Industrial Distribution, Inc. | C12: 46282Blackhawk Industrial Distribution, Inc. | D12: 8653790.5 | E12: 0.096992704
A13: BlueHalo Global Holdings, LLC | B13: BlueHalo Global Holdings, LLC | C13: 45961BlueHalo Global Holdings, LLC | D13: 2628762.5 | E13: 0.1029917
... A76: Zips Car Wash, LLC | B76: Zips Car Wash, LLC | C76: 46843Zips Car Wash, LLC | D76: 8577681.3 | E76: 0
A77: New Insight Holdings, Inc. - Common Equity | B77: Dynata, LLC | C77: New Insight Holdings, Inc. - Common Equity | D77: 79339
A78: 48Forty Intermediate Holdings, Inc.- Common Equity | B78: 48Forty Intermediate Holdings, Inc.- Common Equity | C78: 48Forty Intermediate Holdings, Inc.- Common Equity | D78: 522.15

Sheet Loan List 
A5: Issuer Name | B5: Admin Agent | C5: As of Date | D5: Portfolio Name | E5: Security Name | F5: Loan number | G5: Facility Name | H5: OutstandingAmount | I5: LoanX Id / CUSIP | J5: Currency | K5: Loan Type (Underlying Structure) | L5: S&P Industry | M5: Fixed/Float | N5: Coupon | O5: SOFR/LIBOR Index | P5: LIBOR/SOFR Floor | Q5: Spread | R5: Payment Freq (1=monthly, 3=quarterly) | S5: Default Date | T5: Seniority | U5: Average Life | V5: Maturity Date | W5: Obligor Domicile | X5: Purchase Price | Y5: Market Price | Z5: Sale Price | AA5: Tranche Size (at acquisition) | AB5: EBITDA (at acquisition) | AC5: Cash Interest Coverage Ratio (at acquisition) | AD5: Senior Net Leverage Ratio (at acquisition) | AE5: Revenue (at acquisition) | AF5: Total Leverage Ratio (at acquisition) | AG5: Date of Latest Financial Reporting | AH5: ABL / FO Lev Ratio | AI5: Net Senior Lev Ratio | AJ5: EBITDA ($m) | AK5: Change in Net Senior Lev Ratio Since Acquisition | AL5: Revenue (current) | AM5: Total Leverage Ratio (current) | AN5: Change in Total Lev Ratio Since Acquisition | AO5: Cash Interest Coverage Ratio (current) | AP5: Change in Cash Interest Coverage Ratio Since Acquisition | AQ5: Global Original Facility | AR5: Global Bank Deal | AS5: Covenant Type | AT5: Covenant Lite | AU5: Recurring Revenue | AV5: Firm Asset ID/ ISIN | AW5: Status | AX5: Par Balance (Unadjusted for PIK) | AY5: PIK Amount | AZ5: Principal Balance (Adjusted for PIK) | BA5: Partial PIK | BB5: Eligible Collateral Loan | BC5: Revaluation Event | BD5: Assigned MV | BE5: Not First Lien | BF5: FLLO or 2L | BG5: Second Lien | BH5: Non-USD | BI5: Non-US Domiciled | BJ5: EBITDA < 15mm | BK5: EBITDA < $10mm | BL5: Partial PIK | BM5: Covenant Lite | BN5: Senior Net Lev > 5.5x | BO5: Fixed Rate | BP5: Recurring Revenue | BQ5: Purchase Market Value | BR5: Adjusted Collateral Value | BS5: Adjusted Principal Balance | BT5: Excess Concentrations | BU5: Net Principal Balance | BV5: Sale Proceeds | BW5: EBITDA Bucket | BX5: ABL / FO Bucket | BY5: Designated FL | BZ5: AR Category
A6: A1 Garage Merger Sub, LLC | C6: 45777 | D6: PennantPark Investment Funding I | E6: A1 Garage (Term Loan) | F6: PNNT 1 | G6: First Lien | H6: =AX6 -> 3192037.3 | J6: USD | K6: FL | L6: Energy Equipment & Services | M6: Float | N6: =+VLOOKUP($A6, [2]Sheet2!$M$3:$Z$76, 14, FALSE) -> 0.090749 | O6: SOFR | P6: 0.01 | Q6: =+VLOOKUP($A6, [2]Sheet2!$M$3:$Z$76, 13, FALSE) -> 0.0475 | R6: 3 | T6: Senior Secured | U6: =YEARFRAC(C6,V6) -> 3.6444444 | V6: 47109 | W6: USA | X6: 100 | AB6: 26.53 | AC6: 1.8629212 | AD6: 4.9219777 | AF6: 4.9219777 | AG6: =+VLOOKUP($A6, [2]Sheet2!$M$3:$X$76, 8, FALSE) -> 45716 | AI6: =+VLOOKUP($A6, [2]Sheet2!$M$3:$X$76, 9, FALSE) -> 2.3958956 | AJ6: =+VLOOKUP($A6, [2]Sheet2!$M$3:$X$76, 10, FALSE) -> 60.907 | AK6: =AD6-AI6 -> 2.5260821 | AM6: =+VLOOKUP($A6, [2]Sheet2!$M$3:$X$76, 11, FALSE) -> 2.3958956 | AN6: =AF6-AM6 -> 2.5260821 | AO6: =+VLOOKUP($A6, [2]Sheet2!$M$3:$X$76, 12, FALSE) -> 3.1669615 | AP6: =AC6-AO6 -> -1.3040403 | AS6: Maintenance Covenants | AT6: No | AU6: No | AW6: SETTLED | AX6: 3192037.3 | AZ6: =+AX6-AY6 -> 3192037.3 | BB6: Y | BC6: N | BD6: 100 | BE6: =IF(LEFT(BZ6,3)="FL ",0,1) -> 0 | BF6: =IF(OR(J6="FLLO",L6="2L"),1,0) -> 0 | BG6: =IF(L6="2L",1,0) -> 0 | BH6: =IF(J6="USD",0,1) -> 0 | BI6: =IF(W6="USA",0,1) -> 0 | BJ6: =IF(AJ6<15,1,0) -> 0 | BK6: =IF(AJ6<10,1,0) -> 0 | BL6: =IF(BA6="Yes",1,0) -> 0 | BM6: =IF(AT6="Yes",1,0) -> 0 | BN6: =IF(AI6>5.5,1,0) -> 0 | BO6: =IF(M6="Fixed",1,0) -> 0 | BP6: =IF(AU6="Yes",1,0) -> 0 | BQ6: =H6 -> 3192037.3 | BR6: 100 | BS6: =BR6*AZ6/100 -> 3192037.3 | BU6: =BS6-BT6 -> 3192037.3 | BV6: 0 | BW6: =IF(LEN(AJ6)=0,"EBITDA missing",IF(AJ6>10000,"EBITDA bad",IF(AJ6<=15,"15-",IF(AJ6>=30,"30+","15-30")))) -> 30+ | BX6: =IF(AE6<=0.25,"<0.25",IF(AE6>1.5,">1.50","0.25-1.50")) -> <0.25 | BZ6: =IF(K6="FL",K6&" "&BW6,IF(K6="FLLO",IF(OR(BX6="<0.25",BY6="FL"),"FL"&" "&BW6,K6&" "&BX6),K6)) -> FL 30+
A7: AFC - Dell Holding Corp. | C7: 45777 | D7: PennantPark Investment Funding I | E7: AFC Industries (TL) | F7: PNNT 4 | G7: First Lien | H7: 269595.42 | J7: USD | K7: FL | L7: Distributors | M7: Float | N7: =+VLOOKUP(A7, [2]Sheet2!$M$3:$Z$76, 14, FALSE) -> 0.09807844 | O7: SOFR | P7: 0.01 | Q7: =+VLOOKUP($A7, [2]Sheet2!$M$3:$Z$76, 13, FALSE) -> 0.055 | R7: 3 | T7: Senior Secured | U7: =YEARFRAC(C7,V7) -> 1.9416667 | V7: 46486 | W7: USA | X7: 100 | AB7: 62.582178 | AC7: 1.604889 | AD7: 5.5133081 | AF7: 5.5133081 | AG7: =+VLOOKUP($A7, [2]Sheet2!$M$3:$X$76, 8, FALSE) -> 45716 | AI7: =+VLOOKUP(A7, [2]Sheet2!$M$3:$X$76, 9, FALSE) -> 6.0802911 | AJ7: =+VLOOKUP($A7, [2]Sheet2!$M$3:$X$76, 10, FALSE) -> 76.694092 | AK7: =AD7-AI7 -> -0.56698301 | AM7: =+VLOOKUP($A7, [2]Sheet2!$M$3:$X$76, 11, FALSE) -> 7.1419735 | AN7: =AF7-AM7 -> -1.6286654 | AO7: =+VLOOKUP($A7, [2]Sheet2!$M$3:$X$76, 12, FALSE) -> 1.3690869 | AP7: =AC7-AO7 -> 0.23580212 | AS7: Cov-Lite | AT7: Yes | AU7: No | AW7: SETTLED | AX7: 269595.42 | AZ7: =+AX7-AY7 -> 269595.42 | BB7: Y | BC7: N | BD7: 100 | BE7: =IF(LEFT(BZ7,3)="FL ",0,1) -> 0 | BF7: =IF(OR(J7="FLLO",L7="2L"),1,0) -> 0 | BG7: =IF(L7="2L",1,0) -> 0 | BH7: =IF(J7="USD",0,1) -> 0 | BI7: =IF(W7="USA",0,1) -> 0 | BJ7: =IF(AJ7<15,1,0) -> 0 | BK7: =IF(AJ7<10,1,0) -> 0 | BL7: =IF(BA7="Yes",1,0) -> 0 | BM7: =IF(AT7="Yes",1,0) -> 1 | BN7: =IF(AI7>5.5,1,0) -> 1 | BO7: =IF(M7="Fixed",1,0) -> 0 | BP7: =IF(AU7="Yes",1,0) -> 0 | BQ7: =H7 -> 269595.42 | BR7: 100 | BS7: =BR7*AZ7/100 -> 269595.42 | BU7: =BS7-BT7 -> 269595.42 | BV7: 0 | BW7: =IF(LEN(AJ7)=0,"EBITDA missing",IF(AJ7>10000,"EBITDA bad",IF(AJ7<=15,"15-",IF(AJ7>=30,"30+","15-30")))) -> 30+ | BX7: =IF(AE7<=0.25,"<0.25",IF(AE7>1.5,">1.50","0.25-1.50")) -> <0.25 | BZ7: =IF(K7="FL",K7&" "&BW7,IF(K7="FLLO",IF(OR(BX7="<0.25",BY7="FL"),"FL"&" "&BW7,K7&" "&BX7),K7)) -> FL 30+
A8: Alpine Acquisition Corp II | C8: 45777 | D8: PennantPark Investment Funding I | E8: 48Forty (Term Loan) | F8: PNNT 7 | G8: First Lien | H8: 3933327.4 | J8: USD | K8: FL | L8: Containers and Packaging | M8: Float | N8: =+VLOOKUP(A8, [2]Sheet2!$M$3:$Z$76, 14, FALSE) -> 0.104227 | O8: SOFR | P8: 0.01 | Q8: =+VLOOKUP($A8, [2]Sheet2!$M$3:$Z$76, 13, FALSE) -> 0.061 | R8: 3 | T8: Senior Secured | U8: =YEARFRAC(C8,V8) -> 1.5833333 | V8: 46356 | W8: USA | X8: 100 | AB8: 283.8 | AC8: 2.65 | AD8: 5.41 | AF8: 5.45 | AG8: =+VLOOKUP($A8, [2]Sheet2!$M$3:$X$76, 8, FALSE) -> 45688 | AI8: =+VLOOKUP(A8, [2]Sheet2!$M$3:$X$76, 9, FALSE) -> 16.797918 | AJ8: =+VLOOKUP($A8, [2]Sheet2!$M$3:$X$76, 10, FALSE) -> 109.297 | AK8: =AD8-AI8 -> -11.387918 | AM8: =+VLOOKUP($A8, [2]Sheet2!$M$3:$X$76, 11, FALSE) -> 17.284976 | AN8: =AF8-AM8 -> -11.834976 | AO8: =+VLOOKUP($A8, [2]Sheet2!$M$3:$X$76, 12, FALSE) -> 0.66578745 | AP8: =AC8-AO8 -> 1.9842125 | AS8: Maintenance Covenants | AT8: No | AU8: No | AW8: SETTLED | AX8: 3933849.6 | AZ8: =+AX8-AY8 -> 3933849.6 | BB8: Y | BC8: Y | BD8: 0 | BE8: =IF(LEFT(BZ8,3)="FL ",0,1) -> 0 | BF8: =IF(OR(J8="FLLO",L8="2L"),1,0) -> 0 | BG8: =IF(L8="2L",1,0) -> 0 | BH8: =IF(J8="USD",0,1) -> 0 | BI8: =IF(W8="USA",0,1) -> 0 | BJ8: =IF(AJ8<15,1,0) -> 0 | BK8: =IF(AJ8<10,1,0) -> 0 | BL8: =IF(BA8="Yes",1,0) -> 0 | BM8: =IF(AT8="Yes",1,0) -> 0 | BN8: =IF(AI8>5.5,1,0) -> 1 | BO8: =IF(M8="Fixed",1,0) -> 0 | BP8: =IF(AU8="Yes",1,0) -> 0 | BQ8: =H8 -> 3933327.4 | BR8: 0 | BS8: =BR8*AZ8/100 -> 0 | BU8: =BS8-BT8 -> 0 | BV8: 0 | BW8: =IF(LEN(AJ8)=0,"EBITDA missing",IF(AJ8>10000,"EBITDA bad",IF(AJ8<=15,"15-",IF(AJ8>=30,"30+","15-30")))) -> 30+ | BX8: =IF(AE8<=0.25,"<0.25",IF(AE8>1.5,">1.50","0.25-1.50")) -> <0.25 | BZ8: =IF(K8="FL",K8&" "&BW8,IF(K8="FLLO",IF(OR(BX8="<0.25",BY8="FL"),"FL"&" "&BW8,K8&" "&BX8),K8)) -> FL 30+
A9: Archer Lewis | C9: 45777 | D9: PennantPark Investment Funding I | E9: Archer Lewis (Term Loan) | F9: PNNT 87 | G9: First Lien | H9: 8816867.8 | J9: USD | K9: FL | L9: Diversified Financial Services | M9: Float | N9: =+VLOOKUP(A9, [2]Sheet2!$M$3:$Z$76, 14, FALSE) -> 0.10050563 | O9: SOFR | P9: 0.01 | Q9: =+VLOOKUP($A9, [2]Sheet2!$M$3:$Z$76, 13, FALSE) -> 0.0575 | R9: 3 | T9: Senior Secured | U9: =YEARFRAC(C9,V9) -> 4.3277778 | V9: 47358 | W9: USA | X9: 100 | AB9: 11.028693 | AC9: 2.4621136 | AD9: 2.8065192 | AF9: 2.8065192 | AG9: =+VLOOKUP($A9, [2]Sheet2!$M$3:$X$76, 8, FALSE) -> 45688 | AI9: =+VLOOKUP(A9, [2]Sheet2!$M$3:$X$76, 9, FALSE) -> 5.1697289 | AJ9: =+VLOOKUP($A9, [2]Sheet2!$M$3:$X$76, 10, FALSE) -> 11.193527 | AK9: =AD9-AI9 -> -2.3632097 | AM9: =+VLOOKUP($A9, [2]Sheet2!$M$3:$X$76, 11, FALSE) -> 5.1697289 | AN9: =AF9-AM9 -> -2.3632097 | AO9: =+VLOOKUP($A9, [2]Sheet2!$M$3:$X$76, 12, FALSE) -> 2.4989121 | AP9: =AC9-AO9 -> -0.036798557 | AS9: Maintenance Covenants | AT9: No | AU9: No | AW9: SETTLED | AX9: 8816867.8 | AZ9: =+AX9-AY9 -> 8816867.8 | BB9: Y | BC9: N | BD9: 100 | BE9: =IF(LEFT(BZ9,3)="FL ",0,1) -> 0 | BF9: =IF(OR(J9="FLLO",L9="2L"),1,0) -> 0 | BG9: =IF(L9="2L",1,0) -> 0 | BH9: =IF(J9="USD",0,1) -> 0 | BI9: =IF(W9="USA",0,1) -> 0 | BJ9: =IF(AJ9<15,1,0) -> 1 | BK9: =IF(AJ9<10,1,0) -> 0 | BL9: =IF(BA9="Yes",1,0) -> 0 | BM9: =IF(AT9="Yes",1,0) -> 0 | BN9: =IF(AI9>5.5,1,0) -> 0 | BO9: =IF(M9="Fixed",1,0) -> 0 | BP9: =IF(AU9="Yes",1,0) -> 0 | BQ9: =H9 -> 8816867.8 | BR9: 100 | BS9: =BR9*AZ9/100 -> 8816867.8 | BU9: =BS9-BT9 -> 8816867.8 | BV9: 0 | BW9: =IF(LEN(AJ9)=0,"EBITDA missing",IF(AJ9>10000,"EBITDA bad",IF(AJ9<=15,"15-",IF(AJ9>=30,"30+","15-30")))) -> 15- | BX9: =IF(AE9<=0.25,"<0.25",IF(AE9>1.5,">1.50","0.25-1.50")) -> <0.25 | BZ9: =IF(K9="FL",K9&" "&BW9,IF(K9="FLLO",IF(OR(BX9="<0.25",BY9="FL"),"FL"&" "&BW9,K9&" "&BX9),K9)) -> FL 15-
A10: Argano, LLC | C10: 45777 | D10: PennantPark Investment Funding I | E10: Argano (Term Loan) | F10: PNNT 93 | G10: First Lien | H10: 5472500 | J10: USD | K10: FL | L10: IT Services | M10: Float | N10: =+VLOOKUP(A10, [2]Sheet2!$M$3:$Z$76, 14, FALSE) -> 0.100664 | O10: SOFR | P10: 0.01 | Q10: =+VLOOKUP($A10, [2]Sheet2!$M$3:$Z$76, 13, FALSE) -> 0.0575 | R10: 3 | T10: Senior Secured | U10: =YEARFRAC(C10,V10) -> 4.3694444 | V10: 47374 | W10: USA | X10: 100 | AB10: 63.670152 | AC10: 1.4685834 | AD10: 3.6605579 | AF10: 6.1788209 | AG10: =+VLOOKUP($A10, [2]Sheet2!$M$3:$X$76, 8, FALSE) -> 45688 | AI10: =+VLOOKUP(A10, [2]Sheet2!$M$3:$X$76, 9, FALSE) -> 3.8370896 | AJ10: =+VLOOKUP($A10, [2]Sheet2!$M$3:$X$76, 10, FALSE) -> 62.994302 | AK10: =AD10-AI10 -> -0.17653168 | AM10: =+VLOOKUP($A10, [2]Sheet2!$M$3:$X$76, 11, FALSE) -> 6.2182573 | AN10: =AF10-AM10 -> -0.039436426 | AO10: =+VLOOKUP($A10, [2]Sheet2!$M$3:$X$76, 12, FALSE) -> 1.5420309 | AP10: =AC10-AO10 -> -0.0734475 | AS10: Maintenance Covenants | AT10: No | AU10: No | AW10: SETTLED | AX10: 5472500 | AZ10: =+AX10-AY10 -> 5472500 | BB10: Y | BC10: N | BD10: 100 | BE10: =IF(LEFT(BZ10,3)="FL ",0,1) -> 0 | BF10: =IF(OR(J10="FLLO",L10="2L"),1,0) -> 0 | BG10: =IF(L10="2L",1,0) -> 0 | BH10: =IF(J10="USD",0,1) -> 0 | BI10: =IF(W10="USA",0,1) -> 0 | BJ10: =IF(AJ10<15,1,0) -> 0 | BK10: =IF(AJ10<10,1,0) -> 0 | BL10: =IF(BA10="Yes",1,0) -> 0 | BM10: =IF(AT10="Yes",1,0) -> 0 | BN10: =IF(AI10>5.5,1,0) -> 0 | BO10: =IF(M10="Fixed",1,0) -> 0 | BP10: =IF(AU10="Yes",1,0) -> 0 | BQ10: =H10 -> 5472500 | BR10: 100 | BS10: =BR10*AZ10/100 -> 5472500 | BU10: =BS10-BT10 -> 5472500 | BV10: 0 | BW10: =IF(LEN(AJ10)=0,"EBITDA missing",IF(AJ10>10000,"EBITDA bad",IF(AJ10<=15,"15-",IF(AJ10>=30,"30+","15-30")))) -> 30+ | BX10: =IF(AE10<=0.25,"<0.25",IF(AE10>1.5,">1.50","0.25-1.50")) -> <0.25 | BZ10: =IF(K10="FL",K10&" "&BW10,IF(K10="FLLO",IF(OR(BX10="<0.25",BY10="FL"),"FL"&" "&BW10,K10&" "&BX10),K10)) -> FL 30+
A11: BBB Industries | C11: 45777 | D11: PennantPark Investment Funding I | E11: BBB Industries (First Lien Term Loan) | F11: PNNT 10 | G11: First Lien | H11: 248327.5 | J11: USD | K11: FL | L11: Automobiles | M11: Float | N11: =+VLOOKUP(A11, [2]Sheet2!$M$3:$Z$76, 14, FALSE) -> 0.096492 | O11: SOFR | P11: 0.005 | Q11: =+VLOOKUP($A11, [2]Sheet2!$M$3:$Z$76, 13, FALSE) -> 0.0535 | R11: 3 | T11: Senior Secured | U11: =YEARFRAC(C11,V11) -> 4.2361111 | V11: 47324 | W11: USA | X11: 93 | AB11: 241.8 | AC11: 2.1552003 | AD11: 5.0469961 | AF11: 6.5151516 | AG11: =+VLOOKUP($A11, [2]Sheet2!$M$3:$X$76, 8, FALSE) -> 45565 | AI11: =+VLOOKUP(A11, [2]Sheet2!$M$3:$X$76, 9, FALSE) -> 5.6274247 | AJ11: =+VLOOKUP($A11, [2]Sheet2!$M$3:$X$76, 10, FALSE) -> 299 | AK11: =AD11-AI11 -> -0.58042866 | AM11: =+VLOOKUP($A11, [2]Sheet2!$M$3:$X$76, 11, FALSE) -> 6.8197324 | AN11: =AF11-AM11 -> -0.30458085 | AO11: =+VLOOKUP($A11, [2]Sheet2!$M$3:$X$76, 12, FALSE) -> 1.3906977 | AP11: =AC11-AO11 -> 0.76450259 | AS11: Cov-Lite | AT11: Yes | AU11: No | AW11: SETTLED | AX11: 248327.5 | AZ11: =+AX11-AY11 -> 248327.5 | BB11: Y | BC11: Y | BD11: 93 | BE11: =IF(LEFT(BZ11,3)="FL ",0,1) -> 0 | BF11: =IF(OR(J11="FLLO",L11="2L"),1,0) -> 0 | BG11: =IF(L11="2L",1,0) -> 0 | BH11: =IF(J11="USD",0,1) -> 0 | BI11: =IF(W11="USA",0,1) -> 0 | BJ11: =IF(AJ11<15,1,0) -> 0 | BK11: =IF(AJ11<10,1,0) -> 0 | BL11: =IF(BA11="Yes",1,0) -> 0 | BM11: =IF(AT11="Yes",1,0) -> 1 | BN11: =IF(AI11>5.5,1,0) -> 1 | BO11: =IF(M11="Fixed",1,0) -> 0 | BP11: =IF(AU11="Yes",1,0) -> 0 | BQ11: =H11 -> 248327.5 | BR11: 93 | BS11: =BR11*AZ11/100 -> 230944.58 | BU11: =BS11-BT11 -> 230944.58 | BV11: 0 | BW11: =IF(LEN(AJ11)=0,"EBITDA missing",IF(AJ11>10000,"EBITDA bad",IF(AJ11<=15,"15-",IF(AJ11>=30,"30+","15-30")))) -> 30+ | BX11: =IF(AE11<=0.25,"<0.25",IF(AE11>1.5,">1.50","0.25-1.50")) -> <0.25 | BZ11: =IF(K11="FL",K11&" "&BW11,IF(K11="FLLO",IF(OR(BX11="<0.25",BY11="FL"),"FL"&" "&BW11,K11&" "&BX11),K11)) -> FL 30+
A12: Beacon Behavioral Support Services, LLC | C12: 45777 | D12: PennantPark Investment Funding I | E12: Beacon Behavioral (Term Loan) | F12: PNNT 75 | G12: First Lien | H12: 12170103 | J12: USD | K12: FL | L12: Health Care Providers & Services | M12: Float | N12: =+VLOOKUP(A12, [2]Sheet2!$M$3:$Z$76, 14, FALSE) -> 0.098032852 | O12: SOFR | P12: 0.01 | Q12: =+VLOOKUP($A12, [2]Sheet2!$M$3:$Z$76, 13, FALSE) -> 0.055 | R12: 3 | T12: Senior Secured | U12: =YEARFRAC(C12,V12) -> 4.1416667 | V12: 47290 | W12: USA | X12: 100 | AB12: 18.21 | AC12: 4.25 | AD12: 3.7 | AF12: 4.27 | AG12: =+VLOOKUP($A12, [2]Sheet2!$M$3:$X$76, 8, FALSE) -> 45688 | AI12: =+VLOOKUP(A12, [2]Sheet2!$M$3:$X$76, 9, FALSE) -> 4.9950227 | AJ12: =+VLOOKUP($A12, [2]Sheet2!$M$3:$X$76, 10, FALSE) -> 22.642207 | AK12: =AD12-AI12 -> -1.2950227 | AM12: =+VLOOKUP($A12, [2]Sheet2!$M$3:$X$76, 11, FALSE) -> 5.5571201 | AN12: =AF12-AM12 -> -1.2871201 | AO12: =+VLOOKUP($A12, [2]Sheet2!$M$3:$X$76, 12, FALSE) -> 2.4407488 | AP12: =AC12-AO12 -> 1.8092512 | AS12: Maintenance Covenants | AT12: No | AU12: No | AW12: SETTLED | AX12: 12170103 | AZ12: =+AX12-AY12 -> 12170103 | BB12: Y | BC12: Y | BD12: 100 | BE12: =IF(LEFT(BZ12,3)="FL ",0,1) -> 0 | BF12: =IF(OR(J12="FLLO",L12="2L"),1,0) -> 0 | BG12: =IF(L12="2L",1,0) -> 0 | BH12: =IF(J12="USD",0,1) -> 0 | BI12: =IF(W12="USA",0,1) -> 0 | BJ12: =IF(AJ12<15,1,0) -> 0 | BK12: =IF(AJ12<10,1,0) -> 0 | BL12: =IF(BA12="Yes",1,0) -> 0 | BM12: =IF(AT12="Yes",1,0) -> 0 | BN12: =IF(AI12>5.5,1,0) -> 0 | BO12: =IF(M12="Fixed",1,0) -> 0 | BP12: =IF(AU12="Yes",1,0) -> 0 | BQ12: =H12 -> 12170103 | BR12: 100 | BS12: =BR12*AZ12/100 -> 12170103 | BU12: =BS12-BT12 -> 12170103 | BV12: 0 | BW12: =IF(LEN(AJ12)=0,"EBITDA missing",IF(AJ12>10000,"EBITDA bad",IF(AJ12<=15,"15-",IF(AJ12>=30,"30+","15-30")))) -> 15-30 | BX12: =IF(AE12<=0.25,"<0.25",IF(AE12>1.5,">1.50","0.25-1.50")) -> <0.25 | BZ12: =IF(K12="FL",K12&" "&BW12,IF(K12="FLLO",IF(OR(BX12="<0.25",BY12="FL"),"FL"&" "&BW12,K12&" "&BX12),K12)) -> FL 15-30
A13: BlackHawk Industrial | C13: 45777 | D13: PennantPark Investment Funding I | E13: BlackHawk Industrial (TL) | F13: PNNT 14 | G13: First Lien | H13: 8653790.5 | J13: USD | K13: FL | L13: Distributors | M13: Float | N13: =+VLOOKUP(A13, [2]Sheet2!$M$3:$Z$76, 14, FALSE) -> 0.096993426 | O13: SOFR | P13: 0.01 | Q13: =+VLOOKUP($A13, [2]Sheet2!$M$3:$Z$76, 13, FALSE) -> 0.054 | R13: 3 | T13: Senior Secured | U13: =YEARFRAC(C13,V13) -> 1.3805556 | V13: 46282 | W13: USA | X13: 100 | AB13: 38.43 | AC13: 3.13 | AD13: 4.68 | AF13: 4.68 | AG13: =+VLOOKUP($A13, [2]Sheet2!$M$3:$X$76, 8, FALSE) -> 45716 | AI13: =+VLOOKUP(A13, [2]Sheet2!$M$3:$X$76, 9, FALSE) -> 5.8248222 | AJ13: =+VLOOKUP($A13, [2]Sheet2!$M$3:$X$76, 10, FALSE) -> 51.188 | AK13: =AD13-AI13 -> -1.1448222 | AM13: =+VLOOKUP($A13, [2]Sheet2!$M$3:$X$76, 11, FALSE) -> 6.4096273 | AN13: =AF13-AM13 -> -1.7296273 | AO13: =+VLOOKUP($A13, [2]Sheet2!$M$3:$X$76, 12, FALSE) -> 1.2666221 | AP13: =AC13-AO13 -> 1.8633779 | AS13: Maintenance Covenants | AT13: No | AU13: No | AW13: SETTLED | AX13: 8653790.5 | AZ13: =+AX13-AY13 -> 8653790.5 | BB13: Y | BC13: Y | BD13: 100 | BE13: =IF(LEFT(BZ13,3)="FL ",0,1) -> 0 | BF13: =IF(OR(J13="FLLO",L13="2L"),1,0) -> 0 | BG13: =IF(L13="2L",1,0) -> 0 | BH13: =IF(J13="USD",0,1) -> 0 | BI13: =IF(W13="USA",0,1) -> 0 | BJ13: =IF(AJ13<15,1,0) -> 0 | BK13: =IF(AJ13<10,1,0) -> 0 | BL13: =IF(BA13="Yes",1,0) -> 0 | BM13: =IF(AT13="Yes",1,0) -> 0 | BN13: =IF(AI13>5.5,1,0) -> 1 | BO13: =IF(M13="Fixed",1,0) -> 0 | BP13: =IF(AU13="Yes",1,0) -> 0 | BQ13: =H13 -> 8653790.5 | BR13: 100 | BS13: =BR13*AZ13/100 -> 8653790.5 | BU13: =BS13-BT13 -> 8653790.5 | BV13: 0 | BW13: =IF(LEN(AJ13)=0,"EBITDA missing",IF(AJ13>10000,"EBITDA bad",IF(AJ13<=15,"15-",IF(AJ13>=30,"30+","15-30")))) -> 30+ | BX13: =IF(AE13<=0.25,"<0.25",IF(AE13>1.5,">1.50","0.25-1.50")) -> <0.25 | BZ13: =IF(K13="FL",K13&" "&BW13,IF(K13="FLLO",IF(OR(BX13="<0.25",BY13="FL"),"FL"&" "&BW13,K13&" "&BX13),K13)) -> FL 30+
A14: BlueHalo Financing Holdings, LLC | C14: 45777 | D14: PennantPark Investment Funding I | E14: BlueHalo (Term Loan) | F14: PNNT 15 | G14: First Lien | H14: 2628762.5 | J14: USD | K14: FL | L14: Aerospace & Defense | M14: Float | N14: =+VLOOKUP(A14, [2]Sheet2!$M$3:$Z$76, 14, FALSE) -> 0.10307675 | O14: SOFR | P14: 0.01 | Q14: =+VLOOKUP($A14, [2]Sheet2!$M$3:$Z$76, 13, FALSE) -> 0.06 | R14: 3 | T14: Senior Secured | U14: =YEARFRAC(C14,V14) -> 0.5 | V14: 45961 | W14: USA | X14: 100 | AB14: 57.954 | AC14: 1.9807447 | AD14: 6.9721041 | AF14: 7.084262 | AG14: =+VLOOKUP($A14, [2]Sheet2!$M$3:$X$76, 8, FALSE) -> 45657 | AI14: =+VLOOKUP(A14, [2]Sheet2!$M$3:$X$76, 9, FALSE) -> 7.6702881 | AJ14: =+VLOOKUP($A14, [2]Sheet2!$M$3:$X$76, 10, FALSE) -> 103.7901 | AK14: =AD14-AI14 -> -0.69818402 | AM14: =+VLOOKUP($A14, [2]Sheet2!$M$3:$X$76, 11, FALSE) -> 7.7329145 | AN14: =AF14-AM14 -> -0.64865249 | AO14: =+VLOOKUP($A14, [2]Sheet2!$M$3:$X$76, 12, FALSE) -> 1.5967892 | AP14: =AC14-AO14 -> 0.38395546 | AS14: Maintenance Covenants | AT14: No | AU14: No | AW14: SETTLED | AX14: 2628762.5 | AZ14: =+AX14-AY14 -> 2628762.5 | BB14: Y | BC14: Y | BD14: 100 | BE14: =IF(LEFT(BZ14,3)="FL ",0,1) -> 0 | BF14: =IF(OR(J14="FLLO",L14="2L"),1,0) -> 0 | BG14: =IF(L14="2L",1,0) -> 0 | BH14: =IF(J14="USD",0,1) -> 0 | BI14: =IF(W14="USA",0,1) -> 0 | BJ14: =IF(AJ14<15,1,0) -> 0 | BK14: =IF(AJ14<10,1,0) -> 0 | BL14: =IF(BA14="Yes",1,0) -> 0 | BM14: =IF(AT14="Yes",1,0) -> 0 | BN14: =IF(AI14>5.5,1,0) -> 1 | BO14: =IF(M14="Fixed",1,0) -> 0 | BP14: =IF(AU14="Yes",1,0) -> 0 | BQ14: =H14 -> 2628762.5 | BR14: 100 | BS14: =BR14*AZ14/100 -> 2628762.5 | BU14: =BS14-BT14 -> 2628762.5 | BV14: 0 | BW14: =IF(LEN(AJ14)=0,"EBITDA missing",IF(AJ14>10000,"EBITDA bad",IF(AJ14<=15,"15-",IF(AJ14>=30,"30+","15-30")))) -> 30+ | BX14: =IF(AE14<=0.25,"<0.25",IF(AE14>1.5,">1.50","0.25-1.50")) -> <0.25 | BZ14: =IF(K14="FL",K14&" "&BW14,IF(K14="FLLO",IF(OR(BX14="<0.25",BY14="FL"),"FL"&" "&BW14,K14&" "&BX14),K14)) -> FL 30+
A15: C5MI Acquisition, LLC | C15: 45777 | D15: PennantPark Investment Funding I | E15: C5MI Acquisition LLC First Lien Term Loan T - CF | F15: PNNT 81 | G15: First Lien | H15: 1492500 | J15: USD | K15: FL | L15: IT Services | M15: Float | N15: =+VLOOKUP(A15, [2]Sheet2!$M$3:$Z$76, 14, FALSE) -> 0.102992 | O15: SOFR | P15: 0.01 | Q15: =+VLOOKUP($A15, [2]Sheet2!$M$3:$Z$76, 13, FALSE) -> 0.06 | R15: 3 | T15: Senior Secured | U15: =YEARFRAC(C15,V15) -> 4.25 | V15: 47330 | W15: USA | X15: 100 | AB15: 19.728528 | AC15: 2.1230412 | AD15: 3.9042799 | AF15: 4.2438896 | AG15: =+VLOOKUP($A15, [2]Sheet2!$M$3:$X$76, 8, FALSE) -> 45657 | AI15: =+VLOOKUP(A15, [2]Sheet2!$M$3:$X$76, 9, FALSE) -> 4.1226116 | AJ15: =+VLOOKUP($A15, [2]Sheet2!$M$3:$X$76, 10, FALSE) -> 19.426834 | AK15: =AD15-AI15 -> -0.21833171 | AM15: =+VLOOKUP($A15, [2]Sheet2!$M$3:$X$76, 11, FALSE) -> 4.4674954 | AN15: =AF15-AM15 -> -0.22360576 | AO15: =+VLOOKUP($A15, [2]Sheet2!$M$3:$X$76, 12, FALSE) -> 2.1580575 | AP15: =AC15-AO15 -> -0.03501635 | AS15: Maintenance Covenants | AT15: No | AU15: No | AW15: SETTLED | AX15: 1492500 | AZ15: =+AX15-AY15 -> 1492500 | BB15: Y | BC15: N | BD15: 100 | BE15: =IF(LEFT(BZ15,3)="FL ",0,1) -> 0 | BF15: =IF(OR(J15="FLLO",L15="2L"),1,0) -> 0 | BG15: =IF(L15="2L",1,0) -> 0 | BH15: =IF(J15="USD",0,1) -> 0 | BI15: =IF(W15="USA",0,1) -> 0 | BJ15: =IF(AJ15<15,1,0) -> 0 | BK15: =IF(AJ15<10,1,0) -> 0 | BL15: =IF(BA15="Yes",1,0) -> 0 | BM15: =IF(AT15="Yes",1,0) -> 0 | BN15: =IF(AI15>5.5,1,0) -> 0 | BO15: =IF(M15="Fixed",1,0) -> 0 | BP15: =IF(AU15="Yes",1,0) -> 0 | BQ15: =H15 -> 1492500 | BR15: 100 | BS15: =BR15*AZ15/100 -> 1492500 | BU15: =BS15-BT15 -> 1492500 | BV15: 0 | BW15: =IF(LEN(AJ15)=0,"EBITDA missing",IF(AJ15>10000,"EBITDA bad",IF(AJ15<=15,"15-",IF(AJ15>=30,"30+","15-30")))) -> 15-30 | BX15: =IF(AE15<=0.25,"<0.25",IF(AE15>1.5,">1.50","0.25-1.50")) -> <0.25 | BZ15: =IF(K15="FL",K15&" "&BW15,IF(K15="FLLO",IF(OR(BX15="<0.25",BY15="FL"),"FL"&" "&BW15,K15&" "&BX15),K15)) -> FL 15-30
A16: CF512, Inc. | C16: 45777 | D16: PennantPark Investment Funding I | E16: Gen3 Marketing (Term Loan) | F16: PNNT 97 | G16: First Lien | H16: 6298498.8 | J16: USD | K16: FL | L16: Media | M16: Float | N16: =+VLOOKUP(A16, [2]Sheet2!$M$3:$Z$76, 14, FALSE) -> 0.10503472 | O16: SOFR | P16: 0.01 | Q16: =+VLOOKUP($A16, [2]Sheet2!$M$3:$Z$76, 13, FALSE) -> 0.0619 | R16: 3 | T16: Senior Secured | U16: =YEARFRAC(C16,V16) -> 1.3055556 | V16: 46254 | W16: USA | X16: 100 | AB16: 12.233 | AC16: 1.3879915 | AD16: 5.2933867 | AF16: 5.2933867 | AG16: =+VLOOKUP($A16, [2]Sheet2!$M$3:$X$76, 8, FALSE) -> 45716 | AI16: =+VLOOKUP(A16, [2]Sheet2!$M$3:$X$76, 9, FALSE) -> 5.4679369 | AJ16: =+VLOOKUP($A16, [2]Sheet2!$M$3:$X$76, 10, FALSE) -> 11.914 | AK16: =AD16-AI16 -> -0.17455014 | AM16: =+VLOOKUP($A16, [2]Sheet2!$M$3:$X$76, 11, FALSE) -> 5.4679369 | AN16: =AF16-AM16 -> -0.17455014 | AO16: =+VLOOKUP($A16, [2]Sheet2!$M$3:$X$76, 12, FALSE) -> 1.5635171 | AP16: =AC16-AO16 -> -0.17552556 | AS16: Maintenance Covenants | AT16: No | AU16: No | AW16: SETTLED | AX16: 6298498.8 | AZ16: =+AX16-AY16 -> 6298498.8 | BB16: Y | BC16: N | BD16: 100 | BE16: =IF(LEFT(BZ16,3)="FL ",0,1) -> 0 | BF16: =IF(OR(J16="FLLO",L16="2L"),1,0) -> 0 | BG16: =IF(L16="2L",1,0) -> 0 | BH16: =IF(J16="USD",0,1) -> 0 | BI16: =IF(W16="USA",0,1) -> 0 | BJ16: =IF(AJ16<15,1,0) -> 1 | BK16: =IF(AJ16<10,1,0) -> 0 | BL16: =IF(BA16="Yes",1,0) -> 0 | BM16: =IF(AT16="Yes",1,0) -> 0 | BN16: =IF(AI16>5.5,1,0) -> 0 | BO16: =IF(M16="Fixed",1,0) -> 0 | BP16: =IF(AU16="Yes",1,0) -> 0 | BQ16: =H16 -> 6298498.8 | BR16: 100 | BS16: =BR16*AZ16/100 -> 6298498.8 | BU16: =BS16-BT16 -> 6298498.8 | BV16: 0 | BW16: =IF(LEN(AJ16)=0,"EBITDA missing",IF(AJ16>10000,"EBITDA bad",IF(AJ16<=15,"15-",IF(AJ16>=30,"30+","15-30")))) -> 15- | BX16: =IF(AE16<=0.25,"<0.25",IF(AE16>1.5,">1.50","0.25-1.50")) -> <0.25 | BZ16: =IF(K16="FL",K16&" "&BW16,IF(K16="FLLO",IF(OR(BX16="<0.25",BY16="FL"),"FL"&" "&BW16,K16&" "&BX16),K16)) -> FL 15-
A17: Carnegie Dartlet, LLC | C17: 45777 | D17: PennantPark Investment Funding I | E17: Carnegie Dartlet (Term Loan) | F17: PNNT 76 | G17: First Lien | H17: 6900150.8 | J17: USD | K17: FL | L17: Media | M17: Float | N17: =+VLOOKUP(A17, [2]Sheet2!$M$3:$Z$76, 14, FALSE) -> 0.098249 | O17: SOFR | P17: 0.01 | Q17: =+VLOOKUP($A17, [2]Sheet2!$M$3:$Z$76, 13, FALSE) -> 0.055 | R17: 3 | T17: Senior Secured | U17: =YEARFRAC(C17,V17) -> 4.7694444 | V17: 47521 | W17: USA | X17: 100 | AB17: 19.457816 | AC17: 4.7515887 | AD17: 2.7673367 | AF17: 2.7673367 | AG17: =+VLOOKUP($A17, [2]Sheet2!$M$3:$X$76, 8, FALSE) -> 45657 | AI17: =+VLOOKUP(A17, [2]Sheet2!$M$3:$X$76, 9, FALSE) -> 4.3739976 | AJ17: =+VLOOKUP($A17, [2]Sheet2!$M$3:$X$76, 10, FALSE) -> 19.147376 | AK17: =AD17-AI17 -> -1.6066609 | AM17: =+VLOOKUP($A17, [2]Sheet2!$M$3:$X$76, 11, FALSE) -> 4.3739976 | AN17: =AF17-AM17 -> -1.6066609 | AO17: =+VLOOKUP($A17, [2]Sheet2!$M$3:$X$76, 12, FALSE) -> 2.1762896 | AP17: =AC17-AO17 -> 2.5752991 | AS17: Maintenance Covenants | AT17: No | AU17: No | AW17: SETTLED | AX17: 6900150.8 | AZ17: =+AX17-AY17 -> 6900150.8 | BB17: Y | BC17: Y | BD17: 100 | BE17: =IF(LEFT(BZ17,3)="FL ",0,1) -> 0 | BF17: =IF(OR(J17="FLLO",L17="2L"),1,0) -> 0 | BG17: =IF(L17="2L",1,0) -> 0 | BH17: =IF(J17="USD",0,1) -> 0 | BI17: =IF(W17="USA",0,1) -> 0 | BJ17: =IF(AJ17<15,1,0) -> 0 | BK17: =IF(AJ17<10,1,0) -> 0 | BL17: =IF(BA17="Yes",1,0) -> 0 | BM17: =IF(AT17="Yes",1,0) -> 0 | BN17: =IF(AI17>5.5,1,0) -> 0 | BO17: =IF(M17="Fixed",1,0) -> 0 | BP17: =IF(AU17="Yes",1,0) -> 0 | BQ17: =H17 -> 6900150.8 | BR17: 100 | BS17: =BR17*AZ17/100 -> 6900150.8 | BU17: =BS17-BT17 -> 6900150.8 | BV17: 0 | BW17: =IF(LEN(AJ17)=0,"EBITDA missing",IF(AJ17>10000,"EBITDA bad",IF(AJ17<=15,"15-",IF(AJ17>=30,"30+","15-30")))) -> 15-30 | BX17: =IF(AE17<=0.25,"<0.25",IF(AE17>1.5,">1.50","0.25-1.50")) -> <0.25 | BZ17: =IF(K17="FL",K17&" "&BW17,IF(K17="FLLO",IF(OR(BX17="<0.25",BY17="FL"),"FL"&" "&BW17,K17&" "&BX17),K17)) -> FL 15-30
A18: Carisk Buyer, Inc. | C18: 45777 | D18: PennantPark Investment Funding I | E18: Carisk Partners (TL) | F18: PNNT 16 | G18: First Lien | H18: 1116738.2 | J18: USD | K18: FL | L18: Health Care Providers & Services | M18: Float | N18: =+VLOOKUP(A18, [2]Sheet2!$M$3:$Z$76, 14, FALSE) -> 0.095492 | O18: SOFR | P18: 0.01 | Q18: =+VLOOKUP($A18, [2]Sheet2!$M$3:$Z$76, 13, FALSE) -> 0.0525 | R18: 3 | T18: Senior Secured | U18: =YEARFRAC(C18,V18) -> 4.5833333 | V18: 47452 | W18: USA | X18: 100 | AB18: 10.781094 | AC18: 2.3900626 | AD18: 1.4414121 | AF18: 1.4414121 | AG18: =+VLOOKUP($A18, [2]Sheet2!$M$3:$X$76, 8, FALSE) -> 45688 | AI18: =+VLOOKUP(A18, [2]Sheet2!$M$3:$X$76, 9, FALSE) -> 3.3981829 | AJ18: =+VLOOKUP($A18, [2]Sheet2!$M$3:$X$76, 10, FALSE) -> 18.586851 | AK18: =AD18-AI18 -> -1.9567708 | AM18: =+VLOOKUP($A18, [2]Sheet2!$M$3:$X$76, 11, FALSE) -> 3.3981829 | AN18: =AF18-AM18 -> -1.9567708 | AO18: =+VLOOKUP($A18, [2]Sheet2!$M$3:$X$76, 12, FALSE) -> 2.1388708 | AP18: =AC18-AO18 -> 0.25119186 | AS18: Maintenance Covenants | AT18: No | AU18: No | AW18: SETTLED | AX18: 1116738.2 | AZ18: =+AX18-AY18 -> 1116738.2 | BB18: Y | BC18: Y | BD18: 100 | BE18: =IF(LEFT(BZ18,3)="FL ",0,1) -> 0 | BF18: =IF(OR(J18="FLLO",L18="2L"),1,0) -> 0 | BG18: =IF(L18="2L",1,0) -> 0 | BH18: =IF(J18="USD",0,1) -> 0 | BI18: =IF(W18="USA",0,1) -> 0 | BJ18: =IF(AJ18<15,1,0) -> 0 | BK18: =IF(AJ18<10,1,0) -> 0 | BL18: =IF(BA18="Yes",1,0) -> 0 | BM18: =IF(AT18="Yes",1,0) -> 0 | BN18: =IF(AI18>5.5,1,0) -> 0 | BO18: =IF(M18="Fixed",1,0) -> 0 | BP18: =IF(AU18="Yes",1,0) -> 0 | BQ18: =H18 -> 1116738.2 | BR18: 100 | BS18: =BR18*AZ18/100 -> 1116738.2 | BU18: =BS18-BT18 -> 1116738.2 | BV18: 0 | BW18: =IF(LEN(AJ18)=0,"EBITDA missing",IF(AJ18>10000,"EBITDA bad",IF(AJ18<=15,"15-",IF(AJ18>=30,"30+","15-30")))) -> 15-30 | BX18: =IF(AE18<=0.25,"<0.25",IF(AE18>1.5,">1.50","0.25-1.50")) -> <0.25 | BZ18: =IF(K18="FL",K18&" "&BW18,IF(K18="FLLO",IF(OR(BX18="<0.25",BY18="FL"),"FL"&" "&BW18,K18&" "&BX18),K18)) -> FL 15-30
... A33: Inventus Power Inc. | C33: 45777 | D33: PennantPark Investment Funding I | E33: Inventus (TL) | F33: PNNT 33 | G33: First Lien | H33: 1975484.5 | J33: USD | K33: FL | L33: Electronic Equipment, Instruments & Components | M33: Float | N33: =+VLOOKUP(A33, [2]Sheet2!$M$3:$Z$76, 14, FALSE) -> 0.119394 | O33: SOFR | P33: 0.01 | Q33: =+VLOOKUP($A33, [2]Sheet2!$M$3:$Z$76, 13, FALSE) -> 0.0761 | R33: 3 | T33: Senior Secured | U33: =YEARFRAC(C33,V33) -> 0.16666667 | V33: 45838 | W33: USA | X33: 100 | AB33: 50.403 | AC33: 1.6109886 | AD33: 5.0177508 | AF33: 5.0177508 | AG33: =+VLOOKUP($A33, [2]Sheet2!$M$3:$X$76, 8, FALSE) -> 45716 | AI33: =+VLOOKUP(A33, [2]Sheet2!$M$3:$X$76, 9, FALSE) -> 4.9069445 | AJ33: =+VLOOKUP($A33, [2]Sheet2!$M$3:$X$76, 10, FALSE) -> 51.788 | AK33: =AD33-AI33 -> 0.11080626 | AM33: =+VLOOKUP($A33, [2]Sheet2!$M$3:$X$76, 11, FALSE) -> 4.9069445 | AN33: =AF33-AM33 -> 0.11080626 | AO33: =+VLOOKUP($A33, [2]Sheet2!$M$3:$X$76, 12, FALSE) -> 1.4563555 | AP33: =AC33-AO33 -> 0.15463313 | AS33: Maintenance Covenants | AT33: No | AU33: No | AW33: SETTLED | AX33: 1975484.5 | AZ33: =+AX33-AY33 -> 1975484.5 | BB33: Y | BC33: Y | BD33: 100 | BE33: =IF(LEFT(BZ33,3)="FL ",0,1) -> 0 | BF33: =IF(OR(J33="FLLO",L33="2L"),1,0) -> 0 | BG33: =IF(L33="2L",1,0) -> 0 | BH33: =IF(J33="USD",0,1) -> 0 | BI33: =IF(W33="USA",0,1) -> 0 | BJ33: =IF(AJ33<15,1,0) -> 0 | BK33: =IF(AJ33<10,1,0) -> 0 | BL33: =IF(BA33="Yes",1,0) -> 0 | BM33: =IF(AT33="Yes",1,0) -> 0 | BN33: =IF(AI33>5.5,1,0) -> 0 | BO33: =IF(M33="Fixed",1,0) -> 0 | BP33: =IF(AU33="Yes",1,0) -> 0 | BQ33: =H33 -> 1975484.5 | BR33: 100 | BS33: =BR33*AZ33/100 -> 1975484.5 | BU33: =BS33-BT33 -> 1975484.5 | BV33: 0 | BW33: =IF(LEN(AJ33)=0,"EBITDA missing",IF(AJ33>10000,"EBITDA bad",IF(AJ33<=15,"15-",IF(AJ33>=30,"30+","15-30")))) -> 30+ | BX33: =IF(AE33<=0.25,"<0.25",IF(AE33>1.5,">1.50","0.25-1.50")) -> <0.25 | BZ33: =IF(K33="FL",K33&" "&BW33,IF(K33="FLLO",IF(OR(BX33="<0.25",BY33="FL"),"FL"&" "&BW33,K33&" "&BX33),K33)) -> FL 30+
A34: Lash OpCo, LLC | C34: 45777 | D34: PennantPark Investment Funding I | E34: Lilly Lashes (TL) | F34: PNNT 35 | G34: First Lien | H34: 3328030.9 | J34: USD | K34: FL | L34: Personal Products | M34: Float | N34: =+VLOOKUP(A34, [2]Sheet2!$M$3:$Z$76, 14, FALSE) -> 0.1214 | O34: SOFR | P34: 0.01 | Q34: =+VLOOKUP($A34, [2]Sheet2!$M$3:$Z$76, 13, FALSE) -> 0.0785 | R34: 3 | T34: Senior Secured | U34: =YEARFRAC(C34,V34) -> 1.8 | V34: 46436 | W34: USA | X34: 100 | AB34: 57.462617 | AC34: 2.2122978 | AD34: 5.5235911 | AF34: 5.5235911 | AG34: =+VLOOKUP($A34, [2]Sheet2!$M$3:$X$76, 8, FALSE) -> 45716 | AI34: =+VLOOKUP(A34, [2]Sheet2!$M$3:$X$76, 9, FALSE) -> 8.2594418 | AJ34: =+VLOOKUP($A34, [2]Sheet2!$M$3:$X$76, 10, FALSE) -> 60.446582 | AK34: =AD34-AI34 -> -2.7358507 | AM34: =+VLOOKUP($A34, [2]Sheet2!$M$3:$X$76, 11, FALSE) -> 8.2594418 | AN34: =AF34-AM34 -> -2.7358507 | AO34: =+VLOOKUP($A34, [2]Sheet2!$M$3:$X$76, 12, FALSE) -> 0.91660285 | AP34: =AC34-AO34 -> 1.2956949 | AS34: Maintenance Covenants | AT34: No | AU34: No | AW34: SETTLED | AX34: 3328030.9 | AY34: 466418.03 | AZ34: =+AX34-AY34 -> 2861612.8 | BB34: Y | BC34: Y | BD34: 50 | BE34: =IF(LEFT(BZ34,3)="FL ",0,1) -> 0 | BF34: =IF(OR(J34="FLLO",L34="2L"),1,0) -> 0 | BG34: =IF(L34="2L",1,0) -> 0 | BH34: =IF(J34="USD",0,1) -> 0 | BI34: =IF(W34="USA",0,1) -> 0 | BJ34: =IF(AJ34<15,1,0) -> 0 | BK34: =IF(AJ34<10,1,0) -> 0 | BL34: =IF(BA34="Yes",1,0) -> 0 | BM34: =IF(AT34="Yes",1,0) -> 0 | BN34: =IF(AI34>5.5,1,0) -> 1 | BO34: =IF(M34="Fixed",1,0) -> 0 | BP34: =IF(AU34="Yes",1,0) -> 0 | BQ34: =H34 -> 3328030.9 | BR34: 50 | BS34: =BR34*AZ34/100 -> 1430806.4 | BU34: =BS34-BT34 -> 1430806.4 | BV34: 0 | BW34: =IF(LEN(AJ34)=0,"EBITDA missing",IF(AJ34>10000,"EBITDA bad",IF(AJ34<=15,"15-",IF(AJ34>=30,"30+","15-30")))) -> 30+ | BX34: =IF(AE34<=0.25,"<0.25",IF(AE34>1.5,">1.50","0.25-1.50")) -> <0.25 | BZ34: =IF(K34="FL",K34&" "&BW34,IF(K34="FLLO",IF(OR(BX34="<0.25",BY34="FL"),"FL"&" "&BW34,K34&" "&BX34),K34)) -> FL 30+
A35: MDI Buyer Inc. | C35: 45777 | D35: PennantPark Investment Funding I | E35: MDI (TL) | F35: PNNT 98 | G35: First Lien | H35: 4792248.3 | J35: USD | K35: FL | L35: Chemicals | M35: Float | N35: =+VLOOKUP(A35, [2]Sheet2!$M$3:$Z$76, 14, FALSE) -> 0.093123542 | O35: SOFR | P35: 0.01 | Q35: =+VLOOKUP($A35, [2]Sheet2!$M$3:$Z$76, 13, FALSE) -> 0.05 | R35: 3 | T35: Senior Secured | U35: =YEARFRAC(C35,V35) -> 3.2361111 | V35: 46959 | W35: USA | X35: 100 | AB35: 28.897804 | AC35: 2.33 | AD35: 5.2262471 | AF35: 6.8671075 | AG35: =+VLOOKUP($A35, [2]Sheet2!$M$3:$X$76, 8, FALSE) -> 45688 | AI35: =+VLOOKUP(A35, [2]Sheet2!$M$3:$X$76, 9, FALSE) -> 5.3256205 | AJ35: =+VLOOKUP($A35, [2]Sheet2!$M$3:$X$76, 10, FALSE) -> 33.919818 | AK35: =AD35-AI35 -> -0.099373444 | AM35: =+VLOOKUP($A35, [2]Sheet2!$M$3:$X$76, 11, FALSE) -> 7.094597 | AN35: =AF35-AM35 -> -0.22748952 | AO35: =+VLOOKUP($A35, [2]Sheet2!$M$3:$X$76, 12, FALSE) -> 2.33 | AP35: =AC35-AO35 -> 0 | AS35: Maintenance Covenants | AT35: No | AU35: No | AW35: SETTLED | AX35: 4792248.3 | AZ35: =+AX35-AY35 -> 4792248.3 | BB35: Y | BC35: N | BD35: 100 | BE35: =IF(LEFT(BZ35,3)="FL ",0,1) -> 0 | BF35: =IF(OR(J35="FLLO",L35="2L"),1,0) -> 0 | BG35: =IF(L35="2L",1,0) -> 0 | BH35: =IF(J35="USD",0,1) -> 0 | BI35: =IF(W35="USA",0,1) -> 0 | BJ35: =IF(AJ35<15,1,0) -> 0 | BK35: =IF(AJ35<10,1,0) -> 0 | BL35: =IF(BA35="Yes",1,0) -> 0 | BM35: =IF(AT35="Yes",1,0) -> 0 | BN35: =IF(AI35>5.5,1,0) -> 0 | BO35: =IF(M35="Fixed",1,0) -> 0 | BP35: =IF(AU35="Yes",1,0) -> 0 | BQ35: =H35 -> 4792248.3 | BR35: 100 | BS35: =BR35*AZ35/100 -> 4792248.3 | BU35: =BS35-BT35 -> 4792248.3 | BV35: 0 | BW35: =IF(LEN(AJ35)=0,"EBITDA missing",IF(AJ35>10000,"EBITDA bad",IF(AJ35<=15,"15-",IF(AJ35>=30,"30+","15-30")))) -> 30+ | BX35: =IF(AE35<=0.25,"<0.25",IF(AE35>1.5,">1.50","0.25-1.50")) -> <0.25 | BZ35: =IF(K35="FL",K35&" "&BW35,IF(K35="FLLO",IF(OR(BX35="<0.25",BY35="FL"),"FL"&" "&BW35,K35&" "&BX35),K35)) -> FL 30+
A36: Megawatt Acquisitionco, Inc. | C36: 45777 | D36: PennantPark Investment Funding I | E36: Mission Microwave (Term Loan) | F36: PNNT 39 | G36: First Lien | H36: 4942556.4 | J36: USD | K36: FL | L36: Electronic Equipment, Instruments & Components | M36: Float | N36: =+VLOOKUP(A36, [2]Sheet2!$M$3:$Z$76, 14, FALSE) -> 0.098176597 | O36: SOFR | P36: 0.01 | Q36: =+VLOOKUP($A36, [2]Sheet2!$M$3:$Z$76, 13, FALSE) -> 0.055 | R36: 3 | T36: Senior Secured | U36: =YEARFRAC(C36,V36) -> 4.8361111 | V36: 47543 | W36: USA | X36: 100 | AB36: 28.455 | AC36: 1.8477273 | AD36: 4.895357 | AF36: 4.895357 | AG36: =+VLOOKUP($A36, [2]Sheet2!$M$3:$X$76, 8, FALSE) -> 45716 | AI36: =+VLOOKUP(A36, [2]Sheet2!$M$3:$X$76, 9, FALSE) -> 7.1829156 | AJ36: =+VLOOKUP($A36, [2]Sheet2!$M$3:$X$76, 10, FALSE) -> 19.55 | AK36: =AD36-AI36 -> -2.2875586 | AM36: =+VLOOKUP($A36, [2]Sheet2!$M$3:$X$76, 11, FALSE) -> 7.1829156 | AN36: =AF36-AM36 -> -2.2875586 | AO36: =+VLOOKUP($A36, [2]Sheet2!$M$3:$X$76, 12, FALSE) -> 1.2849162 | AP36: =AC36-AO36 -> 0.56281107 | AS36: Maintenance Covenants | AT36: No | AU36: No | AW36: SETTLED | AX36: 4942556.4 | AZ36: =+AX36-AY36 -> 4942556.4 | BB36: Y | BC36: Y | BD36: 90 | BE36: =IF(LEFT(BZ36,3)="FL ",0,1) -> 0 | BF36: =IF(OR(J36="FLLO",L36="2L"),1,0) -> 0 | BG36: =IF(L36="2L",1,0) -> 0 | BH36: =IF(J36="USD",0,1) -> 0 | BI36: =IF(W36="USA",0,1) -> 0 | BJ36: =IF(AJ36<15,1,0) -> 0 | BK36: =IF(AJ36<10,1,0) -> 0 | BL36: =IF(BA36="Yes",1,0) -> 0 | BM36: =IF(AT36="Yes",1,0) -> 0 | BN36: =IF(AI36>5.5,1,0) -> 1 | BO36: =IF(M36="Fixed",1,0) -> 0 | BP36: =IF(AU36="Yes",1,0) -> 0 | BQ36: =H36 -> 4942556.4 | BR36: 90 | BS36: =BR36*AZ36/100 -> 4448300.8 | BU36: =BS36-BT36 -> 4448300.8 | BV36: 0 | BW36: =IF(LEN(AJ36)=0,"EBITDA missing",IF(AJ36>10000,"EBITDA bad",IF(AJ36<=15,"15-",IF(AJ36>=30,"30+","15-30")))) -> 15-30 | BX36: =IF(AE36<=0.25,"<0.25",IF(AE36>1.5,">1.50","0.25-1.50")) -> <0.25 | BZ36: =IF(K36="FL",K36&" "&BW36,IF(K36="FLLO",IF(OR(BX36="<0.25",BY36="FL"),"FL"&" "&BW36,K36&" "&BX36),K36)) -> FL 15-30
A37: Michael Baker International, LLC | C37: 45777 | D37: PennantPark Investment Funding I | E37: Michael Baker (Term Loan) | F37: PNNT 99 | G37: First Lien | H37: 497493.74 | J37: USD | K37: FL | L37: Construction & Engineering | M37: Float | N37: =+VLOOKUP(A37, [2]Sheet2!$M$3:$Z$76, 14, FALSE) -> 0.083249 | O37: SOFR | P37: 0.01 | Q37: =+VLOOKUP($A37, [2]Sheet2!$M$3:$Z$76, 13, FALSE) -> 0.04 | R37: 3 | T37: Senior Secured | U37: =YEARFRAC(C37,V37) -> 3.6333333 | V37: 47105 | W37: USA | X37: 100 | AB37: 155.68 | AC37: 2.5638576 | AD37: 3.7037513 | AF37: 3.7037513 | AG37: =+VLOOKUP($A37, [2]Sheet2!$M$3:$X$76, 8, FALSE) -> 45565 | AI37: =+VLOOKUP(A37, [2]Sheet2!$M$3:$X$76, 9, FALSE) -> 3.7037513 | AJ37: =+VLOOKUP($A37, [2]Sheet2!$M$3:$X$76, 10, FALSE) -> 155.68 | AK37: =AD37-AI37 -> 0 | AM37: =+VLOOKUP($A37, [2]Sheet2!$M$3:$X$76, 11, FALSE) -> 3.7037513 | AN37: =AF37-AM37 -> 0 | AO37: =+VLOOKUP($A37, [2]Sheet2!$M$3:$X$76, 12, FALSE) -> 2.5638576 | AP37: =AC37-AO37 -> 0 | AS37: Maintenance Covenants | AT37: No | AU37: No | AW37: SETTLED | AX37: 497493.74 | AZ37: =+AX37-AY37 -> 497493.74 | BB37: Y | BC37: N | BD37: 100 | BE37: =IF(LEFT(BZ37,3)="FL ",0,1) -> 0 | BF37: =IF(OR(J37="FLLO",L37="2L"),1,0) -> 0 | BG37: =IF(L37="2L",1,0) -> 0 | BH37: =IF(J37="USD",0,1) -> 0 | BI37: =IF(W37="USA",0,1) -> 0 | BJ37: =IF(AJ37<15,1,0) -> 0 | BK37: =IF(AJ37<10,1,0) -> 0 | BL37: =IF(BA37="Yes",1,0) -> 0 | BM37: =IF(AT37="Yes",1,0) -> 0 | BN37: =IF(AI37>5.5,1,0) -> 0 | BO37: =IF(M37="Fixed",1,0) -> 0 | BP37: =IF(AU37="Yes",1,0) -> 0 | BQ37: =H37 -> 497493.74 | BR37: 100 | BS37: =BR37*AZ37/100 -> 497493.74 | BU37: =BS37-BT37 -> 497493.74 | BV37: 0 | BW37: =IF(LEN(AJ37)=0,"EBITDA missing",IF(AJ37>10000,"EBITDA bad",IF(AJ37<=15,"15-",IF(AJ37>=30,"30+","15-30")))) -> 30+ | BX37: =IF(AE37<=0.25,"<0.25",IF(AE37>1.5,">1.50","0.25-1.50")) -> <0.25 | BZ37: =IF(K37="FL",K37&" "&BW37,IF(K37="FLLO",IF(OR(BX37="<0.25",BY37="FL"),"FL"&" "&BW37,K37&" "&BX37),K37)) -> FL 30+
A38: Municipal Emergency Services, Inc. | C38: 45777 | D38: PennantPark Investment Funding I | E38: MES (Term Loan) | F38: PNNT 79 | G38: First Lien | H38: 2499911.1 | J38: USD | K38: FL | L38: Distributors | M38: Float | N38: =+VLOOKUP(A38, [2]Sheet2!$M$3:$Z$76, 14, FALSE) -> 0.094495622 | O38: SOFR | P38: 0.01 | Q38: =+VLOOKUP($A38, [2]Sheet2!$M$3:$Z$76, 13, FALSE) -> 0.0515 | R38: 3 | T38: Senior Secured | U38: =YEARFRAC(C38,V38) -> 2.4194444 | V38: 46661 | W38: USA | X38: 100 | AB38: 35.017 | AC38: 1.6322173 | AD38: 4.1874411 | AF38: 4.3916623 | AG38: =+VLOOKUP($A38, [2]Sheet2!$M$3:$X$76, 8, FALSE) -> 45716 | AI38: =+VLOOKUP(A38, [2]Sheet2!$M$3:$X$76, 9, FALSE) -> 3.1798182 | AJ38: =+VLOOKUP($A38, [2]Sheet2!$M$3:$X$76, 10, FALSE) -> 41.356385 | AK38: =AD38-AI38 -> 1.0076229 | AM38: =+VLOOKUP($A38, [2]Sheet2!$M$3:$X$76, 11, FALSE) -> 3.1798182 | AN38: =AF38-AM38 -> 1.2118441 | AO38: =+VLOOKUP($A38, [2]Sheet2!$M$3:$X$76, 12, FALSE) -> 3.2794754 | AP38: =AC38-AO38 -> -1.6472582 | AS38: Maintenance Covenants | AT38: No | AU38: No | AW38: SETTLED | AX38: 2499911.1 | AZ38: =+AX38-AY38 -> 2499911.1 | BB38: Y | BC38: N | BD38: 100 | BE38: =IF(LEFT(BZ38,3)="FL ",0,1) -> 0 | BF38: =IF(OR(J38="FLLO",L38="2L"),1,0) -> 0 | BG38: =IF(L38="2L",1,0) -> 0 | BH38: =IF(J38="USD",0,1) -> 0 | BI38: =IF(W38="USA",0,1) -> 0 | BJ38: =IF(AJ38<15,1,0) -> 0 | BK38: =IF(AJ38<10,1,0) -> 0 | BL38: =IF(BA38="Yes",1,0) -> 0 | BM38: =IF(AT38="Yes",1,0) -> 0 | BN38: =IF(AI38>5.5,1,0) -> 0 | BO38: =IF(M38="Fixed",1,0) -> 0 | BP38: =IF(AU38="Yes",1,0) -> 0 | BQ38: =H38 -> 2499911.1 | BR38: 100 | BS38: =BR38*AZ38/100 -> 2499911.1 | BU38: =BS38-BT38 -> 2499911.1 | BV38: 0 | BW38: =IF(LEN(AJ38)=0,"EBITDA missing",IF(AJ38>10000,"EBITDA bad",IF(AJ38<=15,"15-",IF(AJ38>=30,"30+","15-30")))) -> 30+ | BX38: =IF(AE38<=0.25,"<0.25",IF(AE38>1.5,">1.50","0.25-1.50")) -> <0.25 | BZ38: =IF(K38="FL",K38&" "&BW38,IF(K38="FLLO",IF(OR(BX38="<0.25",BY38="FL"),"FL"&" "&BW38,K38&" "&BX38),K38)) -> FL 30+
A39: MOREgroup Holdings, LLC | C39: 45777 | D39: PennantPark Investment Funding I | E39: MOREgroup (Term Loan) | F39: PNNT 41 | G39: First Lien | H39: 4252707.2 | J39: USD | K39: FL | L39: Professional Services | M39: Float | N39: =+VLOOKUP(A39, [2]Sheet2!$M$3:$Z$76, 14, FALSE) -> 0.095492 | O39: SOFR | P39: 0.01 | Q39: =+VLOOKUP($A39, [2]Sheet2!$M$3:$Z$76, 13, FALSE) -> 0.0525 | R39: 3 | T39: Senior Secured | U39: =YEARFRAC(C39,V39) -> 4.7111111 | V39: 47499 | W39: USA | X39: 100 | AB39: 50.913 | AC39: 1.968454 | AD39: 4.4013201 | AF39: 4.4013201 | AG39: =+VLOOKUP($A39, [2]Sheet2!$M$3:$X$76, 8, FALSE) -> 45688 | AI39: =+VLOOKUP(A39, [2]Sheet2!$M$3:$X$76, 9, FALSE) -> 2.7628227 | AJ39: =+VLOOKUP($A39, [2]Sheet2!$M$3:$X$76, 10, FALSE) -> 69.250608 | AK39: =AD39-AI39 -> 1.6384974 | AM39: =+VLOOKUP($A39, [2]Sheet2!$M$3:$X$76, 11, FALSE) -> 2.7628227 | AN39: =AF39-AM39 -> 1.6384974 | AO39: =+VLOOKUP($A39, [2]Sheet2!$M$3:$X$76, 12, FALSE) -> 2.6199003 | AP39: =AC39-AO39 -> -0.65144634 | AS39: Cov-Lite | AT39: Yes | AU39: No | AW39: SETTLED | AX39: 4252707.2 | AZ39: =+AX39-AY39 -> 4252707.2 | BB39: Y | BC39: N | BD39: 100 | BE39: =IF(LEFT(BZ39,3)="FL ",0,1) -> 0 | BF39: =IF(OR(J39="FLLO",L39="2L"),1,0) -> 0 | BG39: =IF(L39="2L",1,0) -> 0 | BH39: =IF(J39="USD",0,1) -> 0 | BI39: =IF(W39="USA",0,1) -> 0 | BJ39: =IF(AJ39<15,1,0) -> 0 | BK39: =IF(AJ39<10,1,0) -> 0 | BL39: =IF(BA39="Yes",1,0) -> 0 | BM39: =IF(AT39="Yes",1,0) -> 1 | BN39: =IF(AI39>5.5,1,0) -> 0 | BO39: =IF(M39="Fixed",1,0) -> 0 | BP39: =IF(AU39="Yes",1,0) -> 0 | BQ39: =H39 -> 4252707.2 | BR39: 100 | BS39: =BR39*AZ39/100 -> 4252707.2 | BU39: =BS39-BT39 -> 4252707.2 | BV39: 0 | BW39: =IF(LEN(AJ39)=0,"EBITDA missing",IF(AJ39>10000,"EBITDA bad",IF(AJ39<=15,"15-",IF(AJ39>=30,"30+","15-30")))) -> 30+ | BX39: =IF(AE39<=0.25,"<0.25",IF(AE39>1.5,">1.50","0.25-1.50")) -> <0.25 | BZ39: =IF(K39="FL",K39&" "&BW39,IF(K39="FLLO",IF(OR(BX39="<0.25",BY39="FL"),"FL"&" "&BW39,K39&" "&BX39),K39)) -> FL 30+
A40: NFS - CFP Holdings, LLC | C40: 45777 | D40: PennantPark Investment Funding I | E40: Commercial Fire Protection (Term Loan) | F40: PNNT 100 | G40: First Lien | H40: 3990869.1 | J40: USD | K40: FL | L40: Professional Services | M40: Float | N40: =+VLOOKUP(A40, [2]Sheet2!$M$3:$Z$76, 14, FALSE) -> 0.09060512 | O40: SOFR | P40: 0.01 | Q40: =+VLOOKUP($A40, [2]Sheet2!$M$3:$Z$76, 13, FALSE) -> 0.0475 | R40: 3 | T40: Senior Secured | U40: =YEARFRAC(C40,V40) -> 5.3888889 | V40: 47746 | W40: USA | X40: 100 | AB40: 10.208521 | AC40: 1.8784216 | AD40: 5.2701072 | AF40: 5.2701072 | AG40: =+VLOOKUP($A40, [2]Sheet2!$M$3:$X$76, 8, FALSE) -> 45688 | AI40: =+VLOOKUP(A40, [2]Sheet2!$M$3:$X$76, 9, FALSE) -> 3.6866285 | AJ40: =+VLOOKUP($A40, [2]Sheet2!$M$3:$X$76, 10, FALSE) -> 21.502073 | AK40: =AD40-AI40 -> 1.5834788 | AM40: =+VLOOKUP($A40, [2]Sheet2!$M$3:$X$76, 11, FALSE) -> 3.6866285 | AN40: =AF40-AM40 -> 1.5834788 | AO40: =+VLOOKUP($A40, [2]Sheet2!$M$3:$X$76, 12, FALSE) -> 2.7217814 | AP40: =AC40-AO40 -> -0.84335986 | AS40: Maintenance Covenants | AT40: No | AU40: No | AW40: SETTLED | AX40: 3990869.1 | AZ40: =+AX40-AY40 -> 3990869.1 | BB40: Y | BC40: N | BD40: 100 | BE40: =IF(LEFT(BZ40,3)="FL ",0,1) -> 0 | BF40: =IF(OR(J40="FLLO",L40="2L"),1,0) -> 0 | BG40: =IF(L40="2L",1,0) -> 0 | BH40: =IF(J40="USD",0,1) -> 0 | BI40: =IF(W40="USA",0,1) -> 0 | BJ40: =IF(AJ40<15,1,0) -> 0 | BK40: =IF(AJ40<10,1,0) -> 0 | BL40: =IF(BA40="Yes",1,0) -> 0 | BM40: =IF(AT40="Yes",1,0) -> 0 | BN40: =IF(AI40>5.5,1,0) -> 0 | BO40: =IF(M40="Fixed",1,0) -> 0 | BP40: =IF(AU40="Yes",1,0) -> 0 | BQ40: =H40 -> 3990869.1 | BR40: 100 | BS40: =BR40*AZ40/100 -> 3990869.1 | BU40: =BS40-BT40 -> 3990869.1 | BV40: 0 | BW40: =IF(LEN(AJ40)=0,"EBITDA missing",IF(AJ40>10000,"EBITDA bad",IF(AJ40<=15,"15-",IF(AJ40>=30,"30+","15-30")))) -> 15-30 | BX40: =IF(AE40<=0.25,"<0.25",IF(AE40>1.5,">1.50","0.25-1.50")) -> <0.25 | BZ40: =IF(K40="FL",K40&" "&BW40,IF(K40="FLLO",IF(OR(BX40="<0.25",BY40="FL"),"FL"&" "&BW40,K40&" "&BX40),K40)) -> FL 15-30
A41: NORA ACQUISITION, LLC | C41: 45777 | D41: PennantPark Investment Funding I | E41: NORA (Term Loan) | F41: PNNT 42 | G41: First Lien | H41: 3777823.2 | J41: USD | K41: FL | L41: Air Freight & Logistics | M41: Float | N41: =+VLOOKUP(A41, [2]Sheet2!$M$3:$Z$76, 14, FALSE) -> 0.106451 | O41: SOFR | P41: 0.01 | Q41: =+VLOOKUP($A41, [2]Sheet2!$M$3:$Z$76, 13, FALSE) -> 0.0635 | R41: 3 | T41: Senior Secured | U41: =YEARFRAC(C41,V41) -> 4.3333333 | V41: 47361 | W41: USA | X41: 100 | AB41: 21.293252 | AC41: 2.2766519 | AD41: 3.6631323 | AF41: 3.6764069 | AG41: =+VLOOKUP($A41, [2]Sheet2!$M$3:$X$76, 8, FALSE) -> 45657 | AI41: =+VLOOKUP(A41, [2]Sheet2!$M$3:$X$76, 9, FALSE) -> 5.3227543 | AJ41: =+VLOOKUP($A41, [2]Sheet2!$M$3:$X$76, 10, FALSE) -> 14.254361 | AK41: =AD41-AI41 -> -1.659622 | AM41: =+VLOOKUP($A41, [2]Sheet2!$M$3:$X$76, 11, FALSE) -> 5.6274855 | AN41: =AF41-AM41 -> -1.9510786 | AO41: =+VLOOKUP($A41, [2]Sheet2!$M$3:$X$76, 12, FALSE) -> 1.4638224 | AP41: =AC41-AO41 -> 0.81282958 | AS41: Maintenance Covenants | AT41: No | AU41: No | AW41: SETTLED | AX41: 3777823.2 | AZ41: =+AX41-AY41 -> 3777823.2 | BB41: Y | BC41: Y | BD41: 100 | BE41: =IF(LEFT(BZ41,3)="FL ",0,1) -> 0 | BF41: =IF(OR(J41="FLLO",L41="2L"),1,0) -> 0 | BG41: =IF(L41="2L",1,0) -> 0 | BH41: =IF(J41="USD",0,1) -> 0 | BI41: =IF(W41="USA",0,1) -> 0 | BJ41: =IF(AJ41<15,1,0) -> 1 | BK41: =IF(AJ41<10,1,0) -> 0 | BL41: =IF(BA41="Yes",1,0) -> 0 | BM41: =IF(AT41="Yes",1,0) -> 0 | BN41: =IF(AI41>5.5,1,0) -> 0 | BO41: =IF(M41="Fixed",1,0) -> 0 | BP41: =IF(AU41="Yes",1,0) -> 0 | BQ41: =H41 -> 3777823.2 | BR41: 100 | BS41: =BR41*AZ41/100 -> 3777823.2 | BU41: =BS41-BT41 -> 3777823.2 | BV41: 0 | BW41: =IF(LEN(AJ41)=0,"EBITDA missing",IF(AJ41>10000,"EBITDA bad",IF(AJ41<=15,"15-",IF(AJ41>=30,"30+","15-30")))) -> 15- | BX41: =IF(AE41<=0.25,"<0.25",IF(AE41>1.5,">1.50","0.25-1.50")) -> <0.25 | BZ41: =IF(K41="FL",K41&" "&BW41,IF(K41="FLLO",IF(OR(BX41="<0.25",BY41="FL"),"FL"&" "&BW41,K41&" "&BX41),K41)) -> FL 15-
A42: Omnia Exterior Solutions, LLC | C42: 45777 | D42: PennantPark Investment Funding I | E42: Omnia (TL) | F42: PNNT 43 | G42: First Lien | H42: 7136692.4 | J42: USD | K42: FL | L42: Diversified Consumer Services | M42: Float | N42: =+VLOOKUP(A42, [2]Sheet2!$M$3:$Z$76, 14, FALSE) -> 0.095548893 | O42: SOFR | P42: 0.01 | Q42: =+VLOOKUP($A42, [2]Sheet2!$M$3:$Z$76, 13, FALSE) -> 0.0525 | R42: 3 | T42: Senior Secured | U42: =YEARFRAC(C42,V42) -> 4.6638889 | V42: 47481 | W42: USA | X42: 100 | AB42: 14.5 | AC42: 2.96 | AD42: 2.07 | AF42: 2.07 | AG42: =+VLOOKUP($A42, [2]Sheet2!$M$3:$X$76, 8, FALSE) -> 45716 | AI42: =+VLOOKUP(A42, [2]Sheet2!$M$3:$X$76, 9, FALSE) -> 3.1991927 | AJ42: =+VLOOKUP($A42, [2]Sheet2!$M$3:$X$76, 10, FALSE) -> 38.156765 | AK42: =AD42-AI42 -> -1.1291927 | AM42: =+VLOOKUP($A42, [2]Sheet2!$M$3:$X$76, 11, FALSE) -> 3.1991927 | AN42: =AF42-AM42 -> -1.1291927 | AO42: =+VLOOKUP($A42, [2]Sheet2!$M$3:$X$76, 12, FALSE) -> 3.5474548 | AP42: =AC42-AO42 -> -0.5874548 | AS42: Cov-Lite | AT42: Yes | AU42: No | AW42: SETTLED | AX42: 7136692.4 | AZ42: =+AX42-AY42 -> 7136692.4 | BB42: Y | BC42: N | BD42: 100 | BE42: =IF(LEFT(BZ42,3)="FL ",0,1) -> 0 | BF42: =IF(OR(J42="FLLO",L42="2L"),1,0) -> 0 | BG42: =IF(L42="2L",1,0) -> 0 | BH42: =IF(J42="USD",0,1) -> 0 | BI42: =IF(W42="USA",0,1) -> 0 | BJ42: =IF(AJ42<15,1,0) -> 0 | BK42: =IF(AJ42<10,1,0) -> 0 | BL42: =IF(BA42="Yes",1,0) -> 0 | BM42: =IF(AT42="Yes",1,0) -> 1 | BN42: =IF(AI42>5.5,1,0) -> 0 | BO42: =IF(M42="Fixed",1,0) -> 0 | BP42: =IF(AU42="Yes",1,0) -> 0 | BQ42: =H42 -> 7136692.4 | BR42: 100 | BS42: =BR42*AZ42/100 -> 7136692.4 | BU42: =BS42-BT42 -> 7136692.4 | BV42: 0 | BW42: =IF(LEN(AJ42)=0,"EBITDA missing",IF(AJ42>10000,"EBITDA bad",IF(AJ42<=15,"15-",IF(AJ42>=30,"30+","15-30")))) -> 30+ | BX42: =IF(AE42<=0.25,"<0.25",IF(AE42>1.5,">1.50","0.25-1.50")) -> <0.25 | BZ42: =IF(K42="FL",K42&" "&BW42,IF(K42="FLLO",IF(OR(BX42="<0.25",BY42="FL"),"FL"&" "&BW42,K42&" "&BX42),K42)) -> FL 30+
A43: PAR Excellence | C43: 45777 | D43: PennantPark Investment Funding I | E43: PAR Excellence (Term Loan) | F43: PNNT 90 | G43: First Lien | H43: 997500 | J43: USD | K43: FL | L43: Health Care Technology | M43: Float | N43: =+VLOOKUP(A43, [2]Sheet2!$M$3:$Z$76, 14, FALSE) -> 0.093185 | O43: SOFR | P43: 0.01 | Q43: =+VLOOKUP($A43, [2]Sheet2!$M$3:$Z$76, 13, FALSE) -> 0.05 | R43: 3 | T43: Senior Secured | U43: =YEARFRAC(C43,V43) -> 5.3416667 | V43: 47729 | W43: USA | X43: 100 | AB43: 22.439 | AC43: 3.2877656 | AD43: 2.3172601 | AF43: 2.3172601 | AG43: =+VLOOKUP($A43, [2]Sheet2!$M$3:$X$76, 8, FALSE) -> 45716 | AI43: =+VLOOKUP(A43, [2]Sheet2!$M$3:$X$76, 9, FALSE) -> 4.0885428 | AJ43: =+VLOOKUP($A43, [2]Sheet2!$M$3:$X$76, 10, FALSE) -> 38.594191 | AK43: =AD43-AI43 -> -1.7712827 | AM43: =+VLOOKUP($A43, [2]Sheet2!$M$3:$X$76, 11, FALSE) -> 4.0885428 | AN43: =AF43-AM43 -> -1.7712827 | AO43: =+VLOOKUP($A43, [2]Sheet2!$M$3:$X$76, 12, FALSE) -> 2.4899478 | AP43: =AC43-AO43 -> 0.79781778 | AS43: Maintenance Covenants | AT43: No | AU43: No | AW43: SETTLED | AX43: 997500 | AZ43: =+AX43-AY43 -> 997500 | BB43: Y | BC43: N | BD43: 100 | BE43: =IF(LEFT(BZ43,3)="FL ",0,1) -> 0 | BF43: =IF(OR(J43="FLLO",L43="2L"),1,0) -> 0 | BG43: =IF(L43="2L",1,0) -> 0 | BH43: =IF(J43="USD",0,1) -> 0 | BI43: =IF(W43="USA",0,1) -> 0 | BJ43: =IF(AJ43<15,1,0) -> 0 | BK43: =IF(AJ43<10,1,0) -> 0 | BL43: =IF(BA43="Yes",1,0) -> 0 | BM43: =IF(AT43="Yes",1,0) -> 0 | BN43: =IF(AI43>5.5,1,0) -> 0 | BO43: =IF(M43="Fixed",1,0) -> 0 | BP43: =IF(AU43="Yes",1,0) -> 0 | BQ43: =H43 -> 997500 | BR43: 100 | BS43: =BR43*AZ43/100 -> 997500 | BU43: =BS43-BT43 -> 997500 | BV43: 0 | BW43: =IF(LEN(AJ43)=0,"EBITDA missing",IF(AJ43>10000,"EBITDA bad",IF(AJ43<=15,"15-",IF(AJ43>=30,"30+","15-30")))) -> 30+ | BX43: =IF(AE43<=0.25,"<0.25",IF(AE43>1.5,">1.50","0.25-1.50")) -> <0.25 | BZ43: =IF(K43="FL",K43&" "&BW43,IF(K43="FLLO",IF(OR(BX43="<0.25",BY43="FL"),"FL"&" "&BW43,K43&" "&BX43),K43)) -> FL 30+
A44: PL Acquisitionco, LLC | C44: 45777 | D44: PennantPark Investment Funding I | E44: Pink Lily (Term Loan) | F44: PNNT 48 | G44: First Lien | H44: 8459233 | J44: USD | K44: FL | L44: Specialty Retail | M44: Float | N44: =+VLOOKUP(A44, [2]Sheet2!$M$3:$Z$76, 14, FALSE) -> 0.115016 | O44: SOFR | P44: 0.01 | Q44: =+VLOOKUP($A44, [2]Sheet2!$M$3:$Z$76, 13, FALSE) -> 0.0725 | R44: 3 | T44: Senior Secured | U44: =YEARFRAC(C44,V44) -> 2.525 | V44: 46700 | W44: USA | X44: 100 | AB44: 26.626187 | AC44: 4.7335444 | AD44: 2.8595157 | AF44: 2.8595157 | AG44: =+VLOOKUP($A44, [2]Sheet2!$M$3:$X$76, 8, FALSE) -> 45716 | AI44: =+VLOOKUP(A44, [2]Sheet2!$M$3:$X$76, 9, FALSE) -> -18.2598 | AJ44: =+VLOOKUP($A44, [2]Sheet2!$M$3:$X$76, 10, FALSE) -> -3.648616 | AK44: =AD44-AI44 -> 21.119316 | AM44: =+VLOOKUP($A44, [2]Sheet2!$M$3:$X$76, 11, FALSE) -> -18.2598 | AN44: =AF44-AM44 -> 21.119316 | AO44: =+VLOOKUP($A44, [2]Sheet2!$M$3:$X$76, 12, FALSE) -> -0.39253534 | AP44: =AC44-AO44 -> 5.1260797 | AS44: Maintenance Covenants | AT44: No | AU44: No | AW44: SETTLED | AX44: 8459233 | AY44: =354001.85+150254.04 -> 504255.89 | AZ44: =+AX44-AY44 -> 7954977.1 | BB44: Y | BC44: Y | BD44: 0 | BE44: =IF(LEFT(BZ44,3)="FL ",0,1) -> 0 | BF44: =IF(OR(J44="FLLO",L44="2L"),1,0) -> 0 | BG44: =IF(L44="2L",1,0) -> 0 | BH44: =IF(J44="USD",0,1) -> 0 | BI44: =IF(W44="USA",0,1) -> 0 | BJ44: =IF(AJ44<15,1,0) -> 1 | BK44: =IF(AJ44<10,1,0) -> 1 | BL44: =IF(BA44="Yes",1,0) -> 0 | BM44: =IF(AT44="Yes",1,0) -> 0 | BN44: =IF(AI44>5.5,1,0) -> 0 | BO44: =IF(M44="Fixed",1,0) -> 0 | BP44: =IF(AU44="Yes",1,0) -> 0 | BQ44: =H44 -> 8459233 | BR44: 0 | BS44: =BR44*AZ44/100 -> 0 | BU44: =BS44-BT44 -> 0 | BV44: 0 | BW44: =IF(LEN(AJ44)=0,"EBITDA missing",IF(AJ44>10000,"EBITDA bad",IF(AJ44<=15,"15-",IF(AJ44>=30,"30+","15-30")))) -> 15- | BX44: =IF(AE44<=0.25,"<0.25",IF(AE44>1.5,">1.50","0.25-1.50")) -> <0.25 | BZ44: =IF(K44="FL",K44&" "&BW44,IF(K44="FLLO",IF(OR(BX44="<0.25",BY44="FL"),"FL"&" "&BW44,K44&" "&BX44),K44)) -> FL 15-
A45: Radius Aerospace | C45: 45777 | D45: PennantPark Investment Funding I | E45: Radius Aerospace (Term Loan) | F45: PNNT 51 | G45: First Lien | H45: 11836624 | J45: USD | K45: FL | L45: Aerospace & Defense | M45: Float | N45: =+VLOOKUP(A45, [2]Sheet2!$M$3:$Z$76, 14, FALSE) -> 0.1047878 | O45: SOFR | P45: 0.01 | Q45: =+VLOOKUP($A45, [2]Sheet2!$M$3:$Z$76, 13, FALSE) -> 0.0615 | R45: 3 | T45: Senior Secured | U45: =YEARFRAC(C45,V45) -> 0.083333333 | V45: 45747 | W45: USA | X45: 100 | AB45: 19.7 | AC45: 2.560104 | AD45: 4.5685279 | AF45: 4.5685279 | AG45: =+VLOOKUP($A45, [2]Sheet2!$M$3:$X$76, 8, FALSE) -> 45716 | AI45: =+VLOOKUP(A45, [2]Sheet2!$M$3:$X$76, 9, FALSE) -> 5.226678 | AJ45: =+VLOOKUP($A45, [2]Sheet2!$M$3:$X$76, 10, FALSE) -> 24.762 | AK45: =AD45-AI45 -> -0.65815006 | AM45: =+VLOOKUP($A45, [2]Sheet2!$M$3:$X$76, 11, FALSE) -> 5.226678 | AN45: =AF45-AM45 -> -0.65815006 | AO45: =+VLOOKUP($A45, [2]Sheet2!$M$3:$X$76, 12, FALSE) -> 1.3540026 | AP45: =AC45-AO45 -> 1.2061013 | AS45: Maintenance Covenants | AT45: No | AU45: No | AW45: SETTLED | AX45: 11836624 | AZ45: =+AX45-AY45 -> 11836624 | BB45: Y | BC45: Y | BD45: 100 | BE45: =IF(LEFT(BZ45,3)="FL ",0,1) -> 0 | BF45: =IF(OR(J45="FLLO",L45="2L"),1,0) -> 0 | BG45: =IF(L45="2L",1,0) -> 0 | BH45: =IF(J45="USD",0,1) -> 0 | BI45: =IF(W45="USA",0,1) -> 0 | BJ45: =IF(AJ45<15,1,0) -> 0 | BK45: =IF(AJ45<10,1,0) -> 0 | BL45: =IF(BA45="Yes",1,0) -> 0 | BM45: =IF(AT45="Yes",1,0) -> 0 | BN45: =IF(AI45>5.5,1,0) -> 0 | BO45: =IF(M45="Fixed",1,0) -> 0 | BP45: =IF(AU45="Yes",1,0) -> 0 | BQ45: =H45 -> 11836624 | BR45: 100 | BS45: =BR45*AZ45/100 -> 11836624 | BU45: =BS45-BT45 -> 11836624 | BV45: 0 | BW45: =IF(LEN(AJ45)=0,"EBITDA missing",IF(AJ45>10000,"EBITDA bad",IF(AJ45<=15,"15-",IF(AJ45>=30,"30+","15-30")))) -> 15-30 | BX45: =IF(AE45<=0.25,"<0.25",IF(AE45>1.5,">1.50","0.25-1.50")) -> <0.25 | BZ45: =IF(K45="FL",K45&" "&BW45,IF(K45="FLLO",IF(OR(BX45="<0.25",BY45="FL"),"FL"&" "&BW45,K45&" "&BX45),K45)) -> FL 15-30
A46: Rancho Medical | C46: 45777 | D46: PennantPark Investment Funding I | E46: Rancho (TL) | F46: PNNT 96 | G46: First Lien | H46: 17337943 | J46: USD | K46: FL | L46: Health Care Providers & Services | M46: Float | N46: =+VLOOKUP(A46, [2]Sheet2!$M$3:$Z$76, 14, FALSE) -> 0.095657909 | O46: SOFR | P46: 0.01 | Q46: =+VLOOKUP($A46, [2]Sheet2!$M$3:$Z$76, 13, FALSE) -> 0.0525 | R46: 3 | T46: Senior Secured | U46: =YEARFRAC(C46,V46) -> 0.63333333 | V46: 46009 | W46: USA | X46: 100 | AB46: 17.41303 | AC46: 2.5001806 | AD46: 3.3033463 | AF46: 3.3033463 | AG46: =+VLOOKUP($A46, [2]Sheet2!$M$3:$X$76, 8, FALSE) -> 45688 | AI46: =+VLOOKUP(A46, [2]Sheet2!$M$3:$X$76, 9, FALSE) -> 3.1208171 | AJ46: =+VLOOKUP($A46, [2]Sheet2!$M$3:$X$76, 10, FALSE) -> 19.009817 | AK46: =AD46-AI46 -> 0.18252913 | AM46: =+VLOOKUP($A46, [2]Sheet2!$M$3:$X$76, 11, FALSE) -> 3.1208171 | AN46: =AF46-AM46 -> 0.18252913 | AO46: =+VLOOKUP($A46, [2]Sheet2!$M$3:$X$76, 12, FALSE) -> 2.4012273 | AP46: =AC46-AO46 -> 0.098953297 | AS46: Maintenance Covenants | AT46: No | AU46: No | AW46: SETTLED | AX46: 17337943 | AZ46: =+AX46-AY46 -> 17337943 | BB46: Y | BC46: N | BD46: 100 | BE46: =IF(LEFT(BZ46,3)="FL ",0,1) -> 0 | BF46: =IF(OR(J46="FLLO",L46="2L"),1,0) -> 0 | BG46: =IF(L46="2L",1,0) -> 0 | BH46: =IF(J46="USD",0,1) -> 0 | BI46: =IF(W46="USA",0,1) -> 0 | BJ46: =IF(AJ46<15,1,0) -> 0 | BK46: =IF(AJ46<10,1,0) -> 0 | BL46: =IF(BA46="Yes",1,0) -> 0 | BM46: =IF(AT46="Yes",1,0) -> 0 | BN46: =IF(AI46>5.5,1,0) -> 0 | BO46: =IF(M46="Fixed",1,0) -> 0 | BP46: =IF(AU46="Yes",1,0) -> 0 | BQ46: =H46 -> 17337943 | BR46: 100 | BS46: =BR46*AZ46/100 -> 17337943 | BU46: =BS46-BT46 -> 17337943 | BV46: 0 | BW46: =IF(LEN(AJ46)=0,"EBITDA missing",IF(AJ46>10000,"EBITDA bad",IF(AJ46<=15,"15-",IF(AJ46>=30,"30+","15-30")))) -> 15-30 | BX46: =IF(AE46<=0.25,"<0.25",IF(AE46>1.5,">1.50","0.25-1.50")) -> <0.25 | BZ46: =IF(K46="FL",K46&" "&BW46,IF(K46="FLLO",IF(OR(BX46="<0.25",BY46="FL"),"FL"&" "&BW46,K46&" "&BX46),K46)) -> FL 15-30
A47: Reception Purchaser, LLC -First Out Term loan | C47: 45777 | D47: PennantPark Investment Funding I | E47: STG (TL) | F47: PNNT 84 | G47: First Lien | H47: 1403243.6 | J47: USD | K47: FL | L47: Air Freight & Logistics | M47: Float | N47: =+VLOOKUP(A47, [2]Sheet2!$M$3:$Z$76, 14, FALSE) -> 0.1267268 | O47: SOFR | P47: 0.01 | Q47: =+VLOOKUP($A47, [2]Sheet2!$M$3:$Z$76, 13, FALSE) -> 0.0835 | R47: 3 | T47: Senior Secured | U47: =YEARFRAC(C47,V47) -> 4.4277778 | V47: 47395 | W47: USA | X47: 92.5466 | AB47: 59.575 | AC47: 0.50393334 | AD47: 14.733233 | AF47: 14.733233 | AG47: =+VLOOKUP($A47, [2]Sheet2!$M$3:$X$76, 8, FALSE) -> 45657 | AI47: =+VLOOKUP(A47, [2]Sheet2!$M$3:$X$76, 9, FALSE) -> 140.9099 | AJ47: =+VLOOKUP($A47, [2]Sheet2!$M$3:$X$76, 10, FALSE) -> 6.3186193 | AK47: =AD47-AI47 -> -126.17666 | AM47: =+VLOOKUP($A47, [2]Sheet2!$M$3:$X$76, 11, FALSE) -> 140.9099 | AN47: =AF47-AM47 -> -126.17666 | AO47: =+VLOOKUP($A47, [2]Sheet2!$M$3:$X$76, 12, FALSE) -> 0.052771172 | AP47: =AC47-AO47 -> 0.45116217 | AS47: Maintenance Covenants | AT47: No | AU47: No | AW47: SETTLED | AX47: 1403243.6 | AY47: 24853.5 | AZ47: =+AX47-AY47 -> 1378390.1 | BB47: Y | BC47: Y | BD47: 0 | BE47: =IF(LEFT(BZ47,3)="FL ",0,1) -> 0 | BF47: =IF(OR(J47="FLLO",L47="2L"),1,0) -> 0 | BG47: =IF(L47="2L",1,0) -> 0 | BH47: =IF(J47="USD",0,1) -> 0 | BI47: =IF(W47="USA",0,1) -> 0 | BJ47: =IF(AJ47<15,1,0) -> 1 | BK47: =IF(AJ47<10,1,0) -> 1 | BL47: =IF(BA47="Yes",1,0) -> 0 | BM47: =IF(AT47="Yes",1,0) -> 0 | BN47: =IF(AI47>5.5,1,0) -> 1 | BO47: =IF(M47="Fixed",1,0) -> 0 | BP47: =IF(AU47="Yes",1,0) -> 0 | BQ47: =H47 -> 1403243.6 | BR47: 0 | BS47: =BR47*AZ47/100 -> 0 | BU47: =BS47-BT47 -> 0 | BV47: 0 | BW47: =IF(LEN(AJ47)=0,"EBITDA missing",IF(AJ47>10000,"EBITDA bad",IF(AJ47<=15,"15-",IF(AJ47>=30,"30+","15-30")))) -> 15- | BX47: =IF(AE47<=0.25,"<0.25",IF(AE47>1.5,">1.50","0.25-1.50")) -> <0.25 | BZ47: =IF(K47="FL",K47&" "&BW47,IF(K47="FLLO",IF(OR(BX47="<0.25",BY47="FL"),"FL"&" "&BW47,K47&" "&BX47),K47)) -> FL 15-
A48: Research Now Group, LLC and Dynata, LLC - First Out Term Loan | C48: 45777 | D48: PennantPark Investment Funding I | E48: Research Now / SSI (1st) | F48: PNNT 53 | G48: First Lien | H48: 1584191.6 | J48: USD | K48: FL | L48: Diversified Consumer Services | M48: Float | N48: =+VLOOKUP(A48, [2]Sheet2!$M$3:$Z$76, 14, FALSE) -> 0.0958459 | O48: SOFR | P48: 0.01 | Q48: =+VLOOKUP($A48, [2]Sheet2!$M$3:$Z$76, 13, FALSE) -> 0.0526 | R48: 3 | T48: Senior Secured | U48: =YEARFRAC(C48,V48) -> 3.2083333 | V48: 46949 | W48: USA | X48: 100 | AB48: 203 | AC48: 2.8116343 | AD48: 3.3596059 | AF48: 4.591133 | AG48: =+VLOOKUP($A48, [2]Sheet2!$M$3:$X$76, 8, FALSE) -> 45657 | AI48: =+VLOOKUP(A48, [2]Sheet2!$M$3:$X$76, 9, FALSE) -> 4.4571244 | AJ48: =+VLOOKUP($A48, [2]Sheet2!$M$3:$X$76, 10, FALSE) -> 159.053 | AK48: =AD48-AI48 -> -1.0975184 | AM48: =+VLOOKUP($A48, [2]Sheet2!$M$3:$X$76, 11, FALSE) -> 4.4571244 | AN48: =AF48-AM48 -> 0.13400865 | AO48: =+VLOOKUP($A48, [2]Sheet2!$M$3:$X$76, 12, FALSE) -> 1.2681832 | AP48: =AC48-AO48 -> 1.5434512 | AS48: Cov-Lite | AT48: Yes | AU48: No | AW48: SETTLED | AX48: 1584191.6 | AZ48: =+AX48-AY48 -> 1584191.6 | BB48: Y | BC48: N | BD48: 100 | BE48: =IF(LEFT(BZ48,3)="FL ",0,1) -> 0 | BF48: =IF(OR(J48="FLLO",L48="2L"),1,0) -> 0 | BG48: =IF(L48="2L",1,0) -> 0 | BH48: =IF(J48="USD",0,1) -> 0 | BI48: =IF(W48="USA",0,1) -> 0 | BJ48: =IF(AJ48<15,1,0) -> 0 | BK48: =IF(AJ48<10,1,0) -> 0 | BL48: =IF(BA48="Yes",1,0) -> 0 | BM48: =IF(AT48="Yes",1,0) -> 1 | BN48: =IF(AI48>5.5,1,0) -> 0 | BO48: =IF(M48="Fixed",1,0) -> 0 | BP48: =IF(AU48="Yes",1,0) -> 0 | BQ48: =H48 -> 1584191.6 | BR48: 100 | BS48: =BR48*AZ48/100 -> 1584191.6 | BU48: =BS48-BT48 -> 1584191.6 | BV48: 0 | BW48: =IF(LEN(AJ48)=0,"EBITDA missing",IF(AJ48>10000,"EBITDA bad",IF(AJ48<=15,"15-",IF(AJ48>=30,"30+","15-30")))) -> 30+ | BX48: =IF(AE48<=0.25,"<0.25",IF(AE48>1.5,">1.50","0.25-1.50")) -> <0.25 | BZ48: =IF(K48="FL",K48&" "&BW48,IF(K48="FLLO",IF(OR(BX48="<0.25",BY48="FL"),"FL"&" "&BW48,K48&" "&BX48),K48)) -> FL 30+
A49: Research Now Group, LLC and Dynata, LLC-Last Out Term loan | C49: 45777 | D49: PennantPark Investment Funding I | E49: Research Now / SSI (1st) | F49: PNNT 54 | G49: First Lien | H49: 5754732.7 | J49: USD | K49: FLLO | L49: Diversified Consumer Services | M49: Float | N49: =+VLOOKUP(A49, [2]Sheet2!$M$3:$Z$76, 14, FALSE) -> 0.0958459 | O49: SOFR | P49: 0.01 | Q49: =+VLOOKUP($A49, [2]Sheet2!$M$3:$Z$76, 13, FALSE) -> 0.0526 | R49: 3 | T49: Senior Secured | U49: =YEARFRAC(C49,V49) -> 3.4583333 | V49: 47041 | W49: USA | X49: 100 | AB49: 203 | AC49: 2.8116343 | AD49: 3.3596059 | AF49: 4.591133 | AG49: =+VLOOKUP($A49, [2]Sheet2!$M$3:$X$76, 8, FALSE) -> 45657 | AI49: =+VLOOKUP(A49, [2]Sheet2!$M$3:$X$76, 9, FALSE) -> 4.4571244 | AJ49: =+VLOOKUP($A49, [2]Sheet2!$M$3:$X$76, 10, FALSE) -> 159.053 | AK49: =AD49-AI49 -> -1.0975184 | AM49: =+VLOOKUP($A49, [2]Sheet2!$M$3:$X$76, 11, FALSE) -> 4.4571244 | AN49: =AF49-AM49 -> 0.13400865 | AO49: =+VLOOKUP($A49, [2]Sheet2!$M$3:$X$76, 12, FALSE) -> 1.2681832 | AP49: =AC49-AO49 -> 1.5434512 | AS49: Cov-Lite | AT49: Yes | AU49: No | AW49: SETTLED | AX49: 5754732.7 | AZ49: =+AX49-AY49 -> 5754732.7 | BB49: Y | BC49: N | BD49: 92.4 | BE49: =IF(LEFT(BZ49,3)="FL ",0,1) -> 1 | BF49: =IF(OR(J49="FLLO",L49="2L"),1,0) -> 0 | BG49: =IF(L49="2L",1,0) -> 0 | BH49: =IF(J49="USD",0,1) -> 0 | BI49: =IF(W49="USA",0,1) -> 0 | BJ49: =IF(AJ49<15,1,0) -> 0 | BK49: =IF(AJ49<10,1,0) -> 0 | BL49: =IF(BA49="Yes",1,0) -> 0 | BM49: =IF(AT49="Yes",1,0) -> 1 | BN49: =IF(AI49>5.5,1,0) -> 0 | BO49: =IF(M49="Fixed",1,0) -> 0 | BP49: =IF(AU49="Yes",1,0) -> 0 | BQ49: =H49 -> 5754732.7 | BR49: 100 | BS49: =BR49*AZ49/100 -> 5754732.7 | BU49: =BS49-BT49 -> 5754732.7 | BV49: 0 | BW49: =IF(LEN(AJ49)=0,"EBITDA missing",IF(AJ49>10000,"EBITDA bad",IF(AJ49<=15,"15-",IF(AJ49>=30,"30+","15-30")))) -> 30+ | BX49: =IF(AE49<=0.25,"<0.25",IF(AE49>1.5,">1.50","0.25-1.50")) -> <0.25 | BZ49: =IF(K49="FL",K49&""&BW49,IF(K49="FLLO",IF(OR(BX49="<0.25",BY49="FL"),"FL"&" "&BW49,K49&" "&BX49),K49)) -> FLLO
A50: RTIC subsidiary Holdings, LLC | C50: 45777 | D50: PennantPark Investment Funding I | E50: RTIC (TL) | F50: PNNT 55 | G50: First Lien | H50: 12885088 | J50: USD | K50: FL | L50: Leisure Products | M50: Float | N50: =+VLOOKUP(A50, [2]Sheet2!$M$3:$Z$76, 14, FALSE) -> 0.100492 | O50: SOFR | P50: 0.01 | Q50: =+VLOOKUP($A50, [2]Sheet2!$M$3:$Z$76, 13, FALSE) -> 0.0575 | R50: 3 | T50: Senior Secured | U50: =YEARFRAC(C50,V50) -> 4.0083333 | V50: 47241 | W50: USA | X50: 100 | AB50: 30.58 | AC50: 1.75 | AD50: 3.92 | AF50: 3.92 | AG50: =+VLOOKUP($A50, [2]Sheet2!$M$3:$X$76, 8, FALSE) -> 45716 | AI50: =+VLOOKUP(A50, [2]Sheet2!$M$3:$X$76, 9, FALSE) -> 4.9428833 | AJ50: =+VLOOKUP($A50, [2]Sheet2!$M$3:$X$76, 10, FALSE) -> 27.504242 | AK50: =AD50-AI50 -> -1.0228833 | AM50: =+VLOOKUP($A50, [2]Sheet2!$M$3:$X$76, 11, FALSE) -> 4.9428833 | AN50: =AF50-AM50 -> -1.0228833 | AO50: =+VLOOKUP($A50, [2]Sheet2!$M$3:$X$76, 12, FALSE) -> 1.5549156 | AP50: =AC50-AO50 -> 0.19508435 | AS50: Maintenance Covenants | AT50: No | AU50: No | AW50: SETTLED | AX50: 12885088 | AZ50: =+AX50-AY50 -> 12885088 | BB50: Y | BC50: Y | BD50: 100 | BE50: =IF(LEFT(BZ50,3)="FL ",0,1) -> 0 | BF50: =IF(OR(J50="FLLO",L50="2L"),1,0) -> 0 | BG50: =IF(L50="2L",1,0) -> 0 | BH50: =IF(J50="USD",0,1) -> 0 | BI50: =IF(W50="USA",0,1) -> 0 | BJ50: =IF(AJ50<15,1,0) -> 0 | BK50: =IF(AJ50<10,1,0) -> 0 | BL50: =IF(BA50="Yes",1,0) -> 0 | BM50: =IF(AT50="Yes",1,0) -> 0 | BN50: =IF(AI50>5.5,1,0) -> 0 | BO50: =IF(M50="Fixed",1,0) -> 0 | BP50: =IF(AU50="Yes",1,0) -> 0 | BQ50: =H50 -> 12885088 | BR50: 100 | BS50: =BR50*AZ50/100 -> 12885088 | BU50: =BS50-BT50 -> 12885088 | BV50: 0 | BW50: =IF(LEN(AJ50)=0,"EBITDA missing",IF(AJ50>10000,"EBITDA bad",IF(AJ50<=15,"15-",IF(AJ50>=30,"30+","15-30")))) -> 15-30 | BX50: =IF(AE50<=0.25,"<0.25",IF(AE50>1.5,">1.50","0.25-1.50")) -> <0.25 | BZ50: =IF(K50="FL",K50&" "&BW50,IF(K50="FLLO",IF(OR(BX50="<0.25",BY50="FL"),"FL"&" "&BW50,K50&" "&BX50),K50)) -> FL 15-30
A51: SV- Aero Holdings, LLC (Aeronix) | C51: 45777 | D51: PennantPark Investment Funding I | E51: Aeronix (TL) | F51: PNNT 5 | G51: First Lien | H51: 795000 | J51: USD | K51: FL | L51: Aerospace & Defense | M51: Float | N51: =+VLOOKUP(A51, [2]Sheet2!$M$3:$Z$76, 14, FALSE) -> 0.095492 | O51: SOFR | P51: 0.01 | Q51: =+VLOOKUP($A51, [2]Sheet2!$M$3:$Z$76, 13, FALSE) -> 0.0525 | R51: 3 | T51: Senior Secured | U51: =YEARFRAC(C51,V51) -> 5.5027778 | V51: 47788 | W51: USA | X51: 100 | AB51: 35.323874 | AC51: 6.5855168 | AD51: 2.0735671 | AF51: 2.0735671 | AG51: =+VLOOKUP($A51, [2]Sheet2!$M$3:$X$76, 8, FALSE) -> 45657 | AI51: =+VLOOKUP(A51, [2]Sheet2!$M$3:$X$76, 9, FALSE) -> 3.4534394 | AJ51: =+VLOOKUP($A51, [2]Sheet2!$M$3:$X$76, 10, FALSE) -> 65.760529 | AK51: =AD51-AI51 -> -1.3798722 | AM51: =+VLOOKUP($A51, [2]Sheet2!$M$3:$X$76, 11, FALSE) -> 3.4534394 | AN51: =AF51-AM51 -> -1.3798722 | AO51: =+VLOOKUP($A51, [2]Sheet2!$M$3:$X$76, 12, FALSE) -> 2.391292 | AP51: =AC51-AO51 -> 4.1942249 | AS51: Maintenance Covenants | AT51: No | AU51: No | AW51: SETTLED | AX51: 795000 | AZ51: =+AX51-AY51 -> 795000 | BB51: Y | BC51: Y | BD51: 100 | BE51: =IF(LEFT(BZ51,3)="FL ",0,1) -> 0 | BF51: =IF(OR(J51="FLLO",L51="2L"),1,0) -> 0 | BG51: =IF(L51="2L",1,0) -> 0 | BH51: =IF(J51="USD",0,1) -> 0 | BI51: =IF(W51="USA",0,1) -> 0 | BJ51: =IF(AJ51<15,1,0) -> 0 | BK51: =IF(AJ51<10,1,0) -> 0 | BL51: =IF(BA51="Yes",1,0) -> 0 | BM51: =IF(AT51="Yes",1,0) -> 0 | BN51: =IF(AI51>5.5,1,0) -> 0 | BO51: =IF(M51="Fixed",1,0) -> 0 | BP51: =IF(AU51="Yes",1,0) -> 0 | BQ51: =H51 -> 795000 | BR51: 100 | BS51: =BR51*AZ51/100 -> 795000 | BU51: =BS51-BT51 -> 795000 | BV51: 0 | BW51: =IF(LEN(AJ51)=0,"EBITDA missing",IF(AJ51>10000,"EBITDA bad",IF(AJ51<=15,"15-",IF(AJ51>=30,"30+","15-30")))) -> 30+ | BX51: =IF(AE51<=0.25,"<0.25",IF(AE51>1.5,">1.50","0.25-1.50")) -> <0.25 | BZ51: =IF(K51="FL",K51&" "&BW51,IF(K51="FLLO",IF(OR(BX51="<0.25",BY51="FL"),"FL"&" "&BW51,K51&" "&BX51),K51)) -> FL 30+
A52: Sabel Systems Technology Solutions, LLC | C52: 45777 | D52: PennantPark Investment Funding I | E52: Sabel Systems (Term Loan) | F52: PNNT 102 | G52: First Lien | H52: 5985000 | J52: USD | K52: FL | L52: IT Services | M52: Float | N52: =+VLOOKUP(A52, [2]Sheet2!$M$3:$Z$76, 14, FALSE) -> 0.105492 | O52: SOFR | P52: 0.01 | Q52: =+VLOOKUP($A52, [2]Sheet2!$M$3:$Z$76, 13, FALSE) -> 0.0625 | R52: 3 | T52: Senior Secured | U52: =YEARFRAC(C52,V52) -> 5.5 | V52: 47787 | W52: USA | X52: 100 | AB52: 22.676727 | AC52: 2.1804545 | AD52: 3.5376566 | AF52: 3.5376566 | AG52: =+VLOOKUP($A52, [2]Sheet2!$M$3:$X$76, 8, FALSE) -> 45688 | AI52: =+VLOOKUP(A52, [2]Sheet2!$M$3:$X$76, 9, FALSE) -> 3.2375411 | AJ52: =+VLOOKUP($A52, [2]Sheet2!$M$3:$X$76, 10, FALSE) -> 23.808713 | AK52: =AD52-AI52 -> 0.3001155 | AM52: =+VLOOKUP($A52, [2]Sheet2!$M$3:$X$76, 11, FALSE) -> 3.2375411 | AN52: =AF52-AM52 -> 0.3001155 | AO52: =+VLOOKUP($A52, [2]Sheet2!$M$3:$X$76, 12, FALSE) -> 2.2892993 | AP52: =AC52-AO52 -> -0.10884478 | AS52: Maintenance Covenants | AT52: No | AU52: No | AW52: SETTLED | AX52: 5985000 | AZ52: =+AX52-AY52 -> 5985000 | BB52: Y | BC52: N | BD52: 100 | BE52: =IF(LEFT(BZ52,3)="FL ",0,1) -> 0 | BF52: =IF(OR(J52="FLLO",L52="2L"),1,0) -> 0 | BG52: =IF(L52="2L",1,0) -> 0 | BH52: =IF(J52="USD",0,1) -> 0 | BI52: =IF(W52="USA",0,1) -> 0 | BJ52: =IF(AJ52<15,1,0) -> 0 | BK52: =IF(AJ52<10,1,0) -> 0 | BL52: =IF(BA52="Yes",1,0) -> 0 | BM52: =IF(AT52="Yes",1,0) -> 0 | BN52: =IF(AI52>5.5,1,0) -> 0 | BO52: =IF(M52="Fixed",1,0) -> 0 | BP52: =IF(AU52="Yes",1,0) -> 0 | BQ52: =H52 -> 5985000 | BR52: 100 | BS52: =BR52*AZ52/100 -> 5985000 | BU52: =BS52-BT52 -> 5985000 | BW52: =IF(LEN(AJ52)=0,"EBITDA missing",IF(AJ52>10000,"EBITDA bad",IF(AJ52<=15,"15-",IF(AJ52>=30,"30+","15-30")))) -> 15-30 | BX52: =IF(AE52<=0.25,"<0.25",IF(AE52>1.5,">1.50","0.25-1.50")) -> <0.25 | BZ52: =IF(K52="FL",K52&" "&BW52,IF(K52="FLLO",IF(OR(BX52="<0.25",BY52="FL"),"FL"&" "&BW52,K52&" "&BX52),K52)) -> FL 15-30
A53: Security 101 | C53: 45777 | D53: PennantPark Investment Funding I | E53: Security 101 (TL) | F53: PNNT 57 | G53: First Lien | H53: 0 | J53: USD | K53: FL | L53: Electronic Equipment, Instruments & Components | M53: Float | N53: =+VLOOKUP(A53, [2]Sheet2!$M$3:$Z$76, 14, FALSE) -> 0.099604 | O53: SOFR | P53: 0.01 | Q53: =+VLOOKUP($A53, [2]Sheet2!$M$3:$Z$76, 13, FALSE) -> 0.0565 | R53: 3 | T53: Senior Secured | U53: =YEARFRAC(C53,V53) -> 1.6638889 | V53: 46385 | W53: USA | X53: 100 | AB53: 23.406038 | AC53: 2.9782795 | AD53: 4.0673265 | AF53: 4.0673265 | AG53: =+VLOOKUP($A53, [2]Sheet2!$M$3:$X$76, 8, FALSE) -> 45716 | AI53: =+VLOOKUP(A53, [2]Sheet2!$M$3:$X$76, 9, FALSE) -> 3.101152 | AJ53: =+VLOOKUP($A53, [2]Sheet2!$M$3:$X$76, 10, FALSE) -> 32.781397 | AK53: =AD53-AI53 -> 0.96617449 | AM53: =+VLOOKUP($A53, [2]Sheet2!$M$3:$X$76, 11, FALSE) -> 3.101152 | AN53: =AF53-AM53 -> 0.96617449 | AO53: =+VLOOKUP($A53, [2]Sheet2!$M$3:$X$76, 12, FALSE) -> 2.9570394 | AP53: =AC53-AO53 -> 0.021240033 | AS53: Maintenance Covenants | AT53: No | AU53: No | AW53: SETTLED | AX53: 0 | AZ53: =+AX53-AY53 -> 0 | BB53: Y | BC53: N | BD53: 100 | BE53: =IF(LEFT(BZ53,3)="FL ",0,1) -> 0 | BF53: =IF(OR(J53="FLLO",L53="2L"),1,0) -> 0 | BG53: =IF(L53="2L",1,0) -> 0 | BH53: =IF(J53="USD",0,1) -> 0 | BI53: =IF(W53="USA",0,1) -> 0 | BJ53: =IF(AJ53<15,1,0) -> 0 | BK53: =IF(AJ53<10,1,0) -> 0 | BL53: =IF(BA53="Yes",1,0) -> 0 | BM53: =IF(AT53="Yes",1,0) -> 0 | BN53: =IF(AI53>5.5,1,0) -> 0 | BO53: =IF(M53="Fixed",1,0) -> 0 | BP53: =IF(AU53="Yes",1,0) -> 0 | BQ53: =H53 -> 0 | BR53: 100 | BS53: =BR53*AZ53/100 -> 0 | BU53: =BS53-BT53 -> 0 | BV53: 0 | BW53: =IF(LEN(AJ53)=0,"EBITDA missing",IF(AJ53>10000,"EBITDA bad",IF(AJ53<=15,"15-",IF(AJ53>=30,"30+","15-30")))) -> 30+ | BX53: =IF(AE53<=0.25,"<0.25",IF(AE53>1.5,">1.50","0.25-1.50")) -> <0.25 | BZ53: =IF(K53="FL",K53&" "&BW53,IF(K53="FLLO",IF(OR(BX53="<0.25",BY53="FL"),"FL"&" "&BW53,K53&" "&BX53),K53)) -> FL 30+
