Workbook
Name DDcommit: 'Balance Sheet'!$H$76

Sheet Balance Sheet
B1: PennantPark Investment Corporation
B2: Trial Balance / Sub Chapter M Test
B3: ='BDC post TB'!D6 -> 01/31/2026:23:59:59
D5: With | F5: Without
B6: Assets | D6: Unfunded | F6: Unfunded
A7: a | B7: Investments at fair value | D7: =SUMIF(Summary!O:O,'Balance Sheet'!A7,Summary!N:N) -> 9.6055743e+08 | F7: =SUMIF(Summary!O:O,'Balance Sheet'!A7,Summary!N:N) -> 9.6055743e+08
A8: b1 | B8: Cash (See Note 8) | D8: =SUMIF(Summary!O:O,'Balance Sheet'!A8,Summary!N:N) -> 17258028 | F8: =SUMIF(Summary!O:O,'Balance Sheet'!A8,Summary!N:N) -> 17258028 | I8: =D8+D9-(SUMIF('BDC post TB'!D:D,J8,'BDC post TB'!J:J)+SUMIF('SBICII post TB (closed)'!D:D,J8,'SBICII post TB (closed)'!J:J)+SUMIF('BDC post TB'!E:E,K8,'BDC post TB'!J:J)+SUMIF('SBICII post TB (closed)'!E:E,K8,'SBICII post TB (closed)'!J:J)) -> 0 | J8: Cash | K8: MoneyMarket
A9: b2 | B9: Cash Equivalents | D9: =SUMIF(Summary!O:O,'Balance Sheet'!A9,Summary!N:N) -> 30530529 | F9: =SUMIF(Summary!O:O,'Balance Sheet'!A9,Summary!N:N) -> 30530529
A10: c | B10: Interest receivable | D10: =SUMIF(Summary!O:O,'Balance Sheet'!A10,Summary!N:N) -> 9324098.6 | F10: =SUMIF(Summary!O:O,'Balance Sheet'!A10,Summary!N:N) -> 9324098.6
A11: d1 | B11: Receivable for investments sold | D11: =SUMIF(Summary!O:O,'Balance Sheet'!A11,Summary!N:N) -> 73832136 | F11: =D11 -> 73832136 | I11: =D11-'Rec-Pay-Month End'!M49 -> 0
A12: d2 | B12: DistributionsReceivable | D12: =SUMIF(Summary!O:O,'Balance Sheet'!A12,Summary!N:N) -> 230769 | F12: =SUMIF(Summary!O:O,'Balance Sheet'!A12,Summary!N:N) -> 230769
A13: dd | B13: Due From Affiliates | D13: =SUMIF(Summary!O:O,'Balance Sheet'!A13,Summary!N:N) -> 81285.15 | F13: =SUMIF(Summary!O:O,'Balance Sheet'!A13,Summary!N:N) -> 81285.15
A14: d | B14: Prepaid expenses and other assets | D14: =SUMIF(Summary!O:O,'Balance Sheet'!A14,Summary!N:N) -> 322349.9 | F14: =SUMIF(Summary!O:O,'Balance Sheet'!A14,Summary!N:N) -> 322349.9
B15: Total assets | D15: =SUM(D6:D14) -> 1.0921366e+09 | F15: =SUM(F6:F14) -> 1.0921366e+09
B17: Liabilities
A18: e | B18: Distributions payable | D18: =-SUMIF(Summary!O:O,'Balance Sheet'!A18,Summary!N:N) -> 5223687.5 | F18: =-SUMIF(Summary!O:O,'Balance Sheet'!A18,Summary!N:N) -> 5223687.5
A19: f | B19: Payable for investments purchased | D19: =-SUMIF(Summary!O:O,'Balance Sheet'!A19,Summary!N:N)+'Rec-Pay-Month End'!M69 -> 4900000 | F19: =D19 -> 4900000 | I19: =D19+'Rec-Pay-Month End'!M59 -> 0
A20: g | B20: Unfunded investments | D20: =-SUMIF(Summary!O:O,'Balance Sheet'!A20,Summary!N:N) -> 0 | F20: =-SUMIF(Summary!O:O,'Balance Sheet'!A20,Summary!N:N) -> 0
A21: h | B21: Credit Facility payable | D21: =-SUMIF(Summary!O:O,'Balance Sheet'!A21,Summary!N:N) -> 2.2146872e+08 | F21: =-SUMIF(Summary!O:O,'Balance Sheet'!A21,Summary!N:N) -> 2.2146872e+08 | H21: =F21+Summary!N20+Summary!N142 -> 2.2146872e+08
A22: i2 | B22: 2024 Notes Payable | C22: DUMPNNTG2024 | D22: =-SUMIF(Summary!O:O,'Balance Sheet'!A22,Summary!N:N)+-SUMIF('BDC Long Short'!D:D,'Balance Sheet'!C22,'BDC Long Short'!L:L) -> 0 | F22: =D22 -> 0 | H22: =-Summary!I28-Summary!I55-Summary!I56-Summary!I57+Summary!N20 -> 3.8899083e+08
A23: i3 | B23: 2026 Notes Payable | C23: DUMPNNTG2026 | D23: =-SUMIF(Summary!O:O,'Balance Sheet'!A23,Summary!N:N)+-SUMIF('BDC Long Short'!D:D,'Balance Sheet'!C23,'BDC Long Short'!L:L) -> 1.4977316e+08 | F23: =D23 -> 1.4977316e+08
A24: i4 | B24: Nov 2026 Notes Payable | C24: DUMPNNT112026 | D24: =-SUMIF(Summary!O:O,'Balance Sheet'!A24,Summary!N:N)+-SUMIF('BDC Long Short'!D:D,'Balance Sheet'!C24,'BDC Long Short'!L:L) -> 1.6421767e+08 | F24: =D24 -> 1.6421767e+08
A25: i5 | B25: Feb 2029 Notes Payable | C25: DUMPNNT022029 | D25: =-SUMIF(Summary!O:O,'Balance Sheet'!A25,Summary!N:N)+-SUMIF('BDC Long Short'!D:D,'Balance Sheet'!C25,'BDC Long Short'!L:L) -> 73607190 | F25: =D25 -> 73607190
A26: j | B26: Interest payable on Credit Facility, and Notes | D26: =-SUMIF(Summary!O:O,'Balance Sheet'!A26,Summary!N:N) -> 4211755.6 | F26: =D26 -> 4211755.6
A27: k | B27: Management fee payable | D27: =-SUMIF(Summary!O:O,'Balance Sheet'!A27,Summary!N:N) -> 3915499 | F27: =-SUMIF(Summary!O:O,'Balance Sheet'!A27,Summary!N:N) -> 3915499
A28: l | B28: Performance-based incentive fee payable | D28: =-SUMIF(Summary!O:O,'Balance Sheet'!A28,Summary!N:N) -> 0 | F28: =-SUMIF(Summary!O:O,'Balance Sheet'!A28,Summary!N:N) -> 0
A29: mm | B29: Deferred tax liability | D29: =-SUMIF(Summary!O:O,'Balance Sheet'!A29,Summary!N:N) -> 0 | F29: =D29 -> 0
A30: nn | B30: Due to Affiliates | D30: =-SUMIF(Summary!O:O,'Balance Sheet'!A30,Summary!N:N) -> 0 | F30: =-SUMIF(Summary!O:O,'Balance Sheet'!A30,Summary!N:N) -> 0
A31: m | B31: Accrued other expenses | D31: =-SUMIF(Summary!O:O,'Balance Sheet'!A31,Summary!N:N) -> 5559686.4 | F31: =-SUMIF(Summary!O:O,'Balance Sheet'!A31,Summary!N:N) -> 5559686.4
B32: Total liabilities | D32: =SUM(D17:D31) -> 6.3287737e+08 | F32: =SUM(F17:F31) -> 6.3287737e+08
B34: Net assets
A35: n | B35: Common stock, | D35: =-SUMIF(Summary!O:O,'Balance Sheet'!A35,Summary!N:N) -> 65296.14 | F35: =-SUMIF(Summary!O:O,'Balance Sheet'!A35,Summary!N:N) -> 65296.14 | I35: PRIOR YEAR
A36: o | B36: Paid-in capital in excess of par value | D36: =-SUMIF(Summary!O:O,'Balance Sheet'!A36,Summary!N:N)-I36 -> 7.405063e+08 | F36: =-SUMIF(Summary!O:O,'Balance Sheet'!A36,Summary!N:N)-I36 -> 7.405063e+08
A37: p | B37: Undistributed net investment income | D37: =-SUMIF(Summary!O:O,'Balance Sheet'!A37,Summary!N:N)+'Income Statement'!G25+'Balance Sheet'!I37 -> 40800451 | F37: =-SUMIF(Summary!O:O,'Balance Sheet'!A37,Summary!N:N)+'Income Statement'!G25+'Balance Sheet'!I37 -> 40800451 | I37: =47474252.5600001+3394442 -> 50868695
A38: q | B38: Accumulated net realized loss on investments | D38: =+I38+'Income Statement'!G28 -> -3.0449104e+08 | F38: =+I38+'Income Statement'!G28 -> -3.0449104e+08 | I38: =-365072732.94+67497 -> -3.6500524e+08
B39: Accumulated net realized FX loss | D39: =+I39+'Income Statement'!G29 -> -8839.89 | F39: =+I39+'Income Statement'!G29 -> -8839.89 | I39: 258362.51
B40: Accumulated net realized loss on debt | D40: =+I40+'Income Statement'!G30 -> -3211181.9 | F40: =+I40+'Income Statement'!G30 -> -3211181.9 | I40: -3211181.9
A41: r | B41: Net unrealized depreciation on investments | D41: =+I41+'Income Statement'!G33 -> -3449916.2 | F41: =+I41+'Income Statement'!G33 -> -3449916.2 | I41: 50415555
B42: Provision for taxes on unrealized appreciation (depreciation) on investments | D42: =+I42+'Income Statement'!G36 -> 0 | F42: =+I42+'Income Statement'!G36 -> 0 | I42: 0
B43: Provision for taxes on realized gain on investments | D43: =+I43+'Income Statement'!G37 -> -10939359 | F43: =+I43+'Income Statement'!G37 -> -10939359 | I43: -10926504
A44: s | B44: Net unrealized depreciation on Credit Facility | D44: =+I44+'Income Statement'!G34 -> -12453.81 | F44: =+I44+'Income Statement'!G34 -> -12453.81 | I44: 978902.3
B45: Total net assets | D45: =SUM(D35:D44) -> 4.5925926e+08 | F45: =SUM(F35:F44) -> 4.5925926e+08
B46: Total liabilities and net assets | D46: =+D32+D45 -> 1.0921366e+09 | F46: =+F32+F45 -> 1.0921366e+09 | I46: =+D46-D15 -> -0.33999991 | J46: =+F15-F46 -> 0.33999991
B48: Total Outstanding shares | D48: =SUMIF('BDC post TB'!C:C,'Balance Sheet'!B48,'BDC post TB'!D:D) -> 65296094 | F48: =SUMIF('BDC post TB'!C:C,'Balance Sheet'!B48,'BDC post TB'!D:D) -> 65296094
B49: Net asset value per share | D49: =+D45/D48 -> 7.0334875 | F49: =+F45/F48 -> 7.0334875 | I49: =VLOOKUP(B49,'BDC post TB'!C:D,2,FALSE)-D49 -> -0.0034874572 | J49: =VLOOKUP(B49,'BDC post TB'!C:D,2,FALSE)-D49 -> -0.0034874572
A51: p | B51: 2026 Distributions Fiscal Year-to-date | D51: =+SUMIF(Summary!O:O,'Balance Sheet'!A51,Summary!N:N) -> 20894750 | F51: =+SUMIF(Summary!O:O,'Balance Sheet'!A51,Summary!N:N) -> 20894750
B53: Calculation of Asset Coverage - Section 18 (H) of The Investment Company Act of 1940 - as summarized
B54: in the SEC No-Action Letter:
B56: Total Assets Less non Senior debt | D56: =F56 -> 1.0697188e+09 | F56: =+F15-F32+H21+H22 -> 1.0697188e+09
B58: Total Senior Debt | D58: =F58 -> 6.1045955e+08 | F58: =+H21+H22 -> 6.1045955e+08
B60: Unfunded commitments | D60: 3.72107e+08 | F60: =D60 -> 3.72107e+08
B62: Total Net assets | D62: =F62 -> 4.5925926e+08 | F62: =+F45-Summary!I142-Summary!I20 -> 4.5925926e+08
B64: Asset Coverage Testing must be equal to or greater than 150% | D64: =(D56+D60)/(D58+D60) -> 1.4674078 | F64: =F56/F58 -> 1.7523173
B65: % of Leverage on NAV | D65: =(+D58+D60)/D62 -> 2.1394594 | F65: =F58/F62 -> 1.3292264
B68: Calculation of Asset Coverage - Without Exemptive Relief:
B70: Total Assets Less non Senior debt | D70: =F70 -> 1.0697188e+09 | F70: =F56 -> 1.0697188e+09
B72: Total Senior Debt | D72: =SUM(H21:H22) -> 6.1045955e+08 | F72: =SUM(H21:H22) -> 6.1045955e+08
B74: Unfunded commitments | D74: =D60 -> 3.72107e+08 | F74: =F60 -> 3.72107e+08
B76: Total Net assets | D76: =D62 -> 4.5925926e+08 | F76: =F62 -> 4.5925926e+08
B78: Asset Coverage Testing must be equal to or greater than 150% | D78: =(D70+D74)/(+D72+D74) -> 1.4674078 | F78: =F70/F72 -> 1.7523173
B79: % of Leverage on NAV | D79: =+(D72+D74)/D76 -> 2.1394594 | F79: =F72/F76 -> 1.3292264
B84: This report (“Report”) is being provided to the Fund(s) identified above as (i) an accommodation to and (ii) solely for informational purposes at the direction of and is solely for the benefit of the Fund(s) and is subject to the terms, conditions and limitations set forth in the Administration Agreement between the Fund(s) and The Bank of New York Mellon (or its affiliates) (collectively, “BNYM”). Notwithstanding anything in this Report to the contrary, no other person, including but not limited to investors in the Fund(s), shall have any rights, interest or claims hereunder or be entitled to any benefits under or on account of the Administration Agreement as a third-party beneficiary or otherwise. The recipient acknowledges that the Report is confidential and may not be disclosed to any third party without the prior written consent of BNYM.
B85: While this Report was prepared using sources and data believed to be reliable, the information contained herein is preliminary, unaudited, subject to change or later reversal and is provided “AS IS.” Any and all data and information included in this Report (“Data”) was collected solely at the direction of the Fund(s) and in the format directed by the Fund(s); BNY Mellon has exercised no discretion or judgment as to how such Data was collected or organized. BNYM makes no representations or warranties of any kind with respect to the Report or the information or Data contained herein, express or implied, in fact or in law, including but not limited to warranties as to accuracy, completeness, timeliness, suitability, merchantability, use or fitness for a particular purpose, and BNYM undertakes no duty to update any information contained in the Report. UNDER NO CIRCUMSTANCES SHALL THE REPORT BE CONSIDERED ADVICE OR A RECOMMENDATION WITH RESPECT TO THE FUND(S), SOLICITATION OR OFFER TO SELL AND/OR PURCHASE ANY SECURITY OR OTHERWISE BE RELIED UPON AS A BASIS FOR ANY ANALYSIS OR INVESTMENT DECISIONS MADE WITH RESPECT TO THE FUND(S). IF ANY OFFER OF INTERESTS IS MADE WITH RESPECT AN INVESTMENT IN THE FUND(S), IT SHALL BE PURSUANT TO A DEFINITIVE OFFERING MEMORANDUM PREPARED BY OR ON BEHALF OF THE FUND WHICH WOULD CONTAIN MATERIAL INFORMATION NOT CONTAINED HEREIN AND WHICH WOULD SUPERSEDE THIS INFORMATION IN ITS ENTIRETY. Past Performance is not indicative of future results. Neither BNYM nor its affiliates or their respective directors, officers or employees shall be responsible or liable for results from any use of the Report, any information or analysis contained therein, or any losses (whether direct, indirect, in contract, tort or otherwise) arising from any decision made or action taken by any party in reliance upon the Report.

Sheet Income Statement
B1: PennantPark Investment Corporation
B2: Income Statement
C5: FY 2026 Quarter to Date | G5: FY 2026
B6: Investment income: | C6: December - 2025 | D6: March - 2026 | E6: June - 2026 | F6: September - 2026 | G6: YEAR TO DATE
A7: a | B7: Interest | C7: 22534987 | D7: =G7-C7 -> 7130703.9 | G7: =-SUMIF(Summary!P:P,'Income Statement'!A7,Summary!N:N) -> 29665691
A8: b1a | B8: PSLF Membership Dividend | C8: 4183813 | D8: =G8-C8 -> 0 | G8: =-SUMIF(Summary!P:P,'Income Statement'!A8,Summary!N:N) -> 4183813
A9: b1b | B9: PTSF II Membership Dividend | C9: 230769 | D9: =G9-C9 -> 0 | G9: =-SUMIF(Summary!P:P,'Income Statement'!A9,Summary!N:N) -> 230769
A10: b3 | B10: Dividend Distribution Income | C10: 3720.89 | D10: =G10-C10 -> 8383.08 | G10: =-SUMIF(Summary!P:P,'Income Statement'!A10,Summary!N:N) -> 12103.97
A11: b2 | B11: Other income | C11: 300732.16 | D11: =G11-C11 -> 21157.91 | G11: =-SUMIF(Summary!P:P,'Income Statement'!A11,Summary!N:N) -> 321890.07
B12: Total investment income | C12: 27254022 | D12: =SUM(D7:D11) -> 7160244.8 | E12: =SUM(E7:E11) -> 0 | F12: =SUM(F7:F11) -> 0 | G12: =SUM(G7:G11) -> 34414267
B14: Expenses:
A15: c | B15: Base management fee | C15: 3915499 | D15: =G15-C15 -> 0 | G15: =SUMIF(Summary!P:P,'Income Statement'!A15,Summary!N:N) -> 3915499
A16: c1 | B16: Base management fee - Waiver | C16: 0 | D16: =G16-C16 -> 0 | G16: =SUMIF(Summary!P:P,'Income Statement'!A16,Summary!N:N) -> 0
A17: d | B17: Performance-based incentive fee | C17: 0 | D17: =G17-C17 -> 0 | G17: =SUMIF(Summary!P:P,'Income Statement'!A17,Summary!N:N) -> 0
A18: e | B18: Interest and expenses on Credit Facility | C18: 10500807 | D18: =G18-C18 -> 2835768.7 | G18: =SUMIF(Summary!P:P,'Income Statement'!A18,Summary!N:N) -> 13336576
A19: f | B19: Administrative services expenses | C19: 450000 | D19: =G19-C19 -> 150000 | G19: =SUMIF(Summary!P:P,'Income Statement'!A19,Summary!N:N) -> 600000
A20: g | B20: Other general and administrative expenses | C20: 849999.99 | D20: =G20-C20 -> 320821.74 | G20: =SUMIF(Summary!P:P,'Income Statement'!A20,Summary!N:N) -> 1170821.7
B21: Expenses before excise taxes | C21: 15716306 | D21: =SUM(D14:D20) -> 3306590.5 | E21: =SUM(E14:E20) -> 0 | F21: =SUM(F14:F20) -> 0 | G21: =SUM(G14:G20) -> 19022897
A22: h | B22: Excise tax | C22: 660000 | D22: =G22-C22 -> 0 | G22: =SUMIF(Summary!P:P,'Income Statement'!A22,Summary!N:N) -> 660000
A23: h1 | B23: Debt issuance costs - Credit Facility Amendment Fee | C23: 3885199.9 | D23: =G23-C23 -> 19663.75 | G23: =SUMIF(Summary!P:P,'Income Statement'!A23,Summary!N:N) -> 3904863.6
B24: Total expenses | C24: 20261506 | D24: =SUM(D21:D23) -> 3326254.2 | E24: =SUM(E21:E23) -> 0 | F24: =SUM(F21:F23) -> 0 | G24: =SUM(G21:G23) -> 23587760
B25: Net investment income | C25: 6992515.9 | D25: =D12-D24 -> 3833990.6 | E25: =E12-E24 -> 0 | F25: =F12-F24 -> 0 | G25: =G12-G24 -> 10826507
B27: Realized gain (loss) on investments and debt:
A28: i | B28: Net realized gain (loss) on non-controlled, non-affiliated investments | C28: 59282326 | D28: =G28-C28 -> 1231874.1 | G28: =-SUMIF(Summary!P:P,'Income Statement'!A28,Summary!N:N) -> 60514200
A29: l | B29: Net realized FX gain (loss) on non-controlled, non-affiliated investments | C29: -267390.28 | D29: =G29-C29 -> 187.88 | G29: =-SUMIF(Summary!P:P,'Income Statement'!A29,Summary!N:N) -> -267202.4
A30: ii | B30: Net realized gain (loss) on debt | C30: 0 | D30: =G30-C30 -> 0 | G30: =-SUMIF(Summary!P:P,'Income Statement'!A30,Summary!N:N) -> 0
B31: Net change in Realized Gain (Loss) | C31: 59014935 | D31: =SUM(D28:D30) -> 1232062 | E31: =SUM(E28:E30) -> 0 | F31: =SUM(F28:F30) -> 0 | G31: =SUM(G28:G30) -> 60246997
B32: Net change in unrealized appreciation (depreciation) on:
A33: j | B33: Investments | C33: -57051550 | D33: =G33-C33 -> 3186079.1 | G33: =-SUMIF(Summary!P:P,'Income Statement'!A33,Summary!N:N) -> -53865471
A34: k | B34: Debt Appreciation | C34: 12884.28 | D34: =G34-C34 -> -1004240.4 | G34: =-SUMIF(Summary!P:P,'Income Statement'!A34,Summary!N:N) -> -991356.11
B35: Net change in unrealized appreciation | C35: -57038666 | D35: =SUM(D33:D34) -> 2181838.7 | E35: =SUM(E33:E34) -> 0 | F35: =SUM(F33:F34) -> 0 | G35: =SUM(G33:G34) -> -54856827
A36: jj | B36: Provision for taxes on unrealized appreciation (depreciation) on investments | C36: 0 | D36: =G36-C36 -> 0 | G36: =-SUMIF(Summary!P:P,'Income Statement'!A36,Summary!N:N) -> 0
A37: kk | B37: Provision for taxes on realized gain on investments | C37: -12855 | D37: =G37-C37 -> 0 | G37: =-SUMIF(Summary!P:P,'Income Statement'!A37,Summary!N:N) -> -12855
B39: Net Realized and unrealized gain (loss) on investments and debt: | C39: 1963414.1 | D39: =D31+D35+SUM(D36:D37) -> 3413900.7 | G39: =G31+G35+G36+G37 -> 5377314.9
B41: Net increase in net assets resulting from operations | C41: 8955930 | D41: =D25+D39 -> 7247891.3 | G41: =+G25+G39 -> 16203821 | I41: =SUMIF('BDC post TB'!C:C,"=Revenue",'BDC post TB'!J:J)+SUMIF('BDC post TB'!C:C,"=Expense",'BDC post TB'!J:J)+G41-G46 -> 0 | J41: income check
B42: Net increase in net assets resulting from operations per share | C42: 0.13715874 | D42: =D41/'Balance Sheet'!D48 -> 0.11100038 | G42: =+G41/'Balance Sheet'!D48 -> 0.24815912 | J42: must be 0
B44: Net investment income per common share | C44: 0.10708934 | D44: =D25/'Balance Sheet'!D48 -> 0.058716998 | G44: =+G25/'Balance Sheet'!D48 -> 0.16580634
A46: p | B46: Distributions | C46: 15671063 | D46: =G46-C46 -> 5223687.5 | G46: =+'Balance Sheet'!D51 -> 20894750
B49: This report (“Report”) is being provided to the Fund(s) identified above as (i) an accommodation to and (ii) solely for informational purposes at the direction of and is solely for the benefit of the Fund(s) and is subject to the terms, conditions and limitations set forth in the Administration Agreement between the Fund(s) and The Bank of New York Mellon (or its affiliates) (collectively, “BNYM”). Notwithstanding anything in this Report to the contrary, no other person, including but not limited to investors in the Fund(s), shall have any rights, interest or claims hereunder or be entitled to any benefits under or on account of the Administration Agreement as a third-party beneficiary or otherwise. The recipient acknowledges that the Report is confidential and may not be disclosed to any third party without the prior written consent of BNYM.
B50: While this Report was prepared using sources and data believed to be reliable, the information contained herein is preliminary, unaudited, subject to change or later reversal and is provided “AS IS.” Any and all data and information included in this Report (“Data”) was collected solely at the direction of the Fund(s) and in the format directed by the Fund(s); BNY Mellon has exercised no discretion or judgment as to how such Data was collected or organized. BNYM makes no representations or warranties of any kind with respect to the Report or the information or Data contained herein, express or implied, in fact or in law, including but not limited to warranties as to accuracy, completeness, timeliness, suitability, merchantability, use or fitness for a particular purpose, and BNYM undertakes no duty to update any information contained in the Report. UNDER NO CIRCUMSTANCES SHALL THE REPORT BE CONSIDERED ADVICE OR A RECOMMENDATION WITH RESPECT TO THE FUND(S), SOLICITATION OR OFFER TO SELL AND/OR PURCHASE ANY SECURITY OR OTHERWISE BE RELIED UPON AS A BASIS FOR ANY ANALYSIS OR INVESTMENT DECISIONS MADE WITH RESPECT TO THE FUND(S). IF ANY OFFER OF INTERESTS IS MADE WITH RESPECT AN INVESTMENT IN THE FUND(S), IT SHALL BE PURSUANT TO A DEFINITIVE OFFERING MEMORANDUM PREPARED BY OR ON BEHALF OF THE FUND WHICH WOULD CONTAIN MATERIAL INFORMATION NOT CONTAINED HEREIN AND WHICH WOULD SUPERSEDE THIS INFORMATION IN ITS ENTIRETY. Past Performance is not indicative of future results. Neither BNYM nor its affiliates or their respective directors, officers or employees shall be responsible or liable for results from any use of the Report, any information or analysis contained therein, or any losses (whether direct, indirect, in contract, tort or otherwise) arising from any decision made or action taken by any party in reliance upon the Report.

Sheet Summary
I1: Legend
I2: A | J2: Eliminates Intercompany Investment in Subsidiary Accounts & Balance Sheet Accounts.
I3: B | J3: Eliminates Intercompany Equity Accounts.
I4: C | J4: Eliminates Intercompany Income Accounts.
J6: Elimination Entries | N6: Consolidated Post-Elimination
B7: Section | C7: Group | D7: Financial Account | E7: Description | F7: BDC | G7: SBIC I | H7: SBIC II | I7: Total | J7: A | K7: B | L7: C | M7: Topside | N7: Closing Balance | O7: Balance Sheet | P7: Income Statement | Q7: Contra Liabilities
A8: =CONCATENATE(D8,E8) -> Debt InstrumentsAccrued Interest | B8: Assets | C8: Investments | D8: Debt Instruments | E8: Accrued Interest | F8: =SUMIF('BDC post TB'!B:B,Summary!A8,'BDC post TB'!J:J) -> 4549181.8 | G8: =SUMIF('SBIC post TB(Closed)'!B:B,Summary!A8,'SBIC post TB(Closed)'!J:J) -> 0 | H8: =SUMIF('SBICII post TB (closed)'!B:B,Summary!A8,'SBICII post TB (closed)'!J:J) -> 0 | I8: =SUM(F8:H8) -> 4549181.8 | N8: =SUM(I8:M8) -> 4549181.8 | O8: c | Q8: =IF(AND(B8="Liabilities",N8>0),N8,0) -> 0
A9: =CONCATENATE(D9,E9) -> Debt InstrumentsAmortization / Accretion | B9: Assets | C9: Investments | D9: Debt Instruments | E9: Amortization / Accretion | F9: =SUMIF('BDC post TB'!B:B,Summary!A9,'BDC post TB'!J:J) -> 1909351 | G9: =SUMIF('SBIC post TB(Closed)'!B:B,Summary!A9,'SBIC post TB(Closed)'!J:J) -> 0 | H9: =SUMIF('SBICII post TB (closed)'!B:B,Summary!A9,'SBICII post TB (closed)'!J:J) -> 0 | I9: =SUM(F9:H9) -> 1909351 | N9: =SUM(I9:M9) -> 1909351 | O9: a | Q9: =IF(AND(B9="Liabilities",N9>0),N9,0) -> 0
A10: =CONCATENATE(D10,E10) -> Debt InstrumentsCost | B10: Assets | C10: Investments | D10: Debt Instruments | E10: Cost | F10: =SUMIF('BDC post TB'!B:B,Summary!A10,'BDC post TB'!J:J) -> 5.3931032e+08 | G10: =SUMIF('SBIC post TB(Closed)'!B:B,Summary!A10,'SBIC post TB(Closed)'!J:J) -> 0 | H10: =SUMIF('SBICII post TB (closed)'!B:B,Summary!A10,'SBICII post TB (closed)'!J:J) -> 0 | I10: =SUM(F10:H10) -> 5.3931032e+08 | N10: =SUM(I10:M10) -> 5.3931032e+08 | O10: a | Q10: =IF(AND(B10="Liabilities",N10>0),N10,0) -> 0
A11: =CONCATENATE(D11,E11) -> Debt InstrumentsUnrealized FX GL | B11: Assets | C11: Investments | D11: Debt Instruments | E11: Unrealized FX GL | F11: =SUMIF('BDC post TB'!B:B,Summary!A11,'BDC post TB'!J:J) -> 184929.38 | G11: =SUMIF('SBIC post TB(Closed)'!B:B,Summary!A11,'SBIC post TB(Closed)'!J:J) -> 0 | H11: =SUMIF('SBICII post TB (closed)'!B:B,Summary!A11,'SBICII post TB (closed)'!J:J) -> 0 | I11: =SUM(F11:H11) -> 184929.38 | N11: =SUM(I11:M11) -> 184929.38 | O11: a | Q11: =IF(AND(B11="Liabilities",N11>0),N11,0) -> 0
A12: =CONCATENATE(D12,E12) -> Debt InstrumentsUnrealized Price G/L | B12: Assets | C12: Investments | D12: Debt Instruments | E12: Unrealized Price G/L | F12: =SUMIF('BDC post TB'!B:B,Summary!A12,'BDC post TB'!J:J) -> -20463819 | G12: =SUMIF('SBIC post TB(Closed)'!B:B,Summary!A12,'SBIC post TB(Closed)'!J:J) -> 0 | H12: =SUMIF('SBICII post TB (closed)'!B:B,Summary!A12,'SBICII post TB (closed)'!J:J) -> 0 | I12: =SUM(F12:H12) -> -20463819 | N12: =SUM(I12:M12) -> -20463819 | O12: a | Q12: =IF(AND(B12="Liabilities",N12>0),N12,0) -> 0
A13: =CONCATENATE(D13,E13) -> Equity InstrumentsAccrued Interest | B13: Assets | C13: Investments | D13: Equity Instruments | E13: Accrued Interest | F13: =SUMIF('BDC post TB'!B:B,Summary!A13,'BDC post TB'!J:J) -> 0 | G13: =SUMIF('SBIC post TB(Closed)'!B:B,Summary!A13,'SBIC post TB(Closed)'!J:J) -> 0 | H13: =SUMIF('SBICII post TB (closed)'!B:B,Summary!A13,'SBICII post TB (closed)'!J:J) -> 0 | I13: =SUM(F13:H13) -> 0 | N13: =SUM(I13:M13) -> 0 | O13: j | Q13: =IF(AND(B13="Liabilities",N13>0),N13,0) -> 0
A14: =CONCATENATE(D14,E14) -> Equity InstrumentsCost | B14: Assets | C14: Investments | D14: Equity Instruments | E14: Cost | F14: =SUMIF('BDC post TB'!B:B,Summary!A14,'BDC post TB'!J:J) -> 1.9228867e+08 | G14: =SUMIF('SBIC post TB(Closed)'!B:B,Summary!A14,'SBIC post TB(Closed)'!J:J) -> 0 | H14: =SUMIF('SBICII post TB (closed)'!B:B,Summary!A14,'SBICII post TB (closed)'!J:J) -> 0 | I14: =SUM(F14:H14) -> 1.9228867e+08 | N14: =SUM(I14:M14) -> 1.9228867e+08 | O14: a | Q14: =IF(AND(B14="Liabilities",N14>0),N14,0) -> 0
A15: =CONCATENATE(D15,E15) -> Equity InstrumentsUnrealized Price G/L | B15: Assets | C15: Investments | D15: Equity Instruments | E15: Unrealized Price G/L | F15: =SUMIF('BDC post TB'!B:B,Summary!A15,'BDC post TB'!J:J) -> 38819784 | G15: =SUMIF('SBIC post TB(Closed)'!B:B,Summary!A15,'SBIC post TB(Closed)'!J:J) -> 0 | H15: =SUMIF('SBICII post TB (closed)'!B:B,Summary!A15,'SBICII post TB (closed)'!J:J) -> 0 | I15: =SUM(F15:H15) -> 38819784 | N15: =SUM(I15:M15) -> 38819784 | O15: a | Q15: =IF(AND(B15="Liabilities",N15>0),N15,0) -> 0
A16: =CONCATENATE(D16,E16) -> Equity InstrumentsUnrealized FX GL | B16: Assets | C16: Investments | D16: Equity Instruments | E16: Unrealized FX GL | F16: =SUMIF('BDC post TB'!B:B,Summary!A16,'BDC post TB'!J:J) -> 217624.93 | G16: =SUMIF('SBIC post TB(Closed)'!B:B,Summary!A16,'SBIC post TB(Closed)'!J:J) -> 0 | H16: =SUMIF('SBICII post TB (closed)'!B:B,Summary!A16,'SBICII post TB (closed)'!J:J) -> 0 | I16: =SUM(F16:H16) -> 217624.93 | N16: =SUM(I16:M16) -> 217624.93 | O16: a | Q16: =IF(AND(B16="Liabilities",N16>0),N16,0) -> 0
A17: =CONCATENATE(D17,E17) -> FinancingAccrued Interest | B17: Assets | C17: Investments | D17: Financing | E17: Accrued Interest | F17: =SUMIF('BDC post TB'!B:B,Summary!A17,'BDC post TB'!J:J) -> -274954.52 | G17: =SUMIF('SBIC post TB(Closed)'!B:B,Summary!A17,'SBIC post TB(Closed)'!J:J) -> 0 | H17: =SUMIF('SBICII post TB (closed)'!B:B,Summary!A17,'SBICII post TB (closed)'!J:J) -> 0 | I17: =SUM(F17:H17) -> -274954.52 | N17: =SUM(I17:M17) -> -274954.52 | O17: j
A18: =CONCATENATE(D18,E18) -> FinancingCost | B18: Assets | C18: Investments | D18: Financing | E18: Cost | F18: =SUMIF('BDC post TB'!B:B,Summary!A18,'BDC post TB'!J:J) -> -51456264 | G18: =SUMIF('SBIC post TB(Closed)'!B:B,Summary!A18,'SBIC post TB(Closed)'!J:J) -> 0 | H18: =SUMIF('SBICII post TB (closed)'!B:B,Summary!A18,'SBICII post TB (closed)'!J:J) -> 0 | I18: =SUM(F18:H18) -> -51456264 | N18: =SUM(I18:M18) -> -51456264 | O18: h
A19: =CONCATENATE(D19,E19) -> FinancingUnrealized FX GL | B19: Assets | C19: Investments | D19: Financing | E19: Unrealized FX GL | F19: =SUMIF('BDC post TB'!B:B,Summary!A19,'BDC post TB'!J:J) -> -12454.14 | G19: =SUMIF('SBIC post TB(Closed)'!B:B,Summary!A19,'SBIC post TB(Closed)'!J:J) -> 0 | H19: =SUMIF('SBICII post TB (closed)'!B:B,Summary!A19,'SBICII post TB (closed)'!J:J) -> 0 | I19: =SUM(F19:H19) -> -12454.14 | N19: =SUM(I19:M19) -> -12454.14 | O19: h
A20: FinancingUnrealized Price G/L | B20: Assets | C20: Investments | D20: Financing | E20: Unrealized Price G/L | F20: =SUMIF('BDC post TB'!B:B,Summary!A20,'BDC post TB'!J:J) -> 0 | G20: =SUMIF('SBIC post TB(Closed)'!B:B,Summary!A20,'SBIC post TB(Closed)'!J:J) -> 0 | H20: =SUMIF('SBICII post TB (closed)'!B:B,Summary!A20,'SBICII post TB (closed)'!J:J) -> 0 | I20: =SUM(F20:H20) -> 0 | N20: =SUM(I20:M20) -> 0 | O20: h
A21: =CONCATENATE(D21,E21) -> MoneyMarketAccrued Interest | B21: Assets | C21: Investments | D21: MoneyMarket | E21: Accrued Interest | F21: =SUMIF('BDC post TB'!B:B,Summary!A21,'BDC post TB'!J:J) -> 0 | G21: =SUMIF('SBIC post TB(Closed)'!B:B,Summary!A21,'SBIC post TB(Closed)'!J:J) -> 0 | H21: =SUMIF('SBICII post TB (closed)'!B:B,Summary!A21,'SBICII post TB (closed)'!J:J) -> 0 | I21: =SUM(F21:H21) -> 0 | N21: =SUM(I21:M21) -> 0 | O21: a | Q21: =IF(AND(B21="Liabilities",N21>0),N21,0) -> 0
A22: =CONCATENATE(D22,E22) -> FundAccrued Interest | B22: Assets | C22: Investments | D22: Fund | E22: Accrued Interest | F22: =SUMIF('BDC post TB'!B:B,Summary!A22,'BDC post TB'!J:J) -> 4291063.6 | G22: =SUMIF('SBIC post TB(Closed)'!B:B,Summary!A22,'SBIC post TB(Closed)'!J:J) -> 0 | H22: =SUMIF('SBICII post TB (closed)'!B:B,Summary!A22,'SBICII post TB (closed)'!J:J) -> 0 | I22: =SUM(F22:H22) -> 4291063.6 | N22: =SUM(I22:M22) -> 4291063.6 | O22: c | Q22: =IF(AND(B22="Liabilities",N22>0),N22,0) -> 0
A23: =CONCATENATE(D23,E23) -> FundCost | B23: Assets | C23: Investments | D23: Fund | E23: Cost | F23: =SUMIF('BDC post TB'!B:B,Summary!A23,'BDC post TB'!J:J) -> 2.3076108e+08 | G23: =SUMIF('SBIC post TB(Closed)'!B:B,Summary!A23,'SBIC post TB(Closed)'!J:J) -> 0 | H23: =SUMIF('SBICII post TB (closed)'!B:B,Summary!A23,'SBICII post TB (closed)'!J:J) -> 0 | I23: =SUM(F23:H23) -> 2.3076108e+08 | N23: =SUM(I23:M23) -> 2.3076108e+08 | O23: a | Q23: =IF(AND(B23="Liabilities",N23>0),N23,0) -> 0
A24: =CONCATENATE(D24,E24) -> FundUnrealized Price G/L | B24: Assets | C24: Investments | D24: Fund | E24: Unrealized Price G/L | F24: =SUMIF('BDC post TB'!B:B,Summary!A24,'BDC post TB'!J:J) -> -22470518 | G24: =SUMIF('SBIC post TB(Closed)'!B:B,Summary!A24,'SBIC post TB(Closed)'!J:J) -> 0 | H24: =SUMIF('SBICII post TB (closed)'!B:B,Summary!A24,'SBICII post TB (closed)'!J:J) -> 0 | I24: =SUM(F24:H24) -> -22470518 | N24: =SUM(I24:M24) -> -22470518 | O24: a | Q24: =IF(AND(B24="Liabilities",N24>0),N24,0) -> 0
A25: =CONCATENATE(D25,E25) -> MoneyMarketCost | B25: Assets | C25: Investments | D25: MoneyMarket | E25: Cost | F25: =SUMIF('BDC post TB'!B:B,Summary!A25,'BDC post TB'!J:J) -> 30530529 | G25: =SUMIF('SBIC post TB(Closed)'!B:B,Summary!A25,'SBIC post TB(Closed)'!J:J) -> 0 | H25: =SUMIF('SBICII post TB (closed)'!B:B,Summary!A25,'SBICII post TB (closed)'!J:J) -> 0 | I25: =SUM(F25:H25) -> 30530529 | N25: =SUM(I25:M25) -> 30530529 | O25: b2 | Q25: =IF(AND(B25="Liabilities",N25>0),N25,0) -> 0
A26: =CONCATENATE(D26,E26) -> OtherAccrued Interest | B26: Assets | C26: Investments | D26: Other | E26: Accrued Interest | F26: =SUMIF('BDC post TB'!B:B,Summary!A26,'BDC post TB'!J:J) -> -3352083.3 | G26: =SUMIF('SBIC post TB(Closed)'!B:B,Summary!A26,'SBIC post TB(Closed)'!J:J) -> 0 | H26: =SUMIF('SBICII post TB (closed)'!B:B,Summary!A26,'SBICII post TB (closed)'!J:J) -> 0 | I26: =SUM(F26:H26) -> -3352083.3 | N26: =SUM(I26:M26) -> -3352083.3 | O26: j
A27: =CONCATENATE(D27,E27) -> OtherAmortization / Accretion | B27: Assets | C27: Investments | D27: Other | E27: Amortization / Accretion | F27: =SUMIF('BDC post TB'!B:B,Summary!A27,'BDC post TB'!J:J) -> 0 | G27: =SUMIF('SBIC post TB(Closed)'!B:B,Summary!A27,'SBIC post TB(Closed)'!J:J) -> 0 | H27: =SUMIF('SBICII post TB (closed)'!B:B,Summary!A27,'SBICII post TB (closed)'!J:J) -> 0 | I27: =SUM(F27:H27) -> 0 | N27: =SUM(I27:M27) -> 0
A28: =CONCATENATE(D28,E28) -> OtherCost | B28: Assets | C28: Investments | D28: Other | E28: Cost | F28: =SUMIF('BDC post TB'!B:B,Summary!A28,'BDC post TB'!J:J) -> -390000000 | G28: =SUMIF('SBIC post TB(Closed)'!B:B,Summary!A28,'SBIC post TB(Closed)'!J:J) -> 0 | H28: =SUMIF('SBICII post TB (closed)'!B:B,Summary!A28,'SBICII post TB (closed)'!J:J) -> 0 | I28: =SUM(F28:H28) -> -390000000 | N28: =SUM(I28:M28) -> -390000000
A29: =CONCATENATE(D29,E29) -> OtherUnrealized Price G/L | B29: Assets | C29: Investments | D29: Other | E29: Unrealized Price G/L | F29: =SUMIF('BDC post TB'!B:B,Summary!A29,'BDC post TB'!J:J) -> 0 | G29: =SUMIF('SBIC post TB(Closed)'!B:B,Summary!A29,'SBIC post TB(Closed)'!J:J) -> 0 | H29: =SUMIF('SBICII post TB (closed)'!B:B,Summary!A29,'SBICII post TB (closed)'!J:J) -> 0 | I29: =SUM(F29:H29) -> 0 | N29: =SUM(I29:M29) -> 0
A30: =CONCATENATE(D30,E30) -> CashCost | B30: Assets | C30: Investments | D30: Cash | E30: Cost | F30: =SUMIF('BDC post TB'!B:B,Summary!A30,'BDC post TB'!J:J) -> 17446868 | G30: =SUMIF('SBIC post TB(Closed)'!B:B,Summary!A30,'SBIC post TB(Closed)'!J:J) -> 0 | H30: =SUMIF('SBICII post TB (closed)'!B:B,Summary!A30,'SBICII post TB (closed)'!J:J) -> 0 | I30: =SUM(F30:H30) -> 17446868 | J30: =-'BDC post TB'!J31 -> -465074.15 | N30: =SUM(I30:M30) -> 16981793 | O30: b1 | Q30: =IF(AND(B30="Liabilities",N30>0),N30,0) -> 0
A31: =CONCATENATE(D31,E31) -> CashUnrealized FX GL | B31: Assets | C31: Investments | D31: Cash | E31: Unrealized FX GL | F31: =SUMIF('BDC post TB'!B:B,Summary!A31,'BDC post TB'!J:J) -> 276235.04 | G31: =SUMIF('SBIC post TB(Closed)'!B:B,Summary!A31,'SBIC post TB(Closed)'!J:J) -> 0 | H31: =SUMIF('SBICII post TB (closed)'!B:B,Summary!A31,'SBICII post TB (closed)'!J:J) -> 0 | I31: =SUM(F31:H31) -> 276235.04 | N31: =SUM(I31:M31) -> 276235.04 | O31: b1 | Q31: =IF(AND(B31="Liabilities",N31>0),N31,0) -> 0
A32: =CONCATENATE(D32,E32) -> DistributionsReceivable Cost | B32: Assets | C32: Receivables | D32: DistributionsReceivable | E32: Cost | F32: =SUMIF('BDC post TB'!B:B,Summary!A32,'BDC post TB'!J:J) -> 0 | G32: =SUMIF('SBIC post TB(Closed)'!B:B,Summary!A32,'SBIC post TB(Closed)'!J:J) -> 0 | H32: =SUMIF('SBICII post TB (closed)'!B:B,Summary!A32,'SBICII post TB (closed)'!J:J) -> 0 | I32: =SUM(F32:H32) -> 0 | N32: =SUM(I32:M32) -> 0 | O32: d2 | Q32: =IF(AND(B32="Liabilities",N32>0),N32,0) -> 0
A33: =CONCATENATE(D33,E33) -> Dividend Receivable Cost | B33: Assets | C33: Receivables | D33: Dividend Receivable | E33: Cost | F33: =SUMIF('BDC post TB'!B:B,Summary!A33,'BDC post TB'!J:J) -> 230769 | G33: =SUMIF('SBIC post TB(Closed)'!B:B,Summary!A33,'SBIC post TB(Closed)'!J:J) -> 0 | H33: =SUMIF('SBICII post TB (closed)'!B:B,Summary!A33,'SBICII post TB (closed)'!J:J) -> 0 | I33: =SUM(F33:H33) -> 230769 | N33: =SUM(I33:M33) -> 230769 | O33: d2
A34: =CONCATENATE(D34,E34) -> Due From PennantPark Admin Cost | B34: Assets | C34: Receivables | D34: Due From PennantPark Admin | E34: Cost | F34: =SUMIF('BDC post TB'!B:B,Summary!A34,'BDC post TB'!J:J) -> 81285.15 | G34: =SUMIF('SBIC post TB(Closed)'!B:B,Summary!A34,'SBIC post TB(Closed)'!J:J) -> 0 | H34: =SUMIF('SBICII post TB (closed)'!B:B,Summary!A34,'SBICII post TB (closed)'!J:J) -> 0 | I34: =SUM(F34:H34) -> 81285.15 | N34: =SUM(I34:M34) -> 81285.15 | O34: dd
A35: =CONCATENATE(D35,E35) -> Receivable Cost | B35: Assets | C35: Receivables | D35: Receivable | E35: Cost | F35: =SUMIF('BDC post TB'!B:B,Summary!A35,'BDC post TB'!J:J) -> 73832136 | G35: =SUMIF('SBIC post TB(Closed)'!B:B,Summary!A35,'SBIC post TB(Closed)'!J:J) -> 0 | H35: =SUMIF('SBICII post TB (closed)'!B:B,Summary!A35,'SBICII post TB (closed)'!J:J) -> 0 | I35: =SUM(F35:H35) -> 73832136 | N35: =SUM(I35:M35) -> 73832136 | O35: d1 | Q35: =IF(AND(B35="Liabilities",N35>0),N35,0) -> 0
A36: =CONCATENATE(D36,E36) -> ReceivablesCost | B36: Assets | C36: Receivables | D36: Receivables | E36: Cost | F36: =SUMIF('BDC post TB'!B:B,Summary!A36,'BDC post TB'!J:J) -> 0 | G36: =SUMIF('SBIC post TB(Closed)'!B:B,Summary!A36,'SBIC post TB(Closed)'!J:J) -> 0 | H36: =SUMIF('SBICII post TB (closed)'!B:B,Summary!A36,'SBICII post TB (closed)'!J:J) -> 0 | I36: =SUM(F36:H36) -> 0 | N36: =SUM(I36:M36) -> 0 | O36: d1 | Q36: =IF(AND(B36="Liabilities",N36>0),N36,0) -> 0
A37: =CONCATENATE(D37,E37) -> CouponInterestReceivable Cost | B37: Assets | C37: Receivables | D37: CouponInterestReceivable | E37: Cost | F37: =SUMIF('BDC post TB'!B:B,Summary!A37,'BDC post TB'!J:J) -> 0 | G37: =SUMIF('SBIC post TB(Closed)'!B:B,Summary!A37,'SBIC post TB(Closed)'!J:J) -> 0 | H37: =SUMIF('SBICII post TB (closed)'!B:B,Summary!A37,'SBICII post TB (closed)'!J:J) -> 0 | I37: =SUM(F37:H37) -> 0 | N37: =SUM(I37:M37) -> 0 | O37: c
A38: =CONCATENATE(D38,E38) -> Interest Receivable Cost | B38: Assets | C38: Receivables | D38: Interest Receivable | E38: Cost | F38: =SUMIF('BDC post TB'!B:B,Summary!A38,'BDC post TB'!J:J) -> 78891.41 | G38: =SUMIF('SBIC post TB(Closed)'!B:B,Summary!A38,'SBIC post TB(Closed)'!J:J) -> 0 | H38: =SUMIF('SBICII post TB (closed)'!B:B,Summary!A38,'SBICII post TB (closed)'!J:J) -> 0 | I38: =SUM(F38:H38) -> 78891.41 | J38: =-J30 -> 465074.15 | N38: =SUM(I38:M38) -> 543965.56 | O38: c | Q38: =IF(AND(B38="Liabilities",N38>0),N38,0) -> 0
A39: =CONCATENATE(D39,E39) -> Interest Receivable Sweep Cost | B39: Assets | C39: Receivables | D39: Interest Receivable Sweep | E39: Cost | F39: =SUMIF('BDC post TB'!B:B,Summary!A39,'BDC post TB'!J:J) -> 0 | G39: =SUMIF('SBIC post TB(Closed)'!B:B,Summary!A39,'SBIC post TB(Closed)'!J:J) -> 0 | H39: =SUMIF('SBICII post TB (closed)'!B:B,Summary!A39,'SBICII post TB (closed)'!J:J) -> 0 | I39: =SUM(F39:H39) -> 0 | N39: =SUM(I39:M39) -> 0 | O39: c | Q39: =IF(AND(B39="Liabilities",N39>0),N39,0) -> 0
A40: =CONCATENATE(D40,E40) -> PIK Interest Receivable Cost | B40: Assets | C40: Receivables | D40: PIK Interest Receivable | E40: Cost | F40: =SUMIF('BDC post TB'!B:B,Summary!A40,'BDC post TB'!J:J) -> 0 | G40: =SUMIF('SBIC post TB(Closed)'!B:B,Summary!A40,'SBIC post TB(Closed)'!J:J) -> 0 | H40: =SUMIF('SBICII post TB (closed)'!B:B,Summary!A40,'SBICII post TB (closed)'!J:J) -> 0 | I40: =SUM(F40:H40) -> 0 | N40: =SUM(I40:M40) -> 0 | O40: c | Q40: =IF(AND(B40="Liabilities",N40>0),N40,0) -> 0
A41: =CONCATENATE(D41,E41) -> Prepaid Admin Fee Cost | B41: Assets | C41: Receivables | D41: Prepaid Admin Fee | E41: Cost | F41: =SUMIF('BDC post TB'!B:B,Summary!A41,'BDC post TB'!J:J) -> 0 | G41: =SUMIF('SBIC post TB(Closed)'!B:B,Summary!A41,'SBIC post TB(Closed)'!J:J) -> 0 | H41: =SUMIF('SBICII post TB (closed)'!B:B,Summary!A41,'SBICII post TB (closed)'!J:J) -> 0 | I41: =SUM(F41:H41) -> 0 | N41: =SUM(I41:M41) -> 0 | O41: d | Q41: =IF(AND(B41="Liabilities",N41>0),N41,0) -> 0
A42: =CONCATENATE(D42,E42) -> Prepaid Fidelity Bond Cost | B42: Assets | C42: Receivables | D42: Prepaid Fidelity Bond | E42: Cost | F42: =SUMIF('BDC post TB'!B:B,Summary!A42,'BDC post TB'!J:J) -> 51349.65 | G42: =SUMIF('SBIC post TB(Closed)'!B:B,Summary!A42,'SBIC post TB(Closed)'!J:J) -> 0 | H42: =SUMIF('SBICII post TB (closed)'!B:B,Summary!A42,'SBICII post TB (closed)'!J:J) -> 0 | I42: =SUM(F42:H42) -> 51349.65 | N42: =SUM(I42:M42) -> 51349.65 | O42: d | Q42: =IF(AND(B42="Liabilities",N42>0),N42,0) -> 0
A43: =CONCATENATE(D43,E43) -> Receivable from IM Cost | B43: Assets | C43: Receivables | D43: Receivable from IM | E43: Cost | F43: =SUMIF('BDC post TB'!B:B,Summary!A43,'BDC post TB'!J:J) -> 0 | G43: =SUMIF('SBIC post TB(Closed)'!B:B,Summary!A43,'SBIC post TB(Closed)'!J:J) -> 0 | H43: =SUMIF('SBICII post TB (closed)'!B:B,Summary!A43,'SBICII post TB (closed)'!J:J) -> 0 | I43: =SUM(F43:H43) -> 0 | N43: =SUM(I43:M43) -> 0 | O43: d | Q43: =IF(AND(B43="Liabilities",N43>0),N43,0) -> 0
A44: =CONCATENATE(D44,E44) -> Other Receivable Cost | B44: Assets | C44: Receivables | D44: Other Receivable | E44: Cost | F44: =SUMIF('BDC post TB'!B:B,Summary!A44,'BDC post TB'!J:J) -> -12855 | G44: =SUMIF('SBIC post TB(Closed)'!B:B,Summary!A44,'SBIC post TB(Closed)'!J:J) -> 0 | H44: =SUMIF('SBICII post TB (closed)'!B:B,Summary!A44,'SBICII post TB (closed)'!J:J) -> 0 | I44: =SUM(F44:H44) -> -12855 | M44: 23656 | N44: =SUM(I44:M44) -> 10801 | O44: d
A45: =CONCATENATE(D45,E45) -> Prepaid Insurance Fee Asset Account Cost | B45: Assets | C45: Receivables | D45: Prepaid Insurance Fee Asset Account | E45: Cost | F45: =SUMIF('BDC post TB'!B:B,Summary!A45,'BDC post TB'!J:J) -> 0 | G45: =SUMIF('SBIC post TB(Closed)'!B:B,Summary!A45,'SBIC post TB(Closed)'!J:J) -> 0 | H45: =SUMIF('SBICII post TB (closed)'!B:B,Summary!A45,'SBICII post TB (closed)'!J:J) -> 0 | I45: =SUM(F45:H45) -> 0 | N45: =SUM(I45:M45) -> 0 | O45: d | Q45: =IF(AND(B45="Liabilities",N45>0),N45,0) -> 0
A46: =CONCATENATE(D46,E46) -> Prepaid Investment Cost | B46: Assets | C46: Receivables | D46: Prepaid Investment | E46: Cost | F46: =SUMIF('BDC post TB'!B:B,Summary!A46,'BDC post TB'!J:J) -> 0 | G46: =SUMIF('SBIC post TB(Closed)'!B:B,Summary!A46,'SBIC post TB(Closed)'!J:J) -> 0 | H46: =SUMIF('SBICII post TB (closed)'!B:B,Summary!A46,'SBICII post TB (closed)'!J:J) -> 0 | I46: =SUM(F46:H46) -> 0 | N46: =SUM(I46:M46) -> 0 | O46: d
A47: =CONCATENATE(D47,E47) -> Prepaid Legal Fee Asset Account Cost | B47: Assets | C47: Receivables | D47: Prepaid Legal Fee Asset Account | E47: Cost | F47: =SUMIF('BDC post TB'!B:B,Summary!A47,'BDC post TB'!J:J) -> 0 | G47: =SUMIF('SBIC post TB(Closed)'!B:B,Summary!A47,'SBIC post TB(Closed)'!J:J) -> 0 | H47: =SUMIF('SBICII post TB (closed)'!B:B,Summary!A47,'SBICII post TB (closed)'!J:J) -> 0 | I47: =SUM(F47:H47) -> 0 | N47: =SUM(I47:M47) -> 0 | O47: d | Q47: =IF(AND(B47="Liabilities",N47>0),N47,0) -> 0
A48: =CONCATENATE(D48,E48) -> Prepaid Insurance Fee Cost | B48: Assets | C48: Receivables | D48: Prepaid Insurance Fee | E48: Cost | F48: =SUMIF('BDC post TB'!B:B,Summary!A48,'BDC post TB'!J:J) -> 52569.97 | G48: =SUMIF('SBIC post TB(Closed)'!B:B,Summary!A48,'SBIC post TB(Closed)'!J:J) -> 0 | H48: =SUMIF('SBICII post TB (closed)'!B:B,Summary!A48,'SBICII post TB (closed)'!J:J) -> 0 | I48: =SUM(F48:H48) -> 52569.97 | N48: =SUM(I48:M48) -> 52569.97 | O48: d | Q48: =IF(AND(B48="Liabilities",N48>0),N48,0) -> 0
A49: =CONCATENATE(D49,E49) -> Prepaid Organization Cost Cost | B49: Assets | C49: Receivables | D49: Prepaid Organization Cost | E49: Cost | F49: =SUMIF('BDC post TB'!B:B,Summary!A49,'BDC post TB'!J:J) -> 8845 | G49: =SUMIF('SBIC post TB(Closed)'!B:B,Summary!A49,'SBIC post TB(Closed)'!J:J) -> 0 | H49: =SUMIF('SBICII post TB (closed)'!B:B,Summary!A49,'SBICII post TB (closed)'!J:J) -> 0 | I49: =SUM(F49:H49) -> 8845 | N49: =SUM(I49:M49) -> 8845 | O49: d
A50: =CONCATENATE(D50,E50) -> Prepaid – Dividend Receivable Cost | B50: Assets | C50: Receivables | D50: Prepaid – Dividend Receivable | E50: Cost | F50: =SUMIF('BDC post TB'!B:B,Summary!A50,'BDC post TB'!J:J) -> 0 | G50: =SUMIF('SBIC post TB(Closed)'!B:B,Summary!A50,'SBIC post TB(Closed)'!J:J) -> 0 | H50: =SUMIF('SBICII post TB (closed)'!B:B,Summary!A50,'SBICII post TB (closed)'!J:J) -> 0 | I50: =SUM(F50:H50) -> 0 | N50: =SUM(I50:M50) -> 0 | O50: d
A51: =CONCATENATE(D51,E51) -> Receivable from Other Entities Cost | B51: Assets | C51: Receivables | D51: Receivable from Other Entities | E51: Cost | F51: =SUMIF('BDC post TB'!B:B,Summary!A51,'BDC post TB'!J:J) -> -193154.05 | G51: =SUMIF('SBIC post TB(Closed)'!B:B,Summary!A51,'SBIC post TB(Closed)'!J:J) -> 0 | H51: =SUMIF('SBICII post TB (closed)'!B:B,Summary!A51,'SBICII post TB (closed)'!J:J) -> 0 | I51: =SUM(F51:H51) -> -193154.05 | N51: =SUM(I51:M51) -> -193154.05 | O51: d
A52: =CONCATENATE(D52,E52) -> Reserve Accruals – Interest Income Cost | B52: Assets | C52: Receivables | D52: Reserve Accruals – Interest Income | E52: Cost | F52: =SUMIF('BDC post TB'!B:B,Summary!A52,'BDC post TB'!J:J) -> -60112.43 | G52: =SUMIF('SBIC post TB(Closed)'!B:B,Summary!A52,'SBIC post TB(Closed)'!J:J) -> 0 | H52: =SUMIF('SBICII post TB (closed)'!B:B,Summary!A52,'SBICII post TB (closed)'!J:J) -> 0 | I52: =SUM(F52:H52) -> -60112.43 | N52: =SUM(I52:M52) -> -60112.43 | O52: c
A53: =CONCATENATE(D53,E53) -> Unrealized FX Gain/Loss Cost | B53: Assets | C53: Receivables | D53: Unrealized FX Gain/Loss | E53: Cost | F53: =SUMIF('BDC post TB'!B:B,Summary!A53,'BDC post TB'!J:J) -> -0.01 | G53: =SUMIF('SBIC post TB(Closed)'!B:B,Summary!A53,'SBIC post TB(Closed)'!J:J) -> 0 | H53: =SUMIF('SBICII post TB (closed)'!B:B,Summary!A53,'SBICII post TB (closed)'!J:J) -> 0 | I53: =SUM(F53:H53) -> -0.01 | N53: =SUM(I53:M53) -> -0.01 | O53: a
A54: =CONCATENATE(D54,E54) -> Prepaid Offering Cost Cost | B54: Assets | C54: Receivables | D54: Prepaid Offering Cost | E54: Cost | F54: =SUMIF('BDC post TB'!B:B,Summary!A54,'BDC post TB'!J:J) -> 134632.79 | G54: =SUMIF('SBIC post TB(Closed)'!B:B,Summary!A54,'SBIC post TB(Closed)'!J:J) -> 0 | H54: =SUMIF('SBICII post TB (closed)'!B:B,Summary!A54,'SBICII post TB (closed)'!J:J) -> 0 | I54: =SUM(F54:H54) -> 134632.79 | N54: =SUM(I54:M54) -> 134632.79 | O54: d
A55: =CONCATENATE(D55,E55) -> Pre paid Offering Costs – 2024 Notes Cost | B55: Assets | C55: Receivables | D55: Pre paid Offering Costs – 2024 Notes | E55: Cost | F55: =SUMIF('BDC post TB'!B:B,Summary!A55,'BDC post TB'!J:J) -> 0 | G55: =SUMIF('SBIC post TB(Closed)'!B:B,Summary!A55,'SBIC post TB(Closed)'!J:J) -> 0 | H55: =SUMIF('SBICII post TB (closed)'!B:B,Summary!A55,'SBICII post TB (closed)'!J:J) -> 0 | I55: =SUM(F55:H55) -> 0 | N55: =SUM(I55:M55) -> 0 | O55: i2
A56: =CONCATENATE(D56,E56) -> Pre paid Offering Costs – 2026 Notes Cost | B56: Assets | C56: Receivables | D56: Pre paid Offering Costs – 2026 Notes | E56: Cost | F56: =SUMIF('BDC post TB'!B:B,Summary!A56,'BDC post TB'!J:J) -> 226842.06 | G56: =SUMIF('SBIC post TB(Closed)'!B:B,Summary!A56,'SBIC post TB(Closed)'!J:J) -> 0 | H56: =SUMIF('SBICII post TB (closed)'!B:B,Summary!A56,'SBICII post TB (closed)'!J:J) -> 0 | I56: =SUM(F56:H56) -> 226842.06 | N56: =SUM(I56:M56) -> 226842.06 | O56: i3
A57: =CONCATENATE(D57,E57) -> Pre paid Offering Costs – Nov 2026 Notes Cost | B57: Assets | C57: Receivables | D57: Pre paid Offering Costs – Nov 2026 Notes | E57: Cost | F57: =SUMIF('BDC post TB'!B:B,Summary!A57,'BDC post TB'!J:J) -> 782327.11 | G57: =SUMIF('SBIC post TB(Closed)'!B:B,Summary!A57,'SBIC post TB(Closed)'!J:J) -> 0 | H57: =SUMIF('SBICII post TB (closed)'!B:B,Summary!A57,'SBICII post TB (closed)'!J:J) -> 0 | I57: =SUM(F57:H57) -> 782327.11 | N57: =SUM(I57:M57) -> 782327.11 | O57: i4
A58: =CONCATENATE(D58,E58) -> Pre paid Offering Costs - Feb 2029 Notes Cost | B58: Assets | C58: Receivables | D58: Pre paid Offering Costs - Feb 2029 Notes | E58: Cost | F58: =SUMIF('BDC post TB'!B:B,Summary!A58,'BDC post TB'!J:J) -> 1392810 | G58: =SUMIF('SBIC post TB(Closed)'!B:B,Summary!A58,'SBIC post TB(Closed)'!J:J) -> 0 | H58: =SUMIF('SBICII post TB (closed)'!B:B,Summary!A58,'SBICII post TB (closed)'!J:J) -> 0 | I58: =SUM(F58:H58) -> 1392810 | N58: =SUM(I58:M58) -> 1392810 | O58: i5
A59: =CONCATENATE(D59,E59) -> Prepaid - Egan-Jones Rating Co Cost | B59: Assets | C59: Receivables | D59: Prepaid - Egan-Jones Rating Co | E59: Cost | F59: =SUMIF('BDC post TB'!B:B,Summary!A59,'BDC post TB'!J:J) -> 57159.38 | G59: =SUMIF('SBIC post TB(Closed)'!B:B,Summary!A59,'SBIC post TB(Closed)'!J:J) -> 0 | H59: =SUMIF('SBICII post TB (closed)'!B:B,Summary!A59,'SBICII post TB (closed)'!J:J) -> 0 | I59: =SUM(F59:H59) -> 57159.38 | N59: =SUM(I59:M59) -> 57159.38 | O59: d
A60: =CONCATENATE(D60,E60) -> Prepaid - NYSE Annual Fee Cost | B60: Assets | C60: Receivables | D60: Prepaid - NYSE Annual Fee | E60: Cost | F60: =SUMIF('BDC post TB'!B:B,Summary!A60,'BDC post TB'!J:J) -> 6992.11 | G60: =SUMIF('SBIC post TB(Closed)'!B:B,Summary!A60,'SBIC post TB(Closed)'!J:J) -> 0 | H60: =SUMIF('SBICII post TB (closed)'!B:B,Summary!A60,'SBICII post TB (closed)'!J:J) -> 0 | I60: =SUM(F60:H60) -> 6992.11 | N60: =SUM(I60:M60) -> 6992.11 | O60: d
A61: =CONCATENATE(D61,E61) -> Prepaid Other Cost | B61: Assets | C61: Receivables | D61: Prepaid Other | E61: Cost | F61: =SUMIF('BDC post TB'!B:B,Summary!A61,'BDC post TB'!J:J) -> 0 | G61: =SUMIF('SBIC post TB(Closed)'!B:B,Summary!A61,'SBIC post TB(Closed)'!J:J) -> 0 | H61: =SUMIF('SBICII post TB (closed)'!B:B,Summary!A61,'SBICII post TB (closed)'!J:J) -> 0 | I61: =SUM(F61:H61) -> 0 | N61: =SUM(I61:M61) -> 0 | O61: d
A62: =CONCATENATE(D62,E62) -> Prepaid Credit Facility Cost | B62: Assets | C62: Receivables | D62: Prepaid Credit Facility | E62: Cost | F62: =SUMIF('BDC post TB'!B:B,Summary!A62,'BDC post TB'!J:J) -> 0 | G62: =SUMIF('SBIC post TB(Closed)'!B:B,Summary!A62,'SBIC post TB(Closed)'!J:J) -> 0 | H62: =SUMIF('SBICII post TB (closed)'!B:B,Summary!A62,'SBICII post TB (closed)'!J:J) -> 0 | I62: =SUM(F62:H62) -> 0 | N62: =SUM(I62:M62) -> 0 | O62: d | Q62: =IF(AND(B62="Liabilities",N62>0),N62,0) -> 0
A63: =CONCATENATE(D63,E63) -> Credit Facility Prepaid Cost | B63: Assets | C63: Receivables | D63: Credit Facility Prepaid | E63: Cost | F63: =SUMIF('BDC post TB'!B:B,Summary!A63,'BDC post TB'!J:J) -> 0 | G63: =SUMIF('SBIC post TB(Closed)'!B:B,Summary!A63,'SBIC post TB(Closed)'!J:J) -> 0 | H63: =SUMIF('SBICII post TB (closed)'!B:B,Summary!A63,'SBICII post TB (closed)'!J:J) -> 0 | I63: =SUM(F63:H63) -> 0 | N63: =SUM(I63:M63) -> 0 | O63: h | Q63: =IF(AND(B63="Liabilities",N63>0),N63,0) -> 0
A64: =CONCATENATE(D64,E64) -> Prepaid Assets Cost | B64: Assets | C64: Receivables | D64: Prepaid Assets | E64: Cost | F64: =SUMIF('BDC post TB'!B:B,Summary!A64,'BDC post TB'!J:J) -> 0 | G64: =SUMIF('SBIC post TB(Closed)'!B:B,Summary!A64,'SBIC post TB(Closed)'!J:J) -> 0 | H64: =SUMIF('SBICII post TB (closed)'!B:B,Summary!A64,'SBICII post TB (closed)'!J:J) -> 0 | I64: =SUM(F64:H64) -> 0 | N64: =SUM(I64:M64) -> 0 | O64: d | Q64: =IF(AND(B64="Liabilities",N64>0),N64,0) -> 0
A65: =CONCATENATE(D65,E65) -> Due from PSLF Cost | B65: Assets | C65: Receivables | D65: Due from PSLF | E65: Cost | F65: =SUMIF('BDC post TB'!B:B,Summary!A65,'BDC post TB'!J:J) -> 0 | G65: =SUMIF('SBIC post TB(Closed)'!B:B,Summary!A65,'SBIC post TB(Closed)'!J:J) -> 0 | H65: =SUMIF('SBICII post TB (closed)'!B:B,Summary!A65,'SBICII post TB (closed)'!J:J) -> 0 | I65: =SUM(F65:H65) -> 0 | N65: =SUM(I65:M65) -> 0 | O65: dd | Q65: =IF(AND(O65="m",N65>0),N65,0) -> 0
A66: =CONCATENATE(D66,E66) -> Due from PTSF II Cost | B66: Assets | C66: Receivables | D66: Due from PTSF II | E66: Cost | F66: =SUMIF('BDC post TB'!B:B,Summary!A66,'BDC post TB'!J:J) -> 0 | G66: =SUMIF('SBIC post TB(Closed)'!B:B,Summary!A66,'SBIC post TB(Closed)'!J:J) -> 0 | H66: =SUMIF('SBICII post TB (closed)'!B:B,Summary!A66,'SBICII post TB (closed)'!J:J) -> 0 | I66: =SUM(F66:H66) -> 0 | N66: =SUM(I66:M66) -> 0 | O66: dd | Q66: =IF(AND(O66="m",N66>0),N66,0) -> 0
A67: =CONCATENATE(D67,E67) -> Prepaid Distribution Fee Cost | B67: Assets | C67: Receivables | D67: Prepaid Distribution Fee | E67: Cost | F67: =SUMIF('BDC post TB'!B:B,Summary!A67,'BDC post TB'!J:J) -> 0 | G67: =SUMIF('SBIC post TB(Closed)'!B:B,Summary!A67,'SBIC post TB(Closed)'!J:J) -> 0 | H67: =SUMIF('SBICII post TB (closed)'!B:B,Summary!A67,'SBICII post TB (closed)'!J:J) -> 0 | I67: =SUM(F67:H67) -> 0 | N67: =SUM(I67:M67) -> 0 | O67: d | Q67: =IF(AND(B67="Liabilities",N67>0),N67,0) -> 0
A68: =CONCATENATE(D68,E68) -> Unrealized FX Gain/Loss Unrealized FX GL | B68: Assets | C68: Receivables | D68: Unrealized FX Gain/Loss | E68: Unrealized FX GL | F68: =SUMIF('BDC post TB'!B:B,Summary!A68,'BDC post TB'!J:J) -> 0 | G68: =SUMIF('SBIC post TB(Closed)'!B:B,Summary!A68,'SBIC post TB(Closed)'!J:J) -> 0 | H68: =SUMIF('SBICII post TB (closed)'!B:B,Summary!A68,'SBICII post TB (closed)'!J:J) -> 0 | I68: =SUM(F68:H68) -> 0 | N68: =SUM(I68:M68) -> 0 | O68: c
A69: =CONCATENATE(D69,E69) -> Receivable from Feeder Cost | B69: Assets | C69: Receivables | D69: Receivable from Feeder | E69: Cost | F69: =SUMIF('BDC post TB'!B:B,Summary!A69,'BDC post TB'!J:J) -> 0 | G69: =SUMIF('SBIC post TB(Closed)'!B:B,Summary!A69,'SBIC post TB(Closed)'!J:J) -> 0 | H69: =SUMIF('SBICII post TB (closed)'!B:B,Summary!A69,'SBICII post TB (closed)'!J:J) -> 0 | I69: =SUM(F69:H69) -> 0 | N69: =SUM(I69:M69) -> 0 | O69: d
A70: ReceivablesUnrealized FX GL | B70: Assets | C70: Receivables | D70: Receivables | E70: Cost | F70: =SUMIF('BDC post TB'!B:B,Summary!A70,'BDC post TB'!J:J) -> 0 | G70: =SUMIF('SBIC post TB(Closed)'!B:B,Summary!A70,'SBIC post TB(Closed)'!J:J) -> 0 | H70: =SUMIF('SBICII post TB (closed)'!B:B,Summary!A70,'SBICII post TB (closed)'!J:J) -> 0 | I70: =SUM(F70:H70) -> 0 | N70: =SUM(I70:M70) -> 0 | O70: d | Q70: =IF(AND(B70="Liabilities",N70>0),N70,0) -> 0
A71: =CONCATENATE(D71,E71) -> Interest Receivable Pending Cost | B71: Assets | C71: Receivables | D71: Interest Receivable Pending | E71: Cost | F71: =SUMIF('BDC post TB'!B:B,Summary!A71,'BDC post TB'!J:J) -> 0 | G71: =SUMIF('SBIC post TB(Closed)'!B:B,Summary!A71,'SBIC post TB(Closed)'!J:J) -> 0 | H71: =SUMIF('SBICII post TB (closed)'!B:B,Summary!A71,'SBICII post TB (closed)'!J:J) -> 0 | I71: =SUM(F71:H71) -> 0 | N71: =SUM(I71:M71) -> 0 | O71: c | Q71: =IF(AND(B71="Liabilities",N71>0),N71,0) -> 0
A72: =CONCATENATE(D72,E72) -> Prepaid Management Fee Cost | B72: Assets | C72: Receivables | D72: Prepaid Management Fee | E72: Cost | F72: =SUMIF('BDC post TB'!B:B,Summary!A72,'BDC post TB'!J:J) -> 0 | G72: =SUMIF('SBIC post TB(Closed)'!B:B,Summary!A72,'SBIC post TB(Closed)'!J:J) -> 0 | H72: =SUMIF('SBICII post TB (closed)'!B:B,Summary!A72,'SBICII post TB (closed)'!J:J) -> 0 | I72: =SUM(F72:H72) -> 0 | N72: =SUM(I72:M72) -> 0 | O72: d | Q72: =IF(AND(B72="Liabilities",N72>0),N72,0) -> 0
A73: =CONCATENATE(D73,E73) -> Other Receivable Escrow Cost | B73: Assets | C73: Receivables | D73: Other Receivable Escrow | E73: Cost | F73: =SUMIF('BDC post TB'!B:B,Summary!A73,'BDC post TB'!J:J) -> 193154.05 | G73: =SUMIF('SBIC post TB(Closed)'!B:B,Summary!A73,'SBIC post TB(Closed)'!J:J) -> 0 | H73: =SUMIF('SBICII post TB (closed)'!B:B,Summary!A73,'SBICII post TB (closed)'!J:J) -> 0 | I73: =SUM(F73:H73) -> 193154.05 | N73: =SUM(I73:M73) -> 193154.05 | O73: d | Q73: =IF(AND(B73="Liabilities",N73>0),N73,0) -> 0
A74: =CONCATENATE(D74,E74) -> PaydownReceivable Cost | B74: Assets | C74: Receivables | D74: PaydownReceivable | E74: Cost | F74: =SUMIF('BDC post TB'!B:B,Summary!A74,'BDC post TB'!J:J) -> 0 | G74: =SUMIF('SBIC post TB(Closed)'!B:B,Summary!A74,'SBIC post TB(Closed)'!J:J) -> 0 | H74: =SUMIF('SBICII post TB (closed)'!B:B,Summary!A74,'SBICII post TB (closed)'!J:J) -> 0 | I74: =SUM(F74:H74) -> 0 | N74: =SUM(I74:M74) -> 0 | O74: d
A75: =CONCATENATE(D75,E75) -> Pre-paid SBIC Incentive Fee Cap Gain Cost | B75: Assets | C75: Receivables | D75: Pre-paid SBIC Incentive Fee Cap Gain | E75: Cost | F75: =SUMIF('BDC post TB'!B:B,Summary!A75,'BDC post TB'!J:J) -> 0 | I75: =SUM(F75:H75) -> 0 | N75: =SUM(I75:M75) -> 0 | O75: d
A76: =CONCATENATE(D76,E76) -> Prepaid SBA Fee Cost | B76: Assets | C76: Receivables | D76: Prepaid SBA Fee | E76: Cost | F76: =SUMIF('BDC post TB'!B:B,Summary!A76,'BDC post TB'!J:J) -> 0 | G76: =SUMIF('SBIC post TB(Closed)'!B:B,Summary!A76,'SBIC post TB(Closed)'!J:J) -> 0 | H76: =SUMIF('SBICII post TB (closed)'!B:B,Summary!A76,'SBICII post TB (closed)'!J:J) -> 0 | I76: =SUM(F76:H76) -> 0 | N76: =SUM(I76:M76) -> 0 | O76: i | Q76: =IF(AND(B76="Liabilities",N76>0),N76,0) -> 0
A77: =CONCATENATE(D77,E77) -> Prepaid SBA Fee 2 Cost | B77: Assets | C77: Receivables | D77: Prepaid SBA Fee 2 | E77: Cost | F77: =SUMIF('BDC post TB'!B:B,Summary!A77,'BDC post TB'!J:J) -> 0 | G77: =SUMIF('SBIC post TB(Closed)'!B:B,Summary!A77,'SBIC post TB(Closed)'!J:J) -> 0 | H77: =SUMIF('SBICII post TB (closed)'!B:B,Summary!A77,'SBICII post TB (closed)'!J:J) -> 0 | I77: =SUM(F77:H77) -> 0 | N77: =SUM(I77:M77) -> 0 | O77: i | Q77: =IF(AND(B77="Liabilities",N77>0),N77,0) -> 0
A78: =CONCATENATE(D78,E78) -> PayablesCost | B78: Liabilities | C78: Payables | D78: Payables | E78: Cost | F78: =SUMIF('BDC post TB'!B:B,Summary!A78,'BDC post TB'!J:J) -> -4900000 | G78: =SUMIF('SBIC post TB(Closed)'!B:B,Summary!A78,'SBIC post TB(Closed)'!J:J) -> 0 | H78: =SUMIF('SBICII post TB (closed)'!B:B,Summary!A78,'SBICII post TB (closed)'!J:J) -> 0 | I78: =SUM(F78:H78) -> -4900000 | N78: =SUM(I78:M78) -> -4900000 | O78: f | Q78: =IF(AND(O78="m",N78>0),N78,0) -> 0
A79: =CONCATENATE(D79,E79) -> PayablesUnrealized FX GL | B79: Liabilities | C79: Payables | D79: Payables | E79: Unrealized FX GL | F79: =SUMIF('BDC post TB'!B:B,Summary!A79,'BDC post TB'!J:J) -> 0 | G79: =SUMIF('SBIC post TB(Closed)'!B:B,Summary!A79,'SBIC post TB(Closed)'!J:J) -> 0 | H79: =SUMIF('SBICII post TB (closed)'!B:B,Summary!A79,'SBICII post TB (closed)'!J:J) -> 0 | I79: =SUM(F79:H79) -> 0 | N79: =SUM(I79:M79) -> 0 | O79: f | Q79: =IF(AND(O79="m",N79>0),N79,0) -> 0
A80: =CONCATENATE(D80,E80) -> Accrued Admin Fee Cost | B80: Liabilities | C80: Payables | D80: Accrued Admin Fee | E80: Cost | F80: =SUMIF('BDC post TB'!B:B,Summary!A80,'BDC post TB'!J:J) -> 0 | G80: =SUMIF('SBIC post TB(Closed)'!B:B,Summary!A80,'SBIC post TB(Closed)'!J:J) -> 0 | H80: =SUMIF('SBICII post TB (closed)'!B:B,Summary!A80,'SBICII post TB (closed)'!J:J) -> 0 | I80: =SUM(F80:H80) -> 0 | N80: =SUM(I80:M80) -> 0 | O80: m | Q80: =IF(AND(O80="m",N80>0),N80,0) -> 0
A81: =CONCATENATE(D81,E81) -> Accrued BNY Admin Fee Cost | B81: Liabilities | C81: Payables | D81: Accrued BNY Admin Fee | E81: Cost | F81: =SUMIF('BDC post TB'!B:B,Summary!A81,'BDC post TB'!J:J) -> -101369.66 | G81: =SUMIF('SBIC post TB(Closed)'!B:B,Summary!A81,'SBIC post TB(Closed)'!J:J) -> 0 | H81: =SUMIF('SBICII post TB (closed)'!B:B,Summary!A81,'SBICII post TB (closed)'!J:J) -> 0 | I81: =SUM(F81:H81) -> -101369.66 | N81: =SUM(I81:M81) -> -101369.66 | O81: m
A82: =CONCATENATE(D82,E82) -> Accrued PP Admin Exp Reimbursement Cost | B82: Liabilities | C82: Payables | D82: Accrued PP Admin Exp Reimbursement | E82: Cost | F82: =SUMIF('BDC post TB'!B:B,Summary!A82,'BDC post TB'!J:J) -> -1092210.8 | G82: =SUMIF('SBIC post TB(Closed)'!B:B,Summary!A82,'SBIC post TB(Closed)'!J:J) -> 0 | H82: =SUMIF('SBICII post TB (closed)'!B:B,Summary!A82,'SBICII post TB (closed)'!J:J) -> 0 | I82: =SUM(F82:H82) -> -1092210.8 | N82: =SUM(I82:M82) -> -1092210.8 | O82: m
A83: =CONCATENATE(D83,E83) -> Accrued PP Advisor Exp Reimbursement Cost | B83: Liabilities | C83: Payables | D83: Accrued PP Advisor Exp Reimbursement | E83: Cost | F83: =SUMIF('BDC post TB'!B:B,Summary!A83,'BDC post TB'!J:J) -> -185824.64 | G83: =SUMIF('SBIC post TB(Closed)'!B:B,Summary!A83,'SBIC post TB(Closed)'!J:J) -> 0 | H83: =SUMIF('SBICII post TB (closed)'!B:B,Summary!A83,'SBICII post TB (closed)'!J:J) -> 0 | I83: =SUM(F83:H83) -> -185824.64 | N83: =SUM(I83:M83) -> -185824.64 | O83: m
A84: =CONCATENATE(D84,E84) -> Accrued Admin OOPs Cost | B84: Liabilities | C84: Payables | D84: Accrued Admin OOPs | E84: Cost | F84: =SUMIF('BDC post TB'!B:B,Summary!A84,'BDC post TB'!J:J) -> 0 | G84: =SUMIF('SBIC post TB(Closed)'!B:B,Summary!A84,'SBIC post TB(Closed)'!J:J) -> 0 | H84: =SUMIF('SBICII post TB (closed)'!B:B,Summary!A84,'SBICII post TB (closed)'!J:J) -> 0 | I84: =SUM(F84:H84) -> 0 | N84: =SUM(I84:M84) -> 0 | O84: m | Q84: =IF(AND(O84="m",N84>0),N84,0) -> 0
A85: =CONCATENATE(D85,E85) -> Accrued Advisory Fees Cost | B85: Liabilities | C85: Payables | D85: Accrued Advisory Fees | E85: Cost | F85: =SUMIF('BDC post TB'!B:B,Summary!A85,'BDC post TB'!J:J) -> 0 | G85: =SUMIF('SBIC post TB(Closed)'!B:B,Summary!A85,'SBIC post TB(Closed)'!J:J) -> 0 | H85: =SUMIF('SBICII post TB (closed)'!B:B,Summary!A85,'SBICII post TB (closed)'!J:J) -> 0 | I85: =SUM(F85:H85) -> 0 | N85: =SUM(I85:M85) -> 0 | O85: m | Q85: =IF(AND(O85="m",N85>0),N85,0) -> 0
A86: =CONCATENATE(D86,E86) -> Accrued CITRIN Pricing Fees Cost | B86: Liabilities | C86: Payables | D86: Accrued CITRIN Pricing Fees | E86: Cost | F86: =SUMIF('BDC post TB'!B:B,Summary!A86,'BDC post TB'!J:J) -> -26387.5 | G86: =SUMIF('SBIC post TB(Closed)'!B:B,Summary!A86,'SBIC post TB(Closed)'!J:J) -> 0 | H86: =SUMIF('SBICII post TB (closed)'!B:B,Summary!A86,'SBICII post TB (closed)'!J:J) -> 0 | I86: =SUM(F86:H86) -> -26387.5 | N86: =SUM(I86:M86) -> -26387.5 | O86: m
A87: =CONCATENATE(D87,E87) -> Accrued Centri Business Consulting Fees Cost | B87: Liabilities | C87: Payables | D87: Accrued Centri Business Consulting Fees | E87: Cost | F87: =SUMIF('BDC post TB'!B:B,Summary!A87,'BDC post TB'!J:J) -> -35022.1 | G87: =SUMIF('SBIC post TB(Closed)'!B:B,Summary!A87,'SBIC post TB(Closed)'!J:J) -> 0 | H87: =SUMIF('SBICII post TB (closed)'!B:B,Summary!A87,'SBICII post TB (closed)'!J:J) -> 0 | I87: =SUM(F87:H87) -> -35022.1 | N87: =SUM(I87:M87) -> -35022.1 | O87: m
A88: =CONCATENATE(D88,E88) -> Accrued DLA SOX/Audit Related Fees Cost | B88: Liabilities | C88: Payables | D88: Accrued DLA SOX/Audit Related Fees | E88: Cost | F88: =SUMIF('BDC post TB'!B:B,Summary!A88,'BDC post TB'!J:J) -> -120000 | G88: =SUMIF('SBIC post TB(Closed)'!B:B,Summary!A88,'SBIC post TB(Closed)'!J:J) -> 0 | H88: =SUMIF('SBICII post TB (closed)'!B:B,Summary!A88,'SBICII post TB (closed)'!J:J) -> 0 | I88: =SUM(F88:H88) -> -120000 | N88: =SUM(I88:M88) -> -120000 | O88: m
A89: =CONCATENATE(D89,E89) -> Accrued Dechert Legal Fees Cost | B89: Liabilities | C89: Payables | D89: Accrued Dechert Legal Fees | E89: Cost | F89: =SUMIF('BDC post TB'!B:B,Summary!A89,'BDC post TB'!J:J) -> -66008.3 | G89: =SUMIF('SBIC post TB(Closed)'!B:B,Summary!A89,'SBIC post TB(Closed)'!J:J) -> 0 | H89: =SUMIF('SBICII post TB (closed)'!B:B,Summary!A89,'SBICII post TB (closed)'!J:J) -> 0 | I89: =SUM(F89:H89) -> -66008.3 | N89: =SUM(I89:M89) -> -66008.3 | O89: m
A90: =CONCATENATE(D90,E90) -> Accrued Grant Thornton Tax Fees Cost | B90: Liabilities | C90: Payables | D90: Accrued Grant Thornton Tax Fees | E90: Cost | F90: =SUMIF('BDC post TB'!B:B,Summary!A90,'BDC post TB'!J:J) -> -5416 | G90: =SUMIF('SBIC post TB(Closed)'!B:B,Summary!A90,'SBIC post TB(Closed)'!J:J) -> 0 | H90: =SUMIF('SBICII post TB (closed)'!B:B,Summary!A90,'SBICII post TB (closed)'!J:J) -> 0 | I90: =SUM(F90:H90) -> -5416 | N90: =SUM(I90:M90) -> -5416 | O90: m
A91: =CONCATENATE(D91,E91) -> Accrued KROLL LLC Pricing Fees Cost | B91: Liabilities | C91: Payables | D91: Accrued KROLL LLC Pricing Fees | E91: Cost | F91: =SUMIF('BDC post TB'!B:B,Summary!A91,'BDC post TB'!J:J) -> -55305.3 | G91: =SUMIF('SBIC post TB(Closed)'!B:B,Summary!A91,'SBIC post TB(Closed)'!J:J) -> 0 | H91: =SUMIF('SBICII post TB (closed)'!B:B,Summary!A91,'SBICII post TB (closed)'!J:J) -> 0 | I91: =SUM(F91:H91) -> -55305.3 | N91: =SUM(I91:M91) -> -55305.3 | O91: m
A92: =CONCATENATE(D92,E92) -> Accrued Kirkland & Ellis LLP Legal Fees Cost | B92: Liabilities | C92: Payables | D92: Accrued Kirkland & Ellis LLP Legal Fees | E92: Cost | F92: =SUMIF('BDC post TB'!B:B,Summary!A92,'BDC post TB'!J:J) -> -34453.75 | G92: =SUMIF('SBIC post TB(Closed)'!B:B,Summary!A92,'SBIC post TB(Closed)'!J:J) -> 0 | H92: =SUMIF('SBICII post TB (closed)'!B:B,Summary!A92,'SBICII post TB (closed)'!J:J) -> 0 | I92: =SUM(F92:H92) -> -34453.75 | N92: =SUM(I92:M92) -> -34453.75 | O92: m
A93: =CONCATENATE(D93,E93) -> Accrued Foley Tax/Consulting Fees Cost | B93: Liabilities | C93: Payables | D93: Accrued Foley Tax/Consulting Fees | E93: Cost | F93: =SUMIF('BDC post TB'!B:B,Summary!A93,'BDC post TB'!J:J) -> -3000.27 | G93: =SUMIF('SBIC post TB(Closed)'!B:B,Summary!A93,'SBIC post TB(Closed)'!J:J) -> 0 | H93: =SUMIF('SBICII post TB (closed)'!B:B,Summary!A93,'SBICII post TB (closed)'!J:J) -> 0 | I93: =SUM(F93:H93) -> -3000.27 | N93: =SUM(I93:M93) -> -3000.27 | O93: m
A94: =CONCATENATE(D94,E94) -> Accrued Lincoln Pricing Fees Cost | B94: Liabilities | C94: Payables | D94: Accrued Lincoln Pricing Fees | E94: Cost | F94: =SUMIF('BDC post TB'!B:B,Summary!A94,'BDC post TB'!J:J) -> -34487.03 | G94: =SUMIF('SBIC post TB(Closed)'!B:B,Summary!A94,'SBIC post TB(Closed)'!J:J) -> 0 | H94: =SUMIF('SBICII post TB (closed)'!B:B,Summary!A94,'SBICII post TB (closed)'!J:J) -> 0 | I94: =SUM(F94:H94) -> -34487.03 | N94: =SUM(I94:M94) -> -34487.03 | O94: m
A95: =CONCATENATE(D95,E95) -> Accrued RSM US LLP Audit Related Fees Cost | B95: Liabilities | C95: Payables | D95: Accrued RSM US LLP Audit Related Fees | E95: Cost | F95: =SUMIF('BDC post TB'!B:B,Summary!A95,'BDC post TB'!J:J) -> -229901 | G95: =SUMIF('SBIC post TB(Closed)'!B:B,Summary!A95,'SBIC post TB(Closed)'!J:J) -> 0 | H95: =SUMIF('SBICII post TB (closed)'!B:B,Summary!A95,'SBICII post TB (closed)'!J:J) -> 0 | I95: =SUM(F95:H95) -> -229901 | N95: =SUM(I95:M95) -> -229901 | O95: m
A96: =CONCATENATE(D96,E96) -> Accrued VRC Pricing Fees Cost | B96: Liabilities | C96: Payables | D96: Accrued VRC Pricing Fees | E96: Cost | F96: =SUMIF('BDC post TB'!B:B,Summary!A96,'BDC post TB'!J:J) -> -93086.11 | G96: =SUMIF('SBIC post TB(Closed)'!B:B,Summary!A96,'SBIC post TB(Closed)'!J:J) -> 0 | H96: =SUMIF('SBICII post TB (closed)'!B:B,Summary!A96,'SBICII post TB (closed)'!J:J) -> 0 | I96: =SUM(F96:H96) -> -93086.11 | N96: =SUM(I96:M96) -> -93086.11 | O96: m
A97: =CONCATENATE(D97,E97) -> Accrued Admin/Adviser Exp. Reimbursement Cost | B97: Liabilities | C97: Payables | D97: Accrued Admin/Adviser Exp. Reimbursement | E97: Cost | F97: =SUMIF('BDC post TB'!B:B,Summary!A97,'BDC post TB'!J:J) -> 0 | G97: =SUMIF('SBIC post TB(Closed)'!B:B,Summary!A97,'SBIC post TB(Closed)'!J:J) -> 0 | H97: =SUMIF('SBICII post TB (closed)'!B:B,Summary!A97,'SBICII post TB (closed)'!J:J) -> 0 | I97: =SUM(F97:H97) -> 0 | N97: =SUM(I97:M97) -> 0 | O97: m | Q97: =IF(AND(O97="m",N97>0),N97,0) -> 0
A98: =CONCATENATE(D98,E98) -> Accrued Audit Fee Cost | B98: Liabilities | C98: Payables | D98: Accrued Audit Fee | E98: Cost | F98: =SUMIF('BDC post TB'!B:B,Summary!A98,'BDC post TB'!J:J) -> 0 | G98: =SUMIF('SBIC post TB(Closed)'!B:B,Summary!A98,'SBIC post TB(Closed)'!J:J) -> 0 | H98: =SUMIF('SBICII post TB (closed)'!B:B,Summary!A98,'SBICII post TB (closed)'!J:J) -> 0 | I98: =SUM(F98:H98) -> 0 | N98: =SUM(I98:M98) -> 0 | O98: m | Q98: =IF(AND(O98="m",N98>0),N98,0) -> 0
A99: =CONCATENATE(D99,E99) -> Accrued Consulting Fees Payable Cost | B99: Liabilities | C99: Payables | D99: Accrued Consulting Fees Payable | E99: Cost | F99: =SUMIF('BDC post TB'!B:B,Summary!A99,'BDC post TB'!J:J) -> 0 | G99: =SUMIF('SBIC post TB(Closed)'!B:B,Summary!A99,'SBIC post TB(Closed)'!J:J) -> 0 | H99: =SUMIF('SBICII post TB (closed)'!B:B,Summary!A99,'SBICII post TB (closed)'!J:J) -> 0 | I99: =SUM(F99:H99) -> 0 | N99: =SUM(I99:M99) -> 0 | O99: m | Q99: =IF(AND(O99="m",N99>0),N99,0) -> 0
A100: =CONCATENATE(D100,E100) -> Accrued Custodian Fees Cost | B100: Liabilities | C100: Payables | D100: Accrued Custodian Fees | E100: Cost | F100: =SUMIF('BDC post TB'!B:B,Summary!A100,'BDC post TB'!J:J) -> -46419.16 | G100: =SUMIF('SBIC post TB(Closed)'!B:B,Summary!A100,'SBIC post TB(Closed)'!J:J) -> 0 | H100: =SUMIF('SBICII post TB (closed)'!B:B,Summary!A100,'SBICII post TB (closed)'!J:J) -> 0 | I100: =SUM(F100:H100) -> -46419.16 | N100: =SUM(I100:M100) -> -46419.16 | O100: m | Q100: =IF(AND(O100="m",N100>0),N100,0) -> 0
A101: =CONCATENATE(D101,E101) -> Accrued Director Fee Cost | B101: Liabilities | C101: Payables | D101: Accrued Director Fee | E101: Cost | F101: =SUMIF('BDC post TB'!B:B,Summary!A101,'BDC post TB'!J:J) -> -209939 | G101: =SUMIF('SBIC post TB(Closed)'!B:B,Summary!A101,'SBIC post TB(Closed)'!J:J) -> 0 | H101: =SUMIF('SBICII post TB (closed)'!B:B,Summary!A101,'SBICII post TB (closed)'!J:J) -> 0 | I101: =SUM(F101:H101) -> -209939 | N101: =SUM(I101:M101) -> -209939 | O101: m | Q101: =IF(AND(O101="m",N101>0),N101,0) -> 0
...

Sheet BDC post TB
C1: Header | D1: Detail
C2: BNY
C3: Custom Trial Balance #304
B4: =IF(C4="PennantPark Investment Corp"," ","Not BDC") | C4: PennantPark Investment Corp
C5: Period Start Date | D5: 01/30/2026:00:00:00
C6: Period End Date | D6: 01/31/2026:23:59:59
C7: Prior Knowledge Date | D7: 01/30/2026:15:18:07
C8: Knowledge Date | D8: 02/09/2026:20:49:59
C9: U.S. Dollars
B10: =CONCATENATE(E10,F10)
A11: =VLOOKUP(B11,Summary!A:A,1,FALSE) -> #N/A | B11: =CONCATENATE(E11,F11) -> FinancialAccountDescription | C11: Section | D11: Group | E11: FinancialAccount | F11: Description | G11: OpeningBalance | H11: Debits | I11: Credits | J11: ClosingBalance
A12: =VLOOKUP(B12,Summary!A:A,1,FALSE) -> Debt InstrumentsAccrued Interest | B12: =CONCATENATE(E12,F12) -> Debt InstrumentsAccrued Interest | C12: Assets | D12: Investments | E12: Debt Instruments | F12: Accrued Interest | G12: 6190456.3 | H12: 0 | I12: -1641274.5 | J12: 4549181.8
A13: =VLOOKUP(B13,Summary!A:A,1,FALSE) -> Debt InstrumentsAmortization / Accretion | B13: =CONCATENATE(E13,F13) -> Debt InstrumentsAmortization / Accretion | C13: Assets | D13: Investments | E13: Debt Instruments | F13: Amortization / Accretion | G13: 2069483.7 | H13: 0 | I13: -160132.7 | J13: 1909351
A14: =VLOOKUP(B14,Summary!A:A,1,FALSE) -> Debt InstrumentsCost | B14: =CONCATENATE(E14,F14) -> Debt InstrumentsCost | C14: Assets | D14: Investments | E14: Debt Instruments | F14: Cost | G14: 6.1416209e+08 | H14: 0 | I14: -74851765 | J14: 5.3931032e+08
A15: =VLOOKUP(B15,Summary!A:A,1,FALSE) -> Debt InstrumentsUnrealized FX GL | B15: =CONCATENATE(E15,F15) -> Debt InstrumentsUnrealized FX GL | C15: Assets | D15: Investments | E15: Debt Instruments | F15: Unrealized FX GL | G15: 336267.1 | H15: 0 | I15: -151337.72 | J15: 184929.38
A16: =VLOOKUP(B16,Summary!A:A,1,FALSE) -> Debt InstrumentsUnrealized Price G/L | B16: =CONCATENATE(E16,F16) -> Debt InstrumentsUnrealized Price G/L | C16: Assets | D16: Investments | E16: Debt Instruments | F16: Unrealized Price G/L | G16: -20045950 | H16: 0 | I16: -417869.35 | J16: -20463819
A17: =VLOOKUP(B17,Summary!A:A,1,FALSE) -> Equity InstrumentsCost | B17: =CONCATENATE(E17,F17) -> Equity InstrumentsCost | C17: Assets | D17: Investments | E17: Equity Instruments | F17: Cost | G17: 1.9228867e+08 | H17: 0 | I17: 0 | J17: 1.9228867e+08
A18: =VLOOKUP(B18,Summary!A:A,1,FALSE) -> Equity InstrumentsUnrealized FX GL | B18: =CONCATENATE(E18,F18) -> Equity InstrumentsUnrealized FX GL | C18: Assets | D18: Investments | E18: Equity Instruments | F18: Unrealized FX GL | G18: 233440.48 | H18: 0 | I18: -15815.55 | J18: 217624.93
A19: =VLOOKUP(B19,Summary!A:A,1,FALSE) -> Equity InstrumentsUnrealized Price G/L | B19: =CONCATENATE(E19,F19) -> Equity InstrumentsUnrealized Price G/L | C19: Assets | D19: Investments | E19: Equity Instruments | F19: Unrealized Price G/L | G19: 38967360 | H19: 0 | I19: -147576.47 | J19: 38819784
A20: =VLOOKUP(B20,Summary!A:A,1,FALSE) -> FinancingAccrued Interest | B20: =CONCATENATE(E20,F20) -> FinancingAccrued Interest | C20: Assets | D20: Investments | E20: Financing | F20: Accrued Interest | G20: -265890.98 | H20: 0 | I20: -9063.54 | J20: -274954.52
A21: =VLOOKUP(B21,Summary!A:A,1,FALSE) -> FinancingCost | B21: =CONCATENATE(E21,F21) -> FinancingCost | C21: Assets | D21: Investments | E21: Financing | F21: Cost | G21: -51456264 | H21: 0 | I21: 0 | J21: -51456264
A22: =VLOOKUP(B22,Summary!A:A,1,FALSE) -> FinancingUnrealized FX GL | B22: =CONCATENATE(E22,F22) -> FinancingUnrealized FX GL | C22: Assets | D22: Investments | E22: Financing | F22: Unrealized FX GL | G22: -161518.62 | H22: 149064.48 | I22: 0 | J22: -12454.14
A23: =VLOOKUP(B23,Summary!A:A,1,FALSE) -> FundAccrued Interest | B23: =CONCATENATE(E23,F23) -> FundAccrued Interest | C23: Assets | D23: Investments | E23: Fund | F23: Accrued Interest | G23: 4198782.7 | H23: 92280.92 | I23: 0 | J23: 4291063.6
... A75: =VLOOKUP(B75,Summary!A:A,1,FALSE) -> Line of Credit - Liability Cost | B75: =CONCATENATE(E75,F75) -> Line of Credit - Liability Cost | C75: Liabilities | D75: Payables | E75: Line of Credit - Liability | F75: Cost | G75: -245000000 | H75: 75000000 | I75: 0 | J75: -170000000
A76: =VLOOKUP(B76,Summary!A:A,1,FALSE) -> Accumulated net realized gain loss on investments prior years | B76: =CONCATENATE(E76,F76) -> Accumulated net realized gain loss on investments prior years | C76: Capital | D76: Partners' Capital | E76: Accumulated net realized gain loss on investments prior years | G76: -67497 | H76: 0 | I76: 0 | J76: -67497
A77: =VLOOKUP(B77,Summary!A:A,1,FALSE) -> Accumulated net realized gl on investments prior years | B77: =CONCATENATE(E77,F77) -> Accumulated net realized gl on investments prior years | C77: Capital | D77: Partners' Capital | E77: Accumulated net realized gl on investments prior years | G77: 71543952 | H77: 0 | I77: 0 | J77: 71543952
A78: =VLOOKUP(B78,Summary!A:A,1,FALSE) -> Capital Stock | B78: =CONCATENATE(E78,F78) -> Capital Stock | C78: Capital | D78: Partners' Capital | E78: Capital Stock | G78: -65296.14 | H78: 0 | I78: 0 | J78: -65296.14
A79: =VLOOKUP(B79,Summary!A:A,1,FALSE) -> ContributedCost | B79: =CONCATENATE(E79,F79) -> ContributedCost | C79: Capital | D79: Partners' Capital | E79: ContributedCost | G79: -7.405063e+08 | H79: 0 | I79: 0 | J79: -7.405063e+08
A80: =VLOOKUP(B80,Summary!A:A,1,FALSE) -> Net unrealized app dep on debt prior years | B80: =CONCATENATE(E80,F80) -> Net unrealized app dep on debt prior years | C80: Capital | D80: Partners' Capital | E80: Net unrealized app dep on debt prior years | G80: -1551670 | H80: 0 | I80: 0 | J80: -1551670
A81: =VLOOKUP(B81,Summary!A:A,1,FALSE) -> Net unrealized app dep on investments prior years | B81: =CONCATENATE(E81,F81) -> Net unrealized app dep on investments prior years | C81: Capital | D81: Partners' Capital | E81: Net unrealized app dep on investments prior years | G81: 111763780 | H81: 0 | I81: 0 | J81: 111763780
A82: =VLOOKUP(B82,Summary!A:A,1,FALSE) -> Undistributed net investment income Prior Years | B82: =CONCATENATE(E82,F82) -> Undistributed net investment income Prior Years | C82: Capital | D82: Partners' Capital | E82: Undistributed net investment income Prior Years | G82: -42600718 | H82: 0 | I82: 0 | J82: -42600718
A83: =VLOOKUP(B83,Summary!A:A,1,FALSE) -> Retained Earnings | B83: =CONCATENATE(E83,F83) -> Retained Earnings | C83: Capital | D83: Retained Earnings | E83: Retained Earnings | G83: 1.3753356e+08 | H83: 0 | I83: 0 | J83: 1.3753356e+08
A84: =VLOOKUP(B84,Summary!A:A,1,FALSE) -> Change in Unrealized FX Gain/Loss | B84: =CONCATENATE(E84,F84) -> Change in Unrealized FX Gain/Loss | C84: Revenue | E84: Change in Unrealized FX Gain/Loss | G84: -257922.04 | H84: 0 | I84: -281259.24 | J84: -539181.28
A85: =VLOOKUP(B85,Summary!A:A,1,FALSE) -> Change in Unrealized Price Gain/Loss | B85: =CONCATENATE(E85,F85) -> Change in Unrealized Price Gain/Loss | C85: Revenue | E85: Change in Unrealized Price Gain/Loss | G85: 57296588 | H85: 0 | I85: -1900579.4 | J85: 55396009
A86: =VLOOKUP(B86,Summary!A:A,1,FALSE) -> ChangeInAccruedInterestLong | B86: =CONCATENATE(E86,F86) -> ChangeInAccruedInterestLong | C86: Revenue | E86: ChangeInAccruedInterestLong | G86: 856088.02 | H86: 0 | I86: -4418132.4 | J86: -3562044.4
A87: =VLOOKUP(B87,Summary!A:A,1,FALSE) -> ChangeInTotalDiscountBasisLong | B87: =CONCATENATE(E87,F87) -> ChangeInTotalDiscountBasisLong | C87: Revenue | E87: ChangeInTotalDiscountBasisLong | G87: 305402.27 | H87: 65564.35 | I87: 0 | J87: 370966.62
A88: =VLOOKUP(B88,Summary!A:A,1,FALSE) -> ChangeInUnfundedLiabilityAccruedInterestLong | B88: =CONCATENATE(E88,F88) -> ChangeInUnfundedLiabilityAccruedInterestLong | C88: Revenue | E88: ChangeInUnfundedLiabilityAccruedInterestLong | G88: 4081.63 | H88: 0 | I88: -35408.29 | J88: -31326.66
A89: =VLOOKUP(B89,Summary!A:A,1,FALSE) -> Dividend Distribution Income | B89: =CONCATENATE(E89,F89) -> Dividend Distribution Income | C89: Revenue | E89: Dividend Distribution Income | G89: -3720.89 | H89: 0 | I89: -8383.08 | J89: -12103.97
A90: =VLOOKUP(B90,Summary!A:A,1,FALSE) -> Dividend Income - PSLF Membership | B90: =CONCATENATE(E90,F90) -> Dividend Income - PSLF Membership | C90: Revenue | E90: Dividend Income - PSLF Membership | G90: -4183813 | H90: 0 | I90: 0 | J90: -4183813
A91: =VLOOKUP(B91,Summary!A:A,1,FALSE) -> Dividend Income - PTSF II Membership | B91: =CONCATENATE(E91,F91) -> Dividend Income - PTSF II Membership | C91: Revenue | E91: Dividend Income - PTSF II Membership | G91: -230769 | H91: 0 | I91: 0 | J91: -230769
A92: =VLOOKUP(B92,Summary!A:A,1,FALSE) -> Interest Domestic Paydown | B92: =CONCATENATE(E92,F92) -> Interest Domestic Paydown | C92: Revenue | E92: Interest Domestic Paydown | G92: 100148.29 | H92: 1000.98 | I92: 0 | J92: 101149.27
A93: =VLOOKUP(B93,Summary!A:A,1,FALSE) -> Interest Income Sweep | B93: =CONCATENATE(E93,F93) -> Interest Income Sweep | C93: Revenue | E93: Interest Income Sweep | G93: -243734.55 | H93: 0 | I93: -157616.69 | J93: -401351.24
A94: =VLOOKUP(B94,Summary!A:A,1,FALSE) -> InterestReceipt | B94: =CONCATENATE(E94,F94) -> InterestReceipt | C94: Revenue | E94: InterestReceipt | G94: -22712075 | H94: 0 | I94: -2380889.9 | J94: -25092965
A95: =VLOOKUP(B95,Summary!A:A,1,FALSE) -> LongTermCurrencyGainLoss | B95: =CONCATENATE(E95,F95) -> LongTermCurrencyGainLoss | C95: Revenue | E95: LongTermCurrencyGainLoss | G95: -0.96 | H95: 0 | I95: 0 | J95: -0.96
... A138: =VLOOKUP(B138,Summary!A:A,1,FALSE) -> interest expense - 2026 Notes | B138: =CONCATENATE(E138,F138) -> interest expense - 2026 Notes | C138: Expense | E138: interest expense - 2026 Notes | G138: 438817.95 | H138: 146272.65 | I138: 0 | J138: 585090.6
A139: =VLOOKUP(B139,Summary!A:A,1,FALSE) | B139: =CONCATENATE(E139,F139)
A140: =VLOOKUP(B140,Summary!A:A,1,FALSE) | B140: =CONCATENATE(E140,F140) | C140: Header | D140: Value
A141: =VLOOKUP(B141,Summary!A:A,1,FALSE) | B141: =CONCATENATE(E141,F141) | C141: Net Asset Value | D141: 4.5925926e+08
A142: =VLOOKUP(B142,Summary!A:A,1,FALSE) | B142: =CONCATENATE(E142,F142) | C142: Total Outstanding shares | D142: 65296094
A143: =VLOOKUP(B143,Summary!A:A,1,FALSE) | B143: =CONCATENATE(E143,F143) | C143: Net asset value per share | D143: 7.03
A144: =VLOOKUP(B144,Summary!A:A,1,FALSE) | B144: =CONCATENATE(E144,F144)
A145: =VLOOKUP(B145,Summary!A:A,1,FALSE) | B145: =CONCATENATE(E145,F145) | C145: ParameterName | D145: ParameterValue
A146: =VLOOKUP(B146,Summary!A:A,1,FALSE) | B146: =CONCATENATE(E146,F146)
A147: =VLOOKUP(B147,Summary!A:A,1,FALSE) | B147: =CONCATENATE(E147,F147)
A148: =VLOOKUP(B148,Summary!A:A,1,FALSE) | B148: =CONCATENATE(E148,F148) | C148: ParameterName | D148: ParameterValue
C151: EventNumber | D151: ErrorMessage
C152: EventNumber | D152: ErrorMessage
C153: EventNumber | D153: ErrorMessage

Sheet BDC Long Short
A1: LongOrShort | B1: Currency | C1: InvestmentType | D1: InvestmentID | E1: TaxLotDescription | F1: Quantity | G1: TaxLotID | H1: LotDay | I1: UnitCost | J1: MarketPrice | K1: CostBook | L1: MarketValueBook | M1: PriceGainOrLoss | N1: FXGainOrLoss | O1: ExtendedDescription | P1: Description3 | Q1: AccruedDescription | R1: Accrued | S1: Coupon | T1: MatDate | U1: LXID
A2: Long Positions | B2: Canadian dollar | C2: Cash and Equivalents | D2: CAD | E2: Canadian dollar-NN_7100PP002 OnHand | F2: 362815.67 | I2: 1 | J2: 1 | K2: 261501.02 | L2: 267928.72 | M2: 0 | N2: 6427.7
A3: Long Positions | B3: Canadian dollar | C3: Bank Debt | D3: LX219880.PP | E3: Infinity Home Services Holdco, Inc. - Amendment No. 1 DDTL | F3: 2185389.8 | G3: 297781145 | H3: 45247 | I3: 98.75 | J3: 100 | K3: 1579569.6 | L3: 1613846.1 | M3: 12740.43 | N3: 21536.11 | P3: 11.00% of Global Commitment | Q3: Accrued Interest | R3: 11683.68 | S3: 0 | T3: 47115
A4: Long Positions | B4: Canadian dollar | C4: Bank Debt | D4: LX219880.PP3 | E4: Infinity Home Services Holdco, Inc. - Amendment No. 1 DDTL | F4: 350825.32 | G4: 305090121 | H4: 45436 | I4: 98.75 | J4: 100 | K4: 253858.66 | L4: 259074.19 | M4: 2348.01 | N4: 2867.52 | P4: 11.00% of Global Commitment | Q4: Accrued Interest | R4: 1875.6 | S4: 0 | T4: 47115
A5: Long Positions | B5: Canadian dollar | C5: Bank Debt | D5: LX219880.PP6 | E5: Infinity Home Services Holdco, Inc. - Amendment No. 1 DDTL | F5: 69244.14 | G5: 319126513 | H5: 45567 | I5: 98.75 | J5: 100 | K5: 50900.42 | L5: 51134.76 | M5: 451.55 | N5: -217.21 | P5: 11.00% of Global Commitment | Q5: Accrued Interest | R5: 370.2 | S5: 0 | T5: 47115
A6: Long Positions | B6: Euro | C6: Cash and Equivalents | D6: EUR | E6: Euro-NN_7100PP002 OnHand | F6: 25.11 | I6: 1 | J6: 1 | K6: 29.26 | L6: 29.87 | M6: 0 | N6: 0.61
A7: Long Positions | B7: U.K. pound | C7: Cash and Equivalents | D7: GBP | E7: U.K. pound-NN_7100PP002 OnHand | F7: 6033842.8 | I7: 1 | J7: 1 | K7: 8010134 | L7: 8279940.7 | M7: 0 | N7: 269806.73
A8: Long Positions | B8: U.K. pound | C8: Bank Debt | D8: LX175551.PP | E8: AKW Holdings Limited - Term Loan | F8: 253996.67 | G8: 297363470 | H8: 45107 | I8: 100 | J8: 100 | K8: 323118.1 | L8: 348546.93 | M8: 0 | N8: 25428.83 | P8: 0.70% of Global Commitment | Q8: Accrued Interest | R8: 3377.09 | S8: 0 | T8: 46461
A9: Long Positions | B9: U.K. pound | C9: Bank Debt | D9: LX175551.PP | E9: AKW Holdings Limited - Term Loan | F9: 326355.94 | G9: 297363552 | H9: 45198 | I9: 100 | J9: 100 | K9: 399210.94 | L9: 447841.93 | M9: 0 | N9: 48630.99 | P9: 0.89% of Global Commitment | Q9: Accrued Interest | R9: 4339.18 | S9: 0 | T9: 46461
A10: Long Positions | B10: U.K. pound | C10: Bank Debt | D10: LX175551.PP | E10: AKW Holdings Limited - Term Loan | F10: 442524.52 | G10: 297363644 | H10: 45289 | I10: 100 | J10: 100 | K10: 564420.54 | L10: 607254.27 | M10: 0 | N10: 42833.73 | P10: 1.21% of Global Commitment | Q10: Accrued Interest | R10: 5883.74 | S10: 0 | T10: 46461
A11: Long Positions | B11: U.K. pound | C11: Bank Debt | D11: LX175551.PP | E11: AKW Holdings Limited - Term Loan | F11: 446572.98 | G11: 297747816 | H11: 44021 | I11: 100 | J11: 100 | K11: 563888.71 | L11: 612809.75 | M11: 0 | N11: 48921.04 | P11: 1.22% of Global Commitment | Q11: Accrued Interest | R11: 5937.56 | S11: 0 | T11: 46461
A12: Long Positions | B12: U.K. pound | C12: Bank Debt | D12: LX175551.PP | E12: AKW Holdings Limited - Term Loan | F12: 446572.98 | G12: 297752234 | H12: 44106 | I12: 100 | J12: 100 | K12: 580330.35 | L12: 612809.75 | M12: 0 | N12: 32479.4 | P12: 1.22% of Global Commitment | Q12: Accrued Interest | R12: 5937.56 | S12: 0 | T12: 46461
A13: Long Positions | B13: U.K. pound | C13: Bank Debt | D13: LX175551.PP | E13: AKW Holdings Limited - Term Loan | F13: 446572.98 | G13: 297747818 | H13: 44179 | I13: 100 | J13: 100 | K13: 594020.98 | L13: 612809.77 | M13: 0 | N13: 18788.79 | P13: 1.22% of Global Commitment | Q13: Accrued Interest | R13: 5937.56 | S13: 0 | T13: 46461
A14: Long Positions | B14: U.K. pound | C14: Bank Debt | D14: LX175551.PP | E14: AKW Holdings Limited - Term Loan | F14: 446572.98 | G14: 297747819 | H14: 44266 | I14: 100 | J14: 100 | K14: 622068.48 | L14: 612809.76 | M14: 0 | N14: -9258.72 | P14: 1.22% of Global Commitment | Q14: Accrued Interest | R14: 5937.56 | S14: 0 | T14: 46461
A15: Long Positions | B15: U.K. pound | C15: Bank Debt | D15: LX175551.PP | E15: AKW Holdings Limited - Term Loan | F15: 446572.98 | G15: 297363117 | H15: 44452 | I15: 100 | J15: 100 | K15: 616931.82 | L15: 612809.76 | M15: 0 | N15: -4122.06 | P15: 1.22% of Global Commitment | Q15: Accrued Interest | R15: 5937.56 | S15: 0 | T15: 46461
A16: Long Positions | B16: U.K. pound | C16: Bank Debt | D16: LX175551.PP | E16: AKW Holdings Limited - Term Loan | F16: 446572.98 | G16: 297363145 | H16: 44543 | I16: 100 | J16: 100 | K16: 590281.31 | L16: 612809.75 | M16: 0 | N16: 22528.44 | P16: 1.22% of Global Commitment | Q16: Accrued Interest | R16: 5937.56 | S16: 0 | T16: 46461
A17: Long Positions | B17: U.K. pound | C17: Bank Debt | D17: LX175551.PP | E17: AKW Holdings Limited - Term Loan | F17: 446572.98 | G17: 297363174 | H17: 44629 | I17: 100 | J17: 100 | K17: 587143.42 | L17: 612809.75 | M17: 0 | N17: 25666.33 | P17: 1.22% of Global Commitment | Q17: Accrued Interest | R17: 5937.56 | S17: 0 | T17: 46461
A18: Long Positions | B18: U.K. pound | C18: Bank Debt | D18: LX175551.PP | E18: AKW Holdings Limited - Term Loan | F18: 475154.97 | G18: 297363383 | H18: 45016 | I18: 100 | J18: 100 | K18: 588499.55 | L18: 652031.4 | M18: 0 | N18: 63531.85 | P18: 1.30% of Global Commitment | Q18: Accrued Interest | R18: 6317.59 | S18: 0 | T18: 46461
A19: Long Positions | B19: U.K. pound | C19: Bank Debt | D19: LX175551.PP | E19: AKW Holdings Limited - Term Loan | F19: 4242443.4 | G19: 297363167 | H19: 44586 | I19: 100 | J19: 100 | K19: 5711803 | L19: 5821693 | M19: 0 | N19: 109890.02 | P19: 11.62% of Global Commitment | Q19: Accrued Interest | R19: 56406.87 | S19: 0 | T19: 46461
... A22: Long Positions | B22: U.K. pound | C22: Bank Debt | D22: LX175551.PP | E22: AKW Holdings Limited - Term Loan | F22: 25008088 | G22: 297745759 | H22: 43166 | I22: 100 | J22: 100 | K22: 34782879 | L22: 34317348 | M22: 0 | N22: -465530.83 | P22: 68.52% of Global Commitment | Q22: Accrued Interest | R22: 332503.63 | S22: 0 | T22: 46461
A23: Long Positions | B23: U.K. pound | C23: Common Stock | D23: 1199211 | E23: AKW Holdings Limited | F23: 938.529 | G23: 297363873 | H23: 43166 | I23: 101.2222 | J23: 35437.108 | K23: 132496.5 | L23: 45639324 | M23: 45508960 | N23: -2132.75
A24: Long Positions | B24: U.K. pound | C24: Common Stock | D24: 1199211A | E24: AKW Holdings Limited - Class B Common share | F24: 12.5 | G24: 345894253 | H24: 45859 | I24: 7333.3336 | J24: 38089.15 | K24: 123690.42 | L24: 653347.96 | M24: 527558.37 | N24: 2099.17
A25: Long Positions | B25: U.K. pound | C25: Common Stock | D25: 1199211B | E25: AKW Holdings Limited - Class C Common share | F25: 12.5 | G25: 345894255 | H25: 45859 | I25: 8666.6664 | J25: 45014.45 | K25: 146179.58 | L25: 772138.49 | M25: 623478.08 | N25: 2480.83
A26: Long Positions | B26: U.K. pound | C26: Common Stock | D26: 1199211C | E26: AKW Holdings Limited - Class D Common share | F26: 87.657 | G26: 356140519 | H26: 45967 | I26: 29173.81 | J26: 38712.117 | K26: 3350687.5 | L26: 4656576.8 | M26: 1147337.4 | N26: 158551.9
A27: Long Positions | B27: U.K. pound | C27: Common Stock | D27: 1199211D | E27: AKW Holdings Limited - Class E Common share | F27: 82.384 | G27: 356140525 | H27: 45967 | I27: 11086.12 | J27: 14710.701 | K27: 1196676.1 | L27: 1663066 | M27: 409764.08 | N27: 56625.78
A28: Long Positions | B28: U.S. Dollars | C28: Cash and Equivalents | D28: USD | E28: U.S. Dollars-NN_7100PP002 CouponInterestReceivable | F28: 465074.15 | I28: 1 | J28: 1 | K28: 465074.15 | L28: 465074.15 | M28: 0 | N28: 0
A29: Long Positions | B29: U.S. Dollars | C29: Cash and Equivalents | D29: USD | E29: U.S. Dollars-NN_7100PP002 OnHand | F29: 3252494.4 | I29: 1 | J29: 1 | K29: 3252494.4 | L29: 3252494.4 | M29: 0 | N29: 0
A30: Long Positions | B30: U.S. Dollars | C30: Cash and Equivalents | D30: USD | E30: U.S. Dollars-NN_7100PP002 Payable | F30: -5184433.4 | I30: 1 | J30: 1 | K30: -5184433.4 | L30: -5184433.4 | M30: 0 | N30: 0
A31: Long Positions | B31: U.S. Dollars | C31: Cash and Equivalents | D31: USD | E31: U.S. Dollars-NN_7100PP002 Receivable | F31: 82048076 | I31: 1 | J31: 1 | K31: 82048076 | L31: 82048076 | M31: 0 | N31: 0
A32: Long Positions | B32: U.S. Dollars | C32: Cash and Equivalents | D32: USD | E32: U.S. Dollars-NN_7100PP012 OnHand | F32: 5457634.7 | I32: 1 | J32: 1 | K32: 5457634.7 | L32: 5457634.7 | M32: 0 | N32: 0
A33: Long Positions | B33: U.S. Dollars | C33: Bank Debt | D33: 104739 | E33: PCS MIDCO INC. First Lien DDTL DDTL - CF | F33: 460869.74 | G33: 298204399 | H33: 45357 | I33: 99 | J33: 100.5 | K33: 457560.57 | L33: 463174.09 | M33: 5613.52 | N33: 0 | P33: 8.85% of Global Commitment | Q33: Accrued Interest | R33: 3859.81 | S33: 1 | T33: 47515 | U33: 104739
A34: Long Positions | B34: U.S. Dollars | C34: Bank Debt | D34: 104739A | E34: PCS MIDCO INC. First Lien DDTL DDTL - CF | F34: 1695434.3 | G34: 319228095 | H34: 45580 | I34: 99 | J34: 100.5 | K34: 1681963.8 | L34: 1703911.5 | M34: 21947.66 | N34: 0 | P34: 8.85% of Global Commitment | Q34: Accrued Interest | R34: 14199.36 | S34: 0 | T34: 47515
A35: Long Positions | B35: U.S. Dollars | C35: Bank Debt | D35: 104739B | E35: PCS MIDCO INC. First Lien DDTL DDTL - CF | F35: 160083.34 | G35: 350183040 | H35: 45911 | I35: 99 | J35: 100.5 | K35: 158619.94 | L35: 160883.76 | M35: 2263.82 | N35: 0 | P35: 8.85% of Global Commitment | Q35: Accrued Interest | R35: 1340.71 | S35: 0 | T35: 47515
A36: Long Positions | B36: U.S. Dollars | C36: Bank Debt | D36: 105214.PP | E36: GGG Midco, LLC - First Lien DDTL C Unfunded | F36: 5190209.1 | G36: 356351395 | H36: 45973 | I36: 99 | J36: 100 | K36: 5138307 | L36: 5190209.1 | M36: 51902.09 | N36: 0 | O36: S + 5.00%; 1.00% Floor | Q36: Accrued Interest | R36: 3460.14 | S36: 0.75 | T36: 47753
A37: Long Positions | B37: U.S. Dollars | C37: Bank Debt | D37: 1328.PP | E37: Ad.net Acquisition, LLC - Revolver | F37: 13333.33 | G37: 297363085 | H37: 44320 | I37: 100 | J37: 100 | K37: 0 | L37: 0 | M37: 0 | N37: 0 | P37: 0.27% of Global Commitment | Q37: Accrued Interest | R37: 5.93 | S37: 0.5 | T37: 46149
A38: Long Positions | B38: U.S. Dollars | C38: Bank Debt | D38: 1328.PP | E38: Ad.net Acquisition, LLC - Revolver | F38: 44444.44 | G38: 297363362 | H38: 44988 | I38: 100 | J38: 100 | K38: 0 | L38: 0 | M38: 0 | N38: 0 | P38: 0.89% of Global Commitment | Q38: Accrued Interest | R38: 19.75 | S38: 0.5 | T38: 46149
A39: Long Positions | B39: U.S. Dollars | C39: Bank Debt | D39: 1328.PP | E39: Ad.net Acquisition, LLC - Revolver | F39: 75555.56 | G39: 297363134 | H39: 44512 | I39: 100 | J39: 100 | K39: 0 | L39: 0 | M39: 0 | N39: 0 | P39: 1.51% of Global Commitment | Q39: Accrued Interest | R39: 33.58 | S39: 0.5 | T39: 46149
A40: Long Positions | B40: U.S. Dollars | C40: Bank Debt | D40: 1328.PP | E40: Ad.net Acquisition, LLC - Revolver | F40: 88888.89 | G40: 297363511 | H40: 45142 | I40: 100 | J40: 100 | K40: 0 | L40: 0 | M40: 0 | N40: 0 | P40: 1.78% of Global Commitment | Q40: Accrued Interest | R40: 39.51 | S40: 0.5 | T40: 46149
A41: Long Positions | B41: U.S. Dollars | C41: Bank Debt | D41: 1328.PP | E41: Ad.net Acquisition, LLC - Revolver | F41: 222222.23 | G41: 297363777 | H41: 45331 | I41: 100 | J41: 100 | K41: 0 | L41: 0 | M41: 0 | N41: 0 | P41: 4.44% of Global Commitment | Q41: Accrued Interest | R41: 98.77 | S41: 0.5 | T41: 46149
A42: Long Positions | B42: U.S. Dollars | C42: Bank Debt | D42: 1360.PP | E42: Connatix Buyer, Inc. - Revolver | F42: 15625 | G42: 297363476 | H42: 45107 | I42: 55.5333 | J42: 100 | K42: 8677.08 | L42: 8677.08 | M42: 0 | N42: 0 | P42: 0.83% of Global Commitment | Q42: Accrued Interest | R42: 62.94 | S42: 0.5 | T42: 46581
A43: Long Positions | B43: U.S. Dollars | C43: Bank Debt | D43: 1360.PP | E43: Connatix Buyer, Inc. - Revolver | F43: 1673437.5 | G43: 297363096 | H43: 44385 | I43: 55.5333 | J43: 100 | K43: 929315.62 | L43: 929315.62 | M43: 0 | N43: 0 | P43: 89.25% of Global Commitment | Q43: Accrued Interest | R43: 6741.08 | S43: 0.5 | T43: 46581
A44: Long Positions | B44: U.S. Dollars | C44: Bank Debt | D44: 1360.PP | E44: Connatix Buyer, Inc. - Revolver | F44: 185937.5 | G44: 297363144 | H44: 44536 | I44: 55.5333 | J44: 100 | K44: 103257.29 | L44: 103257.29 | M44: 0 | N44: 0 | P44: 9.92% of Global Commitment | Q44: Accrued Interest | R44: 749.01 | S44: 0.5 | T44: 46581
A45: Long Positions | B45: U.S. Dollars | C45: Bank Debt | D45: 1400.PP | E45: Lash OpCo, LLC - Term Loan | F45: 37117.66 | G45: 298191518 | H45: 45352 | I45: 100 | J45: 97.5 | K45: 37117.66 | L45: 36189.72 | M45: -927.94 | N45: 0 | P45: 0.02% of Global Commitment | Q45: Accrued Interest | R45: 22.2 | S45: 0 | T45: 46436
A46: Long Positions | B46: U.S. Dollars | C46: Bank Debt | D46: 1400.PP | E46: Lash OpCo, LLC - Term Loan | F46: 36724.54 | G46: 302903414 | H46: 45412 | I46: 100 | J46: 97.5 | K46: 36724.54 | L46: 35806.43 | M46: -918.11 | N46: 0 | P46: 0.02% of Global Commitment | Q46: Accrued Interest | R46: 21.97 | S46: 0 | T46: 46436
A47: Long Positions | B47: U.S. Dollars | C47: Bank Debt | D47: 1400.PP | E47: Lash OpCo, LLC - Term Loan | F47: 38019.29 | G47: 312045001 | H47: 45504 | I47: 100 | J47: 97.5 | K47: 38019.29 | L47: 37068.81 | M47: -950.48 | N47: 0 | P47: 0.02% of Global Commitment | Q47: Accrued Interest | R47: 22.74 | S47: 0 | T47: 46436
A48: Long Positions | B48: U.S. Dollars | C48: Bank Debt | D48: 1400.PP | E48: Lash OpCo, LLC - Term Loan | F48: 38514.8 | G48: 319995803 | H48: 45596 | I48: 100 | J48: 97.5 | K48: 38514.8 | L48: 37551.93 | M48: -962.87 | N48: 0 | P48: 0.02% of Global Commitment | Q48: Accrued Interest | R48: 23.04 | S48: 0 | T48: 46436
... A91: Long Positions | B91: U.S. Dollars | C91: Bank Debt | D91: 1602.PP1 | E91: Flock Financial, LLC - Mezzanine Debt | F91: 23030686 | G91: 305967055 | H91: 45401 | I91: 100 | J91: 100 | K91: 23030686 | L91: 23030686 | M91: 0 | N91: 0 | P91: 77.27% of Global Commitment | Q91: Accrued Interest | R91: 255896.52 | S91: 0 | T91: 46533
A92: Long Positions | B92: U.S. Dollars | C92: Bank Debt | D92: 1613.PP | E92: HV Watterson Holdings, LLC - DDTL | F92: 286210.92 | G92: 297363272 | H92: 44792 | I92: 99.2798 | J92: 31.8 | K92: 285408.99 | L92: 91015.07 | M92: -194393.92 | N92: 0 | P92: 12.50% of Global Commitment | S92: 0 | T92: 46373
A93: Long Positions | B93: U.S. Dollars | C93: Bank Debt | D93: 1617.PP | E93: HV Watterson Holdings, LLC - Revolver | F93: 50000 | G93: 297363225 | H93: 44725 | I93: 99.9749 | J93: 31.8 | K93: 49987.47 | L93: 15887.47 | M93: -34100 | N93: 0 | P93: 0.40% of Global Commitment | Q93: Accrued Interest | R93: 0.01 | S93: 0.5 | T93: 46373
A94: Long Positions | B94: U.S. Dollars | C94: Bank Debt | D94: 1617.PP | E94: HV Watterson Holdings, LLC - Revolver | F94: 100000 | G94: 297363529 | H94: 45174 | I94: 99.9749 | J94: 31.8 | K94: 99974.93 | L94: 31774.93 | M94: -68200 | N94: 0 | P94: 0.80% of Global Commitment | Q94: Accrued Interest | R94: 0.01 | S94: 0.5 | T94: 46373
A95: Long Positions | B95: U.S. Dollars | C95: Bank Debt | D95: 1617.PP | E95: HV Watterson Holdings, LLC - Revolver | F95: 100000 | G95: 297363612 | H95: 45257 | I95: 99.9749 | J95: 31.8 | K95: 99974.93 | L95: 31774.93 | M95: -68200 | N95: 0 | P95: 0.80% of Global Commitment | Q95: Accrued Interest | R95: 0.01 | S95: 0.5 | T95: 46373
A96: Long Positions | B96: U.S. Dollars | C96: Bank Debt | D96: 1617.PP | E96: HV Watterson Holdings, LLC - Revolver | F96: 150000 | G96: 297363379 | H96: 45015 | I96: 99.9749 | J96: 31.8 | K96: 149962.4 | L96: 47662.4 | M96: -102300 | N96: 0 | P96: 1.20% of Global Commitment | Q96: Accrued Interest | R96: 0.02 | S96: 0.5 | T96: 46373
A97: Long Positions | B97: U.S. Dollars | C97: Bank Debt | D97: 1617.PP | E97: HV Watterson Holdings, LLC - Revolver | F97: 200000 | G97: 297363572 | H97: 45205 | I97: 99.9749 | J97: 31.8 | K97: 199949.86 | L97: 63549.86 | M97: -136400 | N97: 0 | P97: 1.60% of Global Commitment | Q97: Accrued Interest | R97: 0.02 | S97: 0.5 | T97: 46373
A98: Long Positions | B98: U.S. Dollars | C98: Bank Debt | D98: 1617.PP | E98: HV Watterson Holdings, LLC - Revolver | F98: 300000 | G98: 297363550 | H98: 45198 | I98: 99.9749 | J98: 31.8 | K98: 299924.79 | L98: 95324.79 | M98: -204600 | N98: 0 | P98: 2.40% of Global Commitment | Q98: Accrued Interest | R98: 0.03 | S98: 0.5 | T98: 46373
A99: Long Positions | B99: U.S. Dollars | C99: Bank Debt | D99: 1617.PP | E99: HV Watterson Holdings, LLC - Revolver | F99: 350000 | G99: 297363471 | H99: 45107 | I99: 99.9749 | J99: 31.8 | K99: 349912.26 | L99: 111212.26 | M99: -238700 | N99: 0 | P99: 2.80% of Global Commitment | Q99: Accrued Interest | R99: 0.04 | S99: 0.5 | T99: 46373
A100: Long Positions | B100: U.S. Dollars | C100: Bank Debt | D100: 1619.PP | E100: Shiftkey, LLC Term Loan | F100: 16569678 | G100: 297363222 | H100: 44729 | I100: 99.0013 | J100: 96.2 | K100: 16508968 | L100: 15940031 | M100: -568937.68 | N100: 0 | P100: 4.50% of Global Commitment | Q100: Accrued Interest | R100: 154843.42 | S100: 0 | T100: 46559
A101: Long Positions | B101: U.S. Dollars | C101: Bank Debt | D101: 1679.PP | E101: TMII (A1 Garage Merger Sub), LLC - Revolver | F101: 2531645.6 | G101: 297363316 | H101: 44914 | I101: 100 | J101: 100 | K101: 0 | L101: 0 | M101: 0 | N101: 0 | P101: 12.66% of Global Commitment | Q101: Accrued Interest | R101: 1125.18 | S101: 0.5 | T101: 47109
A102: Long Positions | B102: U.S. Dollars | C102: Bank Debt | D102: 1684.PP | E102: EDS Buyer, LLC - Revolver | F102: 1914800 | G102: 297363328 | H102: 44914 | I102: 100 | J102: 100.25 | K102: 0 | L102: 4787 | M102: 4787 | N102: 0 | P102: 22.50% of Global Commitment | Q102: Accrued Interest | R102: 851.02 | S102: 0.5 | T102: 47128
A103: Long Positions | B103: U.S. Dollars | C103: Bank Debt | D103: 1702.PP | E103: BioDerm - Revolver | F103: 107142.86 | G103: 297363561 | H103: 45198 | I103: 100 | J103: 98.75 | K103: 107142.86 | L103: 105803.57 | M103: -1339.29 | N103: 0 | P103: 10.00% of Global Commitment | Q103: Accrued Interest | R103: 956.22 | S103: 0.5 | T103: 46783
A104: Long Positions | B104: U.S. Dollars | C104: Bank Debt | D104: 1702.PP | E104: BioDerm - Revolver | F104: 160714.29 | G104: 297363585 | H104: 45224 | I104: 100 | J104: 98.75 | K104: 160714.29 | L104: 158705.36 | M104: -2008.93 | N104: 0 | P104: 15.00% of Global Commitment | Q104: Accrued Interest | R104: 1434.33 | S104: 0.5 | T104: 46783
... A274: Long Positions | B274: U.S. Dollars | C274: Bank Debt | D274: 9787.PP | E274: APT OPCO, LLC - Revolver | F274: 1228240.7 | G274: 351933777 | H274: 45929 | I274: 100 | J274: 98.75 | K274: 0 | L274: -15353.01 | M274: -15353.01 | N274: 0 | P274: 8.19% of Global Commitment | Q274: Accrued Interest | R274: 545.88 | S274: 0.5 | T274: 48120
A275: Long Positions | B275: U.S. Dollars | C275: Bank Debt | D275: BDC 23513A | E275: RRA Corporate, LLC - DDTL 2 Unfunded | F275: 3337070.7 | G275: 312707344 | H275: 45519 | I275: 99 | J275: 96.9 | K275: 3303700 | L275: 3233621.5 | M275: -70078.48 | N275: 0 | O275: 1.00% Ticketing Fee | Q275: Accrued Interest | R275: 2966.29 | S275: 1 | T275: 46249
A276: Long Positions | B276: U.S. Dollars | C276: Bank Debt | D276: BDC 3218 | E276: Project Granite Buyer, Inc.- DDTL Unfunded | F276: 553800 | G276: 326776036 | H276: 45657 | I276: 99 | J276: 101 | K276: 548262 | L276: 559338 | M276: 11076 | N276: 0 | O276: S+5.75%;0.75%Floor | Q276: Accrued Interest | R276: 492.27 | S276: 1 | T276: 47848
A277: Long Positions | B277: U.S. Dollars | C277: Bank Debt | D277: BDC 32743 | E277: First Medical Associates - First Lien DDTL Unfunded | F277: 2820000 | G277: 342807249 | H277: 45821 | I277: 99 | J277: 99 | K277: 2791800 | L277: 2791800 | M277: 0 | N277: 0 | O277: S + 5.75% (1.00% Floor) | Q277: Accrued Interest | R277: 2506.67 | S277: 1 | T277: 46551
A278: Long Positions | B278: U.S. Dollars | C278: Bank Debt | D278: BDC 3276 | E278: Archer Lewis, LLC - DDTL B Unfunded | F278: 5329062.5 | G278: 314272512 | H278: 45532 | I278: 99 | J278: 100 | K278: 5275771.9 | L278: 5329062.5 | M278: 53290.63 | N278: 0 | O278: S + 5.75%, 1.00% Floor | Q278: Accrued Interest | R278: 2368.47 | S278: 0.5 | T278: 46262
A279: Long Positions | B279: U.S. Dollars | C279: Bank Debt | D279: BDC 3287 | E279: SV-Aero Holdings, LLC - DDTL Unfunded | F279: 3562005.3 | G279: 320678497 | H279: 45596 | I279: 99.5 | J279: 100 | K279: 3544195.2 | L279: 3562005.3 | M279: 17810.03 | N279: 0 | O279: SOFR + 4.25% (1% Floor) | Q279: Accrued Interest | R279: 3166.23 | S279: 1 | T279: 46327
A280: Long Positions | B280: U.S. Dollars | C280: Bank Debt | D280: BDC 33435 | E280: LJ Avalon Holdings, LLC - LOC Unfunded | F280: 3915.2 | G280: 300119952 | H280: 45289 | I280: 100 | J280: 100 | K280: 3915.2 | L280: 3915.2 | M280: 0 | N280: 0 | O280: 6.25% Ticketing Fee | Q280: Accrued Interest | R280: 15.66 | S280: 4.5 | T280: 47514
A281: Long Positions | B281: U.S. Dollars | C281: Bank Debt | D281: BDC 33435A | E281: LJ Avalon Holdings, LLC - LOC Unfunded | F281: 8070.65 | G281: 308201670 | H281: 45435 | I281: 100 | J281: 100 | K281: 8070.65 | L281: 8070.65 | M281: 0 | N281: 0 | O281: 5.25% Ticketing Fee | Q281: Accrued Interest | R281: 32.28 | S281: 4.5 | T281: 47514
A282: Long Positions | B282: U.S. Dollars | C282: Bank Debt | D282: BDC 33435A | E282: LJ Avalon Holdings, LLC - LOC Unfunded | F282: 6364.74 | G282: 364014906 | H282: 45930 | I282: 100 | J282: 100 | K282: 6364.74 | L282: 6364.74 | M282: 0 | N282: 0 | O282: 5.25% Ticketing Fee | Q282: Accrued Interest | R282: 25.46 | S282: 4.5 | T282: 47514
A283: Long Positions | B283: U.S. Dollars | C283: Bank Debt | D283: BDC 3395AB | E283: MDI Buyer, Inc. - Revolver Unfunded (1/16/24 Lot) | F283: 418639.17 | G283: 338152192 | H283: 45747 | I283: 100 | J283: 100 | K283: 418639.17 | L283: 418639.17 | M283: 0 | N283: 0 | O283: 0.50% Ticketing Fee | Q283: Accrued Interest | R283: 186.06 | S283: 0.5 | T283: 46959
A284: Long Positions | B284: U.S. Dollars | C284: Bank Debt | D284: BDC 3395AB | E284: MDI Buyer, Inc. - Revolver Unfunded (1/16/24 Lot) | F284: 258309.28 | G284: 354878895 | H284: 45959 | I284: 100 | J284: 100 | K284: 258309.28 | L284: 258309.28 | M284: 0 | N284: 0 | O284: 0.50% Ticketing Fee | Q284: Accrued Interest | R284: 114.8 | S284: 0.5 | T284: 46959
A285: Long Positions | B285: U.S. Dollars | C285: Bank Debt | D285: BDC 35750 | E285: Carisk Buyer, Inc. - DDTL Unfunded | F285: 4812500 | G285: 297364090 | H285: 45257 | I285: 99 | J285: 100.75 | K285: 4764375 | L285: 4848593.8 | M285: 84218.75 | N285: 0 | O285: 1.00% Ticketing Fee | Q285: Accrued Interest | R285: 4277.78 | S285: 1 | T285: 47455
A286: Long Positions | B286: U.S. Dollars | C286: Bank Debt | D286: BDC 3575A | E286: Carisk Buyer, Inc. - Amendment 1 DDTL Unfunded | F286: 1527777.8 | G286: 318680454 | H286: 45566 | I286: 99.25 | J286: 100.75 | K286: 1516319.4 | L286: 1539236.1 | M286: 22916.66 | N286: 0 | O286: 1.00% Ticketing Fee | Q286: Accrued Interest | R286: 1358.02 | S286: 1 | T286: 46296
A287: Long Positions | B287: U.S. Dollars | C287: Bank Debt | D287: BDC 42098 | E287: Peninsula Pacific Entertainment - Term B Facility Loan DDTL Unfunded | F287: 1230661 | G287: 348767870 | H287: 45884 | I287: 99.5 | J287: 100.25 | K287: 1224507.7 | L287: 1233737.6 | M287: 9229.95 | N287: 0 | Q287: Accrued Interest | R287: 2598.06 | S287: 2.375 | T287: 46614
A288: Long Positions | B288: U.S. Dollars | C288: Bank Debt | D288: BDC 42147 | E288: PCS Midco, Inc. - DDTL Unfunded | F288: 2077812.8 | G288: 298062208 | H288: 45352 | I288: 99 | J288: 100.5 | K288: 2057034.6 | L288: 2088201.8 | M288: 31167.19 | N288: 0 | O288: 1.00% Ticketing Fee | Q288: Accrued Interest | R288: 1846.94 | S288: 1 | T288: 46082
A289: Long Positions | B289: U.S. Dollars | C289: Bank Debt | D289: BDC 4332 | E289: Carnegie Dartlet, LLC - DDTL Unfunded | F289: 7679776.7 | G289: 297364107 | H289: 45329 | I289: 99 | J289: 99 | K289: 7602978.9 | L289: 7602978.9 | M289: 0 | N289: 0 | O289: 1.00% Ticketing Fee | Q289: Accrued Interest | R289: 3413.23 | S289: 0.5 | T289: 46062
A290: Long Positions | B290: U.S. Dollars | C290: Bank Debt | D290: BDC 45835 | E290: Spendmend Holdings LLC - Unfunded DDTL (99.50) | F290: 1049600 | G290: 322310949 | H290: 45621 | I290: 99.5 | J290: 100 | K290: 1044352 | L290: 1049600 | M290: 5248 | N290: 0 | O290: 1.00% Ticketing Fee | Q290: Accrued Interest | R290: 932.98 | S290: 1 | T290: 46351
A291: Long Positions | B291: U.S. Dollars | C291: Bank Debt | D291: BDC 4592 | E291: Paving Lessor Corp - DDTL Unfunded | F291: 3291416.9 | G291: 345291196 | H291: 45839 | I291: 99.25 | J291: 99.5 | K291: 3266731.2 | L291: 3274959.8 | M291: 8228.55 | N291: 0 | O291: S + 5.25% (1.00% Floor) | Q291: Accrued Interest | R291: 2925.7 | S291: 1 | T291: 48030
A292: Long Positions | B292: U.S. Dollars | C292: Bank Debt | D292: BDC 4940B.PP1 | E292: Systems Planning and Analysis, Inc. - DDTL B | F292: 110851.55 | G292: 344170192 | H292: 45828 | I292: 99.5 | J292: 99.7 | K292: 110417.02 | L292: 110519 | M292: 101.98 | N292: 0 | P292: 0.74% of Global Commitment | Q292: Accrued Interest | R292: 829.85 | S292: 0 | T292: 46615
A293: Long Positions | B293: U.S. Dollars | C293: Bank Debt | D293: BDC 4940B.PP2 | E293: Systems Planning and Analysis, Inc. - DDTL B | F293: 692876.4 | G293: 344170263 | H293: 45838 | I293: 99.5 | J293: 99.7 | K293: 690126.24 | L293: 690797.77 | M293: 671.53 | N293: 0 | P293: 2.40% of Global Commitment | Q293: Accrued Interest | R293: 5186.99 | S293: 0 | T293: 46615
A294: Long Positions | B294: U.S. Dollars | C294: Bank Debt | D294: BDC 4940B.PP3 | E294: Systems Planning and Analysis, Inc. - DDTL B | F294: 1158476.4 | G294: 352076756 | H294: 45930 | I294: 99.5 | J294: 99.7 | K294: 1153517 | L294: 1155001 | M294: 1484 | N294: 0 | P294: 2.40% of Global Commitment | Q294: Accrued Interest | R294: 8672.55 | S294: 0 | T294: 46615
A295: Long Positions | B295: U.S. Dollars | C295: Bank Debt | D295: BDC 4945 | E295: Systems Planning and Analysis, Inc. - DDTL 2025 Unfunded | F295: 588960 | G295: 342493116 | H295: 45820 | I295: 99.5 | J295: 99.7 | K295: 586015.2 | L295: 587193.12 | M295: 1177.92 | N295: 0 | O295: S + 4.75%, 1.00% Floor | Q295: Accrued Interest | R295: 523.52 | S295: 1 | T295: 46550
A296: Long Positions | B296: U.S. Dollars | C296: Bank Debt | D296: BDC 5696 | E296: Adweek Purchaser, LLC - DDTL Unfunded | F296: 300000 | G296: 305655320 | H296: 45443 | I296: 98.5 | J296: 100 | K296: 295500 | L296: 300000 | M296: 4500 | N296: 0 | O296: 1.0% Ticketing Fee | Q296: Accrued Interest | R296: 133.33 | S296: 0.5 | T296: 46537
A297: Long Positions | B297: U.S. Dollars | C297: Bank Debt | D297: BDC 578742 | E297: Beacon Behavioral Support Services, LLC - 3rd Amendment DDTL Unfunded | F297: 12627344 | G297: 352062270 | H297: 45926 | I297: 99 | J297: 100 | K297: 12501070 | L297: 12627344 | M297: 126273.44 | N297: 0 | O297: S + 5.50%, 1.00% Floor | Q297: Accrued Interest | R297: 11224.31 | S297: 1 | T297: 46559
A298: Long Positions | B298: U.S. Dollars | C298: Bank Debt | D298: BDC 5799A | E298: Beacon Behavioral Support Service, LLC.DDTL unfunded | F298: 1389038.4 | G298: 325567051 | H298: 45639 | I298: 99 | J298: 100 | K298: 1375148 | L298: 1389038.4 | M298: 13890.38 | N298: 0 | O298: 1.00% fee expire in 24 months | Q298: Accrued Interest | R298: 1234.7 | S298: 1 | T298: 46369
A299: Long Positions | B299: U.S. Dollars | C299: Bank Debt | D299: BDC 5908.PP | E299: United Land Services Intermediate Parent Holdings, .DDTL | F299: 3931716.6 | G299: 318935889 | H299: 45569 | I299: 98.8555 | J299: 100 | K299: 3912735.9 | L299: 3931716.6 | M299: 18980.75 | N299: 0 | P299: 60.00% of Global Commitment | Q299: Accrued Interest | R299: 50843.02 | S299: 0 | T299: 46379
A300: Long Positions | B300: U.S. Dollars | C300: Bank Debt | D300: BDC 5908.PP1 | E300: United Land Services Intermediate Parent Holdings, .DDTL | F300: 2634304.2 | G300: 321899503 | H300: 45618 | I300: 98.6676 | J300: 100 | K300: 2618391.2 | L300: 2634304.2 | M300: 15912.98 | N300: 0 | P300: 60.00% of Global Commitment | Q300: Accrued Interest | R300: 34065.52 | S300: 0 | T300: 46379
A301: Long Positions | B301: U.S. Dollars | C301: Bank Debt | D301: BDC 5908.PP2 | E301: United Land Services Intermediate Parent Holdings, .DDTL | F301: 902803.28 | G301: 326338430 | H301: 45649 | I301: 98.5047 | J301: 100 | K301: 896483.03 | L301: 902803.28 | M301: 6320.25 | N301: 0 | P301: 60.00% of Global Commitment | Q301: Accrued Interest | R301: 11674.61 | S301: 0 | T301: 46379
A302: Long Positions | B302: U.S. Dollars | C302: Bank Debt | D302: BDC 5908.PP3 | E302: United Land Services Intermediate Parent Holdings, .DDTL | F302: 225449.83 | G302: 328561929 | H302: 45673 | I302: 98.5429 | J302: 100 | K302: 223843.73 | L302: 225449.83 | M302: 1606.1 | N302: 0 | P302: 60.00% of Global Commitment | Q302: Accrued Interest | R302: 2915.41 | S302: 0 | T302: 46379
A303: Long Positions | B303: U.S. Dollars | C303: Bank Debt | D303: BDC 5908.PP4 | E303: United Land Services Intermediate Parent Holdings, .DDTL | F303: 2541000 | G303: 360688120 | H303: 46010 | I303: 98.5 | J303: 100 | K303: 2507509.4 | L303: 2541000 | M303: 33490.65 | N303: 0 | P303: 60.00% of Global Commitment | Q303: Accrued Interest | R303: 32858.96 | S303: 0 | T303: 46379
A304: Long Positions | B304: U.S. Dollars | C304: Bank Debt | D304: BDC 6142A | E304: Harris & Co. LLC. - Unfunded DDTL B | F304: 510728.8 | G304: 314379990 | H304: 45534 | I304: 99.125 | J304: 99.25 | K304: 506259.92 | L304: 506898.33 | M304: 638.41 | N304: 0 | O304: S+5% , 1.00 Floor | Q304: Accrued Interest | R304: 453.98 | S304: 1 | T304: 46062
A305: Long Positions | B305: U.S. Dollars | C305: Bank Debt | D305: BDC 6219 | E305: NFS - CFP Holdings LLC - DDTL Unfunded | F305: 4756394 | G305: 316462811 | H305: 45558 | I305: 99.25 | J305: 100 | K305: 4720721.1 | L305: 4756394 | M305: 35672.96 | N305: 0 | O305: S + 4.75%, 1.00% Floor | Q305: Accrued Interest | R305: 4227.91 | S305: 1 | T305: 46288
A306: Long Positions | B306: U.S. Dollars | C306: Bank Debt | D306: BDC 6577 | E306: CJX Borrower , LLC. DDTL Unfunded | F306: 74565.82 | G306: 318694597 | H306: 45574 | I306: 81.5 | J306: 100 | K306: 60771.15 | L306: 74565.82 | M306: 13794.67 | N306: 0 | S306: 0 | T306: 46581
A307: Long Positions | B307: U.S. Dollars | C307: Bank Debt | D307: BDC 6901 | E307: Infinity Home Services Holdco, Inc. - Amendment No. 3 CAD/USD Unfunded DDTL | F307: 9090909.1 | G307: 319850723 | H307: 45589 | I307: 99.5 | J307: 100 | K307: 9045454.6 | L307: 9090909.1 | M307: 45454.55 | N307: 0 | Q307: Accrued Interest | R307: 8080.81 | S307: 1 | T307: 47115
A308: Long Positions | B308: U.S. Dollars | C308: Bank Debt | D308: BDC 7268 | E308: DUGGAL ACQUISITION, LLC - DDTL Unfunded | F308: 2042488.6 | G308: 317554455 | H308: 45565 | I308: 99 | J308: 100 | K308: 2022063.7 | L308: 2042488.6 | M308: 20424.89 | N308: 0 | O308: S + 5.00%, 1.00% Floor | Q308: Accrued Interest | R308: 1758.81 | S308: 1 | T308: 46295
A309: Long Positions | B309: U.S. Dollars | C309: Bank Debt | D309: BDC 7329 | E309: Seacoast Service Partners, LLC - DDTL Unfunded | F309: 2615265.9 | G309: 326064852 | H309: 45646 | I309: 99.125 | J309: 95.4 | K309: 2592382.3 | L309: 2494963.7 | M309: -97418.66 | N309: 0 | O309: Unfunded expires in 24mo | Q309: Accrued Interest | R309: 2324.68 | S309: 1 | T309: 46376
A310: Long Positions | B310: U.S. Dollars | C310: Bank Debt | D310: BDC 7329.PP | E310: Seacoast Service Partners, LLC - DDTL | F310: 845191.42 | G310: 333707854 | H310: 45733 | I310: 99.125 | J310: 95.4 | K310: 838876.74 | L310: 806312.61 | M310: -32564.13 | N310: 0 | P310: 27.34% of Global Commitment | Q310: Accrued Interest | R310: 6702.89 | S310: 0 | T310: 47472
A311: Long Positions | B311: U.S. Dollars | C311: Bank Debt | D311: BDC 7329.PP1 | E311: Seacoast Service Partners, LLC - DDTL | F311: 831186.24 | G311: 337452815 | H311: 45757 | I311: 99.125 | J311: 95.4 | K311: 824840.72 | L311: 792951.67 | M311: -31889.05 | N311: 0 | P311: 27.10% of Global Commitment | Q311: Accrued Interest | R311: 6591.82 | S311: 0 | T311: 47472
A312: Long Positions | B312: U.S. Dollars | C312: Bank Debt | D312: BDC 7329.PP2 | E312: Seacoast Service Partners, LLC - DDTL | F312: 119987.37 | G312: 340768046 | H312: 45807 | I312: 99.125 | J312: 95.4 | K312: 119051.12 | L312: 114467.95 | M312: -4583.17 | N312: 0 | P312: 27.10% of Global Commitment | Q312: Accrued Interest | R312: 951.57 | S312: 0 | T312: 47472
A313: Long Positions | B313: U.S. Dollars | C313: Bank Debt | D313: BDC 7329.PP3 | E313: Seacoast Service Partners, LLC - DDTL | F313: 148691.09 | G313: 356234715 | H313: 45964 | I313: 99.125 | J313: 95.4 | K313: 147463.23 | L313: 141851.3 | M313: -5611.93 | N313: 0 | P313: 27.10% of Global Commitment | Q313: Accrued Interest | R313: 1179.21 | S313: 0 | T313: 47472
...

Sheet Rec-Pay-Month End
B3: 1 | C3: Run rec/pay
B4: 2 | C4: Run pur/sale
B5: 3 | C5: Add column K and formula
B6: 4 | C6: Sort by K
B7: 5 | C7: Add non-cash and transfer Broker
A14: Financial_Account | B14: Investment | C14: Investment_Desc | D14: Sec_ID | E14: Hold_ID | F14: Trade_Date | G14: Contractual_Settle_Date | H14: Actual_Settle_Date | I14: Tran_ID | J14: Tran_Description | L14: Local_Amount | M14: Book_Amount | N14: Fund_Legal_Entity | O14: Fund_Structure_Code | P14: Period_End_Date | Q14: Custodian | R14: CustodianAcct | S14: Units | T14: Price | U14: Relieved_IDs | V14: Relieved_Prices
A16: Receivable | B16: USD | C16: Aphix Buyer, Inc - DDTL A | D16: 8993.PP | F16: 46052 | G16: 46052 | H16: 46052 | I16: 365553948 | J16: AccountingRelated | L16: 381224.15 | M16: 381224.15 | N16: NN00-PP | O16: NN00-PP | P16: 46053 | Q16: BNYM | R16: NN_7100PP002 | T16: 100 | U16: 364901759 | V16: 100
A17: Receivable | B17: USD | C17: Aphix Buyer, Inc - Term Loan A | D17: 8979.PP | F17: 46052 | G17: 46052 | H17: 46052 | I17: 365553949 | J17: AccountingRelated | L17: 5747694.8 | M17: 5747694.8 | N17: NN00-PP | O17: NN00-PP | P17: 46053 | Q17: BNYM | R17: NN_7100PP002 | T17: 100 | U17: 364901769 | V17: 100
A18: Receivable | B18: USD | C18: BLC Holding Company, Inc. DDTL | D18: 7048.PP | F18: 46052 | G18: 46052 | H18: 46052 | I18: 365553950 | J18: AccountingRelated | L18: 2242811.9 | M18: 2242811.9 | N18: NN00-PP | O18: NN00-PP | P18: 46053 | Q18: BNYM | R18: NN_7100PP002 | T18: 100 | U18: 364901778 | V18: 100
A19: Receivable | B19: USD | C19: Cartessa Aesthetics, LLC - Term Loan | D19: LX206028.PP | F19: 46052 | G19: 46052 | H19: 46052 | I19: 365553952 | J19: AccountingRelated | L19: 7500000 | M19: 7500000 | N19: NN00-PP | O19: NN00-PP | P19: 46053 | Q19: BNYM | R19: NN_7100PP002 | T19: 100 | U19: 364901785 | V19: 100
A20: Receivable | B20: USD | C20: Halo Buyer, INC. - Refinanced Term Loan | D20: 7818.PP | F20: 46052 | G20: 46052 | H20: 46052 | I20: 365553953 | J20: AccountingRelated | L20: 7500000 | M20: 7500000 | N20: NN00-PP | O20: NN00-PP | P20: 46053 | Q20: BNYM | R20: NN_7100PP002 | T20: 100 | U20: 364901787 | V20: 100
A21: Receivable | B21: USD | C21: Harris & Co. LLC - DDTL B | D21: 6142.PP3 | F21: 46052 | G21: 46052 | H21: 46052 | I21: 365553954 | J21: AccountingRelated | L21: 5210471.2 | M21: 5210471.2 | N21: NN00-PP | O21: NN00-PP | P21: 46053 | Q21: BNYM | R21: NN_7100PP002 | T21: 99.25 | U21: 364901795 | V21: 99.25
A22: Receivable | B22: USD | C22: Highwire Public Relations, LLC Term Loan | D22: 9018.PP | F22: 46052 | G22: 46052 | H22: 46052 | I22: 365553956 | J22: AccountingRelated | L22: 2484375 | M22: 2484375 | N22: NN00-PP | O22: NN00-PP | P22: 46053 | Q22: BNYM | R22: NN_7100PP002 | T22: 99.375 | U22: 364901805 | V22: 99.375
A23: Receivable | B23: USD | C23: Loving Tan Intermediate II, Inc. - Term Loan | D23: LX213391.PP | F23: 46052 | G23: 46052 | H23: 46052 | I23: 365553997 | J23: AccountingRelated | L23: 4656663.9 | M23: 4656663.9 | N23: NN00-PP | O23: NN00-PP | P23: 46053 | Q23: BNYM | R23: NN_7100PP002 | T23: 99.5 | U23: 364901811 | V23: 99.5
A24: Receivable | B24: USD | C24: Loving Tan Intermediate II, Inc. - DDTL | D24: 2221.PP | F24: 46052 | G24: 46052 | H24: 46052 | I24: 365554014 | J24: AccountingRelated | L24: 2327965.9 | M24: 2327965.9 | N24: NN00-PP | O24: NN00-PP | P24: 46053 | Q24: BNYM | R24: NN_7100PP002 | T24: 99.5 | U24: 364901819 | V24: 99.5
A25: Receivable | B25: USD | C25: Loving Tan Intermediate II, Inc. - DDTL | D25: 2221.PP1 | F25: 46052 | G25: 46052 | H25: 46052 | I25: 365554028 | J25: AccountingRelated | L25: 477870.03 | M25: 477870.03 | N25: NN00-PP | O25: NN00-PP | P25: 46053 | Q25: BNYM | R25: NN_7100PP002 | T25: 99.5 | U25: 364901827 | V25: 99.5
A26: Receivable | B26: USD | C26: Marketplace Events Acquisition, LLC - DDTL | D26: 7138.PP | F26: 46052 | G26: 46052 | H26: 46052 | I26: 365554031 | J26: AccountingRelated | L26: 864328.55 | M26: 864328.55 | N26: NN00-PP | O26: NN00-PP | P26: 46053 | Q26: BNYM | R26: NN_7100PP002 | T26: 100 | U26: 364901887 | V26: 100
A27: Receivable | B27: USD | C27: Marketplace Events Acquisition, LLC - DDTL | D27: 7138.PP1 | F27: 46052 | G27: 46052 | H27: 46052 | I27: 365554033 | J27: AccountingRelated | L27: 369190.21 | M27: 369190.21 | N27: NN00-PP | O27: NN00-PP | P27: 46053 | Q27: BNYM | R27: NN_7100PP002 | T27: 100 | U27: 364902009 | V27: 100
... A46: Receivable | B46: USD | C46: The Vertex Companies, LLC - Term Loan B | D46: 3584.PP | F46: 46052 | G46: 46052 | H46: 46052 | I46: 365554177 | J46: AccountingRelated | L46: 180219.99 | M46: 180219.99 | N46: NN00-PP | O46: NN00-PP | P46: 46053 | Q46: BNYM | R46: NN_7100PP002 | T46: 99.4 | U46: 364902366 | V46: 99.4
M49: =SUM(M16:M46) -> 73832136
A58: Payable | B58: USD | C58: Beta Plus Technologies,Inc.- Term Loan | D58: LX206113.PP | F58: 46024 | G58: 46081 | H58: 46081 | I58: 364011657 | J58: Buy | L58: -4900000 | M58: -4900000 | N58: NN00-PP | O58: NN00-PP | P58: 46048 | Q58: BNYM | R58: NN_7100PP002 | S58: 5000000 | T58: 98
M59: =SUM(M51:M58) -> -4900000
M69: =SUM(M63:M68) -> 0
L78: SHOULD BE 0 | M78: =M49+M69 -> 73832136

Sheet SBICII post TB (closed)

Sheet PNNT SPV post TB

Sheet SBIC post TB(Closed)
B4: =IF(C4="PennantPark SBIC, L.L.P."," ","Not SBIC") -> Not SBIC
B10: =CONCATENATE(E10,F10)
B11: =CONCATENATE(E11,F11)
A12: =VLOOKUP(B12,Summary!A:A,1,FALSE) | B12: =CONCATENATE(E12,F12)
A13: =VLOOKUP(B13,Summary!A:A,1,FALSE) | B13: =CONCATENATE(E13,F13)
A14: =VLOOKUP(B14,Summary!A:A,1,FALSE) | B14: =CONCATENATE(E14,F14)
A15: =VLOOKUP(B15,Summary!A:A,1,FALSE) | B15: =CONCATENATE(E15,F15)
A16: =VLOOKUP(B16,Summary!A:A,1,FALSE) | B16: =CONCATENATE(E16,F16)
A17: =VLOOKUP(B17,Summary!A:A,1,FALSE) | B17: =CONCATENATE(E17,F17)
A18: =VLOOKUP(B18,Summary!A:A,1,FALSE) | B18: =CONCATENATE(E18,F18)
A19: =VLOOKUP(B19,Summary!A:A,1,FALSE) | B19: =CONCATENATE(E19,F19)
A20: =VLOOKUP(B20,Summary!A:A,1,FALSE) | B20: =CONCATENATE(E20,F20)
A21: =VLOOKUP(B21,Summary!A:A,1,FALSE) | B21: =CONCATENATE(E21,F21)
A22: =VLOOKUP(B22,Summary!A:A,1,FALSE) | B22: =CONCATENATE(E22,F22)
A23: =VLOOKUP(B23,Summary!A:A,1,FALSE) | B23: =CONCATENATE(E23,F23)
... A70: =VLOOKUP(B70,Summary!A:A,1,FALSE) | B70: =CONCATENATE(E70,F70)
