Workbook
Name IQ_CH: 110000
Name IQ_CQ: 5000
Name IQ_CY: 10000
Name IQ_DAILY: 500000
Name IQ_FH: 100000
Name IQ_FQ: 500
Name IQ_FY: 1000
Name IQ_LTM: 2000
Name IQ_MONTH: 15000
Name IQ_NTM: 6000
Name IQ_WEEK: 50000
Name IQ_YTD: 3000

Sheet Master Ratings
B2: Last Updated | D2: 45785
B4: *Match family name in master comps file
D5: Ratings Data (Borrower)
B6: Borrower Name | D6: Moody's | G6: S&P | L6: Fitch | O6: Date Estimates
B7: Master Comps | D7: Rating | E7: Rating Type | G7: Rating | H7: Rating Type | I7: Recovery Rating | J7: Recovery % | L7: Rating | M7: Rating Type | O7: S&P | P7: Fitch
B9: 48Forty | G9: CCC+** | H9: Rating (Private) | O9: 45737
B10: 4Wall Entertainment | G10: CCC-* | H10: Credit Estimate | L10: B- | M10: Rating (Private) | O10: 45709 | P10: 45345
B11: A1 Garage | G11: B-* | H11: Credit Estimate | O11: 45657
B12: Ad.net | G12: B-* | H12: Credit Estimate | L12: B-* | M12: Credit Estimate | O12: 45750 | P12: 45107
B13: Advantage Sales & Marketing | D13: B2 | E13: Rating (Public) | G13: B+ | H13: Rating (Public)
B14: Aechelon | G14: B* | H14: Credit Estimate | O14: 45679
B15: Aeronix | G15: B-* | H15: Credit Estimate | O15: 45629
B16: AFC | G16: B-* | H16: Rating (Private) | O16: 45616
B17: alphabroder | G17: B* | H17: Rating (Private) | L17: B+* | M17: Credit Estimate | O17: 45481 | P17: 45275
B18: Altamira | G18: B-* | H18: Credit Estimate | O18: 45106
B19: American Insulated Glass | G19: B-* | H19: Credit Estimate | L19: B-* | M19: Credit Estimate | O19: 44825 | P19: 44886
B20: Ankura | D20: B3 | E20: Rating (Public) | G20: B- | H20: Rating (Public)
B21: Any Hour Services | G21: B-* | H21: Credit Estimate | L21: B-* | M21: Credit Estimate | O21: 45447 | P21: 45050
B22: Apex Service Partners | G22: B-* | H22: Credit Estimate | L22: B- | M22: Rating (Private) | O22: 45077 | P22: 44886
B23: API Technologies | D23: B3 | E23: Rating (Public) | G23: CCC+ | H23: Rating (Public)
B24: Applied Technical Services | G24: B-* | H24: Rating (Private) | L24: B* | M24: Credit Estimate | O24: 45660 | P24: 45359
B25: Arcfield | G25: B-* | H25: Credit Estimate | L25: B | M25: Rating (Private) | O25: 45684 | P25: 45198
B26: Archer Lewis | G26: B-* | H26: Credit Estimate | O26: 45729
B27: Ardurra | G27: B-* | H27: Credit Estimate | O27: 45657
B28: Aretec (Cetera) | D28: B2 | E28: Rating (Public) | G28: B | H28: Rating (Public)
B29: Argano | G29: B-** | H29: Credit Estimate | O29: 45775
B30: Ascensus | D30: B3 | E30: Rating (Public) | G30: B- | H30: Rating (Public)
B31: Avenu | G31: B-* | H31: Credit Estimate | L31: B* | M31: Credit Estimate | O31: 45649 | P31: 45310
B32: BBB Industries | D32: B3 | E32: Rating (Public) | G32: B- | H32: Rating (Public)
B33: Beacon Behavioral | G33: B-* | H33: Credit Estimate | O33: 45664
B34: Berlin Packaging | D34: B3 | E34: Rating (Public) | G34: B- | H34: Rating (Public)
B35: Beta+ | D35: B2 | E35: Rating (Public) | G35: B- | H35: Rating (Public)
B36: Big Top | G36: B-* | H36: Credit Estimate | O36: 45693
B37: BiggerPockets | G37: B-* | H37: Credit Estimate | O37: 45660
B38: Bioderm | G38: B-* | H38: Credit Estimate | O38: 45420
B39: Blackhawk Industrial | G39: B-* | H39: Credit Estimate | O39: 45623
B40: Bland Landscaping | G40: B-* | H40: Credit Estimate | O40: 45698
B41: BlueBird | G41: B-* | H41: Credit Estimate | L41: B-* | M41: Credit Estimate | O41: 45670 | P41: 45093
B42: BlueHalo | G42: B-* | H42: Rating (Private) | L42: B-* | M42: Credit Estimate | O42: 45684 | P42: 1.19.2024
B43: Boss Industries | G43: B-* | H43: Credit Estimate | O43: 45702
B44: Bottom Line Systems | G44: B-* | H44: Credit Estimate | O44: 44601
B45: By Light | G45: B-* | H45: Rating (Private) | L45: B-* | M45: Credit Estimate | O45: 45587 | P45: 45275
B46: C5MI | G46: B-* | H46: Credit Estimate | O46: 45679
B47: Cadence Aerospace | G47: B-* | H47: Credit Estimate | L47: B-* | M47: Credit Estimate | O47: 43846 | P47: 43816
B48: Cano Health | D48: B3 | E48: Rating (Public) | G48: B | H48: Rating (Public) | I48: 3 | J48: 0.65
B49: Carisk | G49: B-* | H49: Credit Estimate | O49: 45701
B50: Carnegie Dartlet | G50: B-* | H50: Credit Estimate | O50: 45702
B51: Cartessa | G51: B-* | H51: Credit Estimate | L51: B-* | M51: Credit Estimate | O51: 45750 | P51: 45107
B52: Case Works | G52: B-* | H52: Credit Estimate | O52: 45663
B53: Centauri Health | G53: B-* | H53: Credit Estimate | L53: B* | M53: Credit Estimate | O53: 45693 | P53: 45121
B54: CHA Consulting | G54: B-* | H54: Credit Estimate | L54: B* | M54: Credit Estimate | O54: 45352 | P54: 12.8.2023
B55: Challenger | G55: B-* | H55: Credit Estimate | L55: B-* | M55: Credit Estimate | O55: 43846 | P55: 43837
B56: Circa | D56: Caa1 | E56: Rating (Public) | G56: B- | H56: Rating (Public) | I56: 3 | J56: 0.65
B57: Commercial Fire Protection | G57: B-* | H57: Credit Estimate | O57: 45667
B58: Compex Legal | G58: B-* | H58: Credit Estimate | O58: 45623
B59: Confluent Health | D59: B3 | E59: Rating (Public) | G59: B- | H59: Rating (Public) | I59: 4 | J59: 0.45
B60: Connatix | G60: B-* | H60: Credit Estimate | L60: B-* | M60: Credit Estimate | O60: 45483 | P60: 12.8.2023
B61: Consilio | D61: B3 | E61: Rating (Public) | G61: B- | H61: Rating (Public)
B62: CoolSys | D62: Caa1 | E62: Rating (Public) | G62: CCC+ | H62: Rating (Public)
B63: Convergint | G63: B- | H63: Rating (Public) | I63: 3 | J63: 0.65
B64: Crane 1 | G64: B-* | H64: Credit Estimate | L64: B-* | M64: Credit Estimate | O64: 45707 | P64: 45345
B65: Crash Champions | G65: CCC+* | H65: Credit Estimate | L65: B* | M65: Credit Estimate | O65: 44616 | P65: 44498
B66: Digital Room | D66: B3 | E66: Rating (Public) | G66: B- | H66: Rating (Public) | I66: 3 | J66: 0.65
B67: Douglas | G67: B-* | H67: Credit Estimate | L67: B* | M67: Credit Estimate | O67: 44925 | P67: 44482
B68: Dr. Scholl's | G68: B-* | H68: Rating (Private) | L68: B* | M68: Credit Estimate | O68: 45623 | P68: 45398
B69: Dr. Squatch | G69: B-* | H69: Credit Estimate | L69: B* | M69: Credit Estimate | O69: 45660 | P69: 45324
B70: Duggal | G70: B-* | H70: Credit Estimate | O70: 45695
B71: The Duraco Group | G71: B-* | H71: Credit Estimate | L71: B-* | M71: Credit Estimate | O71: 45016 | P71: 45198
B72: ECL Entertainment | D72: B2 | E72: Rating (Public) | G72: B- | H72: Rating (Public)
B73: ECM Industries | G73: B-* | H73: Credit Estimate | O73: 44995
B74: eCommission | G74: B* | H74: Credit Estimate | L74: B-* | M74: Credit Estimate | O74: 44761 | P74: 44960
B75: ECRM | G75: CCC* | H75: Credit Estimate | L75: B-* | M75: Credit Estimate | O75: 44762 | P75: 44533
B76: Emergency Care Partners | G76: B-* | H76: Credit Estimate | O76: 45708
B77: Empire Resorts | D77: Baa2 | E77: Rating (Public) | G77: BBB | H77: Rating (Public)
B78: Engine and Transmission Exchange | G78: B-* | H78: Credit Estimate | O78: 45626
B79: Epiq | G79: B-* | H79: Credit Estimate | O79: 45657
B80: EvAl | G80: B-* | H80: Credit Estimate | O80: 45684
B81: Exigo | G81: B-* | H81: Credit Estimate | O81: 45513
B82: Fairbanks Morse Defense | D82: B3 | E82: Rating (Public) | G82: B | H82: Rating (Public)
B83: Fantasy Springs | D83: B2 | E83: Rating (Private) | G83: B- | H83: Rating (Private) | I83: NA | J83: NA | L83: B* | M83: Credit Estimate | P83: 44498
B84: Federal Advisory Partners | G84: B-* | H84: Credit Estimate | O84: 45679
B85: Five Star | G85: B-* | H85: Credit Estimate | L85: B* | M85: Credit Estimate | O85: 45727 | P85: 45355
B86: FlexPrint | G86: B-* | H86: Credit Estimate | O86: 44659
B87: GCOM | G87: B-* | H87: Credit Estimate | L87: B-* | M87: Credit Estimate | O87: 45026 | P87: 45107
B88: Gen3 Marketing | G88: B-* | H88: Credit Estimate | L88: B-* | M88: Credit Estimate | O88: 45667 | P88: 1.19.2024
B89: Global | G89: B-* | H89: Credit Estimate | L89: B* | M89: Credit Estimate | O89: 45743 | P89: 45398
B90: Guild Garage | G90: B-* | H90: Credit Estimate | O90: 45708
B91: Hancock | G91: B-* | H91: Credit Estimate | L91: CCC+* | M91: Credit Estimate | O91: 45778 | P91: 45324
B92: Hanley Wood | G92: B-* | H92: Credit Estimate | L92: B* | M92: Credit Estimate | O92: 45680 | P92: 45418
B93: Harris & Co. | G93: B-* | H93: Credit Estimate | O93: 45702
B94: Health-E Commerce | G94: B-* | H94: Credit Estimate | O94: 45645
B95: IDC Infusion Services | G95: B-* | H95: Credit Estimate | L95: B-* | M95: Credit Estimate | O95: 45064 | P95: 45040
B96: Idera | G96: B- | H96: Rating (Public)
B97: IDS | G97: B-* | H97: Credit Estimate | O97: 45657
B98: Imagine Software | G98: B-* | H98: Credit Estimate | O98: 45785
B99: IMIA Holdings, Inc. | G99: B* | H99: Credit Estimate | L99: B* | M99: Credit Estimate | O99: 44370 | P99: 44328
B100: Infinity Home Services | G100: B-* | H100: Credit Estimate | L100: B* | M100: Credit Estimate | O100: 45712 | P100: 1.26.2024
B101: Infolinks | G101: B* | H101: Credit Estimate | O101: 45630
B102: Infosoft | G102: B-* | H102: Credit Estimate | L102: B-* | M102: Credit Estimate | O102: 44900 | P102: 44900
B103: Insight Global | G103: B-* | H103: Rating (Private) | L103: B | M103: Rating (Private) | O103: 45573 | P103: 45121
...

Sheet Ratings by CLO
W1: Credit Estimate
W2: Rating (Private)
B3: CLO | J3: Credit | L3: Moody's | O3: S&P | S3: Fitch | W3: Days Left | Z3: Checks | AG3: Checks | AM3: Checks
B4: PFLT | C4: PSSL | D4: PTSF | E4: PSLF | F4: PTSF II | G4: PSSL (2) | H4: PSLF (2) | L4: Rating | M4: Type | O4: Rating | P4: Type | Q4: Date | S4: Rating | T4: Type | U4: Date | W4: S&P | X4: Fitch | Z4: S&P New | AA4: Fitch New | AB4: S&P Update | AC4: Fitch Update | AE4: NOT NEEDED | AG4: S&P New | AH4: Fitch New | AI4: S&P Update | AJ4: Fitch Update | AM4: S&P New | AN4: Fitch New | AO4: S&P Update | AP4: Fitch Update
B5: =+COUNTIFS(SOIs!$D:$D, 'Ratings by CLO'!$J5) -> 2 | C5: =+COUNTIFS(SOIs!$G:$G, 'Ratings by CLO'!$J5) -> 1 | D5: =+COUNTIFS(SOIs!$J:$J, 'Ratings by CLO'!$J5) -> 1 | E5: =+COUNTIFS(SOIs!$M:$M, 'Ratings by CLO'!$J5) -> 2 | F5: =+COUNTIFS(SOIs!$P:$P, 'Ratings by CLO'!$J5) -> 1 | G5: =+COUNTIFS(SOIs!$S:$S, 'Ratings by CLO'!$J5) -> 1 | H5: =+COUNTIFS(SOIs!$V:$V, 'Ratings by CLO'!$J5) -> 1 | J5: =+SOIs!X6 -> 48Forty | L5: =+IF(INDEX('Master Ratings'!$D:$D, MATCH('Ratings by CLO'!$J5,'Master Ratings'!$B:$B,0),0)=0,"",INDEX('Master Ratings'!$D:$D, MATCH('Ratings by CLO'!$J5,'Master Ratings'!$B:$B,0),0)) | M5: =+IF(INDEX('Master Ratings'!$E:$E, MATCH('Ratings by CLO'!$J5,'Master Ratings'!$B:$B,0),0)=0,"",INDEX('Master Ratings'!$E:$E, MATCH('Ratings by CLO'!$J5,'Master Ratings'!$B:$B,0),0)) | O5: =+IF(INDEX('Master Ratings'!$G:$G, MATCH('Ratings by CLO'!$J5,'Master Ratings'!$B:$B,0),0)=0,"",INDEX('Master Ratings'!$G:$G, MATCH('Ratings by CLO'!$J5,'Master Ratings'!$B:$B,0),0)) -> CCC+** | P5: =+IF(INDEX('Master Ratings'!$H:$H, MATCH('Ratings by CLO'!$J5,'Master Ratings'!$B:$B,0),0)=0,"",INDEX('Master Ratings'!$H:$H, MATCH('Ratings by CLO'!$J5,'Master Ratings'!$B:$B,0),0)) -> Rating (Private) | Q5: =+IF(INDEX('Master Ratings'!$O:$O, MATCH('Ratings by CLO'!$J5,'Master Ratings'!$B:$B,0),0)=0,"",INDEX('Master Ratings'!$O:$O, MATCH('Ratings by CLO'!$J5,'Master Ratings'!$B:$B,0),0)) -> 45737 | S5: =+IF(INDEX('Master Ratings'!$L:$L, MATCH('Ratings by CLO'!$J5,'Master Ratings'!$B:$B,0),0)=0,"",INDEX('Master Ratings'!$L:$L, MATCH('Ratings by CLO'!$J5,'Master Ratings'!$B:$B,0),0)) | T5: =+IF(INDEX('Master Ratings'!$M:$M, MATCH('Ratings by CLO'!$J5,'Master Ratings'!$B:$B,0),0)=0,"",INDEX('Master Ratings'!$M:$M, MATCH('Ratings by CLO'!$J5,'Master Ratings'!$B:$B,0),0)) | U5: =+IF(INDEX('Master Ratings'!$P:$P, MATCH('Ratings by CLO'!$J5,'Master Ratings'!$B:$B,0),0)=0,"",INDEX('Master Ratings'!$P:$P, MATCH('Ratings by CLO'!$J5,'Master Ratings'!$B:$B,0),0)) | W5: =+IF(OR($P5=$W$1,$P5=$W$2),$Q5+365-TODAY(), "") -> 138 | X5: =+IF(OR($T5=$W$1,$T5=$W$2),$U5+365-TODAY(), "") | Z5: =IF(AND(SUM(B5:H5)>=1,ISERROR(W5)),"X","") | AA5: =IF(AND(B5>=1, ISERROR(X5)),"X","") | AB5: =+IFERROR(IF(W5<0,"X",""),"") | AC5: =+IFERROR(IF(AND(B5>0, X5<0),"X",""),"") | AE5: =+IF(SUM(B5:H5)=0,"X","") | AG5: =IF(Z5="X",AG2+1,AG2) -> 0 | AH5: =IF(AA5="X",AH2+1,AH2) -> 0 | AI5: =IF(AB5="X",AI2+1,AI2) -> 0 | AJ5: =IF(AC5="X",AJ2+1,AJ2) -> 0 | AL5: 1 | AM5: =INDEX($J:$J, MATCH($AL5,AG:AG,0),0) -> Edelman | AN5: =INDEX($J:$J, MATCH($AL5,AH:AH,0),0) -> BlueHalo | AO5: =INDEX($J:$J, MATCH($AL5,AI:AI,0),0) -> alphabroder | AP5: =INDEX($J:$J, MATCH($AL5,AJ:AJ,0),0) -> 4Wall Entertainment
B6: =+COUNTIFS(SOIs!$D:$D, 'Ratings by CLO'!$J6) -> 3 | C6: =+COUNTIFS(SOIs!$G:$G, 'Ratings by CLO'!$J6) -> 1 | D6: =+COUNTIFS(SOIs!$J:$J, 'Ratings by CLO'!$J6) -> 0 | E6: =+COUNTIFS(SOIs!$M:$M, 'Ratings by CLO'!$J6) -> 0 | F6: =+COUNTIFS(SOIs!$P:$P, 'Ratings by CLO'!$J6) -> 0 | G6: =+COUNTIFS(SOIs!$S:$S, 'Ratings by CLO'!$J6) -> 1 | H6: =+COUNTIFS(SOIs!$V:$V, 'Ratings by CLO'!$J6) -> 1 | J6: =+SOIs!X7 -> 4Wall Entertainment | L6: =+IF(INDEX('Master Ratings'!$D:$D, MATCH('Ratings by CLO'!$J6,'Master Ratings'!$B:$B,0),0)=0,"",INDEX('Master Ratings'!$D:$D, MATCH('Ratings by CLO'!$J6,'Master Ratings'!$B:$B,0),0)) | M6: =+IF(INDEX('Master Ratings'!$E:$E, MATCH('Ratings by CLO'!$J6,'Master Ratings'!$B:$B,0),0)=0,"",INDEX('Master Ratings'!$E:$E, MATCH('Ratings by CLO'!$J6,'Master Ratings'!$B:$B,0),0)) | O6: =+IF(INDEX('Master Ratings'!$G:$G, MATCH('Ratings by CLO'!$J6,'Master Ratings'!$B:$B,0),0)=0,"",INDEX('Master Ratings'!$G:$G, MATCH('Ratings by CLO'!$J6,'Master Ratings'!$B:$B,0),0)) -> CCC-* | P6: =+IF(INDEX('Master Ratings'!$H:$H, MATCH('Ratings by CLO'!$J6,'Master Ratings'!$B:$B,0),0)=0,"",INDEX('Master Ratings'!$H:$H, MATCH('Ratings by CLO'!$J6,'Master Ratings'!$B:$B,0),0)) -> Credit Estimate | Q6: =+IF(INDEX('Master Ratings'!$O:$O, MATCH('Ratings by CLO'!$J6,'Master Ratings'!$B:$B,0),0)=0,"",INDEX('Master Ratings'!$O:$O, MATCH('Ratings by CLO'!$J6,'Master Ratings'!$B:$B,0),0)) -> 45709 | S6: =+IF(INDEX('Master Ratings'!$L:$L, MATCH('Ratings by CLO'!$J6,'Master Ratings'!$B:$B,0),0)=0,"",INDEX('Master Ratings'!$L:$L, MATCH('Ratings by CLO'!$J6,'Master Ratings'!$B:$B,0),0)) -> B- | T6: =+IF(INDEX('Master Ratings'!$M:$M, MATCH('Ratings by CLO'!$J6,'Master Ratings'!$B:$B,0),0)=0,"",INDEX('Master Ratings'!$M:$M, MATCH('Ratings by CLO'!$J6,'Master Ratings'!$B:$B,0),0)) -> Rating (Private) | U6: =+IF(INDEX('Master Ratings'!$P:$P, MATCH('Ratings by CLO'!$J6,'Master Ratings'!$B:$B,0),0)=0,"",INDEX('Master Ratings'!$P:$P, MATCH('Ratings by CLO'!$J6,'Master Ratings'!$B:$B,0),0)) -> 45345 | W6: =+IF(OR($P6=$W$1,$P6=$W$2),$Q6+365-TODAY(), "") -> 110 | X6: =+IF(OR($T6=$W$1,$T6=$W$2),$U6+365-TODAY(), "") -> -254 | Z6: =IF(AND(SUM(B6:H6)>=1,ISERROR(W6)),"X","") | AA6: =IF(AND(B6>1, ISERROR(X6)),"X","") | AB6: =+IFERROR(IF(W6<0,"X",""),"") | AC6: =+IFERROR(IF(AND(B6>0, X6<0),"X",""),"") -> X | AE6: =+IF(SUM(B6:H6)=0,"X","") | AG6: =IF(Z6="X",AG5+1,AG5) -> 0 | AH6: =IF(AA6="X",AH5+1,AH5) -> 0 | AI6: =IF(AB6="X",AI5+1,AI5) -> 0 | AJ6: =IF(AC6="X",AJ5+1,AJ5) -> 1 | AL6: =AL5+1 -> 2 | AM6: =INDEX($J:$J, MATCH($AL6,AG:AG,0),0) -> Electro Rent | AN6: =INDEX($J:$J, MATCH($AL6,AH:AH,0),0) -> Connatix | AO6: =INDEX($J:$J, MATCH($AL6,AI:AI,0),0) -> American Insulated Glass | AP6: =INDEX($J:$J, MATCH($AL6,AJ:AJ,0),0) -> Ad.net
B7: =+COUNTIFS(SOIs!$D:$D, 'Ratings by CLO'!$J7) -> 0 | C7: =+COUNTIFS(SOIs!$G:$G, 'Ratings by CLO'!$J7) -> 0 | D7: =+COUNTIFS(SOIs!$J:$J, 'Ratings by CLO'!$J7) -> 0 | E7: =+COUNTIFS(SOIs!$M:$M, 'Ratings by CLO'!$J7) -> 0 | F7: =+COUNTIFS(SOIs!$P:$P, 'Ratings by CLO'!$J7) -> 0 | G7: =+COUNTIFS(SOIs!$S:$S, 'Ratings by CLO'!$J7) -> 1 | H7: =+COUNTIFS(SOIs!$V:$V, 'Ratings by CLO'!$J7) -> 1 | J7: =+SOIs!X8 -> A1 Garage | L7: =+IF(INDEX('Master Ratings'!$D:$D, MATCH('Ratings by CLO'!$J7,'Master Ratings'!$B:$B,0),0)=0,"",INDEX('Master Ratings'!$D:$D, MATCH('Ratings by CLO'!$J7,'Master Ratings'!$B:$B,0),0)) | M7: =+IF(INDEX('Master Ratings'!$E:$E, MATCH('Ratings by CLO'!$J7,'Master Ratings'!$B:$B,0),0)=0,"",INDEX('Master Ratings'!$E:$E, MATCH('Ratings by CLO'!$J7,'Master Ratings'!$B:$B,0),0)) | O7: =+IF(INDEX('Master Ratings'!$G:$G, MATCH('Ratings by CLO'!$J7,'Master Ratings'!$B:$B,0),0)=0,"",INDEX('Master Ratings'!$G:$G, MATCH('Ratings by CLO'!$J7,'Master Ratings'!$B:$B,0),0)) -> B-* | P7: =+IF(INDEX('Master Ratings'!$H:$H, MATCH('Ratings by CLO'!$J7,'Master Ratings'!$B:$B,0),0)=0,"",INDEX('Master Ratings'!$H:$H, MATCH('Ratings by CLO'!$J7,'Master Ratings'!$B:$B,0),0)) -> Credit Estimate | Q7: =+IF(INDEX('Master Ratings'!$O:$O, MATCH('Ratings by CLO'!$J7,'Master Ratings'!$B:$B,0),0)=0,"",INDEX('Master Ratings'!$O:$O, MATCH('Ratings by CLO'!$J7,'Master Ratings'!$B:$B,0),0)) -> 45657 | S7: =+IF(INDEX('Master Ratings'!$L:$L, MATCH('Ratings by CLO'!$J7,'Master Ratings'!$B:$B,0),0)=0,"",INDEX('Master Ratings'!$L:$L, MATCH('Ratings by CLO'!$J7,'Master Ratings'!$B:$B,0),0)) | T7: =+IF(INDEX('Master Ratings'!$M:$M, MATCH('Ratings by CLO'!$J7,'Master Ratings'!$B:$B,0),0)=0,"",INDEX('Master Ratings'!$M:$M, MATCH('Ratings by CLO'!$J7,'Master Ratings'!$B:$B,0),0)) | U7: =+IF(INDEX('Master Ratings'!$P:$P, MATCH('Ratings by CLO'!$J7,'Master Ratings'!$B:$B,0),0)=0,"",INDEX('Master Ratings'!$P:$P, MATCH('Ratings by CLO'!$J7,'Master Ratings'!$B:$B,0),0)) | W7: =+IF(OR($P7=$W$1,$P7=$W$2),$Q7+365-TODAY(), "") -> 58 | X7: =+IF(OR($T7=$W$1,$T7=$W$2),$U7+365-TODAY(), "") | Z7: =IF(AND(SUM(B7:H7)>=1,ISERROR(W7)),"X","") | AA7: =IF(AND(B7>1, ISERROR(X7)),"X","") | AB7: =+IFERROR(IF(W7<0,"X",""),"") | AC7: =+IFERROR(IF(AND(B7>0, X7<0),"X",""),"") | AE7: =+IF(SUM(B7:H7)=0,"X","") | AG7: =IF(Z7="X",AG6+1,AG6) -> 0 | AH7: =IF(AA7="X",AH6+1,AH6) -> 0 | AI7: =IF(AB7="X",AI6+1,AI6) -> 0 | AJ7: =IF(AC7="X",AJ6+1,AJ6) -> 1 | AL7: =AL6+1 -> 3 | AM7: =INDEX($J:$J, MATCH($AL7,AG:AG,0),0) -> Engine & Transmission Exchange | AN7: =INDEX($J:$J, MATCH($AL7,AH:AH,0),0) -> Gen3 Marketing | AO7: =INDEX($J:$J, MATCH($AL7,AI:AI,0),0) -> Any Hour Services | AP7: =INDEX($J:$J, MATCH($AL7,AJ:AJ,0),0) -> alphabroder
B8: =+COUNTIFS(SOIs!$D:$D, 'Ratings by CLO'!$J8) -> 4 | C8: =+COUNTIFS(SOIs!$G:$G, 'Ratings by CLO'!$J8) -> 1 | D8: =+COUNTIFS(SOIs!$J:$J, 'Ratings by CLO'!$J8) -> 1 | E8: =+COUNTIFS(SOIs!$M:$M, 'Ratings by CLO'!$J8) -> 1 | F8: =+COUNTIFS(SOIs!$P:$P, 'Ratings by CLO'!$J8) -> 0 | G8: =+COUNTIFS(SOIs!$S:$S, 'Ratings by CLO'!$J8) -> 1 | H8: =+COUNTIFS(SOIs!$V:$V, 'Ratings by CLO'!$J8) -> 0 | J8: =+SOIs!X9 -> Ad.net | L8: =+IF(INDEX('Master Ratings'!$D:$D, MATCH('Ratings by CLO'!$J8,'Master Ratings'!$B:$B,0),0)=0,"",INDEX('Master Ratings'!$D:$D, MATCH('Ratings by CLO'!$J8,'Master Ratings'!$B:$B,0),0)) | M8: =+IF(INDEX('Master Ratings'!$E:$E, MATCH('Ratings by CLO'!$J8,'Master Ratings'!$B:$B,0),0)=0,"",INDEX('Master Ratings'!$E:$E, MATCH('Ratings by CLO'!$J8,'Master Ratings'!$B:$B,0),0)) | O8: =+IF(INDEX('Master Ratings'!$G:$G, MATCH('Ratings by CLO'!$J8,'Master Ratings'!$B:$B,0),0)=0,"",INDEX('Master Ratings'!$G:$G, MATCH('Ratings by CLO'!$J8,'Master Ratings'!$B:$B,0),0)) -> B-* | P8: =+IF(INDEX('Master Ratings'!$H:$H, MATCH('Ratings by CLO'!$J8,'Master Ratings'!$B:$B,0),0)=0,"",INDEX('Master Ratings'!$H:$H, MATCH('Ratings by CLO'!$J8,'Master Ratings'!$B:$B,0),0)) -> Credit Estimate | Q8: =+IF(INDEX('Master Ratings'!$O:$O, MATCH('Ratings by CLO'!$J8,'Master Ratings'!$B:$B,0),0)=0,"",INDEX('Master Ratings'!$O:$O, MATCH('Ratings by CLO'!$J8,'Master Ratings'!$B:$B,0),0)) -> 45750 | S8: =+IF(INDEX('Master Ratings'!$L:$L, MATCH('Ratings by CLO'!$J8,'Master Ratings'!$B:$B,0),0)=0,"",INDEX('Master Ratings'!$L:$L, MATCH('Ratings by CLO'!$J8,'Master Ratings'!$B:$B,0),0)) -> B-* | T8: =+IF(INDEX('Master Ratings'!$M:$M, MATCH('Ratings by CLO'!$J8,'Master Ratings'!$B:$B,0),0)=0,"",INDEX('Master Ratings'!$M:$M, MATCH('Ratings by CLO'!$J8,'Master Ratings'!$B:$B,0),0)) -> Credit Estimate | U8: =+IF(INDEX('Master Ratings'!$P:$P, MATCH('Ratings by CLO'!$J8,'Master Ratings'!$B:$B,0),0)=0,"",INDEX('Master Ratings'!$P:$P, MATCH('Ratings by CLO'!$J8,'Master Ratings'!$B:$B,0),0)) -> 45107 | W8: =+IF(OR($P8=$W$1,$P8=$W$2),$Q8+365-TODAY(), "") -> 151 | X8: =+IF(OR($T8=$W$1,$T8=$W$2),$U8+365-TODAY(), "") -> -492 | Z8: =IF(AND(SUM(B8:H8)>=1,ISERROR(W8)),"X","") | AA8: =IF(AND(B8>1, ISERROR(X8)),"X","") | AB8: =+IFERROR(IF(W8<0,"X",""),"") | AC8: =+IFERROR(IF(AND(B8>0, X8<0),"X",""),"") -> X | AE8: =+IF(SUM(B8:H8)=0,"X","") | AG8: =IF(Z8="X",AG7+1,AG7) -> 0 | AH8: =IF(AA8="X",AH7+1,AH7) -> 0 | AI8: =IF(AB8="X",AI7+1,AI7) -> 0 | AJ8: =IF(AC8="X",AJ7+1,AJ7) -> 2 | AL8: =AL7+1 -> 4 | AM8: =INDEX($J:$J, MATCH($AL8,AG:AG,0),0) -> Hightower | AN8: =INDEX($J:$J, MATCH($AL8,AH:AH,0),0) -> MCR | AO8: =INDEX($J:$J, MATCH($AL8,AI:AI,0),0) -> Apex Service Partners | AP8: =INDEX($J:$J, MATCH($AL8,AJ:AJ,0),0) -> Any Hour Services
B9: =+COUNTIFS(SOIs!$D:$D, 'Ratings by CLO'!$J9) -> 4 | C9: =+COUNTIFS(SOIs!$G:$G, 'Ratings by CLO'!$J9) -> 1 | D9: =+COUNTIFS(SOIs!$J:$J, 'Ratings by CLO'!$J9) -> 1 | E9: =+COUNTIFS(SOIs!$M:$M, 'Ratings by CLO'!$J9) -> 0 | F9: =+COUNTIFS(SOIs!$P:$P, 'Ratings by CLO'!$J9) -> 1 | G9: =+COUNTIFS(SOIs!$S:$S, 'Ratings by CLO'!$J9) -> 0 | H9: =+COUNTIFS(SOIs!$V:$V, 'Ratings by CLO'!$J9) -> 1 | J9: =+SOIs!X10 -> alphabroder | L9: =+IF(INDEX('Master Ratings'!$D:$D, MATCH('Ratings by CLO'!$J9,'Master Ratings'!$B:$B,0),0)=0,"",INDEX('Master Ratings'!$D:$D, MATCH('Ratings by CLO'!$J9,'Master Ratings'!$B:$B,0),0)) | M9: =+IF(INDEX('Master Ratings'!$E:$E, MATCH('Ratings by CLO'!$J9,'Master Ratings'!$B:$B,0),0)=0,"",INDEX('Master Ratings'!$E:$E, MATCH('Ratings by CLO'!$J9,'Master Ratings'!$B:$B,0),0)) | O9: =+IF(INDEX('Master Ratings'!$G:$G, MATCH('Ratings by CLO'!$J9,'Master Ratings'!$B:$B,0),0)=0,"",INDEX('Master Ratings'!$G:$G, MATCH('Ratings by CLO'!$J9,'Master Ratings'!$B:$B,0),0)) -> B* | P9: =+IF(INDEX('Master Ratings'!$H:$H, MATCH('Ratings by CLO'!$J9,'Master Ratings'!$B:$B,0),0)=0,"",INDEX('Master Ratings'!$H:$H, MATCH('Ratings by CLO'!$J9,'Master Ratings'!$B:$B,0),0)) -> Rating (Private) | Q9: =+IF(INDEX('Master Ratings'!$O:$O, MATCH('Ratings by CLO'!$J9,'Master Ratings'!$B:$B,0),0)=0,"",INDEX('Master Ratings'!$O:$O, MATCH('Ratings by CLO'!$J9,'Master Ratings'!$B:$B,0),0)) -> 45481 | S9: =+IF(INDEX('Master Ratings'!$L:$L, MATCH('Ratings by CLO'!$J9,'Master Ratings'!$B:$B,0),0)=0,"",INDEX('Master Ratings'!$L:$L, MATCH('Ratings by CLO'!$J9,'Master Ratings'!$B:$B,0),0)) -> B+* | T9: =+IF(INDEX('Master Ratings'!$M:$M, MATCH('Ratings by CLO'!$J9,'Master Ratings'!$B:$B,0),0)=0,"",INDEX('Master Ratings'!$M:$M, MATCH('Ratings by CLO'!$J9,'Master Ratings'!$B:$B,0),0)) -> Credit Estimate | U9: =+IF(INDEX('Master Ratings'!$P:$P, MATCH('Ratings by CLO'!$J9,'Master Ratings'!$B:$B,0),0)=0,"",INDEX('Master Ratings'!$P:$P, MATCH('Ratings by CLO'!$J9,'Master Ratings'!$B:$B,0),0)) -> 45275 | W9: =+IF(OR($P9=$W$1,$P9=$W$2),$Q9+365-TODAY(), "") -> -118 | X9: =+IF(OR($T9=$W$1,$T9=$W$2),$U9+365-TODAY(), "") -> -324 | Z9: =IF(AND(SUM(B9:H9)>=1,ISERROR(W9)),"X","") | AA9: =IF(AND(B9>1, ISERROR(X9)),"X","") | AB9: =+IFERROR(IF(W9<0,"X",""),"") -> X | AC9: =+IFERROR(IF(AND(B9>0, X9<0),"X",""),"") -> X | AE9: =+IF(SUM(B9:H9)=0,"X","") | AG9: =IF(Z9="X",AG8+1,AG8) -> 0 | AH9: =IF(AA9="X",AH8+1,AH8) -> 0 | AI9: =IF(AB9="X",AI8+1,AI8) -> 1 | AJ9: =IF(AC9="X",AJ8+1,AJ8) -> 3 | AL9: =AL8+1 -> 5 | AM9: =INDEX($J:$J, MATCH($AL9,AG:AG,0),0) -> ImagineAcquisitionCo | AN9: =INDEX($J:$J, MATCH($AL9,AH:AH,0),0) -> MeritDirect | AO9: =INDEX($J:$J, MATCH($AL9,AI:AI,0),0) -> BioDerm | AP9: =INDEX($J:$J, MATCH($AL9,AJ:AJ,0),0) -> Apex Service Partners
B10: =+COUNTIFS(SOIs!$D:$D, 'Ratings by CLO'!$J10) -> 0 | C10: =+COUNTIFS(SOIs!$G:$G, 'Ratings by CLO'!$J10) -> 0 | D10: =+COUNTIFS(SOIs!$J:$J, 'Ratings by CLO'!$J10) -> 0 | E10: =+COUNTIFS(SOIs!$M:$M, 'Ratings by CLO'!$J10) -> 0 | F10: =+COUNTIFS(SOIs!$P:$P, 'Ratings by CLO'!$J10) -> 1 | G10: =+COUNTIFS(SOIs!$S:$S, 'Ratings by CLO'!$J10) -> 0 | H10: =+COUNTIFS(SOIs!$V:$V, 'Ratings by CLO'!$J10) -> 0 | J10: =+SOIs!X11 -> American Insulated Glass | L10: =+IF(INDEX('Master Ratings'!$D:$D, MATCH('Ratings by CLO'!$J10,'Master Ratings'!$B:$B,0),0)=0,"",INDEX('Master Ratings'!$D:$D, MATCH('Ratings by CLO'!$J10,'Master Ratings'!$B:$B,0),0)) | M10: =+IF(INDEX('Master Ratings'!$E:$E, MATCH('Ratings by CLO'!$J10,'Master Ratings'!$B:$B,0),0)=0,"",INDEX('Master Ratings'!$E:$E, MATCH('Ratings by CLO'!$J10,'Master Ratings'!$B:$B,0),0)) | O10: =+IF(INDEX('Master Ratings'!$G:$G, MATCH('Ratings by CLO'!$J10,'Master Ratings'!$B:$B,0),0)=0,"",INDEX('Master Ratings'!$G:$G, MATCH('Ratings by CLO'!$J10,'Master Ratings'!$B:$B,0),0)) -> B-* | P10: =+IF(INDEX('Master Ratings'!$H:$H, MATCH('Ratings by CLO'!$J10,'Master Ratings'!$B:$B,0),0)=0,"",INDEX('Master Ratings'!$H:$H, MATCH('Ratings by CLO'!$J10,'Master Ratings'!$B:$B,0),0)) -> Credit Estimate | Q10: =+IF(INDEX('Master Ratings'!$O:$O, MATCH('Ratings by CLO'!$J10,'Master Ratings'!$B:$B,0),0)=0,"",INDEX('Master Ratings'!$O:$O, MATCH('Ratings by CLO'!$J10,'Master Ratings'!$B:$B,0),0)) -> 44825 | S10: =+IF(INDEX('Master Ratings'!$L:$L, MATCH('Ratings by CLO'!$J10,'Master Ratings'!$B:$B,0),0)=0,"",INDEX('Master Ratings'!$L:$L, MATCH('Ratings by CLO'!$J10,'Master Ratings'!$B:$B,0),0)) -> B-* | T10: =+IF(INDEX('Master Ratings'!$M:$M, MATCH('Ratings by CLO'!$J10,'Master Ratings'!$B:$B,0),0)=0,"",INDEX('Master Ratings'!$M:$M, MATCH('Ratings by CLO'!$J10,'Master Ratings'!$B:$B,0),0)) -> Credit Estimate | U10: =+IF(INDEX('Master Ratings'!$P:$P, MATCH('Ratings by CLO'!$J10,'Master Ratings'!$B:$B,0),0)=0,"",INDEX('Master Ratings'!$P:$P, MATCH('Ratings by CLO'!$J10,'Master Ratings'!$B:$B,0),0)) -> 44886 | W10: =+IF(OR($P10=$W$1,$P10=$W$2),$Q10+365-TODAY(), "") -> -774 | X10: =+IF(OR($T10=$W$1,$T10=$W$2),$U10+365-TODAY(), "") -> -713 | Z10: =IF(AND(SUM(B10:H10)>=1,ISERROR(W10)),"X","") | AA10: =IF(AND(B10>1, ISERROR(X10)),"X","") | AB10: =+IFERROR(IF(W10<0,"X",""),"") -> X | AC10: =+IFERROR(IF(AND(B10>0, X10<0),"X",""),"") | AE10: =+IF(SUM(B10:H10)=0,"X","") | AG10: =IF(Z10="X",AG9+1,AG9) -> 0 | AH10: =IF(AA10="X",AH9+1,AH9) -> 0 | AI10: =IF(AB10="X",AI9+1,AI9) -> 2 | AJ10: =IF(AC10="X",AJ9+1,AJ9) -> 3 | AL10: =AL9+1 -> 6 | AM10: =INDEX($J:$J, MATCH($AL10,AG:AG,0),0) -> Integrated Data Services | AN10: =INDEX($J:$J, MATCH($AL10,AH:AH,0),0) -> Mission Critical Electronics | AO10: =INDEX($J:$J, MATCH($AL10,AI:AI,0),0) -> By Light | AP10: =INDEX($J:$J, MATCH($AL10,AJ:AJ,0),0) -> Applied Technical Services
B11: =+COUNTIFS(SOIs!$D:$D, 'Ratings by CLO'!$J11) -> 0 | C11: =+COUNTIFS(SOIs!$G:$G, 'Ratings by CLO'!$J11) -> 0 | D11: =+COUNTIFS(SOIs!$J:$J, 'Ratings by CLO'!$J11) -> 0 | E11: =+COUNTIFS(SOIs!$M:$M, 'Ratings by CLO'!$J11) -> 0 | F11: =+COUNTIFS(SOIs!$P:$P, 'Ratings by CLO'!$J11) -> 1 | G11: =+COUNTIFS(SOIs!$S:$S, 'Ratings by CLO'!$J11) -> 0 | H11: =+COUNTIFS(SOIs!$V:$V, 'Ratings by CLO'!$J11) -> 0 | J11: =+SOIs!X12 -> Ankura | L11: =+IF(INDEX('Master Ratings'!$D:$D, MATCH('Ratings by CLO'!$J11,'Master Ratings'!$B:$B,0),0)=0,"",INDEX('Master Ratings'!$D:$D, MATCH('Ratings by CLO'!$J11,'Master Ratings'!$B:$B,0),0)) -> B3 | M11: =+IF(INDEX('Master Ratings'!$E:$E, MATCH('Ratings by CLO'!$J11,'Master Ratings'!$B:$B,0),0)=0,"",INDEX('Master Ratings'!$E:$E, MATCH('Ratings by CLO'!$J11,'Master Ratings'!$B:$B,0),0)) -> Rating (Public) | O11: =+IF(INDEX('Master Ratings'!$G:$G, MATCH('Ratings by CLO'!$J11,'Master Ratings'!$B:$B,0),0)=0,"",INDEX('Master Ratings'!$G:$G, MATCH('Ratings by CLO'!$J11,'Master Ratings'!$B:$B,0),0)) -> B- | P11: =+IF(INDEX('Master Ratings'!$H:$H, MATCH('Ratings by CLO'!$J11,'Master Ratings'!$B:$B,0),0)=0,"",INDEX('Master Ratings'!$H:$H, MATCH('Ratings by CLO'!$J11,'Master Ratings'!$B:$B,0),0)) -> Rating (Public) | Q11: =+IF(INDEX('Master Ratings'!$O:$O, MATCH('Ratings by CLO'!$J11,'Master Ratings'!$B:$B,0),0)=0,"",INDEX('Master Ratings'!$O:$O, MATCH('Ratings by CLO'!$J11,'Master Ratings'!$B:$B,0),0)) | S11: =+IF(INDEX('Master Ratings'!$L:$L, MATCH('Ratings by CLO'!$J11,'Master Ratings'!$B:$B,0),0)=0,"",INDEX('Master Ratings'!$L:$L, MATCH('Ratings by CLO'!$J11,'Master Ratings'!$B:$B,0),0)) | T11: =+IF(INDEX('Master Ratings'!$M:$M, MATCH('Ratings by CLO'!$J11,'Master Ratings'!$B:$B,0),0)=0,"",INDEX('Master Ratings'!$M:$M, MATCH('Ratings by CLO'!$J11,'Master Ratings'!$B:$B,0),0)) | U11: =+IF(INDEX('Master Ratings'!$P:$P, MATCH('Ratings by CLO'!$J11,'Master Ratings'!$B:$B,0),0)=0,"",INDEX('Master Ratings'!$P:$P, MATCH('Ratings by CLO'!$J11,'Master Ratings'!$B:$B,0),0)) | W11: =+IF(OR($P11=$W$1,$P11=$W$2),$Q11+365-TODAY(), "") | X11: =+IF(OR($T11=$W$1,$T11=$W$2),$U11+365-TODAY(), "") | Z11: =IF(AND(SUM(B11:H11)>=1,ISERROR(W11)),"X","") | AA11: =IF(AND(B11>1, ISERROR(X11)),"X","") | AB11: =+IFERROR(IF(W11<0,"X",""),"") | AC11: =+IFERROR(IF(AND(B11>0, X11<0),"X",""),"") | AE11: =+IF(SUM(B11:H11)=0,"X","") | AG11: =IF(Z11="X",AG10+1,AG10) -> 0 | AH11: =IF(AA11="X",AH10+1,AH10) -> 0 | AI11: =IF(AB11="X",AI10+1,AI10) -> 2 | AJ11: =IF(AC11="X",AJ10+1,AJ10) -> 3 | AL11: =AL10+1 -> 7 | AM11: =INDEX($J:$J, MATCH($AL11,AG:AG,0),0) -> Rancho Medical | AN11: =INDEX($J:$J, MATCH($AL11,AH:AH,0),0) -> Quantic Electronics | AO11: =INDEX($J:$J, MATCH($AL11,AI:AI,0),0) -> Cadence Aerospace | AP11: =INDEX($J:$J, MATCH($AL11,AJ:AJ,0),0) -> Arcfield
B12: =+COUNTIFS(SOIs!$D:$D, 'Ratings by CLO'!$J12) -> 3 | C12: =+COUNTIFS(SOIs!$G:$G, 'Ratings by CLO'!$J12) -> 1 | D12: =+COUNTIFS(SOIs!$J:$J, 'Ratings by CLO'!$J12) -> 0 | E12: =+COUNTIFS(SOIs!$M:$M, 'Ratings by CLO'!$J12) -> 1 | F12: =+COUNTIFS(SOIs!$P:$P, 'Ratings by CLO'!$J12) -> 0 | G12: =+COUNTIFS(SOIs!$S:$S, 'Ratings by CLO'!$J12) -> 1 | H12: =+COUNTIFS(SOIs!$V:$V, 'Ratings by CLO'!$J12) -> 1 | J12: =+SOIs!X13 -> Any Hour Services | L12: =+IF(INDEX('Master Ratings'!$D:$D, MATCH('Ratings by CLO'!$J12,'Master Ratings'!$B:$B,0),0)=0,"",INDEX('Master Ratings'!$D:$D, MATCH('Ratings by CLO'!$J12,'Master Ratings'!$B:$B,0),0)) | M12: =+IF(INDEX('Master Ratings'!$E:$E, MATCH('Ratings by CLO'!$J12,'Master Ratings'!$B:$B,0),0)=0,"",INDEX('Master Ratings'!$E:$E, MATCH('Ratings by CLO'!$J12,'Master Ratings'!$B:$B,0),0)) | O12: =+IF(INDEX('Master Ratings'!$G:$G, MATCH('Ratings by CLO'!$J12,'Master Ratings'!$B:$B,0),0)=0,"",INDEX('Master Ratings'!$G:$G, MATCH('Ratings by CLO'!$J12,'Master Ratings'!$B:$B,0),0)) -> B-* | P12: =+IF(INDEX('Master Ratings'!$H:$H, MATCH('Ratings by CLO'!$J12,'Master Ratings'!$B:$B,0),0)=0,"",INDEX('Master Ratings'!$H:$H, MATCH('Ratings by CLO'!$J12,'Master Ratings'!$B:$B,0),0)) -> Credit Estimate | Q12: =+IF(INDEX('Master Ratings'!$O:$O, MATCH('Ratings by CLO'!$J12,'Master Ratings'!$B:$B,0),0)=0,"",INDEX('Master Ratings'!$O:$O, MATCH('Ratings by CLO'!$J12,'Master Ratings'!$B:$B,0),0)) -> 45447 | S12: =+IF(INDEX('Master Ratings'!$L:$L, MATCH('Ratings by CLO'!$J12,'Master Ratings'!$B:$B,0),0)=0,"",INDEX('Master Ratings'!$L:$L, MATCH('Ratings by CLO'!$J12,'Master Ratings'!$B:$B,0),0)) -> B-* | T12: =+IF(INDEX('Master Ratings'!$M:$M, MATCH('Ratings by CLO'!$J12,'Master Ratings'!$B:$B,0),0)=0,"",INDEX('Master Ratings'!$M:$M, MATCH('Ratings by CLO'!$J12,'Master Ratings'!$B:$B,0),0)) -> Credit Estimate | U12: =+IF(INDEX('Master Ratings'!$P:$P, MATCH('Ratings by CLO'!$J12,'Master Ratings'!$B:$B,0),0)=0,"",INDEX('Master Ratings'!$P:$P, MATCH('Ratings by CLO'!$J12,'Master Ratings'!$B:$B,0),0)) -> 45050 | W12: =+IF(OR($P12=$W$1,$P12=$W$2),$Q12+365-TODAY(), "") -> -152 | X12: =+IF(OR($T12=$W$1,$T12=$W$2),$U12+365-TODAY(), "") -> -549 | Z12: =IF(AND(SUM(B12:H12)>=1,ISERROR(W12)),"X","") | AA12: =IF(AND(B12>1, ISERROR(X12)),"X","") | AB12: =+IFERROR(IF(W12<0,"X",""),"") -> X | AC12: =+IFERROR(IF(AND(B12>0, X12<0),"X",""),"") -> X | AE12: =+IF(SUM(B12:H12)=0,"X","") | AG12: =IF(Z12="X",AG11+1,AG11) -> 0 | AH12: =IF(AA12="X",AH11+1,AH11) -> 0 | AI12: =IF(AB12="X",AI11+1,AI11) -> 3 | AJ12: =IF(AC12="X",AJ11+1,AJ11) -> 4 | AL12: =AL11+1 -> 8 | AM12: =INDEX($J:$J, MATCH($AL12,AG:AG,0),0) -> Simplicity Group | AN12: =INDEX($J:$J, MATCH($AL12,AH:AH,0),0) -> Sales Benchmark Index (SBI) | AO12: =INDEX($J:$J, MATCH($AL12,AI:AI,0),0) -> Connatix | AP12: =INDEX($J:$J, MATCH($AL12,AJ:AJ,0),0) -> Bluebird
B13: =+COUNTIFS(SOIs!$D:$D, 'Ratings by CLO'!$J13) -> 7 | C13: =+COUNTIFS(SOIs!$G:$G, 'Ratings by CLO'!$J13) -> 3 | D13: =+COUNTIFS(SOIs!$J:$J, 'Ratings by CLO'!$J13) -> 2 | E13: =+COUNTIFS(SOIs!$M:$M, 'Ratings by CLO'!$J13) -> 1 | F13: =+COUNTIFS(SOIs!$P:$P, 'Ratings by CLO'!$J13) -> 1 | G13: =+COUNTIFS(SOIs!$S:$S, 'Ratings by CLO'!$J13) -> 1 | H13: =+COUNTIFS(SOIs!$V:$V, 'Ratings by CLO'!$J13) -> 1 | J13: =+SOIs!X14 -> Apex Service Partners | L13: =+IF(INDEX('Master Ratings'!$D:$D, MATCH('Ratings by CLO'!$J13,'Master Ratings'!$B:$B,0),0)=0,"",INDEX('Master Ratings'!$D:$D, MATCH('Ratings by CLO'!$J13,'Master Ratings'!$B:$B,0),0)) | M13: =+IF(INDEX('Master Ratings'!$E:$E, MATCH('Ratings by CLO'!$J13,'Master Ratings'!$B:$B,0),0)=0,"",INDEX('Master Ratings'!$E:$E, MATCH('Ratings by CLO'!$J13,'Master Ratings'!$B:$B,0),0)) | O13: =+IF(INDEX('Master Ratings'!$G:$G, MATCH('Ratings by CLO'!$J13,'Master Ratings'!$B:$B,0),0)=0,"",INDEX('Master Ratings'!$G:$G, MATCH('Ratings by CLO'!$J13,'Master Ratings'!$B:$B,0),0)) -> B-* | P13: =+IF(INDEX('Master Ratings'!$H:$H, MATCH('Ratings by CLO'!$J13,'Master Ratings'!$B:$B,0),0)=0,"",INDEX('Master Ratings'!$H:$H, MATCH('Ratings by CLO'!$J13,'Master Ratings'!$B:$B,0),0)) -> Credit Estimate | Q13: =+IF(INDEX('Master Ratings'!$O:$O, MATCH('Ratings by CLO'!$J13,'Master Ratings'!$B:$B,0),0)=0,"",INDEX('Master Ratings'!$O:$O, MATCH('Ratings by CLO'!$J13,'Master Ratings'!$B:$B,0),0)) -> 45077 | S13: =+IF(INDEX('Master Ratings'!$L:$L, MATCH('Ratings by CLO'!$J13,'Master Ratings'!$B:$B,0),0)=0,"",INDEX('Master Ratings'!$L:$L, MATCH('Ratings by CLO'!$J13,'Master Ratings'!$B:$B,0),0)) -> B- | T13: =+IF(INDEX('Master Ratings'!$M:$M, MATCH('Ratings by CLO'!$J13,'Master Ratings'!$B:$B,0),0)=0,"",INDEX('Master Ratings'!$M:$M, MATCH('Ratings by CLO'!$J13,'Master Ratings'!$B:$B,0),0)) -> Rating (Private) | U13: =+IF(INDEX('Master Ratings'!$P:$P, MATCH('Ratings by CLO'!$J13,'Master Ratings'!$B:$B,0),0)=0,"",INDEX('Master Ratings'!$P:$P, MATCH('Ratings by CLO'!$J13,'Master Ratings'!$B:$B,0),0)) -> 44886 | W13: =+IF(OR($P13=$W$1,$P13=$W$2),$Q13+365-TODAY(), "") -> -522 | X13: =+IF(OR($T13=$W$1,$T13=$W$2),$U13+365-TODAY(), "") -> -713 | Z13: =IF(AND(SUM(B13:H13)>=1,ISERROR(W13)),"X","") | AA13: =IF(AND(B13>1, ISERROR(X13)),"X","") | AB13: =+IFERROR(IF(W13<0,"X",""),"") -> X | AC13: =+IFERROR(IF(AND(B13>0, X13<0),"X",""),"") -> X | AE13: =+IF(SUM(B13:H13)=0,"X","") | AG13: =IF(Z13="X",AG12+1,AG12) -> 0 | AH13: =IF(AA13="X",AH12+1,AH12) -> 0 | AI13: =IF(AB13="X",AI12+1,AI12) -> 4 | AJ13: =IF(AC13="X",AJ12+1,AJ12) -> 5 | AL13: =AL12+1 -> 9 | AM13: =INDEX($J:$J, MATCH($AL13,AG:AG,0),0) -> TVC | AN13: =INDEX($J:$J, MATCH($AL13,AH:AH,0),0) -> Schlesinger | AO13: =INDEX($J:$J, MATCH($AL13,AI:AI,0),0) -> Exigo | AP13: =INDEX($J:$J, MATCH($AL13,AJ:AJ,0),0) -> By Light
B14: =+COUNTIFS(SOIs!$D:$D, 'Ratings by CLO'!$J14) -> 4 | C14: =+COUNTIFS(SOIs!$G:$G, 'Ratings by CLO'!$J14) -> 2 | D14: =+COUNTIFS(SOIs!$J:$J, 'Ratings by CLO'!$J14) -> 0 | E14: =+COUNTIFS(SOIs!$M:$M, 'Ratings by CLO'!$J14) -> 1 | F14: =+COUNTIFS(SOIs!$P:$P, 'Ratings by CLO'!$J14) -> 1 | G14: =+COUNTIFS(SOIs!$S:$S, 'Ratings by CLO'!$J14) -> 1 | H14: =+COUNTIFS(SOIs!$V:$V, 'Ratings by CLO'!$J14) -> 1 | J14: =+SOIs!X15 -> Applied Technical Services | L14: =+IF(INDEX('Master Ratings'!$D:$D, MATCH('Ratings by CLO'!$J14,'Master Ratings'!$B:$B,0),0)=0,"",INDEX('Master Ratings'!$D:$D, MATCH('Ratings by CLO'!$J14,'Master Ratings'!$B:$B,0),0)) | M14: =+IF(INDEX('Master Ratings'!$E:$E, MATCH('Ratings by CLO'!$J14,'Master Ratings'!$B:$B,0),0)=0,"",INDEX('Master Ratings'!$E:$E, MATCH('Ratings by CLO'!$J14,'Master Ratings'!$B:$B,0),0)) | O14: =+IF(INDEX('Master Ratings'!$G:$G, MATCH('Ratings by CLO'!$J14,'Master Ratings'!$B:$B,0),0)=0,"",INDEX('Master Ratings'!$G:$G, MATCH('Ratings by CLO'!$J14,'Master Ratings'!$B:$B,0),0)) -> B-* | P14: =+IF(INDEX('Master Ratings'!$H:$H, MATCH('Ratings by CLO'!$J14,'Master Ratings'!$B:$B,0),0)=0,"",INDEX('Master Ratings'!$H:$H, MATCH('Ratings by CLO'!$J14,'Master Ratings'!$B:$B,0),0)) -> Rating (Private) | Q14: =+IF(INDEX('Master Ratings'!$O:$O, MATCH('Ratings by CLO'!$J14,'Master Ratings'!$B:$B,0),0)=0,"",INDEX('Master Ratings'!$O:$O, MATCH('Ratings by CLO'!$J14,'Master Ratings'!$B:$B,0),0)) -> 45660 | S14: =+IF(INDEX('Master Ratings'!$L:$L, MATCH('Ratings by CLO'!$J14,'Master Ratings'!$B:$B,0),0)=0,"",INDEX('Master Ratings'!$L:$L, MATCH('Ratings by CLO'!$J14,'Master Ratings'!$B:$B,0),0)) -> B* | T14: =+IF(INDEX('Master Ratings'!$M:$M, MATCH('Ratings by CLO'!$J14,'Master Ratings'!$B:$B,0),0)=0,"",INDEX('Master Ratings'!$M:$M, MATCH('Ratings by CLO'!$J14,'Master Ratings'!$B:$B,0),0)) -> Credit Estimate | U14: =+IF(INDEX('Master Ratings'!$P:$P, MATCH('Ratings by CLO'!$J14,'Master Ratings'!$B:$B,0),0)=0,"",INDEX('Master Ratings'!$P:$P, MATCH('Ratings by CLO'!$J14,'Master Ratings'!$B:$B,0),0)) -> 45359 | W14: =+IF(OR($P14=$W$1,$P14=$W$2),$Q14+365-TODAY(), "") -> 61 | X14: =+IF(OR($T14=$W$1,$T14=$W$2),$U14+365-TODAY(), "") -> -240 | Z14: =IF(AND(SUM(B14:H14)>=1,ISERROR(W14)),"X","") | AA14: =IF(AND(B14>1, ISERROR(X14)),"X","") | AB14: =+IFERROR(IF(W14<0,"X",""),"") | AC14: =+IFERROR(IF(AND(B14>0, X14<0),"X",""),"") -> X | AE14: =+IF(SUM(B14:H14)=0,"X","") | AG14: =IF(Z14="X",AG13+1,AG13) -> 0 | AH14: =IF(AA14="X",AH13+1,AH13) -> 0 | AI14: =IF(AB14="X",AI13+1,AI13) -> 4 | AJ14: =IF(AC14="X",AJ13+1,AJ13) -> 6 | AL14: =AL13+1 -> 10 | AM14: =INDEX($J:$J, MATCH($AL14,AG:AG,0),0) -> #N/A | AN14: =INDEX($J:$J, MATCH($AL14,AH:AH,0),0) -> Sigma Defense | AO14: =INDEX($J:$J, MATCH($AL14,AI:AI,0),0) -> GCOM | AP14: =INDEX($J:$J, MATCH($AL14,AJ:AJ,0),0) -> Cartessa
B15: =+COUNTIFS(SOIs!$D:$D, 'Ratings by CLO'!$J15) -> 3 | C15: =+COUNTIFS(SOIs!$G:$G, 'Ratings by CLO'!$J15) -> 1 | D15: =+COUNTIFS(SOIs!$J:$J, 'Ratings by CLO'!$J15) -> 0 | E15: =+COUNTIFS(SOIs!$M:$M, 'Ratings by CLO'!$J15) -> 0 | F15: =+COUNTIFS(SOIs!$P:$P, 'Ratings by CLO'!$J15) -> 0 | G15: =+COUNTIFS(SOIs!$S:$S, 'Ratings by CLO'!$J15) -> 1 | H15: =+COUNTIFS(SOIs!$V:$V, 'Ratings by CLO'!$J15) -> 1 | J15: =+SOIs!X16 -> Arcfield | L15: =+IF(INDEX('Master Ratings'!$D:$D, MATCH('Ratings by CLO'!$J15,'Master Ratings'!$B:$B,0),0)=0,"",INDEX('Master Ratings'!$D:$D, MATCH('Ratings by CLO'!$J15,'Master Ratings'!$B:$B,0),0)) | M15: =+IF(INDEX('Master Ratings'!$E:$E, MATCH('Ratings by CLO'!$J15,'Master Ratings'!$B:$B,0),0)=0,"",INDEX('Master Ratings'!$E:$E, MATCH('Ratings by CLO'!$J15,'Master Ratings'!$B:$B,0),0)) | O15: =+IF(INDEX('Master Ratings'!$G:$G, MATCH('Ratings by CLO'!$J15,'Master Ratings'!$B:$B,0),0)=0,"",INDEX('Master Ratings'!$G:$G, MATCH('Ratings by CLO'!$J15,'Master Ratings'!$B:$B,0),0)) -> B-* | P15: =+IF(INDEX('Master Ratings'!$H:$H, MATCH('Ratings by CLO'!$J15,'Master Ratings'!$B:$B,0),0)=0,"",INDEX('Master Ratings'!$H:$H, MATCH('Ratings by CLO'!$J15,'Master Ratings'!$B:$B,0),0)) -> Credit Estimate | Q15: =+IF(INDEX('Master Ratings'!$O:$O, MATCH('Ratings by CLO'!$J15,'Master Ratings'!$B:$B,0),0)=0,"",INDEX('Master Ratings'!$O:$O, MATCH('Ratings by CLO'!$J15,'Master Ratings'!$B:$B,0),0)) -> 45684 | S15: =+IF(INDEX('Master Ratings'!$L:$L, MATCH('Ratings by CLO'!$J15,'Master Ratings'!$B:$B,0),0)=0,"",INDEX('Master Ratings'!$L:$L, MATCH('Ratings by CLO'!$J15,'Master Ratings'!$B:$B,0),0)) -> B | T15: =+IF(INDEX('Master Ratings'!$M:$M, MATCH('Ratings by CLO'!$J15,'Master Ratings'!$B:$B,0),0)=0,"",INDEX('Master Ratings'!$M:$M, MATCH('Ratings by CLO'!$J15,'Master Ratings'!$B:$B,0),0)) -> Rating (Private) | U15: =+IF(INDEX('Master Ratings'!$P:$P, MATCH('Ratings by CLO'!$J15,'Master Ratings'!$B:$B,0),0)=0,"",INDEX('Master Ratings'!$P:$P, MATCH('Ratings by CLO'!$J15,'Master Ratings'!$B:$B,0),0)) -> 45198 | W15: =+IF(OR($P15=$W$1,$P15=$W$2),$Q15+365-TODAY(), "") -> 85 | X15: =+IF(OR($T15=$W$1,$T15=$W$2),$U15+365-TODAY(), "") -> -401 | Z15: =IF(AND(SUM(B15:H15)>=1,ISERROR(W15)),"X","") | AA15: =IF(AND(B15>1, ISERROR(X15)),"X","") | AB15: =+IFERROR(IF(W15<0,"X",""),"") | AC15: =+IFERROR(IF(AND(B15>0, X15<0),"X",""),"") -> X | AE15: =+IF(SUM(B15:H15)=0,"X","") | AG15: =IF(Z15="X",AG14+1,AG14) -> 0 | AH15: =IF(AA15="X",AH14+1,AH14) -> 0 | AI15: =IF(AB15="X",AI14+1,AI14) -> 4 | AJ15: =IF(AC15="X",AJ14+1,AJ14) -> 7 | AL15: =AL14+1 -> 11 | AM15: =INDEX($J:$J, MATCH($AL15,AG:AG,0),0) -> #N/A | AN15: =INDEX($J:$J, MATCH($AL15,AH:AH,0),0) -> Signature Systems Group | AO15: =INDEX($J:$J, MATCH($AL15,AI:AI,0),0) -> IDC Infusion Services | AP15: =INDEX($J:$J, MATCH($AL15,AJ:AJ,0),0) -> Centauri Health
B16: =+COUNTIFS(SOIs!$D:$D, 'Ratings by CLO'!$J16) -> 0 | C16: =+COUNTIFS(SOIs!$G:$G, 'Ratings by CLO'!$J16) -> 0 | D16: =+COUNTIFS(SOIs!$J:$J, 'Ratings by CLO'!$J16) -> 0 | E16: =+COUNTIFS(SOIs!$M:$M, 'Ratings by CLO'!$J16) -> 0 | F16: =+COUNTIFS(SOIs!$P:$P, 'Ratings by CLO'!$J16) -> 0 | G16: =+COUNTIFS(SOIs!$S:$S, 'Ratings by CLO'!$J16) -> 1 | H16: =+COUNTIFS(SOIs!$V:$V, 'Ratings by CLO'!$J16) -> 1 | J16: =+SOIs!X17 -> Ardurra | L16: =+IF(INDEX('Master Ratings'!$D:$D, MATCH('Ratings by CLO'!$J16,'Master Ratings'!$B:$B,0),0)=0,"",INDEX('Master Ratings'!$D:$D, MATCH('Ratings by CLO'!$J16,'Master Ratings'!$B:$B,0),0)) | M16: =+IF(INDEX('Master Ratings'!$E:$E, MATCH('Ratings by CLO'!$J16,'Master Ratings'!$B:$B,0),0)=0,"",INDEX('Master Ratings'!$E:$E, MATCH('Ratings by CLO'!$J16,'Master Ratings'!$B:$B,0),0)) | O16: =+IF(INDEX('Master Ratings'!$G:$G, MATCH('Ratings by CLO'!$J16,'Master Ratings'!$B:$B,0),0)=0,"",INDEX('Master Ratings'!$G:$G, MATCH('Ratings by CLO'!$J16,'Master Ratings'!$B:$B,0),0)) -> B-* | P16: =+IF(INDEX('Master Ratings'!$H:$H, MATCH('Ratings by CLO'!$J16,'Master Ratings'!$B:$B,0),0)=0,"",INDEX('Master Ratings'!$H:$H, MATCH('Ratings by CLO'!$J16,'Master Ratings'!$B:$B,0),0)) -> Credit Estimate | Q16: =+IF(INDEX('Master Ratings'!$O:$O, MATCH('Ratings by CLO'!$J16,'Master Ratings'!$B:$B,0),0)=0,"",INDEX('Master Ratings'!$O:$O, MATCH('Ratings by CLO'!$J16,'Master Ratings'!$B:$B,0),0)) -> 45657 | S16: =+IF(INDEX('Master Ratings'!$L:$L, MATCH('Ratings by CLO'!$J16,'Master Ratings'!$B:$B,0),0)=0,"",INDEX('Master Ratings'!$L:$L, MATCH('Ratings by CLO'!$J16,'Master Ratings'!$B:$B,0),0)) | T16: =+IF(INDEX('Master Ratings'!$M:$M, MATCH('Ratings by CLO'!$J16,'Master Ratings'!$B:$B,0),0)=0,"",INDEX('Master Ratings'!$M:$M, MATCH('Ratings by CLO'!$J16,'Master Ratings'!$B:$B,0),0)) | U16: =+IF(INDEX('Master Ratings'!$P:$P, MATCH('Ratings by CLO'!$J16,'Master Ratings'!$B:$B,0),0)=0,"",INDEX('Master Ratings'!$P:$P, MATCH('Ratings by CLO'!$J16,'Master Ratings'!$B:$B,0),0)) | W16: =+IF(OR($P16=$W$1,$P16=$W$2),$Q16+365-TODAY(), "") -> 58 | X16: =+IF(OR($T16=$W$1,$T16=$W$2),$U16+365-TODAY(), "") | Z16: =IF(AND(SUM(B16:H16)>=1,ISERROR(W16)),"X","") | AA16: =IF(AND(B16>1, ISERROR(X16)),"X","") | AB16: =+IFERROR(IF(W16<0,"X",""),"") | AC16: =+IFERROR(IF(AND(B16>0, X16<0),"X",""),"") | AE16: =+IF(SUM(B16:H16)=0,"X","") | AG16: =IF(Z16="X",AG15+1,AG15) -> 0 | AH16: =IF(AA16="X",AH15+1,AH15) -> 0 | AI16: =IF(AB16="X",AI15+1,AI15) -> 4 | AJ16: =IF(AC16="X",AJ15+1,AJ15) -> 7 | AL16: =AL15+1 -> 12 | AM16: =INDEX($J:$J, MATCH($AL16,AG:AG,0),0) -> #N/A | AN16: =INDEX($J:$J, MATCH($AL16,AH:AH,0),0) -> Targeted Pet Care | AO16: =INDEX($J:$J, MATCH($AL16,AI:AI,0),0) -> Insight Global | AP16: =INDEX($J:$J, MATCH($AL16,AJ:AJ,0),0) -> Crane 1
B17: =+COUNTIFS(SOIs!$D:$D, 'Ratings by CLO'!$J17) -> 1 | C17: =+COUNTIFS(SOIs!$G:$G, 'Ratings by CLO'!$J17) -> 0 | D17: =+COUNTIFS(SOIs!$J:$J, 'Ratings by CLO'!$J17) -> 1 | E17: =+COUNTIFS(SOIs!$M:$M, 'Ratings by CLO'!$J17) -> 0 | F17: =+COUNTIFS(SOIs!$P:$P, 'Ratings by CLO'!$J17) -> 2 | G17: =+COUNTIFS(SOIs!$S:$S, 'Ratings by CLO'!$J17) -> 0 | H17: =+COUNTIFS(SOIs!$V:$V, 'Ratings by CLO'!$J17) -> 0 | J17: =+SOIs!X18 -> Ascensus | L17: =+IF(INDEX('Master Ratings'!$D:$D, MATCH('Ratings by CLO'!$J17,'Master Ratings'!$B:$B,0),0)=0,"",INDEX('Master Ratings'!$D:$D, MATCH('Ratings by CLO'!$J17,'Master Ratings'!$B:$B,0),0)) -> B3 | M17: =+IF(INDEX('Master Ratings'!$E:$E, MATCH('Ratings by CLO'!$J17,'Master Ratings'!$B:$B,0),0)=0,"",INDEX('Master Ratings'!$E:$E, MATCH('Ratings by CLO'!$J17,'Master Ratings'!$B:$B,0),0)) -> Rating (Public) | O17: =+IF(INDEX('Master Ratings'!$G:$G, MATCH('Ratings by CLO'!$J17,'Master Ratings'!$B:$B,0),0)=0,"",INDEX('Master Ratings'!$G:$G, MATCH('Ratings by CLO'!$J17,'Master Ratings'!$B:$B,0),0)) -> B- | P17: =+IF(INDEX('Master Ratings'!$H:$H, MATCH('Ratings by CLO'!$J17,'Master Ratings'!$B:$B,0),0)=0,"",INDEX('Master Ratings'!$H:$H, MATCH('Ratings by CLO'!$J17,'Master Ratings'!$B:$B,0),0)) -> Rating (Public) | Q17: =+IF(INDEX('Master Ratings'!$O:$O, MATCH('Ratings by CLO'!$J17,'Master Ratings'!$B:$B,0),0)=0,"",INDEX('Master Ratings'!$O:$O, MATCH('Ratings by CLO'!$J17,'Master Ratings'!$B:$B,0),0)) | S17: =+IF(INDEX('Master Ratings'!$L:$L, MATCH('Ratings by CLO'!$J17,'Master Ratings'!$B:$B,0),0)=0,"",INDEX('Master Ratings'!$L:$L, MATCH('Ratings by CLO'!$J17,'Master Ratings'!$B:$B,0),0)) | T17: =+IF(INDEX('Master Ratings'!$M:$M, MATCH('Ratings by CLO'!$J17,'Master Ratings'!$B:$B,0),0)=0,"",INDEX('Master Ratings'!$M:$M, MATCH('Ratings by CLO'!$J17,'Master Ratings'!$B:$B,0),0)) | U17: =+IF(INDEX('Master Ratings'!$P:$P, MATCH('Ratings by CLO'!$J17,'Master Ratings'!$B:$B,0),0)=0,"",INDEX('Master Ratings'!$P:$P, MATCH('Ratings by CLO'!$J17,'Master Ratings'!$B:$B,0),0)) | W17: =+IF(OR($P17=$W$1,$P17=$W$2),$Q17+365-TODAY(), "") | X17: =+IF(OR($T17=$W$1,$T17=$W$2),$U17+365-TODAY(), "") | Z17: =IF(AND(SUM(B17:H17)>=1,ISERROR(W17)),"X","") | AA17: =IF(AND(B17>1, ISERROR(X17)),"X","") | AB17: =+IFERROR(IF(W17<0,"X",""),"") | AC17: =+IFERROR(IF(AND(B17>0, X17<0),"X",""),"") | AE17: =+IF(SUM(B17:H17)=0,"X","") | AG17: =IF(Z17="X",AG16+1,AG16) -> 0 | AH17: =IF(AA17="X",AH16+1,AH16) -> 0 | AI17: =IF(AB17="X",AI16+1,AI16) -> 4 | AJ17: =IF(AC17="X",AJ16+1,AJ16) -> 7 | AL17: =AL16+1 -> 13 | AM17: =INDEX($J:$J, MATCH($AL17,AG:AG,0),0) -> #N/A | AN17: =INDEX($J:$J, MATCH($AL17,AH:AH,0),0) -> Vertex | AO17: =INDEX($J:$J, MATCH($AL17,AI:AI,0),0) -> Integrity Marketing | AP17: =INDEX($J:$J, MATCH($AL17,AJ:AJ,0),0) -> Dr. Scholl's
... B26: =+COUNTIFS(SOIs!$D:$D, 'Ratings by CLO'!$J26) -> 0 | C26: =+COUNTIFS(SOIs!$G:$G, 'Ratings by CLO'!$J26) -> 0 | D26: =+COUNTIFS(SOIs!$J:$J, 'Ratings by CLO'!$J26) -> 0 | E26: =+COUNTIFS(SOIs!$M:$M, 'Ratings by CLO'!$J26) -> 0 | F26: =+COUNTIFS(SOIs!$P:$P, 'Ratings by CLO'!$J26) -> 0 | G26: =+COUNTIFS(SOIs!$S:$S, 'Ratings by CLO'!$J26) -> 1 | H26: =+COUNTIFS(SOIs!$V:$V, 'Ratings by CLO'!$J26) -> 0 | J26: =+SOIs!X27 -> Cadence Aerospace | L26: =+IF(INDEX('Master Ratings'!$D:$D, MATCH('Ratings by CLO'!$J26,'Master Ratings'!$B:$B,0),0)=0,"",INDEX('Master Ratings'!$D:$D, MATCH('Ratings by CLO'!$J26,'Master Ratings'!$B:$B,0),0)) | M26: =+IF(INDEX('Master Ratings'!$E:$E, MATCH('Ratings by CLO'!$J26,'Master Ratings'!$B:$B,0),0)=0,"",INDEX('Master Ratings'!$E:$E, MATCH('Ratings by CLO'!$J26,'Master Ratings'!$B:$B,0),0)) | O26: =+IF(INDEX('Master Ratings'!$G:$G, MATCH('Ratings by CLO'!$J26,'Master Ratings'!$B:$B,0),0)=0,"",INDEX('Master Ratings'!$G:$G, MATCH('Ratings by CLO'!$J26,'Master Ratings'!$B:$B,0),0)) -> B-* | P26: =+IF(INDEX('Master Ratings'!$H:$H, MATCH('Ratings by CLO'!$J26,'Master Ratings'!$B:$B,0),0)=0,"",INDEX('Master Ratings'!$H:$H, MATCH('Ratings by CLO'!$J26,'Master Ratings'!$B:$B,0),0)) -> Credit Estimate | Q26: =+IF(INDEX('Master Ratings'!$O:$O, MATCH('Ratings by CLO'!$J26,'Master Ratings'!$B:$B,0),0)=0,"",INDEX('Master Ratings'!$O:$O, MATCH('Ratings by CLO'!$J26,'Master Ratings'!$B:$B,0),0)) -> 43846 | S26: =+IF(INDEX('Master Ratings'!$L:$L, MATCH('Ratings by CLO'!$J26,'Master Ratings'!$B:$B,0),0)=0,"",INDEX('Master Ratings'!$L:$L, MATCH('Ratings by CLO'!$J26,'Master Ratings'!$B:$B,0),0)) -> B-* | T26: =+IF(INDEX('Master Ratings'!$M:$M, MATCH('Ratings by CLO'!$J26,'Master Ratings'!$B:$B,0),0)=0,"",INDEX('Master Ratings'!$M:$M, MATCH('Ratings by CLO'!$J26,'Master Ratings'!$B:$B,0),0)) -> Credit Estimate | U26: =+IF(INDEX('Master Ratings'!$P:$P, MATCH('Ratings by CLO'!$J26,'Master Ratings'!$B:$B,0),0)=0,"",INDEX('Master Ratings'!$P:$P, MATCH('Ratings by CLO'!$J26,'Master Ratings'!$B:$B,0),0)) -> 43816 | W26: =+IF(OR($P26=$W$1,$P26=$W$2),$Q26+365-TODAY(), "") -> -1753 | X26: =+IF(OR($T26=$W$1,$T26=$W$2),$U26+365-TODAY(), "") -> -1783 | Z26: =IF(AND(SUM(B26:H26)>=1,ISERROR(W26)),"X","") | AA26: =IF(AND(B26>1, ISERROR(X26)),"X","") | AB26: =+IFERROR(IF(W26<0,"X",""),"") -> X | AC26: =+IFERROR(IF(AND(B26>0, X26<0),"X",""),"") | AE26: =+IF(SUM(B26:H26)=0,"X","") | AG26: =IF(Z26="X",AG25+1,AG25) -> 0 | AH26: =IF(AA26="X",AH25+1,AH25) -> 1 | AI26: =IF(AB26="X",AI25+1,AI25) -> 7 | AJ26: =IF(AC26="X",AJ25+1,AJ25) -> 9 | AL26: =AL25+1 -> 22 | AM26: =INDEX($J:$J, MATCH($AL26,AG:AG,0),0) -> #N/A | AN26: =INDEX($J:$J, MATCH($AL26,AH:AH,0),0) -> #N/A | AO26: =INDEX($J:$J, MATCH($AL26,AI:AI,0),0) -> Ox | AP26: =INDEX($J:$J, MATCH($AL26,AJ:AJ,0),0) -> Inventus
B27: =+COUNTIFS(SOIs!$D:$D, 'Ratings by CLO'!$J27) -> 4 | C27: =+COUNTIFS(SOIs!$G:$G, 'Ratings by CLO'!$J27) -> 1 | D27: =+COUNTIFS(SOIs!$J:$J, 'Ratings by CLO'!$J27) -> 1 | E27: =+COUNTIFS(SOIs!$M:$M, 'Ratings by CLO'!$J27) -> 1 | F27: =+COUNTIFS(SOIs!$P:$P, 'Ratings by CLO'!$J27) -> 1 | G27: =+COUNTIFS(SOIs!$S:$S, 'Ratings by CLO'!$J27) -> 1 | H27: =+COUNTIFS(SOIs!$V:$V, 'Ratings by CLO'!$J27) -> 1 | J27: =+SOIs!X28 -> Cartessa | L27: =+IF(INDEX('Master Ratings'!$D:$D, MATCH('Ratings by CLO'!$J27,'Master Ratings'!$B:$B,0),0)=0,"",INDEX('Master Ratings'!$D:$D, MATCH('Ratings by CLO'!$J27,'Master Ratings'!$B:$B,0),0)) | M27: =+IF(INDEX('Master Ratings'!$E:$E, MATCH('Ratings by CLO'!$J27,'Master Ratings'!$B:$B,0),0)=0,"",INDEX('Master Ratings'!$E:$E, MATCH('Ratings by CLO'!$J27,'Master Ratings'!$B:$B,0),0)) | O27: =+IF(INDEX('Master Ratings'!$G:$G, MATCH('Ratings by CLO'!$J27,'Master Ratings'!$B:$B,0),0)=0,"",INDEX('Master Ratings'!$G:$G, MATCH('Ratings by CLO'!$J27,'Master Ratings'!$B:$B,0),0)) -> B-* | P27: =+IF(INDEX('Master Ratings'!$H:$H, MATCH('Ratings by CLO'!$J27,'Master Ratings'!$B:$B,0),0)=0,"",INDEX('Master Ratings'!$H:$H, MATCH('Ratings by CLO'!$J27,'Master Ratings'!$B:$B,0),0)) -> Credit Estimate | Q27: =+IF(INDEX('Master Ratings'!$O:$O, MATCH('Ratings by CLO'!$J27,'Master Ratings'!$B:$B,0),0)=0,"",INDEX('Master Ratings'!$O:$O, MATCH('Ratings by CLO'!$J27,'Master Ratings'!$B:$B,0),0)) -> 45750 | S27: =+IF(INDEX('Master Ratings'!$L:$L, MATCH('Ratings by CLO'!$J27,'Master Ratings'!$B:$B,0),0)=0,"",INDEX('Master Ratings'!$L:$L, MATCH('Ratings by CLO'!$J27,'Master Ratings'!$B:$B,0),0)) -> B-* | T27: =+IF(INDEX('Master Ratings'!$M:$M, MATCH('Ratings by CLO'!$J27,'Master Ratings'!$B:$B,0),0)=0,"",INDEX('Master Ratings'!$M:$M, MATCH('Ratings by CLO'!$J27,'Master Ratings'!$B:$B,0),0)) -> Credit Estimate | U27: =+IF(INDEX('Master Ratings'!$P:$P, MATCH('Ratings by CLO'!$J27,'Master Ratings'!$B:$B,0),0)=0,"",INDEX('Master Ratings'!$P:$P, MATCH('Ratings by CLO'!$J27,'Master Ratings'!$B:$B,0),0)) -> 45107 | W27: =+IF(OR($P27=$W$1,$P27=$W$2),$Q27+365-TODAY(), "") -> 151 | X27: =+IF(OR($T27=$W$1,$T27=$W$2),$U27+365-TODAY(), "") -> -492 | Z27: =IF(AND(SUM(B27:H27)>=1,ISERROR(W27)),"X","") | AA27: =IF(AND(B27>1, ISERROR(X27)),"X","") | AB27: =+IFERROR(IF(W27<0,"X",""),"") | AC27: =+IFERROR(IF(AND(B27>0, X27<0),"X",""),"") -> X | AE27: =+IF(SUM(B27:H27)=0,"X","") | AG27: =IF(Z27="X",AG26+1,AG26) -> 0 | AH27: =IF(AA27="X",AH26+1,AH26) -> 1 | AI27: =IF(AB27="X",AI26+1,AI26) -> 7 | AJ27: =IF(AC27="X",AJ26+1,AJ26) -> 10
B28: =+COUNTIFS(SOIs!$D:$D, 'Ratings by CLO'!$J28) -> 4 | C28: =+COUNTIFS(SOIs!$G:$G, 'Ratings by CLO'!$J28) -> 1 | D28: =+COUNTIFS(SOIs!$J:$J, 'Ratings by CLO'!$J28) -> 1 | E28: =+COUNTIFS(SOIs!$M:$M, 'Ratings by CLO'!$J28) -> 1 | F28: =+COUNTIFS(SOIs!$P:$P, 'Ratings by CLO'!$J28) -> 1 | G28: =+COUNTIFS(SOIs!$S:$S, 'Ratings by CLO'!$J28) -> 1 | H28: =+COUNTIFS(SOIs!$V:$V, 'Ratings by CLO'!$J28) -> 1 | J28: =+SOIs!X29 -> Centauri Health | L28: =+IF(INDEX('Master Ratings'!$D:$D, MATCH('Ratings by CLO'!$J28,'Master Ratings'!$B:$B,0),0)=0,"",INDEX('Master Ratings'!$D:$D, MATCH('Ratings by CLO'!$J28,'Master Ratings'!$B:$B,0),0)) | M28: =+IF(INDEX('Master Ratings'!$E:$E, MATCH('Ratings by CLO'!$J28,'Master Ratings'!$B:$B,0),0)=0,"",INDEX('Master Ratings'!$E:$E, MATCH('Ratings by CLO'!$J28,'Master Ratings'!$B:$B,0),0)) | O28: =+IF(INDEX('Master Ratings'!$G:$G, MATCH('Ratings by CLO'!$J28,'Master Ratings'!$B:$B,0),0)=0,"",INDEX('Master Ratings'!$G:$G, MATCH('Ratings by CLO'!$J28,'Master Ratings'!$B:$B,0),0)) -> B-* | P28: =+IF(INDEX('Master Ratings'!$H:$H, MATCH('Ratings by CLO'!$J28,'Master Ratings'!$B:$B,0),0)=0,"",INDEX('Master Ratings'!$H:$H, MATCH('Ratings by CLO'!$J28,'Master Ratings'!$B:$B,0),0)) -> Credit Estimate | Q28: =+IF(INDEX('Master Ratings'!$O:$O, MATCH('Ratings by CLO'!$J28,'Master Ratings'!$B:$B,0),0)=0,"",INDEX('Master Ratings'!$O:$O, MATCH('Ratings by CLO'!$J28,'Master Ratings'!$B:$B,0),0)) -> 45693 | S28: =+IF(INDEX('Master Ratings'!$L:$L, MATCH('Ratings by CLO'!$J28,'Master Ratings'!$B:$B,0),0)=0,"",INDEX('Master Ratings'!$L:$L, MATCH('Ratings by CLO'!$J28,'Master Ratings'!$B:$B,0),0)) -> B* | T28: =+IF(INDEX('Master Ratings'!$M:$M, MATCH('Ratings by CLO'!$J28,'Master Ratings'!$B:$B,0),0)=0,"",INDEX('Master Ratings'!$M:$M, MATCH('Ratings by CLO'!$J28,'Master Ratings'!$B:$B,0),0)) -> Credit Estimate | U28: =+IF(INDEX('Master Ratings'!$P:$P, MATCH('Ratings by CLO'!$J28,'Master Ratings'!$B:$B,0),0)=0,"",INDEX('Master Ratings'!$P:$P, MATCH('Ratings by CLO'!$J28,'Master Ratings'!$B:$B,0),0)) -> 45121 | W28: =+IF(OR($P28=$W$1,$P28=$W$2),$Q28+365-TODAY(), "") -> 94 | X28: =+IF(OR($T28=$W$1,$T28=$W$2),$U28+365-TODAY(), "") -> -478 | Z28: =IF(AND(SUM(B28:H28)>=1,ISERROR(W28)),"X","") | AA28: =IF(AND(B28>1, ISERROR(X28)),"X","") | AB28: =+IFERROR(IF(W28<0,"X",""),"") | AC28: =+IFERROR(IF(AND(B28>0, X28<0),"X",""),"") -> X | AE28: =+IF(SUM(B28:H28)=0,"X","") | AG28: =IF(Z28="X",AG27+1,AG27) -> 0 | AH28: =IF(AA28="X",AH27+1,AH27) -> 1 | AI28: =IF(AB28="X",AI27+1,AI27) -> 7 | AJ28: =IF(AC28="X",AJ27+1,AJ27) -> 11
B29: =+COUNTIFS(SOIs!$D:$D, 'Ratings by CLO'!$J29) -> 0 | C29: =+COUNTIFS(SOIs!$G:$G, 'Ratings by CLO'!$J29) -> 0 | D29: =+COUNTIFS(SOIs!$J:$J, 'Ratings by CLO'!$J29) -> 0 | E29: =+COUNTIFS(SOIs!$M:$M, 'Ratings by CLO'!$J29) -> 0 | F29: =+COUNTIFS(SOIs!$P:$P, 'Ratings by CLO'!$J29) -> 1 | G29: =+COUNTIFS(SOIs!$S:$S, 'Ratings by CLO'!$J29) -> 0 | H29: =+COUNTIFS(SOIs!$V:$V, 'Ratings by CLO'!$J29) -> 0 | J29: =+SOIs!X30 -> Compex Legal | L29: =+IF(INDEX('Master Ratings'!$D:$D, MATCH('Ratings by CLO'!$J29,'Master Ratings'!$B:$B,0),0)=0,"",INDEX('Master Ratings'!$D:$D, MATCH('Ratings by CLO'!$J29,'Master Ratings'!$B:$B,0),0)) | M29: =+IF(INDEX('Master Ratings'!$E:$E, MATCH('Ratings by CLO'!$J29,'Master Ratings'!$B:$B,0),0)=0,"",INDEX('Master Ratings'!$E:$E, MATCH('Ratings by CLO'!$J29,'Master Ratings'!$B:$B,0),0)) | O29: =+IF(INDEX('Master Ratings'!$G:$G, MATCH('Ratings by CLO'!$J29,'Master Ratings'!$B:$B,0),0)=0,"",INDEX('Master Ratings'!$G:$G, MATCH('Ratings by CLO'!$J29,'Master Ratings'!$B:$B,0),0)) -> B-* | P29: =+IF(INDEX('Master Ratings'!$H:$H, MATCH('Ratings by CLO'!$J29,'Master Ratings'!$B:$B,0),0)=0,"",INDEX('Master Ratings'!$H:$H, MATCH('Ratings by CLO'!$J29,'Master Ratings'!$B:$B,0),0)) -> Credit Estimate | Q29: =+IF(INDEX('Master Ratings'!$O:$O, MATCH('Ratings by CLO'!$J29,'Master Ratings'!$B:$B,0),0)=0,"",INDEX('Master Ratings'!$O:$O, MATCH('Ratings by CLO'!$J29,'Master Ratings'!$B:$B,0),0)) -> 45623 | S29: =+IF(INDEX('Master Ratings'!$L:$L, MATCH('Ratings by CLO'!$J29,'Master Ratings'!$B:$B,0),0)=0,"",INDEX('Master Ratings'!$L:$L, MATCH('Ratings by CLO'!$J29,'Master Ratings'!$B:$B,0),0)) | T29: =+IF(INDEX('Master Ratings'!$M:$M, MATCH('Ratings by CLO'!$J29,'Master Ratings'!$B:$B,0),0)=0,"",INDEX('Master Ratings'!$M:$M, MATCH('Ratings by CLO'!$J29,'Master Ratings'!$B:$B,0),0)) | U29: =+IF(INDEX('Master Ratings'!$P:$P, MATCH('Ratings by CLO'!$J29,'Master Ratings'!$B:$B,0),0)=0,"",INDEX('Master Ratings'!$P:$P, MATCH('Ratings by CLO'!$J29,'Master Ratings'!$B:$B,0),0)) | W29: =+IF(OR($P29=$W$1,$P29=$W$2),$Q29+365-TODAY(), "") -> 24 | X29: =+IF(OR($T29=$W$1,$T29=$W$2),$U29+365-TODAY(), "") | Z29: =IF(AND(SUM(B29:H29)>=1,ISERROR(W29)),"X","") | AA29: =IF(AND(B29>1, ISERROR(X29)),"X","") | AB29: =+IFERROR(IF(W29<0,"X",""),"") | AC29: =+IFERROR(IF(AND(B29>0, X29<0),"X",""),"") | AE29: =+IF(SUM(B29:H29)=0,"X","") | AG29: =IF(Z29="X",AG28+1,AG28) -> 0 | AH29: =IF(AA29="X",AH28+1,AH28) -> 1 | AI29: =IF(AB29="X",AI28+1,AI28) -> 7 | AJ29: =IF(AC29="X",AJ28+1,AJ28) -> 11
B30: =+COUNTIFS(SOIs!$D:$D, 'Ratings by CLO'!$J30) -> 4 | C30: =+COUNTIFS(SOIs!$G:$G, 'Ratings by CLO'!$J30) -> 1 | D30: =+COUNTIFS(SOIs!$J:$J, 'Ratings by CLO'!$J30) -> 1 | E30: =+COUNTIFS(SOIs!$M:$M, 'Ratings by CLO'!$J30) -> 1 | F30: =+COUNTIFS(SOIs!$P:$P, 'Ratings by CLO'!$J30) -> 1 | G30: =+COUNTIFS(SOIs!$S:$S, 'Ratings by CLO'!$J30) -> 0 | H30: =+COUNTIFS(SOIs!$V:$V, 'Ratings by CLO'!$J30) -> 1 | J30: =+SOIs!X31 -> Connatix | L30: =+IF(INDEX('Master Ratings'!$D:$D, MATCH('Ratings by CLO'!$J30,'Master Ratings'!$B:$B,0),0)=0,"",INDEX('Master Ratings'!$D:$D, MATCH('Ratings by CLO'!$J30,'Master Ratings'!$B:$B,0),0)) | M30: =+IF(INDEX('Master Ratings'!$E:$E, MATCH('Ratings by CLO'!$J30,'Master Ratings'!$B:$B,0),0)=0,"",INDEX('Master Ratings'!$E:$E, MATCH('Ratings by CLO'!$J30,'Master Ratings'!$B:$B,0),0)) | O30: =+IF(INDEX('Master Ratings'!$G:$G, MATCH('Ratings by CLO'!$J30,'Master Ratings'!$B:$B,0),0)=0,"",INDEX('Master Ratings'!$G:$G, MATCH('Ratings by CLO'!$J30,'Master Ratings'!$B:$B,0),0)) -> B-* | P30: =+IF(INDEX('Master Ratings'!$H:$H, MATCH('Ratings by CLO'!$J30,'Master Ratings'!$B:$B,0),0)=0,"",INDEX('Master Ratings'!$H:$H, MATCH('Ratings by CLO'!$J30,'Master Ratings'!$B:$B,0),0)) -> Credit Estimate | Q30: =+IF(INDEX('Master Ratings'!$O:$O, MATCH('Ratings by CLO'!$J30,'Master Ratings'!$B:$B,0),0)=0,"",INDEX('Master Ratings'!$O:$O, MATCH('Ratings by CLO'!$J30,'Master Ratings'!$B:$B,0),0)) -> 45483 | S30: =+IF(INDEX('Master Ratings'!$L:$L, MATCH('Ratings by CLO'!$J30,'Master Ratings'!$B:$B,0),0)=0,"",INDEX('Master Ratings'!$L:$L, MATCH('Ratings by CLO'!$J30,'Master Ratings'!$B:$B,0),0)) -> B-* | T30: =+IF(INDEX('Master Ratings'!$M:$M, MATCH('Ratings by CLO'!$J30,'Master Ratings'!$B:$B,0),0)=0,"",INDEX('Master Ratings'!$M:$M, MATCH('Ratings by CLO'!$J30,'Master Ratings'!$B:$B,0),0)) -> Credit Estimate | U30: =+IF(INDEX('Master Ratings'!$P:$P, MATCH('Ratings by CLO'!$J30,'Master Ratings'!$B:$B,0),0)=0,"",INDEX('Master Ratings'!$P:$P, MATCH('Ratings by CLO'!$J30,'Master Ratings'!$B:$B,0),0)) -> 12.8.2023 | W30: =+IF(OR($P30=$W$1,$P30=$W$2),$Q30+365-TODAY(), "") -> -116 | X30: =+IF(OR($T30=$W$1,$T30=$W$2),$U30+365-TODAY(), "") -> #VALUE! | Z30: =IF(AND(SUM(B30:H30)>=1,ISERROR(W30)),"X","") | AA30: =IF(AND(B30>1, ISERROR(X30)),"X","") -> X | AB30: =+IFERROR(IF(W30<0,"X",""),"") -> X | AC30: =+IFERROR(IF(AND(B30>0, X30<0),"X",""),"") | AE30: =+IF(SUM(B30:H30)=0,"X","") | AG30: =IF(Z30="X",AG29+1,AG29) -> 0 | AH30: =IF(AA30="X",AH29+1,AH29) -> 2 | AI30: =IF(AB30="X",AI29+1,AI29) -> 8 | AJ30: =IF(AC30="X",AJ29+1,AJ29) -> 11
B31: =+COUNTIFS(SOIs!$D:$D, 'Ratings by CLO'!$J31) -> 3 | C31: =+COUNTIFS(SOIs!$G:$G, 'Ratings by CLO'!$J31) -> 1 | D31: =+COUNTIFS(SOIs!$J:$J, 'Ratings by CLO'!$J31) -> 0 | E31: =+COUNTIFS(SOIs!$M:$M, 'Ratings by CLO'!$J31) -> 0 | F31: =+COUNTIFS(SOIs!$P:$P, 'Ratings by CLO'!$J31) -> 1 | G31: =+COUNTIFS(SOIs!$S:$S, 'Ratings by CLO'!$J31) -> 1 | H31: =+COUNTIFS(SOIs!$V:$V, 'Ratings by CLO'!$J31) -> 1 | J31: =+SOIs!X32 -> Consilio | L31: =+IF(INDEX('Master Ratings'!$D:$D, MATCH('Ratings by CLO'!$J31,'Master Ratings'!$B:$B,0),0)=0,"",INDEX('Master Ratings'!$D:$D, MATCH('Ratings by CLO'!$J31,'Master Ratings'!$B:$B,0),0)) -> B3 | M31: =+IF(INDEX('Master Ratings'!$E:$E, MATCH('Ratings by CLO'!$J31,'Master Ratings'!$B:$B,0),0)=0,"",INDEX('Master Ratings'!$E:$E, MATCH('Ratings by CLO'!$J31,'Master Ratings'!$B:$B,0),0)) -> Rating (Public) | O31: =+IF(INDEX('Master Ratings'!$G:$G, MATCH('Ratings by CLO'!$J31,'Master Ratings'!$B:$B,0),0)=0,"",INDEX('Master Ratings'!$G:$G, MATCH('Ratings by CLO'!$J31,'Master Ratings'!$B:$B,0),0)) -> B- | P31: =+IF(INDEX('Master Ratings'!$H:$H, MATCH('Ratings by CLO'!$J31,'Master Ratings'!$B:$B,0),0)=0,"",INDEX('Master Ratings'!$H:$H, MATCH('Ratings by CLO'!$J31,'Master Ratings'!$B:$B,0),0)) -> Rating (Public) | Q31: =+IF(INDEX('Master Ratings'!$O:$O, MATCH('Ratings by CLO'!$J31,'Master Ratings'!$B:$B,0),0)=0,"",INDEX('Master Ratings'!$O:$O, MATCH('Ratings by CLO'!$J31,'Master Ratings'!$B:$B,0),0)) | S31: =+IF(INDEX('Master Ratings'!$L:$L, MATCH('Ratings by CLO'!$J31,'Master Ratings'!$B:$B,0),0)=0,"",INDEX('Master Ratings'!$L:$L, MATCH('Ratings by CLO'!$J31,'Master Ratings'!$B:$B,0),0)) | T31: =+IF(INDEX('Master Ratings'!$M:$M, MATCH('Ratings by CLO'!$J31,'Master Ratings'!$B:$B,0),0)=0,"",INDEX('Master Ratings'!$M:$M, MATCH('Ratings by CLO'!$J31,'Master Ratings'!$B:$B,0),0)) | U31: =+IF(INDEX('Master Ratings'!$P:$P, MATCH('Ratings by CLO'!$J31,'Master Ratings'!$B:$B,0),0)=0,"",INDEX('Master Ratings'!$P:$P, MATCH('Ratings by CLO'!$J31,'Master Ratings'!$B:$B,0),0)) | W31: =+IF(OR($P31=$W$1,$P31=$W$2),$Q31+365-TODAY(), "") | X31: =+IF(OR($T31=$W$1,$T31=$W$2),$U31+365-TODAY(), "") | Z31: =IF(AND(SUM(B31:H31)>=1,ISERROR(W31)),"X","") | AA31: =IF(AND(B31>1, ISERROR(X31)),"X","") | AB31: =+IFERROR(IF(W31<0,"X",""),"") | AC31: =+IFERROR(IF(AND(B31>0, X31<0),"X",""),"") | AE31: =+IF(SUM(B31:H31)=0,"X","") | AG31: =IF(Z31="X",AG30+1,AG30) -> 0 | AH31: =IF(AA31="X",AH30+1,AH30) -> 2 | AI31: =IF(AB31="X",AI30+1,AI30) -> 8 | AJ31: =IF(AC31="X",AJ30+1,AJ30) -> 11
B32: =+COUNTIFS(SOIs!$D:$D, 'Ratings by CLO'!$J32) -> 1 | C32: =+COUNTIFS(SOIs!$G:$G, 'Ratings by CLO'!$J32) -> 0 | D32: =+COUNTIFS(SOIs!$J:$J, 'Ratings by CLO'!$J32) -> 1 | E32: =+COUNTIFS(SOIs!$M:$M, 'Ratings by CLO'!$J32) -> 0 | F32: =+COUNTIFS(SOIs!$P:$P, 'Ratings by CLO'!$J32) -> 1 | G32: =+COUNTIFS(SOIs!$S:$S, 'Ratings by CLO'!$J32) -> 0 | H32: =+COUNTIFS(SOIs!$V:$V, 'Ratings by CLO'!$J32) -> 0 | J32: =+SOIs!X33 -> Convergint | L32: =+IF(INDEX('Master Ratings'!$D:$D, MATCH('Ratings by CLO'!$J32,'Master Ratings'!$B:$B,0),0)=0,"",INDEX('Master Ratings'!$D:$D, MATCH('Ratings by CLO'!$J32,'Master Ratings'!$B:$B,0),0)) | M32: =+IF(INDEX('Master Ratings'!$E:$E, MATCH('Ratings by CLO'!$J32,'Master Ratings'!$B:$B,0),0)=0,"",INDEX('Master Ratings'!$E:$E, MATCH('Ratings by CLO'!$J32,'Master Ratings'!$B:$B,0),0)) | O32: =+IF(INDEX('Master Ratings'!$G:$G, MATCH('Ratings by CLO'!$J32,'Master Ratings'!$B:$B,0),0)=0,"",INDEX('Master Ratings'!$G:$G, MATCH('Ratings by CLO'!$J32,'Master Ratings'!$B:$B,0),0)) -> B- | P32: =+IF(INDEX('Master Ratings'!$H:$H, MATCH('Ratings by CLO'!$J32,'Master Ratings'!$B:$B,0),0)=0,"",INDEX('Master Ratings'!$H:$H, MATCH('Ratings by CLO'!$J32,'Master Ratings'!$B:$B,0),0)) -> Rating (Public) | Q32: =+IF(INDEX('Master Ratings'!$O:$O, MATCH('Ratings by CLO'!$J32,'Master Ratings'!$B:$B,0),0)=0,"",INDEX('Master Ratings'!$O:$O, MATCH('Ratings by CLO'!$J32,'Master Ratings'!$B:$B,0),0)) | S32: =+IF(INDEX('Master Ratings'!$L:$L, MATCH('Ratings by CLO'!$J32,'Master Ratings'!$B:$B,0),0)=0,"",INDEX('Master Ratings'!$L:$L, MATCH('Ratings by CLO'!$J32,'Master Ratings'!$B:$B,0),0)) | T32: =+IF(INDEX('Master Ratings'!$M:$M, MATCH('Ratings by CLO'!$J32,'Master Ratings'!$B:$B,0),0)=0,"",INDEX('Master Ratings'!$M:$M, MATCH('Ratings by CLO'!$J32,'Master Ratings'!$B:$B,0),0)) | U32: =+IF(INDEX('Master Ratings'!$P:$P, MATCH('Ratings by CLO'!$J32,'Master Ratings'!$B:$B,0),0)=0,"",INDEX('Master Ratings'!$P:$P, MATCH('Ratings by CLO'!$J32,'Master Ratings'!$B:$B,0),0)) | W32: =+IF(OR($P32=$W$1,$P32=$W$2),$Q32+365-TODAY(), "") | X32: =+IF(OR($T32=$W$1,$T32=$W$2),$U32+365-TODAY(), "") | Z32: =IF(AND(SUM(B32:H32)>=1,ISERROR(W32)),"X","") | AA32: =IF(AND(B32>1, ISERROR(X32)),"X","") | AB32: =+IFERROR(IF(W32<0,"X",""),"") | AC32: =+IFERROR(IF(AND(B32>0, X32<0),"X",""),"") | AE32: =+IF(SUM(B32:H32)=0,"X","") | AG32: =IF(Z32="X",AG31+1,AG31) -> 0 | AH32: =IF(AA32="X",AH31+1,AH31) -> 2 | AI32: =IF(AB32="X",AI31+1,AI31) -> 8 | AJ32: =IF(AC32="X",AJ31+1,AJ31) -> 11
B33: =+COUNTIFS(SOIs!$D:$D, 'Ratings by CLO'!$J33) -> 3 | C33: =+COUNTIFS(SOIs!$G:$G, 'Ratings by CLO'!$J33) -> 0 | D33: =+COUNTIFS(SOIs!$J:$J, 'Ratings by CLO'!$J33) -> 1 | E33: =+COUNTIFS(SOIs!$M:$M, 'Ratings by CLO'!$J33) -> 0 | F33: =+COUNTIFS(SOIs!$P:$P, 'Ratings by CLO'!$J33) -> 0 | G33: =+COUNTIFS(SOIs!$S:$S, 'Ratings by CLO'!$J33) -> 1 | H33: =+COUNTIFS(SOIs!$V:$V, 'Ratings by CLO'!$J33) -> 1 | J33: =+SOIs!X34 -> Crane 1 | L33: =+IF(INDEX('Master Ratings'!$D:$D, MATCH('Ratings by CLO'!$J33,'Master Ratings'!$B:$B,0),0)=0,"",INDEX('Master Ratings'!$D:$D, MATCH('Ratings by CLO'!$J33,'Master Ratings'!$B:$B,0),0)) | M33: =+IF(INDEX('Master Ratings'!$E:$E, MATCH('Ratings by CLO'!$J33,'Master Ratings'!$B:$B,0),0)=0,"",INDEX('Master Ratings'!$E:$E, MATCH('Ratings by CLO'!$J33,'Master Ratings'!$B:$B,0),0)) | O33: =+IF(INDEX('Master Ratings'!$G:$G, MATCH('Ratings by CLO'!$J33,'Master Ratings'!$B:$B,0),0)=0,"",INDEX('Master Ratings'!$G:$G, MATCH('Ratings by CLO'!$J33,'Master Ratings'!$B:$B,0),0)) -> B-* | P33: =+IF(INDEX('Master Ratings'!$H:$H, MATCH('Ratings by CLO'!$J33,'Master Ratings'!$B:$B,0),0)=0,"",INDEX('Master Ratings'!$H:$H, MATCH('Ratings by CLO'!$J33,'Master Ratings'!$B:$B,0),0)) -> Credit Estimate | Q33: =+IF(INDEX('Master Ratings'!$O:$O, MATCH('Ratings by CLO'!$J33,'Master Ratings'!$B:$B,0),0)=0,"",INDEX('Master Ratings'!$O:$O, MATCH('Ratings by CLO'!$J33,'Master Ratings'!$B:$B,0),0)) -> 45707 | S33: =+IF(INDEX('Master Ratings'!$L:$L, MATCH('Ratings by CLO'!$J33,'Master Ratings'!$B:$B,0),0)=0,"",INDEX('Master Ratings'!$L:$L, MATCH('Ratings by CLO'!$J33,'Master Ratings'!$B:$B,0),0)) -> B-* | T33: =+IF(INDEX('Master Ratings'!$M:$M, MATCH('Ratings by CLO'!$J33,'Master Ratings'!$B:$B,0),0)=0,"",INDEX('Master Ratings'!$M:$M, MATCH('Ratings by CLO'!$J33,'Master Ratings'!$B:$B,0),0)) -> Credit Estimate | U33: =+IF(INDEX('Master Ratings'!$P:$P, MATCH('Ratings by CLO'!$J33,'Master Ratings'!$B:$B,0),0)=0,"",INDEX('Master Ratings'!$P:$P, MATCH('Ratings by CLO'!$J33,'Master Ratings'!$B:$B,0),0)) -> 45345 | W33: =+IF(OR($P33=$W$1,$P33=$W$2),$Q33+365-TODAY(), "") -> 108 | X33: =+IF(OR($T33=$W$1,$T33=$W$2),$U33+365-TODAY(), "") -> -254 | Z33: =IF(AND(SUM(B33:H33)>=1,ISERROR(W33)),"X","") | AA33: =IF(AND(B33>1, ISERROR(X33)),"X","") | AB33: =+IFERROR(IF(W33<0,"X",""),"") | AC33: =+IFERROR(IF(AND(B33>0, X33<0),"X",""),"") -> X | AE33: =+IF(SUM(B33:H33)=0,"X","") | AG33: =IF(Z33="X",AG32+1,AG32) -> 0 | AH33: =IF(AA33="X",AH32+1,AH32) -> 2 | AI33: =IF(AB33="X",AI32+1,AI32) -> 8 | AJ33: =IF(AC33="X",AJ32+1,AJ32) -> 12
B34: =+COUNTIFS(SOIs!$D:$D, 'Ratings by CLO'!$J34) -> 2 | C34: =+COUNTIFS(SOIs!$G:$G, 'Ratings by CLO'!$J34) -> 1 | D34: =+COUNTIFS(SOIs!$J:$J, 'Ratings by CLO'!$J34) -> 1 | E34: =+COUNTIFS(SOIs!$M:$M, 'Ratings by CLO'!$J34) -> 1 | F34: =+COUNTIFS(SOIs!$P:$P, 'Ratings by CLO'!$J34) -> 1 | G34: =+COUNTIFS(SOIs!$S:$S, 'Ratings by CLO'!$J34) -> 1 | H34: =+COUNTIFS(SOIs!$V:$V, 'Ratings by CLO'!$J34) -> 0 | J34: =+SOIs!X35 -> Digital Room | L34: =+IF(INDEX('Master Ratings'!$D:$D, MATCH('Ratings by CLO'!$J34,'Master Ratings'!$B:$B,0),0)=0,"",INDEX('Master Ratings'!$D:$D, MATCH('Ratings by CLO'!$J34,'Master Ratings'!$B:$B,0),0)) -> B3 | M34: =+IF(INDEX('Master Ratings'!$E:$E, MATCH('Ratings by CLO'!$J34,'Master Ratings'!$B:$B,0),0)=0,"",INDEX('Master Ratings'!$E:$E, MATCH('Ratings by CLO'!$J34,'Master Ratings'!$B:$B,0),0)) -> Rating (Public) | O34: =+IF(INDEX('Master Ratings'!$G:$G, MATCH('Ratings by CLO'!$J34,'Master Ratings'!$B:$B,0),0)=0,"",INDEX('Master Ratings'!$G:$G, MATCH('Ratings by CLO'!$J34,'Master Ratings'!$B:$B,0),0)) -> B- | P34: =+IF(INDEX('Master Ratings'!$H:$H, MATCH('Ratings by CLO'!$J34,'Master Ratings'!$B:$B,0),0)=0,"",INDEX('Master Ratings'!$H:$H, MATCH('Ratings by CLO'!$J34,'Master Ratings'!$B:$B,0),0)) -> Rating (Public) | Q34: =+IF(INDEX('Master Ratings'!$O:$O, MATCH('Ratings by CLO'!$J34,'Master Ratings'!$B:$B,0),0)=0,"",INDEX('Master Ratings'!$O:$O, MATCH('Ratings by CLO'!$J34,'Master Ratings'!$B:$B,0),0)) | S34: =+IF(INDEX('Master Ratings'!$L:$L, MATCH('Ratings by CLO'!$J34,'Master Ratings'!$B:$B,0),0)=0,"",INDEX('Master Ratings'!$L:$L, MATCH('Ratings by CLO'!$J34,'Master Ratings'!$B:$B,0),0)) | T34: =+IF(INDEX('Master Ratings'!$M:$M, MATCH('Ratings by CLO'!$J34,'Master Ratings'!$B:$B,0),0)=0,"",INDEX('Master Ratings'!$M:$M, MATCH('Ratings by CLO'!$J34,'Master Ratings'!$B:$B,0),0)) | U34: =+IF(INDEX('Master Ratings'!$P:$P, MATCH('Ratings by CLO'!$J34,'Master Ratings'!$B:$B,0),0)=0,"",INDEX('Master Ratings'!$P:$P, MATCH('Ratings by CLO'!$J34,'Master Ratings'!$B:$B,0),0)) | W34: =+IF(OR($P34=$W$1,$P34=$W$2),$Q34+365-TODAY(), "") | X34: =+IF(OR($T34=$W$1,$T34=$W$2),$U34+365-TODAY(), "") | Z34: =IF(AND(SUM(B34:H34)>=1,ISERROR(W34)),"X","") | AA34: =IF(AND(B34>1, ISERROR(X34)),"X","") | AB34: =+IFERROR(IF(W34<0,"X",""),"") | AC34: =+IFERROR(IF(AND(B34>0, X34<0),"X",""),"") | AE34: =+IF(SUM(B34:H34)=0,"X","") | AG34: =IF(Z34="X",AG33+1,AG33) -> 0 | AH34: =IF(AA34="X",AH33+1,AH33) -> 2 | AI34: =IF(AB34="X",AI33+1,AI33) -> 8 | AJ34: =IF(AC34="X",AJ33+1,AJ33) -> 12
B35: =+COUNTIFS(SOIs!$D:$D, 'Ratings by CLO'!$J35) -> 4 | C35: =+COUNTIFS(SOIs!$G:$G, 'Ratings by CLO'!$J35) -> 1 | D35: =+COUNTIFS(SOIs!$J:$J, 'Ratings by CLO'!$J35) -> 1 | E35: =+COUNTIFS(SOIs!$M:$M, 'Ratings by CLO'!$J35) -> 1 | F35: =+COUNTIFS(SOIs!$P:$P, 'Ratings by CLO'!$J35) -> 1 | G35: =+COUNTIFS(SOIs!$S:$S, 'Ratings by CLO'!$J35) -> 1 | H35: =+COUNTIFS(SOIs!$V:$V, 'Ratings by CLO'!$J35) -> 1 | J35: =+SOIs!X36 -> Dr. Scholl's | L35: =+IF(INDEX('Master Ratings'!$D:$D, MATCH('Ratings by CLO'!$J35,'Master Ratings'!$B:$B,0),0)=0,"",INDEX('Master Ratings'!$D:$D, MATCH('Ratings by CLO'!$J35,'Master Ratings'!$B:$B,0),0)) | M35: =+IF(INDEX('Master Ratings'!$E:$E, MATCH('Ratings by CLO'!$J35,'Master Ratings'!$B:$B,0),0)=0,"",INDEX('Master Ratings'!$E:$E, MATCH('Ratings by CLO'!$J35,'Master Ratings'!$B:$B,0),0)) | O35: =+IF(INDEX('Master Ratings'!$G:$G, MATCH('Ratings by CLO'!$J35,'Master Ratings'!$B:$B,0),0)=0,"",INDEX('Master Ratings'!$G:$G, MATCH('Ratings by CLO'!$J35,'Master Ratings'!$B:$B,0),0)) -> B-* | P35: =+IF(INDEX('Master Ratings'!$H:$H, MATCH('Ratings by CLO'!$J35,'Master Ratings'!$B:$B,0),0)=0,"",INDEX('Master Ratings'!$H:$H, MATCH('Ratings by CLO'!$J35,'Master Ratings'!$B:$B,0),0)) -> Rating (Private) | Q35: =+IF(INDEX('Master Ratings'!$O:$O, MATCH('Ratings by CLO'!$J35,'Master Ratings'!$B:$B,0),0)=0,"",INDEX('Master Ratings'!$O:$O, MATCH('Ratings by CLO'!$J35,'Master Ratings'!$B:$B,0),0)) -> 45623 | S35: =+IF(INDEX('Master Ratings'!$L:$L, MATCH('Ratings by CLO'!$J35,'Master Ratings'!$B:$B,0),0)=0,"",INDEX('Master Ratings'!$L:$L, MATCH('Ratings by CLO'!$J35,'Master Ratings'!$B:$B,0),0)) -> B* | T35: =+IF(INDEX('Master Ratings'!$M:$M, MATCH('Ratings by CLO'!$J35,'Master Ratings'!$B:$B,0),0)=0,"",INDEX('Master Ratings'!$M:$M, MATCH('Ratings by CLO'!$J35,'Master Ratings'!$B:$B,0),0)) -> Credit Estimate | U35: =+IF(INDEX('Master Ratings'!$P:$P, MATCH('Ratings by CLO'!$J35,'Master Ratings'!$B:$B,0),0)=0,"",INDEX('Master Ratings'!$P:$P, MATCH('Ratings by CLO'!$J35,'Master Ratings'!$B:$B,0),0)) -> 45398 | W35: =+IF(OR($P35=$W$1,$P35=$W$2),$Q35+365-TODAY(), "") -> 24 | X35: =+IF(OR($T35=$W$1,$T35=$W$2),$U35+365-TODAY(), "") -> -201 | Z35: =IF(AND(SUM(B35:H35)>=1,ISERROR(W35)),"X","") | AA35: =IF(AND(B35>1, ISERROR(X35)),"X","") | AB35: =+IFERROR(IF(W35<0,"X",""),"") | AC35: =+IFERROR(IF(AND(B35>0, X35<0),"X",""),"") -> X | AE35: =+IF(SUM(B35:H35)=0,"X","") | AG35: =IF(Z35="X",AG34+1,AG34) -> 0 | AH35: =IF(AA35="X",AH34+1,AH34) -> 2 | AI35: =IF(AB35="X",AI34+1,AI34) -> 8 | AJ35: =IF(AC35="X",AJ34+1,AJ34) -> 13
B36: =+COUNTIFS(SOIs!$D:$D, 'Ratings by CLO'!$J36) -> 2 | C36: =+COUNTIFS(SOIs!$G:$G, 'Ratings by CLO'!$J36) -> 1 | D36: =+COUNTIFS(SOIs!$J:$J, 'Ratings by CLO'!$J36) -> 1 | E36: =+COUNTIFS(SOIs!$M:$M, 'Ratings by CLO'!$J36) -> 1 | F36: =+COUNTIFS(SOIs!$P:$P, 'Ratings by CLO'!$J36) -> 1 | G36: =+COUNTIFS(SOIs!$S:$S, 'Ratings by CLO'!$J36) -> 1 | H36: =+COUNTIFS(SOIs!$V:$V, 'Ratings by CLO'!$J36) -> 1 | J36: =+SOIs!X37 -> Dr. Squatch | L36: =+IF(INDEX('Master Ratings'!$D:$D, MATCH('Ratings by CLO'!$J36,'Master Ratings'!$B:$B,0),0)=0,"",INDEX('Master Ratings'!$D:$D, MATCH('Ratings by CLO'!$J36,'Master Ratings'!$B:$B,0),0)) | M36: =+IF(INDEX('Master Ratings'!$E:$E, MATCH('Ratings by CLO'!$J36,'Master Ratings'!$B:$B,0),0)=0,"",INDEX('Master Ratings'!$E:$E, MATCH('Ratings by CLO'!$J36,'Master Ratings'!$B:$B,0),0)) | O36: =+IF(INDEX('Master Ratings'!$G:$G, MATCH('Ratings by CLO'!$J36,'Master Ratings'!$B:$B,0),0)=0,"",INDEX('Master Ratings'!$G:$G, MATCH('Ratings by CLO'!$J36,'Master Ratings'!$B:$B,0),0)) -> B-* | P36: =+IF(INDEX('Master Ratings'!$H:$H, MATCH('Ratings by CLO'!$J36,'Master Ratings'!$B:$B,0),0)=0,"",INDEX('Master Ratings'!$H:$H, MATCH('Ratings by CLO'!$J36,'Master Ratings'!$B:$B,0),0)) -> Credit Estimate | Q36: =+IF(INDEX('Master Ratings'!$O:$O, MATCH('Ratings by CLO'!$J36,'Master Ratings'!$B:$B,0),0)=0,"",INDEX('Master Ratings'!$O:$O, MATCH('Ratings by CLO'!$J36,'Master Ratings'!$B:$B,0),0)) -> 45660 | S36: =+IF(INDEX('Master Ratings'!$L:$L, MATCH('Ratings by CLO'!$J36,'Master Ratings'!$B:$B,0),0)=0,"",INDEX('Master Ratings'!$L:$L, MATCH('Ratings by CLO'!$J36,'Master Ratings'!$B:$B,0),0)) -> B* | T36: =+IF(INDEX('Master Ratings'!$M:$M, MATCH('Ratings by CLO'!$J36,'Master Ratings'!$B:$B,0),0)=0,"",INDEX('Master Ratings'!$M:$M, MATCH('Ratings by CLO'!$J36,'Master Ratings'!$B:$B,0),0)) -> Credit Estimate | U36: =+IF(INDEX('Master Ratings'!$P:$P, MATCH('Ratings by CLO'!$J36,'Master Ratings'!$B:$B,0),0)=0,"",INDEX('Master Ratings'!$P:$P, MATCH('Ratings by CLO'!$J36,'Master Ratings'!$B:$B,0),0)) -> 45324 | W36: =+IF(OR($P36=$W$1,$P36=$W$2),$Q36+365-TODAY(), "") -> 61 | X36: =+IF(OR($T36=$W$1,$T36=$W$2),$U36+365-TODAY(), "") -> -275 | Z36: =IF(AND(SUM(B36:H36)>=1,ISERROR(W36)),"X","") | AA36: =IF(AND(B36>1, ISERROR(X36)),"X","") | AB36: =+IFERROR(IF(W36<0,"X",""),"") | AC36: =+IFERROR(IF(AND(B36>0, X36<0),"X",""),"") -> X | AE36: =+IF(SUM(B36:H36)=0,"X","") | AG36: =IF(Z36="X",AG35+1,AG35) -> 0 | AH36: =IF(AA36="X",AH35+1,AH35) -> 2 | AI36: =IF(AB36="X",AI35+1,AI35) -> 8 | AJ36: =IF(AC36="X",AJ35+1,AJ35) -> 14
B37: =+COUNTIFS(SOIs!$D:$D, 'Ratings by CLO'!$J37) -> 0 | C37: =+COUNTIFS(SOIs!$G:$G, 'Ratings by CLO'!$J37) -> 0 | D37: =+COUNTIFS(SOIs!$J:$J, 'Ratings by CLO'!$J37) -> 0 | E37: =+COUNTIFS(SOIs!$M:$M, 'Ratings by CLO'!$J37) -> 0 | F37: =+COUNTIFS(SOIs!$P:$P, 'Ratings by CLO'!$J37) -> 1 | G37: =+COUNTIFS(SOIs!$S:$S, 'Ratings by CLO'!$J37) -> 0 | H37: =+COUNTIFS(SOIs!$V:$V, 'Ratings by CLO'!$J37) -> 0 | J37: =+SOIs!X38 -> Edelman | L37: =+IF(INDEX('Master Ratings'!$D:$D, MATCH('Ratings by CLO'!$J37,'Master Ratings'!$B:$B,0),0)=0,"",INDEX('Master Ratings'!$D:$D, MATCH('Ratings by CLO'!$J37,'Master Ratings'!$B:$B,0),0)) -> #N/A | M37: =+IF(INDEX('Master Ratings'!$E:$E, MATCH('Ratings by CLO'!$J37,'Master Ratings'!$B:$B,0),0)=0,"",INDEX('Master Ratings'!$E:$E, MATCH('Ratings by CLO'!$J37,'Master Ratings'!$B:$B,0),0)) -> #N/A | O37: =+IF(INDEX('Master Ratings'!$G:$G, MATCH('Ratings by CLO'!$J37,'Master Ratings'!$B:$B,0),0)=0,"",INDEX('Master Ratings'!$G:$G, MATCH('Ratings by CLO'!$J37,'Master Ratings'!$B:$B,0),0)) -> #N/A | P37: =+IF(INDEX('Master Ratings'!$H:$H, MATCH('Ratings by CLO'!$J37,'Master Ratings'!$B:$B,0),0)=0,"",INDEX('Master Ratings'!$H:$H, MATCH('Ratings by CLO'!$J37,'Master Ratings'!$B:$B,0),0)) -> #N/A | Q37: =+IF(INDEX('Master Ratings'!$O:$O, MATCH('Ratings by CLO'!$J37,'Master Ratings'!$B:$B,0),0)=0,"",INDEX('Master Ratings'!$O:$O, MATCH('Ratings by CLO'!$J37,'Master Ratings'!$B:$B,0),0)) -> #N/A | S37: =+IF(INDEX('Master Ratings'!$L:$L, MATCH('Ratings by CLO'!$J37,'Master Ratings'!$B:$B,0),0)=0,"",INDEX('Master Ratings'!$L:$L, MATCH('Ratings by CLO'!$J37,'Master Ratings'!$B:$B,0),0)) -> #N/A | T37: =+IF(INDEX('Master Ratings'!$M:$M, MATCH('Ratings by CLO'!$J37,'Master Ratings'!$B:$B,0),0)=0,"",INDEX('Master Ratings'!$M:$M, MATCH('Ratings by CLO'!$J37,'Master Ratings'!$B:$B,0),0)) -> #N/A | U37: =+IF(INDEX('Master Ratings'!$P:$P, MATCH('Ratings by CLO'!$J37,'Master Ratings'!$B:$B,0),0)=0,"",INDEX('Master Ratings'!$P:$P, MATCH('Ratings by CLO'!$J37,'Master Ratings'!$B:$B,0),0)) -> #N/A | W37: =+IF(OR($P37=$W$1,$P37=$W$2),$Q37+365-TODAY(), "") -> #N/A | X37: =+IF(OR($T37=$W$1,$T37=$W$2),$U37+365-TODAY(), "") -> #N/A | Z37: =IF(AND(SUM(B37:H37)>=1,ISERROR(W37)),"X","") -> X | AA37: =IF(AND(B37>1, ISERROR(X37)),"X","") | AB37: =+IFERROR(IF(W37<0,"X",""),"") | AC37: =+IFERROR(IF(AND(B37>0, X37<0),"X",""),"") | AE37: =+IF(SUM(B37:H37)=0,"X","") | AG37: =IF(Z37="X",AG36+1,AG36) -> 1 | AH37: =IF(AA37="X",AH36+1,AH36) -> 2 | AI37: =IF(AB37="X",AI36+1,AI36) -> 8 | AJ37: =IF(AC37="X",AJ36+1,AJ36) -> 14
B38: =+COUNTIFS(SOIs!$D:$D, 'Ratings by CLO'!$J38) -> 0 | C38: =+COUNTIFS(SOIs!$G:$G, 'Ratings by CLO'!$J38) -> 0 | D38: =+COUNTIFS(SOIs!$J:$J, 'Ratings by CLO'!$J38) -> 0 | E38: =+COUNTIFS(SOIs!$M:$M, 'Ratings by CLO'!$J38) -> 0 | F38: =+COUNTIFS(SOIs!$P:$P, 'Ratings by CLO'!$J38) -> 1 | G38: =+COUNTIFS(SOIs!$S:$S, 'Ratings by CLO'!$J38) -> 1 | H38: =+COUNTIFS(SOIs!$V:$V, 'Ratings by CLO'!$J38) -> 1 | J38: =+SOIs!X39 -> Electro Rent | L38: =+IF(INDEX('Master Ratings'!$D:$D, MATCH('Ratings by CLO'!$J38,'Master Ratings'!$B:$B,0),0)=0,"",INDEX('Master Ratings'!$D:$D, MATCH('Ratings by CLO'!$J38,'Master Ratings'!$B:$B,0),0)) -> #N/A | M38: =+IF(INDEX('Master Ratings'!$E:$E, MATCH('Ratings by CLO'!$J38,'Master Ratings'!$B:$B,0),0)=0,"",INDEX('Master Ratings'!$E:$E, MATCH('Ratings by CLO'!$J38,'Master Ratings'!$B:$B,0),0)) -> #N/A | O38: =+IF(INDEX('Master Ratings'!$G:$G, MATCH('Ratings by CLO'!$J38,'Master Ratings'!$B:$B,0),0)=0,"",INDEX('Master Ratings'!$G:$G, MATCH('Ratings by CLO'!$J38,'Master Ratings'!$B:$B,0),0)) -> #N/A | P38: =+IF(INDEX('Master Ratings'!$H:$H, MATCH('Ratings by CLO'!$J38,'Master Ratings'!$B:$B,0),0)=0,"",INDEX('Master Ratings'!$H:$H, MATCH('Ratings by CLO'!$J38,'Master Ratings'!$B:$B,0),0)) -> #N/A | Q38: =+IF(INDEX('Master Ratings'!$O:$O, MATCH('Ratings by CLO'!$J38,'Master Ratings'!$B:$B,0),0)=0,"",INDEX('Master Ratings'!$O:$O, MATCH('Ratings by CLO'!$J38,'Master Ratings'!$B:$B,0),0)) -> #N/A | S38: =+IF(INDEX('Master Ratings'!$L:$L, MATCH('Ratings by CLO'!$J38,'Master Ratings'!$B:$B,0),0)=0,"",INDEX('Master Ratings'!$L:$L, MATCH('Ratings by CLO'!$J38,'Master Ratings'!$B:$B,0),0)) -> #N/A | T38: =+IF(INDEX('Master Ratings'!$M:$M, MATCH('Ratings by CLO'!$J38,'Master Ratings'!$B:$B,0),0)=0,"",INDEX('Master Ratings'!$M:$M, MATCH('Ratings by CLO'!$J38,'Master Ratings'!$B:$B,0),0)) -> #N/A | U38: =+IF(INDEX('Master Ratings'!$P:$P, MATCH('Ratings by CLO'!$J38,'Master Ratings'!$B:$B,0),0)=0,"",INDEX('Master Ratings'!$P:$P, MATCH('Ratings by CLO'!$J38,'Master Ratings'!$B:$B,0),0)) -> #N/A | W38: =+IF(OR($P38=$W$1,$P38=$W$2),$Q38+365-TODAY(), "") -> #N/A | X38: =+IF(OR($T38=$W$1,$T38=$W$2),$U38+365-TODAY(), "") -> #N/A | Z38: =IF(AND(SUM(B38:H38)>=1,ISERROR(W38)),"X","") -> X | AA38: =IF(AND(B38>1, ISERROR(X38)),"X","") | AB38: =+IFERROR(IF(W38<0,"X",""),"") | AC38: =+IFERROR(IF(AND(B38>0, X38<0),"X",""),"") | AE38: =+IF(SUM(B38:H38)=0,"X","") | AG38: =IF(Z38="X",AG37+1,AG37) -> 2 | AH38: =IF(AA38="X",AH37+1,AH37) -> 2 | AI38: =IF(AB38="X",AI37+1,AI37) -> 8 | AJ38: =IF(AC38="X",AJ37+1,AJ37) -> 14
... B121: =+COUNTIFS(SOIs!$D:$D, 'Ratings by CLO'!$J121) -> 4 | C121: =+COUNTIFS(SOIs!$G:$G, 'Ratings by CLO'!$J121) -> 1 | D121: =+COUNTIFS(SOIs!$J:$J, 'Ratings by CLO'!$J121) -> 1 | E121: =+COUNTIFS(SOIs!$M:$M, 'Ratings by CLO'!$J121) -> 1 | F121: =+COUNTIFS(SOIs!$P:$P, 'Ratings by CLO'!$J121) -> 1 | G121: =+COUNTIFS(SOIs!$S:$S, 'Ratings by CLO'!$J121) -> 1 | H121: =+COUNTIFS(SOIs!$V:$V, 'Ratings by CLO'!$J121) -> 1 | J121: =+SOIs!X122 -> Zips | L121: =+IF(INDEX('Master Ratings'!$D:$D, MATCH('Ratings by CLO'!$J121,'Master Ratings'!$B:$B,0),0)=0,"",INDEX('Master Ratings'!$D:$D, MATCH('Ratings by CLO'!$J121,'Master Ratings'!$B:$B,0),0)) | M121: =+IF(INDEX('Master Ratings'!$E:$E, MATCH('Ratings by CLO'!$J121,'Master Ratings'!$B:$B,0),0)=0,"",INDEX('Master Ratings'!$E:$E, MATCH('Ratings by CLO'!$J121,'Master Ratings'!$B:$B,0),0)) | O121: =+IF(INDEX('Master Ratings'!$G:$G, MATCH('Ratings by CLO'!$J121,'Master Ratings'!$B:$B,0),0)=0,"",INDEX('Master Ratings'!$G:$G, MATCH('Ratings by CLO'!$J121,'Master Ratings'!$B:$B,0),0)) -> D* | P121: =+IF(INDEX('Master Ratings'!$H:$H, MATCH('Ratings by CLO'!$J121,'Master Ratings'!$B:$B,0),0)=0,"",INDEX('Master Ratings'!$H:$H, MATCH('Ratings by CLO'!$J121,'Master Ratings'!$B:$B,0),0)) -> Rating (Private) | Q121: =+IF(INDEX('Master Ratings'!$O:$O, MATCH('Ratings by CLO'!$J121,'Master Ratings'!$B:$B,0),0)=0,"",INDEX('Master Ratings'!$O:$O, MATCH('Ratings by CLO'!$J121,'Master Ratings'!$B:$B,0),0)) -> 45695 | S121: =+IF(INDEX('Master Ratings'!$L:$L, MATCH('Ratings by CLO'!$J121,'Master Ratings'!$B:$B,0),0)=0,"",INDEX('Master Ratings'!$L:$L, MATCH('Ratings by CLO'!$J121,'Master Ratings'!$B:$B,0),0)) -> CCC* | T121: =+IF(INDEX('Master Ratings'!$M:$M, MATCH('Ratings by CLO'!$J121,'Master Ratings'!$B:$B,0),0)=0,"",INDEX('Master Ratings'!$M:$M, MATCH('Ratings by CLO'!$J121,'Master Ratings'!$B:$B,0),0)) -> Credit Estimate | U121: =+IF(INDEX('Master Ratings'!$P:$P, MATCH('Ratings by CLO'!$J121,'Master Ratings'!$B:$B,0),0)=0,"",INDEX('Master Ratings'!$P:$P, MATCH('Ratings by CLO'!$J121,'Master Ratings'!$B:$B,0),0)) -> 45275 | W121: =+IF(OR($P121=$W$1,$P121=$W$2),$Q121+365-TODAY(), "") -> 96 | X121: =+IF(OR($T121=$W$1,$T121=$W$2),$U121+365-TODAY(), "") -> -324 | Z121: =IF(AND(SUM(B121:H121)>=1,ISERROR(W121)),"X","") | AA121: =IF(AND(B121>1, ISERROR(X121)),"X","") | AB121: =+IFERROR(IF(W121<0,"X",""),"") | AC121: =+IFERROR(IF(AND(B121>0, X121<0),"X",""),"") -> X | AE121: =+IF(SUM(B121:H121)=0,"X","") | AG121: =IF(Z121="X",AG120+1,AG120) -> 9 | AH121: =IF(AA121="X",AH120+1,AH120) -> 14 | AI121: =IF(AB121="X",AI120+1,AI120) -> 35 | AJ121: =IF(AC121="X",AJ120+1,AJ120) -> 44

Sheet SOIs
A1: Date | B1: 45199
C3: Copy and Paste from SOIs | F3: Copy and Paste from SOIs | I3: Copy and Paste from SOIs | X3: Copy and Paste Family Names; Remove Duplicates and Sort
C4: PFLT CLO | F4: PSSL CLO | I4: Towerbrook I | L4: PSLF CLO | O4: Towerbrook II | R4: PSSL CLO (2) | U4: PSLF CLO (2)
C5: SOI Name | D5: Family Name | F5: SOI Name | G5: Family Name | I5: SOI Name | J5: Family Name | L5: SOI Name | M5: Family Name | O5: SOI Name | P5: Family Name | X5: Unique Names
C6: Ad.net Acquisition, LLC | D6: =+INDEX('SOI Mapping'!$D:$D, MATCH(SOIs!$C6,'SOI Mapping'!$B:$B,0),0) -> Ad.net | F6: Ad.net Acquisition, LLC | G6: =+INDEX('SOI Mapping'!$D:$D, MATCH(SOIs!$F6,'SOI Mapping'!$B:$B,0),0) -> Ad.net | I6: Ad.net Acquisition, LLC | J6: =+INDEX('SOI Mapping'!$D:$D, MATCH(SOIs!$I6,'SOI Mapping'!$B:$B,0),0) -> Ad.net | L6: Ad.net Acquisition, LLC | M6: =+INDEX('SOI Mapping'!$D:$D, MATCH(SOIs!$L6,'SOI Mapping'!$B:$B,0),0) -> Ad.net | O6: Alpine Acquisition Corp II | P6: =+INDEX('SOI Mapping'!$D:$D, MATCH(SOIs!$O6,'SOI Mapping'!$B:$B,0),0) -> 48Forty | R6: A1 Garage Merger Sub, LLC | S6: =+INDEX('SOI Mapping'!$D:$D, MATCH(SOIs!$R6,'SOI Mapping'!$B:$B,0),0) -> A1 Garage | U6: A1 Garage Merger Sub, LLC | V6: =+INDEX('SOI Mapping'!$D:$D, MATCH(SOIs!$U6,'SOI Mapping'!$B:$B,0),0) -> A1 Garage | X6: 48Forty
C7: Amsive Holding Corporation (f/k/a Vision Purchaser Corporation) | D7: =+INDEX('SOI Mapping'!$D:$D, MATCH(SOIs!$C7,'SOI Mapping'!$B:$B,0),0) -> Vision Integrated | F7: Alpine Acquisition Corp II | G7: =+INDEX('SOI Mapping'!$D:$D, MATCH(SOIs!$F7,'SOI Mapping'!$B:$B,0),0) -> 48Forty | I7: Alpine Acquisition Corp II | J7: =+INDEX('SOI Mapping'!$D:$D, MATCH(SOIs!$I7,'SOI Mapping'!$B:$B,0),0) -> 48Forty | L7: Alpine Acquisition Corp II | M7: =+INDEX('SOI Mapping'!$D:$D, MATCH(SOIs!$L7,'SOI Mapping'!$B:$B,0),0) -> 48Forty | O7: American Insulated Glass, LLC | P7: =+INDEX('SOI Mapping'!$D:$D, MATCH(SOIs!$O7,'SOI Mapping'!$B:$B,0),0) -> American Insulated Glass | R7: Ad.net Acquisition, LLC | S7: =+INDEX('SOI Mapping'!$D:$D, MATCH(SOIs!$R7,'SOI Mapping'!$B:$B,0),0) -> Ad.net | U7: Alpine Acquisition Corp II | V7: =+INDEX('SOI Mapping'!$D:$D, MATCH(SOIs!$U7,'SOI Mapping'!$B:$B,0),0) -> 48Forty | X7: 4Wall Entertainment
C8: Anteriad, LLC (f/k/a MeritDirect, LLC) | D8: =+INDEX('SOI Mapping'!$D:$D, MATCH(SOIs!$C8,'SOI Mapping'!$B:$B,0),0) -> MeritDirect | F8: Anteriad, LLC (f/k/a MeritDirect, LLC) | G8: =+INDEX('SOI Mapping'!$D:$D, MATCH(SOIs!$F8,'SOI Mapping'!$B:$B,0),0) -> MeritDirect | I8: Anteriad, LLC (f/k/a MeritDirect, LLC) | J8: =+INDEX('SOI Mapping'!$D:$D, MATCH(SOIs!$I8,'SOI Mapping'!$B:$B,0),0) -> MeritDirect | L8: Amsive Holding Corporation (f/k/a Vision Purchaser Corporation) | M8: =+INDEX('SOI Mapping'!$D:$D, MATCH(SOIs!$L8,'SOI Mapping'!$B:$B,0),0) -> Vision Integrated | O8: Ankura Consulting Group, LLC | P8: =+INDEX('SOI Mapping'!$D:$D, MATCH(SOIs!$O8,'SOI Mapping'!$B:$B,0),0) -> Ankura | R8: Alpine Acquisition Corp II | S8: =+INDEX('SOI Mapping'!$D:$D, MATCH(SOIs!$R8,'SOI Mapping'!$B:$B,0),0) -> 48Forty | U8: Amsive Holding Corporation (f/k/a Vision Purchaser Corporation) | V8: =+INDEX('SOI Mapping'!$D:$D, MATCH(SOIs!$U8,'SOI Mapping'!$B:$B,0),0) -> Vision Integrated | X8: A1 Garage
C9: Any Hour Services | D9: =+INDEX('SOI Mapping'!$D:$D, MATCH(SOIs!$C9,'SOI Mapping'!$B:$B,0),0) -> Any Hour Services | F9: Any Hour Services | G9: =+INDEX('SOI Mapping'!$D:$D, MATCH(SOIs!$F9,'SOI Mapping'!$B:$B,0),0) -> Any Hour Services | I9: Apex Service Partners, LLC | J9: =+INDEX('SOI Mapping'!$D:$D, MATCH(SOIs!$I9,'SOI Mapping'!$B:$B,0),0) -> Apex Service Partners | L9: Anteriad, LLC (f/k/a MeritDirect, LLC) | M9: =+INDEX('SOI Mapping'!$D:$D, MATCH(SOIs!$L9,'SOI Mapping'!$B:$B,0),0) -> MeritDirect | O9: Anteriad, LLC (f/k/a MeritDirect, LLC) | P9: =+INDEX('SOI Mapping'!$D:$D, MATCH(SOIs!$O9,'SOI Mapping'!$B:$B,0),0) -> MeritDirect | R9: Anteriad, LLC (f/k/a MeritDirect, LLC) - Incremental | S9: MeritDirect | U9: Anteriad, LLC (f/k/a MeritDirect, LLC) | V9: =+INDEX('SOI Mapping'!$D:$D, MATCH(SOIs!$U9,'SOI Mapping'!$B:$B,0),0) -> MeritDirect | X9: Ad.net
C10: Apex Service Partners, LLC | D10: =+INDEX('SOI Mapping'!$D:$D, MATCH(SOIs!$C10,'SOI Mapping'!$B:$B,0),0) -> Apex Service Partners | F10: Apex Service Partners, LLC | G10: =+INDEX('SOI Mapping'!$D:$D, MATCH(SOIs!$F10,'SOI Mapping'!$B:$B,0),0) -> Apex Service Partners | I10: Apex Service Partners, LLC - Term Loan C | J10: =+INDEX('SOI Mapping'!$D:$D, MATCH(SOIs!$I10,'SOI Mapping'!$B:$B,0),0) -> Apex Service Partners | L10: Any Hour Services | M10: =+INDEX('SOI Mapping'!$D:$D, MATCH(SOIs!$L10,'SOI Mapping'!$B:$B,0),0) -> Any Hour Services | O10: Apex Service Partners, LLC - Term Loan C | P10: =+INDEX('SOI Mapping'!$D:$D, MATCH(SOIs!$O10,'SOI Mapping'!$B:$B,0),0) -> Apex Service Partners | R10: Any Hour Services | S10: =+INDEX('SOI Mapping'!$D:$D, MATCH(SOIs!$R10,'SOI Mapping'!$B:$B,0),0) -> Any Hour Services | U10: Any Hour Services | V10: =+INDEX('SOI Mapping'!$D:$D, MATCH(SOIs!$U10,'SOI Mapping'!$B:$B,0),0) -> Any Hour Services | X10: alphabroder
C11: Applied Technical Services, LLC | D11: =+INDEX('SOI Mapping'!$D:$D, MATCH(SOIs!$C11,'SOI Mapping'!$B:$B,0),0) -> Applied Technical Services | F11: Apex Service Partners, LLC Term Loan B | G11: =+INDEX('SOI Mapping'!$D:$D, MATCH(SOIs!$F11,'SOI Mapping'!$B:$B,0),0) -> Apex Service Partners | I11: Ascensus Holdings, Inc. | J11: =+INDEX('SOI Mapping'!$D:$D, MATCH(SOIs!$I11,'SOI Mapping'!$B:$B,0),0) -> Ascensus | L11: Apex Service Partners, LLC | M11: =+INDEX('SOI Mapping'!$D:$D, MATCH(SOIs!$L11,'SOI Mapping'!$B:$B,0),0) -> Apex Service Partners | O11: Applied Technical Services, LLC | P11: =+INDEX('SOI Mapping'!$D:$D, MATCH(SOIs!$O11,'SOI Mapping'!$B:$B,0),0) -> Applied Technical Services | R11: Apex Service Partners, LLC Term Loan C | S11: =+INDEX('SOI Mapping'!$D:$D, MATCH(SOIs!$R11,'SOI Mapping'!$B:$B,0),0) -> Apex Service Partners | U11: Apex Service Partners, LLC - Term Loan C | V11: =+INDEX('SOI Mapping'!$D:$D, MATCH(SOIs!$U11,'SOI Mapping'!$B:$B,0),0) -> Apex Service Partners | X11: American Insulated Glass
C12: Arcfield Acquisition Corp. | D12: =+INDEX('SOI Mapping'!$D:$D, MATCH(SOIs!$C12,'SOI Mapping'!$B:$B,0),0) -> Arcfield | F12: Apex Service Partners, LLC Term Loan C | G12: =+INDEX('SOI Mapping'!$D:$D, MATCH(SOIs!$F12,'SOI Mapping'!$B:$B,0),0) -> Apex Service Partners | I12: Broder Bros., Co. | J12: =+INDEX('SOI Mapping'!$D:$D, MATCH(SOIs!$I12,'SOI Mapping'!$B:$B,0),0) -> alphabroder | L12: Applied Technical Services, LLC | M12: =+INDEX('SOI Mapping'!$D:$D, MATCH(SOIs!$L12,'SOI Mapping'!$B:$B,0),0) -> Applied Technical Services | O12: Ascensus Holdings, Inc. | P12: =+INDEX('SOI Mapping'!$D:$D, MATCH(SOIs!$O12,'SOI Mapping'!$B:$B,0),0) -> Ascensus | R12: Applied Technical Services, LLC | S12: =+INDEX('SOI Mapping'!$D:$D, MATCH(SOIs!$R12,'SOI Mapping'!$B:$B,0),0) -> Applied Technical Services | U12: Applied Technical Services, LLC | V12: =+INDEX('SOI Mapping'!$D:$D, MATCH(SOIs!$U12,'SOI Mapping'!$B:$B,0),0) -> Applied Technical Services | X12: Ankura
C13: Beta Plus Technologies, Inc. | D13: =+INDEX('SOI Mapping'!$D:$D, MATCH(SOIs!$C13,'SOI Mapping'!$B:$B,0),0) -> Beta+ | F13: Applied Technical Services, LLC | G13: =+INDEX('SOI Mapping'!$D:$D, MATCH(SOIs!$F13,'SOI Mapping'!$B:$B,0),0) -> Applied Technical Services | I13: By Light Professional IT Services, LLC | J13: =+INDEX('SOI Mapping'!$D:$D, MATCH(SOIs!$I13,'SOI Mapping'!$B:$B,0),0) -> By Light | L13: Beta Plus Technologies, Inc. | M13: =+INDEX('SOI Mapping'!$D:$D, MATCH(SOIs!$L13,'SOI Mapping'!$B:$B,0),0) -> Beta+ | O13: Berlin Packaging, LLC | P13: =+INDEX('SOI Mapping'!$D:$D, MATCH(SOIs!$O13,'SOI Mapping'!$B:$B,0),0) -> Berlin Packaging | R13: Arcfield Acquisition Corp. | S13: =+INDEX('SOI Mapping'!$D:$D, MATCH(SOIs!$R13,'SOI Mapping'!$B:$B,0),0) -> Arcfield | U13: Arcfield Acquisition Corp. | V13: =+INDEX('SOI Mapping'!$D:$D, MATCH(SOIs!$U13,'SOI Mapping'!$B:$B,0),0) -> Arcfield | X13: Any Hour Services
C14: Broder Bros., Co. | D14: =+INDEX('SOI Mapping'!$D:$D, MATCH(SOIs!$C14,'SOI Mapping'!$B:$B,0),0) -> alphabroder | F14: Applied Technical Services, LLC - DDTL Unfunded | G14: Applied Technical Services | I14: Cartessa Aesthetics, LLC | J14: =+INDEX('SOI Mapping'!$D:$D, MATCH(SOIs!$I14,'SOI Mapping'!$B:$B,0),0) -> Cartessa | L14: Cartessa Aesthetics, LLC | M14: =+INDEX('SOI Mapping'!$D:$D, MATCH(SOIs!$L14,'SOI Mapping'!$B:$B,0),0) -> Cartessa | O14: Blackhawk Industrial Distribution, Inc. | P14: =+INDEX('SOI Mapping'!$D:$D, MATCH(SOIs!$O14,'SOI Mapping'!$B:$B,0),0) -> BlackHawk Industrial | R14: BioDerm, Inc. | S14: =+INDEX('SOI Mapping'!$D:$D, MATCH(SOIs!$R14,'SOI Mapping'!$B:$B,0),0) -> BioDerm | U14: Beta Plus Technologies, Inc. | V14: =+INDEX('SOI Mapping'!$D:$D, MATCH(SOIs!$U14,'SOI Mapping'!$B:$B,0),0) -> Beta+ | X14: Apex Service Partners
C15: By Light Professional IT Services, LLC | D15: =+INDEX('SOI Mapping'!$D:$D, MATCH(SOIs!$C15,'SOI Mapping'!$B:$B,0),0) -> By Light | F15: Arcfield Acquisition Corp. | G15: =+INDEX('SOI Mapping'!$D:$D, MATCH(SOIs!$F15,'SOI Mapping'!$B:$B,0),0) -> Arcfield | I15: CF512, Inc. | J15: =+INDEX('SOI Mapping'!$D:$D, MATCH(SOIs!$I15,'SOI Mapping'!$B:$B,0),0) -> Gen3 Marketing | L15: CF512, Inc. | M15: =+INDEX('SOI Mapping'!$D:$D, MATCH(SOIs!$L15,'SOI Mapping'!$B:$B,0),0) -> Gen3 Marketing | O15: Broder Bros., Co. | P15: =+INDEX('SOI Mapping'!$D:$D, MATCH(SOIs!$O15,'SOI Mapping'!$B:$B,0),0) -> alphabroder | R15: Blackhawk Industrial Distribution, Inc. | S15: =+INDEX('SOI Mapping'!$D:$D, MATCH(SOIs!$R15,'SOI Mapping'!$B:$B,0),0) -> BlackHawk Industrial | U15: Bioderm, Inc. | V15: =+INDEX('SOI Mapping'!$D:$D, MATCH(SOIs!$U15,'SOI Mapping'!$B:$B,0),0) -> BioDerm | X15: Applied Technical Services
C16: Cartessa Aesthetics, LLC | D16: =+INDEX('SOI Mapping'!$D:$D, MATCH(SOIs!$C16,'SOI Mapping'!$B:$B,0),0) -> Cartessa | F16: Beta Plus Technologies, Inc. | G16: =+INDEX('SOI Mapping'!$D:$D, MATCH(SOIs!$F16,'SOI Mapping'!$B:$B,0),0) -> Beta+ | I16: Confluent Health, LLC | J16: =+INDEX('SOI Mapping'!$D:$D, MATCH(SOIs!$I16,'SOI Mapping'!$B:$B,0),0) -> Confluent Health | L16: Connatix Buyer, Inc. | M16: =+INDEX('SOI Mapping'!$D:$D, MATCH(SOIs!$L16,'SOI Mapping'!$B:$B,0),0) -> Connatix | O16: Burgess Point Purchaser Corporation | P16: =+INDEX('SOI Mapping'!$D:$D, MATCH(SOIs!$O16,'SOI Mapping'!$B:$B,0),0) -> BBB Industries | R16: Burgess Point Purchaser Corporation | S16: BBB Industries | U16: Blackhawk Industrial Distribution, Inc. | V16: =+INDEX('SOI Mapping'!$D:$D, MATCH(SOIs!$U16,'SOI Mapping'!$B:$B,0),0) -> BlackHawk Industrial | X16: Arcfield
C17: CF512, Inc. | D17: =+INDEX('SOI Mapping'!$D:$D, MATCH(SOIs!$C17,'SOI Mapping'!$B:$B,0),0) -> Gen3 Marketing | F17: BioDerm, Inc. | G17: =+INDEX('SOI Mapping'!$D:$D, MATCH(SOIs!$F17,'SOI Mapping'!$B:$B,0),0) -> BioDerm | I17: Confluent Health, LLC - Unfunded Term Loan | J17: =+INDEX('SOI Mapping'!$D:$D, MATCH(SOIs!$I17,'SOI Mapping'!$B:$B,0),0) -> Confluent Health | L17: Dr. Squatch, LLC | M17: =+INDEX('SOI Mapping'!$D:$D, MATCH(SOIs!$L17,'SOI Mapping'!$B:$B,0),0) -> Dr. Squatch | O17: By Light Professional IT Services, LLC | P17: =+INDEX('SOI Mapping'!$D:$D, MATCH(SOIs!$O17,'SOI Mapping'!$B:$B,0),0) -> By Light | R17: By Light Professional IT Services, LLC | S17: =+INDEX('SOI Mapping'!$D:$D, MATCH(SOIs!$R17,'SOI Mapping'!$B:$B,0),0) -> By Light | U17: Broder Bros., Co. | V17: =+INDEX('SOI Mapping'!$D:$D, MATCH(SOIs!$U17,'SOI Mapping'!$B:$B,0),0) -> alphabroder | X17: Ardurra
C18: CHA Holdings, Inc. | D18: =+INDEX('SOI Mapping'!$D:$D, MATCH(SOIs!$C18,'SOI Mapping'!$B:$B,0),0) -> CHA Consulting | F18: Blackhawk Industrial Distribution, Inc. | G18: =+INDEX('SOI Mapping'!$D:$D, MATCH(SOIs!$F18,'SOI Mapping'!$B:$B,0),0) -> BlackHawk Industrial | I18: Connatix Buyer, Inc. | J18: =+INDEX('SOI Mapping'!$D:$D, MATCH(SOIs!$I18,'SOI Mapping'!$B:$B,0),0) -> Connatix | L18: DRI Holding Inc. | M18: =+INDEX('SOI Mapping'!$D:$D, MATCH(SOIs!$L18,'SOI Mapping'!$B:$B,0),0) -> Digital Room | O18: Cartessa Aesthetics, LLC | P18: =+INDEX('SOI Mapping'!$D:$D, MATCH(SOIs!$O18,'SOI Mapping'!$B:$B,0),0) -> Cartessa | R18: Cadence Aerospace, LLC | S18: =+INDEX('SOI Mapping'!$D:$D, MATCH(SOIs!$R18,'SOI Mapping'!$B:$B,0),0) -> Cadence Aerospace | U18: Cartessa Aesthetics, LLC | V18: =+INDEX('SOI Mapping'!$D:$D, MATCH(SOIs!$U18,'SOI Mapping'!$B:$B,0),0) -> Cartessa | X18: Ascensus
C19: Connatix Buyer, Inc. | D19: =+INDEX('SOI Mapping'!$D:$D, MATCH(SOIs!$C19,'SOI Mapping'!$B:$B,0),0) -> Connatix | F19: Broder Bros., Co. | G19: =+INDEX('SOI Mapping'!$D:$D, MATCH(SOIs!$F19,'SOI Mapping'!$B:$B,0),0) -> alphabroder | I19: CoolSys, Inc. | J19: =+INDEX('SOI Mapping'!$D:$D, MATCH(SOIs!$I19,'SOI Mapping'!$B:$B,0),0) -> CoolSys | L19: DRS Holdings III, Inc. | M19: =+INDEX('SOI Mapping'!$D:$D, MATCH(SOIs!$L19,'SOI Mapping'!$B:$B,0),0) -> Dr. Scholl's | O19: CF512, Inc. | P19: =+INDEX('SOI Mapping'!$D:$D, MATCH(SOIs!$O19,'SOI Mapping'!$B:$B,0),0) -> Gen3 Marketing | R19: Cartessa Aesthetics, LLC | S19: Cartessa | U19: Connatix Buyer, Inc. | V19: =+INDEX('SOI Mapping'!$D:$D, MATCH(SOIs!$U19,'SOI Mapping'!$B:$B,0),0) -> Connatix | X19: BBB Industries
C20: Crane 1 Services, Inc. | D20: =+INDEX('SOI Mapping'!$D:$D, MATCH(SOIs!$C20,'SOI Mapping'!$B:$B,0),0) -> Crane 1 | F20: By Light Professional IT Services, LLC | G20: =+INDEX('SOI Mapping'!$D:$D, MATCH(SOIs!$F20,'SOI Mapping'!$B:$B,0),0) -> By Light | I20: CoolSys, Inc. - Unfunded Term Loan | J20: =+INDEX('SOI Mapping'!$D:$D, MATCH(SOIs!$I20,'SOI Mapping'!$B:$B,0),0) -> CoolSys | L20: Duraco Specialty Tapes LLC | M20: =+INDEX('SOI Mapping'!$D:$D, MATCH(SOIs!$L20,'SOI Mapping'!$B:$B,0),0) -> The Duraco Group | O20: Compex Legal Services, Inc. | P20: =+INDEX('SOI Mapping'!$D:$D, MATCH(SOIs!$O20,'SOI Mapping'!$B:$B,0),0) -> Compex Legal | R20: CF512, Inc. | S20: =+INDEX('SOI Mapping'!$D:$D, MATCH(SOIs!$R20,'SOI Mapping'!$B:$B,0),0) -> Gen3 Marketing | U20: Crane 1 Services, Inc. | V20: =+INDEX('SOI Mapping'!$D:$D, MATCH(SOIs!$U20,'SOI Mapping'!$B:$B,0),0) -> Crane 1 | X20: Berlin Packaging
C21: Duraco Specialty Tapes LLC | D21: =+INDEX('SOI Mapping'!$D:$D, MATCH(SOIs!$C21,'SOI Mapping'!$B:$B,0),0) -> The Duraco Group | F21: Cartessa Aesthetics, LLC | G21: =+INDEX('SOI Mapping'!$D:$D, MATCH(SOIs!$F21,'SOI Mapping'!$B:$B,0),0) -> Cartessa | I21: Crane 1 Services, Inc. | J21: =+INDEX('SOI Mapping'!$D:$D, MATCH(SOIs!$I21,'SOI Mapping'!$B:$B,0),0) -> Crane 1 | L21: ETE Intermediate II, LLC | M21: Engine & Transmission Exchange | O21: Connatix Buyer, Inc. | P21: =+INDEX('SOI Mapping'!$D:$D, MATCH(SOIs!$O21,'SOI Mapping'!$B:$B,0),0) -> Connatix | R21: Crane 1 Services, Inc. | S21: Crane 1 | U21: Dr. Squatch, LLC | V21: =+INDEX('SOI Mapping'!$D:$D, MATCH(SOIs!$U21,'SOI Mapping'!$B:$B,0),0) -> Dr. Squatch | X21: Beta+
C22: DRS Holdings III, Inc. | D22: =+INDEX('SOI Mapping'!$D:$D, MATCH(SOIs!$C22,'SOI Mapping'!$B:$B,0),0) -> Dr. Scholl's | F22: CF512, Inc. | G22: =+INDEX('SOI Mapping'!$D:$D, MATCH(SOIs!$F22,'SOI Mapping'!$B:$B,0),0) -> Gen3 Marketing | I22: DG Investment Intermediate Holdings 2, Inc. | J22: =+INDEX('SOI Mapping'!$D:$D, MATCH(SOIs!$I22,'SOI Mapping'!$B:$B,0),0) -> Convergint | L22: Exigo Intermediate II, LLC | M22: =+INDEX('SOI Mapping'!$D:$D, MATCH(SOIs!$L22,'SOI Mapping'!$B:$B,0),0) -> Exigo | O22: Deerfield Dakota Holding, LLC | P22: =+INDEX('SOI Mapping'!$D:$D, MATCH(SOIs!$O22,'SOI Mapping'!$B:$B,0),0) -> Kroll | R22: Dr. Squatch, LLC | S22: Dr. Squatch | U22: DRS Holdings III, Inc. | V22: =+INDEX('SOI Mapping'!$D:$D, MATCH(SOIs!$U22,'SOI Mapping'!$B:$B,0),0) -> Dr. Scholl's | X22: BioDerm
C23: ECL Entertainment, LLC | D23: =+INDEX('SOI Mapping'!$D:$D, MATCH(SOIs!$C23,'SOI Mapping'!$B:$B,0),0) -> ECL Entertainment | F23: CHA Holdings, Inc. | G23: =+INDEX('SOI Mapping'!$D:$D, MATCH(SOIs!$F23,'SOI Mapping'!$B:$B,0),0) -> CHA Consulting | I23: Dr. Squatch, LLC | J23: =+INDEX('SOI Mapping'!$D:$D, MATCH(SOIs!$I23,'SOI Mapping'!$B:$B,0),0) -> Dr. Squatch | L23: Global Holdings InterCo LLC | M23: =+INDEX('SOI Mapping'!$D:$D, MATCH(SOIs!$L23,'SOI Mapping'!$B:$B,0),0) -> Global | O23: DG Investment Intermediate Holdings 2, Inc. | P23: =+INDEX('SOI Mapping'!$D:$D, MATCH(SOIs!$O23,'SOI Mapping'!$B:$B,0),0) -> Convergint | R23: DRI Holding Inc. | S23: =+INDEX('SOI Mapping'!$D:$D, MATCH(SOIs!$R23,'SOI Mapping'!$B:$B,0),0) -> Digital Room | U23: Duraco Specialty Tapes LLC | V23: =+INDEX('SOI Mapping'!$D:$D, MATCH(SOIs!$U23,'SOI Mapping'!$B:$B,0),0) -> The Duraco Group | X23: BlackHawk Industrial
C24: eCommission Financial Services, Inc. | D24: =+INDEX('SOI Mapping'!$D:$D, MATCH(SOIs!$C24,'SOI Mapping'!$B:$B,0),0) -> eCommission | F24: Connatix Buyer, Inc. | G24: =+INDEX('SOI Mapping'!$D:$D, MATCH(SOIs!$F24,'SOI Mapping'!$B:$B,0),0) -> Connatix | I24: DRI Holding Inc. | J24: =+INDEX('SOI Mapping'!$D:$D, MATCH(SOIs!$I24,'SOI Mapping'!$B:$B,0),0) -> Digital Room | L24: Graffiti Buyer, Inc. | M24: =+INDEX('SOI Mapping'!$D:$D, MATCH(SOIs!$L24,'SOI Mapping'!$B:$B,0),0) -> Painters Supply and Equipment | O24: Dr. Squatch, LLC | P24: =+INDEX('SOI Mapping'!$D:$D, MATCH(SOIs!$O24,'SOI Mapping'!$B:$B,0),0) -> Dr. Squatch | R24: DRS Holdings III, Inc. | S24: =+INDEX('SOI Mapping'!$D:$D, MATCH(SOIs!$R24,'SOI Mapping'!$B:$B,0),0) -> Dr. Scholl's | U24: EDS Buyer, LLC | V24: =+INDEX('SOI Mapping'!$D:$D, MATCH(SOIs!$U24,'SOI Mapping'!$B:$B,0),0) -> Epiq | X24: Bluebird
C25: Global Holdings InterCo LLC | D25: =+INDEX('SOI Mapping'!$D:$D, MATCH(SOIs!$C25,'SOI Mapping'!$B:$B,0),0) -> Global | F25: Dr. Squatch, LLC | G25: Dr. Squatch | I25: DRS Holdings III, Inc. | J25: =+INDEX('SOI Mapping'!$D:$D, MATCH(SOIs!$I25,'SOI Mapping'!$B:$B,0),0) -> Dr. Scholl's | L25: Hancock Roofing and Construction L.L.C. | M25: =+INDEX('SOI Mapping'!$D:$D, MATCH(SOIs!$L25,'SOI Mapping'!$B:$B,0),0) -> Hancock | O25: DRI Holding Inc. | P25: =+INDEX('SOI Mapping'!$D:$D, MATCH(SOIs!$O25,'SOI Mapping'!$B:$B,0),0) -> Digital Room | R25: Duraco Specialty Tapes LLC | S25: =+INDEX('SOI Mapping'!$D:$D, MATCH(SOIs!$R25,'SOI Mapping'!$B:$B,0),0) -> The Duraco Group | U25: Electro Rent Corporation | V25: =+INDEX('SOI Mapping'!$D:$D, MATCH(SOIs!$U25,'SOI Mapping'!$B:$B,0),0) -> Electro Rent | X25: BlueHalo
C26: Hancock Roofing and Construction L.L.C. | D26: =+INDEX('SOI Mapping'!$D:$D, MATCH(SOIs!$C26,'SOI Mapping'!$B:$B,0),0) -> Hancock | F26: DRI Holding Inc. | G26: =+INDEX('SOI Mapping'!$D:$D, MATCH(SOIs!$F26,'SOI Mapping'!$B:$B,0),0) -> Digital Room | I26: Duraco Specialty Tapes LLC | J26: =+INDEX('SOI Mapping'!$D:$D, MATCH(SOIs!$I26,'SOI Mapping'!$B:$B,0),0) -> The Duraco Group | L26: Holdco Sands Intermediate, LLC | M26: =+INDEX('SOI Mapping'!$D:$D, MATCH(SOIs!$L26,'SOI Mapping'!$B:$B,0),0) -> Smartronix / Trident | O26: DRS Holdings III, Inc. | P26: =+INDEX('SOI Mapping'!$D:$D, MATCH(SOIs!$O26,'SOI Mapping'!$B:$B,0),0) -> Dr. Scholl's | R26: EDS Buyer, LLC | S26: =+INDEX('SOI Mapping'!$D:$D, MATCH(SOIs!$R26,'SOI Mapping'!$B:$B,0),0) -> Epiq | U26: ETE Intermediate II, LLC | V26: Engine & Transmission Exchange | X26: By Light
C27: Holdco Sands Intermediate, LLC | D27: =+INDEX('SOI Mapping'!$D:$D, MATCH(SOIs!$C27,'SOI Mapping'!$B:$B,0),0) -> Smartronix / Trident | F27: DRS Holdings III, Inc. | G27: =+INDEX('SOI Mapping'!$D:$D, MATCH(SOIs!$F27,'SOI Mapping'!$B:$B,0),0) -> Dr. Scholl's | I27: ECL Entertainment, LLC | J27: =+INDEX('SOI Mapping'!$D:$D, MATCH(SOIs!$I27,'SOI Mapping'!$B:$B,0),0) -> ECL Entertainment | L27: HW Holdco, LLC | M27: =+INDEX('SOI Mapping'!$D:$D, MATCH(SOIs!$L27,'SOI Mapping'!$B:$B,0),0) -> Hanley Wood | O27: Duraco Specialty Tapes LLC | P27: =+INDEX('SOI Mapping'!$D:$D, MATCH(SOIs!$O27,'SOI Mapping'!$B:$B,0),0) -> The Duraco Group | R27: Electro Rent Corporation | S27: =+INDEX('SOI Mapping'!$D:$D, MATCH(SOIs!$R27,'SOI Mapping'!$B:$B,0),0) -> Electro Rent | U27: Exigo Intermediate II, LLC | V27: =+INDEX('SOI Mapping'!$D:$D, MATCH(SOIs!$U27,'SOI Mapping'!$B:$B,0),0) -> Exigo | X27: Cadence Aerospace
C28: HW Holdco, LLC | D28: =+INDEX('SOI Mapping'!$D:$D, MATCH(SOIs!$C28,'SOI Mapping'!$B:$B,0),0) -> Hanley Wood | F28: ECL Entertainment, LLC | G28: =+INDEX('SOI Mapping'!$D:$D, MATCH(SOIs!$F28,'SOI Mapping'!$B:$B,0),0) -> ECL Entertainment | I28: ECM Industries, LLC | J28: =+INDEX('SOI Mapping'!$D:$D, MATCH(SOIs!$I28,'SOI Mapping'!$B:$B,0),0) -> ECM Industries | L28: IG Investments Holdings, LLC | M28: =+INDEX('SOI Mapping'!$D:$D, MATCH(SOIs!$L28,'SOI Mapping'!$B:$B,0),0) -> Insight Global | O28: EDS Buyer, LLC | P28: =+INDEX('SOI Mapping'!$D:$D, MATCH(SOIs!$O28,'SOI Mapping'!$B:$B,0),0) -> Epiq | R28: ETE Intermediate II, LLC | S28: Engine & Transmission Exchange | U28: Fairbanks Morse Defense | V28: =+INDEX('SOI Mapping'!$D:$D, MATCH(SOIs!$U28,'SOI Mapping'!$B:$B,0),0) -> Fairbanks Morse Defense | X28: Cartessa
C29: IG Investments Holdings, LLC | D29: =+INDEX('SOI Mapping'!$D:$D, MATCH(SOIs!$C29,'SOI Mapping'!$B:$B,0),0) -> Insight Global | F29: ETE Intermediate II, LLC | G29: Engine & Transmission Exchange | I29: Exigo Intermediate II, LLC | J29: =+INDEX('SOI Mapping'!$D:$D, MATCH(SOIs!$I29,'SOI Mapping'!$B:$B,0),0) -> Exigo | L29: Imagine Acquisitionco, LLC | M29: =+INDEX('SOI Mapping'!$D:$D, MATCH(SOIs!$L29,'SOI Mapping'!$B:$B,0),0) -> ImagineAcquisitionCo | O29: Electro Rent Corporation | P29: =+INDEX('SOI Mapping'!$D:$D, MATCH(SOIs!$O29,'SOI Mapping'!$B:$B,0),0) -> Electro Rent | R29: Exigo Intermediate II, LLC | S29: =+INDEX('SOI Mapping'!$D:$D, MATCH(SOIs!$R29,'SOI Mapping'!$B:$B,0),0) -> Exigo | U29: Five Star Buyer, Inc. | V29: Five Star | X29: Centauri Health
C30: Inception Fertility Ventures, LLC | D30: =+INDEX('SOI Mapping'!$D:$D, MATCH(SOIs!$C30,'SOI Mapping'!$B:$B,0),0) -> Prelude | F30: Exigo Intermediate II, LLC | G30: =+INDEX('SOI Mapping'!$D:$D, MATCH(SOIs!$F30,'SOI Mapping'!$B:$B,0),0) -> Exigo | I30: Fairbanks More Defense | J30: =+INDEX('SOI Mapping'!$D:$D, MATCH(SOIs!$I30,'SOI Mapping'!$B:$B,0),0) -> Fairbanks Morse Defense | L30: Inception Fertility Ventures, LLC | M30: =+INDEX('SOI Mapping'!$D:$D, MATCH(SOIs!$L30,'SOI Mapping'!$B:$B,0),0) -> Prelude | O30: Exigo Intermediate II, LLC | P30: =+INDEX('SOI Mapping'!$D:$D, MATCH(SOIs!$O30,'SOI Mapping'!$B:$B,0),0) -> Exigo | R30: Fairbanks More Defense | S30: =+INDEX('SOI Mapping'!$D:$D, MATCH(SOIs!$R30,'SOI Mapping'!$B:$B,0),0) -> Fairbanks Morse Defense | U30: Global Holdings InterCo LLC | V30: =+INDEX('SOI Mapping'!$D:$D, MATCH(SOIs!$U30,'SOI Mapping'!$B:$B,0),0) -> Global | X30: Compex Legal
C31: Integrative Nutrition, LLC | D31: =+INDEX('SOI Mapping'!$D:$D, MATCH(SOIs!$C31,'SOI Mapping'!$B:$B,0),0) -> Integrative Nutrition | F31: Fairbanks More Defense | G31: =+INDEX('SOI Mapping'!$D:$D, MATCH(SOIs!$F31,'SOI Mapping'!$B:$B,0),0) -> Fairbanks Morse Defense | I31: Gantech Acquisition Corp. | J31: =+INDEX('SOI Mapping'!$D:$D, MATCH(SOIs!$I31,'SOI Mapping'!$B:$B,0),0) -> GCOM | L31: Integrity Marketing Acquisition, LLC | M31: =+INDEX('SOI Mapping'!$D:$D, MATCH(SOIs!$L31,'SOI Mapping'!$B:$B,0),0) -> Integrity Marketing | O31: Fairbanks Morse Defense | P31: =+INDEX('SOI Mapping'!$D:$D, MATCH(SOIs!$O31,'SOI Mapping'!$B:$B,0),0) -> Fairbanks Morse Defense | R31: HW Holdco, LLC | S31: =+INDEX('SOI Mapping'!$D:$D, MATCH(SOIs!$R31,'SOI Mapping'!$B:$B,0),0) -> Hanley Wood | U31: Hancock Roofing and Construction L.L.C. | V31: =+INDEX('SOI Mapping'!$D:$D, MATCH(SOIs!$U31,'SOI Mapping'!$B:$B,0),0) -> Hancock | X31: Connatix
C32: Integrity Marketing Acquisition, LLC | D32: =+INDEX('SOI Mapping'!$D:$D, MATCH(SOIs!$C32,'SOI Mapping'!$B:$B,0),0) -> Integrity Marketing | F32: Global Holdings InterCo LLC | G32: =+INDEX('SOI Mapping'!$D:$D, MATCH(SOIs!$F32,'SOI Mapping'!$B:$B,0),0) -> Global | I32: Global Holdings InterCo LLC | J32: =+INDEX('SOI Mapping'!$D:$D, MATCH(SOIs!$I32,'SOI Mapping'!$B:$B,0),0) -> Global | L32: K2 Pure Solutions NoCal, L.P. | M32: =+INDEX('SOI Mapping'!$D:$D, MATCH(SOIs!$L32,'SOI Mapping'!$B:$B,0),0) -> K2 | O32: Gantech Acquisition Corp. | P32: =+INDEX('SOI Mapping'!$D:$D, MATCH(SOIs!$O32,'SOI Mapping'!$B:$B,0),0) -> GCOM | R32: Imagine Acquisitionco, LLC | S32: =+INDEX('SOI Mapping'!$D:$D, MATCH(SOIs!$R32,'SOI Mapping'!$B:$B,0),0) -> ImagineAcquisitionCo | U32: Holdco Sands Intermediate, LLC | V32: =+INDEX('SOI Mapping'!$D:$D, MATCH(SOIs!$U32,'SOI Mapping'!$B:$B,0),0) -> Smartronix / Trident | X32: Consilio
C33: Inventus Power, Inc. | D33: =+INDEX('SOI Mapping'!$D:$D, MATCH(SOIs!$C33,'SOI Mapping'!$B:$B,0),0) -> Inventus | F33: Graffiti Buyer, Inc. | G33: =+INDEX('SOI Mapping'!$D:$D, MATCH(SOIs!$F33,'SOI Mapping'!$B:$B,0),0) -> Painters Supply and Equipment | I33: Graffiti Buyer, Inc. | J33: =+INDEX('SOI Mapping'!$D:$D, MATCH(SOIs!$I33,'SOI Mapping'!$B:$B,0),0) -> Painters Supply and Equipment | L33: Lash OpCo, LLC | M33: =+INDEX('SOI Mapping'!$D:$D, MATCH(SOIs!$L33,'SOI Mapping'!$B:$B,0),0) -> Lilly Lashes | O33: Hightower Holding, LLC | P33: =+INDEX('SOI Mapping'!$D:$D, MATCH(SOIs!$O33,'SOI Mapping'!$B:$B,0),0) -> Hightower | R33: Inception Fertility Ventures, LLC | S33: =+INDEX('SOI Mapping'!$D:$D, MATCH(SOIs!$R33,'SOI Mapping'!$B:$B,0),0) -> Prelude | U33: HV Watterson Holdings, LLC | V33: =+INDEX('SOI Mapping'!$D:$D, MATCH(SOIs!$U33,'SOI Mapping'!$B:$B,0),0) -> Watterson | X33: Convergint
C34: Kinetic Purchaser, LLC | D34: =+INDEX('SOI Mapping'!$D:$D, MATCH(SOIs!$C34,'SOI Mapping'!$B:$B,0),0) -> KNS | F34: Hancock Roofing and Construction L.L.C. | G34: =+INDEX('SOI Mapping'!$D:$D, MATCH(SOIs!$F34,'SOI Mapping'!$B:$B,0),0) -> Hancock | I34: Graffiti Buyer, Inc. - Unfunded Term Loan | J34: =+INDEX('SOI Mapping'!$D:$D, MATCH(SOIs!$I34,'SOI Mapping'!$B:$B,0),0) -> Painters Supply and Equipment | L34: Lightspeed Buyer Inc. | M34: =+INDEX('SOI Mapping'!$D:$D, MATCH(SOIs!$L34,'SOI Mapping'!$B:$B,0),0) -> Centauri Health | O34: Holdco Sands Intermediate, LLC | P34: =+INDEX('SOI Mapping'!$D:$D, MATCH(SOIs!$O34,'SOI Mapping'!$B:$B,0),0) -> Smartronix / Trident | R34: Infinity Home Services Holdco, Inc. | S34: Infinity Home Services | U34: Imagine Acquisitionco, LLC | V34: =+INDEX('SOI Mapping'!$D:$D, MATCH(SOIs!$U34,'SOI Mapping'!$B:$B,0),0) -> ImagineAcquisitionCo | X34: Crane 1
C35: Lash OpCo, LLC | D35: =+INDEX('SOI Mapping'!$D:$D, MATCH(SOIs!$C35,'SOI Mapping'!$B:$B,0),0) -> Lilly Lashes | F35: Holdco Sands Intermediate, LLC | G35: =+INDEX('SOI Mapping'!$D:$D, MATCH(SOIs!$F35,'SOI Mapping'!$B:$B,0),0) -> Smartronix / Trident | I35: Holdco Sands Intermediate, LLC | J35: =+INDEX('SOI Mapping'!$D:$D, MATCH(SOIs!$I35,'SOI Mapping'!$B:$B,0),0) -> Smartronix / Trident | L35: MAG DS Corp. | M35: =+INDEX('SOI Mapping'!$D:$D, MATCH(SOIs!$L35,'SOI Mapping'!$B:$B,0),0) -> MAG Aerospace | O35: HW Holdco, LLC | P35: =+INDEX('SOI Mapping'!$D:$D, MATCH(SOIs!$O35,'SOI Mapping'!$B:$B,0),0) -> Hanley Wood | R35: Integrated Data Services | S35: Integrated Data Services | U35: Inception Fertility Ventures, LLC | V35: =+INDEX('SOI Mapping'!$D:$D, MATCH(SOIs!$U35,'SOI Mapping'!$B:$B,0),0) -> Prelude | X35: Digital Room
C36: LAV Gear Holdings, Inc. | D36: =+INDEX('SOI Mapping'!$D:$D, MATCH(SOIs!$C36,'SOI Mapping'!$B:$B,0),0) -> 4Wall Entertainment | F36: Imagine Acquisitionco, LLC | G36: =+INDEX('SOI Mapping'!$D:$D, MATCH(SOIs!$F36,'SOI Mapping'!$B:$B,0),0) -> ImagineAcquisitionCo | I36: HW Holdco, LLC | J36: =+INDEX('SOI Mapping'!$D:$D, MATCH(SOIs!$I36,'SOI Mapping'!$B:$B,0),0) -> Hanley Wood | L36: Magenta Buyer, LLC | M36: =+INDEX('SOI Mapping'!$D:$D, MATCH(SOIs!$L36,'SOI Mapping'!$B:$B,0),0) -> McAfee | O36: IDC Infusion Services, Inc. | P36: =+INDEX('SOI Mapping'!$D:$D, MATCH(SOIs!$O36,'SOI Mapping'!$B:$B,0),0) -> IDC Infusion Services | R36: Integrity Marketing Acquisition, LLC | S36: =+INDEX('SOI Mapping'!$D:$D, MATCH(SOIs!$R36,'SOI Mapping'!$B:$B,0),0) -> Integrity Marketing | U36: Infinity Home Services Holdco, Inc. | V36: =+INDEX('SOI Mapping'!$D:$D, MATCH(SOIs!$U36,'SOI Mapping'!$B:$B,0),0) -> Infinity Home Services | X36: Dr. Scholl's
C37: Ledge Lounger, Inc. | D37: =+INDEX('SOI Mapping'!$D:$D, MATCH(SOIs!$C37,'SOI Mapping'!$B:$B,0),0) -> Ledge Lounger | F37: Inception Fertility Ventures, LLC | G37: =+INDEX('SOI Mapping'!$D:$D, MATCH(SOIs!$F37,'SOI Mapping'!$B:$B,0),0) -> Prelude | I37: IDC Infusion Services, Inc. | J37: =+INDEX('SOI Mapping'!$D:$D, MATCH(SOIs!$I37,'SOI Mapping'!$B:$B,0),0) -> IDC Infusion Services | L37: Mars Acquisition Holdings Corp. | M37: =+INDEX('SOI Mapping'!$D:$D, MATCH(SOIs!$L37,'SOI Mapping'!$B:$B,0),0) -> Mars Agency | O37: Idera, Inc. | P37: =+INDEX('SOI Mapping'!$D:$D, MATCH(SOIs!$O37,'SOI Mapping'!$B:$B,0),0) -> Idera | R37: Inventus Power, Inc. | S37: =+INDEX('SOI Mapping'!$D:$D, MATCH(SOIs!$R37,'SOI Mapping'!$B:$B,0),0) -> Inventus | U37: Infolinks Media Buyco, LLC | V37: =+INDEX('SOI Mapping'!$D:$D, MATCH(SOIs!$U37,'SOI Mapping'!$B:$B,0),0) -> Infolinks | X37: Dr. Squatch
C38: Lightspeed Buyer Inc. | D38: =+INDEX('SOI Mapping'!$D:$D, MATCH(SOIs!$C38,'SOI Mapping'!$B:$B,0),0) -> Centauri Health | F38: Integrated Data Services | G38: Integrated Data Services | I38: IG Investments Holdings, LLC | J38: =+INDEX('SOI Mapping'!$D:$D, MATCH(SOIs!$I38,'SOI Mapping'!$B:$B,0),0) -> Insight Global | L38: MBS Holdings, Inc. | M38: =+INDEX('SOI Mapping'!$D:$D, MATCH(SOIs!$L38,'SOI Mapping'!$B:$B,0),0) -> Momentum | O38: Inception Fertility Ventures, LLC | P38: =+INDEX('SOI Mapping'!$D:$D, MATCH(SOIs!$O38,'SOI Mapping'!$B:$B,0),0) -> Prelude | R38: ITI Holdings, Inc. | S38: =+INDEX('SOI Mapping'!$D:$D, MATCH(SOIs!$R38,'SOI Mapping'!$B:$B,0),0) -> Intellectual Technology | U38: Integrity Marketing Acquisition, LLC | V38: =+INDEX('SOI Mapping'!$D:$D, MATCH(SOIs!$U38,'SOI Mapping'!$B:$B,0),0) -> Integrity Marketing | X38: Edelman
C39: MAG DS Corp. | D39: =+INDEX('SOI Mapping'!$D:$D, MATCH(SOIs!$C39,'SOI Mapping'!$B:$B,0),0) -> MAG Aerospace | F39: Integrative Nutrition, LLC | G39: =+INDEX('SOI Mapping'!$D:$D, MATCH(SOIs!$F39,'SOI Mapping'!$B:$B,0),0) -> Integrative Nutrition | I39: Inception Fertility Ventures, LLC | J39: =+INDEX('SOI Mapping'!$D:$D, MATCH(SOIs!$I39,'SOI Mapping'!$B:$B,0),0) -> Prelude | L39: Municipal Emergency Services, Inc. | M39: =+INDEX('SOI Mapping'!$D:$D, MATCH(SOIs!$L39,'SOI Mapping'!$B:$B,0),0) -> MES | O39: Infinity Home Services Holdco, Inc. | P39: =+INDEX('SOI Mapping'!$D:$D, MATCH(SOIs!$O39,'SOI Mapping'!$B:$B,0),0) -> Infinity Home Services | R39: K2 Pure Solutions NoCal, L.P. | S39: =+INDEX('SOI Mapping'!$D:$D, MATCH(SOIs!$R39,'SOI Mapping'!$B:$B,0),0) -> K2 | U39: K2 Pure Solutions NoCal, L.P. | V39: =+INDEX('SOI Mapping'!$D:$D, MATCH(SOIs!$U39,'SOI Mapping'!$B:$B,0),0) -> K2 | X39: Electro Rent
C40: Mars Acquisition Holdings Corp. | D40: =+INDEX('SOI Mapping'!$D:$D, MATCH(SOIs!$C40,'SOI Mapping'!$B:$B,0),0) -> Mars Agency | F40: K2 Pure Solutions NoCal, L.P. | G40: =+INDEX('SOI Mapping'!$D:$D, MATCH(SOIs!$F40,'SOI Mapping'!$B:$B,0),0) -> K2 | I40: Infolinks Media Buyco, LLC | J40: =+INDEX('SOI Mapping'!$D:$D, MATCH(SOIs!$I40,'SOI Mapping'!$B:$B,0),0) -> Infolinks | L40: NBH Group LLC | M40: =+INDEX('SOI Mapping'!$D:$D, MATCH(SOIs!$L40,'SOI Mapping'!$B:$B,0),0) -> Nevada Behavioral Health Systems | O40: Infolinks Media Buyco, LLC | P40: =+INDEX('SOI Mapping'!$D:$D, MATCH(SOIs!$O40,'SOI Mapping'!$B:$B,0),0) -> Infolinks | R40: Kinetic Purchaser, LLC | S40: =+INDEX('SOI Mapping'!$D:$D, MATCH(SOIs!$R40,'SOI Mapping'!$B:$B,0),0) -> KNS | U40: Kinetic Purchaser, LLC | V40: =+INDEX('SOI Mapping'!$D:$D, MATCH(SOIs!$U40,'SOI Mapping'!$B:$B,0),0) -> KNS | X40: Engine & Transmission Exchange
C41: MDI Buyer, Inc. | D41: =+INDEX('SOI Mapping'!$D:$D, MATCH(SOIs!$C41,'SOI Mapping'!$B:$B,0),0) -> Molded Devices | F41: Kinetic Purchaser, LLC | G41: =+INDEX('SOI Mapping'!$D:$D, MATCH(SOIs!$F41,'SOI Mapping'!$B:$B,0),0) -> KNS | I41: Integrity Marketing Acquisition, LLC | J41: =+INDEX('SOI Mapping'!$D:$D, MATCH(SOIs!$I41,'SOI Mapping'!$B:$B,0),0) -> Integrity Marketing | L41: One Stop Mailing, LLC | M41: =+INDEX('SOI Mapping'!$D:$D, MATCH(SOIs!$L41,'SOI Mapping'!$B:$B,0),0) -> OSM | O41: Integrity Marketing Acquisition, LLC | P41: =+INDEX('SOI Mapping'!$D:$D, MATCH(SOIs!$O41,'SOI Mapping'!$B:$B,0),0) -> Integrity Marketing | R41: Lash OpCo, LLC | S41: =+INDEX('SOI Mapping'!$D:$D, MATCH(SOIs!$R41,'SOI Mapping'!$B:$B,0),0) -> Lilly Lashes | U41: LAV Gear Holdings, Inc. | V41: =+INDEX('SOI Mapping'!$D:$D, MATCH(SOIs!$U41,'SOI Mapping'!$B:$B,0),0) -> 4Wall Entertainment | X41: Epiq
C42: Meadowlark Acquirer, LLC | D42: =+INDEX('SOI Mapping'!$D:$D, MATCH(SOIs!$C42,'SOI Mapping'!$B:$B,0),0) -> Meadowlark | F42: Lash OpCo, LLC | G42: =+INDEX('SOI Mapping'!$D:$D, MATCH(SOIs!$F42,'SOI Mapping'!$B:$B,0),0) -> Lilly Lashes | I42: ITI Holdings, Inc. | J42: =+INDEX('SOI Mapping'!$D:$D, MATCH(SOIs!$I42,'SOI Mapping'!$B:$B,0),0) -> Intellectual Technology | L42: Owl Acquisition, LLC | M42: =+INDEX('SOI Mapping'!$D:$D, MATCH(SOIs!$L42,'SOI Mapping'!$B:$B,0),0) -> Wilson Language Training | O42: ITI Holdings, Inc. | P42: =+INDEX('SOI Mapping'!$D:$D, MATCH(SOIs!$O42,'SOI Mapping'!$B:$B,0),0) -> Intellectual Technology | R42: LAV Gear Holdings, Inc. | S42: =+INDEX('SOI Mapping'!$D:$D, MATCH(SOIs!$R42,'SOI Mapping'!$B:$B,0),0) -> 4Wall Entertainment | U42: Lash OpCo, LLC | V42: =+INDEX('SOI Mapping'!$D:$D, MATCH(SOIs!$U42,'SOI Mapping'!$B:$B,0),0) -> Lilly Lashes | X42: Exigo
C43: Mission Critical Electronics Inc. | D43: =+INDEX('SOI Mapping'!$D:$D, MATCH(SOIs!$C43,'SOI Mapping'!$B:$B,0),0) -> Mission Critical Electronics | F43: LAV Gear Holdings, Inc. | G43: =+INDEX('SOI Mapping'!$D:$D, MATCH(SOIs!$F43,'SOI Mapping'!$B:$B,0),0) -> 4Wall Entertainment | I43: Kinetic Purchaser, LLC | J43: =+INDEX('SOI Mapping'!$D:$D, MATCH(SOIs!$I43,'SOI Mapping'!$B:$B,0),0) -> KNS | L43: PlayPower, Inc. | M43: =+INDEX('SOI Mapping'!$D:$D, MATCH(SOIs!$L43,'SOI Mapping'!$B:$B,0),0) -> PlayPower | O43: Kinetic Purchaser, LLC | P43: =+INDEX('SOI Mapping'!$D:$D, MATCH(SOIs!$O43,'SOI Mapping'!$B:$B,0),0) -> KNS | R43: Lightspeed Buyer Inc. | S43: =+INDEX('SOI Mapping'!$D:$D, MATCH(SOIs!$R43,'SOI Mapping'!$B:$B,0),0) -> Centauri Health | U43: Lightspeed Buyer Inc. | V43: =+INDEX('SOI Mapping'!$D:$D, MATCH(SOIs!$U43,'SOI Mapping'!$B:$B,0),0) -> Centauri Health | X43: Fairbanks Morse Defense
C44: Municipal Emergency Services, Inc. | D44: Questex | F44: Lightspeed Buyer Inc. | G44: =+INDEX('SOI Mapping'!$D:$D, MATCH(SOIs!$F44,'SOI Mapping'!$B:$B,0),0) -> Centauri Health | I44: Lash OpCo, LLC | J44: =+INDEX('SOI Mapping'!$D:$D, MATCH(SOIs!$I44,'SOI Mapping'!$B:$B,0),0) -> Lilly Lashes | L44: Quantic Electronics, LLC | M44: =+INDEX('SOI Mapping'!$D:$D, MATCH(SOIs!$L44,'SOI Mapping'!$B:$B,0),0) -> Quantic Electronics | O44: Lash OpCo, LLC | P44: =+INDEX('SOI Mapping'!$D:$D, MATCH(SOIs!$O44,'SOI Mapping'!$B:$B,0),0) -> Lilly Lashes | R44: LJ Avalon Holdings, LLC - Term Loan | S44: Ardurra | U44: LJ Avalon Holdings, LLC | V44: =+INDEX('SOI Mapping'!$D:$D, MATCH(SOIs!$U44,'SOI Mapping'!$B:$B,0),0) -> Ardurra | X44: Five Star
C45: One Stop Mailing, LLC | D45: =+INDEX('SOI Mapping'!$D:$D, MATCH(SOIs!$C45,'SOI Mapping'!$B:$B,0),0) -> OSM | F45: Lucky Bucks, LLC | G45: =+INDEX('SOI Mapping'!$D:$D, MATCH(SOIs!$F45,'SOI Mapping'!$B:$B,0),0) -> Lucky Bucks | I45: Ledge Lounger, Inc. | J45: =+INDEX('SOI Mapping'!$D:$D, MATCH(SOIs!$I45,'SOI Mapping'!$B:$B,0),0) -> Ledge Lounger | L45: Radius Aerospace, Inc. | M45: =+INDEX('SOI Mapping'!$D:$D, MATCH(SOIs!$L45,'SOI Mapping'!$B:$B,0),0) -> Radius Aerospace | O45: Ledge Lounger, Inc. | P45: =+INDEX('SOI Mapping'!$D:$D, MATCH(SOIs!$O45,'SOI Mapping'!$B:$B,0),0) -> Ledge Lounger | R45: MAG DS Corp | S45: MAG Aerospace | U45: MAG DS Corp. | V45: =+INDEX('SOI Mapping'!$D:$D, MATCH(SOIs!$U45,'SOI Mapping'!$B:$B,0),0) -> MAG Aerospace | X45: GCOM
C46: ORL Acquisition, Inc. | D46: =+INDEX('SOI Mapping'!$D:$D, MATCH(SOIs!$C46,'SOI Mapping'!$B:$B,0),0) -> OpenRoad Lending | F46: MAG DS Corp | G46: MAG Aerospace | I46: Lightspeed Buyer Inc. | J46: =+INDEX('SOI Mapping'!$D:$D, MATCH(SOIs!$I46,'SOI Mapping'!$B:$B,0),0) -> Centauri Health | L46: Rancho Health MSO, Inc. | M46: =+INDEX('SOI Mapping'!$D:$D, MATCH(SOIs!$L46,'SOI Mapping'!$B:$B,0),0) -> Rancho Medical | O46: Lightspeed Buyer Inc. | P46: =+INDEX('SOI Mapping'!$D:$D, MATCH(SOIs!$O46,'SOI Mapping'!$B:$B,0),0) -> Centauri Health | R46: Magenta Buyer, LLC | S46: =+INDEX('SOI Mapping'!$D:$D, MATCH(SOIs!$R46,'SOI Mapping'!$B:$B,0),0) -> McAfee | U46: Mars Acquisition Holdings Corp. | V46: =+INDEX('SOI Mapping'!$D:$D, MATCH(SOIs!$U46,'SOI Mapping'!$B:$B,0),0) -> Mars Agency | X46: Gen3 Marketing
C47: Owl Acquisition, LLC | D47: =+INDEX('SOI Mapping'!$D:$D, MATCH(SOIs!$C47,'SOI Mapping'!$B:$B,0),0) -> Wilson Language Training | F47: Mars Acquisition Holdings Corp. | G47: =+INDEX('SOI Mapping'!$D:$D, MATCH(SOIs!$F47,'SOI Mapping'!$B:$B,0),0) -> Mars Agency | I47: Magenta Buyer, LLC | J47: =+INDEX('SOI Mapping'!$D:$D, MATCH(SOIs!$I47,'SOI Mapping'!$B:$B,0),0) -> McAfee | L47: Recteq, LLC | M47: =+INDEX('SOI Mapping'!$D:$D, MATCH(SOIs!$L47,'SOI Mapping'!$B:$B,0),0) -> Recteq | O47: LSF9 Atlantis Holdings, LLC | P47: =+INDEX('SOI Mapping'!$D:$D, MATCH(SOIs!$O47,'SOI Mapping'!$B:$B,0),0) -> Victra | R47: Mars Acquisition Holdings Corp. | S47: =+INDEX('SOI Mapping'!$D:$D, MATCH(SOIs!$R47,'SOI Mapping'!$B:$B,0),0) -> Mars Agency | U47: MBS Holdings, Inc. | V47: =+INDEX('SOI Mapping'!$D:$D, MATCH(SOIs!$U47,'SOI Mapping'!$B:$B,0),0) -> Momentum | X47: Global
C48: Ox Two, LLC (New Issue) | D48: =+INDEX('SOI Mapping'!$D:$D, MATCH(SOIs!$C48,'SOI Mapping'!$B:$B,0),0) -> Ox | F48: MBS Holdings, Inc. | G48: =+INDEX('SOI Mapping'!$D:$D, MATCH(SOIs!$F48,'SOI Mapping'!$B:$B,0),0) -> Momentum | I48: Mars Acquisition Holdings Corp. | J48: =+INDEX('SOI Mapping'!$D:$D, MATCH(SOIs!$I48,'SOI Mapping'!$B:$B,0),0) -> Mars Agency | L48: Research Now Group, LLC and Dynata, LLC | M48: =+INDEX('SOI Mapping'!$D:$D, MATCH(SOIs!$L48,'SOI Mapping'!$B:$B,0),0) -> Research Now/SSI | O48: Magenta Buyer, LLC | P48: =+INDEX('SOI Mapping'!$D:$D, MATCH(SOIs!$O48,'SOI Mapping'!$B:$B,0),0) -> McAfee | R48: MBS Holdings, Inc. | S48: =+INDEX('SOI Mapping'!$D:$D, MATCH(SOIs!$R48,'SOI Mapping'!$B:$B,0),0) -> Momentum | U48: Municipal Emergency Services, Inc. | V48: =+INDEX('SOI Mapping'!$D:$D, MATCH(SOIs!$U48,'SOI Mapping'!$B:$B,0),0) -> MES | X48: Hancock
C49: PlayPower, Inc. | D49: =+INDEX('SOI Mapping'!$D:$D, MATCH(SOIs!$C49,'SOI Mapping'!$B:$B,0),0) -> PlayPower | F49: MDI Buyer, Inc. | G49: Molded Devices | I49: MBS Holdings, Inc. | J49: =+INDEX('SOI Mapping'!$D:$D, MATCH(SOIs!$I49,'SOI Mapping'!$B:$B,0),0) -> Momentum | L49: Riverpoint Medical, LLC | M49: =+INDEX('SOI Mapping'!$D:$D, MATCH(SOIs!$L49,'SOI Mapping'!$B:$B,0),0) -> Riverpoint | O49: MDI Buyer, Inc. | P49: =+INDEX('SOI Mapping'!$D:$D, MATCH(SOIs!$O49,'SOI Mapping'!$B:$B,0),0) -> Molded Devices | R49: MDI Buyer, Inc. | S49: Molded Devices | U49: NBH Group LLC | V49: =+INDEX('SOI Mapping'!$D:$D, MATCH(SOIs!$U49,'SOI Mapping'!$B:$B,0),0) -> Nevada Behavioral Health Systems | X49: Hanley Wood
C50: Quantic Electronics, LLC | D50: =+INDEX('SOI Mapping'!$D:$D, MATCH(SOIs!$C50,'SOI Mapping'!$B:$B,0),0) -> Quantic Electronics | F50: Meadowlark Acquirer, LLC | G50: =+INDEX('SOI Mapping'!$D:$D, MATCH(SOIs!$F50,'SOI Mapping'!$B:$B,0),0) -> Meadowlark | I50: Meadowlark Acquirer, LLC | J50: =+INDEX('SOI Mapping'!$D:$D, MATCH(SOIs!$I50,'SOI Mapping'!$B:$B,0),0) -> Meadowlark | L50: Riverside Assessments, LLC | M50: =+INDEX('SOI Mapping'!$D:$D, MATCH(SOIs!$L50,'SOI Mapping'!$B:$B,0),0) -> Riverside Insights | O50: Meadowlark Acquirer, LLC | P50: =+INDEX('SOI Mapping'!$D:$D, MATCH(SOIs!$O50,'SOI Mapping'!$B:$B,0),0) -> Meadowlark | R50: Mission Critical Electronics, Inc. | S50: =+INDEX('SOI Mapping'!$D:$D, MATCH(SOIs!$R50,'SOI Mapping'!$B:$B,0),0) -> Mission Critical Electronics | U50: Neptune Flood Incorporated | V50: =+INDEX('SOI Mapping'!$D:$D, MATCH(SOIs!$U50,'SOI Mapping'!$B:$B,0),0) -> Neptune Flood | X50: Hightower
C51: Questex, LLC | D51: =+INDEX('SOI Mapping'!$D:$D, MATCH(SOIs!$C51,'SOI Mapping'!$B:$B,0),0) -> Questex | F51: Mission Critical Electronics, Inc. | G51: =+INDEX('SOI Mapping'!$D:$D, MATCH(SOIs!$F51,'SOI Mapping'!$B:$B,0),0) -> Mission Critical Electronics | I51: Municipal Emergency Services, Inc. | J51: =+INDEX('SOI Mapping'!$D:$D, MATCH(SOIs!$I51,'SOI Mapping'!$B:$B,0),0) -> MES | L51: Sales Benchmark Index LLC | M51: =+INDEX('SOI Mapping'!$D:$D, MATCH(SOIs!$L51,'SOI Mapping'!$B:$B,0),0) -> Sales Benchmark Index (SBI) | O51: Municipal Emergency Services, Inc. | P51: =+INDEX('SOI Mapping'!$D:$D, MATCH(SOIs!$O51,'SOI Mapping'!$B:$B,0),0) -> MES | R51: Municipal Emergency Services, Inc. | S51: =+INDEX('SOI Mapping'!$D:$D, MATCH(SOIs!$R51,'SOI Mapping'!$B:$B,0),0) -> MES | U51: One Stop Mailing, LLC | V51: =+INDEX('SOI Mapping'!$D:$D, MATCH(SOIs!$U51,'SOI Mapping'!$B:$B,0),0) -> OSM | X51: IDC Infusion Services
C52: Research Now Group, LLC and Dynata, LLC | D52: =+INDEX('SOI Mapping'!$D:$D, MATCH(SOIs!$C52,'SOI Mapping'!$B:$B,0),0) -> Research Now/SSI | F52: NBH Group LLC | G52: =+INDEX('SOI Mapping'!$D:$D, MATCH(SOIs!$F52,'SOI Mapping'!$B:$B,0),0) -> Nevada Behavioral Health Systems | I52: NBH Group LLC | J52: =+INDEX('SOI Mapping'!$D:$D, MATCH(SOIs!$I52,'SOI Mapping'!$B:$B,0),0) -> Nevada Behavioral Health Systems | L52: Sargent & Greenleaf Inc. | M52: =+INDEX('SOI Mapping'!$D:$D, MATCH(SOIs!$L52,'SOI Mapping'!$B:$B,0),0) -> Sargent & Greenleaf | O52: One Stop Mailing, LLC | P52: =+INDEX('SOI Mapping'!$D:$D, MATCH(SOIs!$O52,'SOI Mapping'!$B:$B,0),0) -> OSM | R52: NBH Group LLC | S52: =+INDEX('SOI Mapping'!$D:$D, MATCH(SOIs!$R52,'SOI Mapping'!$B:$B,0),0) -> Nevada Behavioral Health Systems | U52: Pequod Merger Sub, Inc. | V52: Simplicity Group | X52: Idera
C53: Riverpoint Medical, LLC | D53: =+INDEX('SOI Mapping'!$D:$D, MATCH(SOIs!$C53,'SOI Mapping'!$B:$B,0),0) -> Riverpoint | F53: One Stop Mailing, LLC | G53: =+INDEX('SOI Mapping'!$D:$D, MATCH(SOIs!$F53,'SOI Mapping'!$B:$B,0),0) -> OSM | I53: Neptune Flood Incorporated | J53: =+INDEX('SOI Mapping'!$D:$D, MATCH(SOIs!$I53,'SOI Mapping'!$B:$B,0),0) -> Neptune Flood | L53: Seaway Buyer, LLC | M53: =+INDEX('SOI Mapping'!$D:$D, MATCH(SOIs!$L53,'SOI Mapping'!$B:$B,0),0) -> Seaway Plastics | O53: ORL Acquisition, Inc. | P53: =+INDEX('SOI Mapping'!$D:$D, MATCH(SOIs!$O53,'SOI Mapping'!$B:$B,0),0) -> OpenRoad Lending | R53: Neptune Flood Incorporated | S53: =+INDEX('SOI Mapping'!$D:$D, MATCH(SOIs!$R53,'SOI Mapping'!$B:$B,0),0) -> Neptune Flood | U53: Rancho Health MSO, Inc. | V53: =+INDEX('SOI Mapping'!$D:$D, MATCH(SOIs!$U53,'SOI Mapping'!$B:$B,0),0) -> Rancho Medical | X53: ImagineAcquisitionCo
C54: Riverside Assessments, LLC | D54: =+INDEX('SOI Mapping'!$D:$D, MATCH(SOIs!$C54,'SOI Mapping'!$B:$B,0),0) -> Riverside Insights | F54: Ox Two, LLC | G54: =+INDEX('SOI Mapping'!$D:$D, MATCH(SOIs!$F54,'SOI Mapping'!$B:$B,0),0) -> Ox | I54: One Stop Mailing, LLC | J54: =+INDEX('SOI Mapping'!$D:$D, MATCH(SOIs!$I54,'SOI Mapping'!$B:$B,0),0) -> OSM | L54: Signature Systems Holding Company | M54: =+INDEX('SOI Mapping'!$D:$D, MATCH(SOIs!$L54,'SOI Mapping'!$B:$B,0),0) -> Signature Systems Group | O54: Owl Acquisition, LLC | P54: =+INDEX('SOI Mapping'!$D:$D, MATCH(SOIs!$O54,'SOI Mapping'!$B:$B,0),0) -> Wilson Language Training | R54: New Milani Group LLC | S54: =+INDEX('SOI Mapping'!$D:$D, MATCH(SOIs!$R54,'SOI Mapping'!$B:$B,0),0) -> Milani | U54: Reception Purchaser, LLC | V54: =+INDEX('SOI Mapping'!$D:$D, MATCH(SOIs!$U54,'SOI Mapping'!$B:$B,0),0) -> STG Logistics | X54: Infinity Home Services
C55: Sales Benchmark Index LLC | D55: =+INDEX('SOI Mapping'!$D:$D, MATCH(SOIs!$C55,'SOI Mapping'!$B:$B,0),0) -> Sales Benchmark Index (SBI) | F55: Pequod Merger Sub, Inc. - Term Loan (f/k/a Simplicity Group) | G55: Sparq | I55: ORL Acquisition, Inc. | J55: =+INDEX('SOI Mapping'!$D:$D, MATCH(SOIs!$I55,'SOI Mapping'!$B:$B,0),0) -> OpenRoad Lending | L55: Solutionreach, Inc. | M55: =+INDEX('SOI Mapping'!$D:$D, MATCH(SOIs!$L55,'SOI Mapping'!$B:$B,0),0) -> Solutionreach | O55: Ox Two, LLC (New Issue) | P55: =+INDEX('SOI Mapping'!$D:$D, MATCH(SOIs!$O55,'SOI Mapping'!$B:$B,0),0) -> Ox | R55: One Stop Mailing, LLC | S55: =+INDEX('SOI Mapping'!$D:$D, MATCH(SOIs!$R55,'SOI Mapping'!$B:$B,0),0) -> OSM | U55: Riverside Assessments, LLC | V55: =+INDEX('SOI Mapping'!$D:$D, MATCH(SOIs!$U55,'SOI Mapping'!$B:$B,0),0) -> Riverside Insights | X55: Infolinks
C56: Schlesinger Global, Inc. | D56: =+INDEX('SOI Mapping'!$D:$D, MATCH(SOIs!$C56,'SOI Mapping'!$B:$B,0),0) -> Schlesinger | F56: PH Beauty Holdings III, Inc. | G56: =+INDEX('SOI Mapping'!$D:$D, MATCH(SOIs!$F56,'SOI Mapping'!$B:$B,0),0) -> Paris Presents | I56: Output Services Group, Inc. | J56: =+INDEX('SOI Mapping'!$D:$D, MATCH(SOIs!$I56,'SOI Mapping'!$B:$B,0),0) -> OSG Billing Services | L56: STV Group Incorporated | M56: =+INDEX('SOI Mapping'!$D:$D, MATCH(SOIs!$L56,'SOI Mapping'!$B:$B,0),0) -> STV Group | O56: PL Acquisitionco, LLC | P56: =+INDEX('SOI Mapping'!$D:$D, MATCH(SOIs!$O56,'SOI Mapping'!$B:$B,0),0) -> Pink Lily | R56: ORL Acquisition, Inc. - Term Loan | S56: OpenRoad Lending | U56: Rural Sourcing Holdings, Inc. (HPA SPQ Merger Sub, Inc.) | V56: Sparq | X56: Insight Global
C57: Sigma Defense Systems, LLC | D57: =+INDEX('SOI Mapping'!$D:$D, MATCH(SOIs!$C57,'SOI Mapping'!$B:$B,0),0) -> Sigma Defense | F57: PL Acquisitionco, LLC | G57: =+INDEX('SOI Mapping'!$D:$D, MATCH(SOIs!$F57,'SOI Mapping'!$B:$B,0),0) -> Pink Lily | I57: Owl Acquisition, LLC | J57: =+INDEX('SOI Mapping'!$D:$D, MATCH(SOIs!$I57,'SOI Mapping'!$B:$B,0),0) -> Wilson Language Training | L57: System Planning and Analysis, Inc. (f/k/a Management Consulting & Research, LLC) | M57: =+INDEX('SOI Mapping'!$D:$D, MATCH(SOIs!$L57,'SOI Mapping'!$B:$B,0),0) -> MCR | O57: Quantic Electronics, LLC | P57: =+INDEX('SOI Mapping'!$D:$D, MATCH(SOIs!$O57,'SOI Mapping'!$B:$B,0),0) -> Quantic Electronics | R57: Owl Acquisition, LLC | S57: =+INDEX('SOI Mapping'!$D:$D, MATCH(SOIs!$R57,'SOI Mapping'!$B:$B,0),0) -> Wilson Language Training | U57: Sales Benchmark Index LLC | V57: =+INDEX('SOI Mapping'!$D:$D, MATCH(SOIs!$U57,'SOI Mapping'!$B:$B,0),0) -> Sales Benchmark Index (SBI) | X57: Integrated Data Services
C58: Signature Systems Holding Company | D58: =+INDEX('SOI Mapping'!$D:$D, MATCH(SOIs!$C58,'SOI Mapping'!$B:$B,0),0) -> Signature Systems Group | F58: PlayPower, Inc. | G58: =+INDEX('SOI Mapping'!$D:$D, MATCH(SOIs!$F58,'SOI Mapping'!$B:$B,0),0) -> PlayPower | I58: Ox Two, LLC | J58: =+INDEX('SOI Mapping'!$D:$D, MATCH(SOIs!$I58,'SOI Mapping'!$B:$B,0),0) -> Ox | L58: Teneo Holdings LLC | M58: =+INDEX('SOI Mapping'!$D:$D, MATCH(SOIs!$L58,'SOI Mapping'!$B:$B,0),0) -> Teneo | O58: Quantic Electronics, LLC - Unfunded Term Loan | P58: =+INDEX('SOI Mapping'!$D:$D, MATCH(SOIs!$O58,'SOI Mapping'!$B:$B,0),0) -> Quantic Electronics | R58: Pequod Merger Sub, Inc. - Term Loan (f/k/a Simplicity Group) | S58: Sparq | U58: Seaway Buyer, LLC | V58: =+INDEX('SOI Mapping'!$D:$D, MATCH(SOIs!$U58,'SOI Mapping'!$B:$B,0),0) -> Seaway Plastics | X58: Integrity Marketing
C59: Skopima Consilio Parent, LLC | D59: =+INDEX('SOI Mapping'!$D:$D, MATCH(SOIs!$C59,'SOI Mapping'!$B:$B,0),0) -> Consilio | F59: Pragmatic Institute, LLC | G59: =+INDEX('SOI Mapping'!$D:$D, MATCH(SOIs!$F59,'SOI Mapping'!$B:$B,0),0) -> Pragmatic Institute | I59: PH Beauty Holdings III, Inc. | J59: =+INDEX('SOI Mapping'!$D:$D, MATCH(SOIs!$I59,'SOI Mapping'!$B:$B,0),0) -> Paris Presents | L59: The Aegis Technologies Group, LLC | M59: =+INDEX('SOI Mapping'!$D:$D, MATCH(SOIs!$L59,'SOI Mapping'!$B:$B,0),0) -> BlueHalo | O59: Reception Purchaser, LLC | P59: =+INDEX('SOI Mapping'!$D:$D, MATCH(SOIs!$O59,'SOI Mapping'!$B:$B,0),0) -> STG Logistics | R59: PL Acquisitionco, LLC | S59: =+INDEX('SOI Mapping'!$D:$D, MATCH(SOIs!$R59,'SOI Mapping'!$B:$B,0),0) -> Pink Lily | U59: Signature Systems Holding Company | V59: =+INDEX('SOI Mapping'!$D:$D, MATCH(SOIs!$U59,'SOI Mapping'!$B:$B,0),0) -> Signature Systems Group | X59: Intellectual Technology
C60: Solutionreach, Inc. | D60: =+INDEX('SOI Mapping'!$D:$D, MATCH(SOIs!$C60,'SOI Mapping'!$B:$B,0),0) -> Solutionreach | F60: Quantic Electronics, LLC | G60: =+INDEX('SOI Mapping'!$D:$D, MATCH(SOIs!$F60,'SOI Mapping'!$B:$B,0),0) -> Quantic Electronics | I60: PL Acquisitionco, LLC | J60: =+INDEX('SOI Mapping'!$D:$D, MATCH(SOIs!$I60,'SOI Mapping'!$B:$B,0),0) -> Pink Lily | L60: The Bluebird Group LLC | M60: =+INDEX('SOI Mapping'!$D:$D, MATCH(SOIs!$L60,'SOI Mapping'!$B:$B,0),0) -> Bluebird | O60: Research Now Group, LLC and Dynata, LLC | P60: =+INDEX('SOI Mapping'!$D:$D, MATCH(SOIs!$O60,'SOI Mapping'!$B:$B,0),0) -> Research Now/SSI | R60: Pragmatic Institute, LLC | S60: =+INDEX('SOI Mapping'!$D:$D, MATCH(SOIs!$R60,'SOI Mapping'!$B:$B,0),0) -> Pragmatic Institute | U60: Skopima Consilio Parent, LLC | V60: =+INDEX('SOI Mapping'!$D:$D, MATCH(SOIs!$U60,'SOI Mapping'!$B:$B,0),0) -> Consilio | X60: Inventus
C61: STV Group Incorporated | D61: =+INDEX('SOI Mapping'!$D:$D, MATCH(SOIs!$C61,'SOI Mapping'!$B:$B,0),0) -> STV Group | F61: Recteq, LLC | G61: =+INDEX('SOI Mapping'!$D:$D, MATCH(SOIs!$F61,'SOI Mapping'!$B:$B,0),0) -> Recteq | I61: Quantic Electronics, LLC | J61: =+INDEX('SOI Mapping'!$D:$D, MATCH(SOIs!$I61,'SOI Mapping'!$B:$B,0),0) -> Quantic Electronics | L61: The Vertex Companies, LLC | M61: =+INDEX('SOI Mapping'!$D:$D, MATCH(SOIs!$L61,'SOI Mapping'!$B:$B,0),0) -> Vertex | O61: Riverside Assessments, LLC | P61: =+INDEX('SOI Mapping'!$D:$D, MATCH(SOIs!$O61,'SOI Mapping'!$B:$B,0),0) -> Riverside Insights | R61: Rancho Health MSO, Inc. | S61: Rancho Medical | U61: Solutionreach, Inc. | V61: =+INDEX('SOI Mapping'!$D:$D, MATCH(SOIs!$U61,'SOI Mapping'!$B:$B,0),0) -> Solutionreach | X61: K2
C62: System Planning and Analysis, Inc. (f/k/a Management Consulting & Research, LLC) | D62: =+INDEX('SOI Mapping'!$D:$D, MATCH(SOIs!$C62,'SOI Mapping'!$B:$B,0),0) -> MCR | F62: Research Now Group, LLC and Dynata, LLC | G62: =+INDEX('SOI Mapping'!$D:$D, MATCH(SOIs!$F62,'SOI Mapping'!$B:$B,0),0) -> Research Now/SSI | I62: Rancho Health MSO, Inc. | J62: =+INDEX('SOI Mapping'!$D:$D, MATCH(SOIs!$I62,'SOI Mapping'!$B:$B,0),0) -> Rancho Medical | L62: TPC Canada Parent, Inc. and TPC US Parent, LLC | M62: =+INDEX('SOI Mapping'!$D:$D, MATCH(SOIs!$L62,'SOI Mapping'!$B:$B,0),0) -> Targeted Pet Care | O62: Sales Benchmark Index LLC | P62: =+INDEX('SOI Mapping'!$D:$D, MATCH(SOIs!$O62,'SOI Mapping'!$B:$B,0),0) -> Sales Benchmark Index (SBI) | R62: Reception Purchaser, LLC | S62: STG Logistics | U62: SpendMend Holdings, LLC | V62: SpendMend | X62: KNS
C63: Teneo Holdings LLC | D63: =+INDEX('SOI Mapping'!$D:$D, MATCH(SOIs!$C63,'SOI Mapping'!$B:$B,0),0) -> Teneo | F63: Sales Benchmark Index LLC | G63: =+INDEX('SOI Mapping'!$D:$D, MATCH(SOIs!$F63,'SOI Mapping'!$B:$B,0),0) -> Sales Benchmark Index (SBI) | I63: Rancho Health MSO, Inc. - Unfunded Term Loan | J63: =+INDEX('SOI Mapping'!$D:$D, MATCH(SOIs!$I63,'SOI Mapping'!$B:$B,0),0) -> Rancho Medical | L63: TWS Acquisition Corporation | M63: =+INDEX('SOI Mapping'!$D:$D, MATCH(SOIs!$L63,'SOI Mapping'!$B:$B,0),0) -> StrataTech | O63: Seaway Buyer, LLC | P63: =+INDEX('SOI Mapping'!$D:$D, MATCH(SOIs!$O63,'SOI Mapping'!$B:$B,0),0) -> Seaway Plastics | R63: Rural Sourcing Holdings, Inc. (HPA SPQ Merger Sub, Inc.) | S63: Sparq | U63: STV Group Incorporated | V63: =+INDEX('SOI Mapping'!$D:$D, MATCH(SOIs!$U63,'SOI Mapping'!$B:$B,0),0) -> STV Group | X63: Kroll
C64: The Aegis Technologies Group, LLC | D64: =+INDEX('SOI Mapping'!$D:$D, MATCH(SOIs!$C64,'SOI Mapping'!$B:$B,0),0) -> BlueHalo | F64: Sargent & Greenleaf Inc. | G64: =+INDEX('SOI Mapping'!$D:$D, MATCH(SOIs!$F64,'SOI Mapping'!$B:$B,0),0) -> Sargent & Greenleaf | I64: Reception Purchaser, LLC | J64: =+INDEX('SOI Mapping'!$D:$D, MATCH(SOIs!$I64,'SOI Mapping'!$B:$B,0),0) -> STG Logistics | L64: Tyto Athene, LLC | M64: =+INDEX('SOI Mapping'!$D:$D, MATCH(SOIs!$L64,'SOI Mapping'!$B:$B,0),0) -> Tyto Athene | O64: Sigma Defense Systems, LLC | P64: =+INDEX('SOI Mapping'!$D:$D, MATCH(SOIs!$O64,'SOI Mapping'!$B:$B,0),0) -> Sigma Defense | R64: Sales Benchmark Index LLC | S64: =+INDEX('SOI Mapping'!$D:$D, MATCH(SOIs!$R64,'SOI Mapping'!$B:$B,0),0) -> Sales Benchmark Index (SBI) | U64: Summit Behavioral Healthcare, LLC | V64: =+INDEX('SOI Mapping'!$D:$D, MATCH(SOIs!$U64,'SOI Mapping'!$B:$B,0),0) -> Summit Behavioral Healthcare | X64: Ledge Lounger
C65: The Bluebird Group LLC | D65: =+INDEX('SOI Mapping'!$D:$D, MATCH(SOIs!$C65,'SOI Mapping'!$B:$B,0),0) -> Bluebird | F65: Sigma Defense Systems, LLC | G65: =+INDEX('SOI Mapping'!$D:$D, MATCH(SOIs!$F65,'SOI Mapping'!$B:$B,0),0) -> Sigma Defense | I65: Recteq, LLC | J65: =+INDEX('SOI Mapping'!$D:$D, MATCH(SOIs!$I65,'SOI Mapping'!$B:$B,0),0) -> Recteq | L65: Wildcat Buyerco, Inc. | M65: =+INDEX('SOI Mapping'!$D:$D, MATCH(SOIs!$L65,'SOI Mapping'!$B:$B,0),0) -> Nsi Industries | O65: Skopima Consilio Parent, LLC | P65: =+INDEX('SOI Mapping'!$D:$D, MATCH(SOIs!$O65,'SOI Mapping'!$B:$B,0),0) -> Consilio | R65: Schlesinger Global, Inc. | S65: Schlesinger | U65: System Planning and Analysis, Inc. (f/k/a Management Consulting & Research, LLC) | V65: =+INDEX('SOI Mapping'!$D:$D, MATCH(SOIs!$U65,'SOI Mapping'!$B:$B,0),0) -> MCR | X65: Lilly Lashes
C66: The Vertex Companies, LLC | D66: =+INDEX('SOI Mapping'!$D:$D, MATCH(SOIs!$C66,'SOI Mapping'!$B:$B,0),0) -> Vertex | F66: Skopima Consilio Parent, LLC | G66: =+INDEX('SOI Mapping'!$D:$D, MATCH(SOIs!$F66,'SOI Mapping'!$B:$B,0),0) -> Consilio | I66: Research Now Group, LLC and Dynata, LLC | J66: =+INDEX('SOI Mapping'!$D:$D, MATCH(SOIs!$I66,'SOI Mapping'!$B:$B,0),0) -> Research Now/SSI | L66: Zips Car Wash, LLC | M66: =+INDEX('SOI Mapping'!$D:$D, MATCH(SOIs!$L66,'SOI Mapping'!$B:$B,0),0) -> Zips | O66: Summit Behavioral Healthcare, LLC | P66: =+INDEX('SOI Mapping'!$D:$D, MATCH(SOIs!$O66,'SOI Mapping'!$B:$B,0),0) -> Summit Behavioral Healthcare | R66: Seaway Buyer, LLC | S66: Seaway Plastics | U66: Team Services Group, LLC | V66: =+INDEX('SOI Mapping'!$D:$D, MATCH(SOIs!$U66,'SOI Mapping'!$B:$B,0),0) -> TEAM Services Group | X66: MAG Aerospace
C67: TPC Canada Parent, Inc. and TPC US Parent, LLC | D67: =+INDEX('SOI Mapping'!$D:$D, MATCH(SOIs!$C67,'SOI Mapping'!$B:$B,0),0) -> Targeted Pet Care | F67: Smile Brands Inc. | G67: =+INDEX('SOI Mapping'!$D:$D, MATCH(SOIs!$F67,'SOI Mapping'!$B:$B,0),0) -> Smile Brands | I67: Riverside Assessments, LLC | J67: =+INDEX('SOI Mapping'!$D:$D, MATCH(SOIs!$I67,'SOI Mapping'!$B:$B,0),0) -> Riverside Insights | O67: System Planning and Analysis, Inc. (f/k/a Management Consulting & Research, LLC) | P67: =+INDEX('SOI Mapping'!$D:$D, MATCH(SOIs!$O67,'SOI Mapping'!$B:$B,0),0) -> MCR | R67: Sigma Defense Systems, LLC | S67: =+INDEX('SOI Mapping'!$D:$D, MATCH(SOIs!$R67,'SOI Mapping'!$B:$B,0),0) -> Sigma Defense | U67: The Bluebird Group LLC | V67: =+INDEX('SOI Mapping'!$D:$D, MATCH(SOIs!$U67,'SOI Mapping'!$B:$B,0),0) -> Bluebird | X67: Mars Agency
C68: TWS Acquisition Corporation | D68: =+INDEX('SOI Mapping'!$D:$D, MATCH(SOIs!$C68,'SOI Mapping'!$B:$B,0),0) -> StrataTech | F68: Solutionreach, Inc. | G68: =+INDEX('SOI Mapping'!$D:$D, MATCH(SOIs!$F68,'SOI Mapping'!$B:$B,0),0) -> Solutionreach | I68: Sigma Defense Systems, LLC | J68: =+INDEX('SOI Mapping'!$D:$D, MATCH(SOIs!$I68,'SOI Mapping'!$B:$B,0),0) -> Sigma Defense | O68: Team Services Group, LLC | P68: =+INDEX('SOI Mapping'!$D:$D, MATCH(SOIs!$O68,'SOI Mapping'!$B:$B,0),0) -> TEAM Services Group | R68: Skopima Consilio Parent, LLC | S68: =+INDEX('SOI Mapping'!$D:$D, MATCH(SOIs!$R68,'SOI Mapping'!$B:$B,0),0) -> Consilio | U68: The Vertex Companies, LLC | V68: =+INDEX('SOI Mapping'!$D:$D, MATCH(SOIs!$U68,'SOI Mapping'!$B:$B,0),0) -> Vertex | X68: McAfee
C69: Tyto Athene, LLC (New Issue) | D69: =+INDEX('SOI Mapping'!$D:$D, MATCH(SOIs!$C69,'SOI Mapping'!$B:$B,0),0) -> Tyto Athene | F69: STV Group Incorporated | G69: =+INDEX('SOI Mapping'!$D:$D, MATCH(SOIs!$F69,'SOI Mapping'!$B:$B,0),0) -> STV Group | I69: Smile Brands, Inc. | J69: =+INDEX('SOI Mapping'!$D:$D, MATCH(SOIs!$I69,'SOI Mapping'!$B:$B,0),0) -> Smile Brands | O69: Teneo Holdings LLC | P69: =+INDEX('SOI Mapping'!$D:$D, MATCH(SOIs!$O69,'SOI Mapping'!$B:$B,0),0) -> Teneo | R69: Solutionreach, Inc. | S69: =+INDEX('SOI Mapping'!$D:$D, MATCH(SOIs!$R69,'SOI Mapping'!$B:$B,0),0) -> Solutionreach | U69: TWS Acquisition Corporation | V69: =+INDEX('SOI Mapping'!$D:$D, MATCH(SOIs!$U69,'SOI Mapping'!$B:$B,0),0) -> StrataTech | X69: MCR
C70: Walker Edison Furniture, LLC | D70: Walker Edison | F70: System Planning and Analysis, Inc. (f/k/a Management Consulting & Research, LLC) | G70: =+INDEX('SOI Mapping'!$D:$D, MATCH(SOIs!$F70,'SOI Mapping'!$B:$B,0),0) -> MCR | I70: Southern Veterinary Partners, LLC | J70: =+INDEX('SOI Mapping'!$D:$D, MATCH(SOIs!$I70,'SOI Mapping'!$B:$B,0),0) -> Southern Veterinary Partners | O70: The Bluebird Group LLC | P70: =+INDEX('SOI Mapping'!$D:$D, MATCH(SOIs!$O70,'SOI Mapping'!$B:$B,0),0) -> Bluebird | R70: Spendmend Holdings LLC | S70: =+INDEX('SOI Mapping'!$D:$D, MATCH(SOIs!$R70,'SOI Mapping'!$B:$B,0),0) -> SpendMend | U70: Urology Management Holdings, Inc. | V70: =+INDEX('SOI Mapping'!$D:$D, MATCH(SOIs!$U70,'SOI Mapping'!$B:$B,0),0) -> Solaris Health | X70: Meadowlark
C71: Wildcat Buyerco, Inc. | D71: =+INDEX('SOI Mapping'!$D:$D, MATCH(SOIs!$C71,'SOI Mapping'!$B:$B,0),0) -> Nsi Industries | F71: Team Services Group, LLC | G71: =+INDEX('SOI Mapping'!$D:$D, MATCH(SOIs!$F71,'SOI Mapping'!$B:$B,0),0) -> TEAM Services Group | I71: Summit Behavioral Healthcare, LLC | J71: =+INDEX('SOI Mapping'!$D:$D, MATCH(SOIs!$I71,'SOI Mapping'!$B:$B,0),0) -> Summit Behavioral Healthcare | O71: The Edelman Financial Center, LLC | P71: =+INDEX('SOI Mapping'!$D:$D, MATCH(SOIs!$O71,'SOI Mapping'!$B:$B,0),0) -> Edelman | R71: STV Group Incorporated | S71: =+INDEX('SOI Mapping'!$D:$D, MATCH(SOIs!$R71,'SOI Mapping'!$B:$B,0),0) -> STV Group | U71: Wildcat Buyerco, Inc. | V71: =+INDEX('SOI Mapping'!$D:$D, MATCH(SOIs!$U71,'SOI Mapping'!$B:$B,0),0) -> Nsi Industries | X71: MeritDirect
C72: Zips Car Wash, LLC | D72: =+INDEX('SOI Mapping'!$D:$D, MATCH(SOIs!$C72,'SOI Mapping'!$B:$B,0),0) -> Zips | F72: Teneo Holdings LLC | G72: =+INDEX('SOI Mapping'!$D:$D, MATCH(SOIs!$F72,'SOI Mapping'!$B:$B,0),0) -> Teneo | I72: System Planning and Analysis, Inc. (f/k/a Management Consulting & Research, LLC) | J72: =+INDEX('SOI Mapping'!$D:$D, MATCH(SOIs!$I72,'SOI Mapping'!$B:$B,0),0) -> MCR | O72: TPC Canada Parent, Inc. and TPC US Parent, LLC | P72: =+INDEX('SOI Mapping'!$D:$D, MATCH(SOIs!$O72,'SOI Mapping'!$B:$B,0),0) -> Targeted Pet Care | R72: System Planning and Analysis, Inc. (f/k/a Management Consulting & Research, LLC) | S72: =+INDEX('SOI Mapping'!$D:$D, MATCH(SOIs!$R72,'SOI Mapping'!$B:$B,0),0) -> MCR | U72: Zips Car Wash, LLC | V72: =+INDEX('SOI Mapping'!$D:$D, MATCH(SOIs!$U72,'SOI Mapping'!$B:$B,0),0) -> Zips | X72: MES
F73: The Aegis Technologies Group, LLC | G73: =+INDEX('SOI Mapping'!$D:$D, MATCH(SOIs!$F73,'SOI Mapping'!$B:$B,0),0) -> BlueHalo | I73: Team Services Group, LLC | J73: =+INDEX('SOI Mapping'!$D:$D, MATCH(SOIs!$I73,'SOI Mapping'!$B:$B,0),0) -> TEAM Services Group | O73: TVC Enterprises, LLC | P73: =+INDEX('SOI Mapping'!$D:$D, MATCH(SOIs!$O73,'SOI Mapping'!$B:$B,0),0) -> TVC | R73: The Bluebird Group LLC | S73: =+INDEX('SOI Mapping'!$D:$D, MATCH(SOIs!$R73,'SOI Mapping'!$B:$B,0),0) -> Bluebird | X73: Milani
F74: The Bluebird Group LLC | G74: =+INDEX('SOI Mapping'!$D:$D, MATCH(SOIs!$F74,'SOI Mapping'!$B:$B,0),0) -> Bluebird | I74: Teneo Holdings LLC | J74: =+INDEX('SOI Mapping'!$D:$D, MATCH(SOIs!$I74,'SOI Mapping'!$B:$B,0),0) -> Teneo | O74: TWS Acquisition Corporation | P74: =+INDEX('SOI Mapping'!$D:$D, MATCH(SOIs!$O74,'SOI Mapping'!$B:$B,0),0) -> StrataTech | R74: The Vertex Companies, LLC | S74: =+INDEX('SOI Mapping'!$D:$D, MATCH(SOIs!$R74,'SOI Mapping'!$B:$B,0),0) -> Vertex | X74: Mission Critical Electronics
F75: TPC Canada Parent, Inc. and TPC US Parent, LLC | G75: =+INDEX('SOI Mapping'!$D:$D, MATCH(SOIs!$F75,'SOI Mapping'!$B:$B,0),0) -> Targeted Pet Care | I75: The Aegis Technologies Group, LLC | J75: =+INDEX('SOI Mapping'!$D:$D, MATCH(SOIs!$I75,'SOI Mapping'!$B:$B,0),0) -> BlueHalo | O75: Tyto Athene, LLC | P75: =+INDEX('SOI Mapping'!$D:$D, MATCH(SOIs!$O75,'SOI Mapping'!$B:$B,0),0) -> Tyto Athene | R75: TPC Canada Parent, Inc. and TPC US Parent, LLC | S75: =+INDEX('SOI Mapping'!$D:$D, MATCH(SOIs!$R75,'SOI Mapping'!$B:$B,0),0) -> Targeted Pet Care | X75: Molded Devices
F76: TWS Acquisition Corporation | G76: =+INDEX('SOI Mapping'!$D:$D, MATCH(SOIs!$F76,'SOI Mapping'!$B:$B,0),0) -> StrataTech | I76: The Bluebird Group LLC | J76: =+INDEX('SOI Mapping'!$D:$D, MATCH(SOIs!$I76,'SOI Mapping'!$B:$B,0),0) -> Bluebird | O76: Wildcat Buyerco, Inc. | P76: =+INDEX('SOI Mapping'!$D:$D, MATCH(SOIs!$O76,'SOI Mapping'!$B:$B,0),0) -> Nsi Industries | R76: TWS Acquisition Corporation | S76: =+INDEX('SOI Mapping'!$D:$D, MATCH(SOIs!$R76,'SOI Mapping'!$B:$B,0),0) -> StrataTech | X76: Momentum
F77: Tyto Athene, LLC (New Issue) | G77: =+INDEX('SOI Mapping'!$D:$D, MATCH(SOIs!$F77,'SOI Mapping'!$B:$B,0),0) -> Tyto Athene | I77: The Infosoft Group, LLC | J77: =+INDEX('SOI Mapping'!$D:$D, MATCH(SOIs!$I77,'SOI Mapping'!$B:$B,0),0) -> Infosoft | O77: Wildcat Buyerco, Inc. - Unfunded Term Loan | P77: =+INDEX('SOI Mapping'!$D:$D, MATCH(SOIs!$O77,'SOI Mapping'!$B:$B,0),0) -> Nsi Industries | R77: Tyto Athene, LLC (New Issue) | S77: =+INDEX('SOI Mapping'!$D:$D, MATCH(SOIs!$R77,'SOI Mapping'!$B:$B,0),0) -> Tyto Athene | X77: Neptune Flood
F78: Walker Edison Furniture Company LLC | G78: =+INDEX('SOI Mapping'!$D:$D, MATCH(SOIs!$F78,'SOI Mapping'!$B:$B,0),0) -> Walker Edison | I78: The Vertex Companies, LLC | J78: =+INDEX('SOI Mapping'!$D:$D, MATCH(SOIs!$I78,'SOI Mapping'!$B:$B,0),0) -> Vertex | O78: Zips Car Wash, LLC | P78: =+INDEX('SOI Mapping'!$D:$D, MATCH(SOIs!$O78,'SOI Mapping'!$B:$B,0),0) -> Zips | R78: Urology Management Holdings, Inc. | S78: Solaris Health | X78: Nevada Behavioral Health Systems
F79: Wildcat Buyerco, Inc. | G79: =+INDEX('SOI Mapping'!$D:$D, MATCH(SOIs!$F79,'SOI Mapping'!$B:$B,0),0) -> Nsi Industries | I79: TVC Enterprises, LLC | J79: =+INDEX('SOI Mapping'!$D:$D, MATCH(SOIs!$I79,'SOI Mapping'!$B:$B,0),0) -> TVC | O79: Ascensus Holdings, Inc. - Second Lien | P79: =+INDEX('SOI Mapping'!$D:$D, MATCH(SOIs!$O79,'SOI Mapping'!$B:$B,0),0) -> Ascensus | R79: Wildcat Buyerco, Inc. | S79: =+INDEX('SOI Mapping'!$D:$D, MATCH(SOIs!$R79,'SOI Mapping'!$B:$B,0),0) -> Nsi Industries | X79: Nsi Industries
F80: Zips Car Wash, LLC | G80: =+INDEX('SOI Mapping'!$D:$D, MATCH(SOIs!$F80,'SOI Mapping'!$B:$B,0),0) -> Zips | I80: Tyto Athene, LLC | J80: =+INDEX('SOI Mapping'!$D:$D, MATCH(SOIs!$I80,'SOI Mapping'!$B:$B,0),0) -> Tyto Athene | R80: Zips Car Wash, LLC | S80: =+INDEX('SOI Mapping'!$D:$D, MATCH(SOIs!$R80,'SOI Mapping'!$B:$B,0),0) -> Zips | X80: OpenRoad Lending
I81: Walker Edison Furniture Company LLC | J81: =+INDEX('SOI Mapping'!$D:$D, MATCH(SOIs!$I81,'SOI Mapping'!$B:$B,0),0) -> Walker Edison | X81: OSM
I82: Walker Edison Furniture Company LLC - Incremental TL | J82: Walker Edison | X82: Ox
I83: Wildcat Buyerco, Inc. | J83: =+INDEX('SOI Mapping'!$D:$D, MATCH(SOIs!$I83,'SOI Mapping'!$B:$B,0),0) -> Nsi Industries | X83: Painters Supply and Equipment
I84: Zips Car Wash, LLC | J84: =+INDEX('SOI Mapping'!$D:$D, MATCH(SOIs!$I84,'SOI Mapping'!$B:$B,0),0) -> Zips | X84: Pink Lily
I85: Team Services Group, LLC - 2nd Lien | J85: =+INDEX('SOI Mapping'!$D:$D, MATCH(SOIs!$I85,'SOI Mapping'!$B:$B,0),0) -> TEAM Services Group | X85: PlayPower
X86: Pragmatic Institute
X87: Prelude
X88: Quantic Electronics
X89: Radius Aerospace
X90: Rancho Medical
X91: Recteq
X92: Research Now/SSI
X93: Riverpoint
X94: Riverside Insights
X95: Sales Benchmark Index (SBI)
D96: Ad.net | X96: Sargent & Greenleaf
D97: Vision Integrated | X97: Schlesinger
D98: MeritDirect | X98: Seaway Plastics
D99: Any Hour Services | X99: Sigma Defense
D100: Apex Service Partners | X100: Signature Systems Group
D101: Applied Technical Services | X101: Simplicity Group
...

Sheet SOI Mapping
B2: No Duplicates
B3: General | G3: For Dropdown
B4: SOI Name | C4: Security Name | D4: Family Name | E4: Security Type | G4: Security Types
B5: RECEPTION PURCHASER, LLC | C5: STG (TL) | D5: STG Logistics | E5: First Lien | G5: First Lien
B6: 18 Freemont Street Acquisition, LLC | C6: Circa (TL) | D6: Circa | E6: First Lien | G6: Second Lien
B7: The Edelman Financial Center, LLC | C7: Edelman (Term Loan) | D7: Edelman | E7: First Lien
B8: Hightower Holding, LLC | C8: Hightower (Term Loan) | D8: Hightower | E8: First Lien
B9: A1 Garage Merger Sub, LLC | C9: A1 Garage (Term Loan) | D9: A1 Garage | E9: First Lien
B10: A1 Garage Merger Sub, LLC | C10: A1 Garage (DDTL) | D10: A1 Garage | E10: First Lien
B11: A1 Garage Merger Sub, LLC | C11: A1 Garage (Revolver) | D11: A1 Garage | E11: First Lien
B12: A1 Garage Equity, LLC | C12: A1 Garage (Common Equity) | D12: A1 Garage | E12: Common Equity
B13: Ad.net Acquisition, LLC | C13: Ad.net (Term Loan) | D13: Ad.net | E13: First Lien | G13: Subordinated Debt
B14: Ad.net Acquisition, LLC | C14: Ad.net (Term Loan) | D14: Ad.net | E14: First Lien | G14: Preferred Equity
B15: Ad.net Acquisition, LLC - Funded Revolver | C15: Ad.net (Revolver) | D15: Ad.net | E15: First Lien | G15: Common Equity
B16: Ad.net Acquisition, LLC - Unfunded Revolver | C16: Ad.net (Revolver) | D16: Ad.net | E16: First Lien
B17: Ad.net Holdings, Inc. (Common ) | C17: Ad.net (Common Equity) | D17: Ad.net | E17: Common Equity
B18: Ad.net Holdings, Inc. (Common) | C18: Ad.net (Common Equity) | D18: Ad.net | E18: Preferred Equity
B19: Ad.net Holdings, Inc. (Preferred) | C19: Ad.net (Preferred Equity) | D19: Ad.net | E19: Preferred Equity
B20: Advantage Sales & Marketing | C20: Advantage (TL) | D20: Advantage Sales & Marketing | E20: First Lien
B21: Advantage Sales & Marketing | C21: Advantage (TL) | D21: Advantage Sales & Marketing | E21: First Lien
B22: Advantage Sales & Marketing Inc. | C22: Advantage (TL) | D22: Advantage Sales & Marketing | E22: First Lien
B23: Affinion Group Holdings, Inc. (Warrants) | C23: Affinion (Warrants) | D23: Affinion | E23: Common Equity
B24: AG Investco LP | C24: Athene (Equity) | D24: Athene | E24: Common Equity
B25: AG Investco LP - Unfunded | C25: Athene (Equity) | D25: Athene | E25: Common Equity
B26: AG Investco LP (Unfunded) | C26: Athene (Equity) | D26: Athene | E26: Common Equity
B27: AH Holdings, Inc. | C27: American Surgical (Preferred Equity) | D27: American Surgical | E27: Preferred Equity
... B38: Altamira Technologies, LLC - Unfunded Revolver | C38: Altamira (RC) | D38: Altamira | E38: First Lien
B39: American Auto Auction Group, LLC | C39: XLerate | D39: #N/A | E39: First Lien
B40: American Insulated Glass, LLC | C40: American Insulated Glass (Term Loan) | D40: American Insulated Glass | E40: First Lien
B41: American Insulated Glass, LLC - Unfunded Term Loan | C41: American Insulated Glass (DDTL) | D41: American Insulated Glass | E41: First Lien
B42: American Teleconferencing Services, Ltd. | C42: Premiere Global Services (PGi) (Term Loan) | D42: Premiere Global Services (PGi) | E42: First Lien
B43: American Teleconferencing Services, Ltd. - Funded Revolver | C43: Premiere Global Services (PGi) (Priority Revolver) | D43: Premiere Global Services (PGi) | E43: First Lien
B44: Amsive Holding Corporation | C44: Vision Integrated (TL) | D44: Vision Integrated | E44: First Lien
B45: Amsive Holding Corporation (f/k/a Vision Purchaser Corporation) | C45: Vision Integrated (TL) | D45: Vision Integrated | E45: First Lien
B46: Ankura Consulting Group, LLC | C46: Ankura (TL) | D46: Ankura | E46: First Lien
B47: Any Hour Services | C47: Any Hour Services (Term Loan) | D47: Any Hour Services | E47: First Lien
B48: Any Hour Services - Unfunded Revolver | C48: Any Hour Services (Revolver) | D48: Any Hour Services | E48: First Lien
B49: Any Hour Services - Unfunded Term Loan | C49: Any Hour Services (DDTL) | D49: Any Hour Services | E49: First Lien
B50: Any Hour Services - Unfunded Term Loan II | C50: Any Hour Services (DDTL II) | D50: Any Hour Services | E50: First Lien
B51: Apex Service Partners, LLC | C51: Apex (Term Loan) | D51: Apex Service Partners | E51: First Lien
... B82: Ascensus Holdings, Inc. - Second Lien | C82: Ascensus (2L Term Loan) | D82: Ascensus | E82: Second Lien
B83: ASP LCG Holdings, Inc. (f/k/a Learning Care Group (US), No. 2 Inc.) (Warrants) | C83: Learning Care Group (Common) | D83: #N/A | E83: Common Equity
B84: Athletico Holdings, LLC | C84: Athletico (Common Equity) | D84: Athletico | E84: Common Equity
B85: Atlas Investment Aggregator, LLC | C85: Aspect Software (Equity) | D85: Aspect Software | E85: Common Equity
B86: Atlas Purchaser, Inc. | C86: Aspect Software | D86: Aspect Software | E86: Second Lien
B87: Autumn Games, LLC | C87: CEA (Common) | D87: #N/A | E87: Common Equity
B88: Burgess Point Holdings, L.P. | C88: BBB Industries (Common Equity) | D88: BBB Industries | E88: Common Equity
B89: Burgess Point Purchaser Corporation | C89: BBB Industries (Second Lien Term Loan) | D89: BBB Industries | E89: Second Lien
B90: Burgess Point Purchaser Corporation | C90: BBB Industries (First Lien Term Loan) | D90: BBB Industries | E90: First Lien
B91: Best Practice Associates LLC | C91: Federal Advisory Partners (Term Loan) | D91: Federal Advisory Partners | E91: Second Lien
B92: Beta+ | C92: Beta+ (TL) | D92: Beta+ | E92: First Lien
B93: Beta Plus Technologies, Inc. | C93: Beta+ (TL) | D93: Beta+ | E93: First Lien
B94: Blackhawk Industrial Distribution, Inc. | C94: BlackHawk Industrial (TL) | D94: BlackHawk Industrial | E94: First Lien
B95: Blackhawk Industrial Distribution, Inc. - Funded Revolver | C95: BlackHawk Industrial (Revolver) | D95: BlackHawk Industrial | E95: First Lien
B96: Blackhawk Industrial Distribution, Inc. - Unfunded Revolver | C96: BlackHawk Industrial (Revolver) | D96: BlackHawk Industrial | E96: First Lien
B97: Blackhawk Industrial Distribution, Inc. - Unfunded Term Loan | C97: BlackHawk Industrial (DDTL) | D97: BlackHawk Industrial | E97: First Lien
B98: Bottom Line Systems, LLC | C98: Bottom Line Systems | D98: #N/A | E98: First Lien
B99: Broder Bros, Co. | C99: alphabroder | D99: alphabroder | E99: First Lien
B100: Broder Bros., Co. | C100: alphabroder | D100: alphabroder | E100: First Lien
B101: By Light Investco LP | C101: By Light (Equity) | D101: By Light | E101: Common Equity
B102: By Light Investco LP (Unfunded) | C102: By Light (Equity) | D102: By Light | E102: Common Equity
B103: By Light Professional IT Services, LLC | C103: By Light (Term Loan) | D103: By Light | E103: First Lien
B104: By Light Professional IT Services, LLC - Funded Revolver | C104: By Light (Revolver) | D104: By Light | E104: First Lien
B105: By Light Professional IT Services, LLC - Unfunded Revolver | C105: By Light (Revolver) | D105: By Light | E105: First Lien
B106: By Light Professional IT Services, LLC - Unfunded Term Loan | C106: By Light (DDTL) | D106: By Light | E106: First Lien
B107: By Light Professional Services, LLC | C107: By Light (Term Loan) | D107: By Light | E107: First Lien
B108: Cadence Aerospace, LLC | C108: Cadence Aerospace | D108: Cadence Aerospace | E108: First Lien
B109: Cano Health | C109: Cano Health (Term Loan) | D109: #N/A | E109: First Lien
B110: Cano Health, LLC | C110: Cano Health (Term Loan) | D110: #N/A | E110: First Lien
B111: Cano Health, LLC | C111: Cano Health (Term Loan) | D111: #N/A | E111: Common Equity
B112: Cardenas Markets LLC | C112: Cardenas | D112: Cardenas | E112: First Lien
B113: Cardinal Logistics Holdings LLC (Intermediate Transportation 100, LLC) | C113: Greatwide (Common) | D113: Greatwide | E113: Common Equity
B114: Cartessa Aesthetics, LLC | C114: Cartessa (TL) | D114: Cartessa | E114: First Lien
B115: Cartessa Aesthetics, LLC - Funded Revolver | C115: Cartessa (Revolver) | D115: Cartessa | E115: First Lien
B116: Cartessa Aesthetics, LLC - Unfunded Revolver | C116: Cartessa (Revolver) | D116: Cartessa
B117: Cartessa Aesthetics, LLC (Common) | C117: Cartessa (Common Equity) | D117: Cartessa | E117: Common Equity
B118: Cascade Environmental Holdings LLC (13.00% PIK) | C118: Cascade (Senior Subordinated Notes) | D118: Cascade | E118: Subordinated Debt
B119: Cascade Environmental Holdings LLC (Preffered) | C119: Cascade (Preferred Equity) | D119: Cascade | E119: Preferred Equity
B120: Cascade Environmental Holdings, LLC | C120: Cascade (Common Equity) | D120: Cascade | E120: Common Equity
B121: Cascade Environmental Holdings, LLC (13.00% PIK) | C121: Cascade (Senior Subordinated Notes) | D121: Cascade | E121: Subordinated Debt
B122: Cascade Environmental Holdings, LLC (Common) | C122: Cascade (Common Equity) | D122: Cascade | E122: Common Equity
B123: Cascade Environmental Holdings, LLC (Preferred) | C123: Cascade (Preferred Equity) | D123: Cascade | E123: Preferred Equity
B124: Cascade Environmental Holdings LLC (Common) | C124: Cascade (Common Equity) | D124: Cascade | E124: Common Equity
B125: CF512, Inc. | C125: Gen3 Marketing (Term Loan) | D125: Gen3 Marketing | E125: First Lien
B126: CF512, Inc. - Unfunded Revolver | C126: Gen3 Marketing (Revolver) | D126: Gen3 Marketing | E126: First Lien
B127: CF512, Inc. - Unfunded Term Loan | C127: Gen3 Marketing (DDTL) | D127: Gen3 Marketing | E127: First Lien
B128: CHA Holdings, Inc. | C128: CHA Consulting (TL) | D128: CHA Consulting | E128: First Lien
... B133: CI (Allied) Investment Holdings, LLC (PRA Events, Inc.) | C133: APRA (Common) | D133: APRA | E133: Common Equity
B134: CI (PTN) Investment Holdings II, LLC | C134: PT Network (C. Eq.) | D134: #N/A | E134: Common Equity
B135: CI (PTN) Investment Holdings II, LLC(P) | C135: PT Network (P. Eq.) | D135: #N/A | E135: Preferred Equity
B136: CI (Summit) Investment Holdings, LLC (SFP Holding, Inc.) | C136: Summit Companies (Common Equity) | D136: #N/A | E136: Common Equity
B137: Compex Legal Services, Inc. | C137: Compex (TL) | D137: Compex Legal | E137: First Lien
B138: Compex Legal Services, Inc. | C138: Compex (Incremental TL) | D138: Compex Legal | E138: First Lien
B139: Compex Legal Services, Inc. | C139: Compex (TL) | D139: Compex Legal | E139: First Lien
B140: Compex Legal Services, Inc. - Funded Revolver | C140: Compex (Rev) | D140: Compex Legal | E140: First Lien
B141: Compex Legal Services, Inc. - Unfunded Revolver | C141: Compex (Rev) | D141: Compex Legal | E141: First Lien
B142: Compex Legal Services, Inc. - Unfunded Term Loan | C142: Compex (DDTL) | D142: Compex Legal | E142: First Lien
B143: Condor Borrower, LLC | C143: Comodo (TL) | D143: #N/A | E143: Second Lien
B144: Condor Holdings Limited | C144: Comodo (P Equity 1) | D144: #N/A | E144: Preferred Equity
B145: Condor Top Holdco Limited | C145: Comodo (P Equity 2) | D145: #N/A | E145: Preferred Equity
...
