Workbook
Name _dma1: #REF!
Name _dma2: #REF!
Name _dma3: #REF!
Name _dmb1: #REF!
Name _dmb2: #REF!
Name _dmc1: #REF!
Name _dmc2: #REF!
Name _dmd1: #REF!
Name _dmd2: #REF!
Name _Lag1: #REF!
Name _Lag2: #REF!
Name _PV1: 7
Name a: #REF!
Name A1loss: #REF!
Name A2loss: #REF!
Name A3loss: #REF!
Name AB: #REF!
Name AB_H: #REF!
Name AB_Orig: #REF!
Name ABS_Senior_____10: "FitchRecoverybyType"
Name ActiveRows: #REF!
Name Actual: #REF!
Name Actual12moChargeoffRatio: #REF!
Name Actual3moChargeoffRatio: #REF!
Name Actual3moDefaultRatio: #REF!
Name AdjAdvRate: #REF!
Name adv_rate: #REF!
Name adv_rate_reduced: #REF!
Name adv_rate_type: #REF!
Name advance_outstanding: #REF!
Name AdvancesOS: #REF!
Name agg_commit_bal: #REF!
Name AggregateAdjustedBalanceUSD: #REF!
Name AgingsDetail: #REF!
Name agreed_currency: #REF!
Name amort_adv_outstanding: #REF!
Name amort_period: #REF!
Name AOLB: #REF!
Name AOLBrange: #REF!
Name applicable_margin: #REF!
Name asfsdf: #REF!
Name ASH: #REF!
Name ASL: #REF!
Name asset_rating: #REF!
Name asset_types: #REF!
Name asset_value: #REF!
Name AUSTRALIA_NET: 110
Name AUSTRIA_NET: 107
Name AvailableCollections: #REF!
Name AverageABAgg: #REF!
Name AverageABL: #REF!
Name averageABL2: #REF!
Name AverageAgg: #REF!
Name b: #REF!
Name B1loss: #REF!
Name B2loss: #REF!
Name BackupServiceFee: #REF!
Name balances: #REF!
Name BeginningABAgg: #REF!
Name BeginningABL: #REF!

Sheet aresinput
A1: Fund | B1: Lender | C1: Date | D1: Commitment | E1: Borrowing Base | F1: Outstanding (total) | G1: Availability | H1: FX BB - GBP | I1: GBP Outstanding | J1: FX BB - EUR | K1: EUR Outstanding | L1: FX BB - CAD | M1: CAD Outstanding | N1: FX BB - SEK | O1: SEK Outstanding | P1: FX BB - DKK | Q1: DKK Outstanding | R1: FX BB - NOK | S1: NOK Outstanding | T1: Outstanding Loan Balance (Commitment) | U1: Adjusted Borrowing Value | V1: Wtd Avg Advance Rate | W1: Wtd. Avg Advance Rate (Effective) | X1: Unfunded Commitments | Y1: Unfunded Exposure | Z1: Excess Concentrations | AA1: # of Obligors | AB1: TTM EBITDA | AC1: Interest Coverage | AD1: Senior Net Leverage | AE1: Total Net Leverage | AF1: VAE#s | AG1: VAEs (based on ABV Post Haircut - USD) | AH1: VAEs as of percent of ABV Post Haircut | AI1: VAEs (based on OLB in USD) | AJ1: VAEs as of percent of OLB | AK1: Min Required Equity | AL1: First Lien - OLB | AM1: First Lien - ABV | AN1: First Lien Last Out - OLB | AO1: First Lien Last Out - ABV | AP1: Second Lien - OLB | AQ1: Second Lien - ABV | AR1: BSL - OLB | AS1: BSL - ABV | AT1: Wtd. Avg Spread | AU1: Capital Call Availability / SCV | AV1: Principal Cash | AW1: Unconstrained BB | AX1: FX Cash - CAD | AY1: FX Cash - EUR | AZ1: FX Cash - GBP | BA1: FX Cash - DKK | BB1: FX Cash - SEK | BC1: FX Cash - NOK | BD1: Principal Cash USD | BE1: MF Cash - CAD | BF1: MF Cash - EUR | BG1: MF Cash - GBP | BH1: MF Cash - DKK | BI1: MF Cash - SEK | BJ1: MF Cash - NOK | BK1: Principal O/S Pledged | BL1: Adjusted Borrowing Value (USD) | BM1: Wtd avg. Assigned Value | BN1: Wtd avg. advance rate | BO1: Effective Avg Adv rate | BP1: Adjusted balance | BQ1: Borrowing base2 | BR1: Borrowing outstanding | BS1: Wtd. avg portfolio leverage | BT1: Wtd. avg portfolio interest coverage | BU1: Wtd. avg portfolio EBITDA? | BV1: Fund 2
A2: SDL III | B2: BNP | C2: ='Summary '!I1 -> 45838 | D2: ='Summary '!I4 -> 400000000 | E2: ='Summary '!C11 -> 2.2302859e+08 | F2: ='Summary '!I39 -> 160600000 | G2: =Table2[[#This Row],[Borrowing Base]]-Table2[[#This Row],[Outstanding (total)]] -> 62428593 | H2: 0 | I2: 0 | J2: 0 | K2: 0 | L2: 0 | M2: 0 | N2: 0 | O2: 0 | P2: 0 | Q2: 0 | R2: 0 | S2: 0 | T2: ='Summary '!I38 -> 0 | V2: ='Summary '!C8 -> 0.64941848 | W2: =E2/T2 -> #DIV/0! | AB2: ='Summary '!D58 -> 39.047509 | AC2: ='Summary '!D59 -> 2.1876743 | AD2: ='Summary '!D60 -> 3.818529 | AV2: ='Summary '!C6 -> 0 | BK2: =Calcs!I15*10^6 -> 3.6126999e+14 | BL2: =Calcs!BO15 -> 3.3744891e+08 | BM2: =Table2[[#This Row],[Adjusted Borrowing Value (USD)]]/Table2[[#This Row],[Principal O/S Pledged]] -> 9.3406295e-07 | BN2: ='Summary '!C8 -> 0.64941848 | BO2: =BM2*BN2 -> 6.0659774e-07 | BP2: =BK2*BM2*BN2 -> 2.1914556e+08 | BQ2: ='Summary '!C11 -> 2.2302859e+08 | BR2: ='Summary '!I39 -> 160600000 | BS2: =SUMPRODUCT(Calcs!I17:I117,Calcs!BV17:BV117)/SUM(Calcs!I17:I117) -> 0 | BT2: ='Summary '!D59 -> 2.1876743 | BU2: ='Summary '!D58 -> 39.047509 | BV2: SDL III D

Sheet Summary 
H1: As of Date | I1: 45838 | Q1: =+SUM(Q4:Q800) -> 160600000
B2: BORROWING BASE CALCULATION | O2: Notes Payable: USD
E3: Principal Cash | F3: FX Rate | O3: Date | P3: Day | Q3: Amount
B4: THE SUM OF: | C4: Amount (USD) | D4: USD | E4: 0 | F4: 1 | G4: 7871288400 | H4: Facility size | I4: 400000000 | O4: 43522 | P4: Normal | Q4: 125000000
B5: (i) Principal Collection Subaccount | C5: 3883034.6 | D5: GBP | E5: 0 | F5: 1.28315 | G5: 7871288260 | H5: Inception Date | I5: 43518 | O5: 43532 | P5: Normal | Q5: 10000000
B6: (ii) Trust Subaccount | C6: =C69 -> 0 | D6: EUR | E6: 0 | F6: 1.08345 | G6: 7871289780 | H6: RP End | I6: 46741 | O6: 43550 | P6: Normal | Q6: 7500000
B7: (iii) The product of: | C7: =C8*C9 -> 2.1914556e+08 | D7: CAD | E7: 0 | F7: 0.7336488 | G7: 7871281240 | H7: Facility Termination | I7: 47472 | N7: (b) for which the related Obligor has a Senior Net Leverage Ratio of not more than 6.0x; | O7: 43588 | P7: Normal | Q7: 9000000
B8: (x) the Weighted Average Advance Rate and (y) the Portfolio Advance Rate Adj. | C8: =Calcs!BP15*'Diversity Score'!E7 -> 0.64941848 | D8: AUD | E8: 0 | F8: 0.67465 | G8: 7871280360 | O8: 43607 | P8: Normal | Q8: 4000000
B9: (y) the Aggregate Net Collateral Balance (excluding Loans sold but not settled) | C9: =SUM(Calcs!BO11:BO12) -> 3.3744891e+08 | H9: WAL Test | O9: 43607 | P9: Normal | Q9: 15000000
B10: (iV) Sale price of all Loans not yet settled | C10: =Calcs!V15 -> 0 | H10: Weighted Average Life | I10: =Calcs!BN12 -> 3.5792895 | O10: 43626 | P10: Normal | Q10: 2000000
B11: Borrowing Base | C11: =SUM(C10,C5:C7) -> 2.2302859e+08 | H11: Is less than | I11: 6 | O11: 43637 | P11: Normal | Q11: 2000000
H12: Test Satisfied? | I12: =IF(I10<I11,TRUE,FALSE) -> TRUE | O12: 43641 | P12: Normal | Q12: 3500000
O13: 43651 | P13: Normal | Q13: -10000000
O14: 43675 | P14: Normal | Q14: -13000000
B15: OC Ratio | C15: Amount (USD) | O15: 43706 | P15: Normal | Q15: 16000000
B16: Sum of: | C16: =SUM(C17:C18) -> 2.2302859e+08 | O16: 43742 | P16: Normal | Q16: -16000000
B17: (i) The Borrowing Base | C17: =C11 -> 2.2302859e+08 | H17: Interest Coverage Test | O17: 43746 | P17: Normal | Q17: 2000000
B18: (ii) Implied Equity: of Cashless Contributions | C18: =IFERROR((1-C19)*C20,0) -> 0 | H18: (a) aggregate amount of Interest Proceeds not received but expected | I18: 0 | O18: 43769 | P18: Normal | Q18: 14000000
B19: (a) Weighted Average Advance Rate of Cashless Contributions | C19: =Calcs!BP6 | H19: (b) all amounts on deposit in the Interest Collection Subaccount | O19: 43776 | P19: Normal | Q19: 2000000
B20: (b) Adj. Principal Balance of Cashless Contribution | C20: =Calcs!BO6 -> 0 | H20: Interest Coverage Amount | I20: =I18+I19 -> 0 | O20: 43782 | P20: Normal | Q20: 5000000
B21: divided by (ii) the sum of: | C21: =SUM(C22:C23) -> 160600000 | H21: the amounts payable on the related Payment Date pursuant to Sections 9.01(a)(i)(A) and 9.01(a)(i)(B) | I21: 0 | O21: 43788 | P21: Normal | Q21: 5500000
B22: (x) the Outstanding Principal Balance of the Facility and | C22: =percentage_unused -> 160600000 | H22: all amounts due and payable pursuant to Section 9.01(a)(i)(D) on the related Payment Date. | I22: 0 | O22: 43802 | P22: Normal | Q22: 10000000
B23: (y) the aggregate purchase price of all Loans purchased but not settled | C23: =Calcs!U11 -> 0 | H23: Interest Coverage Ratio | I23: =IFERROR((I20-I21)/I22,"N/A") -> N/A | O23: 43808 | P23: Normal | Q23: 10000000
B24: OC Ratio | C24: =IFERROR(C17/C21,"N/A") -> 1.388721 | H24: Is greater than | I24: 1.5 | O24: 43836 | P24: Normal | Q24: 3000000
B25: Minimum Threshold | C25: 1 | H25: Test Satisfied? | I25: =IF(I23>I24,TRUE,FALSE) -> TRUE | O25: 43837 | P25: Normal | Q25: 24000000
B26: Result | C26: =IF(C24="N/A", "PASS", C24>=C25) -> TRUE | O26: 43844 | P26: Normal | Q26: 10000000
O27: 43861 | P27: Normal | Q27: 4500000
H28: WAS Spread Test | I28: Floating | J28: Fixed | O28: 44043 | P28: Normal | Q28: -22500000
H29: WAS | I29: =Calcs!AO15 -> 0.058103186 | J29: =IF(ISNUMBER(Calcs!$AR$14), SUMPRODUCT(Calcs!AR17:AR35, Calcs!I17:I35)/SUM(Calcs!I17:I35), FALSE) -> FALSE | O29: 44104 | P29: Normal | Q29: -9000000
B30: Concentration Limit Excess | C30: Concentration Limit | D30: Current % | E30: Cushion | H30: Is more than | I30: 0.04 | J30: 0.08 | O30: 44109 | P30: Normal | Q30: 6000000
B31: FLLO/2nd Lien | C31: 0.4 | D31: ='Concentration Limitations'!$X$7 -> 0 | E31: =C31-D31 -> 0.4 | H31: Test Satisfied? | I31: =IF(I29>I30,TRUE,FALSE) -> TRUE | J31: =IF(J29>J30,TRUE,FALSE) -> TRUE | O31: 44146 | P31: Normal | Q31: -37000000
B32: non-USD | C32: 0.1 | D32: ='Concentration Limitations'!$AN$7 -> 0 | E32: =C32-D32 -> 0.1 | O32: 12/8/20202 | P32: Normal | Q32: 5000000
B33: Obligor NOT in US | C33: 0.1 | D33: ='Concentration Limitations'!$AR$7 -> 0 | E33: =C33-D33 -> 0.1 | O33: 44189 | P33: Normal | Q33: 1000000
B34: Senior Net Lev >5.5x | C34: 0.25 | D34: ='Concentration Limitations'!$AV$7 -> 0.075252506 | E34: =C34-D34 -> 0.17474749 | O34: 44196 | P34: Normal | Q34: -3000000
B35: Fixed Rate | C35: 0.05 | D35: ='Concentration Limitations'!AZ7 -> 0.012565525 | E35: =C35-D35 -> 0.037434475 | O35: 44203 | P35: Normal | Q35: 2000000
B36: Not First Lien | C36: 0.25 | D36: ='Concentration Limitations'!$BT$7 -> 0.015678381 | E36: =C36-D36 -> 0.23432162 | O36: 44229 | P36: Normal | Q36: 15000000
B37: Second Liens | C37: 0.1 | D37: ='Concentration Limitations'!BX7 -> 0 | E37: =C37-D37 -> 0.1 | I37: Borrowing Proposal | J37: Override | K37: Maximum advance | L37: Margin | O37: 44251 | P37: Normal | Q37: 2000000
B38: Recurring Revenue | C38: 0.1 | D38: ='Concentration Limitations'!$BH$7 -> 0 | E38: =C38-D38 -> 0.1 | H38: Advance (Pro Forma) | I38: 0 | J38: =Q1 -> 160600000 | K38: =C11 -> 2.2302859e+08 | L38: 0.0225 | M38: 0 | O38: 44280 | P38: Normal | Q38: 7500000
B39: Cov-Lite | C39: 0.15 | D39: ='Concentration Limitations'!AB7 -> 0.098118891 | E39: =C39-D39 -> 0.051881109 | H39: Total used | I39: =SUM(I38:J38) -> 160600000 | J39: =(I4-I39)/I4 -> 0.5985 | K39: =SUM(J38:J38)/SUM(K38:K38) -> 0.72008704 | O39: 44363 | P39: Normal | Q39: 5000000
B40: EBITDA <$15mm | C40: 0.25 | D40: ='Concentration Limitations'!AF7 -> 0.10567782 | E40: =C40-D40 -> 0.14432218 | O40: 44456 | P40: Normal | Q40: 7000000
B41: EBITDA <$10mm | C41: 0.1 | D41: ='Concentration Limitations'!AJ7 -> 0.028926171 | E41: =C41-D41 -> 0.071073829 | O41: 44533 | P41: Normal | Q41: =28000000 -> 28000000
A42: 1 | B42: Partial PIK loans (Origination) | C42: 0.15 | D42: ='Concentration Limitations'!$BL$7 -> 0 | E42: =C42-D42 -> 0.15 | O42: 44622 | P42: Normal | Q42: -210500000
A43: 2 | B43: Partial PIK Loans (Material Mod) | C43: 0.075 | D43: ='Concentration Limitations'!BL7 -> 0 | E43: =C43-D43 -> 0.075 | H43: Value Adjustment Events | O43: 44644 | P43: Normal | Q43: -32500000
A44: 3 | B44: Industry Concentration | C44: 20% / 15% / 12% | H44: Ratios | I44: Trigger | J44: # Assets | K44: Outstanding Bal | L44: Borrowing Value * AR | O44: 44676 | P44: Normal | Q44: =5000000+11500000+2500000+10000000 -> 29000000
A45: 4 | B45: =CONCATENATE(A42, "-",(VLOOKUP(A42,'Concentration Limitations'!$DK:$DL,2,FALSE))) -> 1-Professional Services | C45: =VLOOKUP(A42,'Concentration Limitations'!$DK:$DU,11,FALSE) -> 0.2 | D45: =VLOOKUP(A42,'Concentration Limitations'!$DK:$DS,9,FALSE) -> 0.099789907 | E45: =C45-D45 -> 0.10021009 | H45: Cash Interest Coverage Ratio | J45: =SUM(Calcs!CU17:CU116) -> 35 | K45: =SUMIF(Calcs!$CU$16:$CU$85,">0",Calcs!$BO$16:$BO$85) -> 1.2420429e+08 | L45: =SUMIF(Calcs!$CU$16:$CU$85,">0",Calcs!$BP$16:$BP$85) -> 78328465 | O45: 44718 | P45: Normal | Q45: 10000000
A46: 4 | B46: =CONCATENATE(A43, "-",(VLOOKUP(A43,'Concentration Limitations'!$DK:$DL,2,FALSE))) -> 2-Health Care Providers & Services | C46: =VLOOKUP(A43,'Concentration Limitations'!$DK:$DU,11,FALSE) -> 0.15 | D46: =VLOOKUP(A43,'Concentration Limitations'!$DK:$DS,9,FALSE) -> 0.082804039 | E46: =C46-D46 -> 0.067195961 | H46: Is less than | I46: 1.75 | O46: 44728 | P46: Normal | Q46: 30000000
B47: =CONCATENATE(A44, "-",(VLOOKUP(A44,'Concentration Limitations'!$DK:$DL,2,FALSE))) -> 3-Aerospace & Defense | C47: =VLOOKUP(A44,'Concentration Limitations'!$DK:$DU,11,FALSE) -> 0.12 | D47: =VLOOKUP(A44,'Concentration Limitations'!$DK:$DS,9,FALSE) -> 0.07918876 | E47: =C47-D47 -> 0.04081124 | H47: or decreases (from Cut-Off Date) >: | I47: -0.15 | O47: 44733 | P47: Normal | Q47: 62900000
A48: 1 | B48: =CONCATENATE(A46, "-",(VLOOKUP(A46,'Concentration Limitations'!$DK:$DL,2,FALSE))) -> 4-Media | C48: =VLOOKUP(A46,'Concentration Limitations'!$DK:$DU,11,FALSE) -> 0.1 | D48: =VLOOKUP(A46,'Concentration Limitations'!$DK:$DS,9,FALSE) -> 0.077790765 | E48: =C48-D48 -> 0.022209235 | O48: 44742 | P48: Normal | Q48: -30000000
A49: 2 | B49: Obligor Concentration | C49: 10% / 7% / 5% | H49: Total Leverage Ratio | J49: =SUM(Calcs!CV17:CV116) -> 21 | K49: =SUMIF(Calcs!$CV$16:$CV$85,">0",Calcs!$BO$16:$BO$85) -> 84336257 | L49: =SUMIF(Calcs!$CV$16:$CV$85,">0",Calcs!$BP$16:$BP$85) -> 53028815 | O49: 44756 | P49: Normal | Q49: 13000000
A50: 3 | B50: =CONCATENATE(A48,"-",VLOOKUP(A48,'Concentration Limitations'!$F:$G,2,FALSE)) -> 1-Marketplace | C50: =VLOOKUP(A48,'Concentration Limitations'!$F:$P,11,FALSE) -> 0.1 | D50: =VLOOKUP(A48,'Concentration Limitations'!$F:$Q,12,FALSE) -> 0.033219766 | E50: =C50-D50 -> 0.066780234 | H50: Increase (from Cut-Off Date) >=: | I50: 1 | O50: 44757 | P50: Normal | Q50: 83000000
A51: 4 | B51: =CONCATENATE(A49,"-",VLOOKUP(A49,'Concentration Limitations'!$F:$G,2,FALSE)) -> 2-Sigma Defense Systems, LLC | C51: =VLOOKUP(A49,'Concentration Limitations'!$F:$P,11,FALSE) -> 0.07 | D51: =VLOOKUP(A49,'Concentration Limitations'!$F:$Q,12,FALSE) -> 0.030241285 | E51: =C51-D51 -> 0.039758715 | H51: or Increases (from Cut-Off Date) >: | I51: 0.2 | O51: 44798 | P51: Normal | Q51: 18000000
A52: 5 | B52: =CONCATENATE(A50,"-",VLOOKUP(A50,'Concentration Limitations'!$F:$G,2,FALSE)) -> 3-Rancho Medical | C52: =VLOOKUP(A50,'Concentration Limitations'!$F:$P,11,FALSE) -> 0.05 | D52: =VLOOKUP(A50,'Concentration Limitations'!$F:$Q,12,FALSE) -> 0.028777275 | E52: =C52-D52 -> 0.021222725 | H52: and SNL is above 4x | I52: 4 | O52: 44819 | P52: Normal | Q52: 32700000
B53: =CONCATENATE(A52,"-",VLOOKUP(A52,'Concentration Limitations'!$F:$G,2,FALSE)) -> 5-Lynx Technologies | C53: =VLOOKUP(A52,'Concentration Limitations'!$F:$P,11,FALSE) -> 0.05 | D53: =VLOOKUP(A52,'Concentration Limitations'!$F:$Q,12,FALSE) -> 0.021629137 | E53: =C53-D53 -> 0.028370863 | H53: Loan Assets with VAE | J53: =J45+J49 -> 56 | K53: =K45+K49 -> 2.0854055e+08 | L53: =L45+L49 -> 1.3135728e+08 | O53: 44896 | P53: Normal | Q53: 7000000
O54: 44972 | P54: Normal | Q54: 30000000
O55: 44993 | P55: Normal | Q55: -10000000
O56: 45043 | P56: Normal | Q56: -15000000
B57: WA Credit Stats | C57: At Acquisition | D57: Current | E57: % change | O57: 45057 | P57: Normal | Q57: 40000000
B58: EBITDA (Cash Flow Loans) | C58: =SUMPRODUCT(Calcs!CK17:CK117,Calcs!K17:K117) -> 36.399096 | D58: =SUMPRODUCT(Calcs!K17:K117,Calcs!BY17:BY117) -> 39.047509 | E58: =(D58/C58)-1 -> 0.072760396 | O58: 45071 | P58: Normal | Q58: -19000000
B59: IC Ratio (Cash Flow Loans) | C59: =SUMPRODUCT(Calcs!CF17:CF117,Calcs!K17:K117) -> 2.6957219 | D59: =SUMPRODUCT(Calcs!K17:K117,Calcs!BT17:BT117) -> 2.1876743 | E59: =(D59/C59)-1 -> -0.1884644 | O59: 45131 | P59: Normal | Q59: 12000000
B60: Sr Leverage (Cash Flow Loans) | C60: =SUMPRODUCT(Calcs!CG17:CG117,Calcs!K17:K117) -> 3.9605337 | D60: =SUMPRODUCT(Calcs!K17:K117,Calcs!BU17:BU117) -> 3.818529 | E60: =(D60/C60)-1 -> -0.035854943 | O60: 45133 | P60: Normal | Q60: -200000000
B61: LTV | C61: =SUMPRODUCT(Calcs!CJ17:CJ117,Calcs!K17:K117) -> 0 | D61: =SUMPRODUCT(Calcs!K17:K117,Calcs!BX17:BX117) -> 0 | E61: =IFERROR((D61/C61)-1, 0) -> 0 | O61: 45190 | P61: Normal | Q61: -14000000
O62: 45222 | P62: Normal | Q62: 35000000
O63: 45247 | P63: Normal | Q63: -10000000
H64: Facility Details | O64: 45261 | P64: Normal | Q64: 8000000
H65: Weighted Average Advance Rate: | K65: =C8 -> 0.64941848 | O65: 45271 | P65: Normal | Q65: 10000000
B66: Accounts | E66: Outstandings ($mm) | O66: 45316 | P66: Normal | Q66: 35000000
B67: Interest Collection Account #5652058400 | C67: 8920094.1 | E67: BNP Paribas (All Lenders) | F67: =($K$67/SUM($K$71)*K71)/1000000 -> 160.6 | H67: Advances Outstanding | K67: =+Q1 -> 160600000 | O67: 45378 | P67: Normal | Q67: -3000000
B68: Principal Collection Account (PF for unsettled trades) | C68: =+C75 -> 3883034.6 | E68: Webster Bank | F68: =F67*I72 -> 24.09 | H68: Effective Advance Rate | K68: =K67/(C68+C82) -> 0.47050973 | O68: 45393 | P68: Normal | Q68: 23000000
B69: Trust Account | C69: 0 | E69: BNP Paribas | F69: =F67-F68 -> 136.51 | H69: Diversity Score | K69: ='Diversity Score'!E3 -> 25.30841 | O69: 45413 | P69: Normal | Q69: -18000000
B70: Activity | C70: 0 | I70: Comm. % | J70: Outstanding % | K70: Commitment | O70: 45464 | P70: Normal | Q70: -16000000
B71: Current Cash Balance - Principal Collection #5652098400 | C71: 3883034.6 | H71: BNP Paribas (All Lenders) | I71: =+K71/$I$4 -> 1 | J71: =IFERROR(F67/(K71/1000000),0) -> 0.4015 | K71: =K72+K73 -> 400000000 | O71: 45485 | P71: Normal | Q71: 6000000
B72: Unsettled trades | C72: 0 | H72: Webster Bank | I72: =K72/K71 -> 0.15 | J72: =IFERROR(F68/(K72/1000000),0) -> 0.4015 | K72: 60000000 | O72: 45499 | P72: Normal | Q72: 33000000
B73: Paydown | C73: 0 | H73: BNP Paribas | I73: =K73/K71 -> 0.85 | J73: =IFERROR(F69/(K73/1000000),0) -> 0.4015 | K73: 340000000 | O73: 45503 | P73: Normal | Q73: 68000000
O74: 45540 | P74: Normal | Q74: -12000000
B75: Pro-Forma Cash Balance - Principal Collection | C75: =SUM(C71:C73) -> 3883034.6 | O75: 45573 | P75: Normal | Q75: 20000000
O76: 45583 | P76: Normal | Q76: 50000000
B77: Portfolio Summary | O77: 45604 | P77: Normal | Q77: 20000000
B78: Aggregate Principal Balance | C78: =Calcs!I15 -> 3.6126999e+08 | H78: IN WITNESS WHEREOF, the undersigned has duly executed this Report. | O78: 45645 | P78: Normal | Q78: 40000000
B79: Discount per Discount Factors | C79: =C78-Calcs!U15 -> 23821077 | H79: By: | O79: 45649 | P79: Normal | Q79: =-265000000+30000000 -> -235000000
B80: Adjusted Collateral Value | C80: =C78-C79 -> 3.3744891e+08 | O80: 45688 | P80: Normal | Q80: 72000000
B81: Excess Concentrations | C81: =C80-'Concentration Limitations'!H9 -> 0 | O81: 45723 | P81: Normal | Q81: 12500000
B82: Aggregate Adjusted Collateral Value | C82: =C80-C81 -> 3.3744891e+08 | H82: Signature | O82: 45783 | P82: Normal | Q82: -25000000
B83: Pending Sales | C83: =Calcs!U13 -> 0 | O83: 45800 | P83: Normal | Q83: -27500000
B84: Aggregate Adjusted Collateral Value (net of Sales) | C84: =C82-C83 -> 3.3744891e+08 | H84: Andrew Jordan | O84: 45838 | P84: Normal | Q84: -14000000
H85: (Print Name)
B86: Facility Summary
B87: Maximum Facility Amount | C87: 400000000 | H87: Managing Director
B88: Current Availability | C88: =IF(I25="False","IC Test Breach!",+MIN(C11-K67,C89-K67)) -> 62428593 | H88: Title
B89: Maximum Availability | C89: =+MIN(C11,C87) -> 2.2302859e+08
H90: =TODAY() -> 45863
H91: Date

Sheet Calcs
A1: Indicative Borrowing Base | J1: ="= Manual Input" -> = Manual Input | M1: Maximum Portfolio Amount | O1: =$O$2+$O$3-$O$4-$O$5 -> 6.0054606e+08
B2: [greater than] | C2: [greater than] | D2: [greater than] | E2: [greater than] | F2: [less than] | I2: Harded Items | J2: =Hardcodes | M2: Maximum Facility Size | O2: ='Summary '!$I$4 -> 400000000
C3: Class 1 | D3: Class 2 | E3: Class 3 | F3: Class 4 | M3: Collateral Purchase Amount | O3: =$O$15*1000000 -> 3.6114606e+08
M4: Borrowings | O4: ='Summary '!$J$38 -> 160600000
A5: Tranche Size/ EBITDA | C5: 100 | D5: 25 | E5: 10 | F5: 10 | M5: Principal Distributions | O5: 0 | BO5: Agg Adjusted Collat Balance | BP5: Adv Rate per Each Category
A6: Sr Lev Cut-Off | C6: 6 | D6: 5.5 | E6: 5 | F6: 4.5 | BN6: Bought Not Settled (cashless) | BO6: =SUMIF($R17:$R117,$T$11,$BO$17:$BO$117) -> 0 | BP6: =IFERROR(SUMIF($R17:$R116,$T$11,BP17:BP117)/BO6,"")
A7: Sr Lev Cap | C7: 7 | D7: 6.5 | E7: 6 | F7: 5.5 | BN7: Settled NCB | BO7: =SUMIF($R17:$R117,$T$12,BO17:BO117) -> 3.3744891e+08 | BP7: =IFERROR(SUMIF($R17:$R117,$T$12,BP17:BP117)/BO7,"") -> 0.64941848
A8: 1L AR | C8: 0.7 | D8: 0.675 | E8: 0.65 | F8: 0.625 | BN8: Sold Unsettled | BO8: =SUMIF($R17:$R117,$T$13,BO17:BO117) -> 0 | BP8: =IFERROR(SUMIF($R17:$R116,$T$13,BP17:BP117)/BO8,"")
A9: 1L LO AR | C9: 0.575 | D9: 0.55 | E9: 0.52 | F9: 0.5
A10: 2L AR | C10: 0.4 | D10: 0.35 | E10: 0.35 | F10: 0.3 | T10: EQUITY CONTRIBUTED | U10: =SUMIF($R$17:$R$117,T10,$U$17:$U$117) -> 0
A11: Spread | C11: 0.0225 | D11: 0.0225 | E11: 0.0225 | F11: 0.0225 | T11: BOUGHT UNSETTLED | U11: =SUMIF($R$17:$R$117,T11,$U$17:$U$117) -> 0 | BO11: =SUMIF($R17:$R117,$T$11,BO17:BO117) -> 0
A12: Notional % | C12: =SUMIF($AE$17:$AE$117,C3,$I$17:$I$117)/$I$15 -> 0.066439125 | D12: =SUMIF($AE$17:$AE$117,D3,$I$17:$I$117)/$I$15 -> 0.32247059 | E12: =SUMIF($AE$17:$AE$117,E3,$I$17:$I$117)/$I$15 -> 0.61109029 | F12: =SUMIF($AE$17:$AE$117,F3,$I$17:$I$117)/$I$15 -> 0 | T12: SETTLED | U12: =SUMIF($R$17:$R$117,T12,$U$17:$U$117) -> 3.3744891e+08 | BN12: =SUMPRODUCT($K$16:$K$117,BN$16:BN$117) -> 3.5792895 | BO12: =SUMIF($R17:$R117,$T$12,BO17:BO117) -> 3.3744891e+08
A13: Avg AR | C13: =SUMIF($AE$17:AF117,C3,$AC$17:$AC$117)/SUMIF($AE$17:AF117,C3,$K$17:K117) -> 0.62102879 | D13: =IFERROR(SUMIF($AE$17:AG117,D3,$AC$17:$AC$117)/SUMIF($AE$17:AG117,D3,$K$17:K117), 0) -> 0.62666373 | E13: =IFERROR(SUMIF($AE$17:AI117,E3,$AC$17:$AC$117)/SUMIF($AE$17:AI117,E3,$K$17:K117),0) -> 0.62692613 | F13: =IFERROR(SUMIF($AE$17:AJ117,F3,$AC$17:$AC$117)/SUMIF($AE$17:AJ117,F3,$K$17:L117),0) -> 0 | T13: SOLD UNSETTLED | U13: =SUMIF($R$17:$R$117,T13,$U$17:$U$117) -> 0 | BO13: =SUMIF($R17:$R117,$T$13,BO17:BO117) -> 0
A14: Avg Leverage | C14: =SUMIF($AE$17:$AE$117,C3,$AB$17:$AB$117)/SUMIF($AE$17:$AE$117,C3,$K$17:$K$117) -> 6.4761735 | D14: =IFERROR(SUMIF($AE$17:$AE$117,D3,$AB$17:$AB$117)/SUMIF($AE$17:$AE$117,D3,$K$17:$K$117), 0) -> 1.6323792 | E14: =IFERROR(SUMIF($AE$17:$AE$117,E3,$AB$17:$AB$117)/SUMIF($AE$17:$AE$117,E3,$K$17:$K$117),0) -> 4.6832088 | F14: =IFERROR(SUMIF($AE$17:$AE$117,F3,$AB$17:$AB$117)/SUMIF($AE$17:$AE$117,F3,$K$17:$K$117),0) -> 0
H15: =SUM(H17:H117) -> 3.6126999e+08 | I15: =SUM(I17:I117) -> 3.6126999e+08 | J15: =SUM(J17:J117) -> 0 | O15: =SUM(O17:O117)/1000000 -> 361.14606 | U15: =SUM(U11:U13) -> 3.3744891e+08 | V15: =SUMPRODUCT(V17:V117,I17:I117)*1000000 -> 0 | AL15: =SUMPRODUCT(I17:I117,AL17:AL117)/$I$15 -> 0.6264497 | AN15: =SUMIFS(BP17:BP117,R17:R117,"<>"&"SOLD UNSETTLED")/SUMIFS(BO17:BO117,R17:R117,"<>"&"SOLD UNSETTLED") -> 0.64941848 | AO15: =SUMPRODUCT(I17:I117,AO17:AO117)/$I$15 -> 0.058103186 | BN15: =TODAY() -> 45863 | BO15: =SUM(BO17:BO117) -> 3.3744891e+08 | BP15: =SUM(BP17:BP117)/SUM(BO17:BO117) -> 0.64941848 | BY15: Current Metrics | CJ15: Metrics at Entry | CU15: =SUM(CU17:CU117) -> 35 | CV15: =SUM(CV17:CV117) -> 21 | CW15: =SUM(CW17:CW117) -> 41
A16: Company Name | B16: Admin Agent | C16: Lien | D16: Security Type | E16: Eligibility Criteria | F16: Industry | G16: [Reserved] | H16: Commitment (Local) | I16: Comittment (USD) | J16: Unfunded | K16: % of Port | L16: Purchase Price | M16: Mark Price | N16: Maturity Date | O16: Purchase Price Value | P16: Loan Value | Q16: Primary / Secondary | R16: Status | S16: Revaluation Event | T16: Revaluation Adjustment | U16: Adjusted Collateral Value | V16: Sale Price | W16: Sale Proceeds | X16: Reserved | Y16: Tranche Size | Z16: Reserved | AB16: %Lev | AC16: %AR | AD16: First Out Leverage | AE16: Class | AF16: Lev Cut-off | AG16: Lev Cap | AH16: 1L | AI16: 2L | AJ16: 1L_AR | AK16: 2L_AR | AL16: AR | AM16: AR Adjustment | AN16: Adjusted AR | AO16: Spread above Reference Rate | AP16: Reference Rate | AQ16: Floor | AR16: Fixed Rate Spread | AS16: PIK (LTM actual annualized PIK spread) | AU16: Current Cash Pay | AV16: Excluded PIK: Cash Pay > 4.5% | AW16: Concentration Limit Partial PIK | AX16: Ineligible Partial PIK | AY16: Non-Accrual Loan | AZ16: Moody's or S&P Rated | BA16: Covenent Type | BB16: Not FL | BC16: SNL>5.5x | BD16: USD | BE16: US Obligor | BF16: Non-USD | BG16: Obligor Domicile | BH16: FLLO | BI16: Second Lien | BJ16: Recurring Revenue | BK16: Fixed Rate | BL16: CCC+/Caa1 or below | BM16: Cov-Lite | BN16: WAL | BO16: Aggregate Net Collateral Balance | BP16: Aggregate Net Collateral Balance x AR (excl. sales) | BS16: Financial Statement | BT16: IC Ratio | BU16: Sr Lev | BW16: First Out Leverage | BX16: LTV | BY16: EBITDA | BZ16: LTM Revenue | CA16: LTM ARR | CB16: Net Debt to RR | CC16: Moody's | CD16: S&P | CE16: Financial Statement at Cut Off | CF16: IC Ratio at Cut-Off | CG16: Sr Lev at Cut-Off | CI16: First Out Leverage at Cut-Off | CJ16: LTV at Cut-Off | CK16: EBITDA at Cut-Off | CL16: LTM Revenue at Cut-Off | CM16: LTM ARR at Cut Off | CN16: Net Debt to RR at Cut Off | CO16: Moody's at Cut-Off | CP16: S&P at Cut-Off | CQ16: Cash Interest Coverage Ratio % Change | CR16: Sr Lev % Change | CS16: Sr Lev Change | CT16: EBITDA Change | CU16: Interest Coverage Ratio VAE? | CV16: Sr Leverage Ratio VAE? | CW16: Total VAE | CX16: Material Modification | CY16: Change in Partial PIK Status | CZ16: PIK Option | DA16: PIK Rate | DD16: Moody's | DE16: S&P | DI16: Purchase Price Requirement | DJ16: Currency | DK16: Senior Net Leverage <6.0x | DL16: EBITDA Threshold Covlite | DM16: EBITDA Minimum | DN16: Partial PIK Spread Test | DO16: Defaulted Obligation? | DP16: Eligible Loan?
A17: A1 Garage Merger Sub, LLC | B17: =IFERROR(VLOOKUP(A17,'Loan List '!$A$6:$BZ$75,2,FALSE),NA) -> 0 | C17: =VLOOKUP(A17,'Loan List '!$A$6:$G$75, 7, FALSE) -> First Lien | D17: =VLOOKUP(A17, 'Loan List '!$A$6:$K$82, 11, FALSE) -> FL | E17: =IF(DP17= "YES", TRUE, FALSE) -> TRUE | F17: =VLOOKUP(A17,'Loan List '!$A$6:$L$75, 12, FALSE) -> Energy Equipment & Services | H17: =+I17 -> 3183892.6 | I17: =VLOOKUP(A17,'Loan List '!$A$6:$L$82, 8, FALSE) -> 3183892.6 | J17: 0 | K17: =I17/$I$15 -> 0.008813056 | L17: =VLOOKUP(A17,'Loan List '!$A$6:$BA$82,24, FALSE) -> 100 | N17: =VLOOKUP(A17,'Loan List '!$A$6:$BA$82,22, FALSE) -> 47109 | O17: =IFERROR(MAX(0,I17-J17)*L17,"")/100 -> 3183892.6 | P17: =MIN(IF(AND(L17>=97%,Q17="Primary"),100%,L17),T17) -> 1 | Q17: Primary | R17: SETTLED | S17: =IF(OR(CU17=1,CV17=1,CW17=1),TRUE,FALSE) -> FALSE | T17: =VLOOKUP(A17,'Loan List '!$A$6:$BD$1048576,56,FALSE)/100 -> 1 | U17: =IF(E17=TRUE,P17*I17,0) -> 3183892.6 | V17: =VLOOKUP(A17,'Loan List '!$A$6:$BA$82,26, FALSE) -> 0 | W17: =V17*I17 -> 0 | Y17: =VLOOKUP(A17,'Loan List '!$A$6:$BA$75,27, FALSE) -> 0 | AB17: =K17*BU17 -> 0.01841032 | AC17: =K17*AL17 -> 0.0059488128 | AD17: =BW17 -> 0 | AE17: =IF(CK17>=$C$5,"Class 1",IF(CK17>=$D$5,"Class 2",IF(CK17>=$E$5,"Class 3","Class 4"))) -> Class 2 | AF17: =HLOOKUP($AE17,$B$3:$F$10,4,0) -> 5.5 | AG17: =IF(BB17,1,0)+HLOOKUP($AE17,$B$3:$F$10,5,0) -> 6.5 | AH17: =MIN(AF17/BU17,1) -> 1 | AI17: =IF(BU17>AG17,(AG17-AF17)/BU17,1-AH17) -> 0 | AJ17: =HLOOKUP($AE17,$B$3:$F$10,6,0) -> 0.675 | AK17: =HLOOKUP($AE17,$B$3:$F$10,8,0) -> 0.35 | AL17: =IF(OR(BI17, AND(BH17,AD17>1)), HLOOKUP(AE17,$B$3:$F$10,8,0),AH17*AJ17+AI17*AK17) -> 0.675 | AM17: ='Diversity Score'!$E$7 -> 1 | AN17: =AM17*AL17 -> 0.675 | AO17: =VLOOKUP(A17,'Loan List '!$A$6:$BA$75,17, FALSE) -> 0.045 | AP17: =VLOOKUP(A17,'Loan List '!$A$6:$BA$795,15, FALSE) -> SOFR | AQ17: =VLOOKUP(A17,'Loan List '!$A$6:$BA$795,16, FALSE) -> 0.01 | AR17: 0 | AS17: 0 | AU17: =AO17-AS17 -> 0.045 | AV17: =IF(AND(AS17>0%,AU17>4.5%),TRUE,FALSE) -> FALSE | AW17: =IF(AND(AS17>0%,AU17>=2.25%, AV17=FALSE),TRUE,FALSE) -> FALSE | AX17: =IF(AND(AS17>0%,AW17=FALSE, AV17=FALSE),TRUE, FALSE) -> FALSE | AZ17: =(OR(CC17<>"NR",CD17<>"NR")) -> FALSE | BA17: ='Loan List '!AS6 -> Maintenance Covenants | BB17: =IF(D17="FL",FALSE,TRUE) -> FALSE | BC17: =IF(BU17>5.5, TRUE, FALSE) -> FALSE | BD17: =IF(BF17="USD", TRUE,FALSE) -> TRUE | BE17: =IF(BG17="USA",TRUE,FALSE) -> TRUE | BF17: ='Loan List '!J6 -> USD | BG17: =VLOOKUP(A17,'Loan List '!$A$6:$BZ$75, 23, FALSE) -> USA | BH17: =IF(D17="FLLO", TRUE,FALSE) -> FALSE | BI17: =IF(C17="Second Lien",TRUE,FALSE) -> FALSE | BJ17: =IF('Loan List '!BP6=1, TRUE, FALSE) -> FALSE | BK17: =IF(AR17>0%,TRUE,FALSE) -> FALSE | BL17: =OR(LEFT(CC17,1)="C", LEFT(CD17,1)="C") -> FALSE | BM17: =IF('Loan List '!AT6="Yes", TRUE, FALSE) -> FALSE | BN17: =-($BN$15-N17)/365 -> 3.4136986 | BO17: ='Concentration Limitations'!H12 -> 3183892.6 | BP17: =IF(R17=$T$13,0,BO17*AL17) -> 2149127.5 | BS17: ='Loan List '!AG6 -> 45808 | BT17: ='Loan List '!AO6 -> 3.6700803 | BU17: ='Loan List '!AI6 -> 2.0889825 | BW17: 0 | BX17: - | BY17: ='Loan List '!AJ6 -> 66.178 | BZ17: ='Loan List '!AL6 -> 0 | CA17: 0 | CB17: 0 | CC17: NR | CD17: NR | CE17: - | CF17: ='Loan List '!AC6 -> 1.8629212 | CG17: ='Loan List '!AD6 -> 4.9219777 | CI17: 0 | CJ17: - | CK17: ='Loan List '!AB6 -> 26.53 | CL17: ='Loan List '!AE6 -> 0 | CM17: 0 | CN17: 0 | CO17: NR | CP17: NR | CQ17: =IFERROR(($BT17-$CF17)/$CF17,0) -> 0.97006741 | CR17: =IFERROR(($BU17-$CG17)/$CG17,0) -> -0.57558067 | CS17: =BU17-CG17 -> -2.8329952 | CT17: =(BY17/CK17)-1 -> 1.4944591 | CU17: =IF(OR($CQ17<'Summary '!$I$47,$BT17<'Summary '!$I$46),1,0) -> 0 | CV17: =IF(OR($CS17>='Summary '!$I$50, (AND(BU17>'Summary '!$I$52, Calcs!CR17> 'Summary '!$I$51))),1,0) -> 0 | CW17: =IF(OR(SUM(CU17:CV17)>=1,CX17="Yes"),1,0) -> 0 | CX17: No | CY17: No | CZ17: No | DD17: 0 | DE17: 0 | DI17: =IF(L17<90%,"Not Eligible","Eligible") -> Eligible | DJ17: =IF(OR(BF17="USD",BF17="CAD",BF17="EUR",BF17="GBP",BF17="AUD"),"Eligible","Not Eligible") -> Eligible | DK17: Eligible | DL17: Eligible | DM17: =IF(BM17="FALSE",IF(BY17<5,"Not Eligible","Eligible"),"Eligible") -> Eligible | DN17: =IF(AW17="TRUE",IF(AU17>=3%,"Eligible","Not Eligible"),"Not PIK") -> Not PIK | DO17: No | DP17: =IF(OR(DK17="Not Eligible",DL17="Not Eligible",DI17="Not Eligible",DJ17="Not Eligible",DM17="Not Eligible",DN17="Not Eligible",DO17="Yes"),"NO","YES") -> YES
A18: AFC - Dell Holding Corp. | B18: =IFERROR(VLOOKUP(A18,'Loan List '!$A$6:$BZ$75,2,FALSE),NA) -> 0 | C18: =VLOOKUP(A18,'Loan List '!$A$6:$G$75, 7, FALSE) -> First Lien | D18: =VLOOKUP(A18, 'Loan List '!$A$6:$K$82, 11, FALSE) -> FL | E18: =IF(DP18= "YES", TRUE, FALSE) -> TRUE | F18: =VLOOKUP(A18,'Loan List '!$A$6:$L$75, 12, FALSE) -> Distributors | H18: =+I18 -> 268902.61 | I18: =VLOOKUP(A18,'Loan List '!$A$6:$L$75, 8, FALSE) -> 268902.61 | J18: 0 | K18: =I18/$I$15 -> 0.00074432591 | L18: =VLOOKUP(A18,'Loan List '!$A$6:$BA$82,24, FALSE) -> 100 | N18: =VLOOKUP(A18,'Loan List '!$A$6:$BA$82,22, FALSE) -> 46486 | O18: =IFERROR(MAX(0,I18-J18)*L18,"")/100 -> 268902.61 | P18: =MIN(IF(AND(L18>=97%,Q18="Primary"),100%,L18),T18) -> 1 | Q18: Primary | R18: SETTLED | S18: =IF(OR(CU18=1,CV18=1,CW18=1),TRUE,FALSE) -> TRUE | T18: =VLOOKUP(A18,'Loan List '!$A$6:$BD$1048576,56,FALSE)/100 -> 1 | U18: =IF(E18=TRUE,P18*I18,0) -> 268902.61 | V18: =VLOOKUP(A18,'Loan List '!$A$6:$BA$82,26, FALSE) -> 0 | W18: =V18*I18 -> 0 | Y18: =VLOOKUP(A18,'Loan List '!$A$6:$BA$75,27, FALSE) -> 0 | AB18: =K18*BU18 -> 0.0046553716 | AC18: =K18*AL18 -> 0.00047323879 | AD18: =BW18 -> 0 | AE18: =IF(CK18>=$C$5,"Class 1",IF(CK18>=$D$5,"Class 2",IF(CK18>=$E$5,"Class 3","Class 4"))) -> Class 2 | AF18: =HLOOKUP($AE18,$B$3:$F$10,4,0) -> 5.5 | AG18: =IF(BB18,1,0)+HLOOKUP($AE18,$B$3:$F$10,5,0) -> 6.5 | AH18: =MIN(AF18/BU18,1) -> 0.87936965 | AI18: =IF(BU18>AG18,(AG18-AF18)/BU18,1-AH18) -> 0.12063035 | AJ18: =HLOOKUP($AE18,$B$3:$F$10,6,0) -> 0.675 | AK18: =HLOOKUP($AE18,$B$3:$F$10,8,0) -> 0.35 | AL18: =IF(OR(BI18, AND(BH18,AD18>1)), HLOOKUP(AE18,$B$3:$F$10,8,0),AH18*AJ18+AI18*AK18) -> 0.63579514 | AM18: ='Diversity Score'!$E$7 -> 1 | AN18: =AM18*AL18 -> 0.63579514 | AO18: =VLOOKUP(A18,'Loan List '!$A$6:$BA$75,17, FALSE) -> 0.055 | AP18: =VLOOKUP(A18,'Loan List '!$A$6:$BA$795,15, FALSE) -> SOFR | AQ18: =VLOOKUP(A18,'Loan List '!$A$6:$BA$795,16, FALSE) -> 0.01 | AR18: 0 | AS18: 0 | AU18: =AO18-AS18 -> 0.055 | AV18: =IF(AND(AS18>0%,AU18>4.5%),TRUE,FALSE) -> FALSE | AW18: =IF(AND(AS18>0%,AU18>=2.25%, AV18=FALSE),TRUE,FALSE) -> FALSE | AX18: =IF(AND(AS18>0%,AW18=FALSE, AV18=FALSE),TRUE, FALSE) -> FALSE | AZ18: =(OR(CC18<>"NR",CD18<>"NR")) -> FALSE | BA18: ='Loan List '!AS7 -> Cov-Lite | BB18: =IF(D18="FL",FALSE,TRUE) -> FALSE | BC18: =IF(BU18>5.5, TRUE, FALSE) -> TRUE | BD18: =IF(BF18="USD", TRUE,FALSE) -> TRUE | BE18: =IF(BG18="USA",TRUE,FALSE) -> TRUE | BF18: ='Loan List '!J7 -> USD | BG18: =VLOOKUP(A18,'Loan List '!$A$6:$BZ$75, 23, FALSE) -> USA | BH18: =IF(D18="FLLO", TRUE,FALSE) -> FALSE | BI18: =IF(C18="Second Lien",TRUE,FALSE) -> FALSE | BJ18: =IF('Loan List '!BP7=1, TRUE, FALSE) -> FALSE | BK18: =IF(AR18>0%,TRUE,FALSE) -> FALSE | BL18: =OR(LEFT(CC18,1)="C", LEFT(CD18,1)="C") -> FALSE | BM18: =IF('Loan List '!AT7="Yes", TRUE, FALSE) -> TRUE | BN18: =-($BN$15-N18)/365 -> 1.7068493 | BO18: ='Concentration Limitations'!H13 -> 268902.61 | BP18: =IF(R18=$T$13,0,BO18*AL18) -> 170966.97 | BS18: ='Loan List '!AG7 -> 45808 | BT18: ='Loan List '!AO7 -> 1.3038534 | BU18: ='Loan List '!AI7 -> 6.2544801 | BW18: 0 | BX18: - | BY18: ='Loan List '!AJ7 -> 74.476344 | BZ18: ='Loan List '!AL7 -> 0 | CA18: 0 | CB18: 0 | CC18: NR | CD18: NR | CE18: - | CF18: ='Loan List '!AC7 -> 1.604889 | CG18: ='Loan List '!AD7 -> 5.5133081 | CI18: 0 | CJ18: - | CK18: ='Loan List '!AB7 -> 62.582178 | CL18: ='Loan List '!AE7 -> 0 | CM18: 0 | CN18: 0 | CO18: NR | CP18: NR | CQ18: =IFERROR(($BT18-$CF18)/$CF18,0) -> -0.18757406 | CR18: =IFERROR(($BU18-$CG18)/$CG18,0) -> 0.13443327 | CS18: =BU18-CG18 -> 0.74117202 | CT18: =(BY18/CK18)-1 -> 0.19005678 | CU18: =IF(OR($CQ18<'Summary '!$I$47,$BT18<'Summary '!$I$46),1,0) -> 1 | CV18: =IF(OR($CS18>='Summary '!$I$50, (AND(BU18>'Summary '!$I$52, Calcs!CR18> 'Summary '!$I$51))),1,0) -> 0 | CW18: =IF(OR(SUM(CU18:CV18)>=1,CX18="Yes"),1,0) -> 1 | CX18: No | CY18: No | CZ18: No | DD18: 0 | DE18: 0 | DI18: =IF(L18<90%,"Not Eligible","Eligible") -> Eligible | DJ18: =IF(OR(BF18="USD",BF18="CAD",BF18="EUR",BF18="GBP",BF18="AUD"),"Eligible","Not Eligible") -> Eligible | DK18: Eligible | DL18: Eligible | DM18: =IF(BM18="FALSE",IF(BY18<5,"Not Eligible","Eligible"),"Eligible") -> Eligible | DN18: =IF(AW18=TRUE,IF(AU18>=3%,"Eligible","Not Eligible"),"Not PIK") -> Not PIK | DO18: No | DP18: =IF(OR(DK18="Not Eligible",DL18="Not Eligible",DI18="Not Eligible",DJ18="Not Eligible",DM18="Not Eligible",DN18="Not Eligible",DO18="Yes"),"NO","YES") -> YES
A19: Alpine Acquisition Corp II | B19: =IFERROR(VLOOKUP(A19,'Loan List '!$A$6:$BZ$75,2,FALSE),NA) -> 0 | C19: =VLOOKUP(A19,'Loan List '!$A$6:$G$75, 7, FALSE) -> First Lien | D19: =VLOOKUP(A19, 'Loan List '!$A$6:$K$82, 11, FALSE) -> FL | E19: =IF(DP19= "YES", TRUE, FALSE) -> TRUE | F19: =VLOOKUP(A19,'Loan List '!$A$6:$L$75, 12, FALSE) -> Containers and Packaging | H19: =+I19 -> 3988971 | I19: =VLOOKUP(A19,'Loan List '!$A$6:$L$75, 8, FALSE) -> 3988971 | J19: 0 | K19: =I19/$I$15 -> 0.011041523 | L19: =VLOOKUP(A19,'Loan List '!$A$6:$BA$82,24, FALSE) -> 100 | N19: =VLOOKUP(A19,'Loan List '!$A$6:$BA$82,22, FALSE) -> 47452 | O19: =IFERROR(MAX(0,I19-J19)*L19,"")/100 -> 3988971 | P19: =MIN(IF(AND(L19>=97%,Q19="Primary"),100%,L19),T19) -> 0 | Q19: Primary | R19: SETTLED | S19: =IF(OR(CU19=1,CV19=1,CW19=1),TRUE,FALSE) -> TRUE | T19: =VLOOKUP(A19,'Loan List '!$A$6:$BD$1048576,56,FALSE)/100 -> 0 | U19: =IF(E19=TRUE,P19*I19,0) -> 0 | V19: =VLOOKUP(A19,'Loan List '!$A$6:$BA$82,26, FALSE) -> 0 | W19: =V19*I19 -> 0 | Y19: =VLOOKUP(A19,'Loan List '!$A$6:$BA$75,27, FALSE) -> 0 | AB19: =K19*BU19 -> 0.22592463 | AC19: =K19*AL19 -> 0.0024822884 | AD19: =BW19 -> 0 | AE19: =IF(CK19>=$C$5,"Class 1",IF(CK19>=$D$5,"Class 2",IF(CK19>=$E$5,"Class 3","Class 4"))) -> Class 1 | AF19: =HLOOKUP($AE19,$B$3:$F$10,4,0) -> 6 | AG19: =IF(BB19,1,0)+HLOOKUP($AE19,$B$3:$F$10,5,0) -> 7 | AH19: =MIN(AF19/BU19,1) -> 0.29323558 | AI19: =IF(BU19>AG19,(AG19-AF19)/BU19,1-AH19) -> 0.048872596 | AJ19: =HLOOKUP($AE19,$B$3:$F$10,6,0) -> 0.7 | AK19: =HLOOKUP($AE19,$B$3:$F$10,8,0) -> 0.4 | AL19: =IF(OR(BI19, AND(BH19,AD19>1)), HLOOKUP(AE19,$B$3:$F$10,8,0),AH19*AJ19+AI19*AK19) -> 0.22481394 | AM19: ='Diversity Score'!$E$7 -> 1 | AN19: =AM19*AL19 -> 0.22481394 | AO19: =VLOOKUP(A19,'Loan List '!$A$6:$BA$75,17, FALSE) -> 0.061 | AP19: =VLOOKUP(A19,'Loan List '!$A$6:$BA$795,15, FALSE) -> SOFR | AQ19: =VLOOKUP(A19,'Loan List '!$A$6:$BA$795,16, FALSE) -> 0.01 | AR19: 0 | AS19: 0 | AU19: =AO19-AS19 -> 0.061 | AV19: =IF(AND(AS19>0%,AU19>4.5%),TRUE,FALSE) -> FALSE | AW19: =IF(AND(AS19>0%,AU19>=2.25%, AV19=FALSE),TRUE,FALSE) -> FALSE | AX19: =IF(AND(AS19>0%,AW19=FALSE, AV19=FALSE),TRUE, FALSE) -> FALSE | AZ19: =(OR(CC19<>"NR",CD19<>"NR")) -> FALSE | BA19: ='Loan List '!AS8 -> Maintenance Covenants | BB19: =IF(D19="FL",FALSE,TRUE) -> FALSE | BC19: =IF(BU19>5.5, TRUE, FALSE) -> TRUE | BD19: =IF(BF19="USD", TRUE,FALSE) -> TRUE | BE19: =IF(BG19="USA",TRUE,FALSE) -> TRUE | BF19: ='Loan List '!J8 -> USD | BG19: =VLOOKUP(A19,'Loan List '!$A$6:$BZ$75, 23, FALSE) -> USA | BH19: =IF(D19="FLLO", TRUE,FALSE) -> FALSE | BI19: =IF(C19="Second Lien",TRUE,FALSE) -> FALSE | BJ19: =IF('Loan List '!BP8=1, TRUE, FALSE) -> FALSE | BK19: =IF(AR19>0%,TRUE,FALSE) -> FALSE | BL19: =OR(LEFT(CC19,1)="C", LEFT(CD19,1)="C") -> FALSE | BM19: =IF('Loan List '!AT8="Yes", TRUE, FALSE) -> FALSE | BN19: =-($BN$15-N19)/365 -> 4.3534247 | BO19: ='Concentration Limitations'!H14 -> 0 | BP19: =IF(R19=$T$13,0,BO19*AL19) -> 0 | BS19: ='Loan List '!AG8 -> 45777 | BT19: ='Loan List '!AO8 -> 0.74807019 | BU19: ='Loan List '!AI8 -> 20.461364 | BW19: 0 | BX19: - | BY19: ='Loan List '!AJ8 -> 91.483 | BZ19: ='Loan List '!AL8 -> 0 | CA19: 0 | CB19: 0 | CC19: NR | CD19: NR | CE19: - | CF19: ='Loan List '!AC8 -> 2.65 | CG19: ='Loan List '!AD8 -> 5.41 | CI19: 0 | CJ19: - | CK19: ='Loan List '!AB8 -> 283.8 | CL19: ='Loan List '!AE8 -> 0 | CM19: 0 | CN19: 0 | CO19: NR | CP19: NR | CQ19: =IFERROR(($BT19-$CF19)/$CF19,0) -> -0.71770936 | CR19: =IFERROR(($BU19-$CG19)/$CG19,0) -> 2.7821376 | CS19: =BU19-CG19 -> 15.051364 | CT19: =(BY19/CK19)-1 -> -0.67764975 | CU19: =IF(OR($CQ19<'Summary '!$I$47,$BT19<'Summary '!$I$46),1,0) -> 1 | CV19: =IF(OR($CS19>='Summary '!$I$50, (AND(BU19>'Summary '!$I$52, Calcs!CR19> 'Summary '!$I$51))),1,0) -> 1 | CW19: =IF(OR(SUM(CU19:CV19)>=1,CX19="Yes"),1,0) -> 1 | CX19: No | CY19: No | CZ19: No | DD19: 0 | DE19: 0 | DI19: =IF(L19<90%,"Not Eligible","Eligible") -> Eligible | DJ19: =IF(OR(BF19="USD",BF19="CAD",BF19="EUR",BF19="GBP",BF19="AUD"),"Eligible","Not Eligible") -> Eligible | DK19: Eligible | DL19: Eligible | DM19: =IF(BM19="FALSE",IF(BY19<5,"Not Eligible","Eligible"),"Eligible") -> Eligible | DN19: =IF(AW19=TRUE,IF(AU19>=3%,"Eligible","Not Eligible"),"Not PIK") -> Not PIK | DO19: No | DP19: =IF(OR(DK19="Not Eligible",DL19="Not Eligible",DI19="Not Eligible",DJ19="Not Eligible",DM19="Not Eligible",DN19="Not Eligible",DO19="Yes"),"NO","YES") -> YES
A20: Archer Lewis | B20: =IFERROR(VLOOKUP(A20,'Loan List '!$A$6:$BZ$75,2,FALSE),NA) -> 0 | C20: =VLOOKUP(A20,'Loan List '!$A$6:$G$75, 7, FALSE) -> First Lien | D20: =VLOOKUP(A20, 'Loan List '!$A$6:$K$82, 11, FALSE) -> FL | E20: =IF(DP20= "YES", TRUE, FALSE) -> TRUE | F20: =VLOOKUP(A20,'Loan List '!$A$6:$L$75, 12, FALSE) -> Diversified Financial Services | H20: =+I20 -> 3893383.4 | I20: =VLOOKUP(A20,'Loan List '!$A$6:$L$75, 8, FALSE) -> 3893383.4 | J20: 0 | K20: =I20/$I$15 -> 0.010776936 | L20: =VLOOKUP(A20,'Loan List '!$A$6:$BA$82,24, FALSE) -> 100 | N20: =VLOOKUP(A20,'Loan List '!$A$6:$BA$82,22, FALSE) -> 47358 | O20: =IFERROR(MAX(0,I20-J20)*L20,"")/100 -> 3893383.4 | P20: =MIN(IF(AND(L20>=97%,Q20="Primary"),100%,L20),T20) -> 1 | Q20: Primary | R20: SETTLED | S20: =IF(OR(CU20=1,CV20=1,CW20=1),TRUE,FALSE) -> FALSE | T20: =VLOOKUP(A20,'Loan List '!$A$6:$BD$1048576,56,FALSE)/100 -> 1 | U20: =IF(E20=TRUE,P20*I20,0) -> 3893383.4 | V20: =VLOOKUP(A20,'Loan List '!$A$6:$BA$82,26, FALSE) -> 0 | W20: =V20*I20 -> 0 | Y20: =VLOOKUP(A20,'Loan List '!$A$6:$BA$75,27, FALSE) -> 0 | AB20: =K20*BU20 -> 0.040382181 | AC20: =K20*AL20 -> 0.0070050083 | AD20: =BW20 -> 0 | AE20: =IF(CK20>=$C$5,"Class 1",IF(CK20>=$D$5,"Class 2",IF(CK20>=$E$5,"Class 3","Class 4"))) -> Class 3 | AF20: =HLOOKUP($AE20,$B$3:$F$10,4,0) -> 5 | AG20: =IF(BB20,1,0)+HLOOKUP($AE20,$B$3:$F$10,5,0) -> 6 | AH20: =MIN(AF20/BU20,1) -> 1 | AI20: =IF(BU20>AG20,(AG20-AF20)/BU20,1-AH20) -> 0 | AJ20: =HLOOKUP($AE20,$B$3:$F$10,6,0) -> 0.65 | AK20: =HLOOKUP($AE20,$B$3:$F$10,8,0) -> 0.35 | AL20: =IF(OR(BI20, AND(BH20,AD20>1)), HLOOKUP(AE20,$B$3:$F$10,8,0),AH20*AJ20+AI20*AK20) -> 0.65 | AM20: ='Diversity Score'!$E$7 -> 1 | AN20: =AM20*AL20 -> 0.65 | AO20: =VLOOKUP(A20,'Loan List '!$A$6:$BA$75,17, FALSE) -> 0.0575 | AP20: =VLOOKUP(A20,'Loan List '!$A$6:$BA$795,15, FALSE) -> SOFR | AQ20: =VLOOKUP(A20,'Loan List '!$A$6:$BA$795,16, FALSE) -> 0.01 | AR20: 0 | AS20: 0 | AU20: =AO20-AS20 -> 0.0575 | AV20: =IF(AND(AS20>0%,AU20>4.5%),TRUE,FALSE) -> FALSE | AW20: =IF(AND(AS20>0%,AU20>=2.25%, AV20=FALSE),TRUE,FALSE) -> FALSE | AX20: =IF(AND(AS20>0%,AW20=FALSE, AV20=FALSE),TRUE, FALSE) -> FALSE | AZ20: =(OR(CC20<>"NR",CD20<>"NR")) -> FALSE | BA20: ='Loan List '!AS9 -> Maintenance Covenants | BB20: =IF(D20="FL",FALSE,TRUE) -> FALSE | BC20: =IF(BU20>5.5, TRUE, FALSE) -> FALSE | BD20: =IF(BF20="USD", TRUE,FALSE) -> TRUE | BE20: =IF(BG20="USA",TRUE,FALSE) -> TRUE | BF20: ='Loan List '!J9 -> USD | BG20: =VLOOKUP(A20,'Loan List '!$A$6:$BZ$75, 23, FALSE) -> USA | BH20: =IF(D20="FLLO", TRUE,FALSE) -> FALSE | BI20: =IF(C20="Second Lien",TRUE,FALSE) -> FALSE | BJ20: =IF('Loan List '!BP9=1, TRUE, FALSE) -> FALSE | BK20: =IF(AR20>0%,TRUE,FALSE) -> FALSE | BL20: =OR(LEFT(CC20,1)="C", LEFT(CD20,1)="C") -> FALSE | BM20: =IF('Loan List '!AT9="Yes", TRUE, FALSE) -> FALSE | BN20: =-($BN$15-N20)/365 -> 4.0958904 | BO20: ='Concentration Limitations'!H15 -> 3893383.4 | BP20: =IF(R20=$T$13,0,BO20*AL20) -> 2530699.2 | BS20: ='Loan List '!AG9 -> 45777 | BT20: ='Loan List '!AO9 -> 3.5015353 | BU20: ='Loan List '!AI9 -> 3.7470931 | BW20: 0 | BX20: - | BY20: ='Loan List '!AJ9 -> 15.684637 | BZ20: ='Loan List '!AL9 -> 0 | CA20: 0 | CB20: 0 | CC20: NR | CD20: NR | CE20: - | CF20: ='Loan List '!AC9 -> 2.4621136 | CG20: ='Loan List '!AD9 -> 2.8065192 | CI20: 0 | CJ20: - | CK20: ='Loan List '!AB9 -> 11.028693 | CL20: ='Loan List '!AE9 -> 0 | CM20: 0 | CN20: 0 | CO20: NR | CP20: NR | CQ20: =IFERROR(($BT20-$CF20)/$CF20,0) -> 0.42216644 | CR20: =IFERROR(($BU20-$CG20)/$CG20,0) -> 0.33513895 | CS20: =BU20-CG20 -> 0.94057389 | CT20: =(BY20/CK20)-1 -> 0.42216644 | CU20: =IF(OR($CQ20<'Summary '!$I$47,$BT20<'Summary '!$I$46),1,0) -> 0 | CV20: =IF(OR($CS20>='Summary '!$I$50, (AND(BU20>'Summary '!$I$52, Calcs!CR20> 'Summary '!$I$51))),1,0) -> 0 | CW20: =IF(OR(SUM(CU20:CV20)>=1,CX20="Yes"),1,0) -> 0 | CX20: No | CY20: No | CZ20: No | DD20: 0 | DE20: 0 | DI20: =IF(L20<90%,"Not Eligible","Eligible") -> Eligible | DJ20: =IF(OR(BF20="USD",BF20="CAD",BF20="EUR",BF20="GBP",BF20="AUD"),"Eligible","Not Eligible") -> Eligible | DK20: Eligible | DL20: Eligible | DM20: =IF(BM20="FALSE",IF(BY20<5,"Not Eligible","Eligible"),"Eligible") -> Eligible | DN20: =IF(AW20=TRUE,IF(AU20>=3%,"Eligible","Not Eligible"),"Not PIK") -> Not PIK | DO20: No | DP20: =IF(OR(DK20="Not Eligible",DL20="Not Eligible",DI20="Not Eligible",DJ20="Not Eligible",DM20="Not Eligible",DN20="Not Eligible",DO20="Yes"),"NO","YES") -> YES
A21: Argano, LLC | B21: =IFERROR(VLOOKUP(A21,'Loan List '!$A$6:$BZ$75,2,FALSE),NA) -> 0 | C21: =VLOOKUP(A21,'Loan List '!$A$6:$G$75, 7, FALSE) -> First Lien | D21: =VLOOKUP(A21, 'Loan List '!$A$6:$K$82, 11, FALSE) -> FL | E21: =IF(DP21= "YES", TRUE, FALSE) -> TRUE | F21: =VLOOKUP(A21,'Loan List '!$A$6:$L$75, 12, FALSE) -> IT Services | H21: =+I21 -> 820443.75 | I21: =VLOOKUP(A21,'Loan List '!$A$6:$L$75, 8, FALSE) -> 820443.75 | J21: 0 | K21: =I21/$I$15 -> 0.0022709989 | L21: =VLOOKUP(A21,'Loan List '!$A$6:$BA$82,24, FALSE) -> 100 | N21: =VLOOKUP(A21,'Loan List '!$A$6:$BA$82,22, FALSE) -> 47374 | O21: =IFERROR(MAX(0,I21-J21)*L21,"")/100 -> 820443.75 | P21: =MIN(IF(AND(L21>=97%,Q21="Primary"),100%,L21),T21) -> 1 | Q21: Primary | R21: SETTLED | S21: =IF(OR(CU21=1,CV21=1,CW21=1),TRUE,FALSE) -> TRUE | T21: =VLOOKUP(A21,'Loan List '!$A$6:$BD$1048576,56,FALSE)/100 -> 1 | U21: =IF(E21=TRUE,P21*I21,0) -> 820443.75 | V21: =VLOOKUP(A21,'Loan List '!$A$6:$BA$82,26, FALSE) -> 0 | W21: =V21*I21 -> 0 | Y21: =VLOOKUP(A21,'Loan List '!$A$6:$BA$75,27, FALSE) -> 0 | AB21: =K21*BU21 -> 0.010881625 | AC21: =K21*AL21 -> 0.0015329243 | AD21: =BW21 -> 0 | AE21: =IF(CK21>=$C$5,"Class 1",IF(CK21>=$D$5,"Class 2",IF(CK21>=$E$5,"Class 3","Class 4"))) -> Class 2 | AF21: =HLOOKUP($AE21,$B$3:$F$10,4,0) -> 5.5 | AG21: =IF(BB21,1,0)+HLOOKUP($AE21,$B$3:$F$10,5,0) -> 6.5 | AH21: =MIN(AF21/BU21,1) -> 1 | AI21: =IF(BU21>AG21,(AG21-AF21)/BU21,1-AH21) -> 0 | AJ21: =HLOOKUP($AE21,$B$3:$F$10,6,0) -> 0.675 | AK21: =HLOOKUP($AE21,$B$3:$F$10,8,0) -> 0.35 | AL21: =IF(OR(BI21, AND(BH21,AD21>1)), HLOOKUP(AE21,$B$3:$F$10,8,0),AH21*AJ21+AI21*AK21) -> 0.675 | AM21: ='Diversity Score'!$E$7 -> 1 | AN21: =AM21*AL21 -> 0.675 | AO21: =VLOOKUP(A21,'Loan List '!$A$6:$BA$75,17, FALSE) -> 0.0575 | AP21: =VLOOKUP(A21,'Loan List '!$A$6:$BA$795,15, FALSE) -> SOFR | AQ21: =VLOOKUP(A21,'Loan List '!$A$6:$BA$795,16, FALSE) -> 0.01 | AR21: 0 | AS21: 0 | AU21: =AO21-AS21 -> 0.0575 | AV21: =IF(AND(AS21>0%,AU21>4.5%),TRUE,FALSE) -> FALSE | AW21: =IF(AND(AS21>0%,AU21>=2.25%, AV21=FALSE),TRUE,FALSE) -> FALSE | AX21: =IF(AND(AS21>0%,AW21=FALSE, AV21=FALSE),TRUE, FALSE) -> FALSE | AZ21: =(OR(CC21<>"NR",CD21<>"NR")) -> FALSE | BA21: ='Loan List '!AS10 -> Maintenance Covenants | BB21: =IF(D21="FL",FALSE,TRUE) -> FALSE | BC21: =IF(BU21>5.5, TRUE, FALSE) -> FALSE | BD21: =IF(BF21="USD", TRUE,FALSE) -> TRUE | BE21: =IF(BG21="USA",TRUE,FALSE) -> TRUE | BF21: ='Loan List '!J10 -> USD | BG21: =VLOOKUP(A21,'Loan List '!$A$6:$BZ$75, 23, FALSE) -> USA | BH21: =IF(D21="FLLO", TRUE,FALSE) -> FALSE | BI21: =IF(C21="Second Lien",TRUE,FALSE) -> FALSE | BJ21: =IF('Loan List '!BP10=1, TRUE, FALSE) -> FALSE | BK21: =IF(AR21>0%,TRUE,FALSE) -> FALSE | BL21: =OR(LEFT(CC21,1)="C", LEFT(CD21,1)="C") -> FALSE | BM21: =IF('Loan List '!AT10="Yes", TRUE, FALSE) -> FALSE | BN21: =-($BN$15-N21)/365 -> 4.139726 | BO21: ='Concentration Limitations'!H16 -> 820443.75 | BP21: =IF(R21=$T$13,0,BO21*AL21) -> 553799.53 | BS21: ='Loan List '!AG10 -> 45777 | BT21: ='Loan List '!AO10 -> 1.9659379 | BU21: ='Loan List '!AI10 -> 4.791559 | BW21: 0 | BX21: - | BY21: ='Loan List '!AJ10 -> 78.649518 | BZ21: ='Loan List '!AL10 -> 0 | CA21: 0 | CB21: 0 | CC21: NR | CD21: NR | CE21: - | CF21: ='Loan List '!AC10 -> 1.4685834 | CG21: ='Loan List '!AD10 -> 3.6605579 | CI21: 0 | CJ21: - | CK21: ='Loan List '!AB10 -> 63.670152 | CL21: ='Loan List '!AE10 -> 0 | CM21: 0 | CN21: 0 | CO21: NR | CP21: NR | CQ21: =IFERROR(($BT21-$CF21)/$CF21,0) -> 0.33866271 | CR21: =IFERROR(($BU21-$CG21)/$CG21,0) -> 0.3089696 | CS21: =BU21-CG21 -> 1.1310011 | CT21: =(BY21/CK21)-1 -> 0.23526512 | CU21: =IF(OR($CQ21<'Summary '!$I$47,$BT21<'Summary '!$I$46),1,0) -> 0 | CV21: =IF(OR($CS21>='Summary '!$I$50, (AND(BU21>'Summary '!$I$52, Calcs!CR21> 'Summary '!$I$51))),1,0) -> 1 | CW21: =IF(OR(SUM(CU21:CV21)>=1,CX21="Yes"),1,0) -> 1 | CX21: No | CY21: No | CZ21: No | DD21: 0 | DE21: 0 | DI21: =IF(L21<90%,"Not Eligible","Eligible") -> Eligible | DJ21: =IF(OR(BF21="USD",BF21="CAD",BF21="EUR",BF21="GBP",BF21="AUD"),"Eligible","Not Eligible") -> Eligible | DK21: Eligible | DL21: Eligible | DM21: =IF(BM21="FALSE",IF(BY21<5,"Not Eligible","Eligible"),"Eligible") -> Eligible | DN21: =IF(AW21=TRUE,IF(AU21>=3%,"Eligible","Not Eligible"),"Not PIK") -> Not PIK | DO21: No | DP21: =IF(OR(DK21="Not Eligible",DL21="Not Eligible",DI21="Not Eligible",DJ21="Not Eligible",DM21="Not Eligible",DN21="Not Eligible",DO21="Yes"),"NO","YES") -> YES
A22: BBB Industries | B22: =IFERROR(VLOOKUP(A22,'Loan List '!$A$6:$BZ$75,2,FALSE),NA) -> 0 | C22: =VLOOKUP(A22,'Loan List '!$A$6:$G$75, 7, FALSE) -> First Lien | D22: =VLOOKUP(A22, 'Loan List '!$A$6:$K$82, 11, FALSE) -> FL | E22: =IF(DP22= "YES", TRUE, FALSE) -> TRUE | F22: =VLOOKUP(A22,'Loan List '!$A$6:$L$75, 12, FALSE) -> Automobiles | H22: =+I22 -> 247692.39 | I22: =VLOOKUP(A22,'Loan List '!$A$6:$L$75, 8, FALSE) -> 247692.39 | J22: 0 | K22: =I22/$I$15 -> 0.00068561574 | L22: =VLOOKUP(A22,'Loan List '!$A$6:$BA$82,24, FALSE) -> 93 | N22: =VLOOKUP(A22,'Loan List '!$A$6:$BA$82,22, FALSE) -> 47324 | O22: =IFERROR(MAX(0,I22-J22)*L22,"")/100 -> 230353.92 | P22: =MIN(IF(AND(L22>=97%,Q22="Primary"),100%,L22),T22) -> 0.93 | Q22: Primary | R22: SETTLED | S22: =IF(OR(CU22=1,CV22=1,CW22=1),TRUE,FALSE) -> TRUE | T22: =VLOOKUP(A22,'Loan List '!$A$6:$BD$1048576,56,FALSE)/100 -> 0.93 | U22: =IF(E22=TRUE,P22*I22,0) -> 230353.92 | V22: =VLOOKUP(A22,'Loan List '!$A$6:$BA$82,26, FALSE) -> 0 | W22: =V22*I22 -> 0 | Y22: =VLOOKUP(A22,'Loan List '!$A$6:$BA$75,27, FALSE) -> 0 | AB22: =K22*BU22 -> 0.0039406309 | AC22: =K22*AL22 -> 0.00047993102 | AD22: =BW22 -> 0 | AE22: =IF(CK22>=$C$5,"Class 1",IF(CK22>=$D$5,"Class 2",IF(CK22>=$E$5,"Class 3","Class 4"))) -> Class 1 | AF22: =HLOOKUP($AE22,$B$3:$F$10,4,0) -> 6 | AG22: =IF(BB22,1,0)+HLOOKUP($AE22,$B$3:$F$10,5,0) -> 7 | AH22: =MIN(AF22/BU22,1) -> 1 | AI22: =IF(BU22>AG22,(AG22-AF22)/BU22,1-AH22) -> 0 | AJ22: =HLOOKUP($AE22,$B$3:$F$10,6,0) -> 0.7 | AK22: =HLOOKUP($AE22,$B$3:$F$10,8,0) -> 0.4 | AL22: =IF(OR(BI22, AND(BH22,AD22>1)), HLOOKUP(AE22,$B$3:$F$10,8,0),AH22*AJ22+AI22*AK22) -> 0.7 | AM22: ='Diversity Score'!$E$7 -> 1 | AN22: =AM22*AL22 -> 0.7 | AO22: =VLOOKUP(A22,'Loan List '!$A$6:$BA$75,17, FALSE) -> 0.0535 | AP22: =VLOOKUP(A22,'Loan List '!$A$6:$BA$795,15, FALSE) -> SOFR | AQ22: =VLOOKUP(A22,'Loan List '!$A$6:$BA$795,16, FALSE) -> 0.005 | AR22: 0 | AS22: 0 | AU22: =AO22-AS22 -> 0.0535 | AV22: =IF(AND(AS22>0%,AU22>4.5%),TRUE,FALSE) -> FALSE | AW22: =IF(AND(AS22>0%,AU22>=2.25%, AV22=FALSE),TRUE,FALSE) -> FALSE | AX22: =IF(AND(AS22>0%,AW22=FALSE, AV22=FALSE),TRUE, FALSE) -> FALSE | AZ22: =(OR(CC22<>"NR",CD22<>"NR")) -> FALSE | BA22: ='Loan List '!AS11 -> Cov-Lite | BB22: =IF(D22="FL",FALSE,TRUE) -> FALSE | BC22: =IF(BU22>5.5, TRUE, FALSE) -> TRUE | BD22: =IF(BF22="USD", TRUE,FALSE) -> TRUE | BE22: =IF(BG22="USA",TRUE,FALSE) -> TRUE | BF22: ='Loan List '!J11 -> USD | BG22: =VLOOKUP(A22,'Loan List '!$A$6:$BZ$75, 23, FALSE) -> USA | BH22: =IF(D22="FLLO", TRUE,FALSE) -> FALSE | BI22: =IF(C22="Second Lien",TRUE,FALSE) -> FALSE | BJ22: =IF('Loan List '!BP11=1, TRUE, FALSE) -> FALSE | BK22: =IF(AR22>0%,TRUE,FALSE) -> FALSE | BL22: =OR(LEFT(CC22,1)="C", LEFT(CD22,1)="C") -> FALSE | BM22: =IF('Loan List '!AT11="Yes", TRUE, FALSE) -> TRUE | BN22: =-($BN$15-N22)/365 -> 4.0027397 | BO22: ='Concentration Limitations'!H17 -> 230353.92 | BP22: =IF(R22=$T$13,0,BO22*AL22) -> 161247.75 | BS22: ='Loan List '!AG11 -> 45747 | BT22: ='Loan List '!AO11 -> 1.4094118 | BU22: ='Loan List '!AI11 -> 5.7475793 | BW22: 0 | BX22: - | BY22: ='Loan List '!AJ11 -> 299.5 | BZ22: ='Loan List '!AL11 -> 0 | CA22: 0 | CB22: 0 | CC22: NR | CD22: NR | CE22: - | CF22: ='Loan List '!AC11 -> 2.1552003 | CG22: ='Loan List '!AD11 -> 5.0469961 | CI22: 0 | CJ22: - | CK22: ='Loan List '!AB11 -> 241.8 | CL22: ='Loan List '!AE11 -> 0 | CM22: 0 | CN22: 0 | CO22: NR | CP22: NR | CQ22: =IFERROR(($BT22-$CF22)/$CF22,0) -> -0.34604139 | CR22: =IFERROR(($BU22-$CG22)/$CG22,0) -> 0.13881192 | CS22: =BU22-CG22 -> 0.70058321 | CT22: =(BY22/CK22)-1 -> 0.23862696 | CU22: =IF(OR($CQ22<'Summary '!$I$47,$BT22<'Summary '!$I$46),1,0) -> 1 | CV22: =IF(OR($CS22>='Summary '!$I$50, (AND(BU22>'Summary '!$I$52, Calcs!CR22> 'Summary '!$I$51))),1,0) -> 0 | CW22: =IF(OR(SUM(CU22:CV22)>=1,CX22="Yes"),1,0) -> 1 | CX22: No | CY22: No | CZ22: No | DD22: 0 | DE22: 0 | DI22: =IF(L22<90%,"Not Eligible","Eligible") -> Eligible | DJ22: =IF(OR(BF22="USD",BF22="CAD",BF22="EUR",BF22="GBP",BF22="AUD"),"Eligible","Not Eligible") -> Eligible | DK22: Eligible | DL22: Eligible | DM22: =IF(BM22="FALSE",IF(BY22<5,"Not Eligible","Eligible"),"Eligible") -> Eligible | DN22: =IF(AW22=TRUE,IF(AU22>=3%,"Eligible","Not Eligible"),"Not PIK") -> Not PIK | DO22: No | DP22: =IF(OR(DK22="Not Eligible",DL22="Not Eligible",DI22="Not Eligible",DJ22="Not Eligible",DM22="Not Eligible",DN22="Not Eligible",DO22="Yes"),"NO","YES") -> YES
A23: Beacon Behavioral Support Services, LLC | B23: =IFERROR(VLOOKUP(A23,'Loan List '!$A$6:$BZ$75,2,FALSE),NA) -> 0 | C23: =VLOOKUP(A23,'Loan List '!$A$6:$G$75, 7, FALSE) -> First Lien | D23: =VLOOKUP(A23, 'Loan List '!$A$6:$K$82, 11, FALSE) -> FL | E23: =IF(DP23= "YES", TRUE, FALSE) -> TRUE | F23: =VLOOKUP(A23,'Loan List '!$A$6:$L$75, 12, FALSE) -> Health Care Providers & Services | H23: =+I23 -> 12139547 | I23: =VLOOKUP(A23,'Loan List '!$A$6:$L$75, 8, FALSE) -> 12139547 | J23: 0 | K23: =I23/$I$15 -> 0.033602424 | L23: =VLOOKUP(A23,'Loan List '!$A$6:$BA$82,24, FALSE) -> 100 | N23: =VLOOKUP(A23,'Loan List '!$A$6:$BA$82,22, FALSE) -> 47290 | O23: =IFERROR(MAX(0,I23-J23)*L23,"")/100 -> 12139547 | P23: =MIN(IF(AND(L23>=97%,Q23="Primary"),100%,L23),T23) -> 1 | Q23: Primary | R23: SETTLED | S23: =IF(OR(CU23=1,CV23=1,CW23=1),TRUE,FALSE) -> TRUE | T23: =VLOOKUP(A23,'Loan List '!$A$6:$BD$1048576,56,FALSE)/100 -> 1 | U23: =IF(E23=TRUE,P23*I23,0) -> 12139547 | V23: =VLOOKUP(A23,'Loan List '!$A$6:$BA$82,26, FALSE) -> 0 | W23: =V23*I23 -> 0 | Y23: =VLOOKUP(A23,'Loan List '!$A$6:$BA$75,27, FALSE) -> 0 | AB23: =K23*BU23 -> 0.17404001 | AC23: =K23*AL23 -> 0.021492429 | AD23: =BW23 -> 0 | AE23: =IF(CK23>=$C$5,"Class 1",IF(CK23>=$D$5,"Class 2",IF(CK23>=$E$5,"Class 3","Class 4"))) -> Class 3 | AF23: =HLOOKUP($AE23,$B$3:$F$10,4,0) -> 5 | AG23: =IF(BB23,1,0)+HLOOKUP($AE23,$B$3:$F$10,5,0) -> 6 | AH23: =MIN(AF23/BU23,1) -> 0.96536491 | AI23: =IF(BU23>AG23,(AG23-AF23)/BU23,1-AH23) -> 0.034635088 | AJ23: =HLOOKUP($AE23,$B$3:$F$10,6,0) -> 0.65 | AK23: =HLOOKUP($AE23,$B$3:$F$10,8,0) -> 0.35 | AL23: =IF(OR(BI23, AND(BH23,AD23>1)), HLOOKUP(AE23,$B$3:$F$10,8,0),AH23*AJ23+AI23*AK23) -> 0.63960947 | AM23: ='Diversity Score'!$E$7 -> 1 | AN23: =AM23*AL23 -> 0.63960947 | AO23: =VLOOKUP(A23,'Loan List '!$A$6:$BA$75,17, FALSE) -> 0.055 | AP23: =VLOOKUP(A23,'Loan List '!$A$6:$BA$795,15, FALSE) -> SOFR | AQ23: =VLOOKUP(A23,'Loan List '!$A$6:$BA$795,16, FALSE) -> 0.01 | AR23: 0 | AS23: 0 | AU23: =AO23-AS23 -> 0.055 | AV23: =IF(AND(AS23>0%,AU23>4.5%),TRUE,FALSE) -> FALSE | AW23: =IF(AND(AS23>0%,AU23>=2.25%, AV23=FALSE),TRUE,FALSE) -> FALSE | AX23: =IF(AND(AS23>0%,AW23=FALSE, AV23=FALSE),TRUE, FALSE) -> FALSE | AZ23: =(OR(CC23<>"NR",CD23<>"NR")) -> FALSE | BA23: ='Loan List '!AS12 -> Maintenance Covenants | BB23: =IF(D23="FL",FALSE,TRUE) -> FALSE | BC23: =IF(BU23>5.5, TRUE, FALSE) -> FALSE | BD23: =IF(BF23="USD", TRUE,FALSE) -> TRUE | BE23: =IF(BG23="USA",TRUE,FALSE) -> TRUE | BF23: ='Loan List '!J12 -> USD | BG23: =VLOOKUP(A23,'Loan List '!$A$6:$BZ$75, 23, FALSE) -> USA | BH23: =IF(D23="FLLO", TRUE,FALSE) -> FALSE | BI23: =IF(C23="Second Lien",TRUE,FALSE) -> FALSE | BJ23: =IF('Loan List '!BP12=1, TRUE, FALSE) -> FALSE | BK23: =IF(AR23>0%,TRUE,FALSE) -> FALSE | BL23: =OR(LEFT(CC23,1)="C", LEFT(CD23,1)="C") -> FALSE | BM23: =IF('Loan List '!AT12="Yes", TRUE, FALSE) -> FALSE | BN23: =-($BN$15-N23)/365 -> 3.909589 | BO23: ='Concentration Limitations'!H18 -> 12139547 | BP23: =IF(R23=$T$13,0,BO23*AL23) -> 7764569.4 | BS23: ='Loan List '!AG12 -> 45808 | BT23: ='Loan List '!AO12 -> 1.8527473 | BU23: ='Loan List '!AI12 -> 5.1793886 | BW23: 0 | BX23: - | BY23: ='Loan List '!AJ12 -> 21.173978 | BZ23: ='Loan List '!AL12 -> 0 | CA23: 0 | CB23: 0 | CC23: NR | CD23: NR | CE23: - | CF23: ='Loan List '!AC12 -> 4.25 | CG23: ='Loan List '!AD12 -> 3.7 | CI23: 0 | CJ23: - | CK23: ='Loan List '!AB12 -> 18.21 | CL23: ='Loan List '!AE12 -> 0 | CM23: 0 | CN23: 0 | CO23: NR | CP23: NR | CQ23: =IFERROR(($BT23-$CF23)/$CF23,0) -> -0.56405946 | CR23: =IFERROR(($BU23-$CG23)/$CG23,0) -> 0.39983475 | CS23: =BU23-CG23 -> 1.4793886 | CT23: =(BY23/CK23)-1 -> 0.16276651 | CU23: =IF(OR($CQ23<'Summary '!$I$47,$BT23<'Summary '!$I$46),1,0) -> 1 | CV23: =IF(OR($CS23>='Summary '!$I$50, (AND(BU23>'Summary '!$I$52, Calcs!CR23> 'Summary '!$I$51))),1,0) -> 1 | CW23: =IF(OR(SUM(CU23:CV23)>=1,CX23="Yes"),1,0) -> 1 | CX23: No | CY23: No | CZ23: No | DD23: 0 | DE23: 0 | DI23: =IF(L23<90%,"Not Eligible","Eligible") -> Eligible | DJ23: =IF(OR(BF23="USD",BF23="CAD",BF23="EUR",BF23="GBP",BF23="AUD"),"Eligible","Not Eligible") -> Eligible | DK23: Eligible | DL23: Eligible | DM23: =IF(BM23="FALSE",IF(BY23<5,"Not Eligible","Eligible"),"Eligible") -> Eligible | DN23: =IF(AW23=TRUE,IF(AU23>=3%,"Eligible","Not Eligible"),"Not PIK") -> Not PIK | DO23: No | DP23: =IF(OR(DK23="Not Eligible",DL23="Not Eligible",DI23="Not Eligible",DJ23="Not Eligible",DM23="Not Eligible",DN23="Not Eligible",DO23="Yes"),"NO","YES") -> YES
A24: BlackHawk Industrial | B24: =IFERROR(VLOOKUP(A24,'Loan List '!$A$6:$BZ$75,2,FALSE),NA) -> 0 | C24: =VLOOKUP(A24,'Loan List '!$A$6:$G$75, 7, FALSE) -> First Lien | D24: =VLOOKUP(A24, 'Loan List '!$A$6:$K$82, 11, FALSE) -> FL | E24: =IF(DP24= "YES", TRUE, FALSE) -> TRUE | F24: =VLOOKUP(A24,'Loan List '!$A$6:$L$75, 12, FALSE) -> Distributors | H24: =+I24 -> 8631215.8 | I24: =VLOOKUP(A24,'Loan List '!$A$6:$L$75, 8, FALSE) -> 8631215.8 | J24: 0 | K24: =I24/$I$15 -> 0.023891317 | L24: =VLOOKUP(A24,'Loan List '!$A$6:$BA$82,24, FALSE) -> 100 | N24: =VLOOKUP(A24,'Loan List '!$A$6:$BA$82,22, FALSE) -> 46282 | O24: =IFERROR(MAX(0,I24-J24)*L24,"")/100 -> 8631215.8 | P24: =MIN(IF(AND(L24>=97%,Q24="Primary"),100%,L24),T24) -> 1 | Q24: Primary | R24: SETTLED | S24: =IF(OR(CU24=1,CV24=1,CW24=1),TRUE,FALSE) -> TRUE | T24: =VLOOKUP(A24,'Loan List '!$A$6:$BD$1048576,56,FALSE)/100 -> 1 | U24: =IF(E24=TRUE,P24*I24,0) -> 8631215.8 | V24: =VLOOKUP(A24,'Loan List '!$A$6:$BA$82,26, FALSE) -> 0 | W24: =V24*I24 -> 0 | Y24: =VLOOKUP(A24,'Loan List '!$A$6:$BA$75,27, FALSE) -> 0 | AB24: =K24*BU24 -> 0.1463385 | AC24: =K24*AL24 -> 0.015334126 | AD24: =BW24 -> 0 | AE24: =IF(CK24>=$C$5,"Class 1",IF(CK24>=$D$5,"Class 2",IF(CK24>=$E$5,"Class 3","Class 4"))) -> Class 2 | AF24: =HLOOKUP($AE24,$B$3:$F$10,4,0) -> 5.5 | AG24: =IF(BB24,1,0)+HLOOKUP($AE24,$B$3:$F$10,5,0) -> 6.5 | AH24: =MIN(AF24/BU24,1) -> 0.89793349 | AI24: =IF(BU24>AG24,(AG24-AF24)/BU24,1-AH24) -> 0.10206651 | AJ24: =HLOOKUP($AE24,$B$3:$F$10,6,0) -> 0.675 | AK24: =HLOOKUP($AE24,$B$3:$F$10,8,0) -> 0.35 | AL24: =IF(OR(BI24, AND(BH24,AD24>1)), HLOOKUP(AE24,$B$3:$F$10,8,0),AH24*AJ24+AI24*AK24) -> 0.64182839 | AM24: ='Diversity Score'!$E$7 -> 1 | AN24: =AM24*AL24 -> 0.64182839 | AO24: =VLOOKUP(A24,'Loan List '!$A$6:$BA$75,17, FALSE) -> 0.054 | AP24: =VLOOKUP(A24,'Loan List '!$A$6:$BA$795,15, FALSE) -> SOFR | AQ24: =VLOOKUP(A24,'Loan List '!$A$6:$BA$795,16, FALSE) -> 0.01 | AR24: 0 | AS24: 0 | AU24: =AO24-AS24 -> 0.054 | AV24: =IF(AND(AS24>0%,AU24>4.5%),TRUE,FALSE) -> FALSE | AW24: =IF(AND(AS24>0%,AU24>=2.25%, AV24=FALSE),TRUE,FALSE) -> FALSE | AX24: =IF(AND(AS24>0%,AW24=FALSE, AV24=FALSE),TRUE, FALSE) -> FALSE | AZ24: =(OR(CC24<>"NR",CD24<>"NR")) -> FALSE | BA24: ='Loan List '!AS13 -> Maintenance Covenants | BB24: =IF(D24="FL",FALSE,TRUE) -> FALSE | BC24: =IF(BU24>5.5, TRUE, FALSE) -> TRUE | BD24: =IF(BF24="USD", TRUE,FALSE) -> TRUE | BE24: =IF(BG24="USA",TRUE,FALSE) -> TRUE | BF24: ='Loan List '!J13 -> USD | BG24: =VLOOKUP(A24,'Loan List '!$A$6:$BZ$75, 23, FALSE) -> USA | BH24: =IF(D24="FLLO", TRUE,FALSE) -> FALSE | BI24: =IF(C24="Second Lien",TRUE,FALSE) -> FALSE | BJ24: =IF('Loan List '!BP13=1, TRUE, FALSE) -> FALSE | BK24: =IF(AR24>0%,TRUE,FALSE) -> FALSE | BL24: =OR(LEFT(CC24,1)="C", LEFT(CD24,1)="C") -> FALSE | BM24: =IF('Loan List '!AT13="Yes", TRUE, FALSE) -> FALSE | BN24: =-($BN$15-N24)/365 -> 1.1479452 | BO24: ='Concentration Limitations'!H19 -> 8631215.8 | BP24: =IF(R24=$T$13,0,BO24*AL24) -> 5539759.3 | BS24: ='Loan List '!AG13 -> 45808 | BT24: ='Loan List '!AO13 -> 1.2612408 | BU24: ='Loan List '!AI13 -> 6.1251752 | BW24: 0 | BX24: - | BY24: ='Loan List '!AJ13 -> 49.93 | BZ24: ='Loan List '!AL13 -> 0 | CA24: 0 | CB24: 0 | CC24: NR | CD24: NR | CE24: - | CF24: ='Loan List '!AC13 -> 3.13 | CG24: ='Loan List '!AD13 -> 4.68 | CI24: 0 | CJ24: - | CK24: ='Loan List '!AB13 -> 38.43 | CL24: ='Loan List '!AE13 -> 0 | CM24: 0 | CN24: 0 | CO24: NR | CP24: NR | CQ24: =IFERROR(($BT24-$CF24)/$CF24,0) -> -0.59704767 | CR24: =IFERROR(($BU24-$CG24)/$CG24,0) -> 0.30879813 | CS24: =BU24-CG24 -> 1.4451752 | CT24: =(BY24/CK24)-1 -> 0.29924538 | CU24: =IF(OR($CQ24<'Summary '!$I$47,$BT24<'Summary '!$I$46),1,0) -> 1 | CV24: =IF(OR($CS24>='Summary '!$I$50, (AND(BU24>'Summary '!$I$52, Calcs!CR24> 'Summary '!$I$51))),1,0) -> 1 | CW24: =IF(OR(SUM(CU24:CV24)>=1,CX24="Yes"),1,0) -> 1 | CX24: No | CY24: No | CZ24: No | DD24: 0 | DE24: 0 | DI24: =IF(L24<90%,"Not Eligible","Eligible") -> Eligible | DJ24: =IF(OR(BF24="USD",BF24="CAD",BF24="EUR",BF24="GBP",BF24="AUD"),"Eligible","Not Eligible") -> Eligible | DK24: Eligible | DL24: Eligible | DM24: =IF(BM24="FALSE",IF(BY24<5,"Not Eligible","Eligible"),"Eligible") -> Eligible | DN24: =IF(AW24=TRUE,IF(AU24>=3%,"Eligible","Not Eligible"),"Not PIK") -> Not PIK | DO24: No | DP24: =IF(OR(DK24="Not Eligible",DL24="Not Eligible",DI24="Not Eligible",DJ24="Not Eligible",DM24="Not Eligible",DN24="Not Eligible",DO24="Yes"),"NO","YES") -> YES
A25: C5MI Acquisition, LLC | B25: =IFERROR(VLOOKUP(A25,'Loan List '!$A$6:$BZ$75,2,FALSE),NA) -> 0 | C25: =VLOOKUP(A25,'Loan List '!$A$6:$G$75, 7, FALSE) -> First Lien | D25: =VLOOKUP(A25, 'Loan List '!$A$6:$K$82, 11, FALSE) -> FL | E25: =IF(DP25= "YES", TRUE, FALSE) -> TRUE | F25: =VLOOKUP(A25,'Loan List '!$A$6:$L$75, 12, FALSE) -> IT Services | H25: =+I25 -> 1488750 | I25: =VLOOKUP(A25,'Loan List '!$A$6:$L$75, 8, FALSE) -> 1488750 | J25: 0 | K25: =I25/$I$15 -> 0.0041208793 | L25: =VLOOKUP(A25,'Loan List '!$A$6:$BA$82,24, FALSE) -> 100 | N25: =VLOOKUP(A25,'Loan List '!$A$6:$BA$82,22, FALSE) -> 47330 | O25: =IFERROR(MAX(0,I25-J25)*L25,"")/100 -> 1488750 | P25: =MIN(IF(AND(L25>=97%,Q25="Primary"),100%,L25),T25) -> 1 | Q25: Primary | R25: SETTLED | S25: =IF(OR(CU25=1,CV25=1,CW25=1),TRUE,FALSE) -> FALSE | T25: =VLOOKUP(A25,'Loan List '!$A$6:$BD$1048576,56,FALSE)/100 -> 1 | U25: =IF(E25=TRUE,P25*I25,0) -> 1488750 | V25: =VLOOKUP(A25,'Loan List '!$A$6:$BA$82,26, FALSE) -> 0 | W25: =V25*I25 -> 0 | Y25: =VLOOKUP(A25,'Loan List '!$A$6:$BA$75,27, FALSE) -> 0 | AB25: =K25*BU25 -> 0.017419567 | AC25: =K25*AL25 -> 0.0026785715 | AD25: =BW25 -> 0 | AE25: =IF(CK25>=$C$5,"Class 1",IF(CK25>=$D$5,"Class 2",IF(CK25>=$E$5,"Class 3","Class 4"))) -> Class 3 | AF25: =HLOOKUP($AE25,$B$3:$F$10,4,0) -> 5 | AG25: =IF(BB25,1,0)+HLOOKUP($AE25,$B$3:$F$10,5,0) -> 6 | AH25: =MIN(AF25/BU25,1) -> 1 | AI25: =IF(BU25>AG25,(AG25-AF25)/BU25,1-AH25) -> 0 | AJ25: =HLOOKUP($AE25,$B$3:$F$10,6,0) -> 0.65 | AK25: =HLOOKUP($AE25,$B$3:$F$10,8,0) -> 0.35 | AL25: =IF(OR(BI25, AND(BH25,AD25>1)), HLOOKUP(AE25,$B$3:$F$10,8,0),AH25*AJ25+AI25*AK25) -> 0.65 | AM25: ='Diversity Score'!$E$7 -> 1 | AN25: =AM25*AL25 -> 0.65 | AO25: =VLOOKUP(A25,'Loan List '!$A$6:$BA$75,17, FALSE) -> 0.06 | AP25: =VLOOKUP(A25,'Loan List '!$A$6:$BA$795,15, FALSE) -> SOFR | AQ25: =VLOOKUP(A25,'Loan List '!$A$6:$BA$795,16, FALSE) -> 0.01 | AR25: 0 | AS25: 0 | AU25: =AO25-AS25 -> 0.06 | AV25: =IF(AND(AS25>0%,AU25>4.5%),TRUE,FALSE) -> FALSE | AW25: =IF(AND(AS25>0%,AU25>=2.25%, AV25=FALSE),TRUE,FALSE) -> FALSE | AX25: =IF(AND(AS25>0%,AW25=FALSE, AV25=FALSE),TRUE, FALSE) -> FALSE | AZ25: =(OR(CC25<>"NR",CD25<>"NR")) -> FALSE | BA25: ='Loan List '!AS14 -> Maintenance Covenants | BB25: =IF(D25="FL",FALSE,TRUE) -> FALSE | BC25: =IF(BU25>5.5, TRUE, FALSE) -> FALSE | BD25: =IF(BF25="USD", TRUE,FALSE) -> TRUE | BE25: =IF(BG25="USA",TRUE,FALSE) -> TRUE | BF25: ='Loan List '!J14 -> USD | BG25: =VLOOKUP(A25,'Loan List '!$A$6:$BZ$75, 23, FALSE) -> USA | BH25: =IF(D25="FLLO", TRUE,FALSE) -> FALSE | BI25: =IF(C25="Second Lien",TRUE,FALSE) -> FALSE | BJ25: =IF('Loan List '!BP14=1, TRUE, FALSE) -> FALSE | BK25: =IF(AR25>0%,TRUE,FALSE) -> FALSE | BL25: =OR(LEFT(CC25,1)="C", LEFT(CD25,1)="C") -> FALSE | BM25: =IF('Loan List '!AT14="Yes", TRUE, FALSE) -> FALSE | BN25: =-($BN$15-N25)/365 -> 4.0191781 | BO25: ='Concentration Limitations'!H20 -> 1488750 | BP25: =IF(R25=$T$13,0,BO25*AL25) -> 967687.5 | BS25: ='Loan List '!AG14 -> 45808 | BT25: ='Loan List '!AO14 -> 1.996864 | BU25: ='Loan List '!AI14 -> 4.2271482 | BW25: 0 | BX25: - | BY25: ='Loan List '!AJ14 -> 17.97577 | BZ25: ='Loan List '!AL14 -> 0 | CA25: 0 | CB25: 0 | CC25: NR | CD25: NR | CE25: - | CF25: ='Loan List '!AC14 -> 2.1230412 | CG25: ='Loan List '!AD14 -> 3.9042799 | CI25: 0 | CJ25: - | CK25: ='Loan List '!AB14 -> 19.728528 | CL25: ='Loan List '!AE14 -> 0 | CM25: 0 | CN25: 0 | CO25: NR | CP25: NR | CQ25: =IFERROR(($BT25-$CF25)/$CF25,0) -> -0.059432272 | CR25: =IFERROR(($BU25-$CG25)/$CG25,0) -> 0.082695985 | CS25: =BU25-CG25 -> 0.32286827 | CT25: =(BY25/CK25)-1 -> -0.088843831 | CU25: =IF(OR($CQ25<'Summary '!$I$47,$BT25<'Summary '!$I$46),1,0) -> 0 | CV25: =IF(OR($CS25>='Summary '!$I$50, (AND(BU25>'Summary '!$I$52, Calcs!CR25> 'Summary '!$I$51))),1,0) -> 0 | CW25: =IF(OR(SUM(CU25:CV25)>=1,CX25="Yes"),1,0) -> 0 | CX25: No | CY25: No | CZ25: No | DD25: 0 | DE25: 0 | DI25: =IF(L25<90%,"Not Eligible","Eligible") -> Eligible | DJ25: =IF(OR(BF25="USD",BF25="CAD",BF25="EUR",BF25="GBP",BF25="AUD"),"Eligible","Not Eligible") -> Eligible | DK25: Eligible | DL25: Eligible | DM25: =IF(BM25="FALSE",IF(BY25<5,"Not Eligible","Eligible"),"Eligible") -> Eligible | DN25: =IF(AW25=TRUE,IF(AU25>=3%,"Eligible","Not Eligible"),"Not PIK") -> Not PIK | DO25: No | DP25: =IF(OR(DK25="Not Eligible",DL25="Not Eligible",DI25="Not Eligible",DJ25="Not Eligible",DM25="Not Eligible",DN25="Not Eligible",DO25="Yes"),"NO","YES") -> YES
A26: CF512, Inc. | B26: =IFERROR(VLOOKUP(A26,'Loan List '!$A$6:$BZ$75,2,FALSE),NA) -> 0 | C26: =VLOOKUP(A26,'Loan List '!$A$6:$G$75, 7, FALSE) -> First Lien | D26: =VLOOKUP(A26, 'Loan List '!$A$6:$K$82, 11, FALSE) -> FL | E26: =IF(DP26= "YES", TRUE, FALSE) -> TRUE | F26: =VLOOKUP(A26,'Loan List '!$A$6:$L$75, 12, FALSE) -> Media | H26: =+I26 -> 6282197.3 | I26: =VLOOKUP(A26,'Loan List '!$A$6:$L$75, 8, FALSE) -> 6282197.3 | J26: 0 | K26: =I26/$I$15 -> 0.017389204 | L26: =VLOOKUP(A26,'Loan List '!$A$6:$BA$82,24, FALSE) -> 100 | N26: =VLOOKUP(A26,'Loan List '!$A$6:$BA$82,22, FALSE) -> 46266 | O26: =IFERROR(MAX(0,I26-J26)*L26,"")/100 -> 6282197.3 | P26: =MIN(IF(AND(L26>=97%,Q26="Primary"),100%,L26),T26) -> 1 | Q26: Primary | R26: SETTLED | S26: =IF(OR(CU26=1,CV26=1,CW26=1),TRUE,FALSE) -> TRUE | T26: =VLOOKUP(A26,'Loan List '!$A$6:$BD$1048576,56,FALSE)/100 -> 1 | U26: =IF(E26=TRUE,P26*I26,0) -> 6282197.3 | V26: =VLOOKUP(A26,'Loan List '!$A$6:$BA$82,26, FALSE) -> 0 | W26: =V26*I26 -> 0 | Y26: =VLOOKUP(A26,'Loan List '!$A$6:$BA$75,27, FALSE) -> 0 | AB26: =K26*BU26 -> 0.095517246 | AC26: =K26*AL26 -> 0.010834857 | AD26: =BW26 -> 0 | AE26: =IF(CK26>=$C$5,"Class 1",IF(CK26>=$D$5,"Class 2",IF(CK26>=$E$5,"Class 3","Class 4"))) -> Class 3 | AF26: =HLOOKUP($AE26,$B$3:$F$10,4,0) -> 5 | AG26: =IF(BB26,1,0)+HLOOKUP($AE26,$B$3:$F$10,5,0) -> 6 | AH26: =MIN(AF26/BU26,1) -> 0.91026513 | AI26: =IF(BU26>AG26,(AG26-AF26)/BU26,1-AH26) -> 0.089734874 | AJ26: =HLOOKUP($AE26,$B$3:$F$10,6,0) -> 0.65 | AK26: =HLOOKUP($AE26,$B$3:$F$10,8,0) -> 0.35 | AL26: =IF(OR(BI26, AND(BH26,AD26>1)), HLOOKUP(AE26,$B$3:$F$10,8,0),AH26*AJ26+AI26*AK26) -> 0.62307954 | AM26: ='Diversity Score'!$E$7 -> 1 | AN26: =AM26*AL26 -> 0.62307954 | AO26: =VLOOKUP(A26,'Loan List '!$A$6:$BA$75,17, FALSE) -> 0.0619 | AP26: =VLOOKUP(A26,'Loan List '!$A$6:$BA$795,15, FALSE) -> SOFR | AQ26: =VLOOKUP(A26,'Loan List '!$A$6:$BA$795,16, FALSE) -> 0.01 | AR26: 0 | AS26: 0 | AU26: =AO26-AS26 -> 0.0619 | AV26: =IF(AND(AS26>0%,AU26>4.5%),TRUE,FALSE) -> FALSE | AW26: =IF(AND(AS26>0%,AU26>=2.25%, AV26=FALSE),TRUE,FALSE) -> FALSE | AX26: =IF(AND(AS26>0%,AW26=FALSE, AV26=FALSE),TRUE, FALSE) -> FALSE | AZ26: =(OR(CC26<>"NR",CD26<>"NR")) -> FALSE | BA26: ='Loan List '!AS15 -> Maintenance Covenants | BB26: =IF(D26="FL",FALSE,TRUE) -> FALSE | BC26: =IF(BU26>5.5, TRUE, FALSE) -> FALSE | BD26: =IF(BF26="USD", TRUE,FALSE) -> TRUE | BE26: =IF(BG26="USA",TRUE,FALSE) -> TRUE | BF26: ='Loan List '!J15 -> USD | BG26: =VLOOKUP(A26,'Loan List '!$A$6:$BZ$75, 23, FALSE) -> USA | BH26: =IF(D26="FLLO", TRUE,FALSE) -> FALSE | BI26: =IF(C26="Second Lien",TRUE,FALSE) -> FALSE | BJ26: =IF('Loan List '!BP15=1, TRUE, FALSE) -> FALSE | BK26: =IF(AR26>0%,TRUE,FALSE) -> FALSE | BL26: =OR(LEFT(CC26,1)="C", LEFT(CD26,1)="C") -> FALSE | BM26: =IF('Loan List '!AT15="Yes", TRUE, FALSE) -> FALSE | BN26: =-($BN$15-N26)/365 -> 1.1041096 | BO26: ='Concentration Limitations'!H21 -> 6282197.3 | BP26: =IF(R26=$T$13,0,BO26*AL26) -> 3914308.6 | BS26: ='Loan List '!AG15 -> 45808 | BT26: ='Loan List '!AO15 -> 1.5540854 | BU26: ='Loan List '!AI15 -> 5.4929052 | BW26: 0 | BX26: - | BY26: ='Loan List '!AJ15 -> 12.051 | BZ26: ='Loan List '!AL15 -> 0 | CA26: 0 | CB26: 0 | CC26: NR | CD26: NR | CE26: - | CF26: ='Loan List '!AC15 -> 1.3879915 | CG26: ='Loan List '!AD15 -> 5.2933867 | CI26: 0 | CJ26: - | CK26: ='Loan List '!AB15 -> 12.233 | CL26: ='Loan List '!AE15 -> 0 | CM26: 0 | CN26: 0 | CO26: NR | CP26: NR | CQ26: =IFERROR(($BT26-$CF26)/$CF26,0) -> 0.11966494 | CR26: =IFERROR(($BU26-$CG26)/$CG26,0) -> 0.037692015 | CS26: =BU26-CG26 -> 0.19951841 | CT26: =(BY26/CK26)-1 -> -0.01487779 | CU26: =IF(OR($CQ26<'Summary '!$I$47,$BT26<'Summary '!$I$46),1,0) -> 1 | CV26: =IF(OR($CS26>='Summary '!$I$50, (AND(BU26>'Summary '!$I$52, Calcs!CR26> 'Summary '!$I$51))),1,0) -> 0 | CW26: =IF(OR(SUM(CU26:CV26)>=1,CX26="Yes"),1,0) -> 1 | CX26: No | CY26: No | CZ26: No | DD26: 0 | DE26: 0 | DI26: =IF(L26<90%,"Not Eligible","Eligible") -> Eligible | DJ26: =IF(OR(BF26="USD",BF26="CAD",BF26="EUR",BF26="GBP",BF26="AUD"),"Eligible","Not Eligible") -> Eligible | DK26: Eligible | DL26: Eligible | DM26: =IF(BM26="FALSE",IF(BY26<5,"Not Eligible","Eligible"),"Eligible") -> Eligible | DN26: =IF(AW26=TRUE,IF(AU26>=3%,"Eligible","Not Eligible"),"Not PIK") -> Not PIK | DO26: No | DP26: =IF(OR(DK26="Not Eligible",DL26="Not Eligible",DI26="Not Eligible",DJ26="Not Eligible",DM26="Not Eligible",DN26="Not Eligible",DO26="Yes"),"NO","YES") -> YES
A27: Carnegie Dartlet, LLC | B27: =IFERROR(VLOOKUP(A27,'Loan List '!$A$6:$BZ$75,2,FALSE),NA) -> 0 | C27: =VLOOKUP(A27,'Loan List '!$A$6:$G$75, 7, FALSE) -> First Lien | D27: =VLOOKUP(A27, 'Loan List '!$A$6:$K$82, 11, FALSE) -> FL | E27: =IF(DP27= "YES", TRUE, FALSE) -> TRUE | F27: =VLOOKUP(A27,'Loan List '!$A$6:$L$75, 12, FALSE) -> Media | H27: =+I27 -> 6882726.1 | I27: =VLOOKUP(A27,'Loan List '!$A$6:$L$75, 8, FALSE) -> 6882726.1 | J27: 0 | K27: =I27/$I$15 -> 0.019051475 | L27: =VLOOKUP(A27,'Loan List '!$A$6:$BA$82,24, FALSE) -> 100 | N27: =VLOOKUP(A27,'Loan List '!$A$6:$BA$82,22, FALSE) -> 47521 | O27: =IFERROR(MAX(0,I27-J27)*L27,"")/100 -> 6882726.1 | P27: =MIN(IF(AND(L27>=97%,Q27="Primary"),100%,L27),T27) -> 1 | Q27: Primary | R27: SETTLED | S27: =IF(OR(CU27=1,CV27=1,CW27=1),TRUE,FALSE) -> TRUE | T27: =VLOOKUP(A27,'Loan List '!$A$6:$BD$1048576,56,FALSE)/100 -> 1 | U27: =IF(E27=TRUE,P27*I27,0) -> 6882726.1 | V27: =VLOOKUP(A27,'Loan List '!$A$6:$BA$82,26, FALSE) -> 0 | W27: =V27*I27 -> 0 | Y27: =VLOOKUP(A27,'Loan List '!$A$6:$BA$75,27, FALSE) -> 0 | AB27: =K27*BU27 -> 0.090682642 | AC27: =K27*AL27 -> 0.012383459 | AD27: =BW27 -> 0 | AE27: =IF(CK27>=$C$5,"Class 1",IF(CK27>=$D$5,"Class 2",IF(CK27>=$E$5,"Class 3","Class 4"))) -> Class 3 | AF27: =HLOOKUP($AE27,$B$3:$F$10,4,0) -> 5 | AG27: =IF(BB27,1,0)+HLOOKUP($AE27,$B$3:$F$10,5,0) -> 6 | AH27: =MIN(AF27/BU27,1) -> 1 | AI27: =IF(BU27>AG27,(AG27-AF27)/BU27,1-AH27) -> 0 | AJ27: =HLOOKUP($AE27,$B$3:$F$10,6,0) -> 0.65 | AK27: =HLOOKUP($AE27,$B$3:$F$10,8,0) -> 0.35 | AL27: =IF(OR(BI27, AND(BH27,AD27>1)), HLOOKUP(AE27,$B$3:$F$10,8,0),AH27*AJ27+AI27*AK27) -> 0.65 | AM27: ='Diversity Score'!$E$7 -> 1 | AN27: =AM27*AL27 -> 0.65 | AO27: =VLOOKUP(A27,'Loan List '!$A$6:$BA$75,17, FALSE) -> 0.055 | AP27: =VLOOKUP(A27,'Loan List '!$A$6:$BA$795,15, FALSE) -> SOFR | AQ27: =VLOOKUP(A27,'Loan List '!$A$6:$BA$795,16, FALSE) -> 0.01 | AR27: 0 | AS27: 0 | AU27: =AO27-AS27 -> 0.055 | AV27: =IF(AND(AS27>0%,AU27>4.5%),TRUE,FALSE) -> FALSE | AW27: =IF(AND(AS27>0%,AU27>=2.25%, AV27=FALSE),TRUE,FALSE) -> FALSE | AX27: =IF(AND(AS27>0%,AW27=FALSE, AV27=FALSE),TRUE, FALSE) -> FALSE | AZ27: =(OR(CC27<>"NR",CD27<>"NR")) -> FALSE | BA27: ='Loan List '!AS16 -> Maintenance Covenants | BB27: =IF(D27="FL",FALSE,TRUE) -> FALSE | BC27: =IF(BU27>5.5, TRUE, FALSE) -> FALSE | BD27: =IF(BF27="USD", TRUE,FALSE) -> TRUE | BE27: =IF(BG27="USA",TRUE,FALSE) -> TRUE | BF27: ='Loan List '!J16 -> USD | BG27: =VLOOKUP(A27,'Loan List '!$A$6:$BZ$75, 23, FALSE) -> USA | BH27: =IF(D27="FLLO", TRUE,FALSE) -> FALSE | BI27: =IF(C27="Second Lien",TRUE,FALSE) -> FALSE | BJ27: =IF('Loan List '!BP16=1, TRUE, FALSE) -> FALSE | BK27: =IF(AR27>0%,TRUE,FALSE) -> FALSE | BL27: =OR(LEFT(CC27,1)="C", LEFT(CD27,1)="C") -> FALSE | BM27: =IF('Loan List '!AT16="Yes", TRUE, FALSE) -> FALSE | BN27: =-($BN$15-N27)/365 -> 4.5424658 | BO27: ='Concentration Limitations'!H22 -> 6882726.1 | BP27: =IF(R27=$T$13,0,BO27*AL27) -> 4473772 | BS27: ='Loan List '!AG16 -> 45777 | BT27: ='Loan List '!AO16 -> 1.9328323 | BU27: ='Loan List '!AI16 -> 4.7598751 | BW27: 0 | BX27: - | BY27: ='Loan List '!AJ16 -> 18.576538 | BZ27: ='Loan List '!AL16 -> 0 | CA27: 0 | CB27: 0 | CC27: NR | CD27: NR | CE27: - | CF27: ='Loan List '!AC16 -> 4.7515887 | CG27: ='Loan List '!AD16 -> 2.7673367 | CI27: 0 | CJ27: - | CK27: ='Loan List '!AB16 -> 19.457816 | CL27: ='Loan List '!AE16 -> 0 | CM27: 0 | CN27: 0 | CO27: NR | CP27: NR | CQ27: =IFERROR(($BT27-$CF27)/$CF27,0) -> -0.59322399 | CR27: =IFERROR(($BU27-$CG27)/$CG27,0) -> 0.72002019 | CS27: =BU27-CG27 -> 1.9925383 | CT27: =(BY27/CK27)-1 -> -0.045291732 | CU27: =IF(OR($CQ27<'Summary '!$I$47,$BT27<'Summary '!$I$46),1,0) -> 1 | CV27: =IF(OR($CS27>='Summary '!$I$50, (AND(BU27>'Summary '!$I$52, Calcs!CR27> 'Summary '!$I$51))),1,0) -> 1 | CW27: =IF(OR(SUM(CU27:CV27)>=1,CX27="Yes"),1,0) -> 1 | CX27: No | CY27: No | CZ27: No | DD27: 0 | DE27: 0 | DI27: =IF(L27<90%,"Not Eligible","Eligible") -> Eligible | DJ27: =IF(OR(BF27="USD",BF27="CAD",BF27="EUR",BF27="GBP",BF27="AUD"),"Eligible","Not Eligible") -> Eligible | DK27: Eligible | DL27: Eligible | DM27: =IF(BM27="FALSE",IF(BY27<5,"Not Eligible","Eligible"),"Eligible") -> Eligible | DN27: =IF(AW27=TRUE,IF(AU27>=3%,"Eligible","Not Eligible"),"Not PIK") -> Not PIK | DO27: No | DP27: =IF(OR(DK27="Not Eligible",DL27="Not Eligible",DI27="Not Eligible",DJ27="Not Eligible",DM27="Not Eligible",DN27="Not Eligible",DO27="Yes"),"NO","YES") -> YES
A28: Carisk Buyer, Inc. | B28: =IFERROR(VLOOKUP(A28,'Loan List '!$A$6:$BZ$75,2,FALSE),NA) -> 0 | C28: =VLOOKUP(A28,'Loan List '!$A$6:$G$75, 7, FALSE) -> First Lien | D28: =VLOOKUP(A28, 'Loan List '!$A$6:$K$82, 11, FALSE) -> FL | E28: =IF(DP28= "YES", TRUE, FALSE) -> TRUE | F28: =VLOOKUP(A28,'Loan List '!$A$6:$L$75, 12, FALSE) -> Health Care Providers & Services | H28: =+I28 -> 1113939.4 | I28: =VLOOKUP(A28,'Loan List '!$A$6:$L$75, 8, FALSE) -> 1113939.4 | J28: 0 | K28: =I28/$I$15 -> 0.0030833986 | L28: =VLOOKUP(A28,'Loan List '!$A$6:$BA$82,24, FALSE) -> 100 | N28: =VLOOKUP(A28,'Loan List '!$A$6:$BA$82,22, FALSE) -> 47452 | O28: =IFERROR(MAX(0,I28-J28)*L28,"")/100 -> 1113939.4 | P28: =MIN(IF(AND(L28>=97%,Q28="Primary"),100%,L28),T28) -> 1 | Q28: Primary | R28: SETTLED | S28: =IF(OR(CU28=1,CV28=1,CW28=1),TRUE,FALSE) -> TRUE | T28: =VLOOKUP(A28,'Loan List '!$A$6:$BD$1048576,56,FALSE)/100 -> 1 | U28: =IF(E28=TRUE,P28*I28,0) -> 1113939.4 | V28: =VLOOKUP(A28,'Loan List '!$A$6:$BA$82,26, FALSE) -> 0 | W28: =V28*I28 -> 0 | Y28: =VLOOKUP(A28,'Loan List '!$A$6:$BA$75,27, FALSE) -> 0 | AB28: =K28*BU28 -> 0.0095116129 | AC28: =K28*AL28 -> 0.0020042091 | AD28: =BW28 -> 0 | AE28: =IF(CK28>=$C$5,"Class 1",IF(CK28>=$D$5,"Class 2",IF(CK28>=$E$5,"Class 3","Class 4"))) -> Class 3 | AF28: =HLOOKUP($AE28,$B$3:$F$10,4,0) -> 5 | AG28: =IF(BB28,1,0)+HLOOKUP($AE28,$B$3:$F$10,5,0) -> 6 | AH28: =MIN(AF28/BU28,1) -> 1 | AI28: =IF(BU28>AG28,(AG28-AF28)/BU28,1-AH28) -> 0 | AJ28: =HLOOKUP($AE28,$B$3:$F$10,6,0) -> 0.65 | AK28: =HLOOKUP($AE28,$B$3:$F$10,8,0) -> 0.35 | AL28: =IF(OR(BI28, AND(BH28,AD28>1)), HLOOKUP(AE28,$B$3:$F$10,8,0),AH28*AJ28+AI28*AK28) -> 0.65 | AM28: ='Diversity Score'!$E$7 -> 1 | AN28: =AM28*AL28 -> 0.65 | AO28: =VLOOKUP(A28,'Loan List '!$A$6:$BA$75,17, FALSE) -> 0.0525 | AP28: =VLOOKUP(A28,'Loan List '!$A$6:$BA$795,15, FALSE) -> SOFR | AQ28: =VLOOKUP(A28,'Loan List '!$A$6:$BA$795,16, FALSE) -> 0.01 | AR28: 0 | AS28: 0 | AU28: =AO28-AS28 -> 0.0525 | AV28: =IF(AND(AS28>0%,AU28>4.5%),TRUE,FALSE) -> FALSE | AW28: =IF(AND(AS28>0%,AU28>=2.25%, AV28=FALSE),TRUE,FALSE) -> FALSE | AX28: =IF(AND(AS28>0%,AW28=FALSE, AV28=FALSE),TRUE, FALSE) -> FALSE | AZ28: =(OR(CC28<>"NR",CD28<>"NR")) -> FALSE | BA28: ='Loan List '!AS17 -> Maintenance Covenants | BB28: =IF(D28="FL",FALSE,TRUE) -> FALSE | BC28: =IF(BU28>5.5, TRUE, FALSE) -> FALSE | BD28: =IF(BF28="USD", TRUE,FALSE) -> TRUE | BE28: =IF(BG28="USA",TRUE,FALSE) -> TRUE | BF28: ='Loan List '!J17 -> USD | BG28: =VLOOKUP(A28,'Loan List '!$A$6:$BZ$75, 23, FALSE) -> USA | BH28: =IF(D28="FLLO", TRUE,FALSE) -> FALSE | BI28: =IF(C28="Second Lien",TRUE,FALSE) -> FALSE | BJ28: =IF('Loan List '!BP17=1, TRUE, FALSE) -> FALSE | BK28: =IF(AR28>0%,TRUE,FALSE) -> FALSE | BL28: =OR(LEFT(CC28,1)="C", LEFT(CD28,1)="C") -> FALSE | BM28: =IF('Loan List '!AT17="Yes", TRUE, FALSE) -> FALSE | BN28: =-($BN$15-N28)/365 -> 4.3534247 | BO28: ='Concentration Limitations'!H23 -> 1113939.4 | BP28: =IF(R28=$T$13,0,BO28*AL28) -> 724060.58 | BS28: ='Loan List '!AG17 -> 45777 | BT28: ='Loan List '!AO17 -> 2.2102077 | BU28: ='Loan List '!AI17 -> 3.0847821 | BW28: 0 | BX28: - | BY28: ='Loan List '!AJ17 -> 19.206771 | BZ28: ='Loan List '!AL17 -> 0 | CA28: 0 | CB28: 0 | CC28: NR | CD28: NR | CE28: - | CF28: ='Loan List '!AC17 -> 2.3900626 | CG28: ='Loan List '!AD17 -> 1.4414121 | CI28: 0 | CJ28: - | CK28: ='Loan List '!AB17 -> 10.781094 | CL28: ='Loan List '!AE17 -> 0 | CM28: 0 | CN28: 0 | CO28: NR | CP28: NR | CQ28: =IFERROR(($BT28-$CF28)/$CF28,0) -> -0.075251139 | CR28: =IFERROR(($BU28-$CG28)/$CG28,0) -> 1.1401112 | CS28: =BU28-CG28 -> 1.64337 | CT28: =(BY28/CK28)-1 -> 0.78152331 | CU28: =IF(OR($CQ28<'Summary '!$I$47,$BT28<'Summary '!$I$46),1,0) -> 0 | CV28: =IF(OR($CS28>='Summary '!$I$50, (AND(BU28>'Summary '!$I$52, Calcs!CR28> 'Summary '!$I$51))),1,0) -> 1 | CW28: =IF(OR(SUM(CU28:CV28)>=1,CX28="Yes"),1,0) -> 1 | CX28: No | CY28: No | CZ28: No | DD28: 0 | DE28: 0 | DI28: =IF(L28<90%,"Not Eligible","Eligible") -> Eligible | DJ28: =IF(OR(BF28="USD",BF28="CAD",BF28="EUR",BF28="GBP",BF28="AUD"),"Eligible","Not Eligible") -> Eligible | DK28: Eligible | DL28: Eligible | DM28: =IF(BM28="FALSE",IF(BY28<5,"Not Eligible","Eligible"),"Eligible") -> Eligible | DN28: =IF(AW28=TRUE,IF(AU28>=3%,"Eligible","Not Eligible"),"Not PIK") -> Not PIK | DO28: No | DP28: =IF(OR(DK28="Not Eligible",DL28="Not Eligible",DI28="Not Eligible",DJ28="Not Eligible",DM28="Not Eligible",DN28="Not Eligible",DO28="Yes"),"NO","YES") -> YES
A29: Cartessa | B29: =IFERROR(VLOOKUP(A29,'Loan List '!$A$6:$BZ$75,2,FALSE),NA) -> 0 | C29: =VLOOKUP(A29,'Loan List '!$A$6:$G$75, 7, FALSE) -> First Lien | D29: =VLOOKUP(A29, 'Loan List '!$A$6:$K$82, 11, FALSE) -> FL | E29: =IF(DP29= "YES", TRUE, FALSE) -> TRUE | F29: =VLOOKUP(A29,'Loan List '!$A$6:$L$75, 12, FALSE) -> Distributors | H29: =+I29 -> 5192492.3 | I29: =VLOOKUP(A29,'Loan List '!$A$6:$L$75, 8, FALSE) -> 5192492.3 | J29: 0 | K29: =I29/$I$15 -> 0.014372886 | L29: =VLOOKUP(A29,'Loan List '!$A$6:$BA$82,24, FALSE) -> 100 | N29: =VLOOKUP(A29,'Loan List '!$A$6:$BA$82,22, FALSE) -> 46918 | O29: =IFERROR(MAX(0,I29-J29)*L29,"")/100 -> 5192492.3 | P29: =MIN(IF(AND(L29>=97%,Q29="Primary"),100%,L29),T29) -> 1 | Q29: Primary | R29: SETTLED | S29: =IF(OR(CU29=1,CV29=1,CW29=1),TRUE,FALSE) -> TRUE | T29: =VLOOKUP(A29,'Loan List '!$A$6:$BD$1048576,56,FALSE)/100 -> 1 | U29: =IF(E29=TRUE,P29*I29,0) -> 5192492.3 | V29: =VLOOKUP(A29,'Loan List '!$A$6:$BA$82,26, FALSE) -> 0 | W29: =V29*I29 -> 0 | Y29: =VLOOKUP(A29,'Loan List '!$A$6:$BA$75,27, FALSE) -> 0 | AB29: =K29*BU29 -> 0.054641137 | AC29: =K29*AL29 -> 0.0093423759 | AD29: =BW29 -> 0 | AE29: =IF(CK29>=$C$5,"Class 1",IF(CK29>=$D$5,"Class 2",IF(CK29>=$E$5,"Class 3","Class 4"))) -> Class 3 | AF29: =HLOOKUP($AE29,$B$3:$F$10,4,0) -> 5 | AG29: =IF(BB29,1,0)+HLOOKUP($AE29,$B$3:$F$10,5,0) -> 6 | AH29: =MIN(AF29/BU29,1) -> 1 | AI29: =IF(BU29>AG29,(AG29-AF29)/BU29,1-AH29) -> 0 | AJ29: =HLOOKUP($AE29,$B$3:$F$10,6,0) -> 0.65 | AK29: =HLOOKUP($AE29,$B$3:$F$10,8,0) -> 0.35 | AL29: =IF(OR(BI29, AND(BH29,AD29>1)), HLOOKUP(AE29,$B$3:$F$10,8,0),AH29*AJ29+AI29*AK29) -> 0.65 | AM29: ='Diversity Score'!$E$7 -> 1 | AN29: =AM29*AL29 -> 0.65 | AO29: =VLOOKUP(A29,'Loan List '!$A$6:$BA$75,17, FALSE) -> 0.0575 | AP29: =VLOOKUP(A29,'Loan List '!$A$6:$BA$795,15, FALSE) -> SOFR | AQ29: =VLOOKUP(A29,'Loan List '!$A$6:$BA$795,16, FALSE) -> 0.01 | AR29: 0 | AS29: 0 | AU29: =AO29-AS29 -> 0.0575 | AV29: =IF(AND(AS29>0%,AU29>4.5%),TRUE,FALSE) -> FALSE | AW29: =IF(AND(AS29>0%,AU29>=2.25%, AV29=FALSE),TRUE,FALSE) -> FALSE | AX29: =IF(AND(AS29>0%,AW29=FALSE, AV29=FALSE),TRUE, FALSE) -> FALSE | AZ29: =(OR(CC29<>"NR",CD29<>"NR")) -> FALSE | BA29: ='Loan List '!AS18 -> Maintenance Covenants | BB29: =IF(D29="FL",FALSE,TRUE) -> FALSE | BC29: =IF(BU29>5.5, TRUE, FALSE) -> FALSE | BD29: =IF(BF29="USD", TRUE,FALSE) -> TRUE | BE29: =IF(BG29="USA",TRUE,FALSE) -> TRUE | BF29: ='Loan List '!J18 -> USD | BG29: =VLOOKUP(A29,'Loan List '!$A$6:$BZ$75, 23, FALSE) -> USA | BH29: =IF(D29="FLLO", TRUE,FALSE) -> FALSE | BI29: =IF(C29="Second Lien",TRUE,FALSE) -> FALSE | BJ29: =IF('Loan List '!BP18=1, TRUE, FALSE) -> FALSE | BK29: =IF(AR29>0%,TRUE,FALSE) -> FALSE | BL29: =OR(LEFT(CC29,1)="C", LEFT(CD29,1)="C") -> FALSE | BM29: =IF('Loan List '!AT18="Yes", TRUE, FALSE) -> FALSE | BN29: =-($BN$15-N29)/365 -> 2.890411 | BO29: ='Concentration Limitations'!H24 -> 5192492.3 | BP29: =IF(R29=$T$13,0,BO29*AL29) -> 3375120 | BS29: ='Loan List '!AG18 -> 45777 | BT29: ='Loan List '!AO18 -> 1.9667672 | BU29: ='Loan List '!AI18 -> 3.8016817 | BW29: 0 | BX29: - | BY29: ='Loan List '!AJ18 -> 17.179532 | BZ29: ='Loan List '!AL18 -> 0 | CA29: 0 | CB29: 0 | CC29: NR | CD29: NR | CE29: - | CF29: ='Loan List '!AC18 -> 3.95 | CG29: ='Loan List '!AD18 -> 2.86 | CI29: 0 | CJ29: - | CK29: ='Loan List '!AB18 -> 24.97 | CL29: ='Loan List '!AE18 -> 0 | CM29: 0 | CN29: 0 | CO29: NR | CP29: NR | CQ29: =IFERROR(($BT29-$CF29)/$CF29,0) -> -0.50208425 | CR29: =IFERROR(($BU29-$CG29)/$CG29,0) -> 0.32925932 | CS29: =BU29-CG29 -> 0.94168165 | CT29: =(BY29/CK29)-1 -> -0.3119931 | CU29: =IF(OR($CQ29<'Summary '!$I$47,$BT29<'Summary '!$I$46),1,0) -> 1 | CV29: =IF(OR($CS29>='Summary '!$I$50, (AND(BU29>'Summary '!$I$52, Calcs!CR29> 'Summary '!$I$51))),1,0) -> 0 | CW29: =IF(OR(SUM(CU29:CV29)>=1,CX29="Yes"),1,0) -> 1 | CX29: No | CY29: No | CZ29: No | DD29: 0 | DE29: 0 | DI29: =IF(L29<90%,"Not Eligible","Eligible") -> Eligible | DJ29: =IF(OR(BF29="USD",BF29="CAD",BF29="EUR",BF29="GBP",BF29="AUD"),"Eligible","Not Eligible") -> Eligible | DK29: Eligible | DL29: Eligible | DM29: =IF(BM29="FALSE",IF(BY29<5,"Not Eligible","Eligible"),"Eligible") -> Eligible | DN29: =IF(AW29=TRUE,IF(AU29>=3%,"Eligible","Not Eligible"),"Not PIK") -> Not PIK | DO29: No | DP29: =IF(OR(DK29="Not Eligible",DL29="Not Eligible",DI29="Not Eligible",DJ29="Not Eligible",DM29="Not Eligible",DN29="Not Eligible",DO29="Yes"),"NO","YES") -> YES
... A43: Inventus Power Inc. | B43: =IFERROR(VLOOKUP(A43,'Loan List '!$A$6:$BZ$75,2,FALSE),NA) -> 0 | C43: =VLOOKUP(A43,'Loan List '!$A$6:$G$75, 7, FALSE) -> First Lien | D43: =VLOOKUP(A43, 'Loan List '!$A$6:$K$82, 11, FALSE) -> FL | E43: =IF(DP43= "YES", TRUE, FALSE) -> TRUE | F43: =VLOOKUP(A43,'Loan List '!$A$6:$L$75, 12, FALSE) -> Electronic Equipment, Instruments & Components | H43: =+I43 -> 1970457.8 | I43: =VLOOKUP(A43,'Loan List '!$A$6:$L$75, 8, FALSE) -> 1970457.8 | J43: 0 | K43: =I43/$I$15 -> 0.0054542527 | L43: =VLOOKUP(A43,'Loan List '!$A$6:$BA$82,24, FALSE) -> 100 | N43: =VLOOKUP(A43,'Loan List '!$A$6:$BA$82,22, FALSE) -> 45838 | O43: =IFERROR(MAX(0,I43-J43)*L43,"")/100 -> 1970457.8 | P43: =MIN(IF(AND(L43>=97%,Q43="Primary"),100%,L43),T43) -> 1 | Q43: Primary | R43: SETTLED | S43: =IF(OR(CU43=1,CV43=1,CW43=1),TRUE,FALSE) -> TRUE | T43: =VLOOKUP(A43,'Loan List '!$A$6:$BD$1048576,56,FALSE)/100 -> 1 | U43: =IF(E43=TRUE,P43*I43,0) -> 1970457.8 | V43: =VLOOKUP(A43,'Loan List '!$A$6:$BA$82,26, FALSE) -> 0 | W43: =V43*I43 -> 0 | Y43: =VLOOKUP(A43,'Loan List '!$A$6:$BA$75,27, FALSE) -> 0 | AB43: =K43*BU43 -> 0.02536833 | AC43: =K43*AL43 -> 0.0036816206 | AD43: =BW43 -> 0 | AE43: =IF(CK43>=$C$5,"Class 1",IF(CK43>=$D$5,"Class 2",IF(CK43>=$E$5,"Class 3","Class 4"))) -> Class 2 | AF43: =HLOOKUP($AE43,$B$3:$F$10,4,0) -> 5.5 | AG43: =IF(BB43,1,0)+HLOOKUP($AE43,$B$3:$F$10,5,0) -> 6.5 | AH43: =MIN(AF43/BU43,1) -> 1 | AI43: =IF(BU43>AG43,(AG43-AF43)/BU43,1-AH43) -> 0 | AJ43: =HLOOKUP($AE43,$B$3:$F$10,6,0) -> 0.675 | AK43: =HLOOKUP($AE43,$B$3:$F$10,8,0) -> 0.35 | AL43: =IF(OR(BI43, AND(BH43,AD43>1)), HLOOKUP(AE43,$B$3:$F$10,8,0),AH43*AJ43+AI43*AK43) -> 0.675 | AM43: ='Diversity Score'!$E$7 -> 1 | AN43: =AM43*AL43 -> 0.675 | AO43: =VLOOKUP(A43,'Loan List '!$A$6:$BA$75,17, FALSE) -> 0.0761 | AP43: =VLOOKUP(A43,'Loan List '!$A$6:$BA$795,15, FALSE) -> SOFR | AQ43: =VLOOKUP(A43,'Loan List '!$A$6:$BA$795,16, FALSE) -> 0.01 | AR43: 0 | AS43: 0 | AU43: =AO43-AS43 -> 0.0761 | AV43: =IF(AND(AS43>0%,AU43>4.5%),TRUE,FALSE) -> FALSE | AW43: =IF(AND(AS43>0%,AU43>=2.25%, AV43=FALSE),TRUE,FALSE) -> FALSE | AX43: =IF(AND(AS43>0%,AW43=FALSE, AV43=FALSE),TRUE, FALSE) -> FALSE | AZ43: =(OR(CC43<>"NR",CD43<>"NR")) -> FALSE | BA43: ='Loan List '!AS32 -> Maintenance Covenants | BB43: =IF(D43="FL",FALSE,TRUE) -> FALSE | BC43: =IF(BU43>5.5, TRUE, FALSE) -> FALSE | BD43: =IF(BF43="USD", TRUE,FALSE) -> TRUE | BE43: =IF(BG43="USA",TRUE,FALSE) -> TRUE | BF43: ='Loan List '!J32 -> USD | BG43: =VLOOKUP(A43,'Loan List '!$A$6:$BZ$75, 23, FALSE) -> USA | BH43: =IF(D43="FLLO", TRUE,FALSE) -> FALSE | BI43: =IF(C43="Second Lien",TRUE,FALSE) -> FALSE | BJ43: =IF('Loan List '!BP32=1, TRUE, FALSE) -> FALSE | BK43: =IF(AR43>0%,TRUE,FALSE) -> FALSE | BL43: =OR(LEFT(CC43,1)="C", LEFT(CD43,1)="C") -> FALSE | BM43: =IF('Loan List '!AT32="Yes", TRUE, FALSE) -> FALSE | BN43: =-($BN$15-N43)/365 -> -0.068493151 | BO43: ='Concentration Limitations'!H38 -> 1970457.8 | BP43: =IF(R43=$T$13,0,BO43*AL43) -> 1330059 | BS43: ='Loan List '!AG32 -> 45808 | BT43: ='Loan List '!AO32 -> 1.6064132 | BU43: ='Loan List '!AI32 -> 4.65111 | BW43: 0 | BX43: - | BY43: ='Loan List '!AJ32 -> 56.059 | BZ43: ='Loan List '!AL32 -> 0 | CA43: 0 | CB43: 0 | CC43: NR | CD43: NR | CE43: - | CF43: ='Loan List '!AC32 -> 1.6109886 | CG43: ='Loan List '!AD32 -> 5.0177508 | CI43: 0 | CJ43: - | CK43: ='Loan List '!AB32 -> 50.403 | CL43: ='Loan List '!AE32 -> 0 | CM43: 0 | CN43: 0 | CO43: NR | CP43: NR | CQ43: =IFERROR(($BT43-$CF43)/$CF43,0) -> -0.0028401385 | CR43: =IFERROR(($BU43-$CG43)/$CG43,0) -> -0.073068747 | CS43: =BU43-CG43 -> -0.36664076 | CT43: =(BY43/CK43)-1 -> 0.11221554 | CU43: =IF(OR($CQ43<'Summary '!$I$47,$BT43<'Summary '!$I$46),1,0) -> 1 | CV43: =IF(OR($CS43>='Summary '!$I$50, (AND(BU43>'Summary '!$I$52, Calcs!CR43> 'Summary '!$I$51))),1,0) -> 0 | CW43: =IF(OR(SUM(CU43:CV43)>=1,CX43="Yes"),1,0) -> 1 | CX43: No | CY43: No | CZ43: No | DD43: 0 | DE43: 0 | DI43: =IF(L43<90%,"Not Eligible","Eligible") -> Eligible | DJ43: =IF(OR(BF43="USD",BF43="CAD",BF43="EUR",BF43="GBP",BF43="AUD"),"Eligible","Not Eligible") -> Eligible | DK43: Eligible | DL43: Eligible | DM43: =IF(BM43="FALSE",IF(BY43<5,"Not Eligible","Eligible"),"Eligible") -> Eligible | DN43: =IF(AW43=TRUE,IF(AU43>=3%,"Eligible","Not Eligible"),"Not PIK") -> Not PIK | DO43: No | DP43: =IF(OR(DK43="Not Eligible",DL43="Not Eligible",DI43="Not Eligible",DJ43="Not Eligible",DM43="Not Eligible",DN43="Not Eligible",DO43="Yes"),"NO","YES") -> YES
A44: Lash OpCo, LLC | B44: =IFERROR(VLOOKUP(A44,'Loan List '!$A$6:$BZ$75,2,FALSE),NA) -> 0 | C44: =VLOOKUP(A44,'Loan List '!$A$6:$G$75, 7, FALSE) -> First Lien | D44: =VLOOKUP(A44, 'Loan List '!$A$6:$K$82, 11, FALSE) -> FL | E44: =IF(DP44= "YES", TRUE, FALSE) -> TRUE | F44: =VLOOKUP(A44,'Loan List '!$A$6:$L$75, 12, FALSE) -> Personal Products | H44: =+I44 -> 3369991.8 | I44: =VLOOKUP(A44,'Loan List '!$A$6:$L$75, 8, FALSE) -> 3369991.8 | J44: 0 | K44: =I44/$I$15 -> 0.0093281809 | L44: =VLOOKUP(A44,'Loan List '!$A$6:$BA$82,24, FALSE) -> 100 | N44: =VLOOKUP(A44,'Loan List '!$A$6:$BA$82,22, FALSE) -> 46436 | O44: =IFERROR(MAX(0,I44-J44)*L44,"")/100 -> 3369991.8 | P44: =MIN(IF(AND(L44>=97%,Q44="Primary"),100%,L44),T44) -> 0.5 | Q44: Primary | R44: SETTLED | S44: =IF(OR(CU44=1,CV44=1,CW44=1),TRUE,FALSE) -> TRUE | T44: =VLOOKUP(A44,'Loan List '!$A$6:$BD$1048576,56,FALSE)/100 -> 0.5 | U44: =IF(E44=TRUE,P44*I44,0) -> 1684995.9 | V44: =VLOOKUP(A44,'Loan List '!$A$6:$BA$82,26, FALSE) -> 0 | W44: =V44*I44 -> 0 | Y44: =VLOOKUP(A44,'Loan List '!$A$6:$BA$75,27, FALSE) -> 0 | AB44: =K44*BU44 -> 0.072625063 | AC44: =K44*AL44 -> 0.0048674418 | AD44: =BW44 -> 0 | AE44: =IF(CK44>=$C$5,"Class 1",IF(CK44>=$D$5,"Class 2",IF(CK44>=$E$5,"Class 3","Class 4"))) -> Class 2 | AF44: =HLOOKUP($AE44,$B$3:$F$10,4,0) -> 5.5 | AG44: =IF(BB44,1,0)+HLOOKUP($AE44,$B$3:$F$10,5,0) -> 6.5 | AH44: =MIN(AF44/BU44,1) -> 0.70643649 | AI44: =IF(BU44>AG44,(AG44-AF44)/BU44,1-AH44) -> 0.128443 | AJ44: =HLOOKUP($AE44,$B$3:$F$10,6,0) -> 0.675 | AK44: =HLOOKUP($AE44,$B$3:$F$10,8,0) -> 0.35 | AL44: =IF(OR(BI44, AND(BH44,AD44>1)), HLOOKUP(AE44,$B$3:$F$10,8,0),AH44*AJ44+AI44*AK44) -> 0.52179968 | AM44: ='Diversity Score'!$E$7 -> 1 | AN44: =AM44*AL44 -> 0.52179968 | AO44: 0.071 | AP44: =VLOOKUP(A44,'Loan List '!$A$6:$BA$795,15, FALSE) -> SOFR | AQ44: =VLOOKUP(A44,'Loan List '!$A$6:$BA$795,16, FALSE) -> 0.01 | AR44: 0 | AS44: 0.051 | AU44: =AO44-AS44 -> 0.02 | AV44: =IF(AND(AS44>0%,AU44>4.5%),TRUE,FALSE) -> FALSE | AW44: =IF(AND(AS44>0%,AU44>=2.25%, AV44=FALSE),TRUE,FALSE) -> FALSE | AX44: =IF(AND(AS44>0%,AW44=FALSE, AV44=FALSE),TRUE, FALSE) -> TRUE | AZ44: =(OR(CC44<>"NR",CD44<>"NR")) -> FALSE | BA44: ='Loan List '!AS33 -> Maintenance Covenants | BB44: =IF(D44="FL",FALSE,TRUE) -> FALSE | BC44: =IF(BU44>5.5, TRUE, FALSE) -> TRUE | BD44: =IF(BF44="USD", TRUE,FALSE) -> TRUE | BE44: =IF(BG44="USA",TRUE,FALSE) -> TRUE | BF44: ='Loan List '!J33 -> USD | BG44: =VLOOKUP(A44,'Loan List '!$A$6:$BZ$75, 23, FALSE) -> USA | BH44: =IF(D44="FLLO", TRUE,FALSE) -> FALSE | BI44: =IF(C44="Second Lien",TRUE,FALSE) -> FALSE | BJ44: =IF('Loan List '!BP33=1, TRUE, FALSE) -> FALSE | BK44: =IF(AR44>0%,TRUE,FALSE) -> FALSE | BL44: =OR(LEFT(CC44,1)="C", LEFT(CD44,1)="C") -> FALSE | BM44: =IF('Loan List '!AT33="Yes", TRUE, FALSE) -> FALSE | BN44: =-($BN$15-N44)/365 -> 1.569863 | BO44: ='Concentration Limitations'!H39 -> 1684995.9 | BP44: =IF(R44=$T$13,0,BO44*AL44) -> 879230.32 | BS44: ='Loan List '!AG33 -> 45808 | BT44: ='Loan List '!AO33 -> 0.97264014 | BU44: ='Loan List '!AI33 -> 7.7855548 | BW44: 0 | BX44: - | BY44: ='Loan List '!AJ33 -> 63.074203 | BZ44: ='Loan List '!AL33 -> 0 | CA44: 0 | CB44: 0 | CC44: NR | CD44: NR | CE44: - | CF44: ='Loan List '!AC33 -> 2.2122978 | CG44: ='Loan List '!AD33 -> 5.5235911 | CI44: 0 | CJ44: - | CK44: ='Loan List '!AB33 -> 57.462617 | CL44: ='Loan List '!AE33 -> 0 | CM44: 0 | CN44: 0 | CO44: NR | CP44: NR | CQ44: =IFERROR(($BT44-$CF44)/$CF44,0) -> -0.56034845 | CR44: =IFERROR(($BU44-$CG44)/$CG44,0) -> 0.40950961 | CS44: =BU44-CG44 -> 2.2619637 | CT44: =(BY44/CK44)-1 -> 0.097656296 | CU44: =IF(OR($CQ44<'Summary '!$I$47,$BT44<'Summary '!$I$46),1,0) -> 1 | CV44: =IF(OR($CS44>='Summary '!$I$50, (AND(BU44>'Summary '!$I$52, Calcs!CR44> 'Summary '!$I$51))),1,0) -> 1 | CW44: =IF(OR(SUM(CU44:CV44)>=1,CX44="Yes"),1,0) -> 1 | CX44: No | CY44: No | CZ44: Yes | DA44: 0.051 | DD44: 0 | DE44: 0 | DI44: =IF(L44<90%,"Not Eligible","Eligible") -> Eligible | DJ44: =IF(OR(BF44="USD",BF44="CAD",BF44="EUR",BF44="GBP",BF44="AUD"),"Eligible","Not Eligible") -> Eligible | DK44: Eligible | DL44: Eligible | DM44: =IF(BM44="FALSE",IF(BY44<5,"Not Eligible","Eligible"),"Eligible") -> Eligible | DN44: =IF(AW44=TRUE,IF(AU44>=3%,"Eligible","Not Eligible"),"Not PIK") -> Not PIK | DO44: No | DP44: =IF(OR(DK44="Not Eligible",DL44="Not Eligible",DI44="Not Eligible",DJ44="Not Eligible",DM44="Not Eligible",DN44="Not Eligible",DO44="Yes"),"NO","YES") -> YES
A45: MDI Buyer Inc. | B45: =IFERROR(VLOOKUP(A45,'Loan List '!$A$6:$BZ$75,2,FALSE),NA) -> 0 | C45: =VLOOKUP(A45,'Loan List '!$A$6:$G$75, 7, FALSE) -> First Lien | D45: =VLOOKUP(A45, 'Loan List '!$A$6:$K$82, 11, FALSE) -> FL | E45: =IF(DP45= "YES", TRUE, FALSE) -> TRUE | F45: =VLOOKUP(A45,'Loan List '!$A$6:$L$75, 12, FALSE) -> Chemicals | H45: =+I45 -> 4779960.4 | I45: =VLOOKUP(A45,'Loan List '!$A$6:$L$75, 8, FALSE) -> 4779960.4 | J45: 0 | K45: =I45/$I$15 -> 0.013230992 | L45: =VLOOKUP(A45,'Loan List '!$A$6:$BA$82,24, FALSE) -> 100 | N45: =VLOOKUP(A45,'Loan List '!$A$6:$BA$82,22, FALSE) -> 46959 | O45: =IFERROR(MAX(0,I45-J45)*L45,"")/100 -> 4779960.4 | P45: =MIN(IF(AND(L45>=97%,Q45="Primary"),100%,L45),T45) -> 1 | Q45: Primary | R45: SETTLED | S45: =IF(OR(CU45=1,CV45=1,CW45=1),TRUE,FALSE) -> FALSE | T45: =VLOOKUP(A45,'Loan List '!$A$6:$BD$1048576,56,FALSE)/100 -> 1 | U45: =IF(E45=TRUE,P45*I45,0) -> 4779960.4 | V45: =VLOOKUP(A45,'Loan List '!$A$6:$BA$82,26, FALSE) -> 0 | W45: =V45*I45 -> 0 | Y45: =VLOOKUP(A45,'Loan List '!$A$6:$BA$75,27, FALSE) -> 0 | AB45: =K45*BU45 -> 0.065075038 | AC45: =K45*AL45 -> 0.0089309199 | AD45: =BW45 -> 0 | AE45: =IF(CK45>=$C$5,"Class 1",IF(CK45>=$D$5,"Class 2",IF(CK45>=$E$5,"Class 3","Class 4"))) -> Class 2 | AF45: =HLOOKUP($AE45,$B$3:$F$10,4,0) -> 5.5 | AG45: =IF(BB45,1,0)+HLOOKUP($AE45,$B$3:$F$10,5,0) -> 6.5 | AH45: =MIN(AF45/BU45,1) -> 1 | AI45: =IF(BU45>AG45,(AG45-AF45)/BU45,1-AH45) -> 0 | AJ45: =HLOOKUP($AE45,$B$3:$F$10,6,0) -> 0.675 | AK45: =HLOOKUP($AE45,$B$3:$F$10,8,0) -> 0.35 | AL45: =IF(OR(BI45, AND(BH45,AD45>1)), HLOOKUP(AE45,$B$3:$F$10,8,0),AH45*AJ45+AI45*AK45) -> 0.675 | AM45: ='Diversity Score'!$E$7 -> 1 | AN45: =AM45*AL45 -> 0.675 | AO45: =VLOOKUP(A45,'Loan List '!$A$6:$BA$75,17, FALSE) -> 0.05 | AP45: =VLOOKUP(A45,'Loan List '!$A$6:$BA$795,15, FALSE) -> SOFR | AQ45: =VLOOKUP(A45,'Loan List '!$A$6:$BA$795,16, FALSE) -> 0.01 | AR45: 0 | AS45: 0 | AU45: =AO45-AS45 -> 0.05 | AV45: =IF(AND(AS45>0%,AU45>4.5%),TRUE,FALSE) -> FALSE | AW45: =IF(AND(AS45>0%,AU45>=2.25%, AV45=FALSE),TRUE,FALSE) -> FALSE | AX45: =IF(AND(AS45>0%,AW45=FALSE, AV45=FALSE),TRUE, FALSE) -> FALSE | AZ45: =(OR(CC45<>"NR",CD45<>"NR")) -> FALSE | BA45: ='Loan List '!AS34 -> Maintenance Covenants | BB45: =IF(D45="FL",FALSE,TRUE) -> FALSE | BC45: =IF(BU45>5.5, TRUE, FALSE) -> FALSE | BD45: =IF(BF45="USD", TRUE,FALSE) -> TRUE | BE45: =IF(BG45="USA",TRUE,FALSE) -> TRUE | BF45: ='Loan List '!J34 -> USD | BG45: =VLOOKUP(A45,'Loan List '!$A$6:$BZ$75, 23, FALSE) -> USA | BH45: =IF(D45="FLLO", TRUE,FALSE) -> FALSE | BI45: =IF(C45="Second Lien",TRUE,FALSE) -> FALSE | BJ45: =IF('Loan List '!BP34=1, TRUE, FALSE) -> FALSE | BK45: =IF(AR45>0%,TRUE,FALSE) -> FALSE | BL45: =OR(LEFT(CC45,1)="C", LEFT(CD45,1)="C") -> FALSE | BM45: =IF('Loan List '!AT34="Yes", TRUE, FALSE) -> FALSE | BN45: =-($BN$15-N45)/365 -> 3.0027397 | BO45: ='Concentration Limitations'!H40 -> 4779960.4 | BP45: =IF(R45=$T$13,0,BO45*AL45) -> 3226473.3 | BS45: ='Loan List '!AG34 -> 45808 | BT45: ='Loan List '!AO34 -> 2.33 | BU45: ='Loan List '!AI34 -> 4.9183792 | BW45: 0 | BX45: - | BY45: ='Loan List '!AJ34 -> 36.502036 | BZ45: ='Loan List '!AL34 -> 0 | CA45: 0 | CB45: 0 | CC45: NR | CD45: NR | CE45: - | CF45: ='Loan List '!AC34 -> 2.33 | CG45: ='Loan List '!AD34 -> 5.2262471 | CI45: 0 | CJ45: - | CK45: ='Loan List '!AB34 -> 28.897804 | CL45: ='Loan List '!AE34 -> 0 | CM45: 0 | CN45: 0 | CO45: NR | CP45: NR | CQ45: =IFERROR(($BT45-$CF45)/$CF45,0) -> 0 | CR45: =IFERROR(($BU45-$CG45)/$CG45,0) -> -0.058908029 | CS45: =BU45-CG45 -> -0.30786791 | CT45: =(BY45/CK45)-1 -> 0.26314222 | CU45: =IF(OR($CQ45<'Summary '!$I$47,$BT45<'Summary '!$I$46),1,0) -> 0 | CV45: =IF(OR($CS45>='Summary '!$I$50, (AND(BU45>'Summary '!$I$52, Calcs!CR45> 'Summary '!$I$51))),1,0) -> 0 | CW45: =IF(OR(SUM(CU45:CV45)>=1,CX45="Yes"),1,0) -> 0 | CX45: No | CY45: No | CZ45: No | DD45: 0 | DE45: 0 | DI45: =IF(L45<90%,"Not Eligible","Eligible") -> Eligible | DJ45: =IF(OR(BF45="USD",BF45="CAD",BF45="EUR",BF45="GBP",BF45="AUD"),"Eligible","Not Eligible") -> Eligible | DK45: Eligible | DL45: Eligible | DM45: =IF(BM45="FALSE",IF(BY45<5,"Not Eligible","Eligible"),"Eligible") -> Eligible | DN45: =IF(AW45=TRUE,IF(AU45>=3%,"Eligible","Not Eligible"),"Not PIK") -> Not PIK | DO45: No | DP45: =IF(OR(DK45="Not Eligible",DL45="Not Eligible",DI45="Not Eligible",DJ45="Not Eligible",DM45="Not Eligible",DN45="Not Eligible",DO45="Yes"),"NO","YES") -> YES
A46: Megawatt Acquisitionco, Inc. | B46: =IFERROR(VLOOKUP(A46,'Loan List '!$A$6:$BZ$75,2,FALSE),NA) -> 0 | C46: =VLOOKUP(A46,'Loan List '!$A$6:$G$75, 7, FALSE) -> First Lien | D46: =VLOOKUP(A46, 'Loan List '!$A$6:$K$82, 11, FALSE) -> FL | E46: =IF(DP46= "YES", TRUE, FALSE) -> TRUE | F46: =VLOOKUP(A46,'Loan List '!$A$6:$L$75, 12, FALSE) -> Electronic Equipment, Instruments & Components | H46: =+I46 -> 4930075.2 | I46: =VLOOKUP(A46,'Loan List '!$A$6:$L$75, 8, FALSE) -> 4930075.2 | J46: 0 | K46: =I46/$I$15 -> 0.013646512 | L46: =VLOOKUP(A46,'Loan List '!$A$6:$BA$82,24, FALSE) -> 100 | N46: =VLOOKUP(A46,'Loan List '!$A$6:$BA$82,22, FALSE) -> 47543 | O46: =IFERROR(MAX(0,I46-J46)*L46,"")/100 -> 4930075.2 | P46: =MIN(IF(AND(L46>=97%,Q46="Primary"),100%,L46),T46) -> 0.9 | Q46: Primary | R46: SETTLED | S46: =IF(OR(CU46=1,CV46=1,CW46=1),TRUE,FALSE) -> TRUE | T46: =VLOOKUP(A46,'Loan List '!$A$6:$BD$1048576,56,FALSE)/100 -> 0.9 | U46: =IF(E46=TRUE,P46*I46,0) -> 4437067.7 | V46: =VLOOKUP(A46,'Loan List '!$A$6:$BA$82,26, FALSE) -> 0 | W46: =V46*I46 -> 0 | Y46: =VLOOKUP(A46,'Loan List '!$A$6:$BA$75,27, FALSE) -> 0 | AB46: =K46*BU46 -> 0.091069141 | AC46: =K46*AL46 -> 0.0083074064 | AD46: =BW46 -> 0 | AE46: =IF(CK46>=$C$5,"Class 1",IF(CK46>=$D$5,"Class 2",IF(CK46>=$E$5,"Class 3","Class 4"))) -> Class 2 | AF46: =HLOOKUP($AE46,$B$3:$F$10,4,0) -> 5.5 | AG46: =IF(BB46,1,0)+HLOOKUP($AE46,$B$3:$F$10,5,0) -> 6.5 | AH46: =MIN(AF46/BU46,1) -> 0.824163 | AI46: =IF(BU46>AG46,(AG46-AF46)/BU46,1-AH46) -> 0.14984782 | AJ46: =HLOOKUP($AE46,$B$3:$F$10,6,0) -> 0.675 | AK46: =HLOOKUP($AE46,$B$3:$F$10,8,0) -> 0.35 | AL46: =IF(OR(BI46, AND(BH46,AD46>1)), HLOOKUP(AE46,$B$3:$F$10,8,0),AH46*AJ46+AI46*AK46) -> 0.60875676 | AM46: ='Diversity Score'!$E$7 -> 1 | AN46: =AM46*AL46 -> 0.60875676 | AO46: =VLOOKUP(A46,'Loan List '!$A$6:$BA$75,17, FALSE) -> 0.055 | AP46: =VLOOKUP(A46,'Loan List '!$A$6:$BA$795,15, FALSE) -> SOFR | AQ46: =VLOOKUP(A46,'Loan List '!$A$6:$BA$795,16, FALSE) -> 0.01 | AR46: 0 | AS46: 0 | AU46: =AO46-AS46 -> 0.055 | AV46: =IF(AND(AS46>0%,AU46>4.5%),TRUE,FALSE) -> FALSE | AW46: =IF(AND(AS46>0%,AU46>=2.25%, AV46=FALSE),TRUE,FALSE) -> FALSE | AX46: =IF(AND(AS46>0%,AW46=FALSE, AV46=FALSE),TRUE, FALSE) -> FALSE | AZ46: =(OR(CC46<>"NR",CD46<>"NR")) -> FALSE | BA46: ='Loan List '!AS35 -> Maintenance Covenants | BB46: =IF(D46="FL",FALSE,TRUE) -> FALSE | BC46: =IF(BU46>5.5, TRUE, FALSE) -> TRUE | BD46: =IF(BF46="USD", TRUE,FALSE) -> TRUE | BE46: =IF(BG46="USA",TRUE,FALSE) -> TRUE | BF46: ='Loan List '!J35 -> USD | BG46: =VLOOKUP(A46,'Loan List '!$A$6:$BZ$75, 23, FALSE) -> USA | BH46: =IF(D46="FLLO", TRUE,FALSE) -> FALSE | BI46: =IF(C46="Second Lien",TRUE,FALSE) -> FALSE | BJ46: =IF('Loan List '!BP35=1, TRUE, FALSE) -> FALSE | BK46: =IF(AR46>0%,TRUE,FALSE) -> FALSE | BL46: =OR(LEFT(CC46,1)="C", LEFT(CD46,1)="C") -> FALSE | BM46: =IF('Loan List '!AT35="Yes", TRUE, FALSE) -> FALSE | BN46: =-($BN$15-N46)/365 -> 4.6027397 | BO46: ='Concentration Limitations'!H41 -> 4437067.7 | BP46: =IF(R46=$T$13,0,BO46*AL46) -> 2701094.9 | BS46: ='Loan List '!AG35 -> 45808 | BT46: ='Loan List '!AO35 -> 1.3672243 | BU46: ='Loan List '!AI35 -> 6.6734372 | BW46: 0 | BX46: - | BY46: ='Loan List '!AJ35 -> 20.924 | BZ46: ='Loan List '!AL35 -> 0 | CA46: 0 | CB46: 0 | CC46: NR | CD46: NR | CE46: - | CF46: ='Loan List '!AC35 -> 1.8477273 | CG46: ='Loan List '!AD35 -> 4.895357 | CI46: 0 | CJ46: - | CK46: ='Loan List '!AB35 -> 28.455 | CL46: ='Loan List '!AE35 -> 0 | CM46: 0 | CN46: 0 | CO46: NR | CP46: NR | CQ46: =IFERROR(($BT46-$CF46)/$CF46,0) -> -0.26005083 | CR46: =IFERROR(($BU46-$CG46)/$CG46,0) -> 0.36321768 | CS46: =BU46-CG46 -> 1.7780802 | CT46: =(BY46/CK46)-1 -> -0.2646635 | CU46: =IF(OR($CQ46<'Summary '!$I$47,$BT46<'Summary '!$I$46),1,0) -> 1 | CV46: =IF(OR($CS46>='Summary '!$I$50, (AND(BU46>'Summary '!$I$52, Calcs!CR46> 'Summary '!$I$51))),1,0) -> 1 | CW46: =IF(OR(SUM(CU46:CV46)>=1,CX46="Yes"),1,0) -> 1 | CX46: No | CY46: No | CZ46: No | DD46: 0 | DE46: 0 | DI46: =IF(L46<90%,"Not Eligible","Eligible") -> Eligible | DJ46: =IF(OR(BF46="USD",BF46="CAD",BF46="EUR",BF46="GBP",BF46="AUD"),"Eligible","Not Eligible") -> Eligible | DK46: Eligible | DL46: Eligible | DM46: =IF(BM46="FALSE",IF(BY46<5,"Not Eligible","Eligible"),"Eligible") -> Eligible | DN46: =IF(AW46=TRUE,IF(AU46>=3%,"Eligible","Not Eligible"),"Not PIK") -> Not PIK | DO46: No | DP46: =IF(OR(DK46="Not Eligible",DL46="Not Eligible",DI46="Not Eligible",DJ46="Not Eligible",DM46="Not Eligible",DN46="Not Eligible",DO46="Yes"),"NO","YES") -> YES
A47: Michael Baker International, LLC | B47: =IFERROR(VLOOKUP(A47,'Loan List '!$A$6:$BZ$75,2,FALSE),NA) -> 0 | C47: =VLOOKUP(A47,'Loan List '!$A$6:$G$75, 7, FALSE) -> First Lien | D47: =VLOOKUP(A47, 'Loan List '!$A$6:$K$82, 11, FALSE) -> FL | E47: =IF(DP47= "YES", TRUE, FALSE) -> TRUE | F47: =VLOOKUP(A47,'Loan List '!$A$6:$L$75, 12, FALSE) -> Construction & Engineering | H47: =+I47 -> 496253.14 | I47: =VLOOKUP(A47,'Loan List '!$A$6:$L$75, 8, FALSE) -> 496253.14 | J47: 0 | K47: =I47/$I$15 -> 0.0013736351 | L47: =VLOOKUP(A47,'Loan List '!$A$6:$BA$82,24, FALSE) -> 100 | N47: =VLOOKUP(A47,'Loan List '!$A$6:$BA$82,22, FALSE) -> 47105 | O47: =IFERROR(MAX(0,I47-J47)*L47,"")/100 -> 496253.14 | P47: =MIN(IF(AND(L47>=97%,Q47="Primary"),100%,L47),T47) -> 1 | Q47: Primary | R47: SETTLED | S47: =IF(OR(CU47=1,CV47=1,CW47=1),TRUE,FALSE) -> FALSE | T47: =VLOOKUP(A47,'Loan List '!$A$6:$BD$1048576,56,FALSE)/100 -> 1 | U47: =IF(E47=TRUE,P47*I47,0) -> 496253.14 | V47: =VLOOKUP(A47,'Loan List '!$A$6:$BA$82,26, FALSE) -> 0 | W47: =V47*I47 -> 0 | Y47: =VLOOKUP(A47,'Loan List '!$A$6:$BA$75,27, FALSE) -> 0 | AB47: =K47*BU47 -> 0.0056468313 | AC47: =K47*AL47 -> 0.00096154458 | AD47: =BW47 -> 0 | AE47: =IF(CK47>=$C$5,"Class 1",IF(CK47>=$D$5,"Class 2",IF(CK47>=$E$5,"Class 3","Class 4"))) -> Class 1 | AF47: =HLOOKUP($AE47,$B$3:$F$10,4,0) -> 6 | AG47: =IF(BB47,1,0)+HLOOKUP($AE47,$B$3:$F$10,5,0) -> 7 | AH47: =MIN(AF47/BU47,1) -> 1 | AI47: =IF(BU47>AG47,(AG47-AF47)/BU47,1-AH47) -> 0 | AJ47: =HLOOKUP($AE47,$B$3:$F$10,6,0) -> 0.7 | AK47: =HLOOKUP($AE47,$B$3:$F$10,8,0) -> 0.4 | AL47: =IF(OR(BI47, AND(BH47,AD47>1)), HLOOKUP(AE47,$B$3:$F$10,8,0),AH47*AJ47+AI47*AK47) -> 0.7 | AM47: ='Diversity Score'!$E$7 -> 1 | AN47: =AM47*AL47 -> 0.7 | AO47: =VLOOKUP(A47,'Loan List '!$A$6:$BA$75,17, FALSE) -> 0.04 | AP47: =VLOOKUP(A47,'Loan List '!$A$6:$BA$795,15, FALSE) -> SOFR | AQ47: =VLOOKUP(A47,'Loan List '!$A$6:$BA$795,16, FALSE) -> 0.01 | AR47: 0 | AS47: 0 | AU47: =AO47-AS47 -> 0.04 | AV47: =IF(AND(AS47>0%,AU47>4.5%),TRUE,FALSE) -> FALSE | AW47: =IF(AND(AS47>0%,AU47>=2.25%, AV47=FALSE),TRUE,FALSE) -> FALSE | AX47: =IF(AND(AS47>0%,AW47=FALSE, AV47=FALSE),TRUE, FALSE) -> FALSE | AZ47: =(OR(CC47<>"NR",CD47<>"NR")) -> FALSE | BA47: ='Loan List '!AS36 -> Maintenance Covenants | BB47: =IF(D47="FL",FALSE,TRUE) -> FALSE | BC47: =IF(BU47>5.5, TRUE, FALSE) -> FALSE | BD47: =IF(BF47="USD", TRUE,FALSE) -> TRUE | BE47: =IF(BG47="USA",TRUE,FALSE) -> TRUE | BF47: ='Loan List '!J36 -> USD | BG47: =VLOOKUP(A47,'Loan List '!$A$6:$BZ$75, 23, FALSE) -> USA | BH47: =IF(D47="FLLO", TRUE,FALSE) -> FALSE | BI47: =IF(C47="Second Lien",TRUE,FALSE) -> FALSE | BJ47: =IF('Loan List '!BP36=1, TRUE, FALSE) -> FALSE | BK47: =IF(AR47>0%,TRUE,FALSE) -> FALSE | BL47: =OR(LEFT(CC47,1)="C", LEFT(CD47,1)="C") -> FALSE | BM47: =IF('Loan List '!AT36="Yes", TRUE, FALSE) -> FALSE | BN47: =-($BN$15-N47)/365 -> 3.4027397 | BO47: ='Concentration Limitations'!H42 -> 496253.14 | BP47: =IF(R47=$T$13,0,BO47*AL47) -> 347377.2 | BS47: ='Loan List '!AG36 -> 45747 | BT47: ='Loan List '!AO36 -> 2.9371485 | BU47: ='Loan List '!AI36 -> 4.110867 | BW47: 0 | BX47: - | BY47: ='Loan List '!AJ36 -> 184.356 | BZ47: ='Loan List '!AL36 -> 0 | CA47: 0 | CB47: 0 | CC47: NR | CD47: NR | CE47: - | CF47: ='Loan List '!AC36 -> 2.5638576 | CG47: ='Loan List '!AD36 -> 3.7037513 | CI47: 0 | CJ47: - | CK47: ='Loan List '!AB36 -> 155.68 | CL47: ='Loan List '!AE36 -> 0 | CM47: 0 | CN47: 0 | CO47: NR | CP47: NR | CQ47: =IFERROR(($BT47-$CF47)/$CF47,0) -> 0.14559734 | CR47: =IFERROR(($BU47-$CG47)/$CG47,0) -> 0.10991984 | CS47: =BU47-CG47 -> 0.40711573 | CT47: =(BY47/CK47)-1 -> 0.18419836 | CU47: =IF(OR($CQ47<'Summary '!$I$47,$BT47<'Summary '!$I$46),1,0) -> 0 | CV47: =IF(OR($CS47>='Summary '!$I$50, (AND(BU47>'Summary '!$I$52, Calcs!CR47> 'Summary '!$I$51))),1,0) -> 0 | CW47: =IF(OR(SUM(CU47:CV47)>=1,CX47="Yes"),1,0) -> 0 | CX47: No | CY47: No | CZ47: No | DD47: 0 | DE47: 0 | DI47: =IF(L47<90%,"Not Eligible","Eligible") -> Eligible | DJ47: =IF(OR(BF47="USD",BF47="CAD",BF47="EUR",BF47="GBP",BF47="AUD"),"Eligible","Not Eligible") -> Eligible | DK47: Eligible | DL47: Eligible | DM47: =IF(BM47="FALSE",IF(BY47<5,"Not Eligible","Eligible"),"Eligible") -> Eligible | DN47: =IF(AW47=TRUE,IF(AU47>=3%,"Eligible","Not Eligible"),"Not PIK") -> Not PIK | DO47: No | DP47: =IF(OR(DK47="Not Eligible",DL47="Not Eligible",DI47="Not Eligible",DJ47="Not Eligible",DM47="Not Eligible",DN47="Not Eligible",DO47="Yes"),"NO","YES") -> YES
A48: Municipal Emergency Services, Inc. | B48: =IFERROR(VLOOKUP(A48,'Loan List '!$A$6:$BZ$75,2,FALSE),NA) -> 0 | C48: =VLOOKUP(A48,'Loan List '!$A$6:$G$75, 7, FALSE) -> First Lien | D48: =VLOOKUP(A48, 'Loan List '!$A$6:$K$82, 11, FALSE) -> FL | E48: =IF(DP48= "YES", TRUE, FALSE) -> TRUE | F48: =VLOOKUP(A48,'Loan List '!$A$6:$L$75, 12, FALSE) -> Distributors | H48: =+I48 -> 2493636 | I48: =VLOOKUP(A48,'Loan List '!$A$6:$L$75, 8, FALSE) -> 2493636 | J48: 0 | K48: =I48/$I$15 -> 0.0069024167 | L48: =VLOOKUP(A48,'Loan List '!$A$6:$BA$82,24, FALSE) -> 100 | N48: =VLOOKUP(A48,'Loan List '!$A$6:$BA$82,22, FALSE) -> 46661 | O48: =IFERROR(MAX(0,I48-J48)*L48,"")/100 -> 2493636 | P48: =MIN(IF(AND(L48>=97%,Q48="Primary"),100%,L48),T48) -> 1 | Q48: Primary | R48: SETTLED | S48: =IF(OR(CU48=1,CV48=1,CW48=1),TRUE,FALSE) -> FALSE | T48: =VLOOKUP(A48,'Loan List '!$A$6:$BD$1048576,56,FALSE)/100 -> 1 | U48: =IF(E48=TRUE,P48*I48,0) -> 2493636 | V48: =VLOOKUP(A48,'Loan List '!$A$6:$BA$82,26, FALSE) -> 0 | W48: =V48*I48 -> 0 | Y48: =VLOOKUP(A48,'Loan List '!$A$6:$BA$75,27, FALSE) -> 0 | AB48: =K48*BU48 -> 0.02360974 | AC48: =K48*AL48 -> 0.0046591313 | AD48: =BW48 -> 0 | AE48: =IF(CK48>=$C$5,"Class 1",IF(CK48>=$D$5,"Class 2",IF(CK48>=$E$5,"Class 3","Class 4"))) -> Class 2 | AF48: =HLOOKUP($AE48,$B$3:$F$10,4,0) -> 5.5 | AG48: =IF(BB48,1,0)+HLOOKUP($AE48,$B$3:$F$10,5,0) -> 6.5 | AH48: =MIN(AF48/BU48,1) -> 1 | AI48: =IF(BU48>AG48,(AG48-AF48)/BU48,1-AH48) -> 0 | AJ48: =HLOOKUP($AE48,$B$3:$F$10,6,0) -> 0.675 | AK48: =HLOOKUP($AE48,$B$3:$F$10,8,0) -> 0.35 | AL48: =IF(OR(BI48, AND(BH48,AD48>1)), HLOOKUP(AE48,$B$3:$F$10,8,0),AH48*AJ48+AI48*AK48) -> 0.675 | AM48: ='Diversity Score'!$E$7 -> 1 | AN48: =AM48*AL48 -> 0.675 | AO48: =VLOOKUP(A48,'Loan List '!$A$6:$BA$75,17, FALSE) -> 0.0515 | AP48: =VLOOKUP(A48,'Loan List '!$A$6:$BA$795,15, FALSE) -> SOFR | AQ48: =VLOOKUP(A48,'Loan List '!$A$6:$BA$795,16, FALSE) -> 0.01 | AR48: 0 | AS48: 0 | AU48: =AO48-AS48 -> 0.0515 | AV48: =IF(AND(AS48>0%,AU48>4.5%),TRUE,FALSE) -> FALSE | AW48: =IF(AND(AS48>0%,AU48>=2.25%, AV48=FALSE),TRUE,FALSE) -> FALSE | AX48: =IF(AND(AS48>0%,AW48=FALSE, AV48=FALSE),TRUE, FALSE) -> FALSE | AZ48: =(OR(CC48<>"NR",CD48<>"NR")) -> FALSE | BA48: ='Loan List '!AS37 -> Maintenance Covenants | BB48: =IF(D48="FL",FALSE,TRUE) -> FALSE | BC48: =IF(BU48>5.5, TRUE, FALSE) -> FALSE | BD48: =IF(BF48="USD", TRUE,FALSE) -> TRUE | BE48: =IF(BG48="USA",TRUE,FALSE) -> TRUE | BF48: ='Loan List '!J37 -> USD | BG48: =VLOOKUP(A48,'Loan List '!$A$6:$BZ$75, 23, FALSE) -> USA | BH48: =IF(D48="FLLO", TRUE,FALSE) -> FALSE | BI48: =IF(C48="Second Lien",TRUE,FALSE) -> FALSE | BJ48: =IF('Loan List '!BP37=1, TRUE, FALSE) -> FALSE | BK48: =IF(AR48>0%,TRUE,FALSE) -> FALSE | BL48: =OR(LEFT(CC48,1)="C", LEFT(CD48,1)="C") -> FALSE | BM48: =IF('Loan List '!AT37="Yes", TRUE, FALSE) -> FALSE | BN48: =-($BN$15-N48)/365 -> 2.1863014 | BO48: ='Concentration Limitations'!H43 -> 2493636 | BP48: =IF(R48=$T$13,0,BO48*AL48) -> 1683204.3 | BS48: ='Loan List '!AG37 -> 45808 | BT48: ='Loan List '!AO37 -> 3.1896594 | BU48: ='Loan List '!AI37 -> 3.4205035 | BW48: 0 | BX48: - | BY48: ='Loan List '!AJ37 -> 41.115 | BZ48: ='Loan List '!AL37 -> 0 | CA48: 0 | CB48: 0 | CC48: NR | CD48: NR | CE48: - | CF48: ='Loan List '!AC37 -> 1.6322173 | CG48: ='Loan List '!AD37 -> 4.1874411 | CI48: 0 | CJ48: - | CK48: ='Loan List '!AB37 -> 35.017 | CL48: ='Loan List '!AE37 -> 0 | CM48: 0 | CN48: 0 | CO48: NR | CP48: NR | CQ48: =IFERROR(($BT48-$CF48)/$CF48,0) -> 0.95418798 | CR48: =IFERROR(($BU48-$CG48)/$CG48,0) -> -0.18315187 | CS48: =BU48-CG48 -> -0.76693766 | CT48: =(BY48/CK48)-1 -> 0.17414399 | CU48: =IF(OR($CQ48<'Summary '!$I$47,$BT48<'Summary '!$I$46),1,0) -> 0 | CV48: =IF(OR($CS48>='Summary '!$I$50, (AND(BU48>'Summary '!$I$52, Calcs!CR48> 'Summary '!$I$51))),1,0) -> 0 | CW48: =IF(OR(SUM(CU48:CV48)>=1,CX48="Yes"),1,0) -> 0 | CX48: No | CY48: No | CZ48: No | DD48: 0 | DE48: 0 | DI48: =IF(L48<90%,"Not Eligible","Eligible") -> Eligible | DJ48: =IF(OR(BF48="USD",BF48="CAD",BF48="EUR",BF48="GBP",BF48="AUD"),"Eligible","Not Eligible") -> Eligible | DK48: Eligible | DL48: Eligible | DM48: =IF(BM48="FALSE",IF(BY48<5,"Not Eligible","Eligible"),"Eligible") -> Eligible | DN48: =IF(AW48=TRUE,IF(AU48>=3%,"Eligible","Not Eligible"),"Not PIK") -> Not PIK | DO48: No | DP48: =IF(OR(DK48="Not Eligible",DL48="Not Eligible",DI48="Not Eligible",DJ48="Not Eligible",DM48="Not Eligible",DN48="Not Eligible",DO48="Yes"),"NO","YES") -> YES
A49: MOREgroup Holdings, LLC | B49: =IFERROR(VLOOKUP(A49,'Loan List '!$A$6:$BZ$75,2,FALSE),NA) -> 0 | C49: =VLOOKUP(A49,'Loan List '!$A$6:$G$75, 7, FALSE) -> First Lien | D49: =VLOOKUP(A49, 'Loan List '!$A$6:$K$82, 11, FALSE) -> FL | E49: =IF(DP49= "YES", TRUE, FALSE) -> TRUE | F49: =VLOOKUP(A49,'Loan List '!$A$6:$L$75, 12, FALSE) -> Professional Services | H49: =+I49 -> 4241968 | I49: =VLOOKUP(A49,'Loan List '!$A$6:$L$75, 8, FALSE) -> 4241968 | J49: 0 | K49: =I49/$I$15 -> 0.011741822 | L49: =VLOOKUP(A49,'Loan List '!$A$6:$BA$82,24, FALSE) -> 100 | N49: =VLOOKUP(A49,'Loan List '!$A$6:$BA$82,22, FALSE) -> 47499 | O49: =IFERROR(MAX(0,I49-J49)*L49,"")/100 -> 4241968 | P49: =MIN(IF(AND(L49>=97%,Q49="Primary"),100%,L49),T49) -> 1 | Q49: Primary | R49: SETTLED | S49: =IF(OR(CU49=1,CV49=1,CW49=1),TRUE,FALSE) -> FALSE | T49: =VLOOKUP(A49,'Loan List '!$A$6:$BD$1048576,56,FALSE)/100 -> 1 | U49: =IF(E49=TRUE,P49*I49,0) -> 4241968 | V49: =VLOOKUP(A49,'Loan List '!$A$6:$BA$82,26, FALSE) -> 0 | W49: =V49*I49 -> 0 | Y49: =VLOOKUP(A49,'Loan List '!$A$6:$BA$75,27, FALSE) -> 0 | AB49: =K49*BU49 -> 0.03054571 | AC49: =K49*AL49 -> 0.0079257301 | AD49: =BW49 -> 0 | AE49: =IF(CK49>=$C$5,"Class 1",IF(CK49>=$D$5,"Class 2",IF(CK49>=$E$5,"Class 3","Class 4"))) -> Class 2 | AF49: =HLOOKUP($AE49,$B$3:$F$10,4,0) -> 5.5 | AG49: =IF(BB49,1,0)+HLOOKUP($AE49,$B$3:$F$10,5,0) -> 6.5 | AH49: =MIN(AF49/BU49,1) -> 1 | AI49: =IF(BU49>AG49,(AG49-AF49)/BU49,1-AH49) -> 0 | AJ49: =HLOOKUP($AE49,$B$3:$F$10,6,0) -> 0.675 | AK49: =HLOOKUP($AE49,$B$3:$F$10,8,0) -> 0.35 | AL49: =IF(OR(BI49, AND(BH49,AD49>1)), HLOOKUP(AE49,$B$3:$F$10,8,0),AH49*AJ49+AI49*AK49) -> 0.675 | AM49: ='Diversity Score'!$E$7 -> 1 | AN49: =AM49*AL49 -> 0.675 | AO49: =VLOOKUP(A49,'Loan List '!$A$6:$BA$75,17, FALSE) -> 0.0525 | AP49: =VLOOKUP(A49,'Loan List '!$A$6:$BA$795,15, FALSE) -> SOFR | AQ49: =VLOOKUP(A49,'Loan List '!$A$6:$BA$795,16, FALSE) -> 0.01 | AR49: 0 | AS49: 0 | AU49: =AO49-AS49 -> 0.0525 | AV49: =IF(AND(AS49>0%,AU49>4.5%),TRUE,FALSE) -> FALSE | AW49: =IF(AND(AS49>0%,AU49>=2.25%, AV49=FALSE),TRUE,FALSE) -> FALSE | AX49: =IF(AND(AS49>0%,AW49=FALSE, AV49=FALSE),TRUE, FALSE) -> FALSE | AZ49: =(OR(CC49<>"NR",CD49<>"NR")) -> FALSE | BA49: ='Loan List '!AS38 -> Cov-Lite | BB49: =IF(D49="FL",FALSE,TRUE) -> FALSE | BC49: =IF(BU49>5.5, TRUE, FALSE) -> FALSE | BD49: =IF(BF49="USD", TRUE,FALSE) -> TRUE | BE49: =IF(BG49="USA",TRUE,FALSE) -> TRUE | BF49: ='Loan List '!J38 -> USD | BG49: =VLOOKUP(A49,'Loan List '!$A$6:$BZ$75, 23, FALSE) -> USA | BH49: =IF(D49="FLLO", TRUE,FALSE) -> FALSE | BI49: =IF(C49="Second Lien",TRUE,FALSE) -> FALSE | BJ49: =IF('Loan List '!BP38=1, TRUE, FALSE) -> FALSE | BK49: =IF(AR49>0%,TRUE,FALSE) -> FALSE | BL49: =OR(LEFT(CC49,1)="C", LEFT(CD49,1)="C") -> FALSE | BM49: =IF('Loan List '!AT38="Yes", TRUE, FALSE) -> TRUE | BN49: =-($BN$15-N49)/365 -> 4.4821918 | BO49: ='Concentration Limitations'!H44 -> 4241968 | BP49: =IF(R49=$T$13,0,BO49*AL49) -> 2863328.4 | BS49: ='Loan List '!AG38 -> 45777 | BT49: ='Loan List '!AO38 -> 2.8006857 | BU49: ='Loan List '!AI38 -> 2.6014455 | BW49: 0 | BX49: - | BY49: ='Loan List '!AJ38 -> 69.673245 | BZ49: ='Loan List '!AL38 -> 0 | CA49: 0 | CB49: 0 | CC49: NR | CD49: NR | CE49: - | CF49: ='Loan List '!AC38 -> 1.968454 | CG49: ='Loan List '!AD38 -> 4.4013201 | CI49: 0 | CJ49: - | CK49: ='Loan List '!AB38 -> 50.913 | CL49: ='Loan List '!AE38 -> 0 | CM49: 0 | CN49: 0 | CO49: NR | CP49: NR | CQ49: =IFERROR(($BT49-$CF49)/$CF49,0) -> 0.4227844 | CR49: =IFERROR(($BU49-$CG49)/$CG49,0) -> -0.40893973 | CS49: =BU49-CG49 -> -1.7998746 | CT49: =(BY49/CK49)-1 -> 0.36847651 | CU49: =IF(OR($CQ49<'Summary '!$I$47,$BT49<'Summary '!$I$46),1,0) -> 0 | CV49: =IF(OR($CS49>='Summary '!$I$50, (AND(BU49>'Summary '!$I$52, Calcs!CR49> 'Summary '!$I$51))),1,0) -> 0 | CW49: =IF(OR(SUM(CU49:CV49)>=1,CX49="Yes"),1,0) -> 0 | CX49: No | CY49: No | CZ49: No | DD49: 0 | DE49: 0 | DI49: =IF(L49<90%,"Not Eligible","Eligible") -> Eligible | DJ49: =IF(OR(BF49="USD",BF49="CAD",BF49="EUR",BF49="GBP",BF49="AUD"),"Eligible","Not Eligible") -> Eligible | DK49: Eligible | DL49: Eligible | DM49: =IF(BM49="FALSE",IF(BY49<5,"Not Eligible","Eligible"),"Eligible") -> Eligible | DN49: =IF(AW49=TRUE,IF(AU49>=3%,"Eligible","Not Eligible"),"Not PIK") -> Not PIK | DO49: No | DP49: =IF(OR(DK49="Not Eligible",DL49="Not Eligible",DI49="Not Eligible",DJ49="Not Eligible",DM49="Not Eligible",DN49="Not Eligible",DO49="Yes"),"NO","YES") -> YES
A50: NFS - CFP Holdings, LLC | B50: =IFERROR(VLOOKUP(A50,'Loan List '!$A$6:$BZ$75,2,FALSE),NA) -> 0 | C50: =VLOOKUP(A50,'Loan List '!$A$6:$G$75, 7, FALSE) -> First Lien | D50: =VLOOKUP(A50, 'Loan List '!$A$6:$K$82, 11, FALSE) -> FL | E50: =IF(DP50= "YES", TRUE, FALSE) -> TRUE | F50: =VLOOKUP(A50,'Loan List '!$A$6:$L$75, 12, FALSE) -> Professional Services | H50: =+I50 -> 3980866.9 | I50: =VLOOKUP(A50,'Loan List '!$A$6:$L$75, 8, FALSE) -> 3980866.9 | J50: 0 | K50: =I50/$I$15 -> 0.011019091 | L50: =VLOOKUP(A50,'Loan List '!$A$6:$BA$82,24, FALSE) -> 100 | N50: =VLOOKUP(A50,'Loan List '!$A$6:$BA$82,22, FALSE) -> 47746 | O50: =IFERROR(MAX(0,I50-J50)*L50,"")/100 -> 3980866.9 | P50: =MIN(IF(AND(L50>=97%,Q50="Primary"),100%,L50),T50) -> 1 | Q50: Primary | R50: SETTLED | S50: =IF(OR(CU50=1,CV50=1,CW50=1),TRUE,FALSE) -> FALSE | T50: =VLOOKUP(A50,'Loan List '!$A$6:$BD$1048576,56,FALSE)/100 -> 1 | U50: =IF(E50=TRUE,P50*I50,0) -> 3980866.9 | V50: =VLOOKUP(A50,'Loan List '!$A$6:$BA$82,26, FALSE) -> 0 | W50: =V50*I50 -> 0 | Y50: =VLOOKUP(A50,'Loan List '!$A$6:$BA$75,27, FALSE) -> 0 | AB50: =K50*BU50 -> 0.03786469 | AC50: =K50*AL50 -> 0.0071624092 | AD50: =BW50 -> 0 | AE50: =IF(CK50>=$C$5,"Class 1",IF(CK50>=$D$5,"Class 2",IF(CK50>=$E$5,"Class 3","Class 4"))) -> Class 3 | AF50: =HLOOKUP($AE50,$B$3:$F$10,4,0) -> 5 | AG50: =IF(BB50,1,0)+HLOOKUP($AE50,$B$3:$F$10,5,0) -> 6 | AH50: =MIN(AF50/BU50,1) -> 1 | AI50: =IF(BU50>AG50,(AG50-AF50)/BU50,1-AH50) -> 0 | AJ50: =HLOOKUP($AE50,$B$3:$F$10,6,0) -> 0.65 | AK50: =HLOOKUP($AE50,$B$3:$F$10,8,0) -> 0.35 | AL50: =IF(OR(BI50, AND(BH50,AD50>1)), HLOOKUP(AE50,$B$3:$F$10,8,0),AH50*AJ50+AI50*AK50) -> 0.65 | AM50: ='Diversity Score'!$E$7 -> 1 | AN50: =AM50*AL50 -> 0.65 | AO50: =VLOOKUP(A50,'Loan List '!$A$6:$BA$75,17, FALSE) -> 0.0475 | AP50: =VLOOKUP(A50,'Loan List '!$A$6:$BA$795,15, FALSE) -> SOFR | AQ50: =VLOOKUP(A50,'Loan List '!$A$6:$BA$795,16, FALSE) -> 0.01 | AR50: 0 | AS50: 0 | AU50: =AO50-AS50 -> 0.0475 | AV50: =IF(AND(AS50>0%,AU50>4.5%),TRUE,FALSE) -> FALSE | AW50: =IF(AND(AS50>0%,AU50>=2.25%, AV50=FALSE),TRUE,FALSE) -> FALSE | AX50: =IF(AND(AS50>0%,AW50=FALSE, AV50=FALSE),TRUE, FALSE) -> FALSE | AZ50: =(OR(CC50<>"NR",CD50<>"NR")) -> FALSE | BA50: ='Loan List '!AS39 -> Maintenance Covenants | BB50: =IF(D50="FL",FALSE,TRUE) -> FALSE | BC50: =IF(BU50>5.5, TRUE, FALSE) -> FALSE | BD50: =IF(BF50="USD", TRUE,FALSE) -> TRUE | BE50: =IF(BG50="USA",TRUE,FALSE) -> TRUE | BF50: ='Loan List '!J39 -> USD | BG50: =VLOOKUP(A50,'Loan List '!$A$6:$BZ$75, 23, FALSE) -> USA | BH50: =IF(D50="FLLO", TRUE,FALSE) -> FALSE | BI50: =IF(C50="Second Lien",TRUE,FALSE) -> FALSE | BJ50: =IF('Loan List '!BP39=1, TRUE, FALSE) -> FALSE | BK50: =IF(AR50>0%,TRUE,FALSE) -> FALSE | BL50: =OR(LEFT(CC50,1)="C", LEFT(CD50,1)="C") -> FALSE | BM50: =IF('Loan List '!AT39="Yes", TRUE, FALSE) -> FALSE | BN50: =-($BN$15-N50)/365 -> 5.1589041 | BO50: ='Concentration Limitations'!H45 -> 3980866.9 | BP50: =IF(R50=$T$13,0,BO50*AL50) -> 2587563.5 | BS50: ='Loan List '!AG39 -> 45777 | BT50: ='Loan List '!AO39 -> 2.8747782 | BU50: ='Loan List '!AI39 -> 3.4362807 | BW50: 0 | BX50: - | BY50: ='Loan List '!AJ39 -> 22.710748 | BZ50: ='Loan List '!AL39 -> 0 | CA50: 0 | CB50: 0 | CC50: NR | CD50: NR | CE50: - | CF50: ='Loan List '!AC39 -> 1.8784216 | CG50: ='Loan List '!AD39 -> 5.2701072 | CI50: 0 | CJ50: - | CK50: ='Loan List '!AB39 -> 10.208521 | CL50: ='Loan List '!AE39 -> 0 | CM50: 0 | CN50: 0 | CO50: NR | CP50: NR | CQ50: =IFERROR(($BT50-$CF50)/$CF50,0) -> 0.53042227 | CR50: =IFERROR(($BU50-$CG50)/$CG50,0) -> -0.34796759 | CS50: =BU50-CG50 -> -1.8338265 | CT50: =(BY50/CK50)-1 -> 1.2246854 | CU50: =IF(OR($CQ50<'Summary '!$I$47,$BT50<'Summary '!$I$46),1,0) -> 0 | CV50: =IF(OR($CS50>='Summary '!$I$50, (AND(BU50>'Summary '!$I$52, Calcs!CR50> 'Summary '!$I$51))),1,0) -> 0 | CW50: =IF(OR(SUM(CU50:CV50)>=1,CX50="Yes"),1,0) -> 0 | CX50: No | CY50: No | CZ50: No | DD50: 0 | DE50: 0 | DI50: =IF(L50<90%,"Not Eligible","Eligible") -> Eligible | DJ50: =IF(OR(BF50="USD",BF50="CAD",BF50="EUR",BF50="GBP",BF50="AUD"),"Eligible","Not Eligible") -> Eligible | DK50: Eligible | DL50: Eligible | DM50: =IF(BM50="FALSE",IF(BY50<5,"Not Eligible","Eligible"),"Eligible") -> Eligible | DN50: =IF(AW50=TRUE,IF(AU50>=3%,"Eligible","Not Eligible"),"Not PIK") -> Not PIK | DO50: No | DP50: =IF(OR(DK50="Not Eligible",DL50="Not Eligible",DI50="Not Eligible",DJ50="Not Eligible",DM50="Not Eligible",DN50="Not Eligible",DO50="Yes"),"NO","YES") -> YES
A51: NORA ACQUISITION, LLC | B51: =IFERROR(VLOOKUP(A51,'Loan List '!$A$6:$BZ$75,2,FALSE),NA) -> 0 | C51: =VLOOKUP(A51,'Loan List '!$A$6:$G$75, 7, FALSE) -> First Lien | D51: =VLOOKUP(A51, 'Loan List '!$A$6:$K$82, 11, FALSE) -> FL | E51: =IF(DP51= "YES", TRUE, FALSE) -> TRUE | F51: =VLOOKUP(A51,'Loan List '!$A$6:$L$75, 12, FALSE) -> Air Freight & Logistics | H51: =+I51 -> 3768234.9 | I51: =VLOOKUP(A51,'Loan List '!$A$6:$L$75, 8, FALSE) -> 3768234.9 | J51: 0 | K51: =I51/$I$15 -> 0.010430523 | L51: =VLOOKUP(A51,'Loan List '!$A$6:$BA$82,24, FALSE) -> 100 | N51: =VLOOKUP(A51,'Loan List '!$A$6:$BA$82,22, FALSE) -> 47361 | O51: =IFERROR(MAX(0,I51-J51)*L51,"")/100 -> 3768234.9 | P51: =MIN(IF(AND(L51>=97%,Q51="Primary"),100%,L51),T51) -> 1 | Q51: Primary | R51: SETTLED | S51: =IF(OR(CU51=1,CV51=1,CW51=1),TRUE,FALSE) -> TRUE | T51: =VLOOKUP(A51,'Loan List '!$A$6:$BD$1048576,56,FALSE)/100 -> 1 | U51: =IF(E51=TRUE,P51*I51,0) -> 3768234.9 | V51: =VLOOKUP(A51,'Loan List '!$A$6:$BA$82,26, FALSE) -> 0 | W51: =V51*I51 -> 0 | Y51: =VLOOKUP(A51,'Loan List '!$A$6:$BA$75,27, FALSE) -> 0 | AB51: =K51*BU51 -> 0.061341507 | AC51: =K51*AL51 -> 0.0063110955 | AD51: =BW51 -> 0 | AE51: =IF(CK51>=$C$5,"Class 1",IF(CK51>=$D$5,"Class 2",IF(CK51>=$E$5,"Class 3","Class 4"))) -> Class 3 | AF51: =HLOOKUP($AE51,$B$3:$F$10,4,0) -> 5 | AG51: =IF(BB51,1,0)+HLOOKUP($AE51,$B$3:$F$10,5,0) -> 6 | AH51: =MIN(AF51/BU51,1) -> 0.85020106 | AI51: =IF(BU51>AG51,(AG51-AF51)/BU51,1-AH51) -> 0.14979894 | AJ51: =HLOOKUP($AE51,$B$3:$F$10,6,0) -> 0.65 | AK51: =HLOOKUP($AE51,$B$3:$F$10,8,0) -> 0.35 | AL51: =IF(OR(BI51, AND(BH51,AD51>1)), HLOOKUP(AE51,$B$3:$F$10,8,0),AH51*AJ51+AI51*AK51) -> 0.60506032 | AM51: ='Diversity Score'!$E$7 -> 1 | AN51: =AM51*AL51 -> 0.60506032 | AO51: =VLOOKUP(A51,'Loan List '!$A$6:$BA$75,17, FALSE) -> 0.0635 | AP51: =VLOOKUP(A51,'Loan List '!$A$6:$BA$795,15, FALSE) -> SOFR | AQ51: =VLOOKUP(A51,'Loan List '!$A$6:$BA$795,16, FALSE) -> 0.01 | AR51: 0 | AS51: 0 | AU51: =AO51-AS51 -> 0.0635 | AV51: =IF(AND(AS51>0%,AU51>4.5%),TRUE,FALSE) -> FALSE | AW51: =IF(AND(AS51>0%,AU51>=2.25%, AV51=FALSE),TRUE,FALSE) -> FALSE | AX51: =IF(AND(AS51>0%,AW51=FALSE, AV51=FALSE),TRUE, FALSE) -> FALSE | AZ51: =(OR(CC51<>"NR",CD51<>"NR")) -> FALSE | BA51: ='Loan List '!AS40 -> Maintenance Covenants | BB51: =IF(D51="FL",FALSE,TRUE) -> FALSE | BC51: =IF(BU51>5.5, TRUE, FALSE) -> TRUE | BD51: =IF(BF51="USD", TRUE,FALSE) -> TRUE | BE51: =IF(BG51="USA",TRUE,FALSE) -> TRUE | BF51: ='Loan List '!J40 -> USD | BG51: =VLOOKUP(A51,'Loan List '!$A$6:$BZ$75, 23, FALSE) -> USA | BH51: =IF(D51="FLLO", TRUE,FALSE) -> FALSE | BI51: =IF(C51="Second Lien",TRUE,FALSE) -> FALSE | BJ51: =IF('Loan List '!BP40=1, TRUE, FALSE) -> FALSE | BK51: =IF(AR51>0%,TRUE,FALSE) -> FALSE | BL51: =OR(LEFT(CC51,1)="C", LEFT(CD51,1)="C") -> FALSE | BM51: =IF('Loan List '!AT40="Yes", TRUE, FALSE) -> FALSE | BN51: =-($BN$15-N51)/365 -> 4.1041096 | BO51: ='Concentration Limitations'!H46 -> 3768234.9 | BP51: =IF(R51=$T$13,0,BO51*AL51) -> 2280009.4 | BS51: ='Loan List '!AG40 -> 45777 | BT51: ='Loan List '!AO40 -> 1.3526751 | BU51: ='Loan List '!AI40 -> 5.8809619 | BW51: 0 | BX51: - | BY51: ='Loan List '!AJ40 -> 12.82189 | BZ51: ='Loan List '!AL40 -> 0 | CA51: 0 | CB51: 0 | CC51: NR | CD51: NR | CE51: - | CF51: ='Loan List '!AC40 -> 2.2766519 | CG51: ='Loan List '!AD40 -> 3.6631323 | CI51: 0 | CJ51: - | CK51: ='Loan List '!AB40 -> 21.293252 | CL51: ='Loan List '!AE40 -> 0 | CM51: 0 | CN51: 0 | CO51: NR | CP51: NR | CQ51: =IFERROR(($BT51-$CF51)/$CF51,0) -> -0.40584897 | CR51: =IFERROR(($BU51-$CG51)/$CG51,0) -> 0.60544622 | CS51: =BU51-CG51 -> 2.2178296 | CT51: =(BY51/CK51)-1 -> -0.3978426 | CU51: =IF(OR($CQ51<'Summary '!$I$47,$BT51<'Summary '!$I$46),1,0) -> 1 | CV51: =IF(OR($CS51>='Summary '!$I$50, (AND(BU51>'Summary '!$I$52, Calcs!CR51> 'Summary '!$I$51))),1,0) -> 1 | CW51: =IF(OR(SUM(CU51:CV51)>=1,CX51="Yes"),1,0) -> 1 | CX51: No | CY51: No | CZ51: No | DD51: 0 | DE51: 0 | DI51: =IF(L51<90%,"Not Eligible","Eligible") -> Eligible | DJ51: =IF(OR(BF51="USD",BF51="CAD",BF51="EUR",BF51="GBP",BF51="AUD"),"Eligible","Not Eligible") -> Eligible | DK51: Eligible | DL51: Eligible | DM51: =IF(BM51="FALSE",IF(BY51<5,"Not Eligible","Eligible"),"Eligible") -> Eligible | DN51: =IF(AW51=TRUE,IF(AU51>=3%,"Eligible","Not Eligible"),"Not PIK") -> Not PIK | DO51: No | DP51: =IF(OR(DK51="Not Eligible",DL51="Not Eligible",DI51="Not Eligible",DJ51="Not Eligible",DM51="Not Eligible",DN51="Not Eligible",DO51="Yes"),"NO","YES") -> YES
A52: Omnia Exterior Solutions, LLC | B52: =IFERROR(VLOOKUP(A52,'Loan List '!$A$6:$BZ$75,2,FALSE),NA) -> 0 | C52: =VLOOKUP(A52,'Loan List '!$A$6:$G$75, 7, FALSE) -> First Lien | D52: =VLOOKUP(A52, 'Loan List '!$A$6:$K$82, 11, FALSE) -> FL | E52: =IF(DP52= "YES", TRUE, FALSE) -> TRUE | F52: =VLOOKUP(A52,'Loan List '!$A$6:$L$75, 12, FALSE) -> Diversified Consumer Services | H52: =+I52 -> 7118722.5 | I52: =VLOOKUP(A52,'Loan List '!$A$6:$L$75, 8, FALSE) -> 7118722.5 | J52: 0 | K52: =I52/$I$15 -> 0.019704716 | L52: =VLOOKUP(A52,'Loan List '!$A$6:$BA$82,24, FALSE) -> 100 | N52: =VLOOKUP(A52,'Loan List '!$A$6:$BA$82,22, FALSE) -> 47481 | O52: =IFERROR(MAX(0,I52-J52)*L52,"")/100 -> 7118722.5 | P52: =MIN(IF(AND(L52>=97%,Q52="Primary"),100%,L52),T52) -> 1 | Q52: Primary | R52: SETTLED | S52: =IF(OR(CU52=1,CV52=1,CW52=1),TRUE,FALSE) -> TRUE | T52: =VLOOKUP(A52,'Loan List '!$A$6:$BD$1048576,56,FALSE)/100 -> 1 | U52: =IF(E52=TRUE,P52*I52,0) -> 7118722.5 | V52: =VLOOKUP(A52,'Loan List '!$A$6:$BA$82,26, FALSE) -> 0 | W52: =V52*I52 -> 0 | Y52: =VLOOKUP(A52,'Loan List '!$A$6:$BA$75,27, FALSE) -> 0 | AB52: =K52*BU52 -> 0.078946331 | AC52: =K52*AL52 -> 0.012808065 | AD52: =BW52 -> 0 | AE52: =IF(CK52>=$C$5,"Class 1",IF(CK52>=$D$5,"Class 2",IF(CK52>=$E$5,"Class 3","Class 4"))) -> Class 3 | AF52: =HLOOKUP($AE52,$B$3:$F$10,4,0) -> 5 | AG52: =IF(BB52,1,0)+HLOOKUP($AE52,$B$3:$F$10,5,0) -> 6 | AH52: =MIN(AF52/BU52,1) -> 1 | AI52: =IF(BU52>AG52,(AG52-AF52)/BU52,1-AH52) -> 0 | AJ52: =HLOOKUP($AE52,$B$3:$F$10,6,0) -> 0.65 | AK52: =HLOOKUP($AE52,$B$3:$F$10,8,0) -> 0.35 | AL52: =IF(OR(BI52, AND(BH52,AD52>1)), HLOOKUP(AE52,$B$3:$F$10,8,0),AH52*AJ52+AI52*AK52) -> 0.65 | AM52: ='Diversity Score'!$E$7 -> 1 | AN52: =AM52*AL52 -> 0.65 | AO52: =VLOOKUP(A52,'Loan List '!$A$6:$BA$75,17, FALSE) -> 0.0525 | AP52: =VLOOKUP(A52,'Loan List '!$A$6:$BA$795,15, FALSE) -> SOFR | AQ52: =VLOOKUP(A52,'Loan List '!$A$6:$BA$795,16, FALSE) -> 0.01 | AR52: 0 | AS52: 0 | AU52: =AO52-AS52 -> 0.0525 | AV52: =IF(AND(AS52>0%,AU52>4.5%),TRUE,FALSE) -> FALSE | AW52: =IF(AND(AS52>0%,AU52>=2.25%, AV52=FALSE),TRUE,FALSE) -> FALSE | AX52: =IF(AND(AS52>0%,AW52=FALSE, AV52=FALSE),TRUE, FALSE) -> FALSE | AZ52: =(OR(CC52<>"NR",CD52<>"NR")) -> FALSE | BA52: ='Loan List '!AS41 -> Cov-Lite | BB52: =IF(D52="FL",FALSE,TRUE) -> FALSE | BC52: =IF(BU52>5.5, TRUE, FALSE) -> FALSE | BD52: =IF(BF52="USD", TRUE,FALSE) -> TRUE | BE52: =IF(BG52="USA",TRUE,FALSE) -> TRUE | BF52: ='Loan List '!J41 -> USD | BG52: =VLOOKUP(A52,'Loan List '!$A$6:$BZ$75, 23, FALSE) -> USA | BH52: =IF(D52="FLLO", TRUE,FALSE) -> FALSE | BI52: =IF(C52="Second Lien",TRUE,FALSE) -> FALSE | BJ52: =IF('Loan List '!BP41=1, TRUE, FALSE) -> FALSE | BK52: =IF(AR52>0%,TRUE,FALSE) -> FALSE | BL52: =OR(LEFT(CC52,1)="C", LEFT(CD52,1)="C") -> FALSE | BM52: =IF('Loan List '!AT41="Yes", TRUE, FALSE) -> TRUE | BN52: =-($BN$15-N52)/365 -> 4.4328767 | BO52: ='Concentration Limitations'!H47 -> 7118722.5 | BP52: =IF(R52=$T$13,0,BO52*AL52) -> 4627169.6 | BS52: ='Loan List '!AG41 -> 45808 | BT52: ='Loan List '!AO41 -> 2.755956 | BU52: ='Loan List '!AI41 -> 4.0064689 | BW52: 0 | BX52: - | BY52: ='Loan List '!AJ41 -> 31.489766 | BZ52: ='Loan List '!AL41 -> 0 | CA52: 0 | CB52: 0 | CC52: NR | CD52: NR | CE52: - | CF52: ='Loan List '!AC41 -> 2.96 | CG52: ='Loan List '!AD41 -> 2.07 | CI52: 0 | CJ52: - | CK52: ='Loan List '!AB41 -> 14.5 | CL52: ='Loan List '!AE41 -> 0 | CM52: 0 | CN52: 0 | CO52: NR | CP52: NR | CQ52: =IFERROR(($BT52-$CF52)/$CF52,0) -> -0.068933787 | CR52: =IFERROR(($BU52-$CG52)/$CG52,0) -> 0.9354922 | CS52: =BU52-CG52 -> 1.9364689 | CT52: =(BY52/CK52)-1 -> 1.171708 | CU52: =IF(OR($CQ52<'Summary '!$I$47,$BT52<'Summary '!$I$46),1,0) -> 0 | CV52: =IF(OR($CS52>='Summary '!$I$50, (AND(BU52>'Summary '!$I$52, Calcs!CR52> 'Summary '!$I$51))),1,0) -> 1 | CW52: =IF(OR(SUM(CU52:CV52)>=1,CX52="Yes"),1,0) -> 1 | CX52: No | CY52: No | CZ52: No | DD52: 0 | DE52: 0 | DI52: =IF(L52<90%,"Not Eligible","Eligible") -> Eligible | DJ52: =IF(OR(BF52="USD",BF52="CAD",BF52="EUR",BF52="GBP",BF52="AUD"),"Eligible","Not Eligible") -> Eligible | DK52: Eligible | DL52: Eligible | DM52: =IF(BM52="FALSE",IF(BY52<5,"Not Eligible","Eligible"),"Eligible") -> Eligible | DN52: =IF(AW52=TRUE,IF(AU52>=3%,"Eligible","Not Eligible"),"Not PIK") -> Not PIK | DO52: No | DP52: =IF(OR(DK52="Not Eligible",DL52="Not Eligible",DI52="Not Eligible",DJ52="Not Eligible",DM52="Not Eligible",DN52="Not Eligible",DO52="Yes"),"NO","YES") -> YES
A53: PAR Excellence | B53: =IFERROR(VLOOKUP(A53,'Loan List '!$A$6:$BZ$75,2,FALSE),NA) -> 0 | C53: =VLOOKUP(A53,'Loan List '!$A$6:$G$75, 7, FALSE) -> First Lien | D53: =VLOOKUP(A53, 'Loan List '!$A$6:$K$82, 11, FALSE) -> FL | E53: =IF(DP53= "YES", TRUE, FALSE) -> TRUE | F53: =VLOOKUP(A53,'Loan List '!$A$6:$L$75, 12, FALSE) -> Health Care Technology | H53: =+I53 -> 995000 | I53: =VLOOKUP(A53,'Loan List '!$A$6:$L$75, 8, FALSE) -> 995000 | J53: 0 | K53: =I53/$I$15 -> 0.0027541729 | L53: =VLOOKUP(A53,'Loan List '!$A$6:$BA$82,24, FALSE) -> 100 | N53: =VLOOKUP(A53,'Loan List '!$A$6:$BA$82,22, FALSE) -> 47729 | O53: =IFERROR(MAX(0,I53-J53)*L53,"")/100 -> 995000 | P53: =MIN(IF(AND(L53>=97%,Q53="Primary"),100%,L53),T53) -> 1 | Q53: Primary | R53: SETTLED | S53: =IF(OR(CU53=1,CV53=1,CW53=1),TRUE,FALSE) -> TRUE | T53: =VLOOKUP(A53,'Loan List '!$A$6:$BD$1048576,56,FALSE)/100 -> 1 | U53: =IF(E53=TRUE,P53*I53,0) -> 995000 | V53: =VLOOKUP(A53,'Loan List '!$A$6:$BA$82,26, FALSE) -> 0 | W53: =V53*I53 -> 0 | Y53: =VLOOKUP(A53,'Loan List '!$A$6:$BA$75,27, FALSE) -> 0 | AB53: =K53*BU53 -> 0.010811201 | AC53: =K53*AL53 -> 0.0017902124 | AD53: =BW53 -> 0 | AE53: =IF(CK53>=$C$5,"Class 1",IF(CK53>=$D$5,"Class 2",IF(CK53>=$E$5,"Class 3","Class 4"))) -> Class 3 | AF53: =HLOOKUP($AE53,$B$3:$F$10,4,0) -> 5 | AG53: =IF(BB53,1,0)+HLOOKUP($AE53,$B$3:$F$10,5,0) -> 6 | AH53: =MIN(AF53/BU53,1) -> 1 | AI53: =IF(BU53>AG53,(AG53-AF53)/BU53,1-AH53) -> 0 | AJ53: =HLOOKUP($AE53,$B$3:$F$10,6,0) -> 0.65 | AK53: =HLOOKUP($AE53,$B$3:$F$10,8,0) -> 0.35 | AL53: =IF(OR(BI53, AND(BH53,AD53>1)), HLOOKUP(AE53,$B$3:$F$10,8,0),AH53*AJ53+AI53*AK53) -> 0.65 | AM53: ='Diversity Score'!$E$7 -> 1 | AN53: =AM53*AL53 -> 0.65 | AO53: =VLOOKUP(A53,'Loan List '!$A$6:$BA$75,17, FALSE) -> 0.05 | AP53: =VLOOKUP(A53,'Loan List '!$A$6:$BA$795,15, FALSE) -> SOFR | AQ53: =VLOOKUP(A53,'Loan List '!$A$6:$BA$795,16, FALSE) -> 0.01 | AR53: 0 | AS53: 0 | AU53: =AO53-AS53 -> 0.05 | AV53: =IF(AND(AS53>0%,AU53>4.5%),TRUE,FALSE) -> FALSE | AW53: =IF(AND(AS53>0%,AU53>=2.25%, AV53=FALSE),TRUE,FALSE) -> FALSE | AX53: =IF(AND(AS53>0%,AW53=FALSE, AV53=FALSE),TRUE, FALSE) -> FALSE | AZ53: =(OR(CC53<>"NR",CD53<>"NR")) -> FALSE | BA53: ='Loan List '!AS42 -> Maintenance Covenants | BB53: =IF(D53="FL",FALSE,TRUE) -> FALSE | BC53: =IF(BU53>5.5, TRUE, FALSE) -> FALSE | BD53: =IF(BF53="USD", TRUE,FALSE) -> TRUE | BE53: =IF(BG53="USA",TRUE,FALSE) -> TRUE | BF53: ='Loan List '!J42 -> USD | BG53: =VLOOKUP(A53,'Loan List '!$A$6:$BZ$75, 23, FALSE) -> USA | BH53: =IF(D53="FLLO", TRUE,FALSE) -> FALSE | BI53: =IF(C53="Second Lien",TRUE,FALSE) -> FALSE | BJ53: =IF('Loan List '!BP42=1, TRUE, FALSE) -> FALSE | BK53: =IF(AR53>0%,TRUE,FALSE) -> FALSE | BL53: =OR(LEFT(CC53,1)="C", LEFT(CD53,1)="C") -> FALSE | BM53: =IF('Loan List '!AT42="Yes", TRUE, FALSE) -> FALSE | BN53: =-($BN$15-N53)/365 -> 5.1123288 | BO53: ='Concentration Limitations'!H48 -> 995000 | BP53: =IF(R53=$T$13,0,BO53*AL53) -> 646750 | BS53: ='Loan List '!AG42 -> 45747 | BT53: ='Loan List '!AO42 -> 2.5647097 | BU53: ='Loan List '!AI42 -> 3.9253893 | BW53: 0 | BX53: - | BY53: ='Loan List '!AJ42 -> 39.753 | BZ53: ='Loan List '!AL42 -> 0 | CA53: 0 | CB53: 0 | CC53: NR | CD53: NR | CE53: - | CF53: ='Loan List '!AC42 -> 3.2877656 | CG53: ='Loan List '!AD42 -> 2.3172601 | CI53: 0 | CJ53: - | CK53: ='Loan List '!AB42 -> 22.439 | CL53: ='Loan List '!AE42 -> 0 | CM53: 0 | CN53: 0 | CO53: NR | CP53: NR | CQ53: =IFERROR(($BT53-$CF53)/$CF53,0) -> -0.21992319 | CR53: =IFERROR(($BU53-$CG53)/$CG53,0) -> 0.69397869 | CS53: =BU53-CG53 -> 1.6081292 | CT53: =(BY53/CK53)-1 -> 0.77160301 | CU53: =IF(OR($CQ53<'Summary '!$I$47,$BT53<'Summary '!$I$46),1,0) -> 1 | CV53: =IF(OR($CS53>='Summary '!$I$50, (AND(BU53>'Summary '!$I$52, Calcs!CR53> 'Summary '!$I$51))),1,0) -> 1 | CW53: =IF(OR(SUM(CU53:CV53)>=1,CX53="Yes"),1,0) -> 1 | CX53: No | CY53: No | CZ53: No | DD53: 0 | DE53: 0 | DI53: =IF(L53<90%,"Not Eligible","Eligible") -> Eligible | DJ53: =IF(OR(BF53="USD",BF53="CAD",BF53="EUR",BF53="GBP",BF53="AUD"),"Eligible","Not Eligible") -> Eligible | DK53: Eligible | DL53: Eligible | DM53: =IF(BM53="FALSE",IF(BY53<5,"Not Eligible","Eligible"),"Eligible") -> Eligible | DN53: =IF(AW53=TRUE,IF(AU53>=3%,"Eligible","Not Eligible"),"Not PIK") -> Not PIK | DO53: No | DP53: =IF(OR(DK53="Not Eligible",DL53="Not Eligible",DI53="Not Eligible",DJ53="Not Eligible",DM53="Not Eligible",DN53="Not Eligible",DO53="Yes"),"NO","YES") -> YES
A54: PL Acquisitionco, LLC | B54: =IFERROR(VLOOKUP(A54,'Loan List '!$A$6:$BZ$75,2,FALSE),NA) -> 0 | C54: =VLOOKUP(A54,'Loan List '!$A$6:$G$75, 7, FALSE) -> First Lien | D54: =VLOOKUP(A54, 'Loan List '!$A$6:$K$82, 11, FALSE) -> FL | E54: =IF(DP54= "YES", TRUE, FALSE) -> TRUE | F54: =VLOOKUP(A54,'Loan List '!$A$6:$L$75, 12, FALSE) -> Specialty Retail | H54: =+I54 -> 8608914.5 | I54: =VLOOKUP(A54,'Loan List '!$A$6:$L$75, 8, FALSE) -> 8608914.5 | J54: 0 | K54: =I54/$I$15 -> 0.023829587 | L54: =VLOOKUP(A54,'Loan List '!$A$6:$BA$82,24, FALSE) -> 100 | N54: =VLOOKUP(A54,'Loan List '!$A$6:$BA$82,22, FALSE) -> 46700 | O54: =IFERROR(MAX(0,I54-J54)*L54,"")/100 -> 8608914.5 | P54: =MIN(IF(AND(L54>=97%,Q54="Primary"),100%,L54),T54) -> 0 | Q54: Primary | R54: SETTLED | S54: =IF(OR(CU54=1,CV54=1,CW54=1),TRUE,FALSE) -> TRUE | T54: =VLOOKUP(A54,'Loan List '!$A$6:$BD$1048576,56,FALSE)/100 -> 0 | U54: =IF(E54=TRUE,P54*I54,0) -> 0 | V54: =VLOOKUP(A54,'Loan List '!$A$6:$BA$82,26, FALSE) -> 0 | W54: =V54*I54 -> 0 | Y54: =VLOOKUP(A54,'Loan List '!$A$6:$BA$75,27, FALSE) -> 0 | AB54: =K54*BU54 -> -0.32225425 | AC54: =K54*AL54 -> 0.005190574 | AD54: =BW54 -> 0 | AE54: =IF(CK54>=$C$5,"Class 1",IF(CK54>=$D$5,"Class 2",IF(CK54>=$E$5,"Class 3","Class 4"))) -> Class 2 | AF54: =HLOOKUP($AE54,$B$3:$F$10,4,0) -> 5.5 | AG54: =IF(BB54,1,0)+HLOOKUP($AE54,$B$3:$F$10,5,0) -> 6.5 | AH54: =MIN(AF54/BU54,1) -> -0.40670596 | AI54: =IF(BU54>AG54,(AG54-AF54)/BU54,1-AH54) -> 1.406706 | AJ54: =HLOOKUP($AE54,$B$3:$F$10,6,0) -> 0.675 | AK54: =HLOOKUP($AE54,$B$3:$F$10,8,0) -> 0.35 | AL54: =IF(OR(BI54, AND(BH54,AD54>1)), HLOOKUP(AE54,$B$3:$F$10,8,0),AH54*AJ54+AI54*AK54) -> 0.21782056 | AM54: ='Diversity Score'!$E$7 -> 1 | AN54: =AM54*AL54 -> 0.21782056 | AO54: =VLOOKUP(A54,'Loan List '!$A$6:$BA$75,17, FALSE) -> 0.0725 | AP54: =VLOOKUP(A54,'Loan List '!$A$6:$BA$795,15, FALSE) -> SOFR | AQ54: =VLOOKUP(A54,'Loan List '!$A$6:$BA$795,16, FALSE) -> 0.01 | AR54: 0 | AS54: 0.07 | AU54: =AO54-AS54 -> 0.0025 | AV54: =IF(AND(AS54>0%,AU54>4.5%),TRUE,FALSE) -> FALSE | AW54: =IF(AND(AS54>0%,AU54>=2.25%, AV54=FALSE),TRUE,FALSE) -> FALSE | AX54: =IF(AND(AS54>0%,AW54=FALSE, AV54=FALSE),TRUE, FALSE) -> TRUE | AZ54: =(OR(CC54<>"NR",CD54<>"NR")) -> FALSE | BA54: ='Loan List '!AS43 -> Maintenance Covenants | BB54: =IF(D54="FL",FALSE,TRUE) -> FALSE | BC54: =IF(BU54>5.5, TRUE, FALSE) -> FALSE | BD54: =IF(BF54="USD", TRUE,FALSE) -> TRUE | BE54: =IF(BG54="USA",TRUE,FALSE) -> TRUE | BF54: ='Loan List '!J43 -> USD | BG54: =VLOOKUP(A54,'Loan List '!$A$6:$BZ$75, 23, FALSE) -> USA | BH54: =IF(D54="FLLO", TRUE,FALSE) -> FALSE | BI54: =IF(C54="Second Lien",TRUE,FALSE) -> FALSE | BJ54: =IF('Loan List '!BP43=1, TRUE, FALSE) -> FALSE | BK54: =IF(AR54>0%,TRUE,FALSE) -> FALSE | BL54: =OR(LEFT(CC54,1)="C", LEFT(CD54,1)="C") -> FALSE | BM54: =IF('Loan List '!AT43="Yes", TRUE, FALSE) -> FALSE | BN54: =-($BN$15-N54)/365 -> 2.2931507 | BO54: ='Concentration Limitations'!H49 -> 0 | BP54: =IF(R54=$T$13,0,BO54*AL54) -> 0 | BS54: ='Loan List '!AG43 -> 45777 | BT54: ='Loan List '!AO43 -> -0.54890068 | BU54: ='Loan List '!AI43 -> -13.523283 | BW54: 0 | BX54: - | BY54: ='Loan List '!AJ43 -> -5.068 | BZ54: ='Loan List '!AL43 -> 0 | CA54: 0 | CB54: 0 | CC54: NR | CD54: NR | CE54: - | CF54: ='Loan List '!AC43 -> 4.7335444 | CG54: ='Loan List '!AD43 -> 2.8595157 | CI54: 0 | CJ54: - | CK54: ='Loan List '!AB43 -> 26.626187 | CL54: ='Loan List '!AE43 -> 0 | CM54: 0 | CN54: 0 | CO54: NR | CP54: NR | CQ54: =IFERROR(($BT54-$CF54)/$CF54,0) -> -1.1159598 | CR54: =IFERROR(($BU54-$CG54)/$CG54,0) -> -5.7292216 | CS54: =BU54-CG54 -> -16.382799 | CT54: =(BY54/CK54)-1 -> -1.1903389 | CU54: =IF(OR($CQ54<'Summary '!$I$47,$BT54<'Summary '!$I$46),1,0) -> 1 | CV54: =IF(OR($CS54>='Summary '!$I$50, (AND(BU54>'Summary '!$I$52, Calcs!CR54> 'Summary '!$I$51))),1,0) -> 0 | CW54: =IF(OR(SUM(CU54:CV54)>=1,CX54="Yes"),1,0) -> 1 | CX54: No | CY54: No | CZ54: Yes | DA54: 0.07 | DD54: 0 | DE54: 0 | DI54: =IF(L54<90%,"Not Eligible","Eligible") -> Eligible | DJ54: =IF(OR(BF54="USD",BF54="CAD",BF54="EUR",BF54="GBP",BF54="AUD"),"Eligible","Not Eligible") -> Eligible | DK54: Eligible | DL54: Eligible | DM54: =IF(BM54="FALSE",IF(BY54<5,"Not Eligible","Eligible"),"Eligible") -> Eligible | DN54: =IF(AW54=TRUE,IF(AU54>=3%,"Eligible","Not Eligible"),"Not PIK") -> Not PIK | DO54: No | DP54: =IF(OR(DK54="Not Eligible",DL54="Not Eligible",DI54="Not Eligible",DJ54="Not Eligible",DM54="Not Eligible",DN54="Not Eligible",DO54="Yes"),"NO","YES") -> YES
A55: Radius Aerospace | B55: =IFERROR(VLOOKUP(A55,'Loan List '!$A$6:$BZ$75,2,FALSE),NA) -> 0 | C55: =VLOOKUP(A55,'Loan List '!$A$6:$G$75, 7, FALSE) -> First Lien | D55: =VLOOKUP(A55, 'Loan List '!$A$6:$K$82, 11, FALSE) -> FL | E55: =IF(DP55= "YES", TRUE, FALSE) -> TRUE | F55: =VLOOKUP(A55,'Loan List '!$A$6:$L$75, 12, FALSE) -> Aerospace & Defense | H55: =+I55 -> 11810532 | I55: =VLOOKUP(A55,'Loan List '!$A$6:$L$75, 8, FALSE) -> 11810532 | J55: 0 | K55: =I55/$I$15 -> 0.032691706 | L55: =VLOOKUP(A55,'Loan List '!$A$6:$BA$82,24, FALSE) -> 100 | N55: =VLOOKUP(A55,'Loan List '!$A$6:$BA$82,22, FALSE) -> 46475 | O55: =IFERROR(MAX(0,I55-J55)*L55,"")/100 -> 11810532 | P55: =MIN(IF(AND(L55>=97%,Q55="Primary"),100%,L55),T55) -> 1 | Q55: Primary | R55: SETTLED | S55: =IF(OR(CU55=1,CV55=1,CW55=1),TRUE,FALSE) -> TRUE | T55: =VLOOKUP(A55,'Loan List '!$A$6:$BD$1048576,56,FALSE)/100 -> 1 | U55: =IF(E55=TRUE,P55*I55,0) -> 11810532 | V55: =VLOOKUP(A55,'Loan List '!$A$6:$BA$82,26, FALSE) -> 0 | W55: =V55*I55 -> 0 | Y55: =VLOOKUP(A55,'Loan List '!$A$6:$BA$75,27, FALSE) -> 0 | AB55: =K55*BU55 -> 0.177902 | AC55: =K55*AL55 -> 0.020453359 | AD55: =BW55 -> 0 | AE55: =IF(CK55>=$C$5,"Class 1",IF(CK55>=$D$5,"Class 2",IF(CK55>=$E$5,"Class 3","Class 4"))) -> Class 3 | AF55: =HLOOKUP($AE55,$B$3:$F$10,4,0) -> 5 | AG55: =IF(BB55,1,0)+HLOOKUP($AE55,$B$3:$F$10,5,0) -> 6 | AH55: =MIN(AF55/BU55,1) -> 0.9188122 | AI55: =IF(BU55>AG55,(AG55-AF55)/BU55,1-AH55) -> 0.081187802 | AJ55: =HLOOKUP($AE55,$B$3:$F$10,6,0) -> 0.65 | AK55: =HLOOKUP($AE55,$B$3:$F$10,8,0) -> 0.35 | AL55: =IF(OR(BI55, AND(BH55,AD55>1)), HLOOKUP(AE55,$B$3:$F$10,8,0),AH55*AJ55+AI55*AK55) -> 0.62564366 | AM55: ='Diversity Score'!$E$7 -> 1 | AN55: =AM55*AL55 -> 0.62564366 | AO55: =VLOOKUP(A55,'Loan List '!$A$6:$BA$75,17, FALSE) -> 0.0615 | AP55: =VLOOKUP(A55,'Loan List '!$A$6:$BA$795,15, FALSE) -> SOFR | AQ55: =VLOOKUP(A55,'Loan List '!$A$6:$BA$795,16, FALSE) -> 0.01 | AR55: 0 | AS55: 0 | AU55: =AO55-AS55 -> 0.0615 | AV55: =IF(AND(AS55>0%,AU55>4.5%),TRUE,FALSE) -> FALSE | AW55: =IF(AND(AS55>0%,AU55>=2.25%, AV55=FALSE),TRUE,FALSE) -> FALSE | AX55: =IF(AND(AS55>0%,AW55=FALSE, AV55=FALSE),TRUE, FALSE) -> FALSE | AZ55: =(OR(CC55<>"NR",CD55<>"NR")) -> FALSE | BA55: ='Loan List '!AS44 -> Maintenance Covenants | BB55: =IF(D55="FL",FALSE,TRUE) -> FALSE | BC55: =IF(BU55>5.5, TRUE, FALSE) -> FALSE | BD55: =IF(BF55="USD", TRUE,FALSE) -> TRUE | BE55: =IF(BG55="USA",TRUE,FALSE) -> TRUE | BF55: ='Loan List '!J44 -> USD | BG55: =VLOOKUP(A55,'Loan List '!$A$6:$BZ$75, 23, FALSE) -> USA | BH55: =IF(D55="FLLO", TRUE,FALSE) -> FALSE | BI55: =IF(C55="Second Lien",TRUE,FALSE) -> FALSE | BJ55: =IF('Loan List '!BP44=1, TRUE, FALSE) -> FALSE | BK55: =IF(AR55>0%,TRUE,FALSE) -> FALSE | BL55: =OR(LEFT(CC55,1)="C", LEFT(CD55,1)="C") -> FALSE | BM55: =IF('Loan List '!AT44="Yes", TRUE, FALSE) -> FALSE | BN55: =-($BN$15-N55)/365 -> 1.6767123 | BO55: ='Concentration Limitations'!H50 -> 11810532 | BP55: =IF(R55=$T$13,0,BO55*AL55) -> 7389184.6 | BS55: ='Loan List '!AG44 -> 45777 | BT55: ='Loan List '!AO44 -> 1.3522002 | BU55: ='Loan List '!AI44 -> 5.4418085 | BW55: 0 | BX55: - | BY55: ='Loan List '!AJ44 -> 24.153 | BZ55: ='Loan List '!AL44 -> 0 | CA55: 0 | CB55: 0 | CC55: NR | CD55: NR | CE55: - | CF55: ='Loan List '!AC44 -> 2.560104 | CG55: ='Loan List '!AD44 -> 4.5685279 | CI55: 0 | CJ55: - | CK55: ='Loan List '!AB44 -> 19.7 | CL55: ='Loan List '!AE44 -> 0 | CM55: 0 | CN55: 0 | CO55: NR | CP55: NR | CQ55: =IFERROR(($BT55-$CF55)/$CF55,0) -> -0.47181825 | CR55: =IFERROR(($BU55-$CG55)/$CG55,0) -> 0.19115141 | CS55: =BU55-CG55 -> 0.87328055 | CT55: =(BY55/CK55)-1 -> 0.22604061 | CU55: =IF(OR($CQ55<'Summary '!$I$47,$BT55<'Summary '!$I$46),1,0) -> 1 | CV55: =IF(OR($CS55>='Summary '!$I$50, (AND(BU55>'Summary '!$I$52, Calcs!CR55> 'Summary '!$I$51))),1,0) -> 0 | CW55: =IF(OR(SUM(CU55:CV55)>=1,CX55="Yes"),1,0) -> 1 | CX55: No | CY55: No | CZ55: No | DD55: 0 | DE55: 0 | DI55: =IF(L55<90%,"Not Eligible","Eligible") -> Eligible | DJ55: =IF(OR(BF55="USD",BF55="CAD",BF55="EUR",BF55="GBP",BF55="AUD"),"Eligible","Not Eligible") -> Eligible | DK55: Eligible | DL55: Eligible | DM55: =IF(BM55="FALSE",IF(BY55<5,"Not Eligible","Eligible"),"Eligible") -> Eligible | DN55: =IF(AW55=TRUE,IF(AU55>=3%,"Eligible","Not Eligible"),"Not PIK") -> Not PIK | DO55: No | DP55: =IF(OR(DK55="Not Eligible",DL55="Not Eligible",DI55="Not Eligible",DJ55="Not Eligible",DM55="Not Eligible",DN55="Not Eligible",DO55="Yes"),"NO","YES") -> YES
A56: Rancho Medical | B56: =IFERROR(VLOOKUP(A56,'Loan List '!$A$6:$BZ$75,2,FALSE),NA) -> 0 | C56: =VLOOKUP(A56,'Loan List '!$A$6:$G$75, 7, FALSE) -> First Lien | D56: =VLOOKUP(A56, 'Loan List '!$A$6:$K$82, 11, FALSE) -> FL | E56: =IF(DP56= "YES", TRUE, FALSE) -> TRUE | F56: =VLOOKUP(A56,'Loan List '!$A$6:$L$75, 12, FALSE) -> Health Care Providers & Services | H56: =+I56 -> 17282079 | I56: =VLOOKUP(A56,'Loan List '!$A$6:$L$75, 8, FALSE) -> 17282079 | J56: 0 | K56: =I56/$I$15 -> 0.04783702 | L56: =VLOOKUP(A56,'Loan List '!$A$6:$BA$82,24, FALSE) -> 100 | N56: =VLOOKUP(A56,'Loan List '!$A$6:$BA$82,22, FALSE) -> 47289 | O56: =IFERROR(MAX(0,I56-J56)*L56,"")/100 -> 17282079 | P56: =MIN(IF(AND(L56>=97%,Q56="Primary"),100%,L56),T56) -> 1 | Q56: Primary | R56: SETTLED | S56: =IF(OR(CU56=1,CV56=1,CW56=1),TRUE,FALSE) -> FALSE | T56: =VLOOKUP(A56,'Loan List '!$A$6:$BD$1048576,56,FALSE)/100 -> 1 | U56: =IF(E56=TRUE,P56*I56,0) -> 17282079 | V56: =VLOOKUP(A56,'Loan List '!$A$6:$BA$82,26, FALSE) -> 0 | W56: =V56*I56 -> 0 | Y56: =VLOOKUP(A56,'Loan List '!$A$6:$BA$75,27, FALSE) -> 0 | AB56: =K56*BU56 -> 0.1637964 | AC56: =K56*AL56 -> 0.031094063 | AD56: =BW56 -> 0 | AE56: =IF(CK56>=$C$5,"Class 1",IF(CK56>=$D$5,"Class 2",IF(CK56>=$E$5,"Class 3","Class 4"))) -> Class 3 | AF56: =HLOOKUP($AE56,$B$3:$F$10,4,0) -> 5 | AG56: =IF(BB56,1,0)+HLOOKUP($AE56,$B$3:$F$10,5,0) -> 6 | AH56: =MIN(AF56/BU56,1) -> 1 | AI56: =IF(BU56>AG56,(AG56-AF56)/BU56,1-AH56) -> 0 | AJ56: =HLOOKUP($AE56,$B$3:$F$10,6,0) -> 0.65 | AK56: =HLOOKUP($AE56,$B$3:$F$10,8,0) -> 0.35 | AL56: =IF(OR(BI56, AND(BH56,AD56>1)), HLOOKUP(AE56,$B$3:$F$10,8,0),AH56*AJ56+AI56*AK56) -> 0.65 | AM56: ='Diversity Score'!$E$7 -> 1 | AN56: =AM56*AL56 -> 0.65 | AO56: =VLOOKUP(A56,'Loan List '!$A$6:$BA$75,17, FALSE) -> 0.0525 | AP56: =VLOOKUP(A56,'Loan List '!$A$6:$BA$795,15, FALSE) -> SOFR | AQ56: =VLOOKUP(A56,'Loan List '!$A$6:$BA$795,16, FALSE) -> 0.01 | AR56: 0 | AS56: 0 | AU56: =AO56-AS56 -> 0.0525 | AV56: =IF(AND(AS56>0%,AU56>4.5%),TRUE,FALSE) -> FALSE | AW56: =IF(AND(AS56>0%,AU56>=2.25%, AV56=FALSE),TRUE,FALSE) -> FALSE | AX56: =IF(AND(AS56>0%,AW56=FALSE, AV56=FALSE),TRUE, FALSE) -> FALSE | AZ56: =(OR(CC56<>"NR",CD56<>"NR")) -> FALSE | BA56: ='Loan List '!AS45 -> Maintenance Covenants | BB56: =IF(D56="FL",FALSE,TRUE) -> FALSE | BC56: =IF(BU56>5.5, TRUE, FALSE) -> FALSE | BD56: =IF(BF56="USD", TRUE,FALSE) -> TRUE | BE56: =IF(BG56="USA",TRUE,FALSE) -> TRUE | BF56: ='Loan List '!J45 -> USD | BG56: =VLOOKUP(A56,'Loan List '!$A$6:$BZ$75, 23, FALSE) -> USA | BH56: =IF(D56="FLLO", TRUE,FALSE) -> FALSE | BI56: =IF(C56="Second Lien",TRUE,FALSE) -> FALSE | BJ56: =IF('Loan List '!BP45=1, TRUE, FALSE) -> FALSE | BK56: =IF(AR56>0%,TRUE,FALSE) -> FALSE | BL56: =OR(LEFT(CC56,1)="C", LEFT(CD56,1)="C") -> FALSE | BM56: =IF('Loan List '!AT45="Yes", TRUE, FALSE) -> FALSE | BN56: =-($BN$15-N56)/365 -> 3.9068493 | BO56: ='Concentration Limitations'!H51 -> 17282079 | BP56: =IF(R56=$T$13,0,BO56*AL56) -> 11233352 | BS56: ='Loan List '!AG45 -> 45777 | BT56: ='Loan List '!AO45 -> 2.5217708 | BU56: ='Loan List '!AI45 -> 3.4240511 | BW56: 0 | BX56: - | BY56: ='Loan List '!AJ45 -> 19.015552 | BZ56: ='Loan List '!AL45 -> 0 | CA56: 0 | CB56: 0 | CC56: NR | CD56: NR | CE56: - | CF56: ='Loan List '!AC45 -> 2.5001806 | CG56: ='Loan List '!AD45 -> 3.3033463 | CI56: 0 | CJ56: - | CK56: ='Loan List '!AB45 -> 17.41303 | CL56: ='Loan List '!AE45 -> 0 | CM56: 0 | CN56: 0 | CO56: NR | CP56: NR | CQ56: =IFERROR(($BT56-$CF56)/$CF56,0) -> 0.0086354346 | CR56: =IFERROR(($BU56-$CG56)/$CG56,0) -> 0.036540177 | CS56: =BU56-CG56 -> 0.12070486 | CT56: =(BY56/CK56)-1 -> 0.092030065 | CU56: =IF(OR($CQ56<'Summary '!$I$47,$BT56<'Summary '!$I$46),1,0) -> 0 | CV56: =IF(OR($CS56>='Summary '!$I$50, (AND(BU56>'Summary '!$I$52, Calcs!CR56> 'Summary '!$I$51))),1,0) -> 0 | CW56: =IF(OR(SUM(CU56:CV56)>=1,CX56="Yes"),1,0) -> 0 | CX56: No | CY56: No | CZ56: No | DD56: 0 | DE56: 0 | DI56: =IF(L56<90%,"Not Eligible","Eligible") -> Eligible | DJ56: =IF(OR(BF56="USD",BF56="CAD",BF56="EUR",BF56="GBP",BF56="AUD"),"Eligible","Not Eligible") -> Eligible | DK56: Eligible | DL56: Eligible | DM56: =IF(BM56="FALSE",IF(BY56<5,"Not Eligible","Eligible"),"Eligible") -> Eligible | DN56: =IF(AW56=TRUE,IF(AU56>=3%,"Eligible","Not Eligible"),"Not PIK") -> Not PIK | DO56: No | DP56: =IF(OR(DK56="Not Eligible",DL56="Not Eligible",DI56="Not Eligible",DJ56="Not Eligible",DM56="Not Eligible",DN56="Not Eligible",DO56="Yes"),"NO","YES") -> YES
A57: Reception Purchaser, LLC -First Out Term loan | B57: =IFERROR(VLOOKUP(A57,'Loan List '!$A$6:$BZ$75,2,FALSE),NA) -> 0 | C57: =VLOOKUP(A57,'Loan List '!$A$6:$G$75, 7, FALSE) -> First Lien | D57: =VLOOKUP(A57, 'Loan List '!$A$6:$K$82, 11, FALSE) -> FL | E57: =IF(DP57= "YES", TRUE, FALSE) -> TRUE | F57: =VLOOKUP(A57,'Loan List '!$A$6:$L$75, 12, FALSE) -> Air Freight & Logistics | H57: =+I57 -> 1429975.8 | I57: =VLOOKUP(A57,'Loan List '!$A$6:$L$75, 8, FALSE) -> 1429975.8 | J57: 0 | K57: =I57/$I$15 -> 0.0039581915 | L57: =VLOOKUP(A57,'Loan List '!$A$6:$BA$82,24, FALSE) -> 92.5466 | N57: =VLOOKUP(A57,'Loan List '!$A$6:$BA$82,22, FALSE) -> 47395 | O57: =IFERROR(MAX(0,I57-J57)*L57,"")/100 -> 1323394 | P57: =MIN(IF(AND(L57>=97%,Q57="Primary"),100%,L57),T57) -> 0 | Q57: Primary | R57: SETTLED | S57: =IF(OR(CU57=1,CV57=1,CW57=1),TRUE,FALSE) -> TRUE | T57: =VLOOKUP(A57,'Loan List '!$A$6:$BD$1048576,56,FALSE)/100 -> 0 | U57: =IF(E57=TRUE,P57*I57,0) -> 0 | V57: =VLOOKUP(A57,'Loan List '!$A$6:$BA$82,26, FALSE) -> 0 | W57: =V57*I57 -> 0 | Y57: =VLOOKUP(A57,'Loan List '!$A$6:$BA$75,27, FALSE) -> 0 | AB57: =K57*BU57 -> -0.40477429 | AC57: =K57*AL57 -> 0.0013161797 | AD57: =BW57 -> 0 | AE57: =IF(CK57>=$C$5,"Class 1",IF(CK57>=$D$5,"Class 2",IF(CK57>=$E$5,"Class 3","Class 4"))) -> Class 2 | AF57: =HLOOKUP($AE57,$B$3:$F$10,4,0) -> 5.5 | AG57: =IF(BB57,1,0)+HLOOKUP($AE57,$B$3:$F$10,5,0) -> 6.5 | AH57: =MIN(AF57/BU57,1) -> -0.053783191 | AI57: =IF(BU57>AG57,(AG57-AF57)/BU57,1-AH57) -> 1.0537832 | AJ57: =HLOOKUP($AE57,$B$3:$F$10,6,0) -> 0.675 | AK57: =HLOOKUP($AE57,$B$3:$F$10,8,0) -> 0.35 | AL57: =IF(OR(BI57, AND(BH57,AD57>1)), HLOOKUP(AE57,$B$3:$F$10,8,0),AH57*AJ57+AI57*AK57) -> 0.33252046 | AM57: ='Diversity Score'!$E$7 -> 1 | AN57: =AM57*AL57 -> 0.33252046 | AO57: =VLOOKUP(A57,'Loan List '!$A$6:$BA$75,17, FALSE) -> 0.0835 | AP57: =VLOOKUP(A57,'Loan List '!$A$6:$BA$795,15, FALSE) -> SOFR | AQ57: =VLOOKUP(A57,'Loan List '!$A$6:$BA$795,16, FALSE) -> 0.01 | AR57: 0 | AS57: 0.0725 | AU57: =AO57-AS57 -> 0.011 | AV57: =IF(AND(AS57>0%,AU57>4.5%),TRUE,FALSE) -> FALSE | AW57: =IF(AND(AS57>0%,AU57>=2.25%, AV57=FALSE),TRUE,FALSE) -> FALSE | AX57: =IF(AND(AS57>0%,AW57=FALSE, AV57=FALSE),TRUE, FALSE) -> TRUE | AZ57: =(OR(CC57<>"NR",CD57<>"NR")) -> FALSE | BA57: ='Loan List '!AS46 -> Maintenance Covenants | BB57: =IF(D57="FL",FALSE,TRUE) -> FALSE | BC57: =IF(BU57>5.5, TRUE, FALSE) -> FALSE | BD57: =IF(BF57="USD", TRUE,FALSE) -> TRUE | BE57: =IF(BG57="USA",TRUE,FALSE) -> TRUE | BF57: ='Loan List '!J46 -> USD | BG57: =VLOOKUP(A57,'Loan List '!$A$6:$BZ$75, 23, FALSE) -> USA | BH57: =IF(D57="FLLO", TRUE,FALSE) -> FALSE | BI57: =IF(C57="Second Lien",TRUE,FALSE) -> FALSE | BJ57: =IF('Loan List '!BP46=1, TRUE, FALSE) -> FALSE | BK57: =IF(AR57>0%,TRUE,FALSE) -> FALSE | BL57: =OR(LEFT(CC57,1)="C", LEFT(CD57,1)="C") -> FALSE | BM57: =IF('Loan List '!AT46="Yes", TRUE, FALSE) -> FALSE | BN57: =-($BN$15-N57)/365 -> 4.1972603 | BO57: ='Concentration Limitations'!H52 -> 0 | BP57: =IF(R57=$T$13,0,BO57*AL57) -> 0 | BS57: ='Loan List '!AG46 -> 45747 | BT57: ='Loan List '!AO46 -> -0.076520968 | BU57: ='Loan List '!AI46 -> -102.26243 | BW57: 0 | BX57: - | BY57: ='Loan List '!AJ46 -> -9.149 | BZ57: ='Loan List '!AL46 -> 0 | CA57: 0 | CB57: 0 | CC57: NR | CD57: NR | CE57: - | CF57: ='Loan List '!AC46 -> 0.50393334 | CG57: ='Loan List '!AD46 -> 14.733233 | CI57: 0 | CJ57: - | CK57: ='Loan List '!AB46 -> 59.575 | CL57: ='Loan List '!AE46 -> 0 | CM57: 0 | CN57: 0 | CO57: NR | CP57: NR | CQ57: =IFERROR(($BT57-$CF57)/$CF57,0) -> -1.1518474 | CR57: =IFERROR(($BU57-$CG57)/$CG57,0) -> -7.9409364 | CS57: =BU57-CG57 -> -116.99567 | CT57: =(BY57/CK57)-1 -> -1.1535711 | CU57: =IF(OR($CQ57<'Summary '!$I$47,$BT57<'Summary '!$I$46),1,0) -> 1 | CV57: =IF(OR($CS57>='Summary '!$I$50, (AND(BU57>'Summary '!$I$52, Calcs!CR57> 'Summary '!$I$51))),1,0) -> 0 | CW57: =IF(OR(SUM(CU57:CV57)>=1,CX57="Yes"),1,0) -> 1 | CX57: No | CY57: No | CZ57: Yes | DA57: 0.0725 | DD57: 0 | DE57: 0 | DI57: =IF(L57<90%,"Not Eligible","Eligible") -> Eligible | DJ57: =IF(OR(BF57="USD",BF57="CAD",BF57="EUR",BF57="GBP",BF57="AUD"),"Eligible","Not Eligible") -> Eligible | DK57: Eligible | DL57: Eligible | DM57: =IF(BM57="FALSE",IF(BY57<5,"Not Eligible","Eligible"),"Eligible") -> Eligible | DN57: =IF(AW57=TRUE,IF(AU57>=3%,"Eligible","Not Eligible"),"Not PIK") -> Not PIK | DO57: No | DP57: =IF(OR(DK57="Not Eligible",DL57="Not Eligible",DI57="Not Eligible",DJ57="Not Eligible",DM57="Not Eligible",DN57="Not Eligible",DO57="Yes"),"NO","YES") -> YES
A58: Research Now Group, LLC and Dynata, LLC - First Out Term Loan | B58: =IFERROR(VLOOKUP(A58,'Loan List '!$A$6:$BZ$75,2,FALSE),NA) -> 0 | C58: =VLOOKUP(A58,'Loan List '!$A$6:$G$75, 7, FALSE) -> First Lien | D58: =VLOOKUP(A58, 'Loan List '!$A$6:$K$82, 11, FALSE) -> FL | E58: =IF(DP58= "YES", TRUE, FALSE) -> TRUE | F58: =VLOOKUP(A58,'Loan List '!$A$6:$L$75, 12, FALSE) -> Diversified Consumer Services | H58: =+I58 -> 1576230.8 | I58: =VLOOKUP(A58,'Loan List '!$A$6:$L$75, 8, FALSE) -> 1576230.8 | J58: 0 | K58: =I58/$I$15 -> 0.0043630273 | L58: =VLOOKUP(A58,'Loan List '!$A$6:$BA$82,24, FALSE) -> 100 | N58: =VLOOKUP(A58,'Loan List '!$A$6:$BA$82,22, FALSE) -> 46949 | O58: =IFERROR(MAX(0,I58-J58)*L58,"")/100 -> 1576230.8 | P58: =MIN(IF(AND(L58>=97%,Q58="Primary"),100%,L58),T58) -> 1 | Q58: Primary | R58: SETTLED | S58: =IF(OR(CU58=1,CV58=1,CW58=1),TRUE,FALSE) -> TRUE | T58: =VLOOKUP(A58,'Loan List '!$A$6:$BD$1048576,56,FALSE)/100 -> 1 | U58: =IF(E58=TRUE,P58*I58,0) -> 1576230.8 | V58: =VLOOKUP(A58,'Loan List '!$A$6:$BA$82,26, FALSE) -> 0 | W58: =V58*I58 -> 0 | Y58: =VLOOKUP(A58,'Loan List '!$A$6:$BA$75,27, FALSE) -> 0 | AB58: =K58*BU58 -> 0.02133578 | AC58: =K58*AL58 -> 0.0030541191 | AD58: =BW58 -> 0 | AE58: =IF(CK58>=$C$5,"Class 1",IF(CK58>=$D$5,"Class 2",IF(CK58>=$E$5,"Class 3","Class 4"))) -> Class 1 | AF58: =HLOOKUP($AE58,$B$3:$F$10,4,0) -> 6 | AG58: =IF(BB58,1,0)+HLOOKUP($AE58,$B$3:$F$10,5,0) -> 7 | AH58: =MIN(AF58/BU58,1) -> 1 | AI58: =IF(BU58>AG58,(AG58-AF58)/BU58,1-AH58) -> 0 | AJ58: =HLOOKUP($AE58,$B$3:$F$10,6,0) -> 0.7 | AK58: =HLOOKUP($AE58,$B$3:$F$10,8,0) -> 0.4 | AL58: =IF(OR(BI58, AND(BH58,AD58>1)), HLOOKUP(AE58,$B$3:$F$10,8,0),AH58*AJ58+AI58*AK58) -> 0.7 | AM58: ='Diversity Score'!$E$7 -> 1 | AN58: =AM58*AL58 -> 0.7 | AO58: =VLOOKUP(A58,'Loan List '!$A$6:$BA$75,17, FALSE) -> 0.0526 | AP58: =VLOOKUP(A58,'Loan List '!$A$6:$BA$795,15, FALSE) -> SOFR | AQ58: =VLOOKUP(A58,'Loan List '!$A$6:$BA$795,16, FALSE) -> 0.01 | AR58: 0 | AS58: 0 | AU58: =AO58-AS58 -> 0.0526 | AV58: =IF(AND(AS58>0%,AU58>4.5%),TRUE,FALSE) -> FALSE | AW58: =IF(AND(AS58>0%,AU58>=2.25%, AV58=FALSE),TRUE,FALSE) -> FALSE | AX58: =IF(AND(AS58>0%,AW58=FALSE, AV58=FALSE),TRUE, FALSE) -> FALSE | AZ58: =(OR(CC58<>"NR",CD58<>"NR")) -> FALSE | BA58: ='Loan List '!AS47 -> Cov-Lite | BB58: =IF(D58="FL",FALSE,TRUE) -> FALSE | BC58: =IF(BU58>5.5, TRUE, FALSE) -> FALSE | BD58: =IF(BF58="USD", TRUE,FALSE) -> TRUE | BE58: =IF(BG58="USA",TRUE,FALSE) -> TRUE | BF58: ='Loan List '!J47 -> USD | BG58: =VLOOKUP(A58,'Loan List '!$A$6:$BZ$75, 23, FALSE) -> USA | BH58: =IF(D58="FLLO", TRUE,FALSE) -> FALSE | BI58: =IF(C58="Second Lien",TRUE,FALSE) -> FALSE | BJ58: =IF('Loan List '!BP47=1, TRUE, FALSE) -> FALSE | BK58: =IF(AR58>0%,TRUE,FALSE) -> FALSE | BL58: =OR(LEFT(CC58,1)="C", LEFT(CD58,1)="C") -> FALSE | BM58: =IF('Loan List '!AT47="Yes", TRUE, FALSE) -> TRUE | BN58: =-($BN$15-N58)/365 -> 2.9753425 | BO58: ='Concentration Limitations'!H53 -> 1576230.8 | BP58: =IF(R58=$T$13,0,BO58*AL58) -> 1103361.6 | BS58: ='Loan List '!AG47 -> 45747 | BT58: ='Loan List '!AO47 -> 1.4486821 | BU58: ='Loan List '!AI47 -> 4.8901321 | BW58: 0 | BX58: - | BY58: ='Loan List '!AJ47 -> 150.153 | BZ58: ='Loan List '!AL47 -> 0 | CA58: 0 | CB58: 0 | CC58: NR | CD58: NR | CE58: - | CF58: ='Loan List '!AC47 -> 2.8116343 | CG58: ='Loan List '!AD47 -> 3.3596059 | CI58: 0 | CJ58: - | CK58: ='Loan List '!AB47 -> 203 | CL58: ='Loan List '!AE47 -> 0 | CM58: 0 | CN58: 0 | CO58: NR | CP58: NR | CQ58: =IFERROR(($BT58-$CF58)/$CF58,0) -> -0.48475445 | CR58: =IFERROR(($BU58-$CG58)/$CG58,0) -> 0.45556717 | CS58: =BU58-CG58 -> 1.5305262 | CT58: =(BY58/CK58)-1 -> -0.26033005 | CU58: =IF(OR($CQ58<'Summary '!$I$47,$BT58<'Summary '!$I$46),1,0) -> 1 | CV58: =IF(OR($CS58>='Summary '!$I$50, (AND(BU58>'Summary '!$I$52, Calcs!CR58> 'Summary '!$I$51))),1,0) -> 1 | CW58: =IF(OR(SUM(CU58:CV58)>=1,CX58="Yes"),1,0) -> 1 | CX58: No | CY58: No | CZ58: No | DD58: 0 | DE58: 0 | DI58: =IF(L58<90%,"Not Eligible","Eligible") -> Eligible | DJ58: =IF(OR(BF58="USD",BF58="CAD",BF58="EUR",BF58="GBP",BF58="AUD"),"Eligible","Not Eligible") -> Eligible | DK58: Eligible | DL58: Eligible | DM58: =IF(BM58="FALSE",IF(BY58<5,"Not Eligible","Eligible"),"Eligible") -> Eligible | DN58: =IF(AW58=TRUE,IF(AU58>=3%,"Eligible","Not Eligible"),"Not PIK") -> Not PIK | DO58: No | DP58: =IF(OR(DK58="Not Eligible",DL58="Not Eligible",DI58="Not Eligible",DJ58="Not Eligible",DM58="Not Eligible",DN58="Not Eligible",DO58="Yes"),"NO","YES") -> YES
A59: Research Now Group, LLC and Dynata, LLC-Last Out Term loan | B59: =IFERROR(VLOOKUP(A59,'Loan List '!$A$6:$BZ$75,2,FALSE),NA) -> 0 | C59: =VLOOKUP(A59,'Loan List '!$A$6:$G$75, 7, FALSE) -> First Lien | D59: =VLOOKUP(A59, 'Loan List '!$A$6:$K$82, 11, FALSE) -> FLLO | E59: =IF(DP59= "YES", TRUE, FALSE) -> TRUE | F59: =VLOOKUP(A59,'Loan List '!$A$6:$L$75, 12, FALSE) -> Diversified Consumer Services | H59: =+I59 -> 5725814.5 | I59: =VLOOKUP(A59,'Loan List '!$A$6:$L$75, 8, FALSE) -> 5725814.5 | J59: 0 | K59: =I59/$I$15 -> 0.015849129 | L59: =VLOOKUP(A59,'Loan List '!$A$6:$BA$82,24, FALSE) -> 100 | N59: =VLOOKUP(A59,'Loan List '!$A$6:$BA$82,22, FALSE) -> 47041 | O59: =IFERROR(MAX(0,I59-J59)*L59,"")/100 -> 5725814.5 | P59: =MIN(IF(AND(L59>=97%,Q59="Primary"),100%,L59),T59) -> 0.924 | Q59: Primary | R59: SETTLED | S59: =IF(OR(CU59=1,CV59=1,CW59=1),TRUE,FALSE) -> TRUE | T59: =VLOOKUP(A59,'Loan List '!$A$6:$BD$1048576,56,FALSE)/100 -> 0.924 | U59: =IF(E59=TRUE,P59*I59,0) -> 5290652.6 | V59: =VLOOKUP(A59,'Loan List '!$A$6:$BA$82,26, FALSE) -> 0 | W59: =V59*I59 -> 0 | Y59: =VLOOKUP(A59,'Loan List '!$A$6:$BA$75,27, FALSE) -> 0 | AB59: =K59*BU59 -> 0.077504332 | AC59: =K59*AL59 -> 0.01109439 | AD59: =BW59 -> 0 | AE59: =IF(CK59>=$C$5,"Class 1",IF(CK59>=$D$5,"Class 2",IF(CK59>=$E$5,"Class 3","Class 4"))) -> Class 1 | AF59: =HLOOKUP($AE59,$B$3:$F$10,4,0) -> 6 | AG59: =IF(BB59,1,0)+HLOOKUP($AE59,$B$3:$F$10,5,0) -> 8 | AH59: =MIN(AF59/BU59,1) -> 1 | AI59: =IF(BU59>AG59,(AG59-AF59)/BU59,1-AH59) -> 0 | AJ59: =HLOOKUP($AE59,$B$3:$F$10,6,0) -> 0.7 | AK59: =HLOOKUP($AE59,$B$3:$F$10,8,0) -> 0.4 | AL59: =IF(OR(BI59, AND(BH59,AD59>1)), HLOOKUP(AE59,$B$3:$F$10,8,0),AH59*AJ59+AI59*AK59) -> 0.7 | AM59: ='Diversity Score'!$E$7 -> 1 | AN59: =AM59*AL59 -> 0.7 | AO59: =VLOOKUP(A59,'Loan List '!$A$6:$BA$75,17, FALSE) -> 0.0576 | AP59: =VLOOKUP(A59,'Loan List '!$A$6:$BA$795,15, FALSE) -> SOFR | AQ59: =VLOOKUP(A59,'Loan List '!$A$6:$BA$795,16, FALSE) -> 0.01 | AR59: 0 | AS59: 0 | AU59: =AO59-AS59 -> 0.0576 | AV59: =IF(AND(AS59>0%,AU59>4.5%),TRUE,FALSE) -> FALSE | AW59: =IF(AND(AS59>0%,AU59>=2.25%, AV59=FALSE),TRUE,FALSE) -> FALSE | AX59: =IF(AND(AS59>0%,AW59=FALSE, AV59=FALSE),TRUE, FALSE) -> FALSE | AZ59: =(OR(CC59<>"NR",CD59<>"NR")) -> FALSE | BA59: ='Loan List '!AS48 -> Cov-Lite | BB59: =IF(D59="FL",FALSE,TRUE) -> TRUE | BC59: =IF(BU59>5.5, TRUE, FALSE) -> FALSE | BD59: =IF(BF59="USD", TRUE,FALSE) -> TRUE | BE59: =IF(BG59="USA",TRUE,FALSE) -> TRUE | BF59: ='Loan List '!J48 -> USD | BG59: =VLOOKUP(A59,'Loan List '!$A$6:$BZ$75, 23, FALSE) -> USA | BH59: =IF(D59="FLLO", TRUE,FALSE) -> FALSE | BI59: =IF(C59="Second Lien",TRUE,FALSE) -> FALSE | BJ59: =IF('Loan List '!BP48=1, TRUE, FALSE) -> FALSE | BK59: =IF(AR59>0%,TRUE,FALSE) -> FALSE | BL59: =OR(LEFT(CC59,1)="C", LEFT(CD59,1)="C") -> FALSE | BM59: =IF('Loan List '!AT48="Yes", TRUE, FALSE) -> TRUE | BN59: =-($BN$15-N59)/365 -> 3.2273973 | BO59: ='Concentration Limitations'!H54 -> 5290652.6 | BP59: =IF(R59=$T$13,0,BO59*AL59) -> 3703456.8 | BS59: ='Loan List '!AG48 -> 45747 | BT59: ='Loan List '!AO48 -> 1.4486821 | BU59: ='Loan List '!AI48 -> 4.8901321 | BW59: 0 | BX59: - | BY59: ='Loan List '!AJ48 -> 150.153 | BZ59: ='Loan List '!AL48 -> 0 | CA59: 0 | CB59: 0 | CC59: NR | CD59: NR | CE59: - | CF59: ='Loan List '!AC48 -> 2.8116343 | CG59: ='Loan List '!AD48 -> 3.3596059 | CI59: 0 | CJ59: - | CK59: ='Loan List '!AB48 -> 203 | CL59: ='Loan List '!AE48 -> 0 | CM59: 0 | CN59: 0 | CO59: NR | CP59: NR | CQ59: =IFERROR(($BT59-$CF59)/$CF59,0) -> -0.48475445 | CR59: =IFERROR(($BU59-$CG59)/$CG59,0) -> 0.45556717 | CS59: =BU59-CG59 -> 1.5305262 | CT59: =(BY59/CK59)-1 -> -0.26033005 | CU59: =IF(OR($CQ59<'Summary '!$I$47,$BT59<'Summary '!$I$46),1,0) -> 1 | CV59: =IF(OR($CS59>='Summary '!$I$50, (AND(BU59>'Summary '!$I$52, Calcs!CR59> 'Summary '!$I$51))),1,0) -> 1 | CW59: =IF(OR(SUM(CU59:CV59)>=1,CX59="Yes"),1,0) -> 1 | CX59: No | CY59: No | CZ59: No | DD59: 0 | DE59: 0 | DI59: =IF(L59<90%,"Not Eligible","Eligible") -> Eligible | DJ59: =IF(OR(BF59="USD",BF59="CAD",BF59="EUR",BF59="GBP",BF59="AUD"),"Eligible","Not Eligible") -> Eligible | DK59: Eligible | DL59: Eligible | DM59: =IF(BM59="FALSE",IF(BY59<5,"Not Eligible","Eligible"),"Eligible") -> Eligible | DN59: =IF(AW59=TRUE,IF(AU59>=3%,"Eligible","Not Eligible"),"Not PIK") -> Not PIK | DO59: No | DP59: =IF(OR(DK59="Not Eligible",DL59="Not Eligible",DI59="Not Eligible",DJ59="Not Eligible",DM59="Not Eligible",DN59="Not Eligible",DO59="Yes"),"NO","YES") -> YES
A60: RTIC subsidiary Holdings, LLC | B60: =IFERROR(VLOOKUP(A60,'Loan List '!$A$6:$BZ$75,2,FALSE),NA) -> 0 | C60: =VLOOKUP(A60,'Loan List '!$A$6:$G$75, 7, FALSE) -> First Lien | D60: =VLOOKUP(A60, 'Loan List '!$A$6:$K$82, 11, FALSE) -> FL | E60: =IF(DP60= "YES", TRUE, FALSE) -> TRUE | F60: =VLOOKUP(A60,'Loan List '!$A$6:$L$75, 12, FALSE) -> Leisure Products | H60: =+I60 -> 8862707.1 | I60: =VLOOKUP(A60,'Loan List '!$A$6:$L$75, 8, FALSE) -> 8862707.1 | J60: 0 | K60: =I60/$I$15 -> 0.024532088 | L60: =VLOOKUP(A60,'Loan List '!$A$6:$BA$82,24, FALSE) -> 100 | N60: =VLOOKUP(A60,'Loan List '!$A$6:$BA$82,22, FALSE) -> 47241 | O60: =IFERROR(MAX(0,I60-J60)*L60,"")/100 -> 8862707.1 | P60: =MIN(IF(AND(L60>=97%,Q60="Primary"),100%,L60),T60) -> 1 | Q60: Primary | R60: SETTLED | S60: =IF(OR(CU60=1,CV60=1,CW60=1),TRUE,FALSE) -> FALSE | T60: =VLOOKUP(A60,'Loan List '!$A$6:$BD$1048576,56,FALSE)/100 -> 1 | U60: =IF(E60=TRUE,P60*I60,0) -> 8862707.1 | V60: =VLOOKUP(A60,'Loan List '!$A$6:$BA$82,26, FALSE) -> 0 | W60: =V60*I60 -> 0 | Y60: =VLOOKUP(A60,'Loan List '!$A$6:$BA$75,27, FALSE) -> 0 | AB60: =K60*BU60 -> 0.10787126 | AC60: =K60*AL60 -> 0.01655916 | AD60: =BW60 -> 0 | AE60: =IF(CK60>=$C$5,"Class 1",IF(CK60>=$D$5,"Class 2",IF(CK60>=$E$5,"Class 3","Class 4"))) -> Class 2 | AF60: =HLOOKUP($AE60,$B$3:$F$10,4,0) -> 5.5 | AG60: =IF(BB60,1,0)+HLOOKUP($AE60,$B$3:$F$10,5,0) -> 6.5 | AH60: =MIN(AF60/BU60,1) -> 1 | AI60: =IF(BU60>AG60,(AG60-AF60)/BU60,1-AH60) -> 0 | AJ60: =HLOOKUP($AE60,$B$3:$F$10,6,0) -> 0.675 | AK60: =HLOOKUP($AE60,$B$3:$F$10,8,0) -> 0.35 | AL60: =IF(OR(BI60, AND(BH60,AD60>1)), HLOOKUP(AE60,$B$3:$F$10,8,0),AH60*AJ60+AI60*AK60) -> 0.675 | AM60: ='Diversity Score'!$E$7 -> 1 | AN60: =AM60*AL60 -> 0.675 | AO60: =VLOOKUP(A60,'Loan List '!$A$6:$BA$75,17, FALSE) -> 0.0575 | AP60: =VLOOKUP(A60,'Loan List '!$A$6:$BA$795,15, FALSE) -> SOFR | AQ60: =VLOOKUP(A60,'Loan List '!$A$6:$BA$795,16, FALSE) -> 0.01 | AR60: 0 | AS60: 0 | AU60: =AO60-AS60 -> 0.0575 | AV60: =IF(AND(AS60>0%,AU60>4.5%),TRUE,FALSE) -> FALSE | AW60: =IF(AND(AS60>0%,AU60>=2.25%, AV60=FALSE),TRUE,FALSE) -> FALSE | AX60: =IF(AND(AS60>0%,AW60=FALSE, AV60=FALSE),TRUE, FALSE) -> FALSE | AZ60: =(OR(CC60<>"NR",CD60<>"NR")) -> FALSE | BA60: ='Loan List '!AS49 -> Maintenance Covenants | BB60: =IF(D60="FL",FALSE,TRUE) -> FALSE | BC60: =IF(BU60>5.5, TRUE, FALSE) -> FALSE | BD60: =IF(BF60="USD", TRUE,FALSE) -> TRUE | BE60: =IF(BG60="USA",TRUE,FALSE) -> TRUE | BF60: ='Loan List '!J49 -> USD | BG60: =VLOOKUP(A60,'Loan List '!$A$6:$BZ$75, 23, FALSE) -> USA | BH60: =IF(D60="FLLO", TRUE,FALSE) -> FALSE | BI60: =IF(C60="Second Lien",TRUE,FALSE) -> FALSE | BJ60: =IF('Loan List '!BP49=1, TRUE, FALSE) -> FALSE | BK60: =IF(AR60>0%,TRUE,FALSE) -> FALSE | BL60: =OR(LEFT(CC60,1)="C", LEFT(CD60,1)="C") -> FALSE | BM60: =IF('Loan List '!AT49="Yes", TRUE, FALSE) -> FALSE | BN60: =-($BN$15-N60)/365 -> 3.7753425 | BO60: ='Concentration Limitations'!H55 -> 8862707.1 | BP60: =IF(R60=$T$13,0,BO60*AL60) -> 5982327.3 | BS60: ='Loan List '!AG49 -> 45777 | BT60: ='Loan List '!AO49 -> 1.8625228 | BU60: ='Loan List '!AI49 -> 4.3971494 | BW60: 0 | BX60: - | BY60: ='Loan List '!AJ49 -> 31.900468 | BZ60: ='Loan List '!AL49 -> 0 | CA60: 0 | CB60: 0 | CC60: NR | CD60: NR | CE60: - | CF60: ='Loan List '!AC49 -> 1.75 | CG60: ='Loan List '!AD49 -> 3.92 | CI60: 0 | CJ60: - | CK60: ='Loan List '!AB49 -> 30.58 | CL60: ='Loan List '!AE49 -> 0 | CM60: 0 | CN60: 0 | CO60: NR | CP60: NR | CQ60: =IFERROR(($BT60-$CF60)/$CF60,0) -> 0.064298753 | CR60: =IFERROR(($BU60-$CG60)/$CG60,0) -> 0.12172178 | CS60: =BU60-CG60 -> 0.47714936 | CT60: =(BY60/CK60)-1 -> 0.04318077 | CU60: =IF(OR($CQ60<'Summary '!$I$47,$BT60<'Summary '!$I$46),1,0) -> 0 | CV60: =IF(OR($CS60>='Summary '!$I$50, (AND(BU60>'Summary '!$I$52, Calcs!CR60> 'Summary '!$I$51))),1,0) -> 0 | CW60: =IF(OR(SUM(CU60:CV60)>=1,CX60="Yes"),1,0) -> 0 | CX60: No | CY60: No | CZ60: No | DD60: 0 | DE60: 0 | DI60: =IF(L60<90%,"Not Eligible","Eligible") -> Eligible | DJ60: =IF(OR(BF60="USD",BF60="CAD",BF60="EUR",BF60="GBP",BF60="AUD"),"Eligible","Not Eligible") -> Eligible | DK60: Eligible | DL60: Eligible | DM60: =IF(BM60="FALSE",IF(BY60<5,"Not Eligible","Eligible"),"Eligible") -> Eligible | DN60: =IF(AW60=TRUE,IF(AU60>=3%,"Eligible","Not Eligible"),"Not PIK") -> Not PIK | DO60: No | DP60: =IF(OR(DK60="Not Eligible",DL60="Not Eligible",DI60="Not Eligible",DJ60="Not Eligible",DM60="Not Eligible",DN60="Not Eligible",DO60="Yes"),"NO","YES") -> YES
A61: SV- Aero Holdings, LLC (Aeronix) | B61: =IFERROR(VLOOKUP(A61,'Loan List '!$A$6:$BZ$75,2,FALSE),NA) -> 0 | C61: =VLOOKUP(A61,'Loan List '!$A$6:$G$75, 7, FALSE) -> First Lien | D61: =VLOOKUP(A61, 'Loan List '!$A$6:$K$82, 11, FALSE) -> FL | E61: =IF(DP61= "YES", TRUE, FALSE) -> TRUE | F61: =VLOOKUP(A61,'Loan List '!$A$6:$L$75, 12, FALSE) -> Aerospace & Defense | H61: =+I61 -> 790000 | I61: =VLOOKUP(A61,'Loan List '!$A$6:$L$75, 8, FALSE) -> 790000 | J61: 0 | K61: =I61/$I$15 -> 0.0021867302 | L61: =VLOOKUP(A61,'Loan List '!$A$6:$BA$82,24, FALSE) -> 100 | N61: =VLOOKUP(A61,'Loan List '!$A$6:$BA$82,22, FALSE) -> 47788 | O61: =IFERROR(MAX(0,I61-J61)*L61,"")/100 -> 790000 | P61: =MIN(IF(AND(L61>=97%,Q61="Primary"),100%,L61),T61) -> 1 | Q61: Primary | R61: SETTLED | S61: =IF(OR(CU61=1,CV61=1,CW61=1),TRUE,FALSE) -> TRUE | T61: =VLOOKUP(A61,'Loan List '!$A$6:$BD$1048576,56,FALSE)/100 -> 1 | U61: =IF(E61=TRUE,P61*I61,0) -> 790000 | V61: =VLOOKUP(A61,'Loan List '!$A$6:$BA$82,26, FALSE) -> 0 | W61: =V61*I61 -> 0 | Y61: =VLOOKUP(A61,'Loan List '!$A$6:$BA$75,27, FALSE) -> 0 | AB61: =K61*BU61 -> 0.0061500733 | AC61: =K61*AL61 -> 0.0014760429 | AD61: =BW61 -> 0 | AE61: =IF(CK61>=$C$5,"Class 1",IF(CK61>=$D$5,"Class 2",IF(CK61>=$E$5,"Class 3","Class 4"))) -> Class 2 | AF61: =HLOOKUP($AE61,$B$3:$F$10,4,0) -> 5.5 | AG61: =IF(BB61,1,0)+HLOOKUP($AE61,$B$3:$F$10,5,0) -> 6.5 | AH61: =MIN(AF61/BU61,1) -> 1 | AI61: =IF(BU61>AG61,(AG61-AF61)/BU61,1-AH61) -> 0 | AJ61: =HLOOKUP($AE61,$B$3:$F$10,6,0) -> 0.675 | AK61: =HLOOKUP($AE61,$B$3:$F$10,8,0) -> 0.35 | AL61: =IF(OR(BI61, AND(BH61,AD61>1)), HLOOKUP(AE61,$B$3:$F$10,8,0),AH61*AJ61+AI61*AK61) -> 0.675 | AM61: ='Diversity Score'!$E$7 -> 1 | AN61: =AM61*AL61 -> 0.675 | AO61: =VLOOKUP(A61,'Loan List '!$A$6:$BA$75,17, FALSE) -> 0.0525 | AP61: =VLOOKUP(A61,'Loan List '!$A$6:$BA$795,15, FALSE) -> SOFR | AQ61: =VLOOKUP(A61,'Loan List '!$A$6:$BA$795,16, FALSE) -> 0.01 | AR61: 0 | AS61: 0 | AU61: =AO61-AS61 -> 0.0525 | AV61: =IF(AND(AS61>0%,AU61>4.5%),TRUE,FALSE) -> FALSE | AW61: =IF(AND(AS61>0%,AU61>=2.25%, AV61=FALSE),TRUE,FALSE) -> FALSE | AX61: =IF(AND(AS61>0%,AW61=FALSE, AV61=FALSE),TRUE, FALSE) -> FALSE | AZ61: =(OR(CC61<>"NR",CD61<>"NR")) -> FALSE | BA61: ='Loan List '!AS50 -> Maintenance Covenants | BB61: =IF(D61="FL",FALSE,TRUE) -> FALSE | BC61: =IF(BU61>5.5, TRUE, FALSE) -> FALSE | BD61: =IF(BF61="USD", TRUE,FALSE) -> TRUE | BE61: =IF(BG61="USA",TRUE,FALSE) -> TRUE | BF61: ='Loan List '!J50 -> USD | BG61: =VLOOKUP(A61,'Loan List '!$A$6:$BZ$75, 23, FALSE) -> USA | BH61: =IF(D61="FLLO", TRUE,FALSE) -> FALSE | BI61: =IF(C61="Second Lien",TRUE,FALSE) -> FALSE | BJ61: =IF('Loan List '!BP50=1, TRUE, FALSE) -> FALSE | BK61: =IF(AR61>0%,TRUE,FALSE) -> FALSE | BL61: =OR(LEFT(CC61,1)="C", LEFT(CD61,1)="C") -> FALSE | BM61: =IF('Loan List '!AT50="Yes", TRUE, FALSE) -> FALSE | BN61: =-($BN$15-N61)/365 -> 5.2739726 | BO61: ='Concentration Limitations'!H56 -> 790000 | BP61: =IF(R61=$T$13,0,BO61*AL61) -> 533250 | BS61: ='Loan List '!AG50 -> 45747 | BT61: ='Loan List '!AO50 -> 3.2544514 | BU61: ='Loan List '!AI50 -> 2.8124518 | BW61: 0 | BX61: - | BY61: ='Loan List '!AJ50 -> 89.497414 | BZ61: ='Loan List '!AL50 -> 0 | CA61: 0 | CB61: 0 | CC61: NR | CD61: NR | CE61: - | CF61: ='Loan List '!AC50 -> 6.5855168 | CG61: ='Loan List '!AD50 -> 2.0735671 | CI61: 0 | CJ61: - | CK61: ='Loan List '!AB50 -> 35.323874 | CL61: ='Loan List '!AE50 -> 0 | CM61: 0 | CN61: 0 | CO61: NR | CP61: NR | CQ61: =IFERROR(($BT61-$CF61)/$CF61,0) -> -0.50581685 | CR61: =IFERROR(($BU61-$CG61)/$CG61,0) -> 0.35633505 | CS61: =BU61-CG61 -> 0.73888464 | CT61: =(BY61/CK61)-1 -> 1.533624 | CU61: =IF(OR($CQ61<'Summary '!$I$47,$BT61<'Summary '!$I$46),1,0) -> 1 | CV61: =IF(OR($CS61>='Summary '!$I$50, (AND(BU61>'Summary '!$I$52, Calcs!CR61> 'Summary '!$I$51))),1,0) -> 0 | CW61: =IF(OR(SUM(CU61:CV61)>=1,CX61="Yes"),1,0) -> 1 | CX61: No | CY61: No | CZ61: No | DD61: 0 | DE61: 0 | DI61: =IF(L61<90%,"Not Eligible","Eligible") -> Eligible | DJ61: =IF(OR(BF61="USD",BF61="CAD",BF61="EUR",BF61="GBP",BF61="AUD"),"Eligible","Not Eligible") -> Eligible | DK61: Eligible | DL61: Eligible | DM61: =IF(BM61="FALSE",IF(BY61<5,"Not Eligible","Eligible"),"Eligible") -> Eligible | DN61: =IF(AW61=TRUE,IF(AU61>=3%,"Eligible","Not Eligible"),"Not PIK") -> Not PIK | DO61: No | DP61: =IF(OR(DK61="Not Eligible",DL61="Not Eligible",DI61="Not Eligible",DJ61="Not Eligible",DM61="Not Eligible",DN61="Not Eligible",DO61="Yes"),"NO","YES") -> YES
A62: Sabel Systems Technology Solutions, LLC | B62: =IFERROR(VLOOKUP(A62,'Loan List '!$A$6:$BZ$75,2,FALSE),NA) -> 0 | C62: =VLOOKUP(A62,'Loan List '!$A$6:$G$75, 7, FALSE) -> First Lien | D62: =VLOOKUP(A62, 'Loan List '!$A$6:$K$82, 11, FALSE) -> FL | E62: =IF(DP62= "YES", TRUE, FALSE) -> TRUE | F62: =VLOOKUP(A62,'Loan List '!$A$6:$L$75, 12, FALSE) -> IT Services | H62: =+I62 -> 5970000 | I62: =VLOOKUP(A62,'Loan List '!$A$6:$L$75, 8, FALSE) -> 5970000 | J62: 0 | K62: =I62/$I$15 -> 0.016525037 | L62: =VLOOKUP(A62,'Loan List '!$A$6:$BA$82,24, FALSE) -> 100 | N62: =VLOOKUP(A62,'Loan List '!$A$6:$BA$82,22, FALSE) -> 47787 | O62: =IFERROR(MAX(0,I62-J62)*L62,"")/100 -> 5970000 | P62: =MIN(IF(AND(L62>=97%,Q62="Primary"),100%,L62),T62) -> 1 | Q62: Primary | R62: SETTLED | S62: =IF(OR(CU62=1,CV62=1,CW62=1),TRUE,FALSE) -> FALSE | T62: =VLOOKUP(A62,'Loan List '!$A$6:$BD$1048576,56,FALSE)/100 -> 1 | U62: =IF(E62=TRUE,P62*I62,0) -> 5970000 | V62: =VLOOKUP(A62,'Loan List '!$A$6:$BA$82,26, FALSE) -> 0 | W62: =V62*I62 -> 0 | Y62: =VLOOKUP(A62,'Loan List '!$A$6:$BA$75,27, FALSE) -> 0 | AB62: =K62*BU62 -> 0.056345414 | AC62: =K62*AL62 -> 0.010741274 | AD62: =BW62 -> 0 | AE62: =IF(CK62>=$C$5,"Class 1",IF(CK62>=$D$5,"Class 2",IF(CK62>=$E$5,"Class 3","Class 4"))) -> Class 3 | AF62: =HLOOKUP($AE62,$B$3:$F$10,4,0) -> 5 | AG62: =IF(BB62,1,0)+HLOOKUP($AE62,$B$3:$F$10,5,0) -> 6 | AH62: =MIN(AF62/BU62,1) -> 1 | AI62: =IF(BU62>AG62,(AG62-AF62)/BU62,1-AH62) -> 0 | AJ62: =HLOOKUP($AE62,$B$3:$F$10,6,0) -> 0.65 | AK62: =HLOOKUP($AE62,$B$3:$F$10,8,0) -> 0.35 | AL62: =IF(OR(BI62, AND(BH62,AD62>1)), HLOOKUP(AE62,$B$3:$F$10,8,0),AH62*AJ62+AI62*AK62) -> 0.65 | AM62: ='Diversity Score'!$E$7 -> 1 | AN62: =AM62*AL62 -> 0.65 | AO62: =VLOOKUP(A62,'Loan List '!$A$6:$BA$75,17, FALSE) -> 0.0625 | AP62: =VLOOKUP(A62,'Loan List '!$A$6:$BA$795,15, FALSE) -> SOFR | AQ62: =VLOOKUP(A62,'Loan List '!$A$6:$BA$795,16, FALSE) -> 0.01 | AR62: 0 | AS62: 0 | AU62: =AO62-AS62 -> 0.0625 | AV62: =IF(AND(AS62>0%,AU62>4.5%),TRUE,FALSE) -> FALSE | AW62: =IF(AND(AS62>0%,AU62>=2.25%, AV62=FALSE),TRUE,FALSE) -> FALSE | AX62: =IF(AND(AS62>0%,AW62=FALSE, AV62=FALSE),TRUE, FALSE) -> FALSE | AZ62: =(OR(CC62<>"NR",CD62<>"NR")) -> FALSE | BA62: ='Loan List '!AS51 -> Maintenance Covenants | BB62: =IF(D62="FL",FALSE,TRUE) -> FALSE | BC62: =IF(BU62>5.5, TRUE, FALSE) -> FALSE | BD62: =IF(BF62="USD", TRUE,FALSE) -> TRUE | BE62: =IF(BG62="USA",TRUE,FALSE) -> TRUE | BF62: ='Loan List '!J51 -> USD | BG62: =VLOOKUP(A62,'Loan List '!$A$6:$BZ$75, 23, FALSE) -> USA | BH62: =IF(D62="FLLO", TRUE,FALSE) -> FALSE | BI62: =IF(C62="Second Lien",TRUE,FALSE) -> FALSE | BJ62: =IF('Loan List '!BP51=1, TRUE, FALSE) -> FALSE | BK62: =IF(AR62>0%,TRUE,FALSE) -> FALSE | BL62: =OR(LEFT(CC62,1)="C", LEFT(CD62,1)="C") -> FALSE | BM62: =IF('Loan List '!AT51="Yes", TRUE, FALSE) -> FALSE | BN62: =-($BN$15-N62)/365 -> 5.2712329 | BO62: ='Concentration Limitations'!H57 -> 5970000 | BP62: =IF(R62=$T$13,0,BO62*AL62) -> 3880500 | BS62: ='Loan List '!AG51 -> 45808 | BT62: ='Loan List '!AO51 -> 5.750819 | BU62: ='Loan List '!AI51 -> 3.4096996 | BW62: 0 | BX62: - | BY62: ='Loan List '!AJ51 -> 25.770875 | BZ62: ='Loan List '!AL51 -> 0 | CA62: 0 | CB62: 0 | CC62: NR | CD62: NR | CE62: - | CF62: ='Loan List '!AC51 -> 2.1804545 | CG62: ='Loan List '!AD51 -> 3.5376566 | CI62: 0 | CJ62: - | CK62: ='Loan List '!AB51 -> 22.676727 | CL62: ='Loan List '!#REF! -> #REF! | CM62: 0 | CN62: 0 | CO62: NR | CP62: NR | CQ62: =IFERROR(($BT62-$CF62)/$CF62,0) -> 1.6374405 | CR62: =IFERROR(($BU62-$CG62)/$CG62,0) -> -0.036169969 | CS62: =BU62-CG62 -> -0.12795693 | CT62: =(BY62/CK62)-1 -> 0.13644596 | CU62: =IF(OR($CQ62<'Summary '!$I$47,$BT62<'Summary '!$I$46),1,0) -> 0 | CV62: =IF(OR($CS62>='Summary '!$I$50, (AND(BU62>'Summary '!$I$52, Calcs!CR62> 'Summary '!$I$51))),1,0) -> 0 | CW62: =IF(OR(SUM(CU62:CV62)>=1,CX62="Yes"),1,0) -> 0 | CX62: No | CY62: No | CZ62: No | DD62: 0 | DE62: 0 | DI62: =IF(L62<90%,"Not Eligible","Eligible") -> Eligible | DJ62: =IF(OR(BF62="USD",BF62="CAD",BF62="EUR",BF62="GBP",BF62="AUD"),"Eligible","Not Eligible") -> Eligible | DK62: Eligible | DL62: Eligible | DM62: =IF(BM62="FALSE",IF(BY62<5,"Not Eligible","Eligible"),"Eligible") -> Eligible | DN62: =IF(AW62=TRUE,IF(AU62>=3%,"Eligible","Not Eligible"),"Not PIK") -> Not PIK | DO62: No | DP62: =IF(OR(DK62="Not Eligible",DL62="Not Eligible",DI62="Not Eligible",DJ62="Not Eligible",DM62="Not Eligible",DN62="Not Eligible",DO62="Yes"),"NO","YES") -> YES
A63: Seaway Plastics | B63: =IFERROR(VLOOKUP(A63,'Loan List '!$A$6:$BZ$75,2,FALSE),NA) -> 0 | C63: =VLOOKUP(A63,'Loan List '!$A$6:$G$75, 7, FALSE) -> First Lien | D63: =VLOOKUP(A63, 'Loan List '!$A$6:$K$82, 11, FALSE) -> FL | E63: =IF(DP63= "YES", TRUE, FALSE) -> TRUE | F63: =VLOOKUP(A63,'Loan List '!$A$6:$L$75, 12, FALSE) -> Chemicals | H63: =+I63 -> 606535.84 | I63: =VLOOKUP(A63,'Loan List '!$A$6:$L$75, 8, FALSE) -> 606535.84 | J63: 0 | K63: =I63/$I$15 -> 0.0016788991 | L63: =VLOOKUP(A63,'Loan List '!$A$6:$BA$82,24, FALSE) -> 100 | N63: =VLOOKUP(A63,'Loan List '!$A$6:$BA$82,22, FALSE) -> 47282 | O63: =IFERROR(MAX(0,I63-J63)*L63,"")/100 -> 606535.84 | P63: =MIN(IF(AND(L63>=97%,Q63="Primary"),100%,L63),T63) -> 0.9 | Q63: Primary | R63: SETTLED | S63: =IF(OR(CU63=1,CV63=1,CW63=1),TRUE,FALSE) -> TRUE | T63: =VLOOKUP(A63,'Loan List '!$A$6:$BD$1048576,56,FALSE)/100 -> 0.9 | U63: =IF(E63=TRUE,P63*I63,0) -> 545882.26 | V63: =VLOOKUP(A63,'Loan List '!$A$6:$BA$82,26, FALSE) -> 0 | W63: =V63*I63 -> 0 | Y63: =VLOOKUP(A63,'Loan List '!$A$6:$BA$75,27, FALSE) -> 0 | AB63: =K63*BU63 -> 0.013059159 | AC63: =K63*AL63 -> 0.00077702765 | AD63: =BW63 -> 0 | AE63: =IF(CK63>=$C$5,"Class 1",IF(CK63>=$D$5,"Class 2",IF(CK63>=$E$5,"Class 3","Class 4"))) -> Class 3 | AF63: =HLOOKUP($AE63,$B$3:$F$10,4,0) -> 5 | AG63: =IF(BB63,1,0)+HLOOKUP($AE63,$B$3:$F$10,5,0) -> 6 | AH63: =MIN(AF63/BU63,1) -> 0.64280521 | AI63: =IF(BU63>AG63,(AG63-AF63)/BU63,1-AH63) -> 0.12856104 | AJ63: =HLOOKUP($AE63,$B$3:$F$10,6,0) -> 0.65 | AK63: =HLOOKUP($AE63,$B$3:$F$10,8,0) -> 0.35 | AL63: =IF(OR(BI63, AND(BH63,AD63>1)), HLOOKUP(AE63,$B$3:$F$10,8,0),AH63*AJ63+AI63*AK63) -> 0.46281975 | AM63: ='Diversity Score'!$E$7 -> 1 | AN63: =AM63*AL63 -> 0.46281975 | AO63: =VLOOKUP(A63,'Loan List '!$A$6:$BA$75,17, FALSE) -> 0.0615 | AP63: =VLOOKUP(A63,'Loan List '!$A$6:$BA$795,15, FALSE) -> SOFR | AQ63: =VLOOKUP(A63,'Loan List '!$A$6:$BA$795,16, FALSE) -> 0 | AR63: 0 | AS63: 0 | AU63: =AO63-AS63 -> 0.0615 | AV63: =IF(AND(AS63>0%,AU63>4.5%),TRUE,FALSE) -> FALSE | AW63: =IF(AND(AS63>0%,AU63>=2.25%, AV63=FALSE),TRUE,FALSE) -> FALSE | AX63: =IF(AND(AS63>0%,AW63=FALSE, AV63=FALSE),TRUE, FALSE) -> FALSE | AZ63: =(OR(CC63<>"NR",CD63<>"NR")) -> FALSE | BA63: ='Loan List '!AS52 -> Maintenance Covenants | BB63: =IF(D63="FL",FALSE,TRUE) -> FALSE | BC63: =IF(BU63>5.5, TRUE, FALSE) -> TRUE | BD63: =IF(BF63="USD", TRUE,FALSE) -> TRUE | BE63: =IF(BG63="USA",TRUE,FALSE) -> TRUE | BF63: ='Loan List '!J52 -> USD | BG63: =VLOOKUP(A63,'Loan List '!$A$6:$BZ$75, 23, FALSE) -> USA | BH63: =IF(D63="FLLO", TRUE,FALSE) -> FALSE | BI63: =IF(C63="Second Lien",TRUE,FALSE) -> FALSE | BJ63: =IF('Loan List '!BP52=1, TRUE, FALSE) -> FALSE | BK63: =IF(AR63>0%,TRUE,FALSE) -> FALSE | BL63: =OR(LEFT(CC63,1)="C", LEFT(CD63,1)="C") -> FALSE | BM63: =IF('Loan List '!AT52="Yes", TRUE, FALSE) -> FALSE | BN63: =-($BN$15-N63)/365 -> 3.8876712 | BO63: ='Concentration Limitations'!H58 -> 545882.26 | BP63: =IF(R63=$T$13,0,BO63*AL63) -> 252645.09 | BS63: ='Loan List '!AG52 -> 45777 | BT63: ='Loan List '!AO52 -> 2.889 | BU63: ='Loan List '!AI52 -> 7.7784062 | BW63: 0 | BX63: - | BY63: ='Loan List '!AJ52 -> 8.072336 | BZ63: ='Loan List '!AL52 -> 0 | CA63: 0 | CB63: 0 | CC63: NR | CD63: NR | CE63: - | CF63: ='Loan List '!AC52 -> 2.33 | CG63: ='Loan List '!AD52 -> 5.01 | CI63: 0 | CJ63: - | CK63: ='Loan List '!AB52 -> 11.92 | CL63: ='Loan List '!AE53 -> 0 | CM63: 0 | CN63: 0 | CO63: NR | CP63: NR | CQ63: =IFERROR(($BT63-$CF63)/$CF63,0) -> 0.23991416 | CR63: =IFERROR(($BU63-$CG63)/$CG63,0) -> 0.55257608 | CS63: =BU63-CG63 -> 2.7684062 | CT63: =(BY63/CK63)-1 -> -0.3227906 | CU63: =IF(OR($CQ63<'Summary '!$I$47,$BT63<'Summary '!$I$46),1,0) -> 0 | CV63: =IF(OR($CS63>='Summary '!$I$50, (AND(BU63>'Summary '!$I$52, Calcs!CR63> 'Summary '!$I$51))),1,0) -> 1 | CW63: =IF(OR(SUM(CU63:CV63)>=1,CX63="Yes"),1,0) -> 1 | CX63: No | CY63: No | CZ63: No | DD63: 0 | DE63: 0 | DI63: =IF(L63<90%,"Not Eligible","Eligible") -> Eligible | DJ63: =IF(OR(BF63="USD",BF63="CAD",BF63="EUR",BF63="GBP",BF63="AUD"),"Eligible","Not Eligible") -> Eligible | DK63: Eligible | DL63: Eligible | DM63: =IF(BM63="FALSE",IF(BY63<5,"Not Eligible","Eligible"),"Eligible") -> Eligible | DN63: =IF(AW63=TRUE,IF(AU63>=3%,"Eligible","Not Eligible"),"Not PIK") -> Not PIK | DO63: No | DP63: =IF(OR(DK63="Not Eligible",DL63="Not Eligible",DI63="Not Eligible",DJ63="Not Eligible",DM63="Not Eligible",DN63="Not Eligible",DO63="Yes"),"NO","YES") -> YES
A64: Sigma Defense Systems, LLC | B64: =IFERROR(VLOOKUP(A64,'Loan List '!$A$6:$BZ$75,2,FALSE),NA) -> 0 | C64: =VLOOKUP(A64,'Loan List '!$A$6:$G$75, 7, FALSE) -> First Lien | D64: =VLOOKUP(A64, 'Loan List '!$A$6:$K$82, 11, FALSE) -> FL | E64: =IF(DP64= "YES", TRUE, FALSE) -> TRUE | F64: =VLOOKUP(A64,'Loan List '!$A$6:$L$75, 12, FALSE) -> IT Services | H64: =+I64 -> 18161284 | I64: =VLOOKUP(A64,'Loan List '!$A$6:$L$75, 8, FALSE) -> 18161284 | J64: 0 | K64: =I64/$I$15 -> 0.050270671 | L64: =VLOOKUP(A64,'Loan List '!$A$6:$BA$82,24, FALSE) -> 100 | N64: =VLOOKUP(A64,'Loan List '!$A$6:$BA$82,22, FALSE) -> 46739 | O64: =IFERROR(MAX(0,I64-J64)*L64,"")/100 -> 18161284 | P64: =MIN(IF(AND(L64>=97%,Q64="Primary"),100%,L64),T64) -> 1 | Q64: Primary | R64: SETTLED | S64: =IF(OR(CU64=1,CV64=1,CW64=1),TRUE,FALSE) -> FALSE | T64: =VLOOKUP(A64,'Loan List '!$A$6:$BD$1048576,56,FALSE)/100 -> 1 | U64: =IF(E64=TRUE,P64*I64,0) -> 18161284 | V64: =VLOOKUP(A64,'Loan List '!$A$6:$BA$82,26, FALSE) -> 0 | W64: =V64*I64 -> 0 | Y64: =VLOOKUP(A64,'Loan List '!$A$6:$BA$75,27, FALSE) -> 0 | AB64: =K64*BU64 -> 0.20837242 | AC64: =K64*AL64 -> 0.032675936 | AD64: =BW64 -> 0 | AE64: =IF(CK64>=$C$5,"Class 1",IF(CK64>=$D$5,"Class 2",IF(CK64>=$E$5,"Class 3","Class 4"))) -> Class 3 | AF64: =HLOOKUP($AE64,$B$3:$F$10,4,0) -> 5 | AG64: =IF(BB64,1,0)+HLOOKUP($AE64,$B$3:$F$10,5,0) -> 6 | AH64: =MIN(AF64/BU64,1) -> 1 | AI64: =IF(BU64>AG64,(AG64-AF64)/BU64,1-AH64) -> 0 | AJ64: =HLOOKUP($AE64,$B$3:$F$10,6,0) -> 0.65 | AK64: =HLOOKUP($AE64,$B$3:$F$10,8,0) -> 0.35 | AL64: =IF(OR(BI64, AND(BH64,AD64>1)), HLOOKUP(AE64,$B$3:$F$10,8,0),AH64*AJ64+AI64*AK64) -> 0.65 | AM64: ='Diversity Score'!$E$7 -> 1 | AN64: =AM64*AL64 -> 0.65 | AO64: =VLOOKUP(A64,'Loan List '!$A$6:$BA$75,17, FALSE) -> 0.069 | AP64: =VLOOKUP(A64,'Loan List '!$A$6:$BA$795,15, FALSE) -> SOFR | AQ64: =VLOOKUP(A64,'Loan List '!$A$6:$BA$795,16, FALSE) -> 0.01 | AR64: 0 | AS64: 0 | AU64: =AO64-AS64 -> 0.069 | AV64: =IF(AND(AS64>0%,AU64>4.5%),TRUE,FALSE) -> FALSE | AW64: =IF(AND(AS64>0%,AU64>=2.25%, AV64=FALSE),TRUE,FALSE) -> FALSE | AX64: =IF(AND(AS64>0%,AW64=FALSE, AV64=FALSE),TRUE, FALSE) -> FALSE | AZ64: =(OR(CC64<>"NR",CD64<>"NR")) -> FALSE | BA64: ='Loan List '!AS53 -> Maintenance Covenants | BB64: =IF(D64="FL",FALSE,TRUE) -> FALSE | BC64: =IF(BU64>5.5, TRUE, FALSE) -> FALSE | BD64: =IF(BF64="USD", TRUE,FALSE) -> TRUE | BE64: =IF(BG64="USA",TRUE,FALSE) -> TRUE | BF64: ='Loan List '!J53 -> USD | BG64: =VLOOKUP(A64,'Loan List '!$A$6:$BZ$75, 23, FALSE) -> USA | BH64: =IF(D64="FLLO", TRUE,FALSE) -> FALSE | BI64: =IF(C64="Second Lien",TRUE,FALSE) -> FALSE | BJ64: =IF('Loan List '!BP53=1, TRUE, FALSE) -> FALSE | BK64: =IF(AR64>0%,TRUE,FALSE) -> FALSE | BL64: =OR(LEFT(CC64,1)="C", LEFT(CD64,1)="C") -> FALSE | BM64: =IF('Loan List '!AT53="Yes", TRUE, FALSE) -> FALSE | BN64: =-($BN$15-N64)/365 -> 2.4 | BO64: ='Concentration Limitations'!H59 -> 18161284 | BP64: =IF(R64=$T$13,0,BO64*AL64) -> 11804835 | BS64: ='Loan List '!AG53 -> 45808 | BT64: ='Loan List '!AO53 -> 1.8190375 | BU64: ='Loan List '!AI53 -> 4.1450098 | BW64: 0 | BX64: - | BY64: ='Loan List '!AJ53 -> 31.399443 | BZ64: ='Loan List '!AL53 -> 0 | CA64: 0 | CB64: 0 | CC64: NR | CD64: NR | CE64: - | CF64: ='Loan List '!AC53 -> 1.0997622 | CG64: ='Loan List '!AD53 -> 4.7935387 | CI64: 0 | CJ64: - | CK64: ='Loan List '!AB53 -> 19.343557 | CL64: ='Loan List '!AE54 -> 0 | CM64: 0 | CN64: 0 | CO64: NR | CP64: NR | CQ64: =IFERROR(($BT64-$CF64)/$CF64,0) -> 0.654028 | CR64: =IFERROR(($BU64-$CG64)/$CG64,0) -> -0.1352923 | CS64: =BU64-CG64 -> -0.6485289 | CT64: =(BY64/CK64)-1 -> 0.62325073 | CU64: =IF(OR($CQ64<'Summary '!$I$47,$BT64<'Summary '!$I$46),1,0) -> 0 | CV64: =IF(OR($CS64>='Summary '!$I$50, (AND(BU64>'Summary '!$I$52, Calcs!CR64> 'Summary '!$I$51))),1,0) -> 0 | CW64: =IF(OR(SUM(CU64:CV64)>=1,CX64="Yes"),1,0) -> 0 | CX64: No | CY64: No | CZ64: No | DD64: 0 | DE64: 0 | DI64: =IF(L64<90%,"Not Eligible","Eligible") -> Eligible | DJ64: =IF(OR(BF64="USD",BF64="CAD",BF64="EUR",BF64="GBP",BF64="AUD"),"Eligible","Not Eligible") -> Eligible | DK64: Eligible | DL64: Eligible | DM64: =IF(BM64="FALSE",IF(BY64<5,"Not Eligible","Eligible"),"Eligible") -> Eligible | DN64: =IF(AW64=TRUE,IF(AU64>=3%,"Eligible","Not Eligible"),"Not PIK") -> Not PIK | DO64: No | DP64: =IF(OR(DK64="Not Eligible",DL64="Not Eligible",DI64="Not Eligible",DJ64="Not Eligible",DM64="Not Eligible",DN64="Not Eligible",DO64="Yes"),"NO","YES") -> YES
A65: System Planning and Analysis, Inc. | B65: =IFERROR(VLOOKUP(A65,'Loan List '!$A$6:$BZ$75,2,FALSE),NA) -> 0 | C65: =VLOOKUP(A65,'Loan List '!$A$6:$G$75, 7, FALSE) -> First Lien | D65: =VLOOKUP(A65, 'Loan List '!$A$6:$K$82, 11, FALSE) -> FL | E65: =IF(DP65= "YES", TRUE, FALSE) -> TRUE | F65: =VLOOKUP(A65,'Loan List '!$A$6:$L$75, 12, FALSE) -> Aerospace & Defense | H65: =+I65 -> 1278782.1 | I65: =VLOOKUP(A65,'Loan List '!$A$6:$L$75, 8, FALSE) -> 1278782.1 | J65: 0 | K65: =I65/$I$15 -> 0.0035396855 | L65: =VLOOKUP(A65,'Loan List '!$A$6:$BA$82,24, FALSE) -> 100 | N65: =VLOOKUP(A65,'Loan List '!$A$6:$BA$82,22, FALSE) -> 46615 | O65: =IFERROR(MAX(0,I65-J65)*L65,"")/100 -> 1278782.1 | P65: =MIN(IF(AND(L65>=97%,Q65="Primary"),100%,L65),T65) -> 1 | Q65: Primary | R65: SETTLED | S65: =IF(OR(CU65=1,CV65=1,CW65=1),TRUE,FALSE) -> FALSE | T65: =VLOOKUP(A65,'Loan List '!$A$6:$BD$1048576,56,FALSE)/100 -> 1 | U65: =IF(E65=TRUE,P65*I65,0) -> 1278782.1 | V65: =VLOOKUP(A65,'Loan List '!$A$6:$BA$82,26, FALSE) -> 0 | W65: =V65*I65 -> 0 | Y65: =VLOOKUP(A65,'Loan List '!$A$6:$BA$75,27, FALSE) -> 0 | AB65: =K65*BU65 -> 0.019702796 | AC65: =K65*AL65 -> 0.0023755943 | AD65: =BW65 -> 0 | AE65: =IF(CK65>=$C$5,"Class 1",IF(CK65>=$D$5,"Class 2",IF(CK65>=$E$5,"Class 3","Class 4"))) -> Class 2 | AF65: =HLOOKUP($AE65,$B$3:$F$10,4,0) -> 5.5 | AG65: =IF(BB65,1,0)+HLOOKUP($AE65,$B$3:$F$10,5,0) -> 6.5 | AH65: =MIN(AF65/BU65,1) -> 0.98809684 | AI65: =IF(BU65>AG65,(AG65-AF65)/BU65,1-AH65) -> 0.011903161 | AJ65: =HLOOKUP($AE65,$B$3:$F$10,6,0) -> 0.675 | AK65: =HLOOKUP($AE65,$B$3:$F$10,8,0) -> 0.35 | AL65: =IF(OR(BI65, AND(BH65,AD65>1)), HLOOKUP(AE65,$B$3:$F$10,8,0),AH65*AJ65+AI65*AK65) -> 0.67113147 | AM65: ='Diversity Score'!$E$7 -> 1 | AN65: =AM65*AL65 -> 0.67113147 | AO65: =VLOOKUP(A65,'Loan List '!$A$6:$BA$75,17, FALSE) -> 0.05 | AP65: =VLOOKUP(A65,'Loan List '!$A$6:$BA$795,15, FALSE) -> SOFR | AQ65: =VLOOKUP(A65,'Loan List '!$A$6:$BA$795,16, FALSE) -> 0.01 | AR65: 0 | AS65: 0 | AU65: =AO65-AS65 -> 0.05 | AV65: =IF(AND(AS65>0%,AU65>4.5%),TRUE,FALSE) -> FALSE | AW65: =IF(AND(AS65>0%,AU65>=2.25%, AV65=FALSE),TRUE,FALSE) -> FALSE | AX65: =IF(AND(AS65>0%,AW65=FALSE, AV65=FALSE),TRUE, FALSE) -> FALSE | AZ65: =(OR(CC65<>"NR",CD65<>"NR")) -> FALSE | BA65: ='Loan List '!AS54 -> Maintenance Covenants | BB65: =IF(D65="FL",FALSE,TRUE) -> FALSE | BC65: =IF(BU65>5.5, TRUE, FALSE) -> TRUE | BD65: =IF(BF65="USD", TRUE,FALSE) -> TRUE | BE65: =IF(BG65="USA",TRUE,FALSE) -> TRUE | BF65: ='Loan List '!J54 -> USD | BG65: =VLOOKUP(A65,'Loan List '!$A$6:$BZ$75, 23, FALSE) -> USA | BH65: =IF(D65="FLLO", TRUE,FALSE) -> FALSE | BI65: =IF(C65="Second Lien",TRUE,FALSE) -> FALSE | BJ65: =IF('Loan List '!BP54=1, TRUE, FALSE) -> FALSE | BK65: =IF(AR65>0%,TRUE,FALSE) -> FALSE | BL65: =OR(LEFT(CC65,1)="C", LEFT(CD65,1)="C") -> FALSE | BM65: =IF('Loan List '!AT54="Yes", TRUE, FALSE) -> FALSE | BN65: =-($BN$15-N65)/365 -> 2.060274 | BO65: ='Concentration Limitations'!H60 -> 1278782.1 | BP65: =IF(R65=$T$13,0,BO65*AL65) -> 858230.93 | BS65: ='Loan List '!AG54 -> 45747 | BT65: ='Loan List '!AO54 -> 4.89 | BU65: ='Loan List '!AI54 -> 5.566256 | BW65: 0 | BX65: - | BY65: ='Loan List '!AJ54 -> 82.467293 | BZ65: ='Loan List '!AL54 -> 0 | CA65: 0 | CB65: 0 | CC65: NR | CD65: NR | CE65: - | CF65: ='Loan List '!AC54 -> 4.89 | CG65: ='Loan List '!AD54 -> 5.7423636 | CI65: 0 | CJ65: - | CK65: ='Loan List '!AB54 -> 39.348867 | CL65: ='Loan List '!AE55 -> 0 | CM65: 0 | CN65: 0 | CO65: NR | CP65: NR | CQ65: =IFERROR(($BT65-$CF65)/$CF65,0) -> 0 | CR65: =IFERROR(($BU65-$CG65)/$CG65,0) -> -0.030668124 | CS65: =BU65-CG65 -> -0.17610752 | CT65: =(BY65/CK65)-1 -> 1.0957984 | CU65: =IF(OR($CQ65<'Summary '!$I$47,$BT65<'Summary '!$I$46),1,0) -> 0 | CV65: =IF(OR($CS65>='Summary '!$I$50, (AND(BU65>'Summary '!$I$52, Calcs!CR65> 'Summary '!$I$51))),1,0) -> 0 | CW65: =IF(OR(SUM(CU65:CV65)>=1,CX65="Yes"),1,0) -> 0 | CX65: No | CY65: No | CZ65: No | DD65: 0 | DE65: 0 | DI65: =IF(L65<90%,"Not Eligible","Eligible") -> Eligible | DJ65: =IF(OR(BF65="USD",BF65="CAD",BF65="EUR",BF65="GBP",BF65="AUD"),"Eligible","Not Eligible") -> Eligible | DK65: Eligible | DL65: Eligible | DM65: =IF(BM65="FALSE",IF(BY65<5,"Not Eligible","Eligible"),"Eligible") -> Eligible | DN65: =IF(AW65=TRUE,IF(AU65>=3%,"Eligible","Not Eligible"),"Not PIK") -> Not PIK | DO65: No | DP65: =IF(OR(DK65="Not Eligible",DL65="Not Eligible",DI65="Not Eligible",DJ65="Not Eligible",DM65="Not Eligible",DN65="Not Eligible",DO65="Yes"),"NO","YES") -> YES
A66: Team Services Group, LLC | B66: =IFERROR(VLOOKUP(A66,'Loan List '!$A$6:$BZ$75,2,FALSE),NA) -> 0 | C66: =VLOOKUP(A66,'Loan List '!$A$6:$G$75, 7, FALSE) -> First Lien | D66: =VLOOKUP(A66, 'Loan List '!$A$6:$K$82, 11, FALSE) -> FL | E66: =IF(DP66= "YES", TRUE, FALSE) -> TRUE | F66: =VLOOKUP(A66,'Loan List '!$A$6:$L$75, 12, FALSE) -> Health Care Providers & Services | H66: =+I66 -> 995000 | I66: =VLOOKUP(A66,'Loan List '!$A$6:$L$75, 8, FALSE) -> 995000 | J66: 0 | K66: =I66/$I$15 -> 0.0027541729 | L66: =VLOOKUP(A66,'Loan List '!$A$6:$BA$82,24, FALSE) -> 100 | N66: =VLOOKUP(A66,'Loan List '!$A$6:$BA$82,22, FALSE) -> 47081 | O66: =IFERROR(MAX(0,I66-J66)*L66,"")/100 -> 995000 | P66: =MIN(IF(AND(L66>=97%,Q66="Primary"),100%,L66),T66) -> 1 | Q66: Primary | R66: SETTLED | S66: =IF(OR(CU66=1,CV66=1,CW66=1),TRUE,FALSE) -> FALSE | T66: =VLOOKUP(A66,'Loan List '!$A$6:$BD$1048576,56,FALSE)/100 -> 1 | U66: =IF(E66=TRUE,P66*I66,0) -> 995000 | V66: =VLOOKUP(A66,'Loan List '!$A$6:$BA$82,26, FALSE) -> 0 | W66: =V66*I66 -> 0 | Y66: =VLOOKUP(A66,'Loan List '!$A$6:$BA$75,27, FALSE) -> 0 | AB66: =K66*BU66 -> 0.0091004353 | AC66: =K66*AL66 -> 0.001927921 | AD66: =BW66 -> 0 | AE66: =IF(CK66>=$C$5,"Class 1",IF(CK66>=$D$5,"Class 2",IF(CK66>=$E$5,"Class 3","Class 4"))) -> Class 1 | AF66: =HLOOKUP($AE66,$B$3:$F$10,4,0) -> 6 | AG66: =IF(BB66,1,0)+HLOOKUP($AE66,$B$3:$F$10,5,0) -> 7 | AH66: =MIN(AF66/BU66,1) -> 1 | AI66: =IF(BU66>AG66,(AG66-AF66)/BU66,1-AH66) -> 0 | AJ66: =HLOOKUP($AE66,$B$3:$F$10,6,0) -> 0.7 | AK66: =HLOOKUP($AE66,$B$3:$F$10,8,0) -> 0.4 | AL66: =IF(OR(BI66, AND(BH66,AD66>1)), HLOOKUP(AE66,$B$3:$F$10,8,0),AH66*AJ66+AI66*AK66) -> 0.7 | AM66: ='Diversity Score'!$E$7 -> 1 | AN66: =AM66*AL66 -> 0.7 | AO66: =VLOOKUP(A66,'Loan List '!$A$6:$BA$75,17, FALSE) -> 0.0525 | AP66: =VLOOKUP(A66,'Loan List '!$A$6:$BA$795,15, FALSE) -> SOFR | AQ66: =VLOOKUP(A66,'Loan List '!$A$6:$BA$795,16, FALSE) -> 0.01 | AR66: 0 | AS66: 0 | AU66: =AO66-AS66 -> 0.0525 | AV66: =IF(AND(AS66>0%,AU66>4.5%),TRUE,FALSE) -> FALSE | AW66: =IF(AND(AS66>0%,AU66>=2.25%, AV66=FALSE),TRUE,FALSE) -> FALSE | AX66: =IF(AND(AS66>0%,AW66=FALSE, AV66=FALSE),TRUE, FALSE) -> FALSE | AZ66: =(OR(CC66<>"NR",CD66<>"NR")) -> FALSE | BA66: ='Loan List '!AS55 -> Cov-Lite | BB66: =IF(D66="FL",FALSE,TRUE) -> FALSE | BC66: =IF(BU66>5.5, TRUE, FALSE) -> FALSE | BD66: =IF(BF66="USD", TRUE,FALSE) -> TRUE | BE66: =IF(BG66="USA",TRUE,FALSE) -> TRUE | BF66: ='Loan List '!J55 -> USD | BG66: =VLOOKUP(A66,'Loan List '!$A$6:$BZ$75, 23, FALSE) -> USA | BH66: =IF(D66="FLLO", TRUE,FALSE) -> FALSE | BI66: =IF(C66="Second Lien",TRUE,FALSE) -> FALSE | BJ66: =IF('Loan List '!BP55=1, TRUE, FALSE) -> FALSE | BK66: =IF(AR66>0%,TRUE,FALSE) -> FALSE | BL66: =OR(LEFT(CC66,1)="C", LEFT(CD66,1)="C") -> FALSE | BM66: =IF('Loan List '!AT55="Yes", TRUE, FALSE) -> TRUE | BN66: =-($BN$15-N66)/365 -> 3.3369863 | BO66: ='Concentration Limitations'!H61 -> 995000 | BP66: =IF(R66=$T$13,0,BO66*AL66) -> 696500 | BS66: ='Loan List '!AG55 -> 45747 | BT66: ='Loan List '!AO55 -> 2.1270831 | BU66: ='Loan List '!AI55 -> 3.3042353 | BW66: 0 | BX66: - | BY66: ='Loan List '!AJ55 -> 255.401 | BZ66: ='Loan List '!AL55 -> 0 | CA66: 0 | CB66: 0 | CC66: NR | CD66: NR | CE66: - | CF66: ='Loan List '!AC55 -> 1.69 | CG66: ='Loan List '!AD55 -> 3.75 | CI66: 0 | CJ66: - | CK66: ='Loan List '!AB55 -> 133.95 | CL66: ='Loan List '!AE56 -> 0 | CM66: 0 | CN66: 0 | CO66: NR | CP66: NR | CQ66: =IFERROR(($BT66-$CF66)/$CF66,0) -> 0.25862908 | CR66: =IFERROR(($BU66-$CG66)/$CG66,0) -> -0.11887059 | CS66: =BU66-CG66 -> -0.4457647 | CT66: =(BY66/CK66)-1 -> 0.90668906 | CU66: =IF(OR($CQ66<'Summary '!$I$47,$BT66<'Summary '!$I$46),1,0) -> 0 | CV66: =IF(OR($CS66>='Summary '!$I$50, (AND(BU66>'Summary '!$I$52, Calcs!CR66> 'Summary '!$I$51))),1,0) -> 0 | CW66: =IF(OR(SUM(CU66:CV66)>=1,CX66="Yes"),1,0) -> 0 | CX66: No | CY66: No | CZ66: No | DD66: 0 | DE66: 0 | DI66: =IF(L66<90%,"Not Eligible","Eligible") -> Eligible | DJ66: =IF(OR(BF66="USD",BF66="CAD",BF66="EUR",BF66="GBP",BF66="AUD"),"Eligible","Not Eligible") -> Eligible | DK66: Eligible | DL66: Eligible | DM66: =IF(BM66="FALSE",IF(BY66<5,"Not Eligible","Eligible"),"Eligible") -> Eligible | DN66: =IF(AW66=TRUE,IF(AU66>=3%,"Eligible","Not Eligible"),"Not PIK") -> Not PIK | DO66: No | DP66: =IF(OR(DK66="Not Eligible",DL66="Not Eligible",DI66="Not Eligible",DJ66="Not Eligible",DM66="Not Eligible",DN66="Not Eligible",DO66="Yes"),"NO","YES") -> YES
A67: TCD 3.0 Jogger Acquisitionco, Inc. Term Loan | B67: =IFERROR(VLOOKUP(A67,'Loan List '!$A$6:$BZ$75,2,FALSE),NA) -> 0 | C67: =VLOOKUP(A67,'Loan List '!$A$6:$G$75, 7, FALSE) -> First Lien | D67: =VLOOKUP(A67, 'Loan List '!$A$6:$K$82, 11, FALSE) -> FL | E67: =IF(DP67= "YES", TRUE, FALSE) -> TRUE | F67: =VLOOKUP(A67,'Loan List '!$A$6:$L$75, 12, FALSE) -> Media | H67: =+I67 -> 3920226.1 | I67: =VLOOKUP(A67,'Loan List '!$A$6:$L$75, 8, FALSE) -> 3920226.1 | J67: 0 | K67: =I67/$I$15 -> 0.010851237 | L67: =VLOOKUP(A67,'Loan List '!$A$6:$BA$82,24, FALSE) -> 100 | N67: =VLOOKUP(A67,'Loan List '!$A$6:$BA$82,22, FALSE) -> 47141 | O67: =IFERROR(MAX(0,I67-J67)*L67,"")/100 -> 3920226.1 | P67: =MIN(IF(AND(L67>=97%,Q67="Primary"),100%,L67),T67) -> 1 | Q67: Primary | R67: SETTLED | S67: =IF(OR(CU67=1,CV67=1,CW67=1),TRUE,FALSE) -> TRUE | T67: =VLOOKUP(A67,'Loan List '!$A$6:$BD$1048576,56,FALSE)/100 -> 1 | U67: =IF(E67=TRUE,P67*I67,0) -> 3920226.1 | V67: =VLOOKUP(A67,'Loan List '!$A$6:$BA$82,26, FALSE) -> 0 | W67: =V67*I67 -> 0 | Y67: =VLOOKUP(A67,'Loan List '!$A$6:$BA$75,27, FALSE) -> 0 | AB67: =K67*BU67 -> 0.042062915 | AC67: =K67*AL67 -> 0.0070533039 | AD67: =BW67 -> 0 | AE67: =IF(CK67>=$C$5,"Class 1",IF(CK67>=$D$5,"Class 2",IF(CK67>=$E$5,"Class 3","Class 4"))) -> Class 3 | AF67: =HLOOKUP($AE67,$B$3:$F$10,4,0) -> 5 | AG67: =IF(BB67,1,0)+HLOOKUP($AE67,$B$3:$F$10,5,0) -> 6 | AH67: =MIN(AF67/BU67,1) -> 1 | AI67: =IF(BU67>AG67,(AG67-AF67)/BU67,1-AH67) -> 0 | AJ67: =HLOOKUP($AE67,$B$3:$F$10,6,0) -> 0.65 | AK67: =HLOOKUP($AE67,$B$3:$F$10,8,0) -> 0.35 | AL67: =IF(OR(BI67, AND(BH67,AD67>1)), HLOOKUP(AE67,$B$3:$F$10,8,0),AH67*AJ67+AI67*AK67) -> 0.65 | AM67: ='Diversity Score'!$E$7 -> 1 | AN67: =AM67*AL67 -> 0.65 | AO67: =VLOOKUP(A67,'Loan List '!$A$6:$BA$75,17, FALSE) -> 0.065 | AP67: =VLOOKUP(A67,'Loan List '!$A$6:$BA$795,15, FALSE) -> SOFR | AQ67: =VLOOKUP(A67,'Loan List '!$A$6:$BA$795,16, FALSE) -> 0.01 | AR67: 0 | AS67: 0 | AU67: =AO67-AS67 -> 0.065 | AV67: =IF(AND(AS67>0%,AU67>4.5%),TRUE,FALSE) -> FALSE | AW67: =IF(AND(AS67>0%,AU67>=2.25%, AV67=FALSE),TRUE,FALSE) -> FALSE | AX67: =IF(AND(AS67>0%,AW67=FALSE, AV67=FALSE),TRUE, FALSE) -> FALSE | AZ67: =(OR(CC67<>"NR",CD67<>"NR")) -> FALSE | BA67: ='Loan List '!AS56 -> Cov-Lite | BB67: =IF(D67="FL",FALSE,TRUE) -> FALSE | BC67: =IF(BU67>5.5, TRUE, FALSE) -> FALSE | BD67: =IF(BF67="USD", TRUE,FALSE) -> TRUE | BE67: =IF(BG67="USA",TRUE,FALSE) -> TRUE | BF67: ='Loan List '!J56 -> USD | BG67: =VLOOKUP(A67,'Loan List '!$A$6:$BZ$75, 23, FALSE) -> USA | BH67: =IF(D67="FLLO", TRUE,FALSE) -> FALSE | BI67: =IF(C67="Second Lien",TRUE,FALSE) -> FALSE | BJ67: =IF('Loan List '!BP56=1, TRUE, FALSE) -> FALSE | BK67: =IF(AR67>0%,TRUE,FALSE) -> FALSE | BL67: =OR(LEFT(CC67,1)="C", LEFT(CD67,1)="C") -> FALSE | BM67: =IF('Loan List '!AT56="Yes", TRUE, FALSE) -> TRUE | BN67: =-($BN$15-N67)/365 -> 3.5013699 | BO67: ='Concentration Limitations'!H62 -> 3920226.1 | BP67: =IF(R67=$T$13,0,BO67*AL67) -> 2548147 | BS67: ='Loan List '!AG56 -> 45808 | BT67: ='Loan List '!AO56 -> 2.0688259 | BU67: ='Loan List '!AI56 -> 3.8763246 | BW67: 0 | BX67: - | BY67: ='Loan List '!AJ56 -> 15.15665 | BZ67: ='Loan List '!AL56 -> 0 | CA67: 0 | CB67: 0 | CC67: NR | CD67: NR | CE67: - | CF67: ='Loan List '!AC56 -> 2.5233716 | CG67: ='Loan List '!AD56 -> 3.3181615 | CI67: 0 | CJ67: - | CK67: ='Loan List '!AB56 -> 18.280304 | CL67: ='Loan List '!AE57 -> 0 | CM67: 0 | CN67: 0 | CO67: NR | CP67: NR | CQ67: =IFERROR(($BT67-$CF67)/$CF67,0) -> -0.18013429 | CR67: =IFERROR(($BU67-$CG67)/$CG67,0) -> 0.16821455 | CS67: =BU67-CG67 -> 0.55816306 | CT67: =(BY67/CK67)-1 -> -0.1708754 | CU67: =IF(OR($CQ67<'Summary '!$I$47,$BT67<'Summary '!$I$46),1,0) -> 1 | CV67: =IF(OR($CS67>='Summary '!$I$50, (AND(BU67>'Summary '!$I$52, Calcs!CR67> 'Summary '!$I$51))),1,0) -> 0 | CW67: =IF(OR(SUM(CU67:CV67)>=1,CX67="Yes"),1,0) -> 1 | CX67: No | CY67: No | CZ67: No | DD67: 0 | DE67: 0 | DI67: =IF(L67<90%,"Not Eligible","Eligible") -> Eligible | DJ67: =IF(OR(BF67="USD",BF67="CAD",BF67="EUR",BF67="GBP",BF67="AUD"),"Eligible","Not Eligible") -> Eligible | DK67: Eligible | DL67: Eligible | DM67: =IF(BM67="FALSE",IF(BY67<5,"Not Eligible","Eligible"),"Eligible") -> Eligible | DN67: =IF(AW67=TRUE,IF(AU67>=3%,"Eligible","Not Eligible"),"Not PIK") -> Not PIK | DO67: No | DP67: =IF(OR(DK67="Not Eligible",DL67="Not Eligible",DI67="Not Eligible",DJ67="Not Eligible",DM67="Not Eligible",DN67="Not Eligible",DO67="Yes"),"NO","YES") -> YES
A68: The Bluebird Group LLC | B68: =IFERROR(VLOOKUP(A68,'Loan List '!$A$6:$BZ$75,2,FALSE),NA) -> 0 | C68: =VLOOKUP(A68,'Loan List '!$A$6:$G$75, 7, FALSE) -> First Lien | D68: =VLOOKUP(A68, 'Loan List '!$A$6:$K$82, 11, FALSE) -> FL | E68: =IF(DP68= "YES", TRUE, FALSE) -> TRUE | F68: =VLOOKUP(A68,'Loan List '!$A$6:$L$75, 12, FALSE) -> Professional Services | H68: =+I68 -> 3610766.5 | I68: =VLOOKUP(A68,'Loan List '!$A$6:$L$75, 8, FALSE) -> 3610766.5 | J68: 0 | K68: =I68/$I$15 -> 0.0099946485 | L68: =VLOOKUP(A68,'Loan List '!$A$6:$BA$82,24, FALSE) -> 100 | N68: =VLOOKUP(A68,'Loan List '!$A$6:$BA$82,22, FALSE) -> 46230 | O68: =IFERROR(MAX(0,I68-J68)*L68,"")/100 -> 3610766.5 | P68: =MIN(IF(AND(L68>=97%,Q68="Primary"),100%,L68),T68) -> 1 | Q68: Primary | R68: SETTLED | S68: =IF(OR(CU68=1,CV68=1,CW68=1),TRUE,FALSE) -> FALSE | T68: =VLOOKUP(A68,'Loan List '!$A$6:$BD$1048576,56,FALSE)/100 -> 1 | U68: =IF(E68=TRUE,P68*I68,0) -> 3610766.5 | V68: =VLOOKUP(A68,'Loan List '!$A$6:$BA$82,26, FALSE) -> 0 | W68: =V68*I68 -> 0 | Y68: =VLOOKUP(A68,'Loan List '!$A$6:$BA$75,27, FALSE) -> 0 | AB68: =K68*BU68 -> 0.017291361 | AC68: =K68*AL68 -> 0.0064965215 | AD68: =BW68 -> 0 | AE68: =IF(CK68>=$C$5,"Class 1",IF(CK68>=$D$5,"Class 2",IF(CK68>=$E$5,"Class 3","Class 4"))) -> Class 3 | AF68: =HLOOKUP($AE68,$B$3:$F$10,4,0) -> 5 | AG68: =IF(BB68,1,0)+HLOOKUP($AE68,$B$3:$F$10,5,0) -> 6 | AH68: =MIN(AF68/BU68,1) -> 1 | AI68: =IF(BU68>AG68,(AG68-AF68)/BU68,1-AH68) -> 0 | AJ68: =HLOOKUP($AE68,$B$3:$F$10,6,0) -> 0.65 | AK68: =HLOOKUP($AE68,$B$3:$F$10,8,0) -> 0.35 | AL68: =IF(OR(BI68, AND(BH68,AD68>1)), HLOOKUP(AE68,$B$3:$F$10,8,0),AH68*AJ68+AI68*AK68) -> 0.65 | AM68: ='Diversity Score'!$E$7 -> 1 | AN68: =AM68*AL68 -> 0.65 | AO68: =VLOOKUP(A68,'Loan List '!$A$6:$BA$75,17, FALSE) -> 0.059 | AP68: =VLOOKUP(A68,'Loan List '!$A$6:$BA$795,15, FALSE) -> SOFR | AQ68: =VLOOKUP(A68,'Loan List '!$A$6:$BA$795,16, FALSE) -> 0.01 | AR68: 0 | AS68: 0 | AU68: =AO68-AS68 -> 0.059 | AV68: =IF(AND(AS68>0%,AU68>4.5%),TRUE,FALSE) -> FALSE | AW68: =IF(AND(AS68>0%,AU68>=2.25%, AV68=FALSE),TRUE,FALSE) -> FALSE | AX68: =IF(AND(AS68>0%,AW68=FALSE, AV68=FALSE),TRUE, FALSE) -> FALSE | AZ68: =(OR(CC68<>"NR",CD68<>"NR")) -> FALSE | BA68: ='Loan List '!AS57 -> Maintenance Covenants | BB68: =IF(D68="FL",FALSE,TRUE) -> FALSE | BC68: =IF(BU68>5.5, TRUE, FALSE) -> FALSE | BD68: =IF(BF68="USD", TRUE,FALSE) -> TRUE | BE68: =IF(BG68="USA",TRUE,FALSE) -> TRUE | BF68: ='Loan List '!J57 -> USD | BG68: =VLOOKUP(A68,'Loan List '!$A$6:$BZ$75, 23, FALSE) -> USA | BH68: =IF(D68="FLLO", TRUE,FALSE) -> FALSE | BI68: =IF(C68="Second Lien",TRUE,FALSE) -> FALSE | BJ68: =IF('Loan List '!BP57=1, TRUE, FALSE) -> FALSE | BK68: =IF(AR68>0%,TRUE,FALSE) -> FALSE | BL68: =OR(LEFT(CC68,1)="C", LEFT(CD68,1)="C") -> FALSE | BM68: =IF('Loan List '!AT57="Yes", TRUE, FALSE) -> FALSE | BN68: =-($BN$15-N68)/365 -> 1.0054795 | BO68: ='Concentration Limitations'!H63 -> 3610766.5 | BP68: =IF(R68=$T$13,0,BO68*AL68) -> 2346998.2 | BS68: ='Loan List '!AG57 -> 45808 | BT68: ='Loan List '!AO57 -> 4.2526263 | BU68: ='Loan List '!AI57 -> 1.730062 | BW68: 0 | BX68: - | BY68: ='Loan List '!AJ57 -> 26.115817 | BZ68: ='Loan List '!AL57 -> 0 | CA68: 0 | CB68: 0 | CC68: NR | CD68: NR | CE68: - | CF68: ='Loan List '!AC57 -> 3.21 | CG68: ='Loan List '!AD57 -> 2.79 | CI68: 0 | CJ68: - | CK68: ='Loan List '!AB57 -> 15.9 | CL68: ='Loan List '!AE58 -> 0 | CM68: 0 | CN68: 0 | CO68: NR | CP68: NR | CQ68: =IFERROR(($BT68-$CF68)/$CF68,0) -> 0.32480571 | CR68: =IFERROR(($BU68-$CG68)/$CG68,0) -> -0.37990611 | CS68: =BU68-CG68 -> -1.059938 | CT68: =(BY68/CK68)-1 -> 0.64250422 | CU68: =IF(OR($CQ68<'Summary '!$I$47,$BT68<'Summary '!$I$46),1,0) -> 0 | CV68: =IF(OR($CS68>='Summary '!$I$50, (AND(BU68>'Summary '!$I$52, Calcs!CR68> 'Summary '!$I$51))),1,0) -> 0 | CW68: =IF(OR(SUM(CU68:CV68)>=1,CX68="Yes"),1,0) -> 0 | CX68: No | CY68: No | CZ68: No | DD68: 0 | DE68: 0 | DI68: =IF(L68<90%,"Not Eligible","Eligible") -> Eligible | DJ68: =IF(OR(BF68="USD",BF68="CAD",BF68="EUR",BF68="GBP",BF68="AUD"),"Eligible","Not Eligible") -> Eligible | DK68: Eligible | DL68: Eligible | DM68: =IF(BM68="FALSE",IF(BY68<5,"Not Eligible","Eligible"),"Eligible") -> Eligible | DN68: =IF(AW68=TRUE,IF(AU68>=3%,"Eligible","Not Eligible"),"Not PIK") -> Not PIK | DO68: No | DP68: =IF(OR(DK68="Not Eligible",DL68="Not Eligible",DI68="Not Eligible",DJ68="Not Eligible",DM68="Not Eligible",DN68="Not Eligible",DO68="Yes"),"NO","YES") -> YES
